Workbook

Sheet 0_ReadMe
A1: AI EMERGING RISK SCENARIO — GICS INDUSTRY / SUB-INDUSTRY LEVEL
A2: Revenue decline % and EBITDA margin impact (pp), grounded in real, published AI-exposure research — not invented numbers
A5: REAL DATA SOURCES — VERIFY THESE YOURSELF
A6: 1. The Budget Lab at Yale, "Labor Market AI Exposure: What Do We Know?" (Gimbel, Kendall, Kulsakdinun,
A7: 19 Feb 2026). PCA-weighted composite z-score across SIX published occupational exposure measures,
A8: crosswalked to SOC-2018, 778 occupations with full coverage:
A9: - Felten, Raj & Seamans (2021) AIOE — AI capability-to-occupational-ability mapping via Mechanical Turk
A10: - Eloundou, Manning, Mishkin & Rock (2024) "GPTs are GPTs" (OpenAI) — dv_rating_beta / human_rating_beta,
A11: the most widely-cited LLM occupational exposure study, GPT-4-annotated task-speedup ratings
A12: - Eisfeldt et al. (2023) GenAI exposure (total/core), GPT-4-annotated O*NET task productivity ratings
A13: - Tomlinson et al. (2025, Microsoft) AI Applicability Score, derived from real Copilot conversation data
A14: - Webb (2020) patent-based exposure — EXCLUDED per the Budget Lab's own methodology (a documented
... A76: 1_GICS_Shock_Input sheet (and a new margin-impact column if you want to wire that in).

Sheet 1_SOC_Exposure_Data
A1: REAL DATA, VALUES ONLY. The Budget Lab at Yale, sheet F1, downloaded unmodified 8 Aug 2026. 778 SOC-2018 occupations, PCA-weighted composite exposure z-score across Felten AIOE / Eloundou et al. / Eisfeldt et al. / Tomlinson et al.
A3: SOC 2018 | B3: Occupation | C3: PCA Weighted Score | D3: Z-Score Variance
A4: 11-1011 | B4: Chief Executives | C4: 2.0259 | D4: 0.3166
A5: 11-1021 | B5: General and Operations Managers | C5: 0.5897 | D5: 0.2247
A6: 11-2011 | B6: Advertising and Promotions Managers | C6: 1.9854 | D6: 0.1517
A7: 11-2021 | B7: Marketing Managers | C7: 2.2378 | D7: 0.1935
A8: 11-2022 | B8: Sales Managers | C8: 1.4109 | D8: 0.214
A9: 11-2032 | B9: Public Relations Managers | C9: 0.4688 | D9: 0.9916
A10: 11-2033 | B10: Fundraising Managers | C10: 0.0664 | D10: 0.805
A11: 11-3012 | B11: Administrative Services Managers | C11: 1.4767 | D11: 0.5427
A12: 11-3013 | B12: Facilities Managers | C12: -0.759 | D12: 0.5175
A13: 11-3021 | B13: Computer and Information Systems Managers | C13: 2.7131 | D13: 0.465
A14: 11-3031 | B14: Financial Managers | C14: 1.6898 | D14: 0.303
A15: 11-3051 | B15: Industrial Production Managers | C15: 0.3459 | D15: 0.1033
... A781: 53-7121 | B781: Tank Car, Truck, and Ship Loaders | C781: -2.0472 | D781: 0.1423
A784: SOC MAJOR GROUP ROLLUP (simple mean of the real occupation scores above, computed once)
A785: SOC Major | B785: Group Name | C785: Mean Score | D785: Percentile
A786: 15 | B786: Computer & Mathematical | C786: 4.2416 | D786: 0.9769
A787: 43 | B787: Office & Administrative Support | C787: 2.5248 | D787: 0.8548
A788: 13 | B788: Business & Financial Operations | C788: 2.053 | D788: 0.8008
A789: 41 | B789: Sales & Related | C789: 1.7244 | D789: 0.7506
A790: 19 | B790: Life, Physical & Social Science | C790: 1.6898 | D790: 0.7429
A791: 25 | B791: Educational Instruction & Library | C791: 1.667 | D791: 0.7365
A792: 17 | B792: Architecture & Engineering | C792: 1.5703 | D792: 0.7249
A793: 23 | B793: Legal | C793: 1.5672 | D793: 0.7237
A794: 11 | B794: Management | C794: 1.2691 | D794: 0.6838
A795: 21 | B795: Community & Social Service | C795: 0.9098 | D795: 0.6478
A796: 27 | B796: Arts, Design, Entertainment, Sports & Media | C796: 0.9068 | D796: 0.6478
A797: 29 | B797: Healthcare Practitioners & Technical | C797: -0.3636 | D797: 0.4936
... A807: 47 | B807: Construction & Extraction | C807: -2.6338 | D807: 0.0925

Sheet 2_GICS_Archetype_Map
A1: VALUES ONLY. Every GICS Sub-Industry mapped to one workforce archetype. Default = Industry Group; every deviation from the group default is a named override with its stated reason, visible here, not hidden.
A3: Sub-Ind Code | B3: Sub-Industry | C3: Industry Group | D3: Sector | E3: Archetype | F3: Basis
A4: 10101010 | B4: Oil & Gas Drilling | C4: Energy | D4: Energy | E4: A12_Energy | F4: Industry Group default
A5: 10101020 | B5: Oil & Gas Equipment & Services | C5: Energy | D5: Energy | E5: A12_Energy | F5: Industry Group default
A6: 10102010 | B6: Integrated Oil & Gas | C6: Energy | D6: Energy | E6: A12_Energy | F6: Industry Group default
A7: 10102020 | B7: Oil & Gas Exploration & Production | C7: Energy | D7: Energy | E7: A12_Energy | F7: Industry Group default
A8: 10102030 | B8: Oil & Gas Refining & Marketing | C8: Energy | D8: Energy | E8: A12_Energy | F8: Industry Group default
A9: 10102040 | B9: Oil & Gas Storage & Transportation | C9: Energy | D9: Energy | E9: A12_Energy | F9: Industry Group default
A10: 10102050 | B10: Coal & Consumable Fuels | C10: Energy | D10: Energy | E10: A12_Energy | F10: Industry Group default
A11: 15101010 | B11: Commodity Chemicals | C11: Materials | D11: Materials | E11: A11_MaterialsChemMining | F11: Industry Group default
A12: 15101020 | B12: Diversified Chemicals | C12: Materials | D12: Materials | E12: A11_MaterialsChemMining | F12: Industry Group default
A13: 15101030 | B13: Fertilizers & Agricultural Chemicals | C13: Materials | D13: Materials | E13: A11_MaterialsChemMining | F13: Industry Group default
A14: 15101040 | B14: Industrial Gases | C14: Materials | D14: Materials | E14: A11_MaterialsChemMining | F14: Industry Group default
A15: 15101050 | B15: Specialty Chemicals | C15: Materials | D15: Materials | E15: A11_MaterialsChemMining | F15: Industry Group default
... A166: 60201040 | B166: Real Estate Services | C166: Real Estate Management & Development | D166: Real Estate | E166: A16_RealEstate | F166: Industry Group default

Sheet 3_Archetype_Params
A1: Occupation mix (columns B-W, SOC major group weights, must sum to 100% — judgement, editable) and Labor Cost Intensity (judgement, editable) are values. Exposure Score and Percentile (last two columns) are LIVE FORMULAS computed from the real data on sheet 1 — change the mix and they recalculate.
A3: Archetype | B3: 11 Management | C3: 13 Business & Fin | D3: 15 Computer & Mat | E3: 17 Architecture & | F3: 19 Life, Physical | G3: 21 Community & So | H3: 23 Legal | I3: 25 Educational In | J3: 27 Arts, Design, | K3: 29 Healthcare Pra | L3: 31 Healthcare Sup | M3: 33 Protective Ser | N3: 35 Food Preparati | O3: 37 Building & Gro | P3: 39 Personal Care | Q3: 41 Sales & Relate | R3: 43 Office & Admin | S3: 45 Farming, Fishi | T3: 47 Construction & | U3: 49 Installation, | V3: 51 Production | W3: 53 Transportation | X3: Labor Cost Intensity | Y3: Exposure Score | Z3: Exposure Percentile
A4: A10_IndustrialsMachinery | B4: 0.2 | C4: 0 | D4: 0 | E4: 0.15 | F4: 0 | G4: 0 | H4: 0 | I4: 0 | J4: 0 | K4: 0 | L4: 0 | M4: 0 | N4: 0 | O4: 0 | P4: 0 | Q4: 0 | R4: 0 | S4: 0 | T4: 0 | U4: 0.2 | V4: 0.45 | W4: 0 | X4: 0.25 | Y4: =B4*INDEX('1_SOC_Exposure_Data'!$C$786:$C$807,MATCH("11",'1_SOC_Exposure_Data'!$A$786:$A$807,0))+C4*INDEX('1_SOC_Exposure_Data'!$C$786:$C$807,MATCH("13",'1_SOC_Exposure_Data'!$A$786:$A$807,0))+D4*INDEX('1_SOC_Exposure_Data'!$C$786:$C$807,MATCH("15",'1_SOC_Exposure_Data'!$A$786:$A$807,0))+E4*INDEX('1_SOC_Exposure_Data'!$C$786:$C$807,MATCH("17",'1_SOC_Exposure_Data'!$A$786:$A$807,0))+F4*INDEX('1_SOC_Exposure_Data'!$C$786:$C$807,MATCH("19",'1_SOC_Exposure_Data'!$A$786:$A$807,0))+G4*INDEX('1_SOC_Exposure_Data'!$C$786:$C$807,MATCH("21",'1_SOC_Exposure_Data'!$A$786:$A$807,0))+H4*INDEX('1_SOC_Exposure_Data'!$C$786:$C$807,MATCH("23",'1_SOC_Exposure_Data'!$A$786:$A$807,0))+I4*INDEX('1_SOC_Exposure_Data'!$C$786:$C$807,MATCH("25",'1_SOC_Exposure_Data'!$A$786:$A$807,0))+J4*INDEX('1_SOC_Exposure_Data'!$C$786:$C$807,MATCH("27",'1_SOC_Exposure_Data'!$A$786:$A$807,0))+K4*INDEX('1_SOC_Exposure_Data'!$C$786:$C$807,MATCH("29",'1_SOC_Exposure_Data'!$A$786:$A$807,0))+L4*INDEX('1_SOC_Exposure_Data'!$C$786:$C$807,MATCH("31",'1_SOC_Exposure_Data'!$A$786:$A$807,0))+M4*INDEX('1_SOC_Exposure_Data'!$C$786:$C$807,MATCH("33",'1_SOC_Exposure_Data'!$A$786:$A$807,0))+N4*INDEX('1_SOC_Exposure_Data'!$C$786:$C$807,MATCH("35",'1_SOC_Exposure_Data'!$A$786:$A$807,0))+O4*INDEX('1_SOC_Exposure_Data'!$C$786:$C$807,MATCH("37",'1_SOC_Exposure_Data'!$A$786:$A$807,0))+P4*INDEX('1_SOC_Exposure_Data'!$C$786:$C$807,MATCH("39",'1_SOC_Exposure_Data'!$A$786:$A$807,0))+Q4*INDEX('1_SOC_Exposure_Data'!$C$786:$C$807,MATCH("41",'1_SOC_Exposure_Data'!$A$786:$A$807,0))+R4*INDEX('1_SOC_Exposure_Data'!$C$786:$C$807,MATCH("43",'1_SOC_Exposure_Data'!$A$786:$A$807,0))+S4*INDEX('1_SOC_Exposure_Data'!$C$786:$C$807,MATCH("45",'1_SOC_Exposure_Data'!$A$786:$A$807,0))+T4*INDEX('1_SOC_Exposure_Data'!$C$786:$C$807,MATCH("47",'1_SOC_Exposure_Data'!$A$786:$A$807,0))+U4*INDEX('1_SOC_Exposure_Data'!$C$786:$C$807,MATCH("49",'1_SOC_Exposure_Data'!$A$786:$A$807,0))+V4*INDEX('1_SOC_Exposure_Data'!$C$786:$C$807,MATCH("51",'1_SOC_Exposure_Data'!$A$786:$A$807,0))+W4*INDEX('1_SOC_Exposure_Data'!$C$786:$C$807,MATCH("53",'1_SOC_Exposure_Data'!$A$786:$A$807,0)) | Z4: =COUNTIF('1_SOC_Exposure_Data'!$C$4:$C$781,"<"&Y4)/778
A5: A11_MaterialsChemMining | B5: 0.25 | C5: 0 | D5: 0 | E5: 0.2 | F5: 0.15 | G5: 0 | H5: 0 | I5: 0 | J5: 0 | K5: 0 | L5: 0 | M5: 0 | N5: 0 | O5: 0 | P5: 0 | Q5: 0 | R5: 0 | S5: 0 | T5: 0 | U5: 0 | V5: 0.4 | W5: 0 | X5: 0.2 | Y5: =B5*INDEX('1_SOC_Exposure_Data'!$C$786:$C$807,MATCH("11",'1_SOC_Exposure_Data'!$A$786:$A$807,0))+C5*INDEX('1_SOC_Exposure_Data'!$C$786:$C$807,MATCH("13",'1_SOC_Exposure_Data'!$A$786:$A$807,0))+D5*INDEX('1_SOC_Exposure_Data'!$C$786:$C$807,MATCH("15",'1_SOC_Exposure_Data'!$A$786:$A$807,0))+E5*INDEX('1_SOC_Exposure_Data'!$C$786:$C$807,MATCH("17",'1_SOC_Exposure_Data'!$A$786:$A$807,0))+F5*INDEX('1_SOC_Exposure_Data'!$C$786:$C$807,MATCH("19",'1_SOC_Exposure_Data'!$A$786:$A$807,0))+G5*INDEX('1_SOC_Exposure_Data'!$C$786:$C$807,MATCH("21",'1_SOC_Exposure_Data'!$A$786:$A$807,0))+H5*INDEX('1_SOC_Exposure_Data'!$C$786:$C$807,MATCH("23",'1_SOC_Exposure_Data'!$A$786:$A$807,0))+I5*INDEX('1_SOC_Exposure_Data'!$C$786:$C$807,MATCH("25",'1_SOC_Exposure_Data'!$A$786:$A$807,0))+J5*INDEX('1_SOC_Exposure_Data'!$C$786:$C$807,MATCH("27",'1_SOC_Exposure_Data'!$A$786:$A$807,0))+K5*INDEX('1_SOC_Exposure_Data'!$C$786:$C$807,MATCH("29",'1_SOC_Exposure_Data'!$A$786:$A$807,0))+L5*INDEX('1_SOC_Exposure_Data'!$C$786:$C$807,MATCH("31",'1_SOC_Exposure_Data'!$A$786:$A$807,0))+M5*INDEX('1_SOC_Exposure_Data'!$C$786:$C$807,MATCH("33",'1_SOC_Exposure_Data'!$A$786:$A$807,0))+N5*INDEX('1_SOC_Exposure_Data'!$C$786:$C$807,MATCH("35",'1_SOC_Exposure_Data'!$A$786:$A$807,0))+O5*INDEX('1_SOC_Exposure_Data'!$C$786:$C$807,MATCH("37",'1_SOC_Exposure_Data'!$A$786:$A$807,0))+P5*INDEX('1_SOC_Exposure_Data'!$C$786:$C$807,MATCH("39",'1_SOC_Exposure_Data'!$A$786:$A$807,0))+Q5*INDEX('1_SOC_Exposure_Data'!$C$786:$C$807,MATCH("41",'1_SOC_Exposure_Data'!$A$786:$A$807,0))+R5*INDEX('1_SOC_Exposure_Data'!$C$786:$C$807,MATCH("43",'1_SOC_Exposure_Data'!$A$786:$A$807,0))+S5*INDEX('1_SOC_Exposure_Data'!$C$786:$C$807,MATCH("45",'1_SOC_Exposure_Data'!$A$786:$A$807,0))+T5*INDEX('1_SOC_Exposure_Data'!$C$786:$C$807,MATCH("47",'1_SOC_Exposure_Data'!$A$786:$A$807,0))+U5*INDEX('1_SOC_Exposure_Data'!$C$786:$C$807,MATCH("49",'1_SOC_Exposure_Data'!$A$786:$A$807,0))+V5*INDEX('1_SOC_Exposure_Data'!$C$786:$C$807,MATCH("51",'1_SOC_Exposure_Data'!$A$786:$A$807,0))+W5*INDEX('1_SOC_Exposure_Data'!$C$786:$C$807,MATCH("53",'1_SOC_Exposure_Data'!$A$786:$A$807,0)) | Z5: =COUNTIF('1_SOC_Exposure_Data'!$C$4:$C$781,"<"&Y5)/778
A6: A12_Energy | B6: 0.2 | C6: 0 | D6: 0 | E6: 0.2 | F6: 0 | G6: 0 | H6: 0 | I6: 0 | J6: 0 | K6: 0 | L6: 0 | M6: 0 | N6: 0 | O6: 0 | P6: 0 | Q6: 0 | R6: 0 | S6: 0 | T6: 0 | U6: 0.25 | V6: 0.35 | W6: 0 | X6: 0.15 | Y6: =B6*INDEX('1_SOC_Exposure_Data'!$C$786:$C$807,MATCH("11",'1_SOC_Exposure_Data'!$A$786:$A$807,0))+C6*INDEX('1_SOC_Exposure_Data'!$C$786:$C$807,MATCH("13",'1_SOC_Exposure_Data'!$A$786:$A$807,0))+D6*INDEX('1_SOC_Exposure_Data'!$C$786:$C$807,MATCH("15",'1_SOC_Exposure_Data'!$A$786:$A$807,0))+E6*INDEX('1_SOC_Exposure_Data'!$C$786:$C$807,MATCH("17",'1_SOC_Exposure_Data'!$A$786:$A$807,0))+F6*INDEX('1_SOC_Exposure_Data'!$C$786:$C$807,MATCH("19",'1_SOC_Exposure_Data'!$A$786:$A$807,0))+G6*INDEX('1_SOC_Exposure_Data'!$C$786:$C$807,MATCH("21",'1_SOC_Exposure_Data'!$A$786:$A$807,0))+H6*INDEX('1_SOC_Exposure_Data'!$C$786:$C$807,MATCH("23",'1_SOC_Exposure_Data'!$A$786:$A$807,0))+I6*INDEX('1_SOC_Exposure_Data'!$C$786:$C$807,MATCH("25",'1_SOC_Exposure_Data'!$A$786:$A$807,0))+J6*INDEX('1_SOC_Exposure_Data'!$C$786:$C$807,MATCH("27",'1_SOC_Exposure_Data'!$A$786:$A$807,0))+K6*INDEX('1_SOC_Exposure_Data'!$C$786:$C$807,MATCH("29",'1_SOC_Exposure_Data'!$A$786:$A$807,0))+L6*INDEX('1_SOC_Exposure_Data'!$C$786:$C$807,MATCH("31",'1_SOC_Exposure_Data'!$A$786:$A$807,0))+M6*INDEX('1_SOC_Exposure_Data'!$C$786:$C$807,MATCH("33",'1_SOC_Exposure_Data'!$A$786:$A$807,0))+N6*INDEX('1_SOC_Exposure_Data'!$C$786:$C$807,MATCH("35",'1_SOC_Exposure_Data'!$A$786:$A$807,0))+O6*INDEX('1_SOC_Exposure_Data'!$C$786:$C$807,MATCH("37",'1_SOC_Exposure_Data'!$A$786:$A$807,0))+P6*INDEX('1_SOC_Exposure_Data'!$C$786:$C$807,MATCH("39",'1_SOC_Exposure_Data'!$A$786:$A$807,0))+Q6*INDEX('1_SOC_Exposure_Data'!$C$786:$C$807,MATCH("41",'1_SOC_Exposure_Data'!$A$786:$A$807,0))+R6*INDEX('1_SOC_Exposure_Data'!$C$786:$C$807,MATCH("43",'1_SOC_Exposure_Data'!$A$786:$A$807,0))+S6*INDEX('1_SOC_Exposure_Data'!$C$786:$C$807,MATCH("45",'1_SOC_Exposure_Data'!$A$786:$A$807,0))+T6*INDEX('1_SOC_Exposure_Data'!$C$786:$C$807,MATCH("47",'1_SOC_Exposure_Data'!$A$786:$A$807,0))+U6*INDEX('1_SOC_Exposure_Data'!$C$786:$C$807,MATCH("49",'1_SOC_Exposure_Data'!$A$786:$A$807,0))+V6*INDEX('1_SOC_Exposure_Data'!$C$786:$C$807,MATCH("51",'1_SOC_Exposure_Data'!$A$786:$A$807,0))+W6*INDEX('1_SOC_Exposure_Data'!$C$786:$C$807,MATCH("53",'1_SOC_Exposure_Data'!$A$786:$A$807,0)) | Z6: =COUNTIF('1_SOC_Exposure_Data'!$C$4:$C$781,"<"&Y6)/778
A7: A13_ConstructionHomebuilding | B7: 0.2 | C7: 0 | D7: 0 | E7: 0 | F7: 0 | G7: 0 | H7: 0 | I7: 0 | J7: 0 | K7: 0 | L7: 0 | M7: 0 | N7: 0 | O7: 0 | P7: 0 | Q7: 0.15 | R7: 0 | S7: 0 | T7: 0.45 | U7: 0 | V7: 0.2 | W7: 0 | X7: 0.35 | Y7: =B7*INDEX('1_SOC_Exposure_Data'!$C$786:$C$807,MATCH("11",'1_SOC_Exposure_Data'!$A$786:$A$807,0))+C7*INDEX('1_SOC_Exposure_Data'!$C$786:$C$807,MATCH("13",'1_SOC_Exposure_Data'!$A$786:$A$807,0))+D7*INDEX('1_SOC_Exposure_Data'!$C$786:$C$807,MATCH("15",'1_SOC_Exposure_Data'!$A$786:$A$807,0))+E7*INDEX('1_SOC_Exposure_Data'!$C$786:$C$807,MATCH("17",'1_SOC_Exposure_Data'!$A$786:$A$807,0))+F7*INDEX('1_SOC_Exposure_Data'!$C$786:$C$807,MATCH("19",'1_SOC_Exposure_Data'!$A$786:$A$807,0))+G7*INDEX('1_SOC_Exposure_Data'!$C$786:$C$807,MATCH("21",'1_SOC_Exposure_Data'!$A$786:$A$807,0))+H7*INDEX('1_SOC_Exposure_Data'!$C$786:$C$807,MATCH("23",'1_SOC_Exposure_Data'!$A$786:$A$807,0))+I7*INDEX('1_SOC_Exposure_Data'!$C$786:$C$807,MATCH("25",'1_SOC_Exposure_Data'!$A$786:$A$807,0))+J7*INDEX('1_SOC_Exposure_Data'!$C$786:$C$807,MATCH("27",'1_SOC_Exposure_Data'!$A$786:$A$807,0))+K7*INDEX('1_SOC_Exposure_Data'!$C$786:$C$807,MATCH("29",'1_SOC_Exposure_Data'!$A$786:$A$807,0))+L7*INDEX('1_SOC_Exposure_Data'!$C$786:$C$807,MATCH("31",'1_SOC_Exposure_Data'!$A$786:$A$807,0))+M7*INDEX('1_SOC_Exposure_Data'!$C$786:$C$807,MATCH("33",'1_SOC_Exposure_Data'!$A$786:$A$807,0))+N7*INDEX('1_SOC_Exposure_Data'!$C$786:$C$807,MATCH("35",'1_SOC_Exposure_Data'!$A$786:$A$807,0))+O7*INDEX('1_SOC_Exposure_Data'!$C$786:$C$807,MATCH("37",'1_SOC_Exposure_Data'!$A$786:$A$807,0))+P7*INDEX('1_SOC_Exposure_Data'!$C$786:$C$807,MATCH("39",'1_SOC_Exposure_Data'!$A$786:$A$807,0))+Q7*INDEX('1_SOC_Exposure_Data'!$C$786:$C$807,MATCH("41",'1_SOC_Exposure_Data'!$A$786:$A$807,0))+R7*INDEX('1_SOC_Exposure_Data'!$C$786:$C$807,MATCH("43",'1_SOC_Exposure_Data'!$A$786:$A$807,0))+S7*INDEX('1_SOC_Exposure_Data'!$C$786:$C$807,MATCH("45",'1_SOC_Exposure_Data'!$A$786:$A$807,0))+T7*INDEX('1_SOC_Exposure_Data'!$C$786:$C$807,MATCH("47",'1_SOC_Exposure_Data'!$A$786:$A$807,0))+U7*INDEX('1_SOC_Exposure_Data'!$C$786:$C$807,MATCH("49",'1_SOC_Exposure_Data'!$A$786:$A$807,0))+V7*INDEX('1_SOC_Exposure_Data'!$C$786:$C$807,MATCH("51",'1_SOC_Exposure_Data'!$A$786:$A$807,0))+W7*INDEX('1_SOC_Exposure_Data'!$C$786:$C$807,MATCH("53",'1_SOC_Exposure_Data'!$A$786:$A$807,0)) | Z7: =COUNTIF('1_SOC_Exposure_Data'!$C$4:$C$781,"<"&Y7)/778
A8: A14_ConsumerStaplesMfg | B8: 0.25 | C8: 0.2 | D8: 0 | E8: 0 | F8: 0 | G8: 0 | H8: 0 | I8: 0 | J8: 0 | K8: 0 | L8: 0 | M8: 0 | N8: 0 | O8: 0 | P8: 0 | Q8: 0.2 | R8: 0 | S8: 0 | T8: 0 | U8: 0 | V8: 0.35 | W8: 0 | X8: 0.2 | Y8: =B8*INDEX('1_SOC_Exposure_Data'!$C$786:$C$807,MATCH("11",'1_SOC_Exposure_Data'!$A$786:$A$807,0))+C8*INDEX('1_SOC_Exposure_Data'!$C$786:$C$807,MATCH("13",'1_SOC_Exposure_Data'!$A$786:$A$807,0))+D8*INDEX('1_SOC_Exposure_Data'!$C$786:$C$807,MATCH("15",'1_SOC_Exposure_Data'!$A$786:$A$807,0))+E8*INDEX('1_SOC_Exposure_Data'!$C$786:$C$807,MATCH("17",'1_SOC_Exposure_Data'!$A$786:$A$807,0))+F8*INDEX('1_SOC_Exposure_Data'!$C$786:$C$807,MATCH("19",'1_SOC_Exposure_Data'!$A$786:$A$807,0))+G8*INDEX('1_SOC_Exposure_Data'!$C$786:$C$807,MATCH("21",'1_SOC_Exposure_Data'!$A$786:$A$807,0))+H8*INDEX('1_SOC_Exposure_Data'!$C$786:$C$807,MATCH("23",'1_SOC_Exposure_Data'!$A$786:$A$807,0))+I8*INDEX('1_SOC_Exposure_Data'!$C$786:$C$807,MATCH("25",'1_SOC_Exposure_Data'!$A$786:$A$807,0))+J8*INDEX('1_SOC_Exposure_Data'!$C$786:$C$807,MATCH("27",'1_SOC_Exposure_Data'!$A$786:$A$807,0))+K8*INDEX('1_SOC_Exposure_Data'!$C$786:$C$807,MATCH("29",'1_SOC_Exposure_Data'!$A$786:$A$807,0))+L8*INDEX('1_SOC_Exposure_Data'!$C$786:$C$807,MATCH("31",'1_SOC_Exposure_Data'!$A$786:$A$807,0))+M8*INDEX('1_SOC_Exposure_Data'!$C$786:$C$807,MATCH("33",'1_SOC_Exposure_Data'!$A$786:$A$807,0))+N8*INDEX('1_SOC_Exposure_Data'!$C$786:$C$807,MATCH("35",'1_SOC_Exposure_Data'!$A$786:$A$807,0))+O8*INDEX('1_SOC_Exposure_Data'!$C$786:$C$807,MATCH("37",'1_SOC_Exposure_Data'!$A$786:$A$807,0))+P8*INDEX('1_SOC_Exposure_Data'!$C$786:$C$807,MATCH("39",'1_SOC_Exposure_Data'!$A$786:$A$807,0))+Q8*INDEX('1_SOC_Exposure_Data'!$C$786:$C$807,MATCH("41",'1_SOC_Exposure_Data'!$A$786:$A$807,0))+R8*INDEX('1_SOC_Exposure_Data'!$C$786:$C$807,MATCH("43",'1_SOC_Exposure_Data'!$A$786:$A$807,0))+S8*INDEX('1_SOC_Exposure_Data'!$C$786:$C$807,MATCH("45",'1_SOC_Exposure_Data'!$A$786:$A$807,0))+T8*INDEX('1_SOC_Exposure_Data'!$C$786:$C$807,MATCH("47",'1_SOC_Exposure_Data'!$A$786:$A$807,0))+U8*INDEX('1_SOC_Exposure_Data'!$C$786:$C$807,MATCH("49",'1_SOC_Exposure_Data'!$A$786:$A$807,0))+V8*INDEX('1_SOC_Exposure_Data'!$C$786:$C$807,MATCH("51",'1_SOC_Exposure_Data'!$A$786:$A$807,0))+W8*INDEX('1_SOC_Exposure_Data'!$C$786:$C$807,MATCH("53",'1_SOC_Exposure_Data'!$A$786:$A$807,0)) | Z8: =COUNTIF('1_SOC_Exposure_Data'!$C$4:$C$781,"<"&Y8)/778
A9: A15_RestaurantsHotelsLeisure | B9: 0.25 | C9: 0 | D9: 0 | E9: 0 | F9: 0 | G9: 0 | H9: 0 | I9: 0 | J9: 0 | K9: 0 | L9: 0 | M9: 0 | N9: 0.4 | O9: 0 | P9: 0.2 | Q9: 0.15 | R9: 0 | S9: 0 | T9: 0 | U9: 0 | V9: 0 | W9: 0 | X9: 0.4 | Y9: =B9*INDEX('1_SOC_Exposure_Data'!$C$786:$C$807,MATCH("11",'1_SOC_Exposure_Data'!$A$786:$A$807,0))+C9*INDEX('1_SOC_Exposure_Data'!$C$786:$C$807,MATCH("13",'1_SOC_Exposure_Data'!$A$786:$A$807,0))+D9*INDEX('1_SOC_Exposure_Data'!$C$786:$C$807,MATCH("15",'1_SOC_Exposure_Data'!$A$786:$A$807,0))+E9*INDEX('1_SOC_Exposure_Data'!$C$786:$C$807,MATCH("17",'1_SOC_Exposure_Data'!$A$786:$A$807,0))+F9*INDEX('1_SOC_Exposure_Data'!$C$786:$C$807,MATCH("19",'1_SOC_Exposure_Data'!$A$786:$A$807,0))+G9*INDEX('1_SOC_Exposure_Data'!$C$786:$C$807,MATCH("21",'1_SOC_Exposure_Data'!$A$786:$A$807,0))+H9*INDEX('1_SOC_Exposure_Data'!$C$786:$C$807,MATCH("23",'1_SOC_Exposure_Data'!$A$786:$A$807,0))+I9*INDEX('1_SOC_Exposure_Data'!$C$786:$C$807,MATCH("25",'1_SOC_Exposure_Data'!$A$786:$A$807,0))+J9*INDEX('1_SOC_Exposure_Data'!$C$786:$C$807,MATCH("27",'1_SOC_Exposure_Data'!$A$786:$A$807,0))+K9*INDEX('1_SOC_Exposure_Data'!$C$786:$C$807,MATCH("29",'1_SOC_Exposure_Data'!$A$786:$A$807,0))+L9*INDEX('1_SOC_Exposure_Data'!$C$786:$C$807,MATCH("31",'1_SOC_Exposure_Data'!$A$786:$A$807,0))+M9*INDEX('1_SOC_Exposure_Data'!$C$786:$C$807,MATCH("33",'1_SOC_Exposure_Data'!$A$786:$A$807,0))+N9*INDEX('1_SOC_Exposure_Data'!$C$786:$C$807,MATCH("35",'1_SOC_Exposure_Data'!$A$786:$A$807,0))+O9*INDEX('1_SOC_Exposure_Data'!$C$786:$C$807,MATCH("37",'1_SOC_Exposure_Data'!$A$786:$A$807,0))+P9*INDEX('1_SOC_Exposure_Data'!$C$786:$C$807,MATCH("39",'1_SOC_Exposure_Data'!$A$786:$A$807,0))+Q9*INDEX('1_SOC_Exposure_Data'!$C$786:$C$807,MATCH("41",'1_SOC_Exposure_Data'!$A$786:$A$807,0))+R9*INDEX('1_SOC_Exposure_Data'!$C$786:$C$807,MATCH("43",'1_SOC_Exposure_Data'!$A$786:$A$807,0))+S9*INDEX('1_SOC_Exposure_Data'!$C$786:$C$807,MATCH("45",'1_SOC_Exposure_Data'!$A$786:$A$807,0))+T9*INDEX('1_SOC_Exposure_Data'!$C$786:$C$807,MATCH("47",'1_SOC_Exposure_Data'!$A$786:$A$807,0))+U9*INDEX('1_SOC_Exposure_Data'!$C$786:$C$807,MATCH("49",'1_SOC_Exposure_Data'!$A$786:$A$807,0))+V9*INDEX('1_SOC_Exposure_Data'!$C$786:$C$807,MATCH("51",'1_SOC_Exposure_Data'!$A$786:$A$807,0))+W9*INDEX('1_SOC_Exposure_Data'!$C$786:$C$807,MATCH("53",'1_SOC_Exposure_Data'!$A$786:$A$807,0)) | Z9: =COUNTIF('1_SOC_Exposure_Data'!$C$4:$C$781,"<"&Y9)/778
A10: A16_RealEstate | B10: 0.3 | C10: 0.4 | D10: 0 | E10: 0 | F10: 0 | G10: 0 | H10: 0 | I10: 0 | J10: 0 | K10: 0 | L10: 0 | M10: 0 | N10: 0 | O10: 0 | P10: 0 | Q10: 0.1 | R10: 0.2 | S10: 0 | T10: 0 | U10: 0 | V10: 0 | W10: 0 | X10: 0.15 | Y10: =B10*INDEX('1_SOC_Exposure_Data'!$C$786:$C$807,MATCH("11",'1_SOC_Exposure_Data'!$A$786:$A$807,0))+C10*INDEX('1_SOC_Exposure_Data'!$C$786:$C$807,MATCH("13",'1_SOC_Exposure_Data'!$A$786:$A$807,0))+D10*INDEX('1_SOC_Exposure_Data'!$C$786:$C$807,MATCH("15",'1_SOC_Exposure_Data'!$A$786:$A$807,0))+E10*INDEX('1_SOC_Exposure_Data'!$C$786:$C$807,MATCH("17",'1_SOC_Exposure_Data'!$A$786:$A$807,0))+F10*INDEX('1_SOC_Exposure_Data'!$C$786:$C$807,MATCH("19",'1_SOC_Exposure_Data'!$A$786:$A$807,0))+G10*INDEX('1_SOC_Exposure_Data'!$C$786:$C$807,MATCH("21",'1_SOC_Exposure_Data'!$A$786:$A$807,0))+H10*INDEX('1_SOC_Exposure_Data'!$C$786:$C$807,MATCH("23",'1_SOC_Exposure_Data'!$A$786:$A$807,0))+I10*INDEX('1_SOC_Exposure_Data'!$C$786:$C$807,MATCH("25",'1_SOC_Exposure_Data'!$A$786:$A$807,0))+J10*INDEX('1_SOC_Exposure_Data'!$C$786:$C$807,MATCH("27",'1_SOC_Exposure_Data'!$A$786:$A$807,0))+K10*INDEX('1_SOC_Exposure_Data'!$C$786:$C$807,MATCH("29",'1_SOC_Exposure_Data'!$A$786:$A$807,0))+L10*INDEX('1_SOC_Exposure_Data'!$C$786:$C$807,MATCH("31",'1_SOC_Exposure_Data'!$A$786:$A$807,0))+M10*INDEX('1_SOC_Exposure_Data'!$C$786:$C$807,MATCH("33",'1_SOC_Exposure_Data'!$A$786:$A$807,0))+N10*INDEX('1_SOC_Exposure_Data'!$C$786:$C$807,MATCH("35",'1_SOC_Exposure_Data'!$A$786:$A$807,0))+O10*INDEX('1_SOC_Exposure_Data'!$C$786:$C$807,MATCH("37",'1_SOC_Exposure_Data'!$A$786:$A$807,0))+P10*INDEX('1_SOC_Exposure_Data'!$C$786:$C$807,MATCH("39",'1_SOC_Exposure_Data'!$A$786:$A$807,0))+Q10*INDEX('1_SOC_Exposure_Data'!$C$786:$C$807,MATCH("41",'1_SOC_Exposure_Data'!$A$786:$A$807,0))+R10*INDEX('1_SOC_Exposure_Data'!$C$786:$C$807,MATCH("43",'1_SOC_Exposure_Data'!$A$786:$A$807,0))+S10*INDEX('1_SOC_Exposure_Data'!$C$786:$C$807,MATCH("45",'1_SOC_Exposure_Data'!$A$786:$A$807,0))+T10*INDEX('1_SOC_Exposure_Data'!$C$786:$C$807,MATCH("47",'1_SOC_Exposure_Data'!$A$786:$A$807,0))+U10*INDEX('1_SOC_Exposure_Data'!$C$786:$C$807,MATCH("49",'1_SOC_Exposure_Data'!$A$786:$A$807,0))+V10*INDEX('1_SOC_Exposure_Data'!$C$786:$C$807,MATCH("51",'1_SOC_Exposure_Data'!$A$786:$A$807,0))+W10*INDEX('1_SOC_Exposure_Data'!$C$786:$C$807,MATCH("53",'1_SOC_Exposure_Data'!$A$786:$A$807,0)) | Z10: =COUNTIF('1_SOC_Exposure_Data'!$C$4:$C$781,"<"&Y10)/778
A11: A17_TransportationLogistics | B11: 0.2 | C11: 0 | D11: 0 | E11: 0 | F11: 0 | G11: 0 | H11: 0 | I11: 0 | J11: 0 | K11: 0 | L11: 0 | M11: 0 | N11: 0 | O11: 0 | P11: 0 | Q11: 0.15 | R11: 0.2 | S11: 0 | T11: 0 | U11: 0 | V11: 0 | W11: 0.45 | X11: 0.35 | Y11: =B11*INDEX('1_SOC_Exposure_Data'!$C$786:$C$807,MATCH("11",'1_SOC_Exposure_Data'!$A$786:$A$807,0))+C11*INDEX('1_SOC_Exposure_Data'!$C$786:$C$807,MATCH("13",'1_SOC_Exposure_Data'!$A$786:$A$807,0))+D11*INDEX('1_SOC_Exposure_Data'!$C$786:$C$807,MATCH("15",'1_SOC_Exposure_Data'!$A$786:$A$807,0))+E11*INDEX('1_SOC_Exposure_Data'!$C$786:$C$807,MATCH("17",'1_SOC_Exposure_Data'!$A$786:$A$807,0))+F11*INDEX('1_SOC_Exposure_Data'!$C$786:$C$807,MATCH("19",'1_SOC_Exposure_Data'!$A$786:$A$807,0))+G11*INDEX('1_SOC_Exposure_Data'!$C$786:$C$807,MATCH("21",'1_SOC_Exposure_Data'!$A$786:$A$807,0))+H11*INDEX('1_SOC_Exposure_Data'!$C$786:$C$807,MATCH("23",'1_SOC_Exposure_Data'!$A$786:$A$807,0))+I11*INDEX('1_SOC_Exposure_Data'!$C$786:$C$807,MATCH("25",'1_SOC_Exposure_Data'!$A$786:$A$807,0))+J11*INDEX('1_SOC_Exposure_Data'!$C$786:$C$807,MATCH("27",'1_SOC_Exposure_Data'!$A$786:$A$807,0))+K11*INDEX('1_SOC_Exposure_Data'!$C$786:$C$807,MATCH("29",'1_SOC_Exposure_Data'!$A$786:$A$807,0))+L11*INDEX('1_SOC_Exposure_Data'!$C$786:$C$807,MATCH("31",'1_SOC_Exposure_Data'!$A$786:$A$807,0))+M11*INDEX('1_SOC_Exposure_Data'!$C$786:$C$807,MATCH("33",'1_SOC_Exposure_Data'!$A$786:$A$807,0))+N11*INDEX('1_SOC_Exposure_Data'!$C$786:$C$807,MATCH("35",'1_SOC_Exposure_Data'!$A$786:$A$807,0))+O11*INDEX('1_SOC_Exposure_Data'!$C$786:$C$807,MATCH("37",'1_SOC_Exposure_Data'!$A$786:$A$807,0))+P11*INDEX('1_SOC_Exposure_Data'!$C$786:$C$807,MATCH("39",'1_SOC_Exposure_Data'!$A$786:$A$807,0))+Q11*INDEX('1_SOC_Exposure_Data'!$C$786:$C$807,MATCH("41",'1_SOC_Exposure_Data'!$A$786:$A$807,0))+R11*INDEX('1_SOC_Exposure_Data'!$C$786:$C$807,MATCH("43",'1_SOC_Exposure_Data'!$A$786:$A$807,0))+S11*INDEX('1_SOC_Exposure_Data'!$C$786:$C$807,MATCH("45",'1_SOC_Exposure_Data'!$A$786:$A$807,0))+T11*INDEX('1_SOC_Exposure_Data'!$C$786:$C$807,MATCH("47",'1_SOC_Exposure_Data'!$A$786:$A$807,0))+U11*INDEX('1_SOC_Exposure_Data'!$C$786:$C$807,MATCH("49",'1_SOC_Exposure_Data'!$A$786:$A$807,0))+V11*INDEX('1_SOC_Exposure_Data'!$C$786:$C$807,MATCH("51",'1_SOC_Exposure_Data'!$A$786:$A$807,0))+W11*INDEX('1_SOC_Exposure_Data'!$C$786:$C$807,MATCH("53",'1_SOC_Exposure_Data'!$A$786:$A$807,0)) | Z11: =COUNTIF('1_SOC_Exposure_Data'!$C$4:$C$781,"<"&Y11)/778
A12: A18_Utilities | B12: 0.2 | C12: 0 | D12: 0 | E12: 0.2 | F12: 0 | G12: 0 | H12: 0 | I12: 0 | J12: 0 | K12: 0 | L12: 0 | M12: 0 | N12: 0 | O12: 0 | P12: 0 | Q12: 0 | R12: 0 | S12: 0 | T12: 0 | U12: 0.35 | V12: 0.25 | W12: 0 | X12: 0.15 | Y12: =B12*INDEX('1_SOC_Exposure_Data'!$C$786:$C$807,MATCH("11",'1_SOC_Exposure_Data'!$A$786:$A$807,0))+C12*INDEX('1_SOC_Exposure_Data'!$C$786:$C$807,MATCH("13",'1_SOC_Exposure_Data'!$A$786:$A$807,0))+D12*INDEX('1_SOC_Exposure_Data'!$C$786:$C$807,MATCH("15",'1_SOC_Exposure_Data'!$A$786:$A$807,0))+E12*INDEX('1_SOC_Exposure_Data'!$C$786:$C$807,MATCH("17",'1_SOC_Exposure_Data'!$A$786:$A$807,0))+F12*INDEX('1_SOC_Exposure_Data'!$C$786:$C$807,MATCH("19",'1_SOC_Exposure_Data'!$A$786:$A$807,0))+G12*INDEX('1_SOC_Exposure_Data'!$C$786:$C$807,MATCH("21",'1_SOC_Exposure_Data'!$A$786:$A$807,0))+H12*INDEX('1_SOC_Exposure_Data'!$C$786:$C$807,MATCH("23",'1_SOC_Exposure_Data'!$A$786:$A$807,0))+I12*INDEX('1_SOC_Exposure_Data'!$C$786:$C$807,MATCH("25",'1_SOC_Exposure_Data'!$A$786:$A$807,0))+J12*INDEX('1_SOC_Exposure_Data'!$C$786:$C$807,MATCH("27",'1_SOC_Exposure_Data'!$A$786:$A$807,0))+K12*INDEX('1_SOC_Exposure_Data'!$C$786:$C$807,MATCH("29",'1_SOC_Exposure_Data'!$A$786:$A$807,0))+L12*INDEX('1_SOC_Exposure_Data'!$C$786:$C$807,MATCH("31",'1_SOC_Exposure_Data'!$A$786:$A$807,0))+M12*INDEX('1_SOC_Exposure_Data'!$C$786:$C$807,MATCH("33",'1_SOC_Exposure_Data'!$A$786:$A$807,0))+N12*INDEX('1_SOC_Exposure_Data'!$C$786:$C$807,MATCH("35",'1_SOC_Exposure_Data'!$A$786:$A$807,0))+O12*INDEX('1_SOC_Exposure_Data'!$C$786:$C$807,MATCH("37",'1_SOC_Exposure_Data'!$A$786:$A$807,0))+P12*INDEX('1_SOC_Exposure_Data'!$C$786:$C$807,MATCH("39",'1_SOC_Exposure_Data'!$A$786:$A$807,0))+Q12*INDEX('1_SOC_Exposure_Data'!$C$786:$C$807,MATCH("41",'1_SOC_Exposure_Data'!$A$786:$A$807,0))+R12*INDEX('1_SOC_Exposure_Data'!$C$786:$C$807,MATCH("43",'1_SOC_Exposure_Data'!$A$786:$A$807,0))+S12*INDEX('1_SOC_Exposure_Data'!$C$786:$C$807,MATCH("45",'1_SOC_Exposure_Data'!$A$786:$A$807,0))+T12*INDEX('1_SOC_Exposure_Data'!$C$786:$C$807,MATCH("47",'1_SOC_Exposure_Data'!$A$786:$A$807,0))+U12*INDEX('1_SOC_Exposure_Data'!$C$786:$C$807,MATCH("49",'1_SOC_Exposure_Data'!$A$786:$A$807,0))+V12*INDEX('1_SOC_Exposure_Data'!$C$786:$C$807,MATCH("51",'1_SOC_Exposure_Data'!$A$786:$A$807,0))+W12*INDEX('1_SOC_Exposure_Data'!$C$786:$C$807,MATCH("53",'1_SOC_Exposure_Data'!$A$786:$A$807,0)) | Z12: =COUNTIF('1_SOC_Exposure_Data'!$C$4:$C$781,"<"&Y12)/778
A13: A19_TelecomServices | B13: 0.2 | C13: 0 | D13: 0.25 | E13: 0 | F13: 0 | G13: 0 | H13: 0 | I13: 0 | J13: 0 | K13: 0 | L13: 0 | M13: 0 | N13: 0 | O13: 0 | P13: 0 | Q13: 0 | R13: 0.25 | S13: 0 | T13: 0 | U13: 0.3 | V13: 0 | W13: 0 | X13: 0.25 | Y13: =B13*INDEX('1_SOC_Exposure_Data'!$C$786:$C$807,MATCH("11",'1_SOC_Exposure_Data'!$A$786:$A$807,0))+C13*INDEX('1_SOC_Exposure_Data'!$C$786:$C$807,MATCH("13",'1_SOC_Exposure_Data'!$A$786:$A$807,0))+D13*INDEX('1_SOC_Exposure_Data'!$C$786:$C$807,MATCH("15",'1_SOC_Exposure_Data'!$A$786:$A$807,0))+E13*INDEX('1_SOC_Exposure_Data'!$C$786:$C$807,MATCH("17",'1_SOC_Exposure_Data'!$A$786:$A$807,0))+F13*INDEX('1_SOC_Exposure_Data'!$C$786:$C$807,MATCH("19",'1_SOC_Exposure_Data'!$A$786:$A$807,0))+G13*INDEX('1_SOC_Exposure_Data'!$C$786:$C$807,MATCH("21",'1_SOC_Exposure_Data'!$A$786:$A$807,0))+H13*INDEX('1_SOC_Exposure_Data'!$C$786:$C$807,MATCH("23",'1_SOC_Exposure_Data'!$A$786:$A$807,0))+I13*INDEX('1_SOC_Exposure_Data'!$C$786:$C$807,MATCH("25",'1_SOC_Exposure_Data'!$A$786:$A$807,0))+J13*INDEX('1_SOC_Exposure_Data'!$C$786:$C$807,MATCH("27",'1_SOC_Exposure_Data'!$A$786:$A$807,0))+K13*INDEX('1_SOC_Exposure_Data'!$C$786:$C$807,MATCH("29",'1_SOC_Exposure_Data'!$A$786:$A$807,0))+L13*INDEX('1_SOC_Exposure_Data'!$C$786:$C$807,MATCH("31",'1_SOC_Exposure_Data'!$A$786:$A$807,0))+M13*INDEX('1_SOC_Exposure_Data'!$C$786:$C$807,MATCH("33",'1_SOC_Exposure_Data'!$A$786:$A$807,0))+N13*INDEX('1_SOC_Exposure_Data'!$C$786:$C$807,MATCH("35",'1_SOC_Exposure_Data'!$A$786:$A$807,0))+O13*INDEX('1_SOC_Exposure_Data'!$C$786:$C$807,MATCH("37",'1_SOC_Exposure_Data'!$A$786:$A$807,0))+P13*INDEX('1_SOC_Exposure_Data'!$C$786:$C$807,MATCH("39",'1_SOC_Exposure_Data'!$A$786:$A$807,0))+Q13*INDEX('1_SOC_Exposure_Data'!$C$786:$C$807,MATCH("41",'1_SOC_Exposure_Data'!$A$786:$A$807,0))+R13*INDEX('1_SOC_Exposure_Data'!$C$786:$C$807,MATCH("43",'1_SOC_Exposure_Data'!$A$786:$A$807,0))+S13*INDEX('1_SOC_Exposure_Data'!$C$786:$C$807,MATCH("45",'1_SOC_Exposure_Data'!$A$786:$A$807,0))+T13*INDEX('1_SOC_Exposure_Data'!$C$786:$C$807,MATCH("47",'1_SOC_Exposure_Data'!$A$786:$A$807,0))+U13*INDEX('1_SOC_Exposure_Data'!$C$786:$C$807,MATCH("49",'1_SOC_Exposure_Data'!$A$786:$A$807,0))+V13*INDEX('1_SOC_Exposure_Data'!$C$786:$C$807,MATCH("51",'1_SOC_Exposure_Data'!$A$786:$A$807,0))+W13*INDEX('1_SOC_Exposure_Data'!$C$786:$C$807,MATCH("53",'1_SOC_Exposure_Data'!$A$786:$A$807,0)) | Z13: =COUNTIF('1_SOC_Exposure_Data'!$C$4:$C$781,"<"&Y13)/778
A14: A1_Software | B14: 0.15 | C14: 0 | D14: 0.55 | E14: 0 | F14: 0 | G14: 0 | H14: 0 | I14: 0 | J14: 0 | K14: 0 | L14: 0 | M14: 0 | N14: 0 | O14: 0 | P14: 0 | Q14: 0.2 | R14: 0.1 | S14: 0 | T14: 0 | U14: 0 | V14: 0 | W14: 0 | X14: 0.55 | Y14: =B14*INDEX('1_SOC_Exposure_Data'!$C$786:$C$807,MATCH("11",'1_SOC_Exposure_Data'!$A$786:$A$807,0))+C14*INDEX('1_SOC_Exposure_Data'!$C$786:$C$807,MATCH("13",'1_SOC_Exposure_Data'!$A$786:$A$807,0))+D14*INDEX('1_SOC_Exposure_Data'!$C$786:$C$807,MATCH("15",'1_SOC_Exposure_Data'!$A$786:$A$807,0))+E14*INDEX('1_SOC_Exposure_Data'!$C$786:$C$807,MATCH("17",'1_SOC_Exposure_Data'!$A$786:$A$807,0))+F14*INDEX('1_SOC_Exposure_Data'!$C$786:$C$807,MATCH("19",'1_SOC_Exposure_Data'!$A$786:$A$807,0))+G14*INDEX('1_SOC_Exposure_Data'!$C$786:$C$807,MATCH("21",'1_SOC_Exposure_Data'!$A$786:$A$807,0))+H14*INDEX('1_SOC_Exposure_Data'!$C$786:$C$807,MATCH("23",'1_SOC_Exposure_Data'!$A$786:$A$807,0))+I14*INDEX('1_SOC_Exposure_Data'!$C$786:$C$807,MATCH("25",'1_SOC_Exposure_Data'!$A$786:$A$807,0))+J14*INDEX('1_SOC_Exposure_Data'!$C$786:$C$807,MATCH("27",'1_SOC_Exposure_Data'!$A$786:$A$807,0))+K14*INDEX('1_SOC_Exposure_Data'!$C$786:$C$807,MATCH("29",'1_SOC_Exposure_Data'!$A$786:$A$807,0))+L14*INDEX('1_SOC_Exposure_Data'!$C$786:$C$807,MATCH("31",'1_SOC_Exposure_Data'!$A$786:$A$807,0))+M14*INDEX('1_SOC_Exposure_Data'!$C$786:$C$807,MATCH("33",'1_SOC_Exposure_Data'!$A$786:$A$807,0))+N14*INDEX('1_SOC_Exposure_Data'!$C$786:$C$807,MATCH("35",'1_SOC_Exposure_Data'!$A$786:$A$807,0))+O14*INDEX('1_SOC_Exposure_Data'!$C$786:$C$807,MATCH("37",'1_SOC_Exposure_Data'!$A$786:$A$807,0))+P14*INDEX('1_SOC_Exposure_Data'!$C$786:$C$807,MATCH("39",'1_SOC_Exposure_Data'!$A$786:$A$807,0))+Q14*INDEX('1_SOC_Exposure_Data'!$C$786:$C$807,MATCH("41",'1_SOC_Exposure_Data'!$A$786:$A$807,0))+R14*INDEX('1_SOC_Exposure_Data'!$C$786:$C$807,MATCH("43",'1_SOC_Exposure_Data'!$A$786:$A$807,0))+S14*INDEX('1_SOC_Exposure_Data'!$C$786:$C$807,MATCH("45",'1_SOC_Exposure_Data'!$A$786:$A$807,0))+T14*INDEX('1_SOC_Exposure_Data'!$C$786:$C$807,MATCH("47",'1_SOC_Exposure_Data'!$A$786:$A$807,0))+U14*INDEX('1_SOC_Exposure_Data'!$C$786:$C$807,MATCH("49",'1_SOC_Exposure_Data'!$A$786:$A$807,0))+V14*INDEX('1_SOC_Exposure_Data'!$C$786:$C$807,MATCH("51",'1_SOC_Exposure_Data'!$A$786:$A$807,0))+W14*INDEX('1_SOC_Exposure_Data'!$C$786:$C$807,MATCH("53",'1_SOC_Exposure_Data'!$A$786:$A$807,0)) | Z14: =COUNTIF('1_SOC_Exposure_Data'!$C$4:$C$781,"<"&Y14)/778
A15: A20_EducationServices | B15: 0.25 | C15: 0 | D15: 0 | E15: 0 | F15: 0 | G15: 0 | H15: 0 | I15: 0.55 | J15: 0 | K15: 0 | L15: 0 | M15: 0 | N15: 0 | O15: 0 | P15: 0 | Q15: 0 | R15: 0.2 | S15: 0 | T15: 0 | U15: 0 | V15: 0 | W15: 0 | X15: 0.6 | Y15: =B15*INDEX('1_SOC_Exposure_Data'!$C$786:$C$807,MATCH("11",'1_SOC_Exposure_Data'!$A$786:$A$807,0))+C15*INDEX('1_SOC_Exposure_Data'!$C$786:$C$807,MATCH("13",'1_SOC_Exposure_Data'!$A$786:$A$807,0))+D15*INDEX('1_SOC_Exposure_Data'!$C$786:$C$807,MATCH("15",'1_SOC_Exposure_Data'!$A$786:$A$807,0))+E15*INDEX('1_SOC_Exposure_Data'!$C$786:$C$807,MATCH("17",'1_SOC_Exposure_Data'!$A$786:$A$807,0))+F15*INDEX('1_SOC_Exposure_Data'!$C$786:$C$807,MATCH("19",'1_SOC_Exposure_Data'!$A$786:$A$807,0))+G15*INDEX('1_SOC_Exposure_Data'!$C$786:$C$807,MATCH("21",'1_SOC_Exposure_Data'!$A$786:$A$807,0))+H15*INDEX('1_SOC_Exposure_Data'!$C$786:$C$807,MATCH("23",'1_SOC_Exposure_Data'!$A$786:$A$807,0))+I15*INDEX('1_SOC_Exposure_Data'!$C$786:$C$807,MATCH("25",'1_SOC_Exposure_Data'!$A$786:$A$807,0))+J15*INDEX('1_SOC_Exposure_Data'!$C$786:$C$807,MATCH("27",'1_SOC_Exposure_Data'!$A$786:$A$807,0))+K15*INDEX('1_SOC_Exposure_Data'!$C$786:$C$807,MATCH("29",'1_SOC_Exposure_Data'!$A$786:$A$807,0))+L15*INDEX('1_SOC_Exposure_Data'!$C$786:$C$807,MATCH("31",'1_SOC_Exposure_Data'!$A$786:$A$807,0))+M15*INDEX('1_SOC_Exposure_Data'!$C$786:$C$807,MATCH("33",'1_SOC_Exposure_Data'!$A$786:$A$807,0))+N15*INDEX('1_SOC_Exposure_Data'!$C$786:$C$807,MATCH("35",'1_SOC_Exposure_Data'!$A$786:$A$807,0))+O15*INDEX('1_SOC_Exposure_Data'!$C$786:$C$807,MATCH("37",'1_SOC_Exposure_Data'!$A$786:$A$807,0))+P15*INDEX('1_SOC_Exposure_Data'!$C$786:$C$807,MATCH("39",'1_SOC_Exposure_Data'!$A$786:$A$807,0))+Q15*INDEX('1_SOC_Exposure_Data'!$C$786:$C$807,MATCH("41",'1_SOC_Exposure_Data'!$A$786:$A$807,0))+R15*INDEX('1_SOC_Exposure_Data'!$C$786:$C$807,MATCH("43",'1_SOC_Exposure_Data'!$A$786:$A$807,0))+S15*INDEX('1_SOC_Exposure_Data'!$C$786:$C$807,MATCH("45",'1_SOC_Exposure_Data'!$A$786:$A$807,0))+T15*INDEX('1_SOC_Exposure_Data'!$C$786:$C$807,MATCH("47",'1_SOC_Exposure_Data'!$A$786:$A$807,0))+U15*INDEX('1_SOC_Exposure_Data'!$C$786:$C$807,MATCH("49",'1_SOC_Exposure_Data'!$A$786:$A$807,0))+V15*INDEX('1_SOC_Exposure_Data'!$C$786:$C$807,MATCH("51",'1_SOC_Exposure_Data'!$A$786:$A$807,0))+W15*INDEX('1_SOC_Exposure_Data'!$C$786:$C$807,MATCH("53",'1_SOC_Exposure_Data'!$A$786:$A$807,0)) | Z15: =COUNTIF('1_SOC_Exposure_Data'!$C$4:$C$781,"<"&Y15)/778
... A26: A9_RetailDistribution | B26: 0.2 | C26: 0 | D26: 0 | E26: 0 | F26: 0 | G26: 0 | H26: 0 | I26: 0 | J26: 0 | K26: 0 | L26: 0 | M26: 0 | N26: 0 | O26: 0 | P26: 0 | Q26: 0.4 | R26: 0.25 | S26: 0 | T26: 0 | U26: 0 | V26: 0 | W26: 0.15 | X26: 0.35 | Y26: =B26*INDEX('1_SOC_Exposure_Data'!$C$786:$C$807,MATCH("11",'1_SOC_Exposure_Data'!$A$786:$A$807,0))+C26*INDEX('1_SOC_Exposure_Data'!$C$786:$C$807,MATCH("13",'1_SOC_Exposure_Data'!$A$786:$A$807,0))+D26*INDEX('1_SOC_Exposure_Data'!$C$786:$C$807,MATCH("15",'1_SOC_Exposure_Data'!$A$786:$A$807,0))+E26*INDEX('1_SOC_Exposure_Data'!$C$786:$C$807,MATCH("17",'1_SOC_Exposure_Data'!$A$786:$A$807,0))+F26*INDEX('1_SOC_Exposure_Data'!$C$786:$C$807,MATCH("19",'1_SOC_Exposure_Data'!$A$786:$A$807,0))+G26*INDEX('1_SOC_Exposure_Data'!$C$786:$C$807,MATCH("21",'1_SOC_Exposure_Data'!$A$786:$A$807,0))+H26*INDEX('1_SOC_Exposure_Data'!$C$786:$C$807,MATCH("23",'1_SOC_Exposure_Data'!$A$786:$A$807,0))+I26*INDEX('1_SOC_Exposure_Data'!$C$786:$C$807,MATCH("25",'1_SOC_Exposure_Data'!$A$786:$A$807,0))+J26*INDEX('1_SOC_Exposure_Data'!$C$786:$C$807,MATCH("27",'1_SOC_Exposure_Data'!$A$786:$A$807,0))+K26*INDEX('1_SOC_Exposure_Data'!$C$786:$C$807,MATCH("29",'1_SOC_Exposure_Data'!$A$786:$A$807,0))+L26*INDEX('1_SOC_Exposure_Data'!$C$786:$C$807,MATCH("31",'1_SOC_Exposure_Data'!$A$786:$A$807,0))+M26*INDEX('1_SOC_Exposure_Data'!$C$786:$C$807,MATCH("33",'1_SOC_Exposure_Data'!$A$786:$A$807,0))+N26*INDEX('1_SOC_Exposure_Data'!$C$786:$C$807,MATCH("35",'1_SOC_Exposure_Data'!$A$786:$A$807,0))+O26*INDEX('1_SOC_Exposure_Data'!$C$786:$C$807,MATCH("37",'1_SOC_Exposure_Data'!$A$786:$A$807,0))+P26*INDEX('1_SOC_Exposure_Data'!$C$786:$C$807,MATCH("39",'1_SOC_Exposure_Data'!$A$786:$A$807,0))+Q26*INDEX('1_SOC_Exposure_Data'!$C$786:$C$807,MATCH("41",'1_SOC_Exposure_Data'!$A$786:$A$807,0))+R26*INDEX('1_SOC_Exposure_Data'!$C$786:$C$807,MATCH("43",'1_SOC_Exposure_Data'!$A$786:$A$807,0))+S26*INDEX('1_SOC_Exposure_Data'!$C$786:$C$807,MATCH("45",'1_SOC_Exposure_Data'!$A$786:$A$807,0))+T26*INDEX('1_SOC_Exposure_Data'!$C$786:$C$807,MATCH("47",'1_SOC_Exposure_Data'!$A$786:$A$807,0))+U26*INDEX('1_SOC_Exposure_Data'!$C$786:$C$807,MATCH("49",'1_SOC_Exposure_Data'!$A$786:$A$807,0))+V26*INDEX('1_SOC_Exposure_Data'!$C$786:$C$807,MATCH("51",'1_SOC_Exposure_Data'!$A$786:$A$807,0))+W26*INDEX('1_SOC_Exposure_Data'!$C$786:$C$807,MATCH("53",'1_SOC_Exposure_Data'!$A$786:$A$807,0)) | Z26: =COUNTIF('1_SOC_Exposure_Data'!$C$4:$C$781,"<"&Y26)/778

Sheet 4_Severity_Dials
A1: STEP 4 — five global assumptions. First two are real (Anthropic Economic Index); the rest are editable severity judgements.
A3: Assumption | B3: Value | C3: Note
A4: Automation Share (real) | B4: 0.43 | C4: Anthropic Economic Index, Jan/Mar 2026: share of Claude.ai usage classified as automation (AI performs the task directly).
A5: Augmentation Share (real) | B5: 0.57 | C5: Anthropic Economic Index, Jan/Mar 2026: share classified as augmentation (AI collaborates with a user).
A6: Substitution Severity (dial) | B6: 0.2 | C6: At the 100th percentile of exposure, with 100% of usage being automation-type, up to this % of revenue is judged at risk over the scenario horizon.
A7: Price Deflation Severity (dial) | B7: 0.12 | C7: At the 100th percentile of exposure, up to this many percentage points of EBITDA margin compression from AI-driven competitive/pricing pressure.
A8: Cost Deflation Severity (dial) | B8: 0.35 | C8: At the 100th percentile of exposure AND 100% labor-cost-intensity AND 100% augmentation, up to this many percentage points of EBITDA margin benefit from the firm's own AI adoption.

Sheet 5_GICS_Scenario_Output
A1: STEP 5 — live per-sub-industry output. Looks up each sub-industry's archetype (sheet 2), that archetype's percentile and labor intensity (sheet 3), and the five dials (sheet 4), then computes the three channels. Ready to paste into PC_Deal_Level_Stress_Model.xlsx's 1_GICS_Shock_Input sheet.
A3: Sub-Ind Code | B3: Sub-Industry | C3: Archetype | D3: Exposure Percentile | E3: Labor Cost Intensity | F3: Revenue Decline % | G3: Margin Decline (price, pp) | H3: Margin Benefit (cost, pp) | I3: Net EBITDA Margin (pp) | J3: Sign | K3: Rank (1=most exposed)
A4: ='2_GICS_Archetype_Map'!A4 | B4: ='2_GICS_Archetype_Map'!B4 | C4: ='2_GICS_Archetype_Map'!E4 | D4: =INDEX('3_Archetype_Params'!$Z$4:$Z$26,MATCH(C4,'3_Archetype_Params'!$A$4:$A$26,0)) | E4: =INDEX('3_Archetype_Params'!$X$4:$X$26,MATCH(C4,'3_Archetype_Params'!$A$4:$A$26,0)) | F4: =D4*'4_Severity_Dials'!$B$4*'4_Severity_Dials'!$B$6 | G4: =D4*'4_Severity_Dials'!$B$7 | H4: =D4*E4*'4_Severity_Dials'!$B$5*'4_Severity_Dials'!$B$8 | I4: =H4-G4 | J4: =IF(I4>0,"BENEFIT","HEADWIND") | K4: =RANK(D4,$D$4:$D$166,0)
A5: ='2_GICS_Archetype_Map'!A5 | B5: ='2_GICS_Archetype_Map'!B5 | C5: ='2_GICS_Archetype_Map'!E5 | D5: =INDEX('3_Archetype_Params'!$Z$4:$Z$26,MATCH(C5,'3_Archetype_Params'!$A$4:$A$26,0)) | E5: =INDEX('3_Archetype_Params'!$X$4:$X$26,MATCH(C5,'3_Archetype_Params'!$A$4:$A$26,0)) | F5: =D5*'4_Severity_Dials'!$B$4*'4_Severity_Dials'!$B$6 | G5: =D5*'4_Severity_Dials'!$B$7 | H5: =D5*E5*'4_Severity_Dials'!$B$5*'4_Severity_Dials'!$B$8 | I5: =H5-G5 | J5: =IF(I5>0,"BENEFIT","HEADWIND") | K5: =RANK(D5,$D$4:$D$166,0)
A6: ='2_GICS_Archetype_Map'!A6 | B6: ='2_GICS_Archetype_Map'!B6 | C6: ='2_GICS_Archetype_Map'!E6 | D6: =INDEX('3_Archetype_Params'!$Z$4:$Z$26,MATCH(C6,'3_Archetype_Params'!$A$4:$A$26,0)) | E6: =INDEX('3_Archetype_Params'!$X$4:$X$26,MATCH(C6,'3_Archetype_Params'!$A$4:$A$26,0)) | F6: =D6*'4_Severity_Dials'!$B$4*'4_Severity_Dials'!$B$6 | G6: =D6*'4_Severity_Dials'!$B$7 | H6: =D6*E6*'4_Severity_Dials'!$B$5*'4_Severity_Dials'!$B$8 | I6: =H6-G6 | J6: =IF(I6>0,"BENEFIT","HEADWIND") | K6: =RANK(D6,$D$4:$D$166,0)
A7: ='2_GICS_Archetype_Map'!A7 | B7: ='2_GICS_Archetype_Map'!B7 | C7: ='2_GICS_Archetype_Map'!E7 | D7: =INDEX('3_Archetype_Params'!$Z$4:$Z$26,MATCH(C7,'3_Archetype_Params'!$A$4:$A$26,0)) | E7: =INDEX('3_Archetype_Params'!$X$4:$X$26,MATCH(C7,'3_Archetype_Params'!$A$4:$A$26,0)) | F7: =D7*'4_Severity_Dials'!$B$4*'4_Severity_Dials'!$B$6 | G7: =D7*'4_Severity_Dials'!$B$7 | H7: =D7*E7*'4_Severity_Dials'!$B$5*'4_Severity_Dials'!$B$8 | I7: =H7-G7 | J7: =IF(I7>0,"BENEFIT","HEADWIND") | K7: =RANK(D7,$D$4:$D$166,0)
A8: ='2_GICS_Archetype_Map'!A8 | B8: ='2_GICS_Archetype_Map'!B8 | C8: ='2_GICS_Archetype_Map'!E8 | D8: =INDEX('3_Archetype_Params'!$Z$4:$Z$26,MATCH(C8,'3_Archetype_Params'!$A$4:$A$26,0)) | E8: =INDEX('3_Archetype_Params'!$X$4:$X$26,MATCH(C8,'3_Archetype_Params'!$A$4:$A$26,0)) | F8: =D8*'4_Severity_Dials'!$B$4*'4_Severity_Dials'!$B$6 | G8: =D8*'4_Severity_Dials'!$B$7 | H8: =D8*E8*'4_Severity_Dials'!$B$5*'4_Severity_Dials'!$B$8 | I8: =H8-G8 | J8: =IF(I8>0,"BENEFIT","HEADWIND") | K8: =RANK(D8,$D$4:$D$166,0)
A9: ='2_GICS_Archetype_Map'!A9 | B9: ='2_GICS_Archetype_Map'!B9 | C9: ='2_GICS_Archetype_Map'!E9 | D9: =INDEX('3_Archetype_Params'!$Z$4:$Z$26,MATCH(C9,'3_Archetype_Params'!$A$4:$A$26,0)) | E9: =INDEX('3_Archetype_Params'!$X$4:$X$26,MATCH(C9,'3_Archetype_Params'!$A$4:$A$26,0)) | F9: =D9*'4_Severity_Dials'!$B$4*'4_Severity_Dials'!$B$6 | G9: =D9*'4_Severity_Dials'!$B$7 | H9: =D9*E9*'4_Severity_Dials'!$B$5*'4_Severity_Dials'!$B$8 | I9: =H9-G9 | J9: =IF(I9>0,"BENEFIT","HEADWIND") | K9: =RANK(D9,$D$4:$D$166,0)
A10: ='2_GICS_Archetype_Map'!A10 | B10: ='2_GICS_Archetype_Map'!B10 | C10: ='2_GICS_Archetype_Map'!E10 | D10: =INDEX('3_Archetype_Params'!$Z$4:$Z$26,MATCH(C10,'3_Archetype_Params'!$A$4:$A$26,0)) | E10: =INDEX('3_Archetype_Params'!$X$4:$X$26,MATCH(C10,'3_Archetype_Params'!$A$4:$A$26,0)) | F10: =D10*'4_Severity_Dials'!$B$4*'4_Severity_Dials'!$B$6 | G10: =D10*'4_Severity_Dials'!$B$7 | H10: =D10*E10*'4_Severity_Dials'!$B$5*'4_Severity_Dials'!$B$8 | I10: =H10-G10 | J10: =IF(I10>0,"BENEFIT","HEADWIND") | K10: =RANK(D10,$D$4:$D$166,0)
A11: ='2_GICS_Archetype_Map'!A11 | B11: ='2_GICS_Archetype_Map'!B11 | C11: ='2_GICS_Archetype_Map'!E11 | D11: =INDEX('3_Archetype_Params'!$Z$4:$Z$26,MATCH(C11,'3_Archetype_Params'!$A$4:$A$26,0)) | E11: =INDEX('3_Archetype_Params'!$X$4:$X$26,MATCH(C11,'3_Archetype_Params'!$A$4:$A$26,0)) | F11: =D11*'4_Severity_Dials'!$B$4*'4_Severity_Dials'!$B$6 | G11: =D11*'4_Severity_Dials'!$B$7 | H11: =D11*E11*'4_Severity_Dials'!$B$5*'4_Severity_Dials'!$B$8 | I11: =H11-G11 | J11: =IF(I11>0,"BENEFIT","HEADWIND") | K11: =RANK(D11,$D$4:$D$166,0)
A12: ='2_GICS_Archetype_Map'!A12 | B12: ='2_GICS_Archetype_Map'!B12 | C12: ='2_GICS_Archetype_Map'!E12 | D12: =INDEX('3_Archetype_Params'!$Z$4:$Z$26,MATCH(C12,'3_Archetype_Params'!$A$4:$A$26,0)) | E12: =INDEX('3_Archetype_Params'!$X$4:$X$26,MATCH(C12,'3_Archetype_Params'!$A$4:$A$26,0)) | F12: =D12*'4_Severity_Dials'!$B$4*'4_Severity_Dials'!$B$6 | G12: =D12*'4_Severity_Dials'!$B$7 | H12: =D12*E12*'4_Severity_Dials'!$B$5*'4_Severity_Dials'!$B$8 | I12: =H12-G12 | J12: =IF(I12>0,"BENEFIT","HEADWIND") | K12: =RANK(D12,$D$4:$D$166,0)
A13: ='2_GICS_Archetype_Map'!A13 | B13: ='2_GICS_Archetype_Map'!B13 | C13: ='2_GICS_Archetype_Map'!E13 | D13: =INDEX('3_Archetype_Params'!$Z$4:$Z$26,MATCH(C13,'3_Archetype_Params'!$A$4:$A$26,0)) | E13: =INDEX('3_Archetype_Params'!$X$4:$X$26,MATCH(C13,'3_Archetype_Params'!$A$4:$A$26,0)) | F13: =D13*'4_Severity_Dials'!$B$4*'4_Severity_Dials'!$B$6 | G13: =D13*'4_Severity_Dials'!$B$7 | H13: =D13*E13*'4_Severity_Dials'!$B$5*'4_Severity_Dials'!$B$8 | I13: =H13-G13 | J13: =IF(I13>0,"BENEFIT","HEADWIND") | K13: =RANK(D13,$D$4:$D$166,0)
A14: ='2_GICS_Archetype_Map'!A14 | B14: ='2_GICS_Archetype_Map'!B14 | C14: ='2_GICS_Archetype_Map'!E14 | D14: =INDEX('3_Archetype_Params'!$Z$4:$Z$26,MATCH(C14,'3_Archetype_Params'!$A$4:$A$26,0)) | E14: =INDEX('3_Archetype_Params'!$X$4:$X$26,MATCH(C14,'3_Archetype_Params'!$A$4:$A$26,0)) | F14: =D14*'4_Severity_Dials'!$B$4*'4_Severity_Dials'!$B$6 | G14: =D14*'4_Severity_Dials'!$B$7 | H14: =D14*E14*'4_Severity_Dials'!$B$5*'4_Severity_Dials'!$B$8 | I14: =H14-G14 | J14: =IF(I14>0,"BENEFIT","HEADWIND") | K14: =RANK(D14,$D$4:$D$166,0)
A15: ='2_GICS_Archetype_Map'!A15 | B15: ='2_GICS_Archetype_Map'!B15 | C15: ='2_GICS_Archetype_Map'!E15 | D15: =INDEX('3_Archetype_Params'!$Z$4:$Z$26,MATCH(C15,'3_Archetype_Params'!$A$4:$A$26,0)) | E15: =INDEX('3_Archetype_Params'!$X$4:$X$26,MATCH(C15,'3_Archetype_Params'!$A$4:$A$26,0)) | F15: =D15*'4_Severity_Dials'!$B$4*'4_Severity_Dials'!$B$6 | G15: =D15*'4_Severity_Dials'!$B$7 | H15: =D15*E15*'4_Severity_Dials'!$B$5*'4_Severity_Dials'!$B$8 | I15: =H15-G15 | J15: =IF(I15>0,"BENEFIT","HEADWIND") | K15: =RANK(D15,$D$4:$D$166,0)
... A166: ='2_GICS_Archetype_Map'!A166 | B166: ='2_GICS_Archetype_Map'!B166 | C166: ='2_GICS_Archetype_Map'!E166 | D166: =INDEX('3_Archetype_Params'!$Z$4:$Z$26,MATCH(C166,'3_Archetype_Params'!$A$4:$A$26,0)) | E166: =INDEX('3_Archetype_Params'!$X$4:$X$26,MATCH(C166,'3_Archetype_Params'!$A$4:$A$26,0)) | F166: =D166*'4_Severity_Dials'!$B$4*'4_Severity_Dials'!$B$6 | G166: =D166*'4_Severity_Dials'!$B$7 | H166: =D166*E166*'4_Severity_Dials'!$B$5*'4_Severity_Dials'!$B$8 | I166: =H166-G166 | J166: =IF(I166>0,"BENEFIT","HEADWIND") | K166: =RANK(D166,$D$4:$D$166,0)
