Workbook

Sheet 0_ReadMe
A1: GICS SHOCK PROPAGATION — PRA SWES SECTOR SHOCKS FROM LEVEL 1 TO LEVEL 4
A2: Expanding the PRA's 11 GICS-Sector revenue & EV/EBITDA multiple shocks to all 163 GICS Sub-Industries
A5: THE PROBLEM
A6: The PRA SWES publishes revenue and EV/EBITDA multiple shocks at GICS Level 1 (11 sectors). A real loan
A7: book is tagged at GICS Level 4 (163 sub-industries), and within one sector the true cyclicality of, say,
A8: Automobiles vs. Household Durables (both 'Consumer Discretionary') differs enormously. Applying the flat
A9: sector number to every borrower either overstates the shock for defensive names or understates it for
A10: cyclical ones. This workbook expands (propagates) the coarse shock down to the granularity you actually
A11: hold, without ever contradicting the number the regulator gave you.
A13: THE FRAMEWORK — BETA-CASCADE MULTIPLICATIVE DISAGGREGATION
A14: 1. Get an independent, public, objective measure of relative CYCLICALITY for every GICS sub-industry —
A15: NOT derived from your own portfolio (that would be circular: you'd be using your book to size the
... A72: 'Variable Paths' rows 41-64 / 91-114), read 6 Aug 2026.

Sheet 1_GICS_Structure
A1: STEP 1 — All 163 GICS sub-industries, 4-level hierarchy, crosswalked to a Damodaran industry (col I). Weight (col J) defaults to 1 (equal-weight); overwrite with portfolio MV or index weight to reweight every downstream average.
A2: Sector Code | B2: Sector | C2: IG Code | D2: Industry Group | E2: Industry Code | F2: Industry | G2: Sub-Ind Code | H2: Sub-Industry | I2: Damodaran Industry (crosswalk) | J2: Weight
A3: 10 | B3: Energy | C3: 1010 | D3: Energy | E3: 101010 | F3: Energy Equipment & Services | G3: 10101010 | H3: Oil & Gas Drilling | I3: Oilfield Svcs/Equip. | J3: 1
A4: 10 | B4: Energy | C4: 1010 | D4: Energy | E4: 101010 | F4: Energy Equipment & Services | G4: 10101020 | H4: Oil & Gas Equipment & Services | I4: Oilfield Svcs/Equip. | J4: 1
A5: 10 | B5: Energy | C5: 1010 | D5: Energy | E5: 101020 | F5: Oil, Gas & Consumable Fuels | G5: 10102010 | H5: Integrated Oil & Gas | I5: Oil/Gas (Integrated) | J5: 1
A6: 10 | B6: Energy | C6: 1010 | D6: Energy | E6: 101020 | F6: Oil, Gas & Consumable Fuels | G6: 10102020 | H6: Oil & Gas Exploration & Production | I6: Oil/Gas (Production and Exploration) | J6: 1
A7: 10 | B7: Energy | C7: 1010 | D7: Energy | E7: 101020 | F7: Oil, Gas & Consumable Fuels | G7: 10102030 | H7: Oil & Gas Refining & Marketing | I7: Oil/Gas Distribution | J7: 1
A8: 10 | B8: Energy | C8: 1010 | D8: Energy | E8: 101020 | F8: Oil, Gas & Consumable Fuels | G8: 10102040 | H8: Oil & Gas Storage & Transportation | I8: Oil/Gas Distribution | J8: 1
A9: 10 | B9: Energy | C9: 1010 | D9: Energy | E9: 101020 | F9: Oil, Gas & Consumable Fuels | G9: 10102050 | H9: Coal & Consumable Fuels | I9: Coal & Related Energy | J9: 1
A10: 15 | B10: Materials | C10: 1510 | D10: Materials | E10: 151010 | F10: Chemicals | G10: 15101010 | H10: Commodity Chemicals | I10: Chemical (Basic) | J10: 1
A11: 15 | B11: Materials | C11: 1510 | D11: Materials | E11: 151010 | F11: Chemicals | G11: 15101020 | H11: Diversified Chemicals | I11: Chemical (Diversified) | J11: 1
A12: 15 | B12: Materials | C12: 1510 | D12: Materials | E12: 151010 | F12: Chemicals | G12: 15101030 | H12: Fertilizers & Agricultural Chemicals | I12: Chemical (Basic) | J12: 1
A13: 15 | B13: Materials | C13: 1510 | D13: Materials | E13: 151010 | F13: Chemicals | G13: 15101040 | H13: Industrial Gases | I13: Chemical (Specialty) | J13: 1
A14: 15 | B14: Materials | C14: 1510 | D14: Materials | E14: 151010 | F14: Chemicals | G14: 15101050 | H14: Specialty Chemicals | I14: Chemical (Specialty) | J14: 1
... A165: 60 | B165: Real Estate | C165: 6020 | D165: Real Estate Management & Development | E165: 602010 | F165: Real Estate Management & Development | G165: 60201040 | H165: Real Estate Services | I165: Real Estate (Operations & Services) | J165: 1

Sheet 2_Damodaran_Betas
A1: STEP 2 — Damodaran industry betas (NYU Stern, updated 5 Jan 2026, US companies). Credibility shrinkage toward the ex-financials market mean (E99) with k=10 dampens thin-sample industries (e.g. Reinsurance, n=1).
A2: Industry Name | B2: Number of firms | C2: Raw Beta | D2: Unlevered Beta (corrected for cash) | E2: Credibility n/(n+10) | F2: Shrunk Beta (used in cascade)
A3: Advertising | B3: 52 | C3: 1.2105 | D3: 1.008 | E3: =B3/(B3+10) | F3: =E3*D3+(1-E3)*$F$100
A4: Aerospace/Defense | B4: 79 | C4: 0.9455 | D4: 0.8694 | E4: =B4/(B4+10) | F4: =E4*D4+(1-E4)*$F$100
A5: Air Transport | B5: 23 | C5: 1.1855 | D5: 0.7579 | E5: =B5/(B5+10) | F5: =E5*D5+(1-E5)*$F$100
A6: Apparel | B6: 35 | C6: 0.9359 | D6: 0.7946 | E6: =B6/(B6+10) | F6: =E6*D6+(1-E6)*$F$100
A7: Auto & Truck | B7: 33 | C7: 1.4565 | D7: 1.3082 | E7: =B7/(B7+10) | F7: =E7*D7+(1-E7)*$F$100
A8: Auto Parts | B8: 35 | C8: 1.3394 | D8: 1.1283 | E8: =B8/(B8+10) | F8: =E8*D8+(1-E8)*$F$100
A9: Bank (Money Center) | B9: 15 | C9: 0.761 | D9: 0.4439 | E9: =B9/(B9+10) | F9: =E9*D9+(1-E9)*$F$100
A10: Banks (Regional) | B10: 568 | C10: 0.3985 | D10: 0.3744 | E10: =B10/(B10+10) | F10: =E10*D10+(1-E10)*$F$100
A11: Beverage (Alcoholic) | B11: 14 | C11: 0.8125 | D11: 0.628 | E11: =B11/(B11+10) | F11: =E11*D11+(1-E11)*$F$100
A12: Beverage (Soft) | B12: 27 | C12: 0.6415 | D12: 0.5755 | E12: =B12/(B12+10) | F12: =E12*D12+(1-E12)*$F$100
A13: Broadcasting | B13: 24 | C13: 0.4708 | D13: 0.3153 | E13: =B13/(B13+10) | F13: =E13*D13+(1-E13)*$F$100
A14: Brokerage & Investment Banking | B14: 32 | C14: 1.1715 | D14: 0.6794 | E14: =B14/(B14+10) | F14: =E14*D14+(1-E14)*$F$100
... A97: Total Market (without financials) | B97: 4822 | C97: 0.9913 | D97: 0.901 | E97: =B97/(B97+10) | F97: =E97*D97+(1-E97)*$F$100
A99: Reference:
A100: Total Market unlevered beta (ex-financials) — shrinkage target | F100: 0.901

Sheet 3_PRA_SWES_L1_Input
A1: STEP 3 — PRA SWES Level-1 (GICS Sector) shocks, YEAR 1, from the BoE annex (SWES_variable_paths_BoE_annex.xlsx, 'Variable Paths' rows 41-64 Sector revenues / 91-114 Equity multiples, both 'Annual change'). Year 1 = the peak initial-shock year, consistent with the Y1 convention used elsewhere in this project. Years 2-5 paths exist in the annex if a multi-year cascade is wanted later.
A3: Sector Code | B3: GICS Sector | D3: US Revenue Shock % | E3: US EV/EBITDA Multiple Shock % | G3: UK/EU Revenue Shock % | H3: UK/EU EV/EBITDA Multiple Shock %
A4: 10 | B4: Energy | D4: 0.15 | E4: 0.04 | G4: 0.08 | H4: 0
A5: 15 | B5: Materials | D5: -0.05 | E5: -0.25 | G5: -0.05 | H5: -0.28
A6: 20 | B6: Industrials | D6: -0.1 | E6: -0.26 | G6: -0.1 | H6: -0.32
A7: 25 | B7: Consumer Discretionary | D7: -0.1 | E7: -0.33 | G7: -0.1 | H7: -0.25
A8: 30 | B8: Consumer Staples | D8: -0.05 | E8: -0.23 | G8: -0.05 | H8: -0.25
A9: 35 | B9: Health Care | D9: -0.05 | E9: -0.23 | G9: -0.05 | H9: -0.25
A10: 40 | B10: Financials | D10: -0.1 | E10: -0.36 | G10: -0.1 | H10: -0.32
A11: 45 | B11: Information Technology | D11: -0.1 | E11: -0.34 | G11: -0.1 | H11: -0.36
A12: 50 | B12: Communication Services | D12: -0.05 | E12: -0.3 | G12: -0.05 | H12: -0.26
A13: 55 | B13: Utilities | D13: 0.05 | E13: -0.07 | G13: 0.02 | H13: -0.01
A14: 60 | B14: Real Estate | D14: -0.1 | E14: -0.33 | G14: -0.1 | H14: -0.36
A16: Real annex data as of 6 Aug 2026. 'Telecom' (annex) maps to GICS 'Communication Services' (sector 50) — the annex's broader label; GICS Communication Services also includes Media & Entertainment, which the annex folds into the same Telecom figure.

Sheet 4_Cascade_Engine
A1: STEP 4 — For every GICS sub-industry: shrunk L4 beta -> weighted-avg beta at L3/L2/L1 (grouped directly on the L4 betas, not nested averages) -> relative beta at each level -> cascaded shock. Shock_L4 = Shock_L1 x RelBeta_L2 x RelBeta_L3 x RelBeta_L4, which telescopes to Shock_L1 x (ShrunkBeta_L4 / AvgBeta_L1) — see 0_ReadMe.
A2: Sub-Ind Code | B2: Sub-Industry | C2: Sector Code | D2: IG Code | E2: Ind Code | F2: Weight | G2: Shrunk Beta L4 | H2: Avg Beta L3 | I2: Avg Beta L2 | J2: Avg Beta L1 | K2: RelBeta L2 | L2: RelBeta L3 | M2: RelBeta L4 | N2: US Rev Shock L2 | O2: US Rev Shock L3 | P2: US Rev Shock L4 | Q2: US EV/EBITDA Shock L4 | R2: UK Rev Shock L2 | S2: UK Rev Shock L3 | T2: UK Rev Shock L4 | U2: UK EV/EBITDA Shock L4
A3: ='1_GICS_Structure'!G3 | B3: ='1_GICS_Structure'!H3 | C3: ='1_GICS_Structure'!A3 | D3: ='1_GICS_Structure'!C3 | E3: ='1_GICS_Structure'!E3 | F3: ='1_GICS_Structure'!J3 | G3: =INDEX('2_Damodaran_Betas'!$F$3:$F$97,MATCH('1_GICS_Structure'!I3,'2_Damodaran_Betas'!$A$3:$A$97,0)) | H3: =SUMPRODUCT(($E$3:$E$165=E3)*$F$3:$F$165*$G$3:$G$165)/SUMPRODUCT(($E$3:$E$165=E3)*$F$3:$F$165) | I3: =SUMPRODUCT(($D$3:$D$165=D3)*$F$3:$F$165*$G$3:$G$165)/SUMPRODUCT(($D$3:$D$165=D3)*$F$3:$F$165) | J3: =SUMPRODUCT(($C$3:$C$165=C3)*$F$3:$F$165*$G$3:$G$165)/SUMPRODUCT(($C$3:$C$165=C3)*$F$3:$F$165) | K3: =I3/J3 | L3: =H3/I3 | M3: =G3/H3 | N3: =INDEX('3_PRA_SWES_L1_Input'!$D$4:$D$14,MATCH($C3,'3_PRA_SWES_L1_Input'!$A$4:$A$14,0))*K3 | O3: =N3*L3 | P3: =O3*M3 | Q3: =INDEX('3_PRA_SWES_L1_Input'!$E$4:$E$14,MATCH($C3,'3_PRA_SWES_L1_Input'!$A$4:$A$14,0))*K3*L3*M3 | R3: =INDEX('3_PRA_SWES_L1_Input'!$G$4:$G$14,MATCH($C3,'3_PRA_SWES_L1_Input'!$A$4:$A$14,0))*K3 | S3: =R3*L3 | T3: =S3*M3 | U3: =INDEX('3_PRA_SWES_L1_Input'!$H$4:$H$14,MATCH($C3,'3_PRA_SWES_L1_Input'!$A$4:$A$14,0))*K3*L3*M3
A4: ='1_GICS_Structure'!G4 | B4: ='1_GICS_Structure'!H4 | C4: ='1_GICS_Structure'!A4 | D4: ='1_GICS_Structure'!C4 | E4: ='1_GICS_Structure'!E4 | F4: ='1_GICS_Structure'!J4 | G4: =INDEX('2_Damodaran_Betas'!$F$3:$F$97,MATCH('1_GICS_Structure'!I4,'2_Damodaran_Betas'!$A$3:$A$97,0)) | H4: =SUMPRODUCT(($E$3:$E$165=E4)*$F$3:$F$165*$G$3:$G$165)/SUMPRODUCT(($E$3:$E$165=E4)*$F$3:$F$165) | I4: =SUMPRODUCT(($D$3:$D$165=D4)*$F$3:$F$165*$G$3:$G$165)/SUMPRODUCT(($D$3:$D$165=D4)*$F$3:$F$165) | J4: =SUMPRODUCT(($C$3:$C$165=C4)*$F$3:$F$165*$G$3:$G$165)/SUMPRODUCT(($C$3:$C$165=C4)*$F$3:$F$165) | K4: =I4/J4 | L4: =H4/I4 | M4: =G4/H4 | N4: =INDEX('3_PRA_SWES_L1_Input'!$D$4:$D$14,MATCH($C4,'3_PRA_SWES_L1_Input'!$A$4:$A$14,0))*K4 | O4: =N4*L4 | P4: =O4*M4 | Q4: =INDEX('3_PRA_SWES_L1_Input'!$E$4:$E$14,MATCH($C4,'3_PRA_SWES_L1_Input'!$A$4:$A$14,0))*K4*L4*M4 | R4: =INDEX('3_PRA_SWES_L1_Input'!$G$4:$G$14,MATCH($C4,'3_PRA_SWES_L1_Input'!$A$4:$A$14,0))*K4 | S4: =R4*L4 | T4: =S4*M4 | U4: =INDEX('3_PRA_SWES_L1_Input'!$H$4:$H$14,MATCH($C4,'3_PRA_SWES_L1_Input'!$A$4:$A$14,0))*K4*L4*M4
A5: ='1_GICS_Structure'!G5 | B5: ='1_GICS_Structure'!H5 | C5: ='1_GICS_Structure'!A5 | D5: ='1_GICS_Structure'!C5 | E5: ='1_GICS_Structure'!E5 | F5: ='1_GICS_Structure'!J5 | G5: =INDEX('2_Damodaran_Betas'!$F$3:$F$97,MATCH('1_GICS_Structure'!I5,'2_Damodaran_Betas'!$A$3:$A$97,0)) | H5: =SUMPRODUCT(($E$3:$E$165=E5)*$F$3:$F$165*$G$3:$G$165)/SUMPRODUCT(($E$3:$E$165=E5)*$F$3:$F$165) | I5: =SUMPRODUCT(($D$3:$D$165=D5)*$F$3:$F$165*$G$3:$G$165)/SUMPRODUCT(($D$3:$D$165=D5)*$F$3:$F$165) | J5: =SUMPRODUCT(($C$3:$C$165=C5)*$F$3:$F$165*$G$3:$G$165)/SUMPRODUCT(($C$3:$C$165=C5)*$F$3:$F$165) | K5: =I5/J5 | L5: =H5/I5 | M5: =G5/H5 | N5: =INDEX('3_PRA_SWES_L1_Input'!$D$4:$D$14,MATCH($C5,'3_PRA_SWES_L1_Input'!$A$4:$A$14,0))*K5 | O5: =N5*L5 | P5: =O5*M5 | Q5: =INDEX('3_PRA_SWES_L1_Input'!$E$4:$E$14,MATCH($C5,'3_PRA_SWES_L1_Input'!$A$4:$A$14,0))*K5*L5*M5 | R5: =INDEX('3_PRA_SWES_L1_Input'!$G$4:$G$14,MATCH($C5,'3_PRA_SWES_L1_Input'!$A$4:$A$14,0))*K5 | S5: =R5*L5 | T5: =S5*M5 | U5: =INDEX('3_PRA_SWES_L1_Input'!$H$4:$H$14,MATCH($C5,'3_PRA_SWES_L1_Input'!$A$4:$A$14,0))*K5*L5*M5
A6: ='1_GICS_Structure'!G6 | B6: ='1_GICS_Structure'!H6 | C6: ='1_GICS_Structure'!A6 | D6: ='1_GICS_Structure'!C6 | E6: ='1_GICS_Structure'!E6 | F6: ='1_GICS_Structure'!J6 | G6: =INDEX('2_Damodaran_Betas'!$F$3:$F$97,MATCH('1_GICS_Structure'!I6,'2_Damodaran_Betas'!$A$3:$A$97,0)) | H6: =SUMPRODUCT(($E$3:$E$165=E6)*$F$3:$F$165*$G$3:$G$165)/SUMPRODUCT(($E$3:$E$165=E6)*$F$3:$F$165) | I6: =SUMPRODUCT(($D$3:$D$165=D6)*$F$3:$F$165*$G$3:$G$165)/SUMPRODUCT(($D$3:$D$165=D6)*$F$3:$F$165) | J6: =SUMPRODUCT(($C$3:$C$165=C6)*$F$3:$F$165*$G$3:$G$165)/SUMPRODUCT(($C$3:$C$165=C6)*$F$3:$F$165) | K6: =I6/J6 | L6: =H6/I6 | M6: =G6/H6 | N6: =INDEX('3_PRA_SWES_L1_Input'!$D$4:$D$14,MATCH($C6,'3_PRA_SWES_L1_Input'!$A$4:$A$14,0))*K6 | O6: =N6*L6 | P6: =O6*M6 | Q6: =INDEX('3_PRA_SWES_L1_Input'!$E$4:$E$14,MATCH($C6,'3_PRA_SWES_L1_Input'!$A$4:$A$14,0))*K6*L6*M6 | R6: =INDEX('3_PRA_SWES_L1_Input'!$G$4:$G$14,MATCH($C6,'3_PRA_SWES_L1_Input'!$A$4:$A$14,0))*K6 | S6: =R6*L6 | T6: =S6*M6 | U6: =INDEX('3_PRA_SWES_L1_Input'!$H$4:$H$14,MATCH($C6,'3_PRA_SWES_L1_Input'!$A$4:$A$14,0))*K6*L6*M6
A7: ='1_GICS_Structure'!G7 | B7: ='1_GICS_Structure'!H7 | C7: ='1_GICS_Structure'!A7 | D7: ='1_GICS_Structure'!C7 | E7: ='1_GICS_Structure'!E7 | F7: ='1_GICS_Structure'!J7 | G7: =INDEX('2_Damodaran_Betas'!$F$3:$F$97,MATCH('1_GICS_Structure'!I7,'2_Damodaran_Betas'!$A$3:$A$97,0)) | H7: =SUMPRODUCT(($E$3:$E$165=E7)*$F$3:$F$165*$G$3:$G$165)/SUMPRODUCT(($E$3:$E$165=E7)*$F$3:$F$165) | I7: =SUMPRODUCT(($D$3:$D$165=D7)*$F$3:$F$165*$G$3:$G$165)/SUMPRODUCT(($D$3:$D$165=D7)*$F$3:$F$165) | J7: =SUMPRODUCT(($C$3:$C$165=C7)*$F$3:$F$165*$G$3:$G$165)/SUMPRODUCT(($C$3:$C$165=C7)*$F$3:$F$165) | K7: =I7/J7 | L7: =H7/I7 | M7: =G7/H7 | N7: =INDEX('3_PRA_SWES_L1_Input'!$D$4:$D$14,MATCH($C7,'3_PRA_SWES_L1_Input'!$A$4:$A$14,0))*K7 | O7: =N7*L7 | P7: =O7*M7 | Q7: =INDEX('3_PRA_SWES_L1_Input'!$E$4:$E$14,MATCH($C7,'3_PRA_SWES_L1_Input'!$A$4:$A$14,0))*K7*L7*M7 | R7: =INDEX('3_PRA_SWES_L1_Input'!$G$4:$G$14,MATCH($C7,'3_PRA_SWES_L1_Input'!$A$4:$A$14,0))*K7 | S7: =R7*L7 | T7: =S7*M7 | U7: =INDEX('3_PRA_SWES_L1_Input'!$H$4:$H$14,MATCH($C7,'3_PRA_SWES_L1_Input'!$A$4:$A$14,0))*K7*L7*M7
A8: ='1_GICS_Structure'!G8 | B8: ='1_GICS_Structure'!H8 | C8: ='1_GICS_Structure'!A8 | D8: ='1_GICS_Structure'!C8 | E8: ='1_GICS_Structure'!E8 | F8: ='1_GICS_Structure'!J8 | G8: =INDEX('2_Damodaran_Betas'!$F$3:$F$97,MATCH('1_GICS_Structure'!I8,'2_Damodaran_Betas'!$A$3:$A$97,0)) | H8: =SUMPRODUCT(($E$3:$E$165=E8)*$F$3:$F$165*$G$3:$G$165)/SUMPRODUCT(($E$3:$E$165=E8)*$F$3:$F$165) | I8: =SUMPRODUCT(($D$3:$D$165=D8)*$F$3:$F$165*$G$3:$G$165)/SUMPRODUCT(($D$3:$D$165=D8)*$F$3:$F$165) | J8: =SUMPRODUCT(($C$3:$C$165=C8)*$F$3:$F$165*$G$3:$G$165)/SUMPRODUCT(($C$3:$C$165=C8)*$F$3:$F$165) | K8: =I8/J8 | L8: =H8/I8 | M8: =G8/H8 | N8: =INDEX('3_PRA_SWES_L1_Input'!$D$4:$D$14,MATCH($C8,'3_PRA_SWES_L1_Input'!$A$4:$A$14,0))*K8 | O8: =N8*L8 | P8: =O8*M8 | Q8: =INDEX('3_PRA_SWES_L1_Input'!$E$4:$E$14,MATCH($C8,'3_PRA_SWES_L1_Input'!$A$4:$A$14,0))*K8*L8*M8 | R8: =INDEX('3_PRA_SWES_L1_Input'!$G$4:$G$14,MATCH($C8,'3_PRA_SWES_L1_Input'!$A$4:$A$14,0))*K8 | S8: =R8*L8 | T8: =S8*M8 | U8: =INDEX('3_PRA_SWES_L1_Input'!$H$4:$H$14,MATCH($C8,'3_PRA_SWES_L1_Input'!$A$4:$A$14,0))*K8*L8*M8
A9: ='1_GICS_Structure'!G9 | B9: ='1_GICS_Structure'!H9 | C9: ='1_GICS_Structure'!A9 | D9: ='1_GICS_Structure'!C9 | E9: ='1_GICS_Structure'!E9 | F9: ='1_GICS_Structure'!J9 | G9: =INDEX('2_Damodaran_Betas'!$F$3:$F$97,MATCH('1_GICS_Structure'!I9,'2_Damodaran_Betas'!$A$3:$A$97,0)) | H9: =SUMPRODUCT(($E$3:$E$165=E9)*$F$3:$F$165*$G$3:$G$165)/SUMPRODUCT(($E$3:$E$165=E9)*$F$3:$F$165) | I9: =SUMPRODUCT(($D$3:$D$165=D9)*$F$3:$F$165*$G$3:$G$165)/SUMPRODUCT(($D$3:$D$165=D9)*$F$3:$F$165) | J9: =SUMPRODUCT(($C$3:$C$165=C9)*$F$3:$F$165*$G$3:$G$165)/SUMPRODUCT(($C$3:$C$165=C9)*$F$3:$F$165) | K9: =I9/J9 | L9: =H9/I9 | M9: =G9/H9 | N9: =INDEX('3_PRA_SWES_L1_Input'!$D$4:$D$14,MATCH($C9,'3_PRA_SWES_L1_Input'!$A$4:$A$14,0))*K9 | O9: =N9*L9 | P9: =O9*M9 | Q9: =INDEX('3_PRA_SWES_L1_Input'!$E$4:$E$14,MATCH($C9,'3_PRA_SWES_L1_Input'!$A$4:$A$14,0))*K9*L9*M9 | R9: =INDEX('3_PRA_SWES_L1_Input'!$G$4:$G$14,MATCH($C9,'3_PRA_SWES_L1_Input'!$A$4:$A$14,0))*K9 | S9: =R9*L9 | T9: =S9*M9 | U9: =INDEX('3_PRA_SWES_L1_Input'!$H$4:$H$14,MATCH($C9,'3_PRA_SWES_L1_Input'!$A$4:$A$14,0))*K9*L9*M9
A10: ='1_GICS_Structure'!G10 | B10: ='1_GICS_Structure'!H10 | C10: ='1_GICS_Structure'!A10 | D10: ='1_GICS_Structure'!C10 | E10: ='1_GICS_Structure'!E10 | F10: ='1_GICS_Structure'!J10 | G10: =INDEX('2_Damodaran_Betas'!$F$3:$F$97,MATCH('1_GICS_Structure'!I10,'2_Damodaran_Betas'!$A$3:$A$97,0)) | H10: =SUMPRODUCT(($E$3:$E$165=E10)*$F$3:$F$165*$G$3:$G$165)/SUMPRODUCT(($E$3:$E$165=E10)*$F$3:$F$165) | I10: =SUMPRODUCT(($D$3:$D$165=D10)*$F$3:$F$165*$G$3:$G$165)/SUMPRODUCT(($D$3:$D$165=D10)*$F$3:$F$165) | J10: =SUMPRODUCT(($C$3:$C$165=C10)*$F$3:$F$165*$G$3:$G$165)/SUMPRODUCT(($C$3:$C$165=C10)*$F$3:$F$165) | K10: =I10/J10 | L10: =H10/I10 | M10: =G10/H10 | N10: =INDEX('3_PRA_SWES_L1_Input'!$D$4:$D$14,MATCH($C10,'3_PRA_SWES_L1_Input'!$A$4:$A$14,0))*K10 | O10: =N10*L10 | P10: =O10*M10 | Q10: =INDEX('3_PRA_SWES_L1_Input'!$E$4:$E$14,MATCH($C10,'3_PRA_SWES_L1_Input'!$A$4:$A$14,0))*K10*L10*M10 | R10: =INDEX('3_PRA_SWES_L1_Input'!$G$4:$G$14,MATCH($C10,'3_PRA_SWES_L1_Input'!$A$4:$A$14,0))*K10 | S10: =R10*L10 | T10: =S10*M10 | U10: =INDEX('3_PRA_SWES_L1_Input'!$H$4:$H$14,MATCH($C10,'3_PRA_SWES_L1_Input'!$A$4:$A$14,0))*K10*L10*M10
A11: ='1_GICS_Structure'!G11 | B11: ='1_GICS_Structure'!H11 | C11: ='1_GICS_Structure'!A11 | D11: ='1_GICS_Structure'!C11 | E11: ='1_GICS_Structure'!E11 | F11: ='1_GICS_Structure'!J11 | G11: =INDEX('2_Damodaran_Betas'!$F$3:$F$97,MATCH('1_GICS_Structure'!I11,'2_Damodaran_Betas'!$A$3:$A$97,0)) | H11: =SUMPRODUCT(($E$3:$E$165=E11)*$F$3:$F$165*$G$3:$G$165)/SUMPRODUCT(($E$3:$E$165=E11)*$F$3:$F$165) | I11: =SUMPRODUCT(($D$3:$D$165=D11)*$F$3:$F$165*$G$3:$G$165)/SUMPRODUCT(($D$3:$D$165=D11)*$F$3:$F$165) | J11: =SUMPRODUCT(($C$3:$C$165=C11)*$F$3:$F$165*$G$3:$G$165)/SUMPRODUCT(($C$3:$C$165=C11)*$F$3:$F$165) | K11: =I11/J11 | L11: =H11/I11 | M11: =G11/H11 | N11: =INDEX('3_PRA_SWES_L1_Input'!$D$4:$D$14,MATCH($C11,'3_PRA_SWES_L1_Input'!$A$4:$A$14,0))*K11 | O11: =N11*L11 | P11: =O11*M11 | Q11: =INDEX('3_PRA_SWES_L1_Input'!$E$4:$E$14,MATCH($C11,'3_PRA_SWES_L1_Input'!$A$4:$A$14,0))*K11*L11*M11 | R11: =INDEX('3_PRA_SWES_L1_Input'!$G$4:$G$14,MATCH($C11,'3_PRA_SWES_L1_Input'!$A$4:$A$14,0))*K11 | S11: =R11*L11 | T11: =S11*M11 | U11: =INDEX('3_PRA_SWES_L1_Input'!$H$4:$H$14,MATCH($C11,'3_PRA_SWES_L1_Input'!$A$4:$A$14,0))*K11*L11*M11
A12: ='1_GICS_Structure'!G12 | B12: ='1_GICS_Structure'!H12 | C12: ='1_GICS_Structure'!A12 | D12: ='1_GICS_Structure'!C12 | E12: ='1_GICS_Structure'!E12 | F12: ='1_GICS_Structure'!J12 | G12: =INDEX('2_Damodaran_Betas'!$F$3:$F$97,MATCH('1_GICS_Structure'!I12,'2_Damodaran_Betas'!$A$3:$A$97,0)) | H12: =SUMPRODUCT(($E$3:$E$165=E12)*$F$3:$F$165*$G$3:$G$165)/SUMPRODUCT(($E$3:$E$165=E12)*$F$3:$F$165) | I12: =SUMPRODUCT(($D$3:$D$165=D12)*$F$3:$F$165*$G$3:$G$165)/SUMPRODUCT(($D$3:$D$165=D12)*$F$3:$F$165) | J12: =SUMPRODUCT(($C$3:$C$165=C12)*$F$3:$F$165*$G$3:$G$165)/SUMPRODUCT(($C$3:$C$165=C12)*$F$3:$F$165) | K12: =I12/J12 | L12: =H12/I12 | M12: =G12/H12 | N12: =INDEX('3_PRA_SWES_L1_Input'!$D$4:$D$14,MATCH($C12,'3_PRA_SWES_L1_Input'!$A$4:$A$14,0))*K12 | O12: =N12*L12 | P12: =O12*M12 | Q12: =INDEX('3_PRA_SWES_L1_Input'!$E$4:$E$14,MATCH($C12,'3_PRA_SWES_L1_Input'!$A$4:$A$14,0))*K12*L12*M12 | R12: =INDEX('3_PRA_SWES_L1_Input'!$G$4:$G$14,MATCH($C12,'3_PRA_SWES_L1_Input'!$A$4:$A$14,0))*K12 | S12: =R12*L12 | T12: =S12*M12 | U12: =INDEX('3_PRA_SWES_L1_Input'!$H$4:$H$14,MATCH($C12,'3_PRA_SWES_L1_Input'!$A$4:$A$14,0))*K12*L12*M12
A13: ='1_GICS_Structure'!G13 | B13: ='1_GICS_Structure'!H13 | C13: ='1_GICS_Structure'!A13 | D13: ='1_GICS_Structure'!C13 | E13: ='1_GICS_Structure'!E13 | F13: ='1_GICS_Structure'!J13 | G13: =INDEX('2_Damodaran_Betas'!$F$3:$F$97,MATCH('1_GICS_Structure'!I13,'2_Damodaran_Betas'!$A$3:$A$97,0)) | H13: =SUMPRODUCT(($E$3:$E$165=E13)*$F$3:$F$165*$G$3:$G$165)/SUMPRODUCT(($E$3:$E$165=E13)*$F$3:$F$165) | I13: =SUMPRODUCT(($D$3:$D$165=D13)*$F$3:$F$165*$G$3:$G$165)/SUMPRODUCT(($D$3:$D$165=D13)*$F$3:$F$165) | J13: =SUMPRODUCT(($C$3:$C$165=C13)*$F$3:$F$165*$G$3:$G$165)/SUMPRODUCT(($C$3:$C$165=C13)*$F$3:$F$165) | K13: =I13/J13 | L13: =H13/I13 | M13: =G13/H13 | N13: =INDEX('3_PRA_SWES_L1_Input'!$D$4:$D$14,MATCH($C13,'3_PRA_SWES_L1_Input'!$A$4:$A$14,0))*K13 | O13: =N13*L13 | P13: =O13*M13 | Q13: =INDEX('3_PRA_SWES_L1_Input'!$E$4:$E$14,MATCH($C13,'3_PRA_SWES_L1_Input'!$A$4:$A$14,0))*K13*L13*M13 | R13: =INDEX('3_PRA_SWES_L1_Input'!$G$4:$G$14,MATCH($C13,'3_PRA_SWES_L1_Input'!$A$4:$A$14,0))*K13 | S13: =R13*L13 | T13: =S13*M13 | U13: =INDEX('3_PRA_SWES_L1_Input'!$H$4:$H$14,MATCH($C13,'3_PRA_SWES_L1_Input'!$A$4:$A$14,0))*K13*L13*M13
A14: ='1_GICS_Structure'!G14 | B14: ='1_GICS_Structure'!H14 | C14: ='1_GICS_Structure'!A14 | D14: ='1_GICS_Structure'!C14 | E14: ='1_GICS_Structure'!E14 | F14: ='1_GICS_Structure'!J14 | G14: =INDEX('2_Damodaran_Betas'!$F$3:$F$97,MATCH('1_GICS_Structure'!I14,'2_Damodaran_Betas'!$A$3:$A$97,0)) | H14: =SUMPRODUCT(($E$3:$E$165=E14)*$F$3:$F$165*$G$3:$G$165)/SUMPRODUCT(($E$3:$E$165=E14)*$F$3:$F$165) | I14: =SUMPRODUCT(($D$3:$D$165=D14)*$F$3:$F$165*$G$3:$G$165)/SUMPRODUCT(($D$3:$D$165=D14)*$F$3:$F$165) | J14: =SUMPRODUCT(($C$3:$C$165=C14)*$F$3:$F$165*$G$3:$G$165)/SUMPRODUCT(($C$3:$C$165=C14)*$F$3:$F$165) | K14: =I14/J14 | L14: =H14/I14 | M14: =G14/H14 | N14: =INDEX('3_PRA_SWES_L1_Input'!$D$4:$D$14,MATCH($C14,'3_PRA_SWES_L1_Input'!$A$4:$A$14,0))*K14 | O14: =N14*L14 | P14: =O14*M14 | Q14: =INDEX('3_PRA_SWES_L1_Input'!$E$4:$E$14,MATCH($C14,'3_PRA_SWES_L1_Input'!$A$4:$A$14,0))*K14*L14*M14 | R14: =INDEX('3_PRA_SWES_L1_Input'!$G$4:$G$14,MATCH($C14,'3_PRA_SWES_L1_Input'!$A$4:$A$14,0))*K14 | S14: =R14*L14 | T14: =S14*M14 | U14: =INDEX('3_PRA_SWES_L1_Input'!$H$4:$H$14,MATCH($C14,'3_PRA_SWES_L1_Input'!$A$4:$A$14,0))*K14*L14*M14
... A165: ='1_GICS_Structure'!G165 | B165: ='1_GICS_Structure'!H165 | C165: ='1_GICS_Structure'!A165 | D165: ='1_GICS_Structure'!C165 | E165: ='1_GICS_Structure'!E165 | F165: ='1_GICS_Structure'!J165 | G165: =INDEX('2_Damodaran_Betas'!$F$3:$F$97,MATCH('1_GICS_Structure'!I165,'2_Damodaran_Betas'!$A$3:$A$97,0)) | H165: =SUMPRODUCT(($E$3:$E$165=E165)*$F$3:$F$165*$G$3:$G$165)/SUMPRODUCT(($E$3:$E$165=E165)*$F$3:$F$165) | I165: =SUMPRODUCT(($D$3:$D$165=D165)*$F$3:$F$165*$G$3:$G$165)/SUMPRODUCT(($D$3:$D$165=D165)*$F$3:$F$165) | J165: =SUMPRODUCT(($C$3:$C$165=C165)*$F$3:$F$165*$G$3:$G$165)/SUMPRODUCT(($C$3:$C$165=C165)*$F$3:$F$165) | K165: =I165/J165 | L165: =H165/I165 | M165: =G165/H165 | N165: =INDEX('3_PRA_SWES_L1_Input'!$D$4:$D$14,MATCH($C165,'3_PRA_SWES_L1_Input'!$A$4:$A$14,0))*K165 | O165: =N165*L165 | P165: =O165*M165 | Q165: =INDEX('3_PRA_SWES_L1_Input'!$E$4:$E$14,MATCH($C165,'3_PRA_SWES_L1_Input'!$A$4:$A$14,0))*K165*L165*M165 | R165: =INDEX('3_PRA_SWES_L1_Input'!$G$4:$G$14,MATCH($C165,'3_PRA_SWES_L1_Input'!$A$4:$A$14,0))*K165 | S165: =R165*L165 | T165: =S165*M165 | U165: =INDEX('3_PRA_SWES_L1_Input'!$H$4:$H$14,MATCH($C165,'3_PRA_SWES_L1_Input'!$A$4:$A$14,0))*K165*L165*M165

Sheet 5_Control_Check
A1: STEP 5 — For every sector: weighted-average of the 163 cascaded Level-4 shocks (using the Weight column from sheet 1), compared back to the Level-1 input. Variance should read 0.00% everywhere, by construction (the cascade telescopes exactly). If any row shows a non-zero variance, a formula upstream has been overtyped — investigate before trusting the output.
A3: Sector Code | B3: GICS Sector | C3: L1 Input US Rev % | D3: Weighted-avg L4 US Rev % | E3: Variance | F3: L1 Input US EV/EBITDA % | G3: Weighted-avg L4 US EV/EBITDA % | H3: Variance
A4: 10 | B4: Energy | C4: ='3_PRA_SWES_L1_Input'!D4 | D4: =SUMPRODUCT(('4_Cascade_Engine'!$C$3:$C$165=A4)*'4_Cascade_Engine'!$F$3:$F$165*'4_Cascade_Engine'!$P$3:$P$165)/SUMPRODUCT(('4_Cascade_Engine'!$C$3:$C$165=A4)*'4_Cascade_Engine'!$F$3:$F$165) | E4: =D4-C4 | F4: ='3_PRA_SWES_L1_Input'!E4 | G4: =SUMPRODUCT(('4_Cascade_Engine'!$C$3:$C$165=A4)*'4_Cascade_Engine'!$F$3:$F$165*'4_Cascade_Engine'!$Q$3:$Q$165)/SUMPRODUCT(('4_Cascade_Engine'!$C$3:$C$165=A4)*'4_Cascade_Engine'!$F$3:$F$165) | H4: =G4-F4
A5: 15 | B5: Materials | C5: ='3_PRA_SWES_L1_Input'!D5 | D5: =SUMPRODUCT(('4_Cascade_Engine'!$C$3:$C$165=A5)*'4_Cascade_Engine'!$F$3:$F$165*'4_Cascade_Engine'!$P$3:$P$165)/SUMPRODUCT(('4_Cascade_Engine'!$C$3:$C$165=A5)*'4_Cascade_Engine'!$F$3:$F$165) | E5: =D5-C5 | F5: ='3_PRA_SWES_L1_Input'!E5 | G5: =SUMPRODUCT(('4_Cascade_Engine'!$C$3:$C$165=A5)*'4_Cascade_Engine'!$F$3:$F$165*'4_Cascade_Engine'!$Q$3:$Q$165)/SUMPRODUCT(('4_Cascade_Engine'!$C$3:$C$165=A5)*'4_Cascade_Engine'!$F$3:$F$165) | H5: =G5-F5
A6: 20 | B6: Industrials | C6: ='3_PRA_SWES_L1_Input'!D6 | D6: =SUMPRODUCT(('4_Cascade_Engine'!$C$3:$C$165=A6)*'4_Cascade_Engine'!$F$3:$F$165*'4_Cascade_Engine'!$P$3:$P$165)/SUMPRODUCT(('4_Cascade_Engine'!$C$3:$C$165=A6)*'4_Cascade_Engine'!$F$3:$F$165) | E6: =D6-C6 | F6: ='3_PRA_SWES_L1_Input'!E6 | G6: =SUMPRODUCT(('4_Cascade_Engine'!$C$3:$C$165=A6)*'4_Cascade_Engine'!$F$3:$F$165*'4_Cascade_Engine'!$Q$3:$Q$165)/SUMPRODUCT(('4_Cascade_Engine'!$C$3:$C$165=A6)*'4_Cascade_Engine'!$F$3:$F$165) | H6: =G6-F6
A7: 25 | B7: Consumer Discretionary | C7: ='3_PRA_SWES_L1_Input'!D7 | D7: =SUMPRODUCT(('4_Cascade_Engine'!$C$3:$C$165=A7)*'4_Cascade_Engine'!$F$3:$F$165*'4_Cascade_Engine'!$P$3:$P$165)/SUMPRODUCT(('4_Cascade_Engine'!$C$3:$C$165=A7)*'4_Cascade_Engine'!$F$3:$F$165) | E7: =D7-C7 | F7: ='3_PRA_SWES_L1_Input'!E7 | G7: =SUMPRODUCT(('4_Cascade_Engine'!$C$3:$C$165=A7)*'4_Cascade_Engine'!$F$3:$F$165*'4_Cascade_Engine'!$Q$3:$Q$165)/SUMPRODUCT(('4_Cascade_Engine'!$C$3:$C$165=A7)*'4_Cascade_Engine'!$F$3:$F$165) | H7: =G7-F7
A8: 30 | B8: Consumer Staples | C8: ='3_PRA_SWES_L1_Input'!D8 | D8: =SUMPRODUCT(('4_Cascade_Engine'!$C$3:$C$165=A8)*'4_Cascade_Engine'!$F$3:$F$165*'4_Cascade_Engine'!$P$3:$P$165)/SUMPRODUCT(('4_Cascade_Engine'!$C$3:$C$165=A8)*'4_Cascade_Engine'!$F$3:$F$165) | E8: =D8-C8 | F8: ='3_PRA_SWES_L1_Input'!E8 | G8: =SUMPRODUCT(('4_Cascade_Engine'!$C$3:$C$165=A8)*'4_Cascade_Engine'!$F$3:$F$165*'4_Cascade_Engine'!$Q$3:$Q$165)/SUMPRODUCT(('4_Cascade_Engine'!$C$3:$C$165=A8)*'4_Cascade_Engine'!$F$3:$F$165) | H8: =G8-F8
A9: 35 | B9: Health Care | C9: ='3_PRA_SWES_L1_Input'!D9 | D9: =SUMPRODUCT(('4_Cascade_Engine'!$C$3:$C$165=A9)*'4_Cascade_Engine'!$F$3:$F$165*'4_Cascade_Engine'!$P$3:$P$165)/SUMPRODUCT(('4_Cascade_Engine'!$C$3:$C$165=A9)*'4_Cascade_Engine'!$F$3:$F$165) | E9: =D9-C9 | F9: ='3_PRA_SWES_L1_Input'!E9 | G9: =SUMPRODUCT(('4_Cascade_Engine'!$C$3:$C$165=A9)*'4_Cascade_Engine'!$F$3:$F$165*'4_Cascade_Engine'!$Q$3:$Q$165)/SUMPRODUCT(('4_Cascade_Engine'!$C$3:$C$165=A9)*'4_Cascade_Engine'!$F$3:$F$165) | H9: =G9-F9
A10: 40 | B10: Financials | C10: ='3_PRA_SWES_L1_Input'!D10 | D10: =SUMPRODUCT(('4_Cascade_Engine'!$C$3:$C$165=A10)*'4_Cascade_Engine'!$F$3:$F$165*'4_Cascade_Engine'!$P$3:$P$165)/SUMPRODUCT(('4_Cascade_Engine'!$C$3:$C$165=A10)*'4_Cascade_Engine'!$F$3:$F$165) | E10: =D10-C10 | F10: ='3_PRA_SWES_L1_Input'!E10 | G10: =SUMPRODUCT(('4_Cascade_Engine'!$C$3:$C$165=A10)*'4_Cascade_Engine'!$F$3:$F$165*'4_Cascade_Engine'!$Q$3:$Q$165)/SUMPRODUCT(('4_Cascade_Engine'!$C$3:$C$165=A10)*'4_Cascade_Engine'!$F$3:$F$165) | H10: =G10-F10
A11: 45 | B11: Information Technology | C11: ='3_PRA_SWES_L1_Input'!D11 | D11: =SUMPRODUCT(('4_Cascade_Engine'!$C$3:$C$165=A11)*'4_Cascade_Engine'!$F$3:$F$165*'4_Cascade_Engine'!$P$3:$P$165)/SUMPRODUCT(('4_Cascade_Engine'!$C$3:$C$165=A11)*'4_Cascade_Engine'!$F$3:$F$165) | E11: =D11-C11 | F11: ='3_PRA_SWES_L1_Input'!E11 | G11: =SUMPRODUCT(('4_Cascade_Engine'!$C$3:$C$165=A11)*'4_Cascade_Engine'!$F$3:$F$165*'4_Cascade_Engine'!$Q$3:$Q$165)/SUMPRODUCT(('4_Cascade_Engine'!$C$3:$C$165=A11)*'4_Cascade_Engine'!$F$3:$F$165) | H11: =G11-F11
A12: 50 | B12: Communication Services | C12: ='3_PRA_SWES_L1_Input'!D12 | D12: =SUMPRODUCT(('4_Cascade_Engine'!$C$3:$C$165=A12)*'4_Cascade_Engine'!$F$3:$F$165*'4_Cascade_Engine'!$P$3:$P$165)/SUMPRODUCT(('4_Cascade_Engine'!$C$3:$C$165=A12)*'4_Cascade_Engine'!$F$3:$F$165) | E12: =D12-C12 | F12: ='3_PRA_SWES_L1_Input'!E12 | G12: =SUMPRODUCT(('4_Cascade_Engine'!$C$3:$C$165=A12)*'4_Cascade_Engine'!$F$3:$F$165*'4_Cascade_Engine'!$Q$3:$Q$165)/SUMPRODUCT(('4_Cascade_Engine'!$C$3:$C$165=A12)*'4_Cascade_Engine'!$F$3:$F$165) | H12: =G12-F12
A13: 55 | B13: Utilities | C13: ='3_PRA_SWES_L1_Input'!D13 | D13: =SUMPRODUCT(('4_Cascade_Engine'!$C$3:$C$165=A13)*'4_Cascade_Engine'!$F$3:$F$165*'4_Cascade_Engine'!$P$3:$P$165)/SUMPRODUCT(('4_Cascade_Engine'!$C$3:$C$165=A13)*'4_Cascade_Engine'!$F$3:$F$165) | E13: =D13-C13 | F13: ='3_PRA_SWES_L1_Input'!E13 | G13: =SUMPRODUCT(('4_Cascade_Engine'!$C$3:$C$165=A13)*'4_Cascade_Engine'!$F$3:$F$165*'4_Cascade_Engine'!$Q$3:$Q$165)/SUMPRODUCT(('4_Cascade_Engine'!$C$3:$C$165=A13)*'4_Cascade_Engine'!$F$3:$F$165) | H13: =G13-F13
A14: 60 | B14: Real Estate | C14: ='3_PRA_SWES_L1_Input'!D14 | D14: =SUMPRODUCT(('4_Cascade_Engine'!$C$3:$C$165=A14)*'4_Cascade_Engine'!$F$3:$F$165*'4_Cascade_Engine'!$P$3:$P$165)/SUMPRODUCT(('4_Cascade_Engine'!$C$3:$C$165=A14)*'4_Cascade_Engine'!$F$3:$F$165) | E14: =D14-C14 | F14: ='3_PRA_SWES_L1_Input'!E14 | G14: =SUMPRODUCT(('4_Cascade_Engine'!$C$3:$C$165=A14)*'4_Cascade_Engine'!$F$3:$F$165*'4_Cascade_Engine'!$Q$3:$Q$165)/SUMPRODUCT(('4_Cascade_Engine'!$C$3:$C$165=A14)*'4_Cascade_Engine'!$F$3:$F$165) | H14: =G14-F14
A16: (UK/EU reconciliation is identical mechanics — US shown here for space; add columns I-L mirroring C-F referencing sheet 3 cols G/H and sheet 4 cols T/U if you want it side by side.)

Sheet 6_Output_L4
A1: STEP 6 — Clean output. VLOOKUP your loan tape's GICS Sub-Industry code against column A to pull its Level-4 revenue and EV/EBITDA multiple shock. This sheet is a live mirror of 4_Cascade_Engine columns P, Q, T, U — nothing to edit here.
A2: Sub-Ind Code | B2: Sub-Industry | C2: Sector | D2: US Revenue Shock L4 | E2: US EV/EBITDA Shock L4 | F2: UK Revenue Shock L4 | G2: UK EV/EBITDA Shock L4
A3: ='4_Cascade_Engine'!A3 | B3: ='4_Cascade_Engine'!B3 | C3: ='1_GICS_Structure'!B3 | D3: ='4_Cascade_Engine'!P3 | E3: ='4_Cascade_Engine'!Q3 | F3: ='4_Cascade_Engine'!T3 | G3: ='4_Cascade_Engine'!U3
A4: ='4_Cascade_Engine'!A4 | B4: ='4_Cascade_Engine'!B4 | C4: ='1_GICS_Structure'!B4 | D4: ='4_Cascade_Engine'!P4 | E4: ='4_Cascade_Engine'!Q4 | F4: ='4_Cascade_Engine'!T4 | G4: ='4_Cascade_Engine'!U4
A5: ='4_Cascade_Engine'!A5 | B5: ='4_Cascade_Engine'!B5 | C5: ='1_GICS_Structure'!B5 | D5: ='4_Cascade_Engine'!P5 | E5: ='4_Cascade_Engine'!Q5 | F5: ='4_Cascade_Engine'!T5 | G5: ='4_Cascade_Engine'!U5
A6: ='4_Cascade_Engine'!A6 | B6: ='4_Cascade_Engine'!B6 | C6: ='1_GICS_Structure'!B6 | D6: ='4_Cascade_Engine'!P6 | E6: ='4_Cascade_Engine'!Q6 | F6: ='4_Cascade_Engine'!T6 | G6: ='4_Cascade_Engine'!U6
A7: ='4_Cascade_Engine'!A7 | B7: ='4_Cascade_Engine'!B7 | C7: ='1_GICS_Structure'!B7 | D7: ='4_Cascade_Engine'!P7 | E7: ='4_Cascade_Engine'!Q7 | F7: ='4_Cascade_Engine'!T7 | G7: ='4_Cascade_Engine'!U7
A8: ='4_Cascade_Engine'!A8 | B8: ='4_Cascade_Engine'!B8 | C8: ='1_GICS_Structure'!B8 | D8: ='4_Cascade_Engine'!P8 | E8: ='4_Cascade_Engine'!Q8 | F8: ='4_Cascade_Engine'!T8 | G8: ='4_Cascade_Engine'!U8
A9: ='4_Cascade_Engine'!A9 | B9: ='4_Cascade_Engine'!B9 | C9: ='1_GICS_Structure'!B9 | D9: ='4_Cascade_Engine'!P9 | E9: ='4_Cascade_Engine'!Q9 | F9: ='4_Cascade_Engine'!T9 | G9: ='4_Cascade_Engine'!U9
A10: ='4_Cascade_Engine'!A10 | B10: ='4_Cascade_Engine'!B10 | C10: ='1_GICS_Structure'!B10 | D10: ='4_Cascade_Engine'!P10 | E10: ='4_Cascade_Engine'!Q10 | F10: ='4_Cascade_Engine'!T10 | G10: ='4_Cascade_Engine'!U10
A11: ='4_Cascade_Engine'!A11 | B11: ='4_Cascade_Engine'!B11 | C11: ='1_GICS_Structure'!B11 | D11: ='4_Cascade_Engine'!P11 | E11: ='4_Cascade_Engine'!Q11 | F11: ='4_Cascade_Engine'!T11 | G11: ='4_Cascade_Engine'!U11
A12: ='4_Cascade_Engine'!A12 | B12: ='4_Cascade_Engine'!B12 | C12: ='1_GICS_Structure'!B12 | D12: ='4_Cascade_Engine'!P12 | E12: ='4_Cascade_Engine'!Q12 | F12: ='4_Cascade_Engine'!T12 | G12: ='4_Cascade_Engine'!U12
A13: ='4_Cascade_Engine'!A13 | B13: ='4_Cascade_Engine'!B13 | C13: ='1_GICS_Structure'!B13 | D13: ='4_Cascade_Engine'!P13 | E13: ='4_Cascade_Engine'!Q13 | F13: ='4_Cascade_Engine'!T13 | G13: ='4_Cascade_Engine'!U13
A14: ='4_Cascade_Engine'!A14 | B14: ='4_Cascade_Engine'!B14 | C14: ='1_GICS_Structure'!B14 | D14: ='4_Cascade_Engine'!P14 | E14: ='4_Cascade_Engine'!Q14 | F14: ='4_Cascade_Engine'!T14 | G14: ='4_Cascade_Engine'!U14
... A165: ='4_Cascade_Engine'!A165 | B165: ='4_Cascade_Engine'!B165 | C165: ='1_GICS_Structure'!B165 | D165: ='4_Cascade_Engine'!P165 | E165: ='4_Cascade_Engine'!Q165 | F165: ='4_Cascade_Engine'!T165 | G165: ='4_Cascade_Engine'!U165
