Workbook

Sheet Dashboard
A1: HSBC Asset Management | Alternatives Risk
A2: MAT Monitoring Dashboard · All figures auto-update from strategy input tabs
A4: Asset Class / Fund | B4: Risk Stripe | C4: Mand. | D4: Green | E4: Amb-Grn | F4: Amber | G4: Red | H4: Total
A6: Private Credit & Capital Solutions | C6: =DL!B4+InfraDebt!B4+RCF!B4+NAV!B4+TWCS!B4 -> 21 | D6: =DL!B12+InfraDebt!B12+RCF!B12+NAV!B12+TWCS!B12 -> 121 | E6: =DL!C12+InfraDebt!C12+RCF!C12+NAV!C12+TWCS!C12 -> 2 | F6: =DL!D12+InfraDebt!D12+RCF!D12+NAV!D12+TWCS!D12 -> 2 | G6: =DL!E12+InfraDebt!E12+RCF!E12+NAV!E12+TWCS!E12 -> 2 | H6: =DL!F12+InfraDebt!F12+RCF!F12+NAV!F12+TWCS!F12 -> 127
A7: Direct Lending UK & EUR | B7: All risk stripes | C7: =DL!B4 -> 7 | D7: =DL!B12 -> 52 | E7: =DL!C12 -> 1 | F7: =DL!D12 -> 0 | G7: =DL!E12 -> 0 | H7: =DL!F12 -> 53 | I7: =IF(OR(DL!D12>0,DL!E12>0),"→","")
B8: Market Risk | D8: =DL!B7 -> 38 | E8: =DL!C7 -> 1 | F8: =DL!D7 -> 0 | G8: =DL!E7 -> 0 | H8: =DL!F7 -> 39
B9: Liquidity Risk | D9: =DL!B8 -> 7 | E9: =DL!C8 -> 0 | F9: =DL!D8 -> 0 | G9: =DL!E8 -> 0 | H9: =DL!F8 -> 7
B10: Counterparty / CCR | D10: =DL!B9 -> 0 | E10: =DL!C9 -> 0 | F10: =DL!D9 -> 0 | G10: =DL!E9 -> 0 | H10: =DL!F9 -> 0
B11: Sustainability | D11: =DL!B10 -> 7 | E11: =DL!C10 -> 0 | F11: =DL!D10 -> 0 | G11: =DL!E10 -> 0 | H11: =DL!F10 -> 7
B12: Performance | D12: =DL!B11 -> 0 | E12: =DL!C11 -> 0 | F12: =DL!D11 -> 0 | G12: =DL!E11 -> 0 | H12: =DL!F11 -> 0
A13: Infrastructure Debt | B13: All risk stripes | C13: =InfraDebt!B4 -> 8 | D13: =InfraDebt!B12 -> 36 | E13: =InfraDebt!C12 -> 0 | F13: =InfraDebt!D12 -> 2 | G13: =InfraDebt!E12 -> 2 | H13: =InfraDebt!F12 -> 40 | I13: =IF(OR(InfraDebt!D12>0,InfraDebt!E12>0),"→","") -> →
B14: Market Risk | D14: =InfraDebt!B7 -> 16 | E14: =InfraDebt!C7 -> 0 | F14: =InfraDebt!D7 -> 2 | G14: =InfraDebt!E7 -> 2 | H14: =InfraDebt!F7 -> 20
B15: Liquidity Risk | D15: =InfraDebt!B8 -> 16 | E15: =InfraDebt!C8 -> 0 | F15: =InfraDebt!D8 -> 0 | G15: =InfraDebt!E8 -> 0 | H15: =InfraDebt!F8 -> 16
B16: Counterparty / CCR | D16: =InfraDebt!B9 -> 0 | E16: =InfraDebt!C9 -> 0 | F16: =InfraDebt!D9 -> 0 | G16: =InfraDebt!E9 -> 0 | H16: =InfraDebt!F9 -> 0
B17: Sustainability | D17: =InfraDebt!B10 -> 4 | E17: =InfraDebt!C10 -> 0 | F17: =InfraDebt!D10 -> 0 | G17: =InfraDebt!E10 -> 0 | H17: =InfraDebt!F10 -> 4
B18: Performance | D18: =InfraDebt!B11 -> 0 | E18: =InfraDebt!C11 -> 0 | F18: =InfraDebt!D11 -> 0 | G18: =InfraDebt!E11 -> 0 | H18: =InfraDebt!F11 -> 0
A19: RCF | B19: All risk stripes | C19: =RCF!B4 -> 2 | D19: =RCF!B12 -> 15 | E19: =RCF!C12 -> 1 | F19: =RCF!D12 -> 0 | G19: =RCF!E12 -> 0 | H19: =RCF!F12 -> 16 | I19: =IF(OR(RCF!D12>0,RCF!E12>0),"→","")
B20: Market Risk | D20: =RCF!B7 -> 6 | E20: =RCF!C7 -> 0 | F20: =RCF!D7 -> 0 | G20: =RCF!E7 -> 0 | H20: =RCF!F7 -> 6
B21: Liquidity Risk | D21: =RCF!B8 -> 7 | E21: =RCF!C8 -> 1 | F21: =RCF!D8 -> 0 | G21: =RCF!E8 -> 0 | H21: =RCF!F8 -> 8
B22: Counterparty / CCR | D22: =RCF!B9 -> 0 | E22: =RCF!C9 -> 0 | F22: =RCF!D9 -> 0 | G22: =RCF!E9 -> 0 | H22: =RCF!F9 -> 0
B23: Sustainability | D23: =RCF!B10 -> 2 | E23: =RCF!C10 -> 0 | F23: =RCF!D10 -> 0 | G23: =RCF!E10 -> 0 | H23: =RCF!F10 -> 2
B24: Performance | D24: =RCF!B11 -> 0 | E24: =RCF!C11 -> 0 | F24: =RCF!D11 -> 0 | G24: =RCF!E11 -> 0 | H24: =RCF!F11 -> 0
A25: NAV Financing | B25: All risk stripes | C25: =NAV!B4 -> 2 | D25: =NAV!B12 -> 8 | E25: =NAV!C12 -> 0 | F25: =NAV!D12 -> 0 | G25: =NAV!E12 -> 0 | H25: =NAV!F12 -> 8 | I25: =IF(OR(NAV!D12>0,NAV!E12>0),"→","")
B26: Market Risk | D26: =NAV!B7 -> 6 | E26: =NAV!C7 -> 0 | F26: =NAV!D7 -> 0 | G26: =NAV!E7 -> 0 | H26: =NAV!F7 -> 6
B27: Liquidity Risk | D27: =NAV!B8 -> 0 | E27: =NAV!C8 -> 0 | F27: =NAV!D8 -> 0 | G27: =NAV!E8 -> 0 | H27: =NAV!F8 -> 0
B28: Counterparty / CCR | D28: =NAV!B9 -> 0 | E28: =NAV!C9 -> 0 | F28: =NAV!D9 -> 0 | G28: =NAV!E9 -> 0 | H28: =NAV!F9 -> 0
B29: Sustainability | D29: =NAV!B10 -> 2 | E29: =NAV!C10 -> 0 | F29: =NAV!D10 -> 0 | G29: =NAV!E10 -> 0 | H29: =NAV!F10 -> 2
B30: Performance | D30: =NAV!B11 -> 0 | E30: =NAV!C11 -> 0 | F30: =NAV!D11 -> 0 | G30: =NAV!E11 -> 0 | H30: =NAV!F11 -> 0
A31: Trade & Working Capital | B31: All risk stripes | C31: =TWCS!B4 -> 2 | D31: =TWCS!B12 -> 10 | E31: =TWCS!C12 -> 0 | F31: =TWCS!D12 -> 0 | G31: =TWCS!E12 -> 0 | H31: =TWCS!F12 -> 10 | I31: =IF(OR(TWCS!D12>0,TWCS!E12>0),"→","")
B32: Market Risk | D32: =TWCS!B7 -> 10 | E32: =TWCS!C7 -> 0 | F32: =TWCS!D7 -> 0 | G32: =TWCS!E7 -> 0 | H32: =TWCS!F7 -> 10
B33: Liquidity Risk | D33: =TWCS!B8 -> 0 | E33: =TWCS!C8 -> 0 | F33: =TWCS!D8 -> 0 | G33: =TWCS!E8 -> 0 | H33: =TWCS!F8 -> 0
B34: Counterparty / CCR | D34: =TWCS!B9 -> 0 | E34: =TWCS!C9 -> 0 | F34: =TWCS!D9 -> 0 | G34: =TWCS!E9 -> 0 | H34: =TWCS!F9 -> 0
B35: Sustainability | D35: =TWCS!B10 -> 0 | E35: =TWCS!C10 -> 0 | F35: =TWCS!D10 -> 0 | G35: =TWCS!E10 -> 0 | H35: =TWCS!F10 -> 0
B36: Performance | D36: =TWCS!B11 -> 0 | E36: =TWCS!C11 -> 0 | F36: =TWCS!D11 -> 0 | G36: =TWCS!E11 -> 0 | H36: =TWCS!F11 -> 0
A38: Real Asset | C38: ='HAIL RE'!B4+'HTRE RE'!B4+'RE Asia'!B4+REIM!B4+ETI!B4 -> 22 | D38: ='HAIL RE'!B12+'HTRE RE'!B12+'RE Asia'!B12+REIM!B12+ETI!B12 -> 104 | E38: ='HAIL RE'!C12+'HTRE RE'!C12+'RE Asia'!C12+REIM!C12+ETI!C12 -> 16 | F38: ='HAIL RE'!D12+'HTRE RE'!D12+'RE Asia'!D12+REIM!D12+ETI!D12 -> 4 | G38: ='HAIL RE'!E12+'HTRE RE'!E12+'RE Asia'!E12+REIM!E12+ETI!E12 -> 5 | H38: ='HAIL RE'!F12+'HTRE RE'!F12+'RE Asia'!F12+REIM!F12+ETI!F12 -> 129
A39: HAIL Direct RE | B39: All risk stripes | C39: ='HAIL RE'!B4 -> 7 | D39: ='HAIL RE'!B12 -> 23 | E39: ='HAIL RE'!C12 -> 10 | F39: ='HAIL RE'!D12 -> 0 | G39: ='HAIL RE'!E12 -> 2 | H39: ='HAIL RE'!F12 -> 35 | I39: =IF(OR('HAIL RE'!D12>0,'HAIL RE'!E12>0),"→","") -> →
B40: Market Risk | D40: ='HAIL RE'!B7 -> 23 | E40: ='HAIL RE'!C7 -> 10 | F40: ='HAIL RE'!D7 -> 0 | G40: ='HAIL RE'!E7 -> 2 | H40: ='HAIL RE'!F7 -> 35
B41: Liquidity Risk | D41: ='HAIL RE'!B8 -> 0 | E41: ='HAIL RE'!C8 -> 0 | F41: ='HAIL RE'!D8 -> 0 | G41: ='HAIL RE'!E8 -> 0 | H41: ='HAIL RE'!F8 -> 0
B42: Counterparty / CCR | D42: ='HAIL RE'!B9 -> 0 | E42: ='HAIL RE'!C9 -> 0 | F42: ='HAIL RE'!D9 -> 0 | G42: ='HAIL RE'!E9 -> 0 | H42: ='HAIL RE'!F9 -> 0
B43: Sustainability | D43: ='HAIL RE'!B10 -> 0 | E43: ='HAIL RE'!C10 -> 0 | F43: ='HAIL RE'!D10 -> 0 | G43: ='HAIL RE'!E10 -> 0 | H43: ='HAIL RE'!F10 -> 0
B44: Performance | D44: ='HAIL RE'!B11 -> 0 | E44: ='HAIL RE'!C11 -> 0 | F44: ='HAIL RE'!D11 -> 0 | G44: ='HAIL RE'!E11 -> 0 | H44: ='HAIL RE'!F11 -> 0
A45: HTRE RE | B45: All risk stripes | C45: ='HTRE RE'!B4 -> 6 | D45: ='HTRE RE'!B12 -> 33 | E45: ='HTRE RE'!C12 -> 1 | F45: ='HTRE RE'!D12 -> 1 | G45: ='HTRE RE'!E12 -> 1 | H45: ='HTRE RE'!F12 -> 36 | I45: =IF(OR('HTRE RE'!D12>0,'HTRE RE'!E12>0),"→","") -> →
B46: Market Risk | D46: ='HTRE RE'!B7 -> 27 | E46: ='HTRE RE'!C7 -> 1 | F46: ='HTRE RE'!D7 -> 1 | G46: ='HTRE RE'!E7 -> 1 | H46: ='HTRE RE'!F7 -> 30
B47: Liquidity Risk | D47: ='HTRE RE'!B8 -> 0 | E47: ='HTRE RE'!C8 -> 0 | F47: ='HTRE RE'!D8 -> 0 | G47: ='HTRE RE'!E8 -> 0 | H47: ='HTRE RE'!F8 -> 0
B48: Counterparty / CCR | D48: ='HTRE RE'!B9 -> 0 | E48: ='HTRE RE'!C9 -> 0 | F48: ='HTRE RE'!D9 -> 0 | G48: ='HTRE RE'!E9 -> 0 | H48: ='HTRE RE'!F9 -> 0
B49: Sustainability | D49: ='HTRE RE'!B10 -> 6 | E49: ='HTRE RE'!C10 -> 0 | F49: ='HTRE RE'!D10 -> 0 | G49: ='HTRE RE'!E10 -> 0 | H49: ='HTRE RE'!F10 -> 6
B50: Performance | D50: ='HTRE RE'!B11 -> 0 | E50: ='HTRE RE'!C11 -> 0 | F50: ='HTRE RE'!D11 -> 0 | G50: ='HTRE RE'!E11 -> 0 | H50: ='HTRE RE'!F11 -> 0
A51: Real Estate Asia | B51: All risk stripes | C51: ='RE Asia'!B4 -> 5 | D51: ='RE Asia'!B12 -> 24 | E51: ='RE Asia'!C12 -> 4 | F51: ='RE Asia'!D12 -> 1 | G51: ='RE Asia'!E12 -> 1 | H51: ='RE Asia'!F12 -> 30 | I51: =IF(OR('RE Asia'!D12>0,'RE Asia'!E12>0),"→","") -> →
B52: Market Risk | D52: ='RE Asia'!B7 -> 11 | E52: ='RE Asia'!C7 -> 2 | F52: ='RE Asia'!D7 -> 1 | G52: ='RE Asia'!E7 -> 1 | H52: ='RE Asia'!F7 -> 15
B53: Liquidity Risk | D53: ='RE Asia'!B8 -> 5 | E53: ='RE Asia'!C8 -> 0 | F53: ='RE Asia'!D8 -> 0 | G53: ='RE Asia'!E8 -> 0 | H53: ='RE Asia'!F8 -> 5
B54: Counterparty / CCR | D54: ='RE Asia'!B9 -> 5 | E54: ='RE Asia'!C9 -> 0 | F54: ='RE Asia'!D9 -> 0 | G54: ='RE Asia'!E9 -> 0 | H54: ='RE Asia'!F9 -> 5
B55: Sustainability | D55: ='RE Asia'!B10 -> 3 | E55: ='RE Asia'!C10 -> 2 | F55: ='RE Asia'!D10 -> 0 | G55: ='RE Asia'!E10 -> 0 | H55: ='RE Asia'!F10 -> 5
B56: Performance | D56: ='RE Asia'!B11 -> 0 | E56: ='RE Asia'!C11 -> 0 | F56: ='RE Asia'!D11 -> 0 | G56: ='RE Asia'!E11 -> 0 | H56: ='RE Asia'!F11 -> 0
A57: REIM | B57: All risk stripes | C57: =REIM!B4 -> 3 | D57: =REIM!B12 -> 15 | E57: =REIM!C12 -> 1 | F57: =REIM!D12 -> 2 | G57: =REIM!E12 -> 0 | H57: =REIM!F12 -> 18 | I57: =IF(OR(REIM!D12>0,REIM!E12>0),"→","") -> →
B58: Market Risk | D58: =REIM!B7 -> 7 | E58: =REIM!C7 -> 1 | F58: =REIM!D7 -> 1 | G58: =REIM!E7 -> 0 | H58: =REIM!F7 -> 9
B59: Liquidity Risk | D59: =REIM!B8 -> 2 | E59: =REIM!C8 -> 0 | F59: =REIM!D8 -> 1 | G59: =REIM!E8 -> 0 | H59: =REIM!F8 -> 3
B60: Counterparty / CCR | D60: =REIM!B9 -> 3 | E60: =REIM!C9 -> 0 | F60: =REIM!D9 -> 0 | G60: =REIM!E9 -> 0 | H60: =REIM!F9 -> 3
B61: Sustainability | D61: =REIM!B10 -> 3 | E61: =REIM!C10 -> 0 | F61: =REIM!D10 -> 0 | G61: =REIM!E10 -> 0 | H61: =REIM!F10 -> 3
B62: Performance | D62: =REIM!B11 -> 0 | E62: =REIM!C11 -> 0 | F62: =REIM!D11 -> 0 | G62: =REIM!E11 -> 0 | H62: =REIM!F11 -> 0
A63: ETI | B63: All risk stripes | C63: =ETI!B4 -> 1 | D63: =ETI!B12 -> 9 | E63: =ETI!C12 -> 0 | F63: =ETI!D12 -> 0 | G63: =ETI!E12 -> 1 | H63: =ETI!F12 -> 10 | I63: =IF(OR(ETI!D12>0,ETI!E12>0),"→","") -> →
B64: Market Risk | D64: =ETI!B7 -> 5 | E64: =ETI!C7 -> 0 | F64: =ETI!D7 -> 0 | G64: =ETI!E7 -> 1 | H64: =ETI!F7 -> 6
B65: Liquidity Risk | D65: =ETI!B8 -> 0 | E65: =ETI!C8 -> 0 | F65: =ETI!D8 -> 0 | G65: =ETI!E8 -> 0 | H65: =ETI!F8 -> 0
B66: Counterparty / CCR | D66: =ETI!B9 -> 2 | E66: =ETI!C9 -> 0 | F66: =ETI!D9 -> 0 | G66: =ETI!E9 -> 0 | H66: =ETI!F9 -> 2
B67: Sustainability | D67: =ETI!B10 -> 2 | E67: =ETI!C10 -> 0 | F67: =ETI!D10 -> 0 | G67: =ETI!E10 -> 0 | H67: =ETI!F10 -> 2
B68: Performance | D68: =ETI!B11 -> 0 | E68: =ETI!C11 -> 0 | F68: =ETI!D11 -> 0 | G68: =ETI!E11 -> 0 | H68: =ETI!F11 -> 0
A70: Private Markets & Hedge Funds | C70: =HF!B4+PrivMkts!B4+VC!B4 -> 13 | D70: =HF!B12+PrivMkts!B12+VC!B12 -> 56 | E70: =HF!C12+PrivMkts!C12+VC!C12 -> 1 | F70: =HF!D12+PrivMkts!D12+VC!D12 -> 0 | G70: =HF!E12+PrivMkts!E12+VC!E12 -> 1 | H70: =HF!F12+PrivMkts!F12+VC!F12 -> 58
A71: Hedge Funds | B71: All risk stripes | C71: =HF!B4 -> 5 | D71: =HF!B12 -> 19 | E71: =HF!C12 -> 0 | F71: =HF!D12 -> 0 | G71: =HF!E12 -> 1 | H71: =HF!F12 -> 20 | I71: =IF(OR(HF!D12>0,HF!E12>0),"→","") -> →
B72: Market Risk | D72: =HF!B7 -> 9 | E72: =HF!C7 -> 0 | F72: =HF!D7 -> 0 | G72: =HF!E7 -> 1 | H72: =HF!F7 -> 10
B73: Liquidity Risk | D73: =HF!B8 -> 5 | E73: =HF!C8 -> 0 | F73: =HF!D8 -> 0 | G73: =HF!E8 -> 0 | H73: =HF!F8 -> 5
B74: Counterparty / CCR | D74: =HF!B9 -> 5 | E74: =HF!C9 -> 0 | F74: =HF!D9 -> 0 | G74: =HF!E9 -> 0 | H74: =HF!F9 -> 5
B75: Sustainability | D75: =HF!B10 -> 0 | E75: =HF!C10 -> 0 | F75: =HF!D10 -> 0 | G75: =HF!E10 -> 0 | H75: =HF!F10 -> 0
B76: Performance | D76: =HF!B11 -> 0 | E76: =HF!C11 -> 0 | F76: =HF!D11 -> 0 | G76: =HF!E11 -> 0 | H76: =HF!F11 -> 0
A77: Private Markets | B77: All risk stripes | C77: =PrivMkts!B4 -> 7 | D77: =PrivMkts!B12 -> 34 | E77: =PrivMkts!C12 -> 1 | F77: =PrivMkts!D12 -> 0 | G77: =PrivMkts!E12 -> 0 | H77: =PrivMkts!F12 -> 35 | I77: =IF(OR(PrivMkts!D12>0,PrivMkts!E12>0),"→","")
B78: Market Risk | D78: =PrivMkts!B7 -> 27 | E78: =PrivMkts!C7 -> 1 | F78: =PrivMkts!D7 -> 0 | G78: =PrivMkts!E7 -> 0 | H78: =PrivMkts!F7 -> 28
B79: Liquidity Risk | D79: =PrivMkts!B8 -> 7 | E79: =PrivMkts!C8 -> 0 | F79: =PrivMkts!D8 -> 0 | G79: =PrivMkts!E8 -> 0 | H79: =PrivMkts!F8 -> 7
B80: Counterparty / CCR | D80: =PrivMkts!B9 -> 0 | E80: =PrivMkts!C9 -> 0 | F80: =PrivMkts!D9 -> 0 | G80: =PrivMkts!E9 -> 0 | H80: =PrivMkts!F9 -> 0
B81: Sustainability | D81: =PrivMkts!B10 -> 0 | E81: =PrivMkts!C10 -> 0 | F81: =PrivMkts!D10 -> 0 | G81: =PrivMkts!E10 -> 0 | H81: =PrivMkts!F10 -> 0
B82: Performance | D82: =PrivMkts!B11 -> 0 | E82: =PrivMkts!C11 -> 0 | F82: =PrivMkts!D11 -> 0 | G82: =PrivMkts!E11 -> 0 | H82: =PrivMkts!F11 -> 0
A83: Venture Capital | B83: All risk stripes | C83: =VC!B4 -> 1 | D83: =VC!B12 -> 3 | E83: =VC!C12 -> 0 | F83: =VC!D12 -> 0 | G83: =VC!E12 -> 0 | H83: =VC!F12 -> 3 | I83: =IF(OR(VC!D12>0,VC!E12>0),"→","")
B84: Market Risk | D84: =VC!B7 -> 2 | E84: =VC!C7 -> 0 | F84: =VC!D7 -> 0 | G84: =VC!E7 -> 0 | H84: =VC!F7 -> 2
B85: Liquidity Risk | D85: =VC!B8 -> 0 | E85: =VC!C8 -> 0 | F85: =VC!D8 -> 0 | G85: =VC!E8 -> 0 | H85: =VC!F8 -> 0
B86: Counterparty / CCR | D86: =VC!B9 -> 0 | E86: =VC!C9 -> 0 | F86: =VC!D9 -> 0 | G86: =VC!E9 -> 0 | H86: =VC!F9 -> 0
B87: Sustainability | D87: =VC!B10 -> 1 | E87: =VC!C10 -> 0 | F87: =VC!D10 -> 0 | G87: =VC!E10 -> 0 | H87: =VC!F10 -> 1
B88: Performance | D88: =VC!B11 -> 0 | E88: =VC!C11 -> 0 | F88: =VC!D11 -> 0 | G88: =VC!E11 -> 0 | H88: =VC!F11 -> 0
A90: RAG STATUS DEFINITIONS
A91: ▪ Green (G) | B91: No MATs triggered
A92: ▪ Amber-Green (AG) | B92: MATs triggered but not material; portfolio under enhanced monitoring
A93: ▪ Amber (A) | B93: MATs triggered & material; action plan in place and on track
A94: ▪ Red (R) | B94: MATs triggered & material; NO action plan / not on track
A97: ESCALATION FLAGS · Strategies with Amber or Red MATs
A98: Strategy | C98: Mand. | D98: Amber | E98: Red | F98: A+R | G98: Status
A99: Direct Lending UK & EUR | C99: =DL!B4 -> 7 | D99: =DL!D12 -> 0 | E99: =DL!E12 -> 0 | F99: =D99+E99 -> 0 | G99: =IF(E99>0,"RED - Escalate to CRO",IF(D99>0,"AMBER - Monitor","GREEN - On Track")) -> GREEN - On Track
A100: Infrastructure Debt | C100: =InfraDebt!B4 -> 8 | D100: =InfraDebt!D12 -> 2 | E100: =InfraDebt!E12 -> 2 | F100: =D100+E100 -> 4 | G100: =IF(E100>0,"RED - Escalate to CRO",IF(D100>0,"AMBER - Monitor","GREEN - On Track")) -> RED - Escalate to CRO
A101: RCF | C101: =RCF!B4 -> 2 | D101: =RCF!D12 -> 0 | E101: =RCF!E12 -> 0 | F101: =D101+E101 -> 0 | G101: =IF(E101>0,"RED - Escalate to CRO",IF(D101>0,"AMBER - Monitor","GREEN - On Track")) -> GREEN - On Track
A102: NAV Financing | C102: =NAV!B4 -> 2 | D102: =NAV!D12 -> 0 | E102: =NAV!E12 -> 0 | F102: =D102+E102 -> 0 | G102: =IF(E102>0,"RED - Escalate to CRO",IF(D102>0,"AMBER - Monitor","GREEN - On Track")) -> GREEN - On Track
A103: Trade & Working Capital | C103: =TWCS!B4 -> 2 | D103: =TWCS!D12 -> 0 | E103: =TWCS!E12 -> 0 | F103: =D103+E103 -> 0 | G103: =IF(E103>0,"RED - Escalate to CRO",IF(D103>0,"AMBER - Monitor","GREEN - On Track")) -> GREEN - On Track
A104: HAIL Direct RE | C104: ='HAIL RE'!B4 -> 7 | D104: ='HAIL RE'!D12 -> 0 | E104: ='HAIL RE'!E12 -> 2 | F104: =D104+E104 -> 2 | G104: =IF(E104>0,"RED - Escalate to CRO",IF(D104>0,"AMBER - Monitor","GREEN - On Track")) -> RED - Escalate to CRO
A105: HTRE RE | C105: ='HTRE RE'!B4 -> 6 | D105: ='HTRE RE'!D12 -> 1 | E105: ='HTRE RE'!E12 -> 1 | F105: =D105+E105 -> 2 | G105: =IF(E105>0,"RED - Escalate to CRO",IF(D105>0,"AMBER - Monitor","GREEN - On Track")) -> RED - Escalate to CRO
A106: Real Estate Asia | C106: ='RE Asia'!B4 -> 5 | D106: ='RE Asia'!D12 -> 1 | E106: ='RE Asia'!E12 -> 1 | F106: =D106+E106 -> 2 | G106: =IF(E106>0,"RED - Escalate to CRO",IF(D106>0,"AMBER - Monitor","GREEN - On Track")) -> RED - Escalate to CRO
A107: REIM | C107: =REIM!B4 -> 3 | D107: =REIM!D12 -> 2 | E107: =REIM!E12 -> 0 | F107: =D107+E107 -> 2 | G107: =IF(E107>0,"RED - Escalate to CRO",IF(D107>0,"AMBER - Monitor","GREEN - On Track")) -> AMBER - Monitor
...

Sheet CRO Charts
A1: HSBC Asset Management | Alternatives · MAT Risk Executive Summary | S1: ◀ CHART DATA ZONE – formula-driven from input tabs – do not edit manually
A2: CRO Dashboard · Private Credit | Real Assets | Private Markets & HF
S3: Section | T3: Green | U3: Amb-Grn | V3: Amber | W3: Red | X3: A+R | Y3: Total
A4: TOTAL MATs MONITORED | E4: ON TRACK (Green + AG) | I4: UNDER WATCH (Amber) | M4: ESCALATED (Red) | S4: Private Credit | T4: =DL!B12+InfraDebt!B12+RCF!B12+NAV!B12+TWCS!B12 -> 121 | U4: =DL!C12+InfraDebt!C12+RCF!C12+NAV!C12+TWCS!C12 -> 2 | V4: =DL!D12+InfraDebt!D12+RCF!D12+NAV!D12+TWCS!D12 -> 2 | W4: =DL!E12+InfraDebt!E12+RCF!E12+NAV!E12+TWCS!E12 -> 2 | X4: =V4+W4 -> 4 | Y4: =DL!F12+InfraDebt!F12+RCF!F12+NAV!F12+TWCS!F12 -> 127
S5: Real Asset | T5: ='HAIL RE'!B12+'HTRE RE'!B12+'RE Asia'!B12+REIM!B12+ETI!B12 -> 104 | U5: ='HAIL RE'!C12+'HTRE RE'!C12+'RE Asia'!C12+REIM!C12+ETI!C12 -> 16 | V5: ='HAIL RE'!D12+'HTRE RE'!D12+'RE Asia'!D12+REIM!D12+ETI!D12 -> 4 | W5: ='HAIL RE'!E12+'HTRE RE'!E12+'RE Asia'!E12+REIM!E12+ETI!E12 -> 5 | X5: =V5+W5 -> 9 | Y5: ='HAIL RE'!F12+'HTRE RE'!F12+'RE Asia'!F12+REIM!F12+ETI!F12 -> 129
A6: =DL!F12+InfraDebt!F12+RCF!F12+NAV!F12+TWCS!F12+'HAIL RE'!F12+'HTRE RE'!F12+'RE Asia'!F12+REIM!F12+ETI!F12+HF!F12+PrivMkts!F12+VC!F12 -> 314 | E6: =DL!B12+InfraDebt!B12+RCF!B12+NAV!B12+TWCS!B12+'HAIL RE'!B12+'HTRE RE'!B12+'RE Asia'!B12+REIM!B12+ETI!B12+HF!B12+PrivMkts!B12+VC!B12+DL!C12+InfraDebt!C12+RCF!C12+NAV!C12+TWCS!C12+'HAIL RE'!C12+'HTRE RE'!C12+'RE Asia'!C12+REIM!C12+ETI!C12+HF!C12+PrivMkts!C12+VC!C12 -> 300 | I6: =DL!D12+InfraDebt!D12+RCF!D12+NAV!D12+TWCS!D12+'HAIL RE'!D12+'HTRE RE'!D12+'RE Asia'!D12+REIM!D12+ETI!D12+HF!D12+PrivMkts!D12+VC!D12 -> 6 | M6: =DL!E12+InfraDebt!E12+RCF!E12+NAV!E12+TWCS!E12+'HAIL RE'!E12+'HTRE RE'!E12+'RE Asia'!E12+REIM!E12+ETI!E12+HF!E12+PrivMkts!E12+VC!E12 -> 8 | S6: Priv Mkts + HF | T6: =HF!B12+PrivMkts!B12+VC!B12 -> 56 | U6: =HF!C12+PrivMkts!C12+VC!C12 -> 1 | V6: =HF!D12+PrivMkts!D12+VC!D12 -> 0 | W6: =HF!E12+PrivMkts!E12+VC!E12 -> 1 | X6: =V6+W6 -> 1 | Y6: =HF!F12+PrivMkts!F12+VC!F12 -> 58
S7: TOTAL | T7: =SUM(T4:T6) -> 281 | U7: =SUM(U4:U6) -> 19 | V7: =SUM(V4:V6) -> 6 | W7: =SUM(W4:W6) -> 8 | X7: =SUM(X4:X6) -> 14 | Y7: =SUM(Y4:Y6) -> 314
A9: Across all strategies & risk stripes | E9: No escalation required | I9: Action plans in place — monitor closely | M9: Requires CRO attention & action | S9: Strategy | T9: Green | U9: Amb-Grn | V9: Amber | W9: Red | X9: A+R | Y9: Total
S10: Direct Lending UK … | T10: =DL!B12 -> 52 | U10: =DL!C12 -> 1 | V10: =DL!D12 -> 0 | W10: =DL!E12 -> 0 | X10: =V10+W10 -> 0 | Y10: =DL!F12 -> 53
S11: Infrastructure Debt | T11: =InfraDebt!B12 -> 36 | U11: =InfraDebt!C12 -> 0 | V11: =InfraDebt!D12 -> 2 | W11: =InfraDebt!E12 -> 2 | X11: =V11+W11 -> 4 | Y11: =InfraDebt!F12 -> 40
S12: RCF | T12: =RCF!B12 -> 15 | U12: =RCF!C12 -> 1 | V12: =RCF!D12 -> 0 | W12: =RCF!E12 -> 0 | X12: =V12+W12 -> 0 | Y12: =RCF!F12 -> 16
S13: NAV Financing | T13: =NAV!B12 -> 8 | U13: =NAV!C12 -> 0 | V13: =NAV!D12 -> 0 | W13: =NAV!E12 -> 0 | X13: =V13+W13 -> 0 | Y13: =NAV!F12 -> 8
S14: Trade & Working Ca… | T14: =TWCS!B12 -> 10 | U14: =TWCS!C12 -> 0 | V14: =TWCS!D12 -> 0 | W14: =TWCS!E12 -> 0 | X14: =V14+W14 -> 0 | Y14: =TWCS!F12 -> 10
S15: HAIL Direct RE | T15: ='HAIL RE'!B12 -> 23 | U15: ='HAIL RE'!C12 -> 10 | V15: ='HAIL RE'!D12 -> 0 | W15: ='HAIL RE'!E12 -> 2 | X15: =V15+W15 -> 2 | Y15: ='HAIL RE'!F12 -> 35
S16: HTRE RE | T16: ='HTRE RE'!B12 -> 33 | U16: ='HTRE RE'!C12 -> 1 | V16: ='HTRE RE'!D12 -> 1 | W16: ='HTRE RE'!E12 -> 1 | X16: =V16+W16 -> 2 | Y16: ='HTRE RE'!F12 -> 36
S17: Real Estate Asia | T17: ='RE Asia'!B12 -> 24 | U17: ='RE Asia'!C12 -> 4 | V17: ='RE Asia'!D12 -> 1 | W17: ='RE Asia'!E12 -> 1 | X17: =V17+W17 -> 2 | Y17: ='RE Asia'!F12 -> 30
S18: REIM | T18: =REIM!B12 -> 15 | U18: =REIM!C12 -> 1 | V18: =REIM!D12 -> 2 | W18: =REIM!E12 -> 0 | X18: =V18+W18 -> 2 | Y18: =REIM!F12 -> 18
S19: ETI | T19: =ETI!B12 -> 9 | U19: =ETI!C12 -> 0 | V19: =ETI!D12 -> 0 | W19: =ETI!E12 -> 1 | X19: =V19+W19 -> 1 | Y19: =ETI!F12 -> 10
S20: Hedge Funds | T20: =HF!B12 -> 19 | U20: =HF!C12 -> 0 | V20: =HF!D12 -> 0 | W20: =HF!E12 -> 1 | X20: =V20+W20 -> 1 | Y20: =HF!F12 -> 20
S21: Private Markets | T21: =PrivMkts!B12 -> 34 | U21: =PrivMkts!C12 -> 1 | V21: =PrivMkts!D12 -> 0 | W21: =PrivMkts!E12 -> 0 | X21: =V21+W21 -> 0 | Y21: =PrivMkts!F12 -> 35
S22: Venture Capital | T22: =VC!B12 -> 3 | U22: =VC!C12 -> 0 | V22: =VC!D12 -> 0 | W22: =VC!E12 -> 0 | X22: =V22+W22 -> 0 | Y22: =VC!F12 -> 3
S24: Risk Stripe | T24: Green | U24: Amb-Grn | V24: Amber | W24: Red | X24: A+R | Y24: Total
S25: Market Risk | T25: =DL!B7+InfraDebt!B7+RCF!B7+NAV!B7+TWCS!B7+'HAIL RE'!B7+'HTRE RE'!B7+'RE Asia'!B7+REIM!B7+ETI!B7+HF!B7+PrivMkts!B7+VC!B7 -> 187 | U25: =DL!C7+InfraDebt!C7+RCF!C7+NAV!C7+TWCS!C7+'HAIL RE'!C7+'HTRE RE'!C7+'RE Asia'!C7+REIM!C7+ETI!C7+HF!C7+PrivMkts!C7+VC!C7 -> 16 | V25: =DL!D7+InfraDebt!D7+RCF!D7+NAV!D7+TWCS!D7+'HAIL RE'!D7+'HTRE RE'!D7+'RE Asia'!D7+REIM!D7+ETI!D7+HF!D7+PrivMkts!D7+VC!D7 -> 5 | W25: =DL!E7+InfraDebt!E7+RCF!E7+NAV!E7+TWCS!E7+'HAIL RE'!E7+'HTRE RE'!E7+'RE Asia'!E7+REIM!E7+ETI!E7+HF!E7+PrivMkts!E7+VC!E7 -> 8 | X25: =V25+W25 -> 13 | Y25: =DL!F7+InfraDebt!F7+RCF!F7+NAV!F7+TWCS!F7+'HAIL RE'!F7+'HTRE RE'!F7+'RE Asia'!F7+REIM!F7+ETI!F7+HF!F7+PrivMkts!F7+VC!F7 -> 216
S26: Liquidity Risk | T26: =DL!B8+InfraDebt!B8+RCF!B8+NAV!B8+TWCS!B8+'HAIL RE'!B8+'HTRE RE'!B8+'RE Asia'!B8+REIM!B8+ETI!B8+HF!B8+PrivMkts!B8+VC!B8 -> 49 | U26: =DL!C8+InfraDebt!C8+RCF!C8+NAV!C8+TWCS!C8+'HAIL RE'!C8+'HTRE RE'!C8+'RE Asia'!C8+REIM!C8+ETI!C8+HF!C8+PrivMkts!C8+VC!C8 -> 1 | V26: =DL!D8+InfraDebt!D8+RCF!D8+NAV!D8+TWCS!D8+'HAIL RE'!D8+'HTRE RE'!D8+'RE Asia'!D8+REIM!D8+ETI!D8+HF!D8+PrivMkts!D8+VC!D8 -> 1 | W26: =DL!E8+InfraDebt!E8+RCF!E8+NAV!E8+TWCS!E8+'HAIL RE'!E8+'HTRE RE'!E8+'RE Asia'!E8+REIM!E8+ETI!E8+HF!E8+PrivMkts!E8+VC!E8 -> 0 | X26: =V26+W26 -> 1 | Y26: =DL!F8+InfraDebt!F8+RCF!F8+NAV!F8+TWCS!F8+'HAIL RE'!F8+'HTRE RE'!F8+'RE Asia'!F8+REIM!F8+ETI!F8+HF!F8+PrivMkts!F8+VC!F8 -> 51
S27: Counterparty / CCR | T27: =DL!B9+InfraDebt!B9+RCF!B9+NAV!B9+TWCS!B9+'HAIL RE'!B9+'HTRE RE'!B9+'RE Asia'!B9+REIM!B9+ETI!B9+HF!B9+PrivMkts!B9+VC!B9 -> 15 | U27: =DL!C9+InfraDebt!C9+RCF!C9+NAV!C9+TWCS!C9+'HAIL RE'!C9+'HTRE RE'!C9+'RE Asia'!C9+REIM!C9+ETI!C9+HF!C9+PrivMkts!C9+VC!C9 -> 0 | V27: =DL!D9+InfraDebt!D9+RCF!D9+NAV!D9+TWCS!D9+'HAIL RE'!D9+'HTRE RE'!D9+'RE Asia'!D9+REIM!D9+ETI!D9+HF!D9+PrivMkts!D9+VC!D9 -> 0 | W27: =DL!E9+InfraDebt!E9+RCF!E9+NAV!E9+TWCS!E9+'HAIL RE'!E9+'HTRE RE'!E9+'RE Asia'!E9+REIM!E9+ETI!E9+HF!E9+PrivMkts!E9+VC!E9 -> 0 | X27: =V27+W27 -> 0 | Y27: =DL!F9+InfraDebt!F9+RCF!F9+NAV!F9+TWCS!F9+'HAIL RE'!F9+'HTRE RE'!F9+'RE Asia'!F9+REIM!F9+ETI!F9+HF!F9+PrivMkts!F9+VC!F9 -> 15
S28: Sustainability | T28: =DL!B10+InfraDebt!B10+RCF!B10+NAV!B10+TWCS!B10+'HAIL RE'!B10+'HTRE RE'!B10+'RE Asia'!B10+REIM!B10+ETI!B10+HF!B10+PrivMkts!B10+VC!B10 -> 30 | U28: =DL!C10+InfraDebt!C10+RCF!C10+NAV!C10+TWCS!C10+'HAIL RE'!C10+'HTRE RE'!C10+'RE Asia'!C10+REIM!C10+ETI!C10+HF!C10+PrivMkts!C10+VC!C10 -> 2 | V28: =DL!D10+InfraDebt!D10+RCF!D10+NAV!D10+TWCS!D10+'HAIL RE'!D10+'HTRE RE'!D10+'RE Asia'!D10+REIM!D10+ETI!D10+HF!D10+PrivMkts!D10+VC!D10 -> 0 | W28: =DL!E10+InfraDebt!E10+RCF!E10+NAV!E10+TWCS!E10+'HAIL RE'!E10+'HTRE RE'!E10+'RE Asia'!E10+REIM!E10+ETI!E10+HF!E10+PrivMkts!E10+VC!E10 -> 0 | X28: =V28+W28 -> 0 | Y28: =DL!F10+InfraDebt!F10+RCF!F10+NAV!F10+TWCS!F10+'HAIL RE'!F10+'HTRE RE'!F10+'RE Asia'!F10+REIM!F10+ETI!F10+HF!F10+PrivMkts!F10+VC!F10 -> 32
S29: Performance | T29: =DL!B11+InfraDebt!B11+RCF!B11+NAV!B11+TWCS!B11+'HAIL RE'!B11+'HTRE RE'!B11+'RE Asia'!B11+REIM!B11+ETI!B11+HF!B11+PrivMkts!B11+VC!B11 -> 0 | U29: =DL!C11+InfraDebt!C11+RCF!C11+NAV!C11+TWCS!C11+'HAIL RE'!C11+'HTRE RE'!C11+'RE Asia'!C11+REIM!C11+ETI!C11+HF!C11+PrivMkts!C11+VC!C11 -> 0 | V29: =DL!D11+InfraDebt!D11+RCF!D11+NAV!D11+TWCS!D11+'HAIL RE'!D11+'HTRE RE'!D11+'RE Asia'!D11+REIM!D11+ETI!D11+HF!D11+PrivMkts!D11+VC!D11 -> 0 | W29: =DL!E11+InfraDebt!E11+RCF!E11+NAV!E11+TWCS!E11+'HAIL RE'!E11+'HTRE RE'!E11+'RE Asia'!E11+REIM!E11+ETI!E11+HF!E11+PrivMkts!E11+VC!E11 -> 0 | X29: =V29+W29 -> 0 | Y29: =DL!F11+InfraDebt!F11+RCF!F11+NAV!F11+TWCS!F11+'HAIL RE'!F11+'HTRE RE'!F11+'RE Asia'!F11+REIM!F11+ETI!F11+HF!F11+PrivMkts!F11+VC!F11 -> 0
S31: Strategy | T31: Amber | U31: Red
S32: Direct Lending UK … | T32: =V10 -> 0 | U32: =W10 -> 0
S33: OVERALL RAG SPLIT (%) | T33: =V11 -> 2 | U33: =W11 -> 2
S34: Green | T34: =T7/Y7 -> 0.89490446 | U34: =W12 -> 0
S35: Amber-Green | T35: =U7/Y7 -> 0.060509554 | U35: =W13 -> 0
S36: Amber | T36: =V7/Y7 -> 0.01910828 | U36: =W14 -> 0
S37: Red | T37: =W7/Y7 -> 0.025477707 | U37: =W15 -> 2
S38: HTRE RE | T38: =V16 -> 1 | U38: =W16 -> 1
S39: Real Estate Asia | T39: =V17 -> 1 | U39: =W17 -> 1
S40: REIM | T40: =V18 -> 2 | U40: =W18 -> 0
S41: ETI | T41: =V19 -> 0 | U41: =W19 -> 1
S42: Hedge Funds | T42: =V20 -> 0 | U42: =W20 -> 1
S43: Private Markets | T43: =V21 -> 0 | U43: =W21 -> 0
S44: Venture Capital | T44: =V22 -> 0 | U44: =W22 -> 0

Sheet Data Guide
A1: Data Guide – How to Update the Dashboard Each Quarter
A3: Quarterly Update Workflow
A5: 1. Open the strategy tab for the report received (e.g. 'DL' for Direct Lending).
A6: 2. Update cell B3 → reporting period (e.g. 'Q4 2025').
A7: 3. Update cell B4 → number of mandates / funds in scope.
A8: 4. Enter G / AG / A / R per fund per MAT in the fund cells (row 15+).
A9: Columns D onwards = individual funds. Rows = individual MAT metrics.
A10: Status codes: G = Green | AG = Amber-Green | A = Amber | R = Red
A11: Cells colour automatically via conditional formatting.
A12: 5. Rows 7–12 (Strategy Summary) recalculate instantly via SUMPRODUCT formulas.
A13: 6. Switch to 'Dashboard' or 'CRO Charts' – all totals refresh automatically.
A15: How the formulas work
... A27: Strategy Tabs
A29: Tab | B29: Strategy | C29: Section | D29: Period
A30: DL | B30: Direct Lending UK & EUR | C30: Private Credit | D30: Q3 2025
A31: InfraDebt | B31: Infrastructure Debt | C31: Private Credit | D31: Q3 2025
A32: RCF | B32: RCF | C32: Private Credit | D32: Q3 2025
A33: NAV | B33: NAV Financing | C33: Private Credit | D33: Q4 2025
A34: TWCS | B34: Trade & Working Capital | C34: Private Credit | D34: Q4 2025
A35: HAIL RE | B35: HAIL Direct RE | C35: Real Assets | D35: Q4 2025
A36: HTRE RE | B36: HTRE RE | C36: Real Assets | D36: Q3 2025
A37: RE Asia | B37: Real Estate Asia | C37: Real Assets | D37: Q3 2025
A38: REIM | B38: REIM | C38: Real Assets | D38: Q3 2025
A39: ETI | B39: ETI | C39: Real Assets | D39: Q3 2025
A40: HF | B40: Hedge Funds | C40: Priv Mkts + HF | D40: Q3 2025
... A42: VC | B42: Venture Capital | C42: Priv Mkts + HF | D42: Q3 2025

Sheet DL
A1: Direct Lending UK & EUR · MAT Monitoring
A2: ▸ Update B3 = Reporting Period ▸ Update B4 = Number of Mandates ▸ Enter G / AG / A / R per fund in the coloured cells below (rows 15+) ▸ Strategy Summary (rows 7–12) and Dashboard auto-refresh via formulas
A3: Reporting Period | B3: Q3 2025
A4: Number of Mandates / Funds | B4: 7
A6: STRATEGY SUMMARY (auto-calculated from fund data below ▼) | B6: Green | C6: Amb-Grn | D6: Amber | E6: Red | F6: Total
A7: Market Risk | B7: =SUMPRODUCT(($B$15:$B$200="Market Risk")*(($D$15:$D$200="G")+($E$15:$E$200="G")+($F$15:$F$200="G")+($G$15:$G$200="G")+($H$15:$H$200="G")+($I$15:$I$200="G")+($J$15:$J$200="G")+($K$15:$K$200="G")+($L$15:$L$200="G")+($M$15:$M$200="G"))) -> 38 | C7: =SUMPRODUCT(($B$15:$B$200="Market Risk")*(($D$15:$D$200="AG")+($E$15:$E$200="AG")+($F$15:$F$200="AG")+($G$15:$G$200="AG")+($H$15:$H$200="AG")+($I$15:$I$200="AG")+($J$15:$J$200="AG")+($K$15:$K$200="AG")+($L$15:$L$200="AG")+($M$15:$M$200="AG"))) -> 1 | D7: =SUMPRODUCT(($B$15:$B$200="Market Risk")*(($D$15:$D$200="A")+($E$15:$E$200="A")+($F$15:$F$200="A")+($G$15:$G$200="A")+($H$15:$H$200="A")+($I$15:$I$200="A")+($J$15:$J$200="A")+($K$15:$K$200="A")+($L$15:$L$200="A")+($M$15:$M$200="A"))) -> 0 | E7: =SUMPRODUCT(($B$15:$B$200="Market Risk")*(($D$15:$D$200="R")+($E$15:$E$200="R")+($F$15:$F$200="R")+($G$15:$G$200="R")+($H$15:$H$200="R")+($I$15:$I$200="R")+($J$15:$J$200="R")+($K$15:$K$200="R")+($L$15:$L$200="R")+($M$15:$M$200="R"))) -> 0 | F7: =SUM(B7:E7) -> 39
A8: Liquidity Risk | B8: =SUMPRODUCT(($B$15:$B$200="Liquidity Risk")*(($D$15:$D$200="G")+($E$15:$E$200="G")+($F$15:$F$200="G")+($G$15:$G$200="G")+($H$15:$H$200="G")+($I$15:$I$200="G")+($J$15:$J$200="G")+($K$15:$K$200="G")+($L$15:$L$200="G")+($M$15:$M$200="G"))) -> 7 | C8: =SUMPRODUCT(($B$15:$B$200="Liquidity Risk")*(($D$15:$D$200="AG")+($E$15:$E$200="AG")+($F$15:$F$200="AG")+($G$15:$G$200="AG")+($H$15:$H$200="AG")+($I$15:$I$200="AG")+($J$15:$J$200="AG")+($K$15:$K$200="AG")+($L$15:$L$200="AG")+($M$15:$M$200="AG"))) -> 0 | D8: =SUMPRODUCT(($B$15:$B$200="Liquidity Risk")*(($D$15:$D$200="A")+($E$15:$E$200="A")+($F$15:$F$200="A")+($G$15:$G$200="A")+($H$15:$H$200="A")+($I$15:$I$200="A")+($J$15:$J$200="A")+($K$15:$K$200="A")+($L$15:$L$200="A")+($M$15:$M$200="A"))) -> 0 | E8: =SUMPRODUCT(($B$15:$B$200="Liquidity Risk")*(($D$15:$D$200="R")+($E$15:$E$200="R")+($F$15:$F$200="R")+($G$15:$G$200="R")+($H$15:$H$200="R")+($I$15:$I$200="R")+($J$15:$J$200="R")+($K$15:$K$200="R")+($L$15:$L$200="R")+($M$15:$M$200="R"))) -> 0 | F8: =SUM(B8:E8) -> 7
A9: Counterparty / CCR | B9: =SUMPRODUCT(($B$15:$B$200="Counterparty / CCR")*(($D$15:$D$200="G")+($E$15:$E$200="G")+($F$15:$F$200="G")+($G$15:$G$200="G")+($H$15:$H$200="G")+($I$15:$I$200="G")+($J$15:$J$200="G")+($K$15:$K$200="G")+($L$15:$L$200="G")+($M$15:$M$200="G"))) -> 0 | C9: =SUMPRODUCT(($B$15:$B$200="Counterparty / CCR")*(($D$15:$D$200="AG")+($E$15:$E$200="AG")+($F$15:$F$200="AG")+($G$15:$G$200="AG")+($H$15:$H$200="AG")+($I$15:$I$200="AG")+($J$15:$J$200="AG")+($K$15:$K$200="AG")+($L$15:$L$200="AG")+($M$15:$M$200="AG"))) -> 0 | D9: =SUMPRODUCT(($B$15:$B$200="Counterparty / CCR")*(($D$15:$D$200="A")+($E$15:$E$200="A")+($F$15:$F$200="A")+($G$15:$G$200="A")+($H$15:$H$200="A")+($I$15:$I$200="A")+($J$15:$J$200="A")+($K$15:$K$200="A")+($L$15:$L$200="A")+($M$15:$M$200="A"))) -> 0 | E9: =SUMPRODUCT(($B$15:$B$200="Counterparty / CCR")*(($D$15:$D$200="R")+($E$15:$E$200="R")+($F$15:$F$200="R")+($G$15:$G$200="R")+($H$15:$H$200="R")+($I$15:$I$200="R")+($J$15:$J$200="R")+($K$15:$K$200="R")+($L$15:$L$200="R")+($M$15:$M$200="R"))) -> 0 | F9: =SUM(B9:E9) -> 0
A10: Sustainability | B10: =SUMPRODUCT(($B$15:$B$200="Sustainability")*(($D$15:$D$200="G")+($E$15:$E$200="G")+($F$15:$F$200="G")+($G$15:$G$200="G")+($H$15:$H$200="G")+($I$15:$I$200="G")+($J$15:$J$200="G")+($K$15:$K$200="G")+($L$15:$L$200="G")+($M$15:$M$200="G"))) -> 7 | C10: =SUMPRODUCT(($B$15:$B$200="Sustainability")*(($D$15:$D$200="AG")+($E$15:$E$200="AG")+($F$15:$F$200="AG")+($G$15:$G$200="AG")+($H$15:$H$200="AG")+($I$15:$I$200="AG")+($J$15:$J$200="AG")+($K$15:$K$200="AG")+($L$15:$L$200="AG")+($M$15:$M$200="AG"))) -> 0 | D10: =SUMPRODUCT(($B$15:$B$200="Sustainability")*(($D$15:$D$200="A")+($E$15:$E$200="A")+($F$15:$F$200="A")+($G$15:$G$200="A")+($H$15:$H$200="A")+($I$15:$I$200="A")+($J$15:$J$200="A")+($K$15:$K$200="A")+($L$15:$L$200="A")+($M$15:$M$200="A"))) -> 0 | E10: =SUMPRODUCT(($B$15:$B$200="Sustainability")*(($D$15:$D$200="R")+($E$15:$E$200="R")+($F$15:$F$200="R")+($G$15:$G$200="R")+($H$15:$H$200="R")+($I$15:$I$200="R")+($J$15:$J$200="R")+($K$15:$K$200="R")+($L$15:$L$200="R")+($M$15:$M$200="R"))) -> 0 | F10: =SUM(B10:E10) -> 7
A11: Performance | B11: =SUMPRODUCT(($B$15:$B$200="Performance")*(($D$15:$D$200="G")+($E$15:$E$200="G")+($F$15:$F$200="G")+($G$15:$G$200="G")+($H$15:$H$200="G")+($I$15:$I$200="G")+($J$15:$J$200="G")+($K$15:$K$200="G")+($L$15:$L$200="G")+($M$15:$M$200="G"))) -> 0 | C11: =SUMPRODUCT(($B$15:$B$200="Performance")*(($D$15:$D$200="AG")+($E$15:$E$200="AG")+($F$15:$F$200="AG")+($G$15:$G$200="AG")+($H$15:$H$200="AG")+($I$15:$I$200="AG")+($J$15:$J$200="AG")+($K$15:$K$200="AG")+($L$15:$L$200="AG")+($M$15:$M$200="AG"))) -> 0 | D11: =SUMPRODUCT(($B$15:$B$200="Performance")*(($D$15:$D$200="A")+($E$15:$E$200="A")+($F$15:$F$200="A")+($G$15:$G$200="A")+($H$15:$H$200="A")+($I$15:$I$200="A")+($J$15:$J$200="A")+($K$15:$K$200="A")+($L$15:$L$200="A")+($M$15:$M$200="A"))) -> 0 | E11: =SUMPRODUCT(($B$15:$B$200="Performance")*(($D$15:$D$200="R")+($E$15:$E$200="R")+($F$15:$F$200="R")+($G$15:$G$200="R")+($H$15:$H$200="R")+($I$15:$I$200="R")+($J$15:$J$200="R")+($K$15:$K$200="R")+($L$15:$L$200="R")+($M$15:$M$200="R"))) -> 0 | F11: =SUM(B11:E11) -> 0
A12: TOTAL | B12: =SUM(B7:B11) -> 52 | C12: =SUM(C7:C11) -> 1 | D12: =SUM(D7:D11) -> 0 | E12: =SUM(E7:E11) -> 0 | F12: =SUM(F7:F11) -> 53
A14: FUND-LEVEL MAT DATA · 7 funds · Enter G / AG / A / R per fund in each cell ▼
A15: MAT Metric | B15: Risk Type | C15: Trigger | D15: SDLF I | E15: SDLF II | F15: ESDLF | G15: Anglo | H15: Hollywood | I15: INSP | J15: Orchid
A16: Watchlist (% Amber / any red) | B16: Market Risk | C16: >=20% | D16: G | E16: G | F16: G | G16: G | H16: G | I16: G | J16: G
A17: Portfolio Leverage at Origination | B17: Market Risk | C17: >=4.5x | D17: G | E17: G | F17: G | G17: G | H17: G | I17: G | J17: G
A18: Portfolio Leverage Over Time | B18: Market Risk | C18: >=5.0x | D18: G | E18: G | F18: G | G18: AG | H18: G | I18: G | J18: G
A19: Industry Concentration Risk | B19: Market Risk | C19: >30% | D19: G | E19: G | F19: G | G19: G | H19: G | I19: G | J19: G
A20: Breach of Covenants / Guidelines | B20: Market Risk | C20: >0 | D20: G | E20: G | F20: G | G20: G | H20: G | I20: G | J20: G
A21: Breach of Liquidity MATs | B21: Market Risk | D21: G | E21: G | F21: G | G21: G
A22: Downgrade to 'Weak' rating | B22: Liquidity Risk | D22: G | E22: G | F22: G | G22: G | H22: G | I22: G | J22: G
A23: Sustainability | B23: Sustainability | D23: G | E23: G | F23: G | G23: G | H23: G | I23: G | J23: G

Sheet InfraDebt
A1: Infrastructure Debt · MAT Monitoring
A2: ▸ Update B3 = Reporting Period ▸ Update B4 = Number of Mandates ▸ Enter G / AG / A / R per fund in the coloured cells below (rows 15+) ▸ Strategy Summary (rows 7–12) and Dashboard auto-refresh via formulas
A3: Reporting Period | B3: Q3 2025
A4: Number of Mandates / Funds | B4: 8
A6: STRATEGY SUMMARY (auto-calculated from fund data below ▼) | B6: Green | C6: Amb-Grn | D6: Amber | E6: Red | F6: Total
A7: Market Risk | B7: =SUMPRODUCT(($B$15:$B$200="Market Risk")*(($D$15:$D$200="G")+($E$15:$E$200="G")+($F$15:$F$200="G")+($G$15:$G$200="G")+($H$15:$H$200="G")+($I$15:$I$200="G")+($J$15:$J$200="G")+($K$15:$K$200="G")+($L$15:$L$200="G")+($M$15:$M$200="G"))) -> 16 | C7: =SUMPRODUCT(($B$15:$B$200="Market Risk")*(($D$15:$D$200="AG")+($E$15:$E$200="AG")+($F$15:$F$200="AG")+($G$15:$G$200="AG")+($H$15:$H$200="AG")+($I$15:$I$200="AG")+($J$15:$J$200="AG")+($K$15:$K$200="AG")+($L$15:$L$200="AG")+($M$15:$M$200="AG"))) -> 0 | D7: =SUMPRODUCT(($B$15:$B$200="Market Risk")*(($D$15:$D$200="A")+($E$15:$E$200="A")+($F$15:$F$200="A")+($G$15:$G$200="A")+($H$15:$H$200="A")+($I$15:$I$200="A")+($J$15:$J$200="A")+($K$15:$K$200="A")+($L$15:$L$200="A")+($M$15:$M$200="A"))) -> 2 | E7: =SUMPRODUCT(($B$15:$B$200="Market Risk")*(($D$15:$D$200="R")+($E$15:$E$200="R")+($F$15:$F$200="R")+($G$15:$G$200="R")+($H$15:$H$200="R")+($I$15:$I$200="R")+($J$15:$J$200="R")+($K$15:$K$200="R")+($L$15:$L$200="R")+($M$15:$M$200="R"))) -> 2 | F7: =SUM(B7:E7) -> 20
A8: Liquidity Risk | B8: =SUMPRODUCT(($B$15:$B$200="Liquidity Risk")*(($D$15:$D$200="G")+($E$15:$E$200="G")+($F$15:$F$200="G")+($G$15:$G$200="G")+($H$15:$H$200="G")+($I$15:$I$200="G")+($J$15:$J$200="G")+($K$15:$K$200="G")+($L$15:$L$200="G")+($M$15:$M$200="G"))) -> 16 | C8: =SUMPRODUCT(($B$15:$B$200="Liquidity Risk")*(($D$15:$D$200="AG")+($E$15:$E$200="AG")+($F$15:$F$200="AG")+($G$15:$G$200="AG")+($H$15:$H$200="AG")+($I$15:$I$200="AG")+($J$15:$J$200="AG")+($K$15:$K$200="AG")+($L$15:$L$200="AG")+($M$15:$M$200="AG"))) -> 0 | D8: =SUMPRODUCT(($B$15:$B$200="Liquidity Risk")*(($D$15:$D$200="A")+($E$15:$E$200="A")+($F$15:$F$200="A")+($G$15:$G$200="A")+($H$15:$H$200="A")+($I$15:$I$200="A")+($J$15:$J$200="A")+($K$15:$K$200="A")+($L$15:$L$200="A")+($M$15:$M$200="A"))) -> 0 | E8: =SUMPRODUCT(($B$15:$B$200="Liquidity Risk")*(($D$15:$D$200="R")+($E$15:$E$200="R")+($F$15:$F$200="R")+($G$15:$G$200="R")+($H$15:$H$200="R")+($I$15:$I$200="R")+($J$15:$J$200="R")+($K$15:$K$200="R")+($L$15:$L$200="R")+($M$15:$M$200="R"))) -> 0 | F8: =SUM(B8:E8) -> 16
A9: Counterparty / CCR | B9: =SUMPRODUCT(($B$15:$B$200="Counterparty / CCR")*(($D$15:$D$200="G")+($E$15:$E$200="G")+($F$15:$F$200="G")+($G$15:$G$200="G")+($H$15:$H$200="G")+($I$15:$I$200="G")+($J$15:$J$200="G")+($K$15:$K$200="G")+($L$15:$L$200="G")+($M$15:$M$200="G"))) -> 0 | C9: =SUMPRODUCT(($B$15:$B$200="Counterparty / CCR")*(($D$15:$D$200="AG")+($E$15:$E$200="AG")+($F$15:$F$200="AG")+($G$15:$G$200="AG")+($H$15:$H$200="AG")+($I$15:$I$200="AG")+($J$15:$J$200="AG")+($K$15:$K$200="AG")+($L$15:$L$200="AG")+($M$15:$M$200="AG"))) -> 0 | D9: =SUMPRODUCT(($B$15:$B$200="Counterparty / CCR")*(($D$15:$D$200="A")+($E$15:$E$200="A")+($F$15:$F$200="A")+($G$15:$G$200="A")+($H$15:$H$200="A")+($I$15:$I$200="A")+($J$15:$J$200="A")+($K$15:$K$200="A")+($L$15:$L$200="A")+($M$15:$M$200="A"))) -> 0 | E9: =SUMPRODUCT(($B$15:$B$200="Counterparty / CCR")*(($D$15:$D$200="R")+($E$15:$E$200="R")+($F$15:$F$200="R")+($G$15:$G$200="R")+($H$15:$H$200="R")+($I$15:$I$200="R")+($J$15:$J$200="R")+($K$15:$K$200="R")+($L$15:$L$200="R")+($M$15:$M$200="R"))) -> 0 | F9: =SUM(B9:E9) -> 0
A10: Sustainability | B10: =SUMPRODUCT(($B$15:$B$200="Sustainability")*(($D$15:$D$200="G")+($E$15:$E$200="G")+($F$15:$F$200="G")+($G$15:$G$200="G")+($H$15:$H$200="G")+($I$15:$I$200="G")+($J$15:$J$200="G")+($K$15:$K$200="G")+($L$15:$L$200="G")+($M$15:$M$200="G"))) -> 4 | C10: =SUMPRODUCT(($B$15:$B$200="Sustainability")*(($D$15:$D$200="AG")+($E$15:$E$200="AG")+($F$15:$F$200="AG")+($G$15:$G$200="AG")+($H$15:$H$200="AG")+($I$15:$I$200="AG")+($J$15:$J$200="AG")+($K$15:$K$200="AG")+($L$15:$L$200="AG")+($M$15:$M$200="AG"))) -> 0 | D10: =SUMPRODUCT(($B$15:$B$200="Sustainability")*(($D$15:$D$200="A")+($E$15:$E$200="A")+($F$15:$F$200="A")+($G$15:$G$200="A")+($H$15:$H$200="A")+($I$15:$I$200="A")+($J$15:$J$200="A")+($K$15:$K$200="A")+($L$15:$L$200="A")+($M$15:$M$200="A"))) -> 0 | E10: =SUMPRODUCT(($B$15:$B$200="Sustainability")*(($D$15:$D$200="R")+($E$15:$E$200="R")+($F$15:$F$200="R")+($G$15:$G$200="R")+($H$15:$H$200="R")+($I$15:$I$200="R")+($J$15:$J$200="R")+($K$15:$K$200="R")+($L$15:$L$200="R")+($M$15:$M$200="R"))) -> 0 | F10: =SUM(B10:E10) -> 4
A11: Performance | B11: =SUMPRODUCT(($B$15:$B$200="Performance")*(($D$15:$D$200="G")+($E$15:$E$200="G")+($F$15:$F$200="G")+($G$15:$G$200="G")+($H$15:$H$200="G")+($I$15:$I$200="G")+($J$15:$J$200="G")+($K$15:$K$200="G")+($L$15:$L$200="G")+($M$15:$M$200="G"))) -> 0 | C11: =SUMPRODUCT(($B$15:$B$200="Performance")*(($D$15:$D$200="AG")+($E$15:$E$200="AG")+($F$15:$F$200="AG")+($G$15:$G$200="AG")+($H$15:$H$200="AG")+($I$15:$I$200="AG")+($J$15:$J$200="AG")+($K$15:$K$200="AG")+($L$15:$L$200="AG")+($M$15:$M$200="AG"))) -> 0 | D11: =SUMPRODUCT(($B$15:$B$200="Performance")*(($D$15:$D$200="A")+($E$15:$E$200="A")+($F$15:$F$200="A")+($G$15:$G$200="A")+($H$15:$H$200="A")+($I$15:$I$200="A")+($J$15:$J$200="A")+($K$15:$K$200="A")+($L$15:$L$200="A")+($M$15:$M$200="A"))) -> 0 | E11: =SUMPRODUCT(($B$15:$B$200="Performance")*(($D$15:$D$200="R")+($E$15:$E$200="R")+($F$15:$F$200="R")+($G$15:$G$200="R")+($H$15:$H$200="R")+($I$15:$I$200="R")+($J$15:$J$200="R")+($K$15:$K$200="R")+($L$15:$L$200="R")+($M$15:$M$200="R"))) -> 0 | F11: =SUM(B11:E11) -> 0
A12: TOTAL | B12: =SUM(B7:B11) -> 36 | C12: =SUM(C7:C11) -> 0 | D12: =SUM(D7:D11) -> 2 | E12: =SUM(E7:E11) -> 2 | F12: =SUM(F7:F11) -> 40
A14: FUND-LEVEL MAT DATA · 8 funds · Enter G / AG / A / R per fund in each cell ▼
A15: MAT Metric | B15: Risk Type | C15: Trigger | D15: SGIDF | E15: GIDF | F15: GTIDF | G15: Red Hex | H15: INHK | I15: HSIC | J15: INSP | K15: AIA
A16: Watchlist (% Amber / any red) | B16: Market Risk | C16: >=20% | D16: G | E16: R | F16: G | G16: G | H16: R | I16: G | J16: G | K16: A
A17: Breach of any guidelines | B17: Market Risk | C17: >0 | D17: G | E17: A | F17: G | G17: G | H17: G | I17: G | J17: G | K17: G
A18: Utilisation of credit facility >80% | B18: Liquidity Risk | C18: >2wks | D18: G | E18: G | F18: G | G18: G
A19: Outside FX hedge ratio 98-102% | B19: Market Risk | C19: >2 days | D19: G | E19: G | F19: G | G19: G
A20: Liquidity test triggered | B20: Liquidity Risk | C20: Yes | D20: G | E20: G | F20: G | G20: G
A21: Downgrade to 'Weak' rating | B21: Liquidity Risk | D21: G | E21: G | F21: G | G21: G | H21: G | I21: G | J21: G | K21: G
A22: Sustainability | B22: Sustainability | D22: G | E22: G | F22: G | G22: G

Sheet RCF
A1: RCF · MAT Monitoring
A2: ▸ Update B3 = Reporting Period ▸ Update B4 = Number of Mandates ▸ Enter G / AG / A / R per fund in the coloured cells below (rows 15+) ▸ Strategy Summary (rows 7–12) and Dashboard auto-refresh via formulas
A3: Reporting Period | B3: Q3 2025
A4: Number of Mandates / Funds | B4: 2
A6: STRATEGY SUMMARY (auto-calculated from fund data below ▼) | B6: Green | C6: Amb-Grn | D6: Amber | E6: Red | F6: Total
A7: Market Risk | B7: =SUMPRODUCT(($B$15:$B$200="Market Risk")*(($D$15:$D$200="G")+($E$15:$E$200="G")+($F$15:$F$200="G")+($G$15:$G$200="G")+($H$15:$H$200="G")+($I$15:$I$200="G")+($J$15:$J$200="G")+($K$15:$K$200="G")+($L$15:$L$200="G")+($M$15:$M$200="G"))) -> 6 | C7: =SUMPRODUCT(($B$15:$B$200="Market Risk")*(($D$15:$D$200="AG")+($E$15:$E$200="AG")+($F$15:$F$200="AG")+($G$15:$G$200="AG")+($H$15:$H$200="AG")+($I$15:$I$200="AG")+($J$15:$J$200="AG")+($K$15:$K$200="AG")+($L$15:$L$200="AG")+($M$15:$M$200="AG"))) -> 0 | D7: =SUMPRODUCT(($B$15:$B$200="Market Risk")*(($D$15:$D$200="A")+($E$15:$E$200="A")+($F$15:$F$200="A")+($G$15:$G$200="A")+($H$15:$H$200="A")+($I$15:$I$200="A")+($J$15:$J$200="A")+($K$15:$K$200="A")+($L$15:$L$200="A")+($M$15:$M$200="A"))) -> 0 | E7: =SUMPRODUCT(($B$15:$B$200="Market Risk")*(($D$15:$D$200="R")+($E$15:$E$200="R")+($F$15:$F$200="R")+($G$15:$G$200="R")+($H$15:$H$200="R")+($I$15:$I$200="R")+($J$15:$J$200="R")+($K$15:$K$200="R")+($L$15:$L$200="R")+($M$15:$M$200="R"))) -> 0 | F7: =SUM(B7:E7) -> 6
A8: Liquidity Risk | B8: =SUMPRODUCT(($B$15:$B$200="Liquidity Risk")*(($D$15:$D$200="G")+($E$15:$E$200="G")+($F$15:$F$200="G")+($G$15:$G$200="G")+($H$15:$H$200="G")+($I$15:$I$200="G")+($J$15:$J$200="G")+($K$15:$K$200="G")+($L$15:$L$200="G")+($M$15:$M$200="G"))) -> 7 | C8: =SUMPRODUCT(($B$15:$B$200="Liquidity Risk")*(($D$15:$D$200="AG")+($E$15:$E$200="AG")+($F$15:$F$200="AG")+($G$15:$G$200="AG")+($H$15:$H$200="AG")+($I$15:$I$200="AG")+($J$15:$J$200="AG")+($K$15:$K$200="AG")+($L$15:$L$200="AG")+($M$15:$M$200="AG"))) -> 1 | D8: =SUMPRODUCT(($B$15:$B$200="Liquidity Risk")*(($D$15:$D$200="A")+($E$15:$E$200="A")+($F$15:$F$200="A")+($G$15:$G$200="A")+($H$15:$H$200="A")+($I$15:$I$200="A")+($J$15:$J$200="A")+($K$15:$K$200="A")+($L$15:$L$200="A")+($M$15:$M$200="A"))) -> 0 | E8: =SUMPRODUCT(($B$15:$B$200="Liquidity Risk")*(($D$15:$D$200="R")+($E$15:$E$200="R")+($F$15:$F$200="R")+($G$15:$G$200="R")+($H$15:$H$200="R")+($I$15:$I$200="R")+($J$15:$J$200="R")+($K$15:$K$200="R")+($L$15:$L$200="R")+($M$15:$M$200="R"))) -> 0 | F8: =SUM(B8:E8) -> 8
A9: Counterparty / CCR | B9: =SUMPRODUCT(($B$15:$B$200="Counterparty / CCR")*(($D$15:$D$200="G")+($E$15:$E$200="G")+($F$15:$F$200="G")+($G$15:$G$200="G")+($H$15:$H$200="G")+($I$15:$I$200="G")+($J$15:$J$200="G")+($K$15:$K$200="G")+($L$15:$L$200="G")+($M$15:$M$200="G"))) -> 0 | C9: =SUMPRODUCT(($B$15:$B$200="Counterparty / CCR")*(($D$15:$D$200="AG")+($E$15:$E$200="AG")+($F$15:$F$200="AG")+($G$15:$G$200="AG")+($H$15:$H$200="AG")+($I$15:$I$200="AG")+($J$15:$J$200="AG")+($K$15:$K$200="AG")+($L$15:$L$200="AG")+($M$15:$M$200="AG"))) -> 0 | D9: =SUMPRODUCT(($B$15:$B$200="Counterparty / CCR")*(($D$15:$D$200="A")+($E$15:$E$200="A")+($F$15:$F$200="A")+($G$15:$G$200="A")+($H$15:$H$200="A")+($I$15:$I$200="A")+($J$15:$J$200="A")+($K$15:$K$200="A")+($L$15:$L$200="A")+($M$15:$M$200="A"))) -> 0 | E9: =SUMPRODUCT(($B$15:$B$200="Counterparty / CCR")*(($D$15:$D$200="R")+($E$15:$E$200="R")+($F$15:$F$200="R")+($G$15:$G$200="R")+($H$15:$H$200="R")+($I$15:$I$200="R")+($J$15:$J$200="R")+($K$15:$K$200="R")+($L$15:$L$200="R")+($M$15:$M$200="R"))) -> 0 | F9: =SUM(B9:E9) -> 0
A10: Sustainability | B10: =SUMPRODUCT(($B$15:$B$200="Sustainability")*(($D$15:$D$200="G")+($E$15:$E$200="G")+($F$15:$F$200="G")+($G$15:$G$200="G")+($H$15:$H$200="G")+($I$15:$I$200="G")+($J$15:$J$200="G")+($K$15:$K$200="G")+($L$15:$L$200="G")+($M$15:$M$200="G"))) -> 2 | C10: =SUMPRODUCT(($B$15:$B$200="Sustainability")*(($D$15:$D$200="AG")+($E$15:$E$200="AG")+($F$15:$F$200="AG")+($G$15:$G$200="AG")+($H$15:$H$200="AG")+($I$15:$I$200="AG")+($J$15:$J$200="AG")+($K$15:$K$200="AG")+($L$15:$L$200="AG")+($M$15:$M$200="AG"))) -> 0 | D10: =SUMPRODUCT(($B$15:$B$200="Sustainability")*(($D$15:$D$200="A")+($E$15:$E$200="A")+($F$15:$F$200="A")+($G$15:$G$200="A")+($H$15:$H$200="A")+($I$15:$I$200="A")+($J$15:$J$200="A")+($K$15:$K$200="A")+($L$15:$L$200="A")+($M$15:$M$200="A"))) -> 0 | E10: =SUMPRODUCT(($B$15:$B$200="Sustainability")*(($D$15:$D$200="R")+($E$15:$E$200="R")+($F$15:$F$200="R")+($G$15:$G$200="R")+($H$15:$H$200="R")+($I$15:$I$200="R")+($J$15:$J$200="R")+($K$15:$K$200="R")+($L$15:$L$200="R")+($M$15:$M$200="R"))) -> 0 | F10: =SUM(B10:E10) -> 2
A11: Performance | B11: =SUMPRODUCT(($B$15:$B$200="Performance")*(($D$15:$D$200="G")+($E$15:$E$200="G")+($F$15:$F$200="G")+($G$15:$G$200="G")+($H$15:$H$200="G")+($I$15:$I$200="G")+($J$15:$J$200="G")+($K$15:$K$200="G")+($L$15:$L$200="G")+($M$15:$M$200="G"))) -> 0 | C11: =SUMPRODUCT(($B$15:$B$200="Performance")*(($D$15:$D$200="AG")+($E$15:$E$200="AG")+($F$15:$F$200="AG")+($G$15:$G$200="AG")+($H$15:$H$200="AG")+($I$15:$I$200="AG")+($J$15:$J$200="AG")+($K$15:$K$200="AG")+($L$15:$L$200="AG")+($M$15:$M$200="AG"))) -> 0 | D11: =SUMPRODUCT(($B$15:$B$200="Performance")*(($D$15:$D$200="A")+($E$15:$E$200="A")+($F$15:$F$200="A")+($G$15:$G$200="A")+($H$15:$H$200="A")+($I$15:$I$200="A")+($J$15:$J$200="A")+($K$15:$K$200="A")+($L$15:$L$200="A")+($M$15:$M$200="A"))) -> 0 | E11: =SUMPRODUCT(($B$15:$B$200="Performance")*(($D$15:$D$200="R")+($E$15:$E$200="R")+($F$15:$F$200="R")+($G$15:$G$200="R")+($H$15:$H$200="R")+($I$15:$I$200="R")+($J$15:$J$200="R")+($K$15:$K$200="R")+($L$15:$L$200="R")+($M$15:$M$200="R"))) -> 0 | F11: =SUM(B11:E11) -> 0
A12: TOTAL | B12: =SUM(B7:B11) -> 15 | C12: =SUM(C7:C11) -> 1 | D12: =SUM(D7:D11) -> 0 | E12: =SUM(E7:E11) -> 0 | F12: =SUM(F7:F11) -> 16
A14: FUND-LEVEL MAT DATA · 2 funds · Enter G / AG / A / R per fund in each cell ▼
A15: MAT Metric | B15: Risk Type | C15: Trigger | D15: RCF | E15: OMERS
A16: Watchlist (% Amber / any red) | B16: Market Risk | C16: >=20% | D16: G | E16: G
A17: Fund borrowings / credit lines | B17: Liquidity Risk | C17: >=50% | D17: G | E17: G
A18: Increase in RCF drawings 1wk | B18: Liquidity Risk | C18: >=10% | D18: G | E18: G
A19: Increase in RCF drawings 1mth | B19: Liquidity Risk | C19: >=35% | D19: G | E19: G
A20: SLF outstanding maturity | B20: Liquidity Risk | C20: <=6mths | D20: AG | E20: G
A21: Unhedged non-EUR exposure | B21: Market Risk | C21: >40% | D21: G | E21: G
A22: Downgrade to 'Weak' rating | B22: Market Risk | D22: G | E22: G
A23: Sustainability | B23: Sustainability | D23: G | E23: G

Sheet NAV
A1: NAV Financing · MAT Monitoring
A2: ▸ Update B3 = Reporting Period ▸ Update B4 = Number of Mandates ▸ Enter G / AG / A / R per fund in the coloured cells below (rows 15+) ▸ Strategy Summary (rows 7–12) and Dashboard auto-refresh via formulas
A3: Reporting Period | B3: Q4 2025
A4: Number of Mandates / Funds | B4: 2
A6: STRATEGY SUMMARY (auto-calculated from fund data below ▼) | B6: Green | C6: Amb-Grn | D6: Amber | E6: Red | F6: Total
A7: Market Risk | B7: =SUMPRODUCT(($B$15:$B$200="Market Risk")*(($D$15:$D$200="G")+($E$15:$E$200="G")+($F$15:$F$200="G")+($G$15:$G$200="G")+($H$15:$H$200="G")+($I$15:$I$200="G")+($J$15:$J$200="G")+($K$15:$K$200="G")+($L$15:$L$200="G")+($M$15:$M$200="G"))) -> 6 | C7: =SUMPRODUCT(($B$15:$B$200="Market Risk")*(($D$15:$D$200="AG")+($E$15:$E$200="AG")+($F$15:$F$200="AG")+($G$15:$G$200="AG")+($H$15:$H$200="AG")+($I$15:$I$200="AG")+($J$15:$J$200="AG")+($K$15:$K$200="AG")+($L$15:$L$200="AG")+($M$15:$M$200="AG"))) -> 0 | D7: =SUMPRODUCT(($B$15:$B$200="Market Risk")*(($D$15:$D$200="A")+($E$15:$E$200="A")+($F$15:$F$200="A")+($G$15:$G$200="A")+($H$15:$H$200="A")+($I$15:$I$200="A")+($J$15:$J$200="A")+($K$15:$K$200="A")+($L$15:$L$200="A")+($M$15:$M$200="A"))) -> 0 | E7: =SUMPRODUCT(($B$15:$B$200="Market Risk")*(($D$15:$D$200="R")+($E$15:$E$200="R")+($F$15:$F$200="R")+($G$15:$G$200="R")+($H$15:$H$200="R")+($I$15:$I$200="R")+($J$15:$J$200="R")+($K$15:$K$200="R")+($L$15:$L$200="R")+($M$15:$M$200="R"))) -> 0 | F7: =SUM(B7:E7) -> 6
A8: Liquidity Risk | B8: =SUMPRODUCT(($B$15:$B$200="Liquidity Risk")*(($D$15:$D$200="G")+($E$15:$E$200="G")+($F$15:$F$200="G")+($G$15:$G$200="G")+($H$15:$H$200="G")+($I$15:$I$200="G")+($J$15:$J$200="G")+($K$15:$K$200="G")+($L$15:$L$200="G")+($M$15:$M$200="G"))) -> 0 | C8: =SUMPRODUCT(($B$15:$B$200="Liquidity Risk")*(($D$15:$D$200="AG")+($E$15:$E$200="AG")+($F$15:$F$200="AG")+($G$15:$G$200="AG")+($H$15:$H$200="AG")+($I$15:$I$200="AG")+($J$15:$J$200="AG")+($K$15:$K$200="AG")+($L$15:$L$200="AG")+($M$15:$M$200="AG"))) -> 0 | D8: =SUMPRODUCT(($B$15:$B$200="Liquidity Risk")*(($D$15:$D$200="A")+($E$15:$E$200="A")+($F$15:$F$200="A")+($G$15:$G$200="A")+($H$15:$H$200="A")+($I$15:$I$200="A")+($J$15:$J$200="A")+($K$15:$K$200="A")+($L$15:$L$200="A")+($M$15:$M$200="A"))) -> 0 | E8: =SUMPRODUCT(($B$15:$B$200="Liquidity Risk")*(($D$15:$D$200="R")+($E$15:$E$200="R")+($F$15:$F$200="R")+($G$15:$G$200="R")+($H$15:$H$200="R")+($I$15:$I$200="R")+($J$15:$J$200="R")+($K$15:$K$200="R")+($L$15:$L$200="R")+($M$15:$M$200="R"))) -> 0 | F8: =SUM(B8:E8) -> 0
A9: Counterparty / CCR | B9: =SUMPRODUCT(($B$15:$B$200="Counterparty / CCR")*(($D$15:$D$200="G")+($E$15:$E$200="G")+($F$15:$F$200="G")+($G$15:$G$200="G")+($H$15:$H$200="G")+($I$15:$I$200="G")+($J$15:$J$200="G")+($K$15:$K$200="G")+($L$15:$L$200="G")+($M$15:$M$200="G"))) -> 0 | C9: =SUMPRODUCT(($B$15:$B$200="Counterparty / CCR")*(($D$15:$D$200="AG")+($E$15:$E$200="AG")+($F$15:$F$200="AG")+($G$15:$G$200="AG")+($H$15:$H$200="AG")+($I$15:$I$200="AG")+($J$15:$J$200="AG")+($K$15:$K$200="AG")+($L$15:$L$200="AG")+($M$15:$M$200="AG"))) -> 0 | D9: =SUMPRODUCT(($B$15:$B$200="Counterparty / CCR")*(($D$15:$D$200="A")+($E$15:$E$200="A")+($F$15:$F$200="A")+($G$15:$G$200="A")+($H$15:$H$200="A")+($I$15:$I$200="A")+($J$15:$J$200="A")+($K$15:$K$200="A")+($L$15:$L$200="A")+($M$15:$M$200="A"))) -> 0 | E9: =SUMPRODUCT(($B$15:$B$200="Counterparty / CCR")*(($D$15:$D$200="R")+($E$15:$E$200="R")+($F$15:$F$200="R")+($G$15:$G$200="R")+($H$15:$H$200="R")+($I$15:$I$200="R")+($J$15:$J$200="R")+($K$15:$K$200="R")+($L$15:$L$200="R")+($M$15:$M$200="R"))) -> 0 | F9: =SUM(B9:E9) -> 0
A10: Sustainability | B10: =SUMPRODUCT(($B$15:$B$200="Sustainability")*(($D$15:$D$200="G")+($E$15:$E$200="G")+($F$15:$F$200="G")+($G$15:$G$200="G")+($H$15:$H$200="G")+($I$15:$I$200="G")+($J$15:$J$200="G")+($K$15:$K$200="G")+($L$15:$L$200="G")+($M$15:$M$200="G"))) -> 2 | C10: =SUMPRODUCT(($B$15:$B$200="Sustainability")*(($D$15:$D$200="AG")+($E$15:$E$200="AG")+($F$15:$F$200="AG")+($G$15:$G$200="AG")+($H$15:$H$200="AG")+($I$15:$I$200="AG")+($J$15:$J$200="AG")+($K$15:$K$200="AG")+($L$15:$L$200="AG")+($M$15:$M$200="AG"))) -> 0 | D10: =SUMPRODUCT(($B$15:$B$200="Sustainability")*(($D$15:$D$200="A")+($E$15:$E$200="A")+($F$15:$F$200="A")+($G$15:$G$200="A")+($H$15:$H$200="A")+($I$15:$I$200="A")+($J$15:$J$200="A")+($K$15:$K$200="A")+($L$15:$L$200="A")+($M$15:$M$200="A"))) -> 0 | E10: =SUMPRODUCT(($B$15:$B$200="Sustainability")*(($D$15:$D$200="R")+($E$15:$E$200="R")+($F$15:$F$200="R")+($G$15:$G$200="R")+($H$15:$H$200="R")+($I$15:$I$200="R")+($J$15:$J$200="R")+($K$15:$K$200="R")+($L$15:$L$200="R")+($M$15:$M$200="R"))) -> 0 | F10: =SUM(B10:E10) -> 2
A11: Performance | B11: =SUMPRODUCT(($B$15:$B$200="Performance")*(($D$15:$D$200="G")+($E$15:$E$200="G")+($F$15:$F$200="G")+($G$15:$G$200="G")+($H$15:$H$200="G")+($I$15:$I$200="G")+($J$15:$J$200="G")+($K$15:$K$200="G")+($L$15:$L$200="G")+($M$15:$M$200="G"))) -> 0 | C11: =SUMPRODUCT(($B$15:$B$200="Performance")*(($D$15:$D$200="AG")+($E$15:$E$200="AG")+($F$15:$F$200="AG")+($G$15:$G$200="AG")+($H$15:$H$200="AG")+($I$15:$I$200="AG")+($J$15:$J$200="AG")+($K$15:$K$200="AG")+($L$15:$L$200="AG")+($M$15:$M$200="AG"))) -> 0 | D11: =SUMPRODUCT(($B$15:$B$200="Performance")*(($D$15:$D$200="A")+($E$15:$E$200="A")+($F$15:$F$200="A")+($G$15:$G$200="A")+($H$15:$H$200="A")+($I$15:$I$200="A")+($J$15:$J$200="A")+($K$15:$K$200="A")+($L$15:$L$200="A")+($M$15:$M$200="A"))) -> 0 | E11: =SUMPRODUCT(($B$15:$B$200="Performance")*(($D$15:$D$200="R")+($E$15:$E$200="R")+($F$15:$F$200="R")+($G$15:$G$200="R")+($H$15:$H$200="R")+($I$15:$I$200="R")+($J$15:$J$200="R")+($K$15:$K$200="R")+($L$15:$L$200="R")+($M$15:$M$200="R"))) -> 0 | F11: =SUM(B11:E11) -> 0
A12: TOTAL | B12: =SUM(B7:B11) -> 8 | C12: =SUM(C7:C11) -> 0 | D12: =SUM(D7:D11) -> 0 | E12: =SUM(E7:E11) -> 0 | F12: =SUM(F7:F11) -> 8
A14: FUND-LEVEL MAT DATA · 2 funds · Enter G / AG / A / R per fund in each cell ▼
A15: MAT Metric | B15: Risk Type | C15: Trigger | D15: NAV Fund | E15: AXA
A16: Watchlist (% Amber / any red) | B16: Market Risk | C16: >=20% | D16: G | E16: G
A17: SLF outstanding maturity | B17: Market Risk | C17: <=12mths | D17: G | E17: G
A18: Unhedged non-EUR exposure | B18: Market Risk | C18: >20% | D18: G | E18: G
A19: Sustainability | B19: Sustainability | D19: G | E19: G

Sheet TWCS
A1: Trade & Working Capital · MAT Monitoring
A2: ▸ Update B3 = Reporting Period ▸ Update B4 = Number of Mandates ▸ Enter G / AG / A / R per fund in the coloured cells below (rows 15+) ▸ Strategy Summary (rows 7–12) and Dashboard auto-refresh via formulas
A3: Reporting Period | B3: Q4 2025
A4: Number of Mandates / Funds | B4: 2
A6: STRATEGY SUMMARY (auto-calculated from fund data below ▼) | B6: Green | C6: Amb-Grn | D6: Amber | E6: Red | F6: Total
A7: Market Risk | B7: =SUMPRODUCT(($B$15:$B$200="Market Risk")*(($D$15:$D$200="G")+($E$15:$E$200="G")+($F$15:$F$200="G")+($G$15:$G$200="G")+($H$15:$H$200="G")+($I$15:$I$200="G")+($J$15:$J$200="G")+($K$15:$K$200="G")+($L$15:$L$200="G")+($M$15:$M$200="G"))) -> 10 | C7: =SUMPRODUCT(($B$15:$B$200="Market Risk")*(($D$15:$D$200="AG")+($E$15:$E$200="AG")+($F$15:$F$200="AG")+($G$15:$G$200="AG")+($H$15:$H$200="AG")+($I$15:$I$200="AG")+($J$15:$J$200="AG")+($K$15:$K$200="AG")+($L$15:$L$200="AG")+($M$15:$M$200="AG"))) -> 0 | D7: =SUMPRODUCT(($B$15:$B$200="Market Risk")*(($D$15:$D$200="A")+($E$15:$E$200="A")+($F$15:$F$200="A")+($G$15:$G$200="A")+($H$15:$H$200="A")+($I$15:$I$200="A")+($J$15:$J$200="A")+($K$15:$K$200="A")+($L$15:$L$200="A")+($M$15:$M$200="A"))) -> 0 | E7: =SUMPRODUCT(($B$15:$B$200="Market Risk")*(($D$15:$D$200="R")+($E$15:$E$200="R")+($F$15:$F$200="R")+($G$15:$G$200="R")+($H$15:$H$200="R")+($I$15:$I$200="R")+($J$15:$J$200="R")+($K$15:$K$200="R")+($L$15:$L$200="R")+($M$15:$M$200="R"))) -> 0 | F7: =SUM(B7:E7) -> 10
A8: Liquidity Risk | B8: =SUMPRODUCT(($B$15:$B$200="Liquidity Risk")*(($D$15:$D$200="G")+($E$15:$E$200="G")+($F$15:$F$200="G")+($G$15:$G$200="G")+($H$15:$H$200="G")+($I$15:$I$200="G")+($J$15:$J$200="G")+($K$15:$K$200="G")+($L$15:$L$200="G")+($M$15:$M$200="G"))) -> 0 | C8: =SUMPRODUCT(($B$15:$B$200="Liquidity Risk")*(($D$15:$D$200="AG")+($E$15:$E$200="AG")+($F$15:$F$200="AG")+($G$15:$G$200="AG")+($H$15:$H$200="AG")+($I$15:$I$200="AG")+($J$15:$J$200="AG")+($K$15:$K$200="AG")+($L$15:$L$200="AG")+($M$15:$M$200="AG"))) -> 0 | D8: =SUMPRODUCT(($B$15:$B$200="Liquidity Risk")*(($D$15:$D$200="A")+($E$15:$E$200="A")+($F$15:$F$200="A")+($G$15:$G$200="A")+($H$15:$H$200="A")+($I$15:$I$200="A")+($J$15:$J$200="A")+($K$15:$K$200="A")+($L$15:$L$200="A")+($M$15:$M$200="A"))) -> 0 | E8: =SUMPRODUCT(($B$15:$B$200="Liquidity Risk")*(($D$15:$D$200="R")+($E$15:$E$200="R")+($F$15:$F$200="R")+($G$15:$G$200="R")+($H$15:$H$200="R")+($I$15:$I$200="R")+($J$15:$J$200="R")+($K$15:$K$200="R")+($L$15:$L$200="R")+($M$15:$M$200="R"))) -> 0 | F8: =SUM(B8:E8) -> 0
A9: Counterparty / CCR | B9: =SUMPRODUCT(($B$15:$B$200="Counterparty / CCR")*(($D$15:$D$200="G")+($E$15:$E$200="G")+($F$15:$F$200="G")+($G$15:$G$200="G")+($H$15:$H$200="G")+($I$15:$I$200="G")+($J$15:$J$200="G")+($K$15:$K$200="G")+($L$15:$L$200="G")+($M$15:$M$200="G"))) -> 0 | C9: =SUMPRODUCT(($B$15:$B$200="Counterparty / CCR")*(($D$15:$D$200="AG")+($E$15:$E$200="AG")+($F$15:$F$200="AG")+($G$15:$G$200="AG")+($H$15:$H$200="AG")+($I$15:$I$200="AG")+($J$15:$J$200="AG")+($K$15:$K$200="AG")+($L$15:$L$200="AG")+($M$15:$M$200="AG"))) -> 0 | D9: =SUMPRODUCT(($B$15:$B$200="Counterparty / CCR")*(($D$15:$D$200="A")+($E$15:$E$200="A")+($F$15:$F$200="A")+($G$15:$G$200="A")+($H$15:$H$200="A")+($I$15:$I$200="A")+($J$15:$J$200="A")+($K$15:$K$200="A")+($L$15:$L$200="A")+($M$15:$M$200="A"))) -> 0 | E9: =SUMPRODUCT(($B$15:$B$200="Counterparty / CCR")*(($D$15:$D$200="R")+($E$15:$E$200="R")+($F$15:$F$200="R")+($G$15:$G$200="R")+($H$15:$H$200="R")+($I$15:$I$200="R")+($J$15:$J$200="R")+($K$15:$K$200="R")+($L$15:$L$200="R")+($M$15:$M$200="R"))) -> 0 | F9: =SUM(B9:E9) -> 0
A10: Sustainability | B10: =SUMPRODUCT(($B$15:$B$200="Sustainability")*(($D$15:$D$200="G")+($E$15:$E$200="G")+($F$15:$F$200="G")+($G$15:$G$200="G")+($H$15:$H$200="G")+($I$15:$I$200="G")+($J$15:$J$200="G")+($K$15:$K$200="G")+($L$15:$L$200="G")+($M$15:$M$200="G"))) -> 0 | C10: =SUMPRODUCT(($B$15:$B$200="Sustainability")*(($D$15:$D$200="AG")+($E$15:$E$200="AG")+($F$15:$F$200="AG")+($G$15:$G$200="AG")+($H$15:$H$200="AG")+($I$15:$I$200="AG")+($J$15:$J$200="AG")+($K$15:$K$200="AG")+($L$15:$L$200="AG")+($M$15:$M$200="AG"))) -> 0 | D10: =SUMPRODUCT(($B$15:$B$200="Sustainability")*(($D$15:$D$200="A")+($E$15:$E$200="A")+($F$15:$F$200="A")+($G$15:$G$200="A")+($H$15:$H$200="A")+($I$15:$I$200="A")+($J$15:$J$200="A")+($K$15:$K$200="A")+($L$15:$L$200="A")+($M$15:$M$200="A"))) -> 0 | E10: =SUMPRODUCT(($B$15:$B$200="Sustainability")*(($D$15:$D$200="R")+($E$15:$E$200="R")+($F$15:$F$200="R")+($G$15:$G$200="R")+($H$15:$H$200="R")+($I$15:$I$200="R")+($J$15:$J$200="R")+($K$15:$K$200="R")+($L$15:$L$200="R")+($M$15:$M$200="R"))) -> 0 | F10: =SUM(B10:E10) -> 0
A11: Performance | B11: =SUMPRODUCT(($B$15:$B$200="Performance")*(($D$15:$D$200="G")+($E$15:$E$200="G")+($F$15:$F$200="G")+($G$15:$G$200="G")+($H$15:$H$200="G")+($I$15:$I$200="G")+($J$15:$J$200="G")+($K$15:$K$200="G")+($L$15:$L$200="G")+($M$15:$M$200="G"))) -> 0 | C11: =SUMPRODUCT(($B$15:$B$200="Performance")*(($D$15:$D$200="AG")+($E$15:$E$200="AG")+($F$15:$F$200="AG")+($G$15:$G$200="AG")+($H$15:$H$200="AG")+($I$15:$I$200="AG")+($J$15:$J$200="AG")+($K$15:$K$200="AG")+($L$15:$L$200="AG")+($M$15:$M$200="AG"))) -> 0 | D11: =SUMPRODUCT(($B$15:$B$200="Performance")*(($D$15:$D$200="A")+($E$15:$E$200="A")+($F$15:$F$200="A")+($G$15:$G$200="A")+($H$15:$H$200="A")+($I$15:$I$200="A")+($J$15:$J$200="A")+($K$15:$K$200="A")+($L$15:$L$200="A")+($M$15:$M$200="A"))) -> 0 | E11: =SUMPRODUCT(($B$15:$B$200="Performance")*(($D$15:$D$200="R")+($E$15:$E$200="R")+($F$15:$F$200="R")+($G$15:$G$200="R")+($H$15:$H$200="R")+($I$15:$I$200="R")+($J$15:$J$200="R")+($K$15:$K$200="R")+($L$15:$L$200="R")+($M$15:$M$200="R"))) -> 0 | F11: =SUM(B11:E11) -> 0
A12: TOTAL | B12: =SUM(B7:B11) -> 10 | C12: =SUM(C7:C11) -> 0 | D12: =SUM(D7:D11) -> 0 | E12: =SUM(E7:E11) -> 0 | F12: =SUM(F7:F11) -> 10
A14: FUND-LEVEL MAT DATA · 2 funds · Enter G / AG / A / R per fund in each cell ▼
A15: MAT Metric | B15: Risk Type | C15: Trigger | D15: Note | E15: Fund
A16: Leverage | B16: Market Risk | C16: >5.0x | D16: G | E16: G
A17: Programme Utilisation | B17: Market Risk | C17: <50% | D17: G | E17: G
A18: Late payment rate | B18: Market Risk | C18: >2% | D18: G | E18: G
A19: Avg maturity of invoices increase | B19: Market Risk | C19: >2wks | D19: G | E19: G
A20: Portfolio concentration | B20: Market Risk | C20: >40m | D20: G | E20: G

Sheet HAIL RE
A1: HAIL Direct RE · MAT Monitoring
A2: ▸ Update B3 = Reporting Period ▸ Update B4 = Number of Mandates ▸ Enter G / AG / A / R per fund in the coloured cells below (rows 15+) ▸ Strategy Summary (rows 7–12) and Dashboard auto-refresh via formulas
A3: Reporting Period | B3: Q4 2025
A4: Number of Mandates / Funds | B4: 7
A6: STRATEGY SUMMARY (auto-calculated from fund data below ▼) | B6: Green | C6: Amb-Grn | D6: Amber | E6: Red | F6: Total
A7: Market Risk | B7: =SUMPRODUCT(($B$15:$B$200="Market Risk")*(($D$15:$D$200="G")+($E$15:$E$200="G")+($F$15:$F$200="G")+($G$15:$G$200="G")+($H$15:$H$200="G")+($I$15:$I$200="G")+($J$15:$J$200="G")+($K$15:$K$200="G")+($L$15:$L$200="G")+($M$15:$M$200="G"))) -> 23 | C7: =SUMPRODUCT(($B$15:$B$200="Market Risk")*(($D$15:$D$200="AG")+($E$15:$E$200="AG")+($F$15:$F$200="AG")+($G$15:$G$200="AG")+($H$15:$H$200="AG")+($I$15:$I$200="AG")+($J$15:$J$200="AG")+($K$15:$K$200="AG")+($L$15:$L$200="AG")+($M$15:$M$200="AG"))) -> 10 | D7: =SUMPRODUCT(($B$15:$B$200="Market Risk")*(($D$15:$D$200="A")+($E$15:$E$200="A")+($F$15:$F$200="A")+($G$15:$G$200="A")+($H$15:$H$200="A")+($I$15:$I$200="A")+($J$15:$J$200="A")+($K$15:$K$200="A")+($L$15:$L$200="A")+($M$15:$M$200="A"))) -> 0 | E7: =SUMPRODUCT(($B$15:$B$200="Market Risk")*(($D$15:$D$200="R")+($E$15:$E$200="R")+($F$15:$F$200="R")+($G$15:$G$200="R")+($H$15:$H$200="R")+($I$15:$I$200="R")+($J$15:$J$200="R")+($K$15:$K$200="R")+($L$15:$L$200="R")+($M$15:$M$200="R"))) -> 2 | F7: =SUM(B7:E7) -> 35
A8: Liquidity Risk | B8: =SUMPRODUCT(($B$15:$B$200="Liquidity Risk")*(($D$15:$D$200="G")+($E$15:$E$200="G")+($F$15:$F$200="G")+($G$15:$G$200="G")+($H$15:$H$200="G")+($I$15:$I$200="G")+($J$15:$J$200="G")+($K$15:$K$200="G")+($L$15:$L$200="G")+($M$15:$M$200="G"))) -> 0 | C8: =SUMPRODUCT(($B$15:$B$200="Liquidity Risk")*(($D$15:$D$200="AG")+($E$15:$E$200="AG")+($F$15:$F$200="AG")+($G$15:$G$200="AG")+($H$15:$H$200="AG")+($I$15:$I$200="AG")+($J$15:$J$200="AG")+($K$15:$K$200="AG")+($L$15:$L$200="AG")+($M$15:$M$200="AG"))) -> 0 | D8: =SUMPRODUCT(($B$15:$B$200="Liquidity Risk")*(($D$15:$D$200="A")+($E$15:$E$200="A")+($F$15:$F$200="A")+($G$15:$G$200="A")+($H$15:$H$200="A")+($I$15:$I$200="A")+($J$15:$J$200="A")+($K$15:$K$200="A")+($L$15:$L$200="A")+($M$15:$M$200="A"))) -> 0 | E8: =SUMPRODUCT(($B$15:$B$200="Liquidity Risk")*(($D$15:$D$200="R")+($E$15:$E$200="R")+($F$15:$F$200="R")+($G$15:$G$200="R")+($H$15:$H$200="R")+($I$15:$I$200="R")+($J$15:$J$200="R")+($K$15:$K$200="R")+($L$15:$L$200="R")+($M$15:$M$200="R"))) -> 0 | F8: =SUM(B8:E8) -> 0
A9: Counterparty / CCR | B9: =SUMPRODUCT(($B$15:$B$200="Counterparty / CCR")*(($D$15:$D$200="G")+($E$15:$E$200="G")+($F$15:$F$200="G")+($G$15:$G$200="G")+($H$15:$H$200="G")+($I$15:$I$200="G")+($J$15:$J$200="G")+($K$15:$K$200="G")+($L$15:$L$200="G")+($M$15:$M$200="G"))) -> 0 | C9: =SUMPRODUCT(($B$15:$B$200="Counterparty / CCR")*(($D$15:$D$200="AG")+($E$15:$E$200="AG")+($F$15:$F$200="AG")+($G$15:$G$200="AG")+($H$15:$H$200="AG")+($I$15:$I$200="AG")+($J$15:$J$200="AG")+($K$15:$K$200="AG")+($L$15:$L$200="AG")+($M$15:$M$200="AG"))) -> 0 | D9: =SUMPRODUCT(($B$15:$B$200="Counterparty / CCR")*(($D$15:$D$200="A")+($E$15:$E$200="A")+($F$15:$F$200="A")+($G$15:$G$200="A")+($H$15:$H$200="A")+($I$15:$I$200="A")+($J$15:$J$200="A")+($K$15:$K$200="A")+($L$15:$L$200="A")+($M$15:$M$200="A"))) -> 0 | E9: =SUMPRODUCT(($B$15:$B$200="Counterparty / CCR")*(($D$15:$D$200="R")+($E$15:$E$200="R")+($F$15:$F$200="R")+($G$15:$G$200="R")+($H$15:$H$200="R")+($I$15:$I$200="R")+($J$15:$J$200="R")+($K$15:$K$200="R")+($L$15:$L$200="R")+($M$15:$M$200="R"))) -> 0 | F9: =SUM(B9:E9) -> 0
A10: Sustainability | B10: =SUMPRODUCT(($B$15:$B$200="Sustainability")*(($D$15:$D$200="G")+($E$15:$E$200="G")+($F$15:$F$200="G")+($G$15:$G$200="G")+($H$15:$H$200="G")+($I$15:$I$200="G")+($J$15:$J$200="G")+($K$15:$K$200="G")+($L$15:$L$200="G")+($M$15:$M$200="G"))) -> 0 | C10: =SUMPRODUCT(($B$15:$B$200="Sustainability")*(($D$15:$D$200="AG")+($E$15:$E$200="AG")+($F$15:$F$200="AG")+($G$15:$G$200="AG")+($H$15:$H$200="AG")+($I$15:$I$200="AG")+($J$15:$J$200="AG")+($K$15:$K$200="AG")+($L$15:$L$200="AG")+($M$15:$M$200="AG"))) -> 0 | D10: =SUMPRODUCT(($B$15:$B$200="Sustainability")*(($D$15:$D$200="A")+($E$15:$E$200="A")+($F$15:$F$200="A")+($G$15:$G$200="A")+($H$15:$H$200="A")+($I$15:$I$200="A")+($J$15:$J$200="A")+($K$15:$K$200="A")+($L$15:$L$200="A")+($M$15:$M$200="A"))) -> 0 | E10: =SUMPRODUCT(($B$15:$B$200="Sustainability")*(($D$15:$D$200="R")+($E$15:$E$200="R")+($F$15:$F$200="R")+($G$15:$G$200="R")+($H$15:$H$200="R")+($I$15:$I$200="R")+($J$15:$J$200="R")+($K$15:$K$200="R")+($L$15:$L$200="R")+($M$15:$M$200="R"))) -> 0 | F10: =SUM(B10:E10) -> 0
A11: Performance | B11: =SUMPRODUCT(($B$15:$B$200="Performance")*(($D$15:$D$200="G")+($E$15:$E$200="G")+($F$15:$F$200="G")+($G$15:$G$200="G")+($H$15:$H$200="G")+($I$15:$I$200="G")+($J$15:$J$200="G")+($K$15:$K$200="G")+($L$15:$L$200="G")+($M$15:$M$200="G"))) -> 0 | C11: =SUMPRODUCT(($B$15:$B$200="Performance")*(($D$15:$D$200="AG")+($E$15:$E$200="AG")+($F$15:$F$200="AG")+($G$15:$G$200="AG")+($H$15:$H$200="AG")+($I$15:$I$200="AG")+($J$15:$J$200="AG")+($K$15:$K$200="AG")+($L$15:$L$200="AG")+($M$15:$M$200="AG"))) -> 0 | D11: =SUMPRODUCT(($B$15:$B$200="Performance")*(($D$15:$D$200="A")+($E$15:$E$200="A")+($F$15:$F$200="A")+($G$15:$G$200="A")+($H$15:$H$200="A")+($I$15:$I$200="A")+($J$15:$J$200="A")+($K$15:$K$200="A")+($L$15:$L$200="A")+($M$15:$M$200="A"))) -> 0 | E11: =SUMPRODUCT(($B$15:$B$200="Performance")*(($D$15:$D$200="R")+($E$15:$E$200="R")+($F$15:$F$200="R")+($G$15:$G$200="R")+($H$15:$H$200="R")+($I$15:$I$200="R")+($J$15:$J$200="R")+($K$15:$K$200="R")+($L$15:$L$200="R")+($M$15:$M$200="R"))) -> 0 | F11: =SUM(B11:E11) -> 0
A12: TOTAL | B12: =SUM(B7:B11) -> 23 | C12: =SUM(C7:C11) -> 10 | D12: =SUM(D7:D11) -> 0 | E12: =SUM(E7:E11) -> 2 | F12: =SUM(F7:F11) -> 35
A14: FUND-LEVEL MAT DATA · 7 funds · Enter G / AG / A / R per fund in each cell ▼
A15: MAT Metric | B15: Risk Type | C15: Trigger | D15: Downing | E15: Port H | F15: Stand LH | G15: Exch Pl | H15: Geneva | I15: Vienna | J15: Brussels
A16: Target Exit Date | B16: Market Risk | C16: <1yr | D16: AG | E16: G | F16: G | G16: G
A17: Debt Maturity | B17: Market Risk | C17: <1yr | D17: G | E17: G | F17: G | G17: G | H17: G
A18: Occupancy % | B18: Market Risk | C18: <=85% | D18: G | E18: R | F18: G | G18: AG | H18: G | I18: G | J18: R
A19: LTV vs covenant buffer | B19: Market Risk | C19: <10% under | D19: G | E19: G | F19: G | G19: AG | H19: AG | I19: G
A20: ICR vs covenant buffer | B20: Market Risk | C20: <25% over | D20: G | E20: G | F20: G | G20: G | H20: AG
A21: Equity Multiple | B21: Market Risk | C21: <=1.0x | D21: G | E21: AG | F21: AG | G21: AG
A22: Total Multiple | B22: Market Risk | C22: <=1.0x | D22: G | E22: G | F22: AG | G22: AG

Sheet HTRE RE
A1: HTRE RE · MAT Monitoring
A2: ▸ Update B3 = Reporting Period ▸ Update B4 = Number of Mandates ▸ Enter G / AG / A / R per fund in the coloured cells below (rows 15+) ▸ Strategy Summary (rows 7–12) and Dashboard auto-refresh via formulas
A3: Reporting Period | B3: Q3 2025
A4: Number of Mandates / Funds | B4: 6
A6: STRATEGY SUMMARY (auto-calculated from fund data below ▼) | B6: Green | C6: Amb-Grn | D6: Amber | E6: Red | F6: Total
A7: Market Risk | B7: =SUMPRODUCT(($B$15:$B$200="Market Risk")*(($D$15:$D$200="G")+($E$15:$E$200="G")+($F$15:$F$200="G")+($G$15:$G$200="G")+($H$15:$H$200="G")+($I$15:$I$200="G")+($J$15:$J$200="G")+($K$15:$K$200="G")+($L$15:$L$200="G")+($M$15:$M$200="G"))) -> 27 | C7: =SUMPRODUCT(($B$15:$B$200="Market Risk")*(($D$15:$D$200="AG")+($E$15:$E$200="AG")+($F$15:$F$200="AG")+($G$15:$G$200="AG")+($H$15:$H$200="AG")+($I$15:$I$200="AG")+($J$15:$J$200="AG")+($K$15:$K$200="AG")+($L$15:$L$200="AG")+($M$15:$M$200="AG"))) -> 1 | D7: =SUMPRODUCT(($B$15:$B$200="Market Risk")*(($D$15:$D$200="A")+($E$15:$E$200="A")+($F$15:$F$200="A")+($G$15:$G$200="A")+($H$15:$H$200="A")+($I$15:$I$200="A")+($J$15:$J$200="A")+($K$15:$K$200="A")+($L$15:$L$200="A")+($M$15:$M$200="A"))) -> 1 | E7: =SUMPRODUCT(($B$15:$B$200="Market Risk")*(($D$15:$D$200="R")+($E$15:$E$200="R")+($F$15:$F$200="R")+($G$15:$G$200="R")+($H$15:$H$200="R")+($I$15:$I$200="R")+($J$15:$J$200="R")+($K$15:$K$200="R")+($L$15:$L$200="R")+($M$15:$M$200="R"))) -> 1 | F7: =SUM(B7:E7) -> 30
A8: Liquidity Risk | B8: =SUMPRODUCT(($B$15:$B$200="Liquidity Risk")*(($D$15:$D$200="G")+($E$15:$E$200="G")+($F$15:$F$200="G")+($G$15:$G$200="G")+($H$15:$H$200="G")+($I$15:$I$200="G")+($J$15:$J$200="G")+($K$15:$K$200="G")+($L$15:$L$200="G")+($M$15:$M$200="G"))) -> 0 | C8: =SUMPRODUCT(($B$15:$B$200="Liquidity Risk")*(($D$15:$D$200="AG")+($E$15:$E$200="AG")+($F$15:$F$200="AG")+($G$15:$G$200="AG")+($H$15:$H$200="AG")+($I$15:$I$200="AG")+($J$15:$J$200="AG")+($K$15:$K$200="AG")+($L$15:$L$200="AG")+($M$15:$M$200="AG"))) -> 0 | D8: =SUMPRODUCT(($B$15:$B$200="Liquidity Risk")*(($D$15:$D$200="A")+($E$15:$E$200="A")+($F$15:$F$200="A")+($G$15:$G$200="A")+($H$15:$H$200="A")+($I$15:$I$200="A")+($J$15:$J$200="A")+($K$15:$K$200="A")+($L$15:$L$200="A")+($M$15:$M$200="A"))) -> 0 | E8: =SUMPRODUCT(($B$15:$B$200="Liquidity Risk")*(($D$15:$D$200="R")+($E$15:$E$200="R")+($F$15:$F$200="R")+($G$15:$G$200="R")+($H$15:$H$200="R")+($I$15:$I$200="R")+($J$15:$J$200="R")+($K$15:$K$200="R")+($L$15:$L$200="R")+($M$15:$M$200="R"))) -> 0 | F8: =SUM(B8:E8) -> 0
A9: Counterparty / CCR | B9: =SUMPRODUCT(($B$15:$B$200="Counterparty / CCR")*(($D$15:$D$200="G")+($E$15:$E$200="G")+($F$15:$F$200="G")+($G$15:$G$200="G")+($H$15:$H$200="G")+($I$15:$I$200="G")+($J$15:$J$200="G")+($K$15:$K$200="G")+($L$15:$L$200="G")+($M$15:$M$200="G"))) -> 0 | C9: =SUMPRODUCT(($B$15:$B$200="Counterparty / CCR")*(($D$15:$D$200="AG")+($E$15:$E$200="AG")+($F$15:$F$200="AG")+($G$15:$G$200="AG")+($H$15:$H$200="AG")+($I$15:$I$200="AG")+($J$15:$J$200="AG")+($K$15:$K$200="AG")+($L$15:$L$200="AG")+($M$15:$M$200="AG"))) -> 0 | D9: =SUMPRODUCT(($B$15:$B$200="Counterparty / CCR")*(($D$15:$D$200="A")+($E$15:$E$200="A")+($F$15:$F$200="A")+($G$15:$G$200="A")+($H$15:$H$200="A")+($I$15:$I$200="A")+($J$15:$J$200="A")+($K$15:$K$200="A")+($L$15:$L$200="A")+($M$15:$M$200="A"))) -> 0 | E9: =SUMPRODUCT(($B$15:$B$200="Counterparty / CCR")*(($D$15:$D$200="R")+($E$15:$E$200="R")+($F$15:$F$200="R")+($G$15:$G$200="R")+($H$15:$H$200="R")+($I$15:$I$200="R")+($J$15:$J$200="R")+($K$15:$K$200="R")+($L$15:$L$200="R")+($M$15:$M$200="R"))) -> 0 | F9: =SUM(B9:E9) -> 0
A10: Sustainability | B10: =SUMPRODUCT(($B$15:$B$200="Sustainability")*(($D$15:$D$200="G")+($E$15:$E$200="G")+($F$15:$F$200="G")+($G$15:$G$200="G")+($H$15:$H$200="G")+($I$15:$I$200="G")+($J$15:$J$200="G")+($K$15:$K$200="G")+($L$15:$L$200="G")+($M$15:$M$200="G"))) -> 6 | C10: =SUMPRODUCT(($B$15:$B$200="Sustainability")*(($D$15:$D$200="AG")+($E$15:$E$200="AG")+($F$15:$F$200="AG")+($G$15:$G$200="AG")+($H$15:$H$200="AG")+($I$15:$I$200="AG")+($J$15:$J$200="AG")+($K$15:$K$200="AG")+($L$15:$L$200="AG")+($M$15:$M$200="AG"))) -> 0 | D10: =SUMPRODUCT(($B$15:$B$200="Sustainability")*(($D$15:$D$200="A")+($E$15:$E$200="A")+($F$15:$F$200="A")+($G$15:$G$200="A")+($H$15:$H$200="A")+($I$15:$I$200="A")+($J$15:$J$200="A")+($K$15:$K$200="A")+($L$15:$L$200="A")+($M$15:$M$200="A"))) -> 0 | E10: =SUMPRODUCT(($B$15:$B$200="Sustainability")*(($D$15:$D$200="R")+($E$15:$E$200="R")+($F$15:$F$200="R")+($G$15:$G$200="R")+($H$15:$H$200="R")+($I$15:$I$200="R")+($J$15:$J$200="R")+($K$15:$K$200="R")+($L$15:$L$200="R")+($M$15:$M$200="R"))) -> 0 | F10: =SUM(B10:E10) -> 6
A11: Performance | B11: =SUMPRODUCT(($B$15:$B$200="Performance")*(($D$15:$D$200="G")+($E$15:$E$200="G")+($F$15:$F$200="G")+($G$15:$G$200="G")+($H$15:$H$200="G")+($I$15:$I$200="G")+($J$15:$J$200="G")+($K$15:$K$200="G")+($L$15:$L$200="G")+($M$15:$M$200="G"))) -> 0 | C11: =SUMPRODUCT(($B$15:$B$200="Performance")*(($D$15:$D$200="AG")+($E$15:$E$200="AG")+($F$15:$F$200="AG")+($G$15:$G$200="AG")+($H$15:$H$200="AG")+($I$15:$I$200="AG")+($J$15:$J$200="AG")+($K$15:$K$200="AG")+($L$15:$L$200="AG")+($M$15:$M$200="AG"))) -> 0 | D11: =SUMPRODUCT(($B$15:$B$200="Performance")*(($D$15:$D$200="A")+($E$15:$E$200="A")+($F$15:$F$200="A")+($G$15:$G$200="A")+($H$15:$H$200="A")+($I$15:$I$200="A")+($J$15:$J$200="A")+($K$15:$K$200="A")+($L$15:$L$200="A")+($M$15:$M$200="A"))) -> 0 | E11: =SUMPRODUCT(($B$15:$B$200="Performance")*(($D$15:$D$200="R")+($E$15:$E$200="R")+($F$15:$F$200="R")+($G$15:$G$200="R")+($H$15:$H$200="R")+($I$15:$I$200="R")+($J$15:$J$200="R")+($K$15:$K$200="R")+($L$15:$L$200="R")+($M$15:$M$200="R"))) -> 0 | F11: =SUM(B11:E11) -> 0
A12: TOTAL | B12: =SUM(B7:B11) -> 33 | C12: =SUM(C7:C11) -> 1 | D12: =SUM(D7:D11) -> 1 | E12: =SUM(E7:E11) -> 1 | F12: =SUM(F7:F11) -> 36
A14: FUND-LEVEL MAT DATA · 6 funds · Enter G / AG / A / R per fund in each cell ▼
A15: MAT Metric | B15: Risk Type | C15: Trigger | D15: Fonds 3 | E15: Fonds 6 | F15: Fonds 7 | G15: Fonds 8 | H15: Fonds 11 | I15: Fonds 12
A16: Occupancy % | B16: Market Risk | C16: <90% | D16: G | E16: G | F16: G | G16: G | H16: G | I16: G
A17: Distribution in % | B17: Market Risk | C17: <2.9% | D17: G | E17: G | F17: AG | G17: G | H17: G | I17: G
A18: LTV % | B18: Market Risk | C18: >=50% | D18: G | E18: G | F18: R | G18: A | H18: G | I18: G
A19: Selling option | B19: Market Risk | C19: No | D19: G | E19: G | F19: G | G19: G | H19: G | I19: G
A20: Audit (without reservation) | B20: Market Risk | C20: No | D20: G | E20: G | F20: G | G20: G | H20: G | I20: G
A21: Sustainability | B21: Sustainability | D21: G | E21: G | F21: G | G21: G | H21: G | I21: G

Sheet RE Asia
A1: Real Estate Asia · MAT Monitoring
A2: ▸ Update B3 = Reporting Period ▸ Update B4 = Number of Mandates ▸ Enter G / AG / A / R per fund in the coloured cells below (rows 15+) ▸ Strategy Summary (rows 7–12) and Dashboard auto-refresh via formulas
A3: Reporting Period | B3: Q3 2025
A4: Number of Mandates / Funds | B4: 5
A6: STRATEGY SUMMARY (auto-calculated from fund data below ▼) | B6: Green | C6: Amb-Grn | D6: Amber | E6: Red | F6: Total
A7: Market Risk | B7: =SUMPRODUCT(($B$15:$B$200="Market Risk")*(($D$15:$D$200="G")+($E$15:$E$200="G")+($F$15:$F$200="G")+($G$15:$G$200="G")+($H$15:$H$200="G")+($I$15:$I$200="G")+($J$15:$J$200="G")+($K$15:$K$200="G")+($L$15:$L$200="G")+($M$15:$M$200="G"))) -> 11 | C7: =SUMPRODUCT(($B$15:$B$200="Market Risk")*(($D$15:$D$200="AG")+($E$15:$E$200="AG")+($F$15:$F$200="AG")+($G$15:$G$200="AG")+($H$15:$H$200="AG")+($I$15:$I$200="AG")+($J$15:$J$200="AG")+($K$15:$K$200="AG")+($L$15:$L$200="AG")+($M$15:$M$200="AG"))) -> 2 | D7: =SUMPRODUCT(($B$15:$B$200="Market Risk")*(($D$15:$D$200="A")+($E$15:$E$200="A")+($F$15:$F$200="A")+($G$15:$G$200="A")+($H$15:$H$200="A")+($I$15:$I$200="A")+($J$15:$J$200="A")+($K$15:$K$200="A")+($L$15:$L$200="A")+($M$15:$M$200="A"))) -> 1 | E7: =SUMPRODUCT(($B$15:$B$200="Market Risk")*(($D$15:$D$200="R")+($E$15:$E$200="R")+($F$15:$F$200="R")+($G$15:$G$200="R")+($H$15:$H$200="R")+($I$15:$I$200="R")+($J$15:$J$200="R")+($K$15:$K$200="R")+($L$15:$L$200="R")+($M$15:$M$200="R"))) -> 1 | F7: =SUM(B7:E7) -> 15
A8: Liquidity Risk | B8: =SUMPRODUCT(($B$15:$B$200="Liquidity Risk")*(($D$15:$D$200="G")+($E$15:$E$200="G")+($F$15:$F$200="G")+($G$15:$G$200="G")+($H$15:$H$200="G")+($I$15:$I$200="G")+($J$15:$J$200="G")+($K$15:$K$200="G")+($L$15:$L$200="G")+($M$15:$M$200="G"))) -> 5 | C8: =SUMPRODUCT(($B$15:$B$200="Liquidity Risk")*(($D$15:$D$200="AG")+($E$15:$E$200="AG")+($F$15:$F$200="AG")+($G$15:$G$200="AG")+($H$15:$H$200="AG")+($I$15:$I$200="AG")+($J$15:$J$200="AG")+($K$15:$K$200="AG")+($L$15:$L$200="AG")+($M$15:$M$200="AG"))) -> 0 | D8: =SUMPRODUCT(($B$15:$B$200="Liquidity Risk")*(($D$15:$D$200="A")+($E$15:$E$200="A")+($F$15:$F$200="A")+($G$15:$G$200="A")+($H$15:$H$200="A")+($I$15:$I$200="A")+($J$15:$J$200="A")+($K$15:$K$200="A")+($L$15:$L$200="A")+($M$15:$M$200="A"))) -> 0 | E8: =SUMPRODUCT(($B$15:$B$200="Liquidity Risk")*(($D$15:$D$200="R")+($E$15:$E$200="R")+($F$15:$F$200="R")+($G$15:$G$200="R")+($H$15:$H$200="R")+($I$15:$I$200="R")+($J$15:$J$200="R")+($K$15:$K$200="R")+($L$15:$L$200="R")+($M$15:$M$200="R"))) -> 0 | F8: =SUM(B8:E8) -> 5
A9: Counterparty / CCR | B9: =SUMPRODUCT(($B$15:$B$200="Counterparty / CCR")*(($D$15:$D$200="G")+($E$15:$E$200="G")+($F$15:$F$200="G")+($G$15:$G$200="G")+($H$15:$H$200="G")+($I$15:$I$200="G")+($J$15:$J$200="G")+($K$15:$K$200="G")+($L$15:$L$200="G")+($M$15:$M$200="G"))) -> 5 | C9: =SUMPRODUCT(($B$15:$B$200="Counterparty / CCR")*(($D$15:$D$200="AG")+($E$15:$E$200="AG")+($F$15:$F$200="AG")+($G$15:$G$200="AG")+($H$15:$H$200="AG")+($I$15:$I$200="AG")+($J$15:$J$200="AG")+($K$15:$K$200="AG")+($L$15:$L$200="AG")+($M$15:$M$200="AG"))) -> 0 | D9: =SUMPRODUCT(($B$15:$B$200="Counterparty / CCR")*(($D$15:$D$200="A")+($E$15:$E$200="A")+($F$15:$F$200="A")+($G$15:$G$200="A")+($H$15:$H$200="A")+($I$15:$I$200="A")+($J$15:$J$200="A")+($K$15:$K$200="A")+($L$15:$L$200="A")+($M$15:$M$200="A"))) -> 0 | E9: =SUMPRODUCT(($B$15:$B$200="Counterparty / CCR")*(($D$15:$D$200="R")+($E$15:$E$200="R")+($F$15:$F$200="R")+($G$15:$G$200="R")+($H$15:$H$200="R")+($I$15:$I$200="R")+($J$15:$J$200="R")+($K$15:$K$200="R")+($L$15:$L$200="R")+($M$15:$M$200="R"))) -> 0 | F9: =SUM(B9:E9) -> 5
A10: Sustainability | B10: =SUMPRODUCT(($B$15:$B$200="Sustainability")*(($D$15:$D$200="G")+($E$15:$E$200="G")+($F$15:$F$200="G")+($G$15:$G$200="G")+($H$15:$H$200="G")+($I$15:$I$200="G")+($J$15:$J$200="G")+($K$15:$K$200="G")+($L$15:$L$200="G")+($M$15:$M$200="G"))) -> 3 | C10: =SUMPRODUCT(($B$15:$B$200="Sustainability")*(($D$15:$D$200="AG")+($E$15:$E$200="AG")+($F$15:$F$200="AG")+($G$15:$G$200="AG")+($H$15:$H$200="AG")+($I$15:$I$200="AG")+($J$15:$J$200="AG")+($K$15:$K$200="AG")+($L$15:$L$200="AG")+($M$15:$M$200="AG"))) -> 2 | D10: =SUMPRODUCT(($B$15:$B$200="Sustainability")*(($D$15:$D$200="A")+($E$15:$E$200="A")+($F$15:$F$200="A")+($G$15:$G$200="A")+($H$15:$H$200="A")+($I$15:$I$200="A")+($J$15:$J$200="A")+($K$15:$K$200="A")+($L$15:$L$200="A")+($M$15:$M$200="A"))) -> 0 | E10: =SUMPRODUCT(($B$15:$B$200="Sustainability")*(($D$15:$D$200="R")+($E$15:$E$200="R")+($F$15:$F$200="R")+($G$15:$G$200="R")+($H$15:$H$200="R")+($I$15:$I$200="R")+($J$15:$J$200="R")+($K$15:$K$200="R")+($L$15:$L$200="R")+($M$15:$M$200="R"))) -> 0 | F10: =SUM(B10:E10) -> 5
A11: Performance | B11: =SUMPRODUCT(($B$15:$B$200="Performance")*(($D$15:$D$200="G")+($E$15:$E$200="G")+($F$15:$F$200="G")+($G$15:$G$200="G")+($H$15:$H$200="G")+($I$15:$I$200="G")+($J$15:$J$200="G")+($K$15:$K$200="G")+($L$15:$L$200="G")+($M$15:$M$200="G"))) -> 0 | C11: =SUMPRODUCT(($B$15:$B$200="Performance")*(($D$15:$D$200="AG")+($E$15:$E$200="AG")+($F$15:$F$200="AG")+($G$15:$G$200="AG")+($H$15:$H$200="AG")+($I$15:$I$200="AG")+($J$15:$J$200="AG")+($K$15:$K$200="AG")+($L$15:$L$200="AG")+($M$15:$M$200="AG"))) -> 0 | D11: =SUMPRODUCT(($B$15:$B$200="Performance")*(($D$15:$D$200="A")+($E$15:$E$200="A")+($F$15:$F$200="A")+($G$15:$G$200="A")+($H$15:$H$200="A")+($I$15:$I$200="A")+($J$15:$J$200="A")+($K$15:$K$200="A")+($L$15:$L$200="A")+($M$15:$M$200="A"))) -> 0 | E11: =SUMPRODUCT(($B$15:$B$200="Performance")*(($D$15:$D$200="R")+($E$15:$E$200="R")+($F$15:$F$200="R")+($G$15:$G$200="R")+($H$15:$H$200="R")+($I$15:$I$200="R")+($J$15:$J$200="R")+($K$15:$K$200="R")+($L$15:$L$200="R")+($M$15:$M$200="R"))) -> 0 | F11: =SUM(B11:E11) -> 0
A12: TOTAL | B12: =SUM(B7:B11) -> 24 | C12: =SUM(C7:C11) -> 4 | D12: =SUM(D7:D11) -> 1 | E12: =SUM(E7:E11) -> 1 | F12: =SUM(F7:F11) -> 30
A14: FUND-LEVEL MAT DATA · 5 funds · Enter G / AG / A / R per fund in each cell ▼
A15: MAT Metric | B15: Risk Type | C15: Trigger | D15: Fund 1 | E15: Fund 2 | F15: Fund 3 | G15: Fund 4 | H15: Fund 5
A16: Market MAT 1 | B16: Market Risk | D16: G | E16: G | F16: G | G16: AG | H16: G
A17: Market MAT 2 | B17: Market Risk | D17: G | E17: AG | F17: G | G17: G | H17: G
A18: Market MAT 3 | B18: Market Risk | D18: G | E18: G | F18: A | G18: G | H18: R
A19: Liquidity (Closed End) | B19: Liquidity Risk | D19: G | E19: G | F19: G | G19: G | H19: G
A20: Counterparty exposure | B20: Counterparty / CCR | D20: G | E20: G | F20: G | G20: G | H20: G
A21: Sustainability | B21: Sustainability | D21: G | E21: AG | F21: G | G21: AG | H21: G

Sheet REIM
A1: REIM · MAT Monitoring
A2: ▸ Update B3 = Reporting Period ▸ Update B4 = Number of Mandates ▸ Enter G / AG / A / R per fund in the coloured cells below (rows 15+) ▸ Strategy Summary (rows 7–12) and Dashboard auto-refresh via formulas
A3: Reporting Period | B3: Q3 2025
A4: Number of Mandates / Funds | B4: 3
A6: STRATEGY SUMMARY (auto-calculated from fund data below ▼) | B6: Green | C6: Amb-Grn | D6: Amber | E6: Red | F6: Total
A7: Market Risk | B7: =SUMPRODUCT(($B$15:$B$200="Market Risk")*(($D$15:$D$200="G")+($E$15:$E$200="G")+($F$15:$F$200="G")+($G$15:$G$200="G")+($H$15:$H$200="G")+($I$15:$I$200="G")+($J$15:$J$200="G")+($K$15:$K$200="G")+($L$15:$L$200="G")+($M$15:$M$200="G"))) -> 7 | C7: =SUMPRODUCT(($B$15:$B$200="Market Risk")*(($D$15:$D$200="AG")+($E$15:$E$200="AG")+($F$15:$F$200="AG")+($G$15:$G$200="AG")+($H$15:$H$200="AG")+($I$15:$I$200="AG")+($J$15:$J$200="AG")+($K$15:$K$200="AG")+($L$15:$L$200="AG")+($M$15:$M$200="AG"))) -> 1 | D7: =SUMPRODUCT(($B$15:$B$200="Market Risk")*(($D$15:$D$200="A")+($E$15:$E$200="A")+($F$15:$F$200="A")+($G$15:$G$200="A")+($H$15:$H$200="A")+($I$15:$I$200="A")+($J$15:$J$200="A")+($K$15:$K$200="A")+($L$15:$L$200="A")+($M$15:$M$200="A"))) -> 1 | E7: =SUMPRODUCT(($B$15:$B$200="Market Risk")*(($D$15:$D$200="R")+($E$15:$E$200="R")+($F$15:$F$200="R")+($G$15:$G$200="R")+($H$15:$H$200="R")+($I$15:$I$200="R")+($J$15:$J$200="R")+($K$15:$K$200="R")+($L$15:$L$200="R")+($M$15:$M$200="R"))) -> 0 | F7: =SUM(B7:E7) -> 9
A8: Liquidity Risk | B8: =SUMPRODUCT(($B$15:$B$200="Liquidity Risk")*(($D$15:$D$200="G")+($E$15:$E$200="G")+($F$15:$F$200="G")+($G$15:$G$200="G")+($H$15:$H$200="G")+($I$15:$I$200="G")+($J$15:$J$200="G")+($K$15:$K$200="G")+($L$15:$L$200="G")+($M$15:$M$200="G"))) -> 2 | C8: =SUMPRODUCT(($B$15:$B$200="Liquidity Risk")*(($D$15:$D$200="AG")+($E$15:$E$200="AG")+($F$15:$F$200="AG")+($G$15:$G$200="AG")+($H$15:$H$200="AG")+($I$15:$I$200="AG")+($J$15:$J$200="AG")+($K$15:$K$200="AG")+($L$15:$L$200="AG")+($M$15:$M$200="AG"))) -> 0 | D8: =SUMPRODUCT(($B$15:$B$200="Liquidity Risk")*(($D$15:$D$200="A")+($E$15:$E$200="A")+($F$15:$F$200="A")+($G$15:$G$200="A")+($H$15:$H$200="A")+($I$15:$I$200="A")+($J$15:$J$200="A")+($K$15:$K$200="A")+($L$15:$L$200="A")+($M$15:$M$200="A"))) -> 1 | E8: =SUMPRODUCT(($B$15:$B$200="Liquidity Risk")*(($D$15:$D$200="R")+($E$15:$E$200="R")+($F$15:$F$200="R")+($G$15:$G$200="R")+($H$15:$H$200="R")+($I$15:$I$200="R")+($J$15:$J$200="R")+($K$15:$K$200="R")+($L$15:$L$200="R")+($M$15:$M$200="R"))) -> 0 | F8: =SUM(B8:E8) -> 3
A9: Counterparty / CCR | B9: =SUMPRODUCT(($B$15:$B$200="Counterparty / CCR")*(($D$15:$D$200="G")+($E$15:$E$200="G")+($F$15:$F$200="G")+($G$15:$G$200="G")+($H$15:$H$200="G")+($I$15:$I$200="G")+($J$15:$J$200="G")+($K$15:$K$200="G")+($L$15:$L$200="G")+($M$15:$M$200="G"))) -> 3 | C9: =SUMPRODUCT(($B$15:$B$200="Counterparty / CCR")*(($D$15:$D$200="AG")+($E$15:$E$200="AG")+($F$15:$F$200="AG")+($G$15:$G$200="AG")+($H$15:$H$200="AG")+($I$15:$I$200="AG")+($J$15:$J$200="AG")+($K$15:$K$200="AG")+($L$15:$L$200="AG")+($M$15:$M$200="AG"))) -> 0 | D9: =SUMPRODUCT(($B$15:$B$200="Counterparty / CCR")*(($D$15:$D$200="A")+($E$15:$E$200="A")+($F$15:$F$200="A")+($G$15:$G$200="A")+($H$15:$H$200="A")+($I$15:$I$200="A")+($J$15:$J$200="A")+($K$15:$K$200="A")+($L$15:$L$200="A")+($M$15:$M$200="A"))) -> 0 | E9: =SUMPRODUCT(($B$15:$B$200="Counterparty / CCR")*(($D$15:$D$200="R")+($E$15:$E$200="R")+($F$15:$F$200="R")+($G$15:$G$200="R")+($H$15:$H$200="R")+($I$15:$I$200="R")+($J$15:$J$200="R")+($K$15:$K$200="R")+($L$15:$L$200="R")+($M$15:$M$200="R"))) -> 0 | F9: =SUM(B9:E9) -> 3
A10: Sustainability | B10: =SUMPRODUCT(($B$15:$B$200="Sustainability")*(($D$15:$D$200="G")+($E$15:$E$200="G")+($F$15:$F$200="G")+($G$15:$G$200="G")+($H$15:$H$200="G")+($I$15:$I$200="G")+($J$15:$J$200="G")+($K$15:$K$200="G")+($L$15:$L$200="G")+($M$15:$M$200="G"))) -> 3 | C10: =SUMPRODUCT(($B$15:$B$200="Sustainability")*(($D$15:$D$200="AG")+($E$15:$E$200="AG")+($F$15:$F$200="AG")+($G$15:$G$200="AG")+($H$15:$H$200="AG")+($I$15:$I$200="AG")+($J$15:$J$200="AG")+($K$15:$K$200="AG")+($L$15:$L$200="AG")+($M$15:$M$200="AG"))) -> 0 | D10: =SUMPRODUCT(($B$15:$B$200="Sustainability")*(($D$15:$D$200="A")+($E$15:$E$200="A")+($F$15:$F$200="A")+($G$15:$G$200="A")+($H$15:$H$200="A")+($I$15:$I$200="A")+($J$15:$J$200="A")+($K$15:$K$200="A")+($L$15:$L$200="A")+($M$15:$M$200="A"))) -> 0 | E10: =SUMPRODUCT(($B$15:$B$200="Sustainability")*(($D$15:$D$200="R")+($E$15:$E$200="R")+($F$15:$F$200="R")+($G$15:$G$200="R")+($H$15:$H$200="R")+($I$15:$I$200="R")+($J$15:$J$200="R")+($K$15:$K$200="R")+($L$15:$L$200="R")+($M$15:$M$200="R"))) -> 0 | F10: =SUM(B10:E10) -> 3
A11: Performance | B11: =SUMPRODUCT(($B$15:$B$200="Performance")*(($D$15:$D$200="G")+($E$15:$E$200="G")+($F$15:$F$200="G")+($G$15:$G$200="G")+($H$15:$H$200="G")+($I$15:$I$200="G")+($J$15:$J$200="G")+($K$15:$K$200="G")+($L$15:$L$200="G")+($M$15:$M$200="G"))) -> 0 | C11: =SUMPRODUCT(($B$15:$B$200="Performance")*(($D$15:$D$200="AG")+($E$15:$E$200="AG")+($F$15:$F$200="AG")+($G$15:$G$200="AG")+($H$15:$H$200="AG")+($I$15:$I$200="AG")+($J$15:$J$200="AG")+($K$15:$K$200="AG")+($L$15:$L$200="AG")+($M$15:$M$200="AG"))) -> 0 | D11: =SUMPRODUCT(($B$15:$B$200="Performance")*(($D$15:$D$200="A")+($E$15:$E$200="A")+($F$15:$F$200="A")+($G$15:$G$200="A")+($H$15:$H$200="A")+($I$15:$I$200="A")+($J$15:$J$200="A")+($K$15:$K$200="A")+($L$15:$L$200="A")+($M$15:$M$200="A"))) -> 0 | E11: =SUMPRODUCT(($B$15:$B$200="Performance")*(($D$15:$D$200="R")+($E$15:$E$200="R")+($F$15:$F$200="R")+($G$15:$G$200="R")+($H$15:$H$200="R")+($I$15:$I$200="R")+($J$15:$J$200="R")+($K$15:$K$200="R")+($L$15:$L$200="R")+($M$15:$M$200="R"))) -> 0 | F11: =SUM(B11:E11) -> 0
A12: TOTAL | B12: =SUM(B7:B11) -> 15 | C12: =SUM(C7:C11) -> 1 | D12: =SUM(D7:D11) -> 2 | E12: =SUM(E7:E11) -> 0 | F12: =SUM(F7:F11) -> 18
A14: FUND-LEVEL MAT DATA · 3 funds · Enter G / AG / A / R per fund in each cell ▼
A15: MAT Metric | B15: Risk Type | C15: Trigger | D15: Fund A | E15: Fund B | F15: Fund C
A16: Market MAT 1 | B16: Market Risk | D16: G | E16: G | F16: G
A17: Market MAT 2 | B17: Market Risk | D17: G | E17: AG | F17: G
A18: Market MAT 3 | B18: Market Risk | D18: G | E18: G | F18: A
A19: Liquidity (Open End) | B19: Liquidity Risk | D19: G | E19: G | F19: A
A20: Counterparty exposure | B20: Counterparty / CCR | D20: G | E20: G | F20: G
A21: Sustainability | B21: Sustainability | D21: G | E21: G | F21: G

Sheet ETI
A1: ETI · MAT Monitoring
A2: ▸ Update B3 = Reporting Period ▸ Update B4 = Number of Mandates ▸ Enter G / AG / A / R per fund in the coloured cells below (rows 15+) ▸ Strategy Summary (rows 7–12) and Dashboard auto-refresh via formulas
A3: Reporting Period | B3: Q3 2025
A4: Number of Mandates / Funds | B4: 1
A6: STRATEGY SUMMARY (auto-calculated from fund data below ▼) | B6: Green | C6: Amb-Grn | D6: Amber | E6: Red | F6: Total
A7: Market Risk | B7: =SUMPRODUCT(($B$15:$B$200="Market Risk")*(($D$15:$D$200="G")+($E$15:$E$200="G")+($F$15:$F$200="G")+($G$15:$G$200="G")+($H$15:$H$200="G")+($I$15:$I$200="G")+($J$15:$J$200="G")+($K$15:$K$200="G")+($L$15:$L$200="G")+($M$15:$M$200="G"))) -> 5 | C7: =SUMPRODUCT(($B$15:$B$200="Market Risk")*(($D$15:$D$200="AG")+($E$15:$E$200="AG")+($F$15:$F$200="AG")+($G$15:$G$200="AG")+($H$15:$H$200="AG")+($I$15:$I$200="AG")+($J$15:$J$200="AG")+($K$15:$K$200="AG")+($L$15:$L$200="AG")+($M$15:$M$200="AG"))) -> 0 | D7: =SUMPRODUCT(($B$15:$B$200="Market Risk")*(($D$15:$D$200="A")+($E$15:$E$200="A")+($F$15:$F$200="A")+($G$15:$G$200="A")+($H$15:$H$200="A")+($I$15:$I$200="A")+($J$15:$J$200="A")+($K$15:$K$200="A")+($L$15:$L$200="A")+($M$15:$M$200="A"))) -> 0 | E7: =SUMPRODUCT(($B$15:$B$200="Market Risk")*(($D$15:$D$200="R")+($E$15:$E$200="R")+($F$15:$F$200="R")+($G$15:$G$200="R")+($H$15:$H$200="R")+($I$15:$I$200="R")+($J$15:$J$200="R")+($K$15:$K$200="R")+($L$15:$L$200="R")+($M$15:$M$200="R"))) -> 1 | F7: =SUM(B7:E7) -> 6
A8: Liquidity Risk | B8: =SUMPRODUCT(($B$15:$B$200="Liquidity Risk")*(($D$15:$D$200="G")+($E$15:$E$200="G")+($F$15:$F$200="G")+($G$15:$G$200="G")+($H$15:$H$200="G")+($I$15:$I$200="G")+($J$15:$J$200="G")+($K$15:$K$200="G")+($L$15:$L$200="G")+($M$15:$M$200="G"))) -> 0 | C8: =SUMPRODUCT(($B$15:$B$200="Liquidity Risk")*(($D$15:$D$200="AG")+($E$15:$E$200="AG")+($F$15:$F$200="AG")+($G$15:$G$200="AG")+($H$15:$H$200="AG")+($I$15:$I$200="AG")+($J$15:$J$200="AG")+($K$15:$K$200="AG")+($L$15:$L$200="AG")+($M$15:$M$200="AG"))) -> 0 | D8: =SUMPRODUCT(($B$15:$B$200="Liquidity Risk")*(($D$15:$D$200="A")+($E$15:$E$200="A")+($F$15:$F$200="A")+($G$15:$G$200="A")+($H$15:$H$200="A")+($I$15:$I$200="A")+($J$15:$J$200="A")+($K$15:$K$200="A")+($L$15:$L$200="A")+($M$15:$M$200="A"))) -> 0 | E8: =SUMPRODUCT(($B$15:$B$200="Liquidity Risk")*(($D$15:$D$200="R")+($E$15:$E$200="R")+($F$15:$F$200="R")+($G$15:$G$200="R")+($H$15:$H$200="R")+($I$15:$I$200="R")+($J$15:$J$200="R")+($K$15:$K$200="R")+($L$15:$L$200="R")+($M$15:$M$200="R"))) -> 0 | F8: =SUM(B8:E8) -> 0
A9: Counterparty / CCR | B9: =SUMPRODUCT(($B$15:$B$200="Counterparty / CCR")*(($D$15:$D$200="G")+($E$15:$E$200="G")+($F$15:$F$200="G")+($G$15:$G$200="G")+($H$15:$H$200="G")+($I$15:$I$200="G")+($J$15:$J$200="G")+($K$15:$K$200="G")+($L$15:$L$200="G")+($M$15:$M$200="G"))) -> 2 | C9: =SUMPRODUCT(($B$15:$B$200="Counterparty / CCR")*(($D$15:$D$200="AG")+($E$15:$E$200="AG")+($F$15:$F$200="AG")+($G$15:$G$200="AG")+($H$15:$H$200="AG")+($I$15:$I$200="AG")+($J$15:$J$200="AG")+($K$15:$K$200="AG")+($L$15:$L$200="AG")+($M$15:$M$200="AG"))) -> 0 | D9: =SUMPRODUCT(($B$15:$B$200="Counterparty / CCR")*(($D$15:$D$200="A")+($E$15:$E$200="A")+($F$15:$F$200="A")+($G$15:$G$200="A")+($H$15:$H$200="A")+($I$15:$I$200="A")+($J$15:$J$200="A")+($K$15:$K$200="A")+($L$15:$L$200="A")+($M$15:$M$200="A"))) -> 0 | E9: =SUMPRODUCT(($B$15:$B$200="Counterparty / CCR")*(($D$15:$D$200="R")+($E$15:$E$200="R")+($F$15:$F$200="R")+($G$15:$G$200="R")+($H$15:$H$200="R")+($I$15:$I$200="R")+($J$15:$J$200="R")+($K$15:$K$200="R")+($L$15:$L$200="R")+($M$15:$M$200="R"))) -> 0 | F9: =SUM(B9:E9) -> 2
A10: Sustainability | B10: =SUMPRODUCT(($B$15:$B$200="Sustainability")*(($D$15:$D$200="G")+($E$15:$E$200="G")+($F$15:$F$200="G")+($G$15:$G$200="G")+($H$15:$H$200="G")+($I$15:$I$200="G")+($J$15:$J$200="G")+($K$15:$K$200="G")+($L$15:$L$200="G")+($M$15:$M$200="G"))) -> 2 | C10: =SUMPRODUCT(($B$15:$B$200="Sustainability")*(($D$15:$D$200="AG")+($E$15:$E$200="AG")+($F$15:$F$200="AG")+($G$15:$G$200="AG")+($H$15:$H$200="AG")+($I$15:$I$200="AG")+($J$15:$J$200="AG")+($K$15:$K$200="AG")+($L$15:$L$200="AG")+($M$15:$M$200="AG"))) -> 0 | D10: =SUMPRODUCT(($B$15:$B$200="Sustainability")*(($D$15:$D$200="A")+($E$15:$E$200="A")+($F$15:$F$200="A")+($G$15:$G$200="A")+($H$15:$H$200="A")+($I$15:$I$200="A")+($J$15:$J$200="A")+($K$15:$K$200="A")+($L$15:$L$200="A")+($M$15:$M$200="A"))) -> 0 | E10: =SUMPRODUCT(($B$15:$B$200="Sustainability")*(($D$15:$D$200="R")+($E$15:$E$200="R")+($F$15:$F$200="R")+($G$15:$G$200="R")+($H$15:$H$200="R")+($I$15:$I$200="R")+($J$15:$J$200="R")+($K$15:$K$200="R")+($L$15:$L$200="R")+($M$15:$M$200="R"))) -> 0 | F10: =SUM(B10:E10) -> 2
A11: Performance | B11: =SUMPRODUCT(($B$15:$B$200="Performance")*(($D$15:$D$200="G")+($E$15:$E$200="G")+($F$15:$F$200="G")+($G$15:$G$200="G")+($H$15:$H$200="G")+($I$15:$I$200="G")+($J$15:$J$200="G")+($K$15:$K$200="G")+($L$15:$L$200="G")+($M$15:$M$200="G"))) -> 0 | C11: =SUMPRODUCT(($B$15:$B$200="Performance")*(($D$15:$D$200="AG")+($E$15:$E$200="AG")+($F$15:$F$200="AG")+($G$15:$G$200="AG")+($H$15:$H$200="AG")+($I$15:$I$200="AG")+($J$15:$J$200="AG")+($K$15:$K$200="AG")+($L$15:$L$200="AG")+($M$15:$M$200="AG"))) -> 0 | D11: =SUMPRODUCT(($B$15:$B$200="Performance")*(($D$15:$D$200="A")+($E$15:$E$200="A")+($F$15:$F$200="A")+($G$15:$G$200="A")+($H$15:$H$200="A")+($I$15:$I$200="A")+($J$15:$J$200="A")+($K$15:$K$200="A")+($L$15:$L$200="A")+($M$15:$M$200="A"))) -> 0 | E11: =SUMPRODUCT(($B$15:$B$200="Performance")*(($D$15:$D$200="R")+($E$15:$E$200="R")+($F$15:$F$200="R")+($G$15:$G$200="R")+($H$15:$H$200="R")+($I$15:$I$200="R")+($J$15:$J$200="R")+($K$15:$K$200="R")+($L$15:$L$200="R")+($M$15:$M$200="R"))) -> 0 | F11: =SUM(B11:E11) -> 0
A12: TOTAL | B12: =SUM(B7:B11) -> 9 | C12: =SUM(C7:C11) -> 0 | D12: =SUM(D7:D11) -> 0 | E12: =SUM(E7:E11) -> 1 | F12: =SUM(F7:F11) -> 10
A14: FUND-LEVEL MAT DATA · 2 funds · Enter G / AG / A / R per fund in each cell ▼
A15: MAT Metric | B15: Risk Type | C15: Trigger | D15: Q2 2025 | E15: Q3 2025
A16: Performance – Fund level (lower threshold) | B16: Market Risk | C16: 5% | D16: R | E16: G
A17: Credit facility usage (upper threshold) | B17: Market Risk | C17: 20% | D17: G | E17: G
A18: Capital Deployment (lower threshold) | B18: Market Risk | C18: 50% | D18: G | E18: G
A19: Counterparty / Credit exposure | B19: Counterparty / CCR | D19: G | E19: G
A20: ESG / SIFfA – investment level | B20: Sustainability | C20: Fail | D20: G | E20: G

Sheet HF
A1: Hedge Funds · MAT Monitoring
A2: ▸ Update B3 = Reporting Period ▸ Update B4 = Number of Mandates ▸ Enter G / AG / A / R per fund in the coloured cells below (rows 15+) ▸ Strategy Summary (rows 7–12) and Dashboard auto-refresh via formulas
A3: Reporting Period | B3: Q3 2025
A4: Number of Mandates / Funds | B4: 5
A6: STRATEGY SUMMARY (auto-calculated from fund data below ▼) | B6: Green | C6: Amb-Grn | D6: Amber | E6: Red | F6: Total
A7: Market Risk | B7: =SUMPRODUCT(($B$15:$B$200="Market Risk")*(($D$15:$D$200="G")+($E$15:$E$200="G")+($F$15:$F$200="G")+($G$15:$G$200="G")+($H$15:$H$200="G")+($I$15:$I$200="G")+($J$15:$J$200="G")+($K$15:$K$200="G")+($L$15:$L$200="G")+($M$15:$M$200="G"))) -> 9 | C7: =SUMPRODUCT(($B$15:$B$200="Market Risk")*(($D$15:$D$200="AG")+($E$15:$E$200="AG")+($F$15:$F$200="AG")+($G$15:$G$200="AG")+($H$15:$H$200="AG")+($I$15:$I$200="AG")+($J$15:$J$200="AG")+($K$15:$K$200="AG")+($L$15:$L$200="AG")+($M$15:$M$200="AG"))) -> 0 | D7: =SUMPRODUCT(($B$15:$B$200="Market Risk")*(($D$15:$D$200="A")+($E$15:$E$200="A")+($F$15:$F$200="A")+($G$15:$G$200="A")+($H$15:$H$200="A")+($I$15:$I$200="A")+($J$15:$J$200="A")+($K$15:$K$200="A")+($L$15:$L$200="A")+($M$15:$M$200="A"))) -> 0 | E7: =SUMPRODUCT(($B$15:$B$200="Market Risk")*(($D$15:$D$200="R")+($E$15:$E$200="R")+($F$15:$F$200="R")+($G$15:$G$200="R")+($H$15:$H$200="R")+($I$15:$I$200="R")+($J$15:$J$200="R")+($K$15:$K$200="R")+($L$15:$L$200="R")+($M$15:$M$200="R"))) -> 1 | F7: =SUM(B7:E7) -> 10
A8: Liquidity Risk | B8: =SUMPRODUCT(($B$15:$B$200="Liquidity Risk")*(($D$15:$D$200="G")+($E$15:$E$200="G")+($F$15:$F$200="G")+($G$15:$G$200="G")+($H$15:$H$200="G")+($I$15:$I$200="G")+($J$15:$J$200="G")+($K$15:$K$200="G")+($L$15:$L$200="G")+($M$15:$M$200="G"))) -> 5 | C8: =SUMPRODUCT(($B$15:$B$200="Liquidity Risk")*(($D$15:$D$200="AG")+($E$15:$E$200="AG")+($F$15:$F$200="AG")+($G$15:$G$200="AG")+($H$15:$H$200="AG")+($I$15:$I$200="AG")+($J$15:$J$200="AG")+($K$15:$K$200="AG")+($L$15:$L$200="AG")+($M$15:$M$200="AG"))) -> 0 | D8: =SUMPRODUCT(($B$15:$B$200="Liquidity Risk")*(($D$15:$D$200="A")+($E$15:$E$200="A")+($F$15:$F$200="A")+($G$15:$G$200="A")+($H$15:$H$200="A")+($I$15:$I$200="A")+($J$15:$J$200="A")+($K$15:$K$200="A")+($L$15:$L$200="A")+($M$15:$M$200="A"))) -> 0 | E8: =SUMPRODUCT(($B$15:$B$200="Liquidity Risk")*(($D$15:$D$200="R")+($E$15:$E$200="R")+($F$15:$F$200="R")+($G$15:$G$200="R")+($H$15:$H$200="R")+($I$15:$I$200="R")+($J$15:$J$200="R")+($K$15:$K$200="R")+($L$15:$L$200="R")+($M$15:$M$200="R"))) -> 0 | F8: =SUM(B8:E8) -> 5
A9: Counterparty / CCR | B9: =SUMPRODUCT(($B$15:$B$200="Counterparty / CCR")*(($D$15:$D$200="G")+($E$15:$E$200="G")+($F$15:$F$200="G")+($G$15:$G$200="G")+($H$15:$H$200="G")+($I$15:$I$200="G")+($J$15:$J$200="G")+($K$15:$K$200="G")+($L$15:$L$200="G")+($M$15:$M$200="G"))) -> 5 | C9: =SUMPRODUCT(($B$15:$B$200="Counterparty / CCR")*(($D$15:$D$200="AG")+($E$15:$E$200="AG")+($F$15:$F$200="AG")+($G$15:$G$200="AG")+($H$15:$H$200="AG")+($I$15:$I$200="AG")+($J$15:$J$200="AG")+($K$15:$K$200="AG")+($L$15:$L$200="AG")+($M$15:$M$200="AG"))) -> 0 | D9: =SUMPRODUCT(($B$15:$B$200="Counterparty / CCR")*(($D$15:$D$200="A")+($E$15:$E$200="A")+($F$15:$F$200="A")+($G$15:$G$200="A")+($H$15:$H$200="A")+($I$15:$I$200="A")+($J$15:$J$200="A")+($K$15:$K$200="A")+($L$15:$L$200="A")+($M$15:$M$200="A"))) -> 0 | E9: =SUMPRODUCT(($B$15:$B$200="Counterparty / CCR")*(($D$15:$D$200="R")+($E$15:$E$200="R")+($F$15:$F$200="R")+($G$15:$G$200="R")+($H$15:$H$200="R")+($I$15:$I$200="R")+($J$15:$J$200="R")+($K$15:$K$200="R")+($L$15:$L$200="R")+($M$15:$M$200="R"))) -> 0 | F9: =SUM(B9:E9) -> 5
A10: Sustainability | B10: =SUMPRODUCT(($B$15:$B$200="Sustainability")*(($D$15:$D$200="G")+($E$15:$E$200="G")+($F$15:$F$200="G")+($G$15:$G$200="G")+($H$15:$H$200="G")+($I$15:$I$200="G")+($J$15:$J$200="G")+($K$15:$K$200="G")+($L$15:$L$200="G")+($M$15:$M$200="G"))) -> 0 | C10: =SUMPRODUCT(($B$15:$B$200="Sustainability")*(($D$15:$D$200="AG")+($E$15:$E$200="AG")+($F$15:$F$200="AG")+($G$15:$G$200="AG")+($H$15:$H$200="AG")+($I$15:$I$200="AG")+($J$15:$J$200="AG")+($K$15:$K$200="AG")+($L$15:$L$200="AG")+($M$15:$M$200="AG"))) -> 0 | D10: =SUMPRODUCT(($B$15:$B$200="Sustainability")*(($D$15:$D$200="A")+($E$15:$E$200="A")+($F$15:$F$200="A")+($G$15:$G$200="A")+($H$15:$H$200="A")+($I$15:$I$200="A")+($J$15:$J$200="A")+($K$15:$K$200="A")+($L$15:$L$200="A")+($M$15:$M$200="A"))) -> 0 | E10: =SUMPRODUCT(($B$15:$B$200="Sustainability")*(($D$15:$D$200="R")+($E$15:$E$200="R")+($F$15:$F$200="R")+($G$15:$G$200="R")+($H$15:$H$200="R")+($I$15:$I$200="R")+($J$15:$J$200="R")+($K$15:$K$200="R")+($L$15:$L$200="R")+($M$15:$M$200="R"))) -> 0 | F10: =SUM(B10:E10) -> 0
A11: Performance | B11: =SUMPRODUCT(($B$15:$B$200="Performance")*(($D$15:$D$200="G")+($E$15:$E$200="G")+($F$15:$F$200="G")+($G$15:$G$200="G")+($H$15:$H$200="G")+($I$15:$I$200="G")+($J$15:$J$200="G")+($K$15:$K$200="G")+($L$15:$L$200="G")+($M$15:$M$200="G"))) -> 0 | C11: =SUMPRODUCT(($B$15:$B$200="Performance")*(($D$15:$D$200="AG")+($E$15:$E$200="AG")+($F$15:$F$200="AG")+($G$15:$G$200="AG")+($H$15:$H$200="AG")+($I$15:$I$200="AG")+($J$15:$J$200="AG")+($K$15:$K$200="AG")+($L$15:$L$200="AG")+($M$15:$M$200="AG"))) -> 0 | D11: =SUMPRODUCT(($B$15:$B$200="Performance")*(($D$15:$D$200="A")+($E$15:$E$200="A")+($F$15:$F$200="A")+($G$15:$G$200="A")+($H$15:$H$200="A")+($I$15:$I$200="A")+($J$15:$J$200="A")+($K$15:$K$200="A")+($L$15:$L$200="A")+($M$15:$M$200="A"))) -> 0 | E11: =SUMPRODUCT(($B$15:$B$200="Performance")*(($D$15:$D$200="R")+($E$15:$E$200="R")+($F$15:$F$200="R")+($G$15:$G$200="R")+($H$15:$H$200="R")+($I$15:$I$200="R")+($J$15:$J$200="R")+($K$15:$K$200="R")+($L$15:$L$200="R")+($M$15:$M$200="R"))) -> 0 | F11: =SUM(B11:E11) -> 0
A12: TOTAL | B12: =SUM(B7:B11) -> 19 | C12: =SUM(C7:C11) -> 0 | D12: =SUM(D7:D11) -> 0 | E12: =SUM(E7:E11) -> 1 | F12: =SUM(F7:F11) -> 20
A14: FUND-LEVEL MAT DATA · 5 funds · Enter G / AG / A / R per fund in each cell ▼
A15: MAT Metric | B15: Risk Type | C15: Trigger | D15: GH | E15: Alpha Core | F15: Orbit | G15: UCITS ADV | H15: GH Lux
A16: Volatility (min/max band) | B16: Market Risk | C16: Min/Max | D16: G | E16: G | F16: G | G16: R | H16: G
A17: VaR breach | B17: Market Risk | C17: >limit | D17: G | E17: G | F17: G | G17: G | H17: G
A18: Liquidity risk | B18: Liquidity Risk | D18: G | E18: G | F18: G | G18: G | H18: G
A19: Counterparty exposure | B19: Counterparty / CCR | D19: G | E19: G | F19: G | G19: G | H19: G

Sheet PrivMkts
A1: Private Markets · MAT Monitoring
A2: ▸ Update B3 = Reporting Period ▸ Update B4 = Number of Mandates ▸ Enter G / AG / A / R per fund in the coloured cells below (rows 15+) ▸ Strategy Summary (rows 7–12) and Dashboard auto-refresh via formulas
A3: Reporting Period | B3: Q3 2025
A4: Number of Mandates / Funds | B4: 7
A6: STRATEGY SUMMARY (auto-calculated from fund data below ▼) | B6: Green | C6: Amb-Grn | D6: Amber | E6: Red | F6: Total
A7: Market Risk | B7: =SUMPRODUCT(($B$15:$B$200="Market Risk")*(($D$15:$D$200="G")+($E$15:$E$200="G")+($F$15:$F$200="G")+($G$15:$G$200="G")+($H$15:$H$200="G")+($I$15:$I$200="G")+($J$15:$J$200="G")+($K$15:$K$200="G")+($L$15:$L$200="G")+($M$15:$M$200="G"))) -> 27 | C7: =SUMPRODUCT(($B$15:$B$200="Market Risk")*(($D$15:$D$200="AG")+($E$15:$E$200="AG")+($F$15:$F$200="AG")+($G$15:$G$200="AG")+($H$15:$H$200="AG")+($I$15:$I$200="AG")+($J$15:$J$200="AG")+($K$15:$K$200="AG")+($L$15:$L$200="AG")+($M$15:$M$200="AG"))) -> 1 | D7: =SUMPRODUCT(($B$15:$B$200="Market Risk")*(($D$15:$D$200="A")+($E$15:$E$200="A")+($F$15:$F$200="A")+($G$15:$G$200="A")+($H$15:$H$200="A")+($I$15:$I$200="A")+($J$15:$J$200="A")+($K$15:$K$200="A")+($L$15:$L$200="A")+($M$15:$M$200="A"))) -> 0 | E7: =SUMPRODUCT(($B$15:$B$200="Market Risk")*(($D$15:$D$200="R")+($E$15:$E$200="R")+($F$15:$F$200="R")+($G$15:$G$200="R")+($H$15:$H$200="R")+($I$15:$I$200="R")+($J$15:$J$200="R")+($K$15:$K$200="R")+($L$15:$L$200="R")+($M$15:$M$200="R"))) -> 0 | F7: =SUM(B7:E7) -> 28
A8: Liquidity Risk | B8: =SUMPRODUCT(($B$15:$B$200="Liquidity Risk")*(($D$15:$D$200="G")+($E$15:$E$200="G")+($F$15:$F$200="G")+($G$15:$G$200="G")+($H$15:$H$200="G")+($I$15:$I$200="G")+($J$15:$J$200="G")+($K$15:$K$200="G")+($L$15:$L$200="G")+($M$15:$M$200="G"))) -> 7 | C8: =SUMPRODUCT(($B$15:$B$200="Liquidity Risk")*(($D$15:$D$200="AG")+($E$15:$E$200="AG")+($F$15:$F$200="AG")+($G$15:$G$200="AG")+($H$15:$H$200="AG")+($I$15:$I$200="AG")+($J$15:$J$200="AG")+($K$15:$K$200="AG")+($L$15:$L$200="AG")+($M$15:$M$200="AG"))) -> 0 | D8: =SUMPRODUCT(($B$15:$B$200="Liquidity Risk")*(($D$15:$D$200="A")+($E$15:$E$200="A")+($F$15:$F$200="A")+($G$15:$G$200="A")+($H$15:$H$200="A")+($I$15:$I$200="A")+($J$15:$J$200="A")+($K$15:$K$200="A")+($L$15:$L$200="A")+($M$15:$M$200="A"))) -> 0 | E8: =SUMPRODUCT(($B$15:$B$200="Liquidity Risk")*(($D$15:$D$200="R")+($E$15:$E$200="R")+($F$15:$F$200="R")+($G$15:$G$200="R")+($H$15:$H$200="R")+($I$15:$I$200="R")+($J$15:$J$200="R")+($K$15:$K$200="R")+($L$15:$L$200="R")+($M$15:$M$200="R"))) -> 0 | F8: =SUM(B8:E8) -> 7
A9: Counterparty / CCR | B9: =SUMPRODUCT(($B$15:$B$200="Counterparty / CCR")*(($D$15:$D$200="G")+($E$15:$E$200="G")+($F$15:$F$200="G")+($G$15:$G$200="G")+($H$15:$H$200="G")+($I$15:$I$200="G")+($J$15:$J$200="G")+($K$15:$K$200="G")+($L$15:$L$200="G")+($M$15:$M$200="G"))) -> 0 | C9: =SUMPRODUCT(($B$15:$B$200="Counterparty / CCR")*(($D$15:$D$200="AG")+($E$15:$E$200="AG")+($F$15:$F$200="AG")+($G$15:$G$200="AG")+($H$15:$H$200="AG")+($I$15:$I$200="AG")+($J$15:$J$200="AG")+($K$15:$K$200="AG")+($L$15:$L$200="AG")+($M$15:$M$200="AG"))) -> 0 | D9: =SUMPRODUCT(($B$15:$B$200="Counterparty / CCR")*(($D$15:$D$200="A")+($E$15:$E$200="A")+($F$15:$F$200="A")+($G$15:$G$200="A")+($H$15:$H$200="A")+($I$15:$I$200="A")+($J$15:$J$200="A")+($K$15:$K$200="A")+($L$15:$L$200="A")+($M$15:$M$200="A"))) -> 0 | E9: =SUMPRODUCT(($B$15:$B$200="Counterparty / CCR")*(($D$15:$D$200="R")+($E$15:$E$200="R")+($F$15:$F$200="R")+($G$15:$G$200="R")+($H$15:$H$200="R")+($I$15:$I$200="R")+($J$15:$J$200="R")+($K$15:$K$200="R")+($L$15:$L$200="R")+($M$15:$M$200="R"))) -> 0 | F9: =SUM(B9:E9) -> 0
A10: Sustainability | B10: =SUMPRODUCT(($B$15:$B$200="Sustainability")*(($D$15:$D$200="G")+($E$15:$E$200="G")+($F$15:$F$200="G")+($G$15:$G$200="G")+($H$15:$H$200="G")+($I$15:$I$200="G")+($J$15:$J$200="G")+($K$15:$K$200="G")+($L$15:$L$200="G")+($M$15:$M$200="G"))) -> 0 | C10: =SUMPRODUCT(($B$15:$B$200="Sustainability")*(($D$15:$D$200="AG")+($E$15:$E$200="AG")+($F$15:$F$200="AG")+($G$15:$G$200="AG")+($H$15:$H$200="AG")+($I$15:$I$200="AG")+($J$15:$J$200="AG")+($K$15:$K$200="AG")+($L$15:$L$200="AG")+($M$15:$M$200="AG"))) -> 0 | D10: =SUMPRODUCT(($B$15:$B$200="Sustainability")*(($D$15:$D$200="A")+($E$15:$E$200="A")+($F$15:$F$200="A")+($G$15:$G$200="A")+($H$15:$H$200="A")+($I$15:$I$200="A")+($J$15:$J$200="A")+($K$15:$K$200="A")+($L$15:$L$200="A")+($M$15:$M$200="A"))) -> 0 | E10: =SUMPRODUCT(($B$15:$B$200="Sustainability")*(($D$15:$D$200="R")+($E$15:$E$200="R")+($F$15:$F$200="R")+($G$15:$G$200="R")+($H$15:$H$200="R")+($I$15:$I$200="R")+($J$15:$J$200="R")+($K$15:$K$200="R")+($L$15:$L$200="R")+($M$15:$M$200="R"))) -> 0 | F10: =SUM(B10:E10) -> 0
A11: Performance | B11: =SUMPRODUCT(($B$15:$B$200="Performance")*(($D$15:$D$200="G")+($E$15:$E$200="G")+($F$15:$F$200="G")+($G$15:$G$200="G")+($H$15:$H$200="G")+($I$15:$I$200="G")+($J$15:$J$200="G")+($K$15:$K$200="G")+($L$15:$L$200="G")+($M$15:$M$200="G"))) -> 0 | C11: =SUMPRODUCT(($B$15:$B$200="Performance")*(($D$15:$D$200="AG")+($E$15:$E$200="AG")+($F$15:$F$200="AG")+($G$15:$G$200="AG")+($H$15:$H$200="AG")+($I$15:$I$200="AG")+($J$15:$J$200="AG")+($K$15:$K$200="AG")+($L$15:$L$200="AG")+($M$15:$M$200="AG"))) -> 0 | D11: =SUMPRODUCT(($B$15:$B$200="Performance")*(($D$15:$D$200="A")+($E$15:$E$200="A")+($F$15:$F$200="A")+($G$15:$G$200="A")+($H$15:$H$200="A")+($I$15:$I$200="A")+($J$15:$J$200="A")+($K$15:$K$200="A")+($L$15:$L$200="A")+($M$15:$M$200="A"))) -> 0 | E11: =SUMPRODUCT(($B$15:$B$200="Performance")*(($D$15:$D$200="R")+($E$15:$E$200="R")+($F$15:$F$200="R")+($G$15:$G$200="R")+($H$15:$H$200="R")+($I$15:$I$200="R")+($J$15:$J$200="R")+($K$15:$K$200="R")+($L$15:$L$200="R")+($M$15:$M$200="R"))) -> 0 | F11: =SUM(B11:E11) -> 0
A12: TOTAL | B12: =SUM(B7:B11) -> 34 | C12: =SUM(C7:C11) -> 1 | D12: =SUM(D7:D11) -> 0 | E12: =SUM(E7:E11) -> 0 | F12: =SUM(F7:F11) -> 35
A14: FUND-LEVEL MAT DATA · 7 funds · Enter G / AG / A / R per fund in each cell ▼
A15: MAT Metric | B15: Risk Type | C15: Trigger | D15: PB-PE pre-20 | E15: PB-PC pre-20 | F15: PB post-19 | G15: Lux Entities | H15: RE Syndic. | I15: Legacy PE | J15: Legacy FoF
A16: Performance vs target (PE) | B16: Market Risk | C16: Various | D16: G | E16: G | F16: G | G16: G | H16: G | I16: G | J16: G
A17: Performance vs target (PC) | B17: Market Risk | C17: Various | D17: G | E17: G | F17: G | G17: G | H17: G | I17: G | J17: G
A18: Capital deployment pace | B18: Market Risk | D18: G | E18: G | F18: G | G18: G | H18: G | I18: G | J18: G
A19: Concentration risk | B19: Market Risk | C19: >20% | D19: G | E19: G | F19: G | G19: AG | H19: G | I19: G | J19: G
A20: Liquidity / fund term | B20: Liquidity Risk | D20: G | E20: G | F20: G | G20: G | H20: G | I20: G | J20: G

Sheet VC
A1: Venture Capital · MAT Monitoring
A2: ▸ Update B3 = Reporting Period ▸ Update B4 = Number of Mandates ▸ Enter G / AG / A / R per fund in the coloured cells below (rows 15+) ▸ Strategy Summary (rows 7–12) and Dashboard auto-refresh via formulas
A3: Reporting Period | B3: Q3 2025
A4: Number of Mandates / Funds | B4: 1
A6: STRATEGY SUMMARY (auto-calculated from fund data below ▼) | B6: Green | C6: Amb-Grn | D6: Amber | E6: Red | F6: Total
A7: Market Risk | B7: =SUMPRODUCT(($B$15:$B$200="Market Risk")*(($D$15:$D$200="G")+($E$15:$E$200="G")+($F$15:$F$200="G")+($G$15:$G$200="G")+($H$15:$H$200="G")+($I$15:$I$200="G")+($J$15:$J$200="G")+($K$15:$K$200="G")+($L$15:$L$200="G")+($M$15:$M$200="G"))) -> 2 | C7: =SUMPRODUCT(($B$15:$B$200="Market Risk")*(($D$15:$D$200="AG")+($E$15:$E$200="AG")+($F$15:$F$200="AG")+($G$15:$G$200="AG")+($H$15:$H$200="AG")+($I$15:$I$200="AG")+($J$15:$J$200="AG")+($K$15:$K$200="AG")+($L$15:$L$200="AG")+($M$15:$M$200="AG"))) -> 0 | D7: =SUMPRODUCT(($B$15:$B$200="Market Risk")*(($D$15:$D$200="A")+($E$15:$E$200="A")+($F$15:$F$200="A")+($G$15:$G$200="A")+($H$15:$H$200="A")+($I$15:$I$200="A")+($J$15:$J$200="A")+($K$15:$K$200="A")+($L$15:$L$200="A")+($M$15:$M$200="A"))) -> 0 | E7: =SUMPRODUCT(($B$15:$B$200="Market Risk")*(($D$15:$D$200="R")+($E$15:$E$200="R")+($F$15:$F$200="R")+($G$15:$G$200="R")+($H$15:$H$200="R")+($I$15:$I$200="R")+($J$15:$J$200="R")+($K$15:$K$200="R")+($L$15:$L$200="R")+($M$15:$M$200="R"))) -> 0 | F7: =SUM(B7:E7) -> 2
A8: Liquidity Risk | B8: =SUMPRODUCT(($B$15:$B$200="Liquidity Risk")*(($D$15:$D$200="G")+($E$15:$E$200="G")+($F$15:$F$200="G")+($G$15:$G$200="G")+($H$15:$H$200="G")+($I$15:$I$200="G")+($J$15:$J$200="G")+($K$15:$K$200="G")+($L$15:$L$200="G")+($M$15:$M$200="G"))) -> 0 | C8: =SUMPRODUCT(($B$15:$B$200="Liquidity Risk")*(($D$15:$D$200="AG")+($E$15:$E$200="AG")+($F$15:$F$200="AG")+($G$15:$G$200="AG")+($H$15:$H$200="AG")+($I$15:$I$200="AG")+($J$15:$J$200="AG")+($K$15:$K$200="AG")+($L$15:$L$200="AG")+($M$15:$M$200="AG"))) -> 0 | D8: =SUMPRODUCT(($B$15:$B$200="Liquidity Risk")*(($D$15:$D$200="A")+($E$15:$E$200="A")+($F$15:$F$200="A")+($G$15:$G$200="A")+($H$15:$H$200="A")+($I$15:$I$200="A")+($J$15:$J$200="A")+($K$15:$K$200="A")+($L$15:$L$200="A")+($M$15:$M$200="A"))) -> 0 | E8: =SUMPRODUCT(($B$15:$B$200="Liquidity Risk")*(($D$15:$D$200="R")+($E$15:$E$200="R")+($F$15:$F$200="R")+($G$15:$G$200="R")+($H$15:$H$200="R")+($I$15:$I$200="R")+($J$15:$J$200="R")+($K$15:$K$200="R")+($L$15:$L$200="R")+($M$15:$M$200="R"))) -> 0 | F8: =SUM(B8:E8) -> 0
A9: Counterparty / CCR | B9: =SUMPRODUCT(($B$15:$B$200="Counterparty / CCR")*(($D$15:$D$200="G")+($E$15:$E$200="G")+($F$15:$F$200="G")+($G$15:$G$200="G")+($H$15:$H$200="G")+($I$15:$I$200="G")+($J$15:$J$200="G")+($K$15:$K$200="G")+($L$15:$L$200="G")+($M$15:$M$200="G"))) -> 0 | C9: =SUMPRODUCT(($B$15:$B$200="Counterparty / CCR")*(($D$15:$D$200="AG")+($E$15:$E$200="AG")+($F$15:$F$200="AG")+($G$15:$G$200="AG")+($H$15:$H$200="AG")+($I$15:$I$200="AG")+($J$15:$J$200="AG")+($K$15:$K$200="AG")+($L$15:$L$200="AG")+($M$15:$M$200="AG"))) -> 0 | D9: =SUMPRODUCT(($B$15:$B$200="Counterparty / CCR")*(($D$15:$D$200="A")+($E$15:$E$200="A")+($F$15:$F$200="A")+($G$15:$G$200="A")+($H$15:$H$200="A")+($I$15:$I$200="A")+($J$15:$J$200="A")+($K$15:$K$200="A")+($L$15:$L$200="A")+($M$15:$M$200="A"))) -> 0 | E9: =SUMPRODUCT(($B$15:$B$200="Counterparty / CCR")*(($D$15:$D$200="R")+($E$15:$E$200="R")+($F$15:$F$200="R")+($G$15:$G$200="R")+($H$15:$H$200="R")+($I$15:$I$200="R")+($J$15:$J$200="R")+($K$15:$K$200="R")+($L$15:$L$200="R")+($M$15:$M$200="R"))) -> 0 | F9: =SUM(B9:E9) -> 0
A10: Sustainability | B10: =SUMPRODUCT(($B$15:$B$200="Sustainability")*(($D$15:$D$200="G")+($E$15:$E$200="G")+($F$15:$F$200="G")+($G$15:$G$200="G")+($H$15:$H$200="G")+($I$15:$I$200="G")+($J$15:$J$200="G")+($K$15:$K$200="G")+($L$15:$L$200="G")+($M$15:$M$200="G"))) -> 1 | C10: =SUMPRODUCT(($B$15:$B$200="Sustainability")*(($D$15:$D$200="AG")+($E$15:$E$200="AG")+($F$15:$F$200="AG")+($G$15:$G$200="AG")+($H$15:$H$200="AG")+($I$15:$I$200="AG")+($J$15:$J$200="AG")+($K$15:$K$200="AG")+($L$15:$L$200="AG")+($M$15:$M$200="AG"))) -> 0 | D10: =SUMPRODUCT(($B$15:$B$200="Sustainability")*(($D$15:$D$200="A")+($E$15:$E$200="A")+($F$15:$F$200="A")+($G$15:$G$200="A")+($H$15:$H$200="A")+($I$15:$I$200="A")+($J$15:$J$200="A")+($K$15:$K$200="A")+($L$15:$L$200="A")+($M$15:$M$200="A"))) -> 0 | E10: =SUMPRODUCT(($B$15:$B$200="Sustainability")*(($D$15:$D$200="R")+($E$15:$E$200="R")+($F$15:$F$200="R")+($G$15:$G$200="R")+($H$15:$H$200="R")+($I$15:$I$200="R")+($J$15:$J$200="R")+($K$15:$K$200="R")+($L$15:$L$200="R")+($M$15:$M$200="R"))) -> 0 | F10: =SUM(B10:E10) -> 1
A11: Performance | B11: =SUMPRODUCT(($B$15:$B$200="Performance")*(($D$15:$D$200="G")+($E$15:$E$200="G")+($F$15:$F$200="G")+($G$15:$G$200="G")+($H$15:$H$200="G")+($I$15:$I$200="G")+($J$15:$J$200="G")+($K$15:$K$200="G")+($L$15:$L$200="G")+($M$15:$M$200="G"))) -> 0 | C11: =SUMPRODUCT(($B$15:$B$200="Performance")*(($D$15:$D$200="AG")+($E$15:$E$200="AG")+($F$15:$F$200="AG")+($G$15:$G$200="AG")+($H$15:$H$200="AG")+($I$15:$I$200="AG")+($J$15:$J$200="AG")+($K$15:$K$200="AG")+($L$15:$L$200="AG")+($M$15:$M$200="AG"))) -> 0 | D11: =SUMPRODUCT(($B$15:$B$200="Performance")*(($D$15:$D$200="A")+($E$15:$E$200="A")+($F$15:$F$200="A")+($G$15:$G$200="A")+($H$15:$H$200="A")+($I$15:$I$200="A")+($J$15:$J$200="A")+($K$15:$K$200="A")+($L$15:$L$200="A")+($M$15:$M$200="A"))) -> 0 | E11: =SUMPRODUCT(($B$15:$B$200="Performance")*(($D$15:$D$200="R")+($E$15:$E$200="R")+($F$15:$F$200="R")+($G$15:$G$200="R")+($H$15:$H$200="R")+($I$15:$I$200="R")+($J$15:$J$200="R")+($K$15:$K$200="R")+($L$15:$L$200="R")+($M$15:$M$200="R"))) -> 0 | F11: =SUM(B11:E11) -> 0
A12: TOTAL | B12: =SUM(B7:B11) -> 3 | C12: =SUM(C7:C11) -> 0 | D12: =SUM(D7:D11) -> 0 | E12: =SUM(E7:E11) -> 0 | F12: =SUM(F7:F11) -> 3
A14: FUND-LEVEL MAT DATA · 1 funds · Enter G / AG / A / R per fund in each cell ▼
A15: MAT Metric | B15: Risk Type | C15: Trigger | D15: FinTech Fund
A16: Gross IRR | B16: Market Risk | C16: <15% | D16: G
A17: Investment concentration | B17: Market Risk | C17: >20% | D17: G
A18: Sustainability | B18: Sustainability | D18: G
