Workbook

Sheet 0_ReadMe
A1: UK REVENUE & EV/EBITDA SHOCK PROPAGATION — BETA vs REAL-DATA, SIDE BY SIDE
A2: GICS Level 1 (Sector) -> Level 4 (Sub-Industry), UK only, both metrics, both methods compared
A5: SCOPE
A6: This workbook is UK-only (US removed) and covers both PRA SWES metrics: Revenue and EV/EBITDA multiple.
A7: For each of 163 GICS sub-industries, both a Damodaran-beta-based estimate AND a real-Bloomberg-data-based
A8: estimate are computed side by side, with the divergence between them shown explicitly. Companion to
A9: GICS_Shock_Propagation_L1_to_L4.xlsx (the original, broader US+UK build) and
A10: UK_EVEBITDA_Methodology_Change.pdf (the first-principles rationale for the real-data substitution).
A12: A BUG FIXED FROM THE PREVIOUS FILE
A13: The prior workbook showed #VALUE! errors in the live cascade once opened in real Excel, despite passing
A14: every structural check I could run without a live Excel engine. Most likely cause: a chain of formulas
A15: referencing formulas across sheets (a helper column computed by INDEX/MATCH, itself fed into a SUMPRODUCT
... A54: 7_Output clean flat table for lookup against a loan tape's GICS sub-industry code

Sheet 1_GICS_Structure
A1: Reference sheet, unchanged from GICS_Shock_Propagation_L1_to_L4.xlsx. All 163 GICS sub-industries, crosswalked to a Damodaran industry. Weight defaults to 1 (equal-weight).
A2: Sector Code | B2: Sector | C2: IG Code | D2: Industry Group | E2: Industry Code | F2: Industry | G2: Sub-Ind Code | H2: Sub-Industry | I2: Damodaran Industry (crosswalk) | J2: Weight
A3: 10 | B3: Energy | C3: 1010 | D3: Energy | E3: 101010 | F3: Energy Equipment & Services | G3: 10101010 | H3: Oil & Gas Drilling | I3: Oilfield Svcs/Equip. | J3: 1
A4: 10 | B4: Energy | C4: 1010 | D4: Energy | E4: 101010 | F4: Energy Equipment & Services | G4: 10101020 | H4: Oil & Gas Equipment & Services | I4: Oilfield Svcs/Equip. | J4: 1
A5: 10 | B5: Energy | C5: 1010 | D5: Energy | E5: 101020 | F5: Oil, Gas & Consumable Fuels | G5: 10102010 | H5: Integrated Oil & Gas | I5: Oil/Gas (Integrated) | J5: 1
A6: 10 | B6: Energy | C6: 1010 | D6: Energy | E6: 101020 | F6: Oil, Gas & Consumable Fuels | G6: 10102020 | H6: Oil & Gas Exploration & Production | I6: Oil/Gas (Production and Exploration) | J6: 1
A7: 10 | B7: Energy | C7: 1010 | D7: Energy | E7: 101020 | F7: Oil, Gas & Consumable Fuels | G7: 10102030 | H7: Oil & Gas Refining & Marketing | I7: Oil/Gas Distribution | J7: 1
A8: 10 | B8: Energy | C8: 1010 | D8: Energy | E8: 101020 | F8: Oil, Gas & Consumable Fuels | G8: 10102040 | H8: Oil & Gas Storage & Transportation | I8: Oil/Gas Distribution | J8: 1
A9: 10 | B9: Energy | C9: 1010 | D9: Energy | E9: 101020 | F9: Oil, Gas & Consumable Fuels | G9: 10102050 | H9: Coal & Consumable Fuels | I9: Coal & Related Energy | J9: 1
A10: 15 | B10: Materials | C10: 1510 | D10: Materials | E10: 151010 | F10: Chemicals | G10: 15101010 | H10: Commodity Chemicals | I10: Chemical (Basic) | J10: 1
A11: 15 | B11: Materials | C11: 1510 | D11: Materials | E11: 151010 | F11: Chemicals | G11: 15101020 | H11: Diversified Chemicals | I11: Chemical (Diversified) | J11: 1
A12: 15 | B12: Materials | C12: 1510 | D12: Materials | E12: 151010 | F12: Chemicals | G12: 15101030 | H12: Fertilizers & Agricultural Chemicals | I12: Chemical (Basic) | J12: 1
A13: 15 | B13: Materials | C13: 1510 | D13: Materials | E13: 151010 | F13: Chemicals | G13: 15101040 | H13: Industrial Gases | I13: Chemical (Specialty) | J13: 1
A14: 15 | B14: Materials | C14: 1510 | D14: Materials | E14: 151010 | F14: Chemicals | G14: 15101050 | H14: Specialty Chemicals | I14: Chemical (Specialty) | J14: 1
... A165: 60 | B165: Real Estate | C165: 6020 | D165: Real Estate Management & Development | E165: 602010 | F165: Real Estate Management & Development | G165: 60201040 | H165: Real Estate Services | I165: Real Estate (Operations & Services) | J165: 1

Sheet 2_Damodaran_Betas
A1: Reference sheet, unchanged. Damodaran industry betas (NYU Stern, updated 5 Jan 2026, US companies), credibility-shrunk toward the ex-financials market mean.
A2: Industry Name | B2: Number of firms | C2: Raw Beta | D2: Unlevered Beta (corrected for cash) | E2: Credibility n/(n+10) | F2: Shrunk Beta (used in cascade)
A3: Advertising | B3: 52 | C3: 1.2105 | D3: 1.008 | E3: =B3/(B3+10) | F3: =E3*D3+(1-E3)*$F$100
A4: Aerospace/Defense | B4: 79 | C4: 0.9455 | D4: 0.8694 | E4: =B4/(B4+10) | F4: =E4*D4+(1-E4)*$F$100
A5: Air Transport | B5: 23 | C5: 1.1855 | D5: 0.7579 | E5: =B5/(B5+10) | F5: =E5*D5+(1-E5)*$F$100
A6: Apparel | B6: 35 | C6: 0.9359 | D6: 0.7946 | E6: =B6/(B6+10) | F6: =E6*D6+(1-E6)*$F$100
A7: Auto & Truck | B7: 33 | C7: 1.4565 | D7: 1.3082 | E7: =B7/(B7+10) | F7: =E7*D7+(1-E7)*$F$100
A8: Auto Parts | B8: 35 | C8: 1.3394 | D8: 1.1283 | E8: =B8/(B8+10) | F8: =E8*D8+(1-E8)*$F$100
A9: Bank (Money Center) | B9: 15 | C9: 0.761 | D9: 0.4439 | E9: =B9/(B9+10) | F9: =E9*D9+(1-E9)*$F$100
A10: Banks (Regional) | B10: 568 | C10: 0.3985 | D10: 0.3744 | E10: =B10/(B10+10) | F10: =E10*D10+(1-E10)*$F$100
A11: Beverage (Alcoholic) | B11: 14 | C11: 0.8125 | D11: 0.628 | E11: =B11/(B11+10) | F11: =E11*D11+(1-E11)*$F$100
A12: Beverage (Soft) | B12: 27 | C12: 0.6415 | D12: 0.5755 | E12: =B12/(B12+10) | F12: =E12*D12+(1-E12)*$F$100
A13: Broadcasting | B13: 24 | C13: 0.4708 | D13: 0.3153 | E13: =B13/(B13+10) | F13: =E13*D13+(1-E13)*$F$100
A14: Brokerage & Investment Banking | B14: 32 | C14: 1.1715 | D14: 0.6794 | E14: =B14/(B14+10) | F14: =E14*D14+(1-E14)*$F$100
... A97: Total Market (without financials) | B97: 4822 | C97: 0.9913 | D97: 0.901 | E97: =B97/(B97+10) | F97: =E97*D97+(1-E97)*$F$100
A99: Reference:
A100: Total Market unlevered beta (ex-financials) — shrinkage target | F100: 0.901

Sheet 3_UK_Bloomberg_Data
A1: REAL DATA, VALUES ONLY (no formulas in this sheet — see 0_ReadMe for why). Bloomberg EQS<GO>, UK Refined/Investable Universe (1,298 companies), GICS Sub-Industry level, two independent exports (EV/EBITDA and Revenue) cross-validated against each other: 139/139 names and market caps matched exactly. Read 8 Aug 2026.
A3: Sub-Ind Code | B3: Sub-Industry | C3: N Cos | D3: Sector Code | E3: Market Cap (GBP) | F3: Revenue T12M (GBP) | G3: Current EV/EBITDA | H3: BF EV/EBITDA | I3: Multiple Used (outlier-corrected) | J3: Note
A4: 10101010 | B4: Oil & Gas Drilling | C4: 1 | D4: 10 | E4: 2270000000 | F4: 554970000 | G4: 3.74 | H4: 3.3 | I4: 3.74
A5: 10101020 | B5: Oil & Gas Equipment & Services | C5: 7 | D5: 10 | E5: 18050000000 | F5: 2690000000 | G5: 8.22 | H5: 6.7 | I5: 8.22
A6: 10102010 | B6: Integrated Oil & Gas | C6: 2 | D6: 10 | E6: 131690000000 | F6: 256880000000 | G6: 3.39 | H6: 3.6 | I6: 3.39
A7: 10102020 | B7: Oil & Gas Exploration & Production | C7: 48 | D7: 10 | E7: 288850000 | F7: 217770000 | G7: 3.17 | H7: 2.1 | I7: 3.17
A8: 10102030 | B8: Oil & Gas Refining & Marketing | C8: 1 | D8: 10 | E8: 22750000 | F8: 87000
A9: 10102040 | B9: Oil & Gas Storage & Transportation | C9: 3 | D9: 10 | E9: 6580000000 | F9: 901710000 | G9: 3.94 | H9: 4.2 | I9: 3.94
A10: 10102050 | B10: Coal & Consumable Fuels | C10: 8 | D10: 10 | E10: 210400000 | G10: 9.47 | H10: 16 | I10: 9.47 | J10: Revenue shows 0.00 in source — treated as no-data
A11: 15101010 | B11: Commodity Chemicals | C11: 2 | D11: 15 | E11: 266070000 | F11: 246000000 | G11: 5.64 | H11: 5.5 | I11: 5.64
A12: 15101030 | B12: Fertilizers & Agricultural Chemicals | C12: 3 | D12: 15 | E12: 20780000 | F12: 21070000
A13: 15101040 | B13: Industrial Gases | C13: 2 | D13: 15 | E13: 44030000 | J13: Revenue shows 0.00 in source — treated as no-data
A14: 15101050 | B14: Specialty Chemicals | C14: 13 | D14: 15 | E14: 876550000 | F14: 1590000000 | G14: 8.87 | H14: 15.9 | I14: 8.87
A15: 15102010 | B15: Construction Materials | C15: 6 | D15: 15 | E15: 655910000 | F15: 699210000 | G15: 6.57 | H15: 6.1 | I15: 6.57
A16: 15103010 | B16: Metal, Glass & Plastic Containers | C16: 1 | D16: 15 | E16: 5110000 | F16: 33260000
A17: 15103020 | B17: Paper & Plastic Packaging Products & Materials | C17: 1 | D17: 15 | E17: 20940000 | F17: 56210000 | G17: 3.38 | H17: 3.2 | I17: 3.38
A18: 15104020 | B18: Diversified Metals & Mining | C18: 47 | D18: 15 | E18: 3860000000 | F18: 1930000000 | G18: 5.94 | H18: 5 | I18: 5.94
A19: 15104025 | B19: Copper | C19: 3 | D19: 15 | E19: 98500000 | F19: 76620000 | G19: 1.5 | H19: 1.3 | I19: 1.5
A20: 15104030 | B20: Gold | C20: 14 | D20: 15 | E20: 1430000000 | F20: 410600000 | G20: 4.23 | H20: 3.2 | I20: 4.23
A21: 15104040 | B21: Precious Metals & Minerals | C21: 6 | D21: 15 | E21: 32640000 | F21: 20970000
A22: 15104050 | B22: Steel | C22: 6 | D22: 15 | E22: 509320000 | F22: 229700000 | G22: 10.16 | H22: 10 | I22: 10.16
A23: 15105010 | B23: Forest Products | C23: 1 | D23: 15 | E23: 170210000 | F23: 153280000 | G23: 9.59 | H23: 8.7 | I23: 9.59
A24: 15105020 | B24: Paper Products | C24: 2 | D24: 15 | E24: 2060000000 | F24: 3920000000 | G24: 6.56 | H24: 6 | I24: 6.56
A25: 20101010 | B25: Aerospace & Defense | C25: 14 | D25: 20 | E25: 15250000000 | F25: 4670000000 | G25: 13.03 | H25: 11.4 | I25: 13.03
A26: 20102010 | B26: Building Products | C26: 9 | D26: 20 | E26: 358510000 | F26: 250880000 | G26: 7.16 | H26: 6.5 | I26: 7.16
A27: 20103010 | B27: Construction & Engineering | C27: 14 | D27: 20 | E27: 850040000 | F27: 1920000000 | G27: 6.91 | H27: 5.9 | I27: 6.91
A28: 20104010 | B28: Electrical Components & Equipment | C28: 16 | D28: 20 | E28: 2040000000 | F28: 480480000 | G28: 213.01 | H28: 9.8 | I28: 9.8 | J28: Current EV/EBITDA (213.01x) is a near-zero-EBITDA artifact — using BF instead
A29: 20104020 | B29: Heavy Electrical Equipment | C29: 4 | D29: 20 | E29: 2180000000 | F29: 229090000 | G29: 38.05 | H29: 32.3 | I29: 38.05
A30: 20105010 | B30: Industrial Conglomerates | C30: 2 | D30: 20 | E30: 3980000000 | F30: 1130000000 | G30: 12.91 | H30: 12.9 | I30: 12.91
A31: 20106015 | B31: Agricultural & Farm Machinery | C31: 1 | D31: 20 | E31: 13500000000 | F31: 18180000000 | G31: 27.38 | H31: 23.7 | I31: 27.38
A32: 20106020 | B32: Industrial Machinery & Supplies & Components | C32: 17 | D32: 20 | E32: 2440000000 | F32: 966980000 | G32: 10.77 | H32: 10.1 | I32: 10.77
A33: 20107010 | B33: Trading Companies & Distributors | C33: 18 | D33: 20 | E33: 1790000000 | F33: 1710000000 | G33: 7.57 | H33: 7.2 | I33: 7.57
A34: 20201010 | B34: Commercial Printing | C34: 1 | D34: 20 | E34: 62410000 | F34: 22260000
A35: 20201050 | B35: Environmental & Facilities Services | C35: 6 | D35: 20 | E35: 2410000000 | F35: 2970000000 | G35: 8.34 | H35: 7.9 | I35: 8.34
A36: 20201070 | B36: Diversified Support Services | C36: 10 | D36: 20 | E36: 221420000 | F36: 272250000 | G36: 5.61 | H36: 5.5 | I36: 5.61
A37: 20201080 | B37: Security & Alarm Services | C37: 1 | D37: 20 | E37: 9930000000 | F37: 13500000000 | G37: 8.49 | H37: 8 | I37: 8.49
A38: 20202010 | B38: Human Resource & Employment Services | C38: 10 | D38: 20 | E38: 225530000 | F38: 1210000000 | G38: 9.43 | H38: 6.1 | I38: 9.43
A39: 20202020 | B39: Research & Consulting Services | C39: 25 | D39: 20 | E39: 2380000000 | F39: 760740000 | G39: 7.31 | H39: 6.7 | I39: 7.31
A40: 20202030 | B40: Data Processing & Outsourced Services | C40: 1 | D40: 20 | E40: 318990000 | F40: 279910000 | G40: 6.59 | H40: 5.1 | I40: 6.59
A41: 20301010 | B41: Air Freight & Logistics | C41: 1 | D41: 20 | E41: 731310000 | F41: 137040000 | G41: 6.05 | H41: 5.7 | I41: 6.05
A42: 20302010 | B42: Passenger Airlines | C42: 3 | D42: 20 | E42: 9190000000 | F42: 17130000000 | G42: 3.69 | H42: 3.3 | I42: 3.69
A43: 20303010 | B43: Marine Transportation | C43: 3 | D43: 20 | E43: 7130000000 | F43: 1460000000 | G43: 6 | H43: 5.8 | I43: 6
A44: 20304010 | B44: Rail Transportation | C44: 1 | D44: 20 | E44: 1010000000 | F44: 4750000000 | G44: 2.53 | H44: 2.9 | I44: 2.53
A45: 20304040 | B45: Passenger Ground Transportation | C45: 2 | D45: 20 | E45: 613190000 | F45: 2300000000 | G45: 3.68 | H45: 3.6 | I45: 3.68
A46: 20305030 | B46: Marine Ports & Services | C46: 3 | D46: 20 | E46: 107990000 | F46: 180500000 | G46: 4.85 | H46: 4.5 | I46: 4.85
... A48: 25102010 | B48: Automobile Manufacturers | C48: 1 | D48: 25 | E48: 357390000 | F48: 1430000000 | G48: 6.3 | H48: 5.6 | I48: 6.3
A49: 25102020 | B49: Motorcycle Manufacturers | C49: 1 | D49: 25 | E49: 651000 | J49: Revenue shows 0.00 in source — treated as no-data
A50: 25201010 | B50: Consumer Electronics | C50: 2 | D50: 25 | E50: 117000000 | F50: 196060000 | G50: 7.26 | H50: 5.7 | I50: 7.26
A51: 25201020 | B51: Home Furnishings | C51: 4 | D51: 25 | E51: 52820000 | F51: 321410000 | G51: 6.76 | H51: 6.3 | I51: 6.76
A52: 25201030 | B52: Homebuilding | C52: 12 | D52: 25 | E52: 1550000000 | F52: 2020000000 | G52: 7.39 | H52: 6.7 | I52: 7.39
A53: 25201040 | B53: Household Appliances | C53: 2 | D53: 25 | E53: 300730000 | F53: 426540000 | G53: 7.75 | H53: 7.4 | I53: 7.75
A54: 25201050 | B54: Housewares & Specialties | C54: 3 | D54: 25 | E54: 55210000 | F54: 128400000 | G54: 6.28 | H54: 6.2 | I54: 6.28
A55: 25202010 | B55: Leisure Products | C55: 3 | D55: 25 | E55: 2100000000 | F55: 260530000 | G55: 11.68 | H55: 13.1 | I55: 11.68
A56: 25203010 | B56: Apparel, Accessories & Luxury Goods | C56: 6 | D56: 25 | E56: 1020000000 | F56: 1210000000 | G56: 7.24 | H56: 7 | I56: 7.24
A57: 25203020 | B57: Footwear | C57: 2 | D57: 25 | E57: 3940000000 | F57: 1470000000 | G57: 7.46 | H57: 6.6 | I57: 7.46
A58: 25203030 | B58: Textiles | C58: 1 | D58: 25 | E58: 1660000000 | F58: 1600000000 | G58: 7.15 | H58: 6.6 | I58: 7.15
A59: 25301010 | B59: Casinos & Gaming | C59: 5 | D59: 25 | E59: 1610000000 | F59: 1740000000 | G59: 7.29 | H59: 5.9 | I59: 7.29
A60: 25301020 | B60: Hotels, Resorts & Cruise Lines | C60: 7 | D60: 25 | E60: 4130000000 | F60: 1270000000 | G60: 9.21 | H60: 8.1 | I60: 9.21
A61: 25301030 | B61: Leisure Facilities | C61: 4 | D61: 25 | E61: 223280000 | F61: 148090000 | G61: 6.4 | H61: 6.1 | I61: 6.4
... A72: 25504060 | B72: Homefurnishing Retail | C72: 3 | D72: 25 | E72: 740720000 | F72: 359370000 | G72: 4.6 | H72: 4.4 | I72: 4.6
A73: 30101010 | B73: Drug Retail | C73: 1 | D73: 30 | E73: 55230000 | J73: Revenue shows 0.00 in source — treated as no-data
A74: 30101030 | B74: Food Retail | C74: 7 | D74: 30 | E74: 6860000000 | F74: 18100000000 | G74: 5.77 | H74: 6.2 | I74: 5.77
A75: 30201010 | B75: Brewers | C75: 2 | D75: 30 | E75: 44350000 | F75: 113830000 | G75: 6.18 | H75: 6 | I75: 6.18
A76: 30201020 | B76: Distillers & Vintners | C76: 4 | D76: 30 | E76: 9990000000 | F76: 4920000000 | G76: 19.57 | H76: 17.8 | I76: 19.57
A77: 30201030 | B77: Soft Drinks & Non-alcoholic Beverages | C77: 4 | D77: 30 | E77: 12510000000 | F77: 5570000000 | G77: 11.96 | H77: 10.9 | I77: 11.96
A78: 30202010 | B78: Agricultural Products & Services | C78: 7 | D78: 30 | E78: 316950000 | F78: 700400000 | G78: 5.8 | H78: 5.4 | I78: 5.8
A79: 30202030 | B79: Packaged Foods & Meats | C79: 10 | D79: 30 | E79: 2520000000 | F79: 3470000000 | G79: 7.49 | H79: 7.2 | I79: 7.49
A80: 30203010 | B80: Tobacco | C80: 2 | D80: 30 | E80: 58530000000 | F80: 26210000000 | G80: 8.57 | H80: 8.3 | I80: 8.57
A81: 30301010 | B81: Household Products | C81: 2 | D81: 30 | E81: 16990000000 | F81: 7280000000 | G81: 8.12 | H81: 7.8 | I81: 8.12
A82: 30302010 | B82: Personal Care Products | C82: 11 | D82: 30 | E82: 10240000000 | F82: 4710000000 | G82: 10.41 | H82: 9.2 | I82: 10.41
A83: 35101010 | B83: Health Care Equipment | C83: 11 | D83: 35 | E83: 1400000000 | F83: 795190000 | G83: 13.59 | H83: 12.4 | I83: 13.59
A84: 35101020 | B84: Health Care Supplies | C84: 8 | D84: 35 | E84: 787430000 | F84: 112670000 | G84: 12.07 | H84: 10.8 | I84: 12.07
A85: 35102010 | B85: Health Care Distributors | C85: 1 | D85: 35 | E85: 2380000 | F85: 12420
A86: 35102015 | B86: Health Care Services | C86: 9 | D86: 35 | E86: 57660000 | F86: 26960000 | G86: 4.62 | H86: 3.7 | I86: 4.62
A87: 35102020 | B87: Health Care Facilities | C87: 3 | D87: 35 | E87: 610570000 | F87: 756150000 | G87: 7.33 | H87: 6.7 | I87: 7.33
A88: 35103010 | B88: Health Care Technology | C88: 8 | D88: 35 | E88: 82100000 | F88: 173230000 | G88: 8.13 | H88: 32.7 | I88: 8.13
A89: 35201010 | B89: Biotechnology | C89: 35 | D89: 35 | E89: 407840000 | F89: 72750000 | G89: 25.22 | H89: 22.9 | I89: 25.22
A90: 35202010 | B90: Pharmaceuticals | C90: 15 | D90: 35 | E90: 21460000000 | F90: 7290000000 | G90: 9.18 | H90: 8.7 | I90: 9.18
A91: 35203010 | B91: Life Sciences Tools & Services | C91: 9 | D91: 35 | E91: 162120000 | F91: 36120000 | G91: 58.62 | H91: 16.2 | I91: 16.2 | J91: Current EV/EBITDA (58.62x) is a near-zero-EBITDA artifact — using BF instead
A92: 40101010 | B92: Diversified Banks | C92: 9 | D92: 40 | E92: 56790000000 | F92: 28150000000
A93: 40101015 | B93: Regional Banks | C93: 2 | D93: 40 | E93: 1450000000 | F93: 410600000
A94: 40201020 | B94: Diversified Financial Services | C94: 1 | D94: 40 | E94: 8750000000 | F94: 18230000000
A95: 40201040 | B95: Specialized Finance | C95: 6 | D95: 40 | E95: 41070000 | F95: 41090000 | G95: 6.17 | H95: 5.4 | I95: 6.17
A96: 40201050 | B96: Commercial & Residential Mortgage Finance | C96: 6 | D96: 40 | E96: 1010000000 | F96: 3880000000 | G96: 5.95 | H96: 5.5 | I96: 5.95
A97: 40201060 | B97: Transaction & Payment Processing Services | C97: 9 | D97: 40 | E97: 2980000000 | F97: 1010000000 | G97: 15.31 | H97: 9.6 | I97: 15.31
A98: 40202010 | B98: Consumer Finance | C98: 5 | D98: 40 | E98: 276710000 | F98: 246000000 | G98: 5.59 | H98: 4.6 | I98: 5.59
A99: 40203010 | B99: Asset Management & Custody Banks | C99: 75 | D99: 40 | E99: 1280000000 | F99: 3060000000 | G99: 11.61 | H99: 9.4 | I99: 11.61
A100: 40203020 | B100: Investment Banking & Brokerage | C100: 11 | D100: 40 | E100: 1060000000 | F100: 421470000 | G100: 10.49 | H100: 10.1 | I100: 10.49
A101: 40203040 | B101: Financial Exchanges & Data | C101: 4 | D101: 40 | E101: 12530000000 | F101: 2630000000 | G101: 11.47 | H101: 10.4 | I101: 11.47
A102: 40301010 | B102: Insurance Brokers | C102: 2 | D102: 40 | E102: 54010000000 | F102: 13840000000 | G102: 13.45 | H102: 12.6 | I102: 13.45
A103: 40301020 | B103: Life & Health Insurance | C103: 3 | D103: 40 | E103: 9250000000 | F103: 13500000000
A104: 40301030 | B104: Multi-line Insurance | C104: 3 | D104: 40 | E104: 7540000000 | F104: 9240000000 | G104: 9.53 | H104: 8.9 | I104: 9.53
A105: 40301040 | B105: Property & Casualty Insurance | C105: 5 | D105: 40 | E105: 4340000000 | F105: 2690000000
A106: 45102010 | B106: IT Consulting & Other Services | C106: 15 | D106: 45 | E106: 745840000 | F106: 845570000 | G106: 9.31 | H106: 8.5 | I106: 9.31
A107: 45102030 | B107: Internet Services & Infrastructure | C107: 7 | D107: 45 | E107: 144280000 | F107: 85470000 | G107: 7.59 | H107: 6.1 | I107: 7.59
A108: 45103010 | B108: Application Software | C108: 49 | D108: 45 | E108: 354900000 | F108: 100060000 | G108: 12.1 | H108: 8.8 | I108: 12.1
A109: 45103020 | B109: Systems Software | C109: 5 | D109: 45 | E109: 27190000 | F109: 14860000 | G109: 19.39 | H109: 15.6 | I109: 19.39
A110: 45201020 | B110: Communications Equipment | C110: 4 | D110: 45 | E110: 203930000 | F110: 46790000 | G110: 20.73 | H110: 22.6 | I110: 20.73
A111: 45202030 | B111: Technology Hardware, Storage & Peripherals | C111: 3 | D111: 45 | E111: 554470000 | F111: 143870000 | G111: 25.1 | H111: 22.1 | I111: 25.1
A112: 45203010 | B112: Electronic Equipment & Instruments | C112: 15 | D112: 45 | E112: 1350000000 | F112: 1190000000 | G112: 10.82 | H112: 10.7 | I112: 10.82
...

Sheet 4_UK_L1_Input
A1: STEP 4 — PASTE ZONE. PRA SWES Level-1 (GICS Sector) UK shocks, Year 1, from the BoE annex.
A3: Sector Code | B3: GICS Sector | C3: UK Revenue Shock % | D3: UK EV/EBITDA Shock %
A4: 10 | B4: Energy | C4: 0.08 | D4: 0
A5: 15 | B5: Materials | C5: -0.05 | D5: -0.28
A6: 20 | B6: Industrials | C6: -0.1 | D6: -0.32
A7: 25 | B7: Consumer Discretionary | C7: -0.1 | D7: -0.25
A8: 30 | B8: Consumer Staples | C8: -0.05 | D8: -0.25
A9: 35 | B9: Health Care | C9: -0.05 | D9: -0.25
A10: 40 | B10: Financials | C10: -0.1 | D10: -0.32
A11: 45 | B11: Information Technology | C11: -0.1 | D11: -0.36
A12: 50 | B12: Communication Services | C12: -0.05 | D12: -0.26
A13: 55 | B13: Utilities | C13: 0.02 | D13: -0.01
A14: 60 | B14: Real Estate | C14: -0.1 | D14: -0.36

Sheet 5_Cascade_Engine
A1: STEP 5 — 163 sub-industries. Columns F-O: the ORIGINAL Damodaran-beta cascade, equal-weighted (unchanged method). Columns P-AD: the REAL-DATA cascade — Revenue keeps the beta DIFFERENTIATOR but reweights by real UK revenue; EV/EBITDA uses the real multiple as the differentiator outright, falling back to the beta estimate only where no UK listing exists. Columns AE-AF: the divergence between the two.
A2: Sub-Ind Code | B2: Sub-Industry | C2: Sector Code | D2: IG Code | E2: Ind Code | F2: Shrunk Beta L4 | G2: Weight (=1) | H2: AvgBeta L3 (eq-wt) | I2: AvgBeta L2 (eq-wt) | J2: AvgBeta L1 (eq-wt) | K2: RelBeta L2 | L2: RelBeta L3 | M2: RelBeta L4 | N2: [BETA] Rev Shock L4 | O2: [BETA] EV/EBITDA Shock L4 | P2: Real UK Revenue | Q2: Real UK Market Cap | R2: Real UK Multiple Used | S2: AvgBeta L3 (real-rev-wt) | T2: AvgBeta L2 (real-rev-wt) | U2: AvgBeta L1 (real-rev-wt) | V2: RelBeta L2 (real-rev-wt) | W2: RelBeta L3 (real-rev-wt) | X2: RelBeta L4 (real-rev-wt) | Y2: [REAL] Rev Shock L4 | Z2: Rev Source | AA2: Real Sector Wtd-Avg Multiple | AB2: RelMultiple (real) | AC2: [REAL] EV/EBITDA Shock L4 | AD2: EV/EBITDA Source | AE2: Rev Divergence | AF2: EV/EBITDA Divergence
A3: 10101010 | B3: Oil & Gas Drilling | C3: 10 | D3: 1010 | E3: 101010 | F3: 0.797703 | G3: 1 | H3: =SUMPRODUCT(($E$3:$E$165=E3)*$G$3:$G$165*$F$3:$F$165)/SUMPRODUCT(($E$3:$E$165=E3)*$G$3:$G$165) | I3: =SUMPRODUCT(($D$3:$D$165=D3)*$G$3:$G$165*$F$3:$F$165)/SUMPRODUCT(($D$3:$D$165=D3)*$G$3:$G$165) | J3: =SUMPRODUCT(($C$3:$C$165=C3)*$G$3:$G$165*$F$3:$F$165)/SUMPRODUCT(($C$3:$C$165=C3)*$G$3:$G$165) | K3: =I3/J3 | L3: =H3/I3 | M3: =F3/H3 | N3: =INDEX('4_UK_L1_Input'!$C$4:$C$14,MATCH($C3,'4_UK_L1_Input'!$A$4:$A$14,0))*K3*L3*M3 | O3: =INDEX('4_UK_L1_Input'!$D$4:$D$14,MATCH($C3,'4_UK_L1_Input'!$A$4:$A$14,0))*K3*L3*M3 | P3: 554970000 | Q3: 2270000000 | R3: 3.74 | S3: =IFERROR(SUMPRODUCT(($E$3:$E$165=E3)*ISNUMBER($P$3:$P$165)*$P$3:$P$165*$F$3:$F$165)/SUMPRODUCT(($E$3:$E$165=E3)*ISNUMBER($P$3:$P$165)*$P$3:$P$165),"") | T3: =IFERROR(SUMPRODUCT(($D$3:$D$165=D3)*ISNUMBER($P$3:$P$165)*$P$3:$P$165*$F$3:$F$165)/SUMPRODUCT(($D$3:$D$165=D3)*ISNUMBER($P$3:$P$165)*$P$3:$P$165),"") | U3: =IFERROR(SUMPRODUCT(($C$3:$C$165=C3)*ISNUMBER($P$3:$P$165)*$P$3:$P$165*$F$3:$F$165)/SUMPRODUCT(($C$3:$C$165=C3)*ISNUMBER($P$3:$P$165)*$P$3:$P$165),"") | V3: =IF(OR(T3="",U3=""),"",T3/U3) | W3: =IF(OR(S3="",T3=""),"",S3/T3) | X3: =IF(S3="","",F3/S3) | Y3: =IF(V3="",N3,INDEX('4_UK_L1_Input'!$C$4:$C$14,MATCH($C3,'4_UK_L1_Input'!$A$4:$A$14,0))*V3*W3*X3) | Z3: =IF(V3="","BETA FALLBACK","REAL (Bloomberg UK)") | AA3: =IFERROR(SUMPRODUCT(($C$3:$C$165=C3)*ISNUMBER($R$3:$R$165)*$Q$3:$Q$165*IF(ISNUMBER($R$3:$R$165),$R$3:$R$165,0))/SUMPRODUCT(($C$3:$C$165=C3)*ISNUMBER($R$3:$R$165)*$Q$3:$Q$165),"") | AB3: =IF(OR(R3="",AA3=""),"",R3/AA3) | AC3: =IF(AB3="",O3,INDEX('4_UK_L1_Input'!$D$4:$D$14,MATCH($C3,'4_UK_L1_Input'!$A$4:$A$14,0))*AB3) | AD3: =IF(AB3="","BETA FALLBACK","REAL (Bloomberg UK)") | AE3: =Y3-N3 | AF3: =AC3-O3
A4: 10101020 | B4: Oil & Gas Equipment & Services | C4: 10 | D4: 1010 | E4: 101010 | F4: 0.797703 | G4: 1 | H4: =SUMPRODUCT(($E$3:$E$165=E4)*$G$3:$G$165*$F$3:$F$165)/SUMPRODUCT(($E$3:$E$165=E4)*$G$3:$G$165) | I4: =SUMPRODUCT(($D$3:$D$165=D4)*$G$3:$G$165*$F$3:$F$165)/SUMPRODUCT(($D$3:$D$165=D4)*$G$3:$G$165) | J4: =SUMPRODUCT(($C$3:$C$165=C4)*$G$3:$G$165*$F$3:$F$165)/SUMPRODUCT(($C$3:$C$165=C4)*$G$3:$G$165) | K4: =I4/J4 | L4: =H4/I4 | M4: =F4/H4 | N4: =INDEX('4_UK_L1_Input'!$C$4:$C$14,MATCH($C4,'4_UK_L1_Input'!$A$4:$A$14,0))*K4*L4*M4 | O4: =INDEX('4_UK_L1_Input'!$D$4:$D$14,MATCH($C4,'4_UK_L1_Input'!$A$4:$A$14,0))*K4*L4*M4 | P4: 2690000000 | Q4: 18050000000 | R4: 8.22 | S4: =IFERROR(SUMPRODUCT(($E$3:$E$165=E4)*ISNUMBER($P$3:$P$165)*$P$3:$P$165*$F$3:$F$165)/SUMPRODUCT(($E$3:$E$165=E4)*ISNUMBER($P$3:$P$165)*$P$3:$P$165),"") | T4: =IFERROR(SUMPRODUCT(($D$3:$D$165=D4)*ISNUMBER($P$3:$P$165)*$P$3:$P$165*$F$3:$F$165)/SUMPRODUCT(($D$3:$D$165=D4)*ISNUMBER($P$3:$P$165)*$P$3:$P$165),"") | U4: =IFERROR(SUMPRODUCT(($C$3:$C$165=C4)*ISNUMBER($P$3:$P$165)*$P$3:$P$165*$F$3:$F$165)/SUMPRODUCT(($C$3:$C$165=C4)*ISNUMBER($P$3:$P$165)*$P$3:$P$165),"") | V4: =IF(OR(T4="",U4=""),"",T4/U4) | W4: =IF(OR(S4="",T4=""),"",S4/T4) | X4: =IF(S4="","",F4/S4) | Y4: =IF(V4="",N4,INDEX('4_UK_L1_Input'!$C$4:$C$14,MATCH($C4,'4_UK_L1_Input'!$A$4:$A$14,0))*V4*W4*X4) | Z4: =IF(V4="","BETA FALLBACK","REAL (Bloomberg UK)") | AA4: =IFERROR(SUMPRODUCT(($C$3:$C$165=C4)*ISNUMBER($R$3:$R$165)*$Q$3:$Q$165*IF(ISNUMBER($R$3:$R$165),$R$3:$R$165,0))/SUMPRODUCT(($C$3:$C$165=C4)*ISNUMBER($R$3:$R$165)*$Q$3:$Q$165),"") | AB4: =IF(OR(R4="",AA4=""),"",R4/AA4) | AC4: =IF(AB4="",O4,INDEX('4_UK_L1_Input'!$D$4:$D$14,MATCH($C4,'4_UK_L1_Input'!$A$4:$A$14,0))*AB4) | AD4: =IF(AB4="","BETA FALLBACK","REAL (Bloomberg UK)") | AE4: =Y4-N4 | AF4: =AC4-O4
A5: 10102010 | B5: Integrated Oil & Gas | C5: 10 | D5: 1010 | E5: 101020 | F5: 0.722978 | G5: 1 | H5: =SUMPRODUCT(($E$3:$E$165=E5)*$G$3:$G$165*$F$3:$F$165)/SUMPRODUCT(($E$3:$E$165=E5)*$G$3:$G$165) | I5: =SUMPRODUCT(($D$3:$D$165=D5)*$G$3:$G$165*$F$3:$F$165)/SUMPRODUCT(($D$3:$D$165=D5)*$G$3:$G$165) | J5: =SUMPRODUCT(($C$3:$C$165=C5)*$G$3:$G$165*$F$3:$F$165)/SUMPRODUCT(($C$3:$C$165=C5)*$G$3:$G$165) | K5: =I5/J5 | L5: =H5/I5 | M5: =F5/H5 | N5: =INDEX('4_UK_L1_Input'!$C$4:$C$14,MATCH($C5,'4_UK_L1_Input'!$A$4:$A$14,0))*K5*L5*M5 | O5: =INDEX('4_UK_L1_Input'!$D$4:$D$14,MATCH($C5,'4_UK_L1_Input'!$A$4:$A$14,0))*K5*L5*M5 | P5: 256880000000 | Q5: 131690000000 | R5: 3.39 | S5: =IFERROR(SUMPRODUCT(($E$3:$E$165=E5)*ISNUMBER($P$3:$P$165)*$P$3:$P$165*$F$3:$F$165)/SUMPRODUCT(($E$3:$E$165=E5)*ISNUMBER($P$3:$P$165)*$P$3:$P$165),"") | T5: =IFERROR(SUMPRODUCT(($D$3:$D$165=D5)*ISNUMBER($P$3:$P$165)*$P$3:$P$165*$F$3:$F$165)/SUMPRODUCT(($D$3:$D$165=D5)*ISNUMBER($P$3:$P$165)*$P$3:$P$165),"") | U5: =IFERROR(SUMPRODUCT(($C$3:$C$165=C5)*ISNUMBER($P$3:$P$165)*$P$3:$P$165*$F$3:$F$165)/SUMPRODUCT(($C$3:$C$165=C5)*ISNUMBER($P$3:$P$165)*$P$3:$P$165),"") | V5: =IF(OR(T5="",U5=""),"",T5/U5) | W5: =IF(OR(S5="",T5=""),"",S5/T5) | X5: =IF(S5="","",F5/S5) | Y5: =IF(V5="",N5,INDEX('4_UK_L1_Input'!$C$4:$C$14,MATCH($C5,'4_UK_L1_Input'!$A$4:$A$14,0))*V5*W5*X5) | Z5: =IF(V5="","BETA FALLBACK","REAL (Bloomberg UK)") | AA5: =IFERROR(SUMPRODUCT(($C$3:$C$165=C5)*ISNUMBER($R$3:$R$165)*$Q$3:$Q$165*IF(ISNUMBER($R$3:$R$165),$R$3:$R$165,0))/SUMPRODUCT(($C$3:$C$165=C5)*ISNUMBER($R$3:$R$165)*$Q$3:$Q$165),"") | AB5: =IF(OR(R5="",AA5=""),"",R5/AA5) | AC5: =IF(AB5="",O5,INDEX('4_UK_L1_Input'!$D$4:$D$14,MATCH($C5,'4_UK_L1_Input'!$A$4:$A$14,0))*AB5) | AD5: =IF(AB5="","BETA FALLBACK","REAL (Bloomberg UK)") | AE5: =Y5-N5 | AF5: =AC5-O5
A6: 10102020 | B6: Oil & Gas Exploration & Production | C6: 10 | D6: 1010 | E6: 101020 | F6: 0.599753 | G6: 1 | H6: =SUMPRODUCT(($E$3:$E$165=E6)*$G$3:$G$165*$F$3:$F$165)/SUMPRODUCT(($E$3:$E$165=E6)*$G$3:$G$165) | I6: =SUMPRODUCT(($D$3:$D$165=D6)*$G$3:$G$165*$F$3:$F$165)/SUMPRODUCT(($D$3:$D$165=D6)*$G$3:$G$165) | J6: =SUMPRODUCT(($C$3:$C$165=C6)*$G$3:$G$165*$F$3:$F$165)/SUMPRODUCT(($C$3:$C$165=C6)*$G$3:$G$165) | K6: =I6/J6 | L6: =H6/I6 | M6: =F6/H6 | N6: =INDEX('4_UK_L1_Input'!$C$4:$C$14,MATCH($C6,'4_UK_L1_Input'!$A$4:$A$14,0))*K6*L6*M6 | O6: =INDEX('4_UK_L1_Input'!$D$4:$D$14,MATCH($C6,'4_UK_L1_Input'!$A$4:$A$14,0))*K6*L6*M6 | P6: 217770000 | Q6: 288850000 | R6: 3.17 | S6: =IFERROR(SUMPRODUCT(($E$3:$E$165=E6)*ISNUMBER($P$3:$P$165)*$P$3:$P$165*$F$3:$F$165)/SUMPRODUCT(($E$3:$E$165=E6)*ISNUMBER($P$3:$P$165)*$P$3:$P$165),"") | T6: =IFERROR(SUMPRODUCT(($D$3:$D$165=D6)*ISNUMBER($P$3:$P$165)*$P$3:$P$165*$F$3:$F$165)/SUMPRODUCT(($D$3:$D$165=D6)*ISNUMBER($P$3:$P$165)*$P$3:$P$165),"") | U6: =IFERROR(SUMPRODUCT(($C$3:$C$165=C6)*ISNUMBER($P$3:$P$165)*$P$3:$P$165*$F$3:$F$165)/SUMPRODUCT(($C$3:$C$165=C6)*ISNUMBER($P$3:$P$165)*$P$3:$P$165),"") | V6: =IF(OR(T6="",U6=""),"",T6/U6) | W6: =IF(OR(S6="",T6=""),"",S6/T6) | X6: =IF(S6="","",F6/S6) | Y6: =IF(V6="",N6,INDEX('4_UK_L1_Input'!$C$4:$C$14,MATCH($C6,'4_UK_L1_Input'!$A$4:$A$14,0))*V6*W6*X6) | Z6: =IF(V6="","BETA FALLBACK","REAL (Bloomberg UK)") | AA6: =IFERROR(SUMPRODUCT(($C$3:$C$165=C6)*ISNUMBER($R$3:$R$165)*$Q$3:$Q$165*IF(ISNUMBER($R$3:$R$165),$R$3:$R$165,0))/SUMPRODUCT(($C$3:$C$165=C6)*ISNUMBER($R$3:$R$165)*$Q$3:$Q$165),"") | AB6: =IF(OR(R6="",AA6=""),"",R6/AA6) | AC6: =IF(AB6="",O6,INDEX('4_UK_L1_Input'!$D$4:$D$14,MATCH($C6,'4_UK_L1_Input'!$A$4:$A$14,0))*AB6) | AD6: =IF(AB6="","BETA FALLBACK","REAL (Bloomberg UK)") | AE6: =Y6-N6 | AF6: =AC6-O6
A7: 10102030 | B7: Oil & Gas Refining & Marketing | C7: 10 | D7: 1010 | E7: 101020 | F7: 0.600078 | G7: 1 | H7: =SUMPRODUCT(($E$3:$E$165=E7)*$G$3:$G$165*$F$3:$F$165)/SUMPRODUCT(($E$3:$E$165=E7)*$G$3:$G$165) | I7: =SUMPRODUCT(($D$3:$D$165=D7)*$G$3:$G$165*$F$3:$F$165)/SUMPRODUCT(($D$3:$D$165=D7)*$G$3:$G$165) | J7: =SUMPRODUCT(($C$3:$C$165=C7)*$G$3:$G$165*$F$3:$F$165)/SUMPRODUCT(($C$3:$C$165=C7)*$G$3:$G$165) | K7: =I7/J7 | L7: =H7/I7 | M7: =F7/H7 | N7: =INDEX('4_UK_L1_Input'!$C$4:$C$14,MATCH($C7,'4_UK_L1_Input'!$A$4:$A$14,0))*K7*L7*M7 | O7: =INDEX('4_UK_L1_Input'!$D$4:$D$14,MATCH($C7,'4_UK_L1_Input'!$A$4:$A$14,0))*K7*L7*M7 | P7: 87000 | Q7: 22750000 | S7: =IFERROR(SUMPRODUCT(($E$3:$E$165=E7)*ISNUMBER($P$3:$P$165)*$P$3:$P$165*$F$3:$F$165)/SUMPRODUCT(($E$3:$E$165=E7)*ISNUMBER($P$3:$P$165)*$P$3:$P$165),"") | T7: =IFERROR(SUMPRODUCT(($D$3:$D$165=D7)*ISNUMBER($P$3:$P$165)*$P$3:$P$165*$F$3:$F$165)/SUMPRODUCT(($D$3:$D$165=D7)*ISNUMBER($P$3:$P$165)*$P$3:$P$165),"") | U7: =IFERROR(SUMPRODUCT(($C$3:$C$165=C7)*ISNUMBER($P$3:$P$165)*$P$3:$P$165*$F$3:$F$165)/SUMPRODUCT(($C$3:$C$165=C7)*ISNUMBER($P$3:$P$165)*$P$3:$P$165),"") | V7: =IF(OR(T7="",U7=""),"",T7/U7) | W7: =IF(OR(S7="",T7=""),"",S7/T7) | X7: =IF(S7="","",F7/S7) | Y7: =IF(V7="",N7,INDEX('4_UK_L1_Input'!$C$4:$C$14,MATCH($C7,'4_UK_L1_Input'!$A$4:$A$14,0))*V7*W7*X7) | Z7: =IF(V7="","BETA FALLBACK","REAL (Bloomberg UK)") | AA7: =IFERROR(SUMPRODUCT(($C$3:$C$165=C7)*ISNUMBER($R$3:$R$165)*$Q$3:$Q$165*IF(ISNUMBER($R$3:$R$165),$R$3:$R$165,0))/SUMPRODUCT(($C$3:$C$165=C7)*ISNUMBER($R$3:$R$165)*$Q$3:$Q$165),"") | AB7: =IF(OR(R7="",AA7=""),"",R7/AA7) | AC7: =IF(AB7="",O7,INDEX('4_UK_L1_Input'!$D$4:$D$14,MATCH($C7,'4_UK_L1_Input'!$A$4:$A$14,0))*AB7) | AD7: =IF(AB7="","BETA FALLBACK","REAL (Bloomberg UK)") | AE7: =Y7-N7 | AF7: =AC7-O7
A8: 10102040 | B8: Oil & Gas Storage & Transportation | C8: 10 | D8: 1010 | E8: 101020 | F8: 0.600078 | G8: 1 | H8: =SUMPRODUCT(($E$3:$E$165=E8)*$G$3:$G$165*$F$3:$F$165)/SUMPRODUCT(($E$3:$E$165=E8)*$G$3:$G$165) | I8: =SUMPRODUCT(($D$3:$D$165=D8)*$G$3:$G$165*$F$3:$F$165)/SUMPRODUCT(($D$3:$D$165=D8)*$G$3:$G$165) | J8: =SUMPRODUCT(($C$3:$C$165=C8)*$G$3:$G$165*$F$3:$F$165)/SUMPRODUCT(($C$3:$C$165=C8)*$G$3:$G$165) | K8: =I8/J8 | L8: =H8/I8 | M8: =F8/H8 | N8: =INDEX('4_UK_L1_Input'!$C$4:$C$14,MATCH($C8,'4_UK_L1_Input'!$A$4:$A$14,0))*K8*L8*M8 | O8: =INDEX('4_UK_L1_Input'!$D$4:$D$14,MATCH($C8,'4_UK_L1_Input'!$A$4:$A$14,0))*K8*L8*M8 | P8: 901710000 | Q8: 6580000000 | R8: 3.94 | S8: =IFERROR(SUMPRODUCT(($E$3:$E$165=E8)*ISNUMBER($P$3:$P$165)*$P$3:$P$165*$F$3:$F$165)/SUMPRODUCT(($E$3:$E$165=E8)*ISNUMBER($P$3:$P$165)*$P$3:$P$165),"") | T8: =IFERROR(SUMPRODUCT(($D$3:$D$165=D8)*ISNUMBER($P$3:$P$165)*$P$3:$P$165*$F$3:$F$165)/SUMPRODUCT(($D$3:$D$165=D8)*ISNUMBER($P$3:$P$165)*$P$3:$P$165),"") | U8: =IFERROR(SUMPRODUCT(($C$3:$C$165=C8)*ISNUMBER($P$3:$P$165)*$P$3:$P$165*$F$3:$F$165)/SUMPRODUCT(($C$3:$C$165=C8)*ISNUMBER($P$3:$P$165)*$P$3:$P$165),"") | V8: =IF(OR(T8="",U8=""),"",T8/U8) | W8: =IF(OR(S8="",T8=""),"",S8/T8) | X8: =IF(S8="","",F8/S8) | Y8: =IF(V8="",N8,INDEX('4_UK_L1_Input'!$C$4:$C$14,MATCH($C8,'4_UK_L1_Input'!$A$4:$A$14,0))*V8*W8*X8) | Z8: =IF(V8="","BETA FALLBACK","REAL (Bloomberg UK)") | AA8: =IFERROR(SUMPRODUCT(($C$3:$C$165=C8)*ISNUMBER($R$3:$R$165)*$Q$3:$Q$165*IF(ISNUMBER($R$3:$R$165),$R$3:$R$165,0))/SUMPRODUCT(($C$3:$C$165=C8)*ISNUMBER($R$3:$R$165)*$Q$3:$Q$165),"") | AB8: =IF(OR(R8="",AA8=""),"",R8/AA8) | AC8: =IF(AB8="",O8,INDEX('4_UK_L1_Input'!$D$4:$D$14,MATCH($C8,'4_UK_L1_Input'!$A$4:$A$14,0))*AB8) | AD8: =IF(AB8="","BETA FALLBACK","REAL (Bloomberg UK)") | AE8: =Y8-N8 | AF8: =AC8-O8
A9: 10102050 | B9: Coal & Consumable Fuels | C9: 10 | D9: 1010 | E9: 101020 | F9: 1.07418 | G9: 1 | H9: =SUMPRODUCT(($E$3:$E$165=E9)*$G$3:$G$165*$F$3:$F$165)/SUMPRODUCT(($E$3:$E$165=E9)*$G$3:$G$165) | I9: =SUMPRODUCT(($D$3:$D$165=D9)*$G$3:$G$165*$F$3:$F$165)/SUMPRODUCT(($D$3:$D$165=D9)*$G$3:$G$165) | J9: =SUMPRODUCT(($C$3:$C$165=C9)*$G$3:$G$165*$F$3:$F$165)/SUMPRODUCT(($C$3:$C$165=C9)*$G$3:$G$165) | K9: =I9/J9 | L9: =H9/I9 | M9: =F9/H9 | N9: =INDEX('4_UK_L1_Input'!$C$4:$C$14,MATCH($C9,'4_UK_L1_Input'!$A$4:$A$14,0))*K9*L9*M9 | O9: =INDEX('4_UK_L1_Input'!$D$4:$D$14,MATCH($C9,'4_UK_L1_Input'!$A$4:$A$14,0))*K9*L9*M9 | Q9: 210400000 | R9: 9.47 | S9: =IFERROR(SUMPRODUCT(($E$3:$E$165=E9)*ISNUMBER($P$3:$P$165)*$P$3:$P$165*$F$3:$F$165)/SUMPRODUCT(($E$3:$E$165=E9)*ISNUMBER($P$3:$P$165)*$P$3:$P$165),"") | T9: =IFERROR(SUMPRODUCT(($D$3:$D$165=D9)*ISNUMBER($P$3:$P$165)*$P$3:$P$165*$F$3:$F$165)/SUMPRODUCT(($D$3:$D$165=D9)*ISNUMBER($P$3:$P$165)*$P$3:$P$165),"") | U9: =IFERROR(SUMPRODUCT(($C$3:$C$165=C9)*ISNUMBER($P$3:$P$165)*$P$3:$P$165*$F$3:$F$165)/SUMPRODUCT(($C$3:$C$165=C9)*ISNUMBER($P$3:$P$165)*$P$3:$P$165),"") | V9: =IF(OR(T9="",U9=""),"",T9/U9) | W9: =IF(OR(S9="",T9=""),"",S9/T9) | X9: =IF(S9="","",F9/S9) | Y9: =IF(V9="",N9,INDEX('4_UK_L1_Input'!$C$4:$C$14,MATCH($C9,'4_UK_L1_Input'!$A$4:$A$14,0))*V9*W9*X9) | Z9: =IF(V9="","BETA FALLBACK","REAL (Bloomberg UK)") | AA9: =IFERROR(SUMPRODUCT(($C$3:$C$165=C9)*ISNUMBER($R$3:$R$165)*$Q$3:$Q$165*IF(ISNUMBER($R$3:$R$165),$R$3:$R$165,0))/SUMPRODUCT(($C$3:$C$165=C9)*ISNUMBER($R$3:$R$165)*$Q$3:$Q$165),"") | AB9: =IF(OR(R9="",AA9=""),"",R9/AA9) | AC9: =IF(AB9="",O9,INDEX('4_UK_L1_Input'!$D$4:$D$14,MATCH($C9,'4_UK_L1_Input'!$A$4:$A$14,0))*AB9) | AD9: =IF(AB9="","BETA FALLBACK","REAL (Bloomberg UK)") | AE9: =Y9-N9 | AF9: =AC9-O9
A10: 15101010 | B10: Commodity Chemicals | C10: 15 | D10: 1510 | E10: 151010 | F10: 0.704523 | G10: 1 | H10: =SUMPRODUCT(($E$3:$E$165=E10)*$G$3:$G$165*$F$3:$F$165)/SUMPRODUCT(($E$3:$E$165=E10)*$G$3:$G$165) | I10: =SUMPRODUCT(($D$3:$D$165=D10)*$G$3:$G$165*$F$3:$F$165)/SUMPRODUCT(($D$3:$D$165=D10)*$G$3:$G$165) | J10: =SUMPRODUCT(($C$3:$C$165=C10)*$G$3:$G$165*$F$3:$F$165)/SUMPRODUCT(($C$3:$C$165=C10)*$G$3:$G$165) | K10: =I10/J10 | L10: =H10/I10 | M10: =F10/H10 | N10: =INDEX('4_UK_L1_Input'!$C$4:$C$14,MATCH($C10,'4_UK_L1_Input'!$A$4:$A$14,0))*K10*L10*M10 | O10: =INDEX('4_UK_L1_Input'!$D$4:$D$14,MATCH($C10,'4_UK_L1_Input'!$A$4:$A$14,0))*K10*L10*M10 | P10: 246000000 | Q10: 266070000 | R10: 5.64 | S10: =IFERROR(SUMPRODUCT(($E$3:$E$165=E10)*ISNUMBER($P$3:$P$165)*$P$3:$P$165*$F$3:$F$165)/SUMPRODUCT(($E$3:$E$165=E10)*ISNUMBER($P$3:$P$165)*$P$3:$P$165),"") | T10: =IFERROR(SUMPRODUCT(($D$3:$D$165=D10)*ISNUMBER($P$3:$P$165)*$P$3:$P$165*$F$3:$F$165)/SUMPRODUCT(($D$3:$D$165=D10)*ISNUMBER($P$3:$P$165)*$P$3:$P$165),"") | U10: =IFERROR(SUMPRODUCT(($C$3:$C$165=C10)*ISNUMBER($P$3:$P$165)*$P$3:$P$165*$F$3:$F$165)/SUMPRODUCT(($C$3:$C$165=C10)*ISNUMBER($P$3:$P$165)*$P$3:$P$165),"") | V10: =IF(OR(T10="",U10=""),"",T10/U10) | W10: =IF(OR(S10="",T10=""),"",S10/T10) | X10: =IF(S10="","",F10/S10) | Y10: =IF(V10="",N10,INDEX('4_UK_L1_Input'!$C$4:$C$14,MATCH($C10,'4_UK_L1_Input'!$A$4:$A$14,0))*V10*W10*X10) | Z10: =IF(V10="","BETA FALLBACK","REAL (Bloomberg UK)") | AA10: =IFERROR(SUMPRODUCT(($C$3:$C$165=C10)*ISNUMBER($R$3:$R$165)*$Q$3:$Q$165*IF(ISNUMBER($R$3:$R$165),$R$3:$R$165,0))/SUMPRODUCT(($C$3:$C$165=C10)*ISNUMBER($R$3:$R$165)*$Q$3:$Q$165),"") | AB10: =IF(OR(R10="",AA10=""),"",R10/AA10) | AC10: =IF(AB10="",O10,INDEX('4_UK_L1_Input'!$D$4:$D$14,MATCH($C10,'4_UK_L1_Input'!$A$4:$A$14,0))*AB10) | AD10: =IF(AB10="","BETA FALLBACK","REAL (Bloomberg UK)") | AE10: =Y10-N10 | AF10: =AC10-O10
A11: 15101020 | B11: Diversified Chemicals | C11: 15 | D11: 1510 | E11: 151010 | F11: 0.759589 | G11: 1 | H11: =SUMPRODUCT(($E$3:$E$165=E11)*$G$3:$G$165*$F$3:$F$165)/SUMPRODUCT(($E$3:$E$165=E11)*$G$3:$G$165) | I11: =SUMPRODUCT(($D$3:$D$165=D11)*$G$3:$G$165*$F$3:$F$165)/SUMPRODUCT(($D$3:$D$165=D11)*$G$3:$G$165) | J11: =SUMPRODUCT(($C$3:$C$165=C11)*$G$3:$G$165*$F$3:$F$165)/SUMPRODUCT(($C$3:$C$165=C11)*$G$3:$G$165) | K11: =I11/J11 | L11: =H11/I11 | M11: =F11/H11 | N11: =INDEX('4_UK_L1_Input'!$C$4:$C$14,MATCH($C11,'4_UK_L1_Input'!$A$4:$A$14,0))*K11*L11*M11 | O11: =INDEX('4_UK_L1_Input'!$D$4:$D$14,MATCH($C11,'4_UK_L1_Input'!$A$4:$A$14,0))*K11*L11*M11 | S11: =IFERROR(SUMPRODUCT(($E$3:$E$165=E11)*ISNUMBER($P$3:$P$165)*$P$3:$P$165*$F$3:$F$165)/SUMPRODUCT(($E$3:$E$165=E11)*ISNUMBER($P$3:$P$165)*$P$3:$P$165),"") | T11: =IFERROR(SUMPRODUCT(($D$3:$D$165=D11)*ISNUMBER($P$3:$P$165)*$P$3:$P$165*$F$3:$F$165)/SUMPRODUCT(($D$3:$D$165=D11)*ISNUMBER($P$3:$P$165)*$P$3:$P$165),"") | U11: =IFERROR(SUMPRODUCT(($C$3:$C$165=C11)*ISNUMBER($P$3:$P$165)*$P$3:$P$165*$F$3:$F$165)/SUMPRODUCT(($C$3:$C$165=C11)*ISNUMBER($P$3:$P$165)*$P$3:$P$165),"") | V11: =IF(OR(T11="",U11=""),"",T11/U11) | W11: =IF(OR(S11="",T11=""),"",S11/T11) | X11: =IF(S11="","",F11/S11) | Y11: =IF(V11="",N11,INDEX('4_UK_L1_Input'!$C$4:$C$14,MATCH($C11,'4_UK_L1_Input'!$A$4:$A$14,0))*V11*W11*X11) | Z11: =IF(V11="","BETA FALLBACK","REAL (Bloomberg UK)") | AA11: =IFERROR(SUMPRODUCT(($C$3:$C$165=C11)*ISNUMBER($R$3:$R$165)*$Q$3:$Q$165*IF(ISNUMBER($R$3:$R$165),$R$3:$R$165,0))/SUMPRODUCT(($C$3:$C$165=C11)*ISNUMBER($R$3:$R$165)*$Q$3:$Q$165),"") | AB11: =IF(OR(R11="",AA11=""),"",R11/AA11) | AC11: =IF(AB11="",O11,INDEX('4_UK_L1_Input'!$D$4:$D$14,MATCH($C11,'4_UK_L1_Input'!$A$4:$A$14,0))*AB11) | AD11: =IF(AB11="","BETA FALLBACK","REAL (Bloomberg UK)") | AE11: =Y11-N11 | AF11: =AC11-O11
A12: 15101030 | B12: Fertilizers & Agricultural Chemicals | C12: 15 | D12: 1510 | E12: 151010 | F12: 0.704523 | G12: 1 | H12: =SUMPRODUCT(($E$3:$E$165=E12)*$G$3:$G$165*$F$3:$F$165)/SUMPRODUCT(($E$3:$E$165=E12)*$G$3:$G$165) | I12: =SUMPRODUCT(($D$3:$D$165=D12)*$G$3:$G$165*$F$3:$F$165)/SUMPRODUCT(($D$3:$D$165=D12)*$G$3:$G$165) | J12: =SUMPRODUCT(($C$3:$C$165=C12)*$G$3:$G$165*$F$3:$F$165)/SUMPRODUCT(($C$3:$C$165=C12)*$G$3:$G$165) | K12: =I12/J12 | L12: =H12/I12 | M12: =F12/H12 | N12: =INDEX('4_UK_L1_Input'!$C$4:$C$14,MATCH($C12,'4_UK_L1_Input'!$A$4:$A$14,0))*K12*L12*M12 | O12: =INDEX('4_UK_L1_Input'!$D$4:$D$14,MATCH($C12,'4_UK_L1_Input'!$A$4:$A$14,0))*K12*L12*M12 | P12: 21070000 | Q12: 20780000 | S12: =IFERROR(SUMPRODUCT(($E$3:$E$165=E12)*ISNUMBER($P$3:$P$165)*$P$3:$P$165*$F$3:$F$165)/SUMPRODUCT(($E$3:$E$165=E12)*ISNUMBER($P$3:$P$165)*$P$3:$P$165),"") | T12: =IFERROR(SUMPRODUCT(($D$3:$D$165=D12)*ISNUMBER($P$3:$P$165)*$P$3:$P$165*$F$3:$F$165)/SUMPRODUCT(($D$3:$D$165=D12)*ISNUMBER($P$3:$P$165)*$P$3:$P$165),"") | U12: =IFERROR(SUMPRODUCT(($C$3:$C$165=C12)*ISNUMBER($P$3:$P$165)*$P$3:$P$165*$F$3:$F$165)/SUMPRODUCT(($C$3:$C$165=C12)*ISNUMBER($P$3:$P$165)*$P$3:$P$165),"") | V12: =IF(OR(T12="",U12=""),"",T12/U12) | W12: =IF(OR(S12="",T12=""),"",S12/T12) | X12: =IF(S12="","",F12/S12) | Y12: =IF(V12="",N12,INDEX('4_UK_L1_Input'!$C$4:$C$14,MATCH($C12,'4_UK_L1_Input'!$A$4:$A$14,0))*V12*W12*X12) | Z12: =IF(V12="","BETA FALLBACK","REAL (Bloomberg UK)") | AA12: =IFERROR(SUMPRODUCT(($C$3:$C$165=C12)*ISNUMBER($R$3:$R$165)*$Q$3:$Q$165*IF(ISNUMBER($R$3:$R$165),$R$3:$R$165,0))/SUMPRODUCT(($C$3:$C$165=C12)*ISNUMBER($R$3:$R$165)*$Q$3:$Q$165),"") | AB12: =IF(OR(R12="",AA12=""),"",R12/AA12) | AC12: =IF(AB12="",O12,INDEX('4_UK_L1_Input'!$D$4:$D$14,MATCH($C12,'4_UK_L1_Input'!$A$4:$A$14,0))*AB12) | AD12: =IF(AB12="","BETA FALLBACK","REAL (Bloomberg UK)") | AE12: =Y12-N12 | AF12: =AC12-O12
A13: 15101040 | B13: Industrial Gases | C13: 15 | D13: 1510 | E13: 151010 | F13: 0.835557 | G13: 1 | H13: =SUMPRODUCT(($E$3:$E$165=E13)*$G$3:$G$165*$F$3:$F$165)/SUMPRODUCT(($E$3:$E$165=E13)*$G$3:$G$165) | I13: =SUMPRODUCT(($D$3:$D$165=D13)*$G$3:$G$165*$F$3:$F$165)/SUMPRODUCT(($D$3:$D$165=D13)*$G$3:$G$165) | J13: =SUMPRODUCT(($C$3:$C$165=C13)*$G$3:$G$165*$F$3:$F$165)/SUMPRODUCT(($C$3:$C$165=C13)*$G$3:$G$165) | K13: =I13/J13 | L13: =H13/I13 | M13: =F13/H13 | N13: =INDEX('4_UK_L1_Input'!$C$4:$C$14,MATCH($C13,'4_UK_L1_Input'!$A$4:$A$14,0))*K13*L13*M13 | O13: =INDEX('4_UK_L1_Input'!$D$4:$D$14,MATCH($C13,'4_UK_L1_Input'!$A$4:$A$14,0))*K13*L13*M13 | Q13: 44030000 | S13: =IFERROR(SUMPRODUCT(($E$3:$E$165=E13)*ISNUMBER($P$3:$P$165)*$P$3:$P$165*$F$3:$F$165)/SUMPRODUCT(($E$3:$E$165=E13)*ISNUMBER($P$3:$P$165)*$P$3:$P$165),"") | T13: =IFERROR(SUMPRODUCT(($D$3:$D$165=D13)*ISNUMBER($P$3:$P$165)*$P$3:$P$165*$F$3:$F$165)/SUMPRODUCT(($D$3:$D$165=D13)*ISNUMBER($P$3:$P$165)*$P$3:$P$165),"") | U13: =IFERROR(SUMPRODUCT(($C$3:$C$165=C13)*ISNUMBER($P$3:$P$165)*$P$3:$P$165*$F$3:$F$165)/SUMPRODUCT(($C$3:$C$165=C13)*ISNUMBER($P$3:$P$165)*$P$3:$P$165),"") | V13: =IF(OR(T13="",U13=""),"",T13/U13) | W13: =IF(OR(S13="",T13=""),"",S13/T13) | X13: =IF(S13="","",F13/S13) | Y13: =IF(V13="",N13,INDEX('4_UK_L1_Input'!$C$4:$C$14,MATCH($C13,'4_UK_L1_Input'!$A$4:$A$14,0))*V13*W13*X13) | Z13: =IF(V13="","BETA FALLBACK","REAL (Bloomberg UK)") | AA13: =IFERROR(SUMPRODUCT(($C$3:$C$165=C13)*ISNUMBER($R$3:$R$165)*$Q$3:$Q$165*IF(ISNUMBER($R$3:$R$165),$R$3:$R$165,0))/SUMPRODUCT(($C$3:$C$165=C13)*ISNUMBER($R$3:$R$165)*$Q$3:$Q$165),"") | AB13: =IF(OR(R13="",AA13=""),"",R13/AA13) | AC13: =IF(AB13="",O13,INDEX('4_UK_L1_Input'!$D$4:$D$14,MATCH($C13,'4_UK_L1_Input'!$A$4:$A$14,0))*AB13) | AD13: =IF(AB13="","BETA FALLBACK","REAL (Bloomberg UK)") | AE13: =Y13-N13 | AF13: =AC13-O13
A14: 15101050 | B14: Specialty Chemicals | C14: 15 | D14: 1510 | E14: 151010 | F14: 0.835557 | G14: 1 | H14: =SUMPRODUCT(($E$3:$E$165=E14)*$G$3:$G$165*$F$3:$F$165)/SUMPRODUCT(($E$3:$E$165=E14)*$G$3:$G$165) | I14: =SUMPRODUCT(($D$3:$D$165=D14)*$G$3:$G$165*$F$3:$F$165)/SUMPRODUCT(($D$3:$D$165=D14)*$G$3:$G$165) | J14: =SUMPRODUCT(($C$3:$C$165=C14)*$G$3:$G$165*$F$3:$F$165)/SUMPRODUCT(($C$3:$C$165=C14)*$G$3:$G$165) | K14: =I14/J14 | L14: =H14/I14 | M14: =F14/H14 | N14: =INDEX('4_UK_L1_Input'!$C$4:$C$14,MATCH($C14,'4_UK_L1_Input'!$A$4:$A$14,0))*K14*L14*M14 | O14: =INDEX('4_UK_L1_Input'!$D$4:$D$14,MATCH($C14,'4_UK_L1_Input'!$A$4:$A$14,0))*K14*L14*M14 | P14: 1590000000 | Q14: 876550000 | R14: 8.87 | S14: =IFERROR(SUMPRODUCT(($E$3:$E$165=E14)*ISNUMBER($P$3:$P$165)*$P$3:$P$165*$F$3:$F$165)/SUMPRODUCT(($E$3:$E$165=E14)*ISNUMBER($P$3:$P$165)*$P$3:$P$165),"") | T14: =IFERROR(SUMPRODUCT(($D$3:$D$165=D14)*ISNUMBER($P$3:$P$165)*$P$3:$P$165*$F$3:$F$165)/SUMPRODUCT(($D$3:$D$165=D14)*ISNUMBER($P$3:$P$165)*$P$3:$P$165),"") | U14: =IFERROR(SUMPRODUCT(($C$3:$C$165=C14)*ISNUMBER($P$3:$P$165)*$P$3:$P$165*$F$3:$F$165)/SUMPRODUCT(($C$3:$C$165=C14)*ISNUMBER($P$3:$P$165)*$P$3:$P$165),"") | V14: =IF(OR(T14="",U14=""),"",T14/U14) | W14: =IF(OR(S14="",T14=""),"",S14/T14) | X14: =IF(S14="","",F14/S14) | Y14: =IF(V14="",N14,INDEX('4_UK_L1_Input'!$C$4:$C$14,MATCH($C14,'4_UK_L1_Input'!$A$4:$A$14,0))*V14*W14*X14) | Z14: =IF(V14="","BETA FALLBACK","REAL (Bloomberg UK)") | AA14: =IFERROR(SUMPRODUCT(($C$3:$C$165=C14)*ISNUMBER($R$3:$R$165)*$Q$3:$Q$165*IF(ISNUMBER($R$3:$R$165),$R$3:$R$165,0))/SUMPRODUCT(($C$3:$C$165=C14)*ISNUMBER($R$3:$R$165)*$Q$3:$Q$165),"") | AB14: =IF(OR(R14="",AA14=""),"",R14/AA14) | AC14: =IF(AB14="",O14,INDEX('4_UK_L1_Input'!$D$4:$D$14,MATCH($C14,'4_UK_L1_Input'!$A$4:$A$14,0))*AB14) | AD14: =IF(AB14="","BETA FALLBACK","REAL (Bloomberg UK)") | AE14: =Y14-N14 | AF14: =AC14-O14
A15: 15102010 | B15: Construction Materials | C15: 15 | D15: 1510 | E15: 151020 | F15: 1.017657 | G15: 1 | H15: =SUMPRODUCT(($E$3:$E$165=E15)*$G$3:$G$165*$F$3:$F$165)/SUMPRODUCT(($E$3:$E$165=E15)*$G$3:$G$165) | I15: =SUMPRODUCT(($D$3:$D$165=D15)*$G$3:$G$165*$F$3:$F$165)/SUMPRODUCT(($D$3:$D$165=D15)*$G$3:$G$165) | J15: =SUMPRODUCT(($C$3:$C$165=C15)*$G$3:$G$165*$F$3:$F$165)/SUMPRODUCT(($C$3:$C$165=C15)*$G$3:$G$165) | K15: =I15/J15 | L15: =H15/I15 | M15: =F15/H15 | N15: =INDEX('4_UK_L1_Input'!$C$4:$C$14,MATCH($C15,'4_UK_L1_Input'!$A$4:$A$14,0))*K15*L15*M15 | O15: =INDEX('4_UK_L1_Input'!$D$4:$D$14,MATCH($C15,'4_UK_L1_Input'!$A$4:$A$14,0))*K15*L15*M15 | P15: 699210000 | Q15: 655910000 | R15: 6.57 | S15: =IFERROR(SUMPRODUCT(($E$3:$E$165=E15)*ISNUMBER($P$3:$P$165)*$P$3:$P$165*$F$3:$F$165)/SUMPRODUCT(($E$3:$E$165=E15)*ISNUMBER($P$3:$P$165)*$P$3:$P$165),"") | T15: =IFERROR(SUMPRODUCT(($D$3:$D$165=D15)*ISNUMBER($P$3:$P$165)*$P$3:$P$165*$F$3:$F$165)/SUMPRODUCT(($D$3:$D$165=D15)*ISNUMBER($P$3:$P$165)*$P$3:$P$165),"") | U15: =IFERROR(SUMPRODUCT(($C$3:$C$165=C15)*ISNUMBER($P$3:$P$165)*$P$3:$P$165*$F$3:$F$165)/SUMPRODUCT(($C$3:$C$165=C15)*ISNUMBER($P$3:$P$165)*$P$3:$P$165),"") | V15: =IF(OR(T15="",U15=""),"",T15/U15) | W15: =IF(OR(S15="",T15=""),"",S15/T15) | X15: =IF(S15="","",F15/S15) | Y15: =IF(V15="",N15,INDEX('4_UK_L1_Input'!$C$4:$C$14,MATCH($C15,'4_UK_L1_Input'!$A$4:$A$14,0))*V15*W15*X15) | Z15: =IF(V15="","BETA FALLBACK","REAL (Bloomberg UK)") | AA15: =IFERROR(SUMPRODUCT(($C$3:$C$165=C15)*ISNUMBER($R$3:$R$165)*$Q$3:$Q$165*IF(ISNUMBER($R$3:$R$165),$R$3:$R$165,0))/SUMPRODUCT(($C$3:$C$165=C15)*ISNUMBER($R$3:$R$165)*$Q$3:$Q$165),"") | AB15: =IF(OR(R15="",AA15=""),"",R15/AA15) | AC15: =IF(AB15="",O15,INDEX('4_UK_L1_Input'!$D$4:$D$14,MATCH($C15,'4_UK_L1_Input'!$A$4:$A$14,0))*AB15) | AD15: =IF(AB15="","BETA FALLBACK","REAL (Bloomberg UK)") | AE15: =Y15-N15 | AF15: =AC15-O15
A16: 15103010 | B16: Metal, Glass & Plastic Containers | C16: 15 | D16: 1510 | E16: 151030 | F16: 0.801397 | G16: 1 | H16: =SUMPRODUCT(($E$3:$E$165=E16)*$G$3:$G$165*$F$3:$F$165)/SUMPRODUCT(($E$3:$E$165=E16)*$G$3:$G$165) | I16: =SUMPRODUCT(($D$3:$D$165=D16)*$G$3:$G$165*$F$3:$F$165)/SUMPRODUCT(($D$3:$D$165=D16)*$G$3:$G$165) | J16: =SUMPRODUCT(($C$3:$C$165=C16)*$G$3:$G$165*$F$3:$F$165)/SUMPRODUCT(($C$3:$C$165=C16)*$G$3:$G$165) | K16: =I16/J16 | L16: =H16/I16 | M16: =F16/H16 | N16: =INDEX('4_UK_L1_Input'!$C$4:$C$14,MATCH($C16,'4_UK_L1_Input'!$A$4:$A$14,0))*K16*L16*M16 | O16: =INDEX('4_UK_L1_Input'!$D$4:$D$14,MATCH($C16,'4_UK_L1_Input'!$A$4:$A$14,0))*K16*L16*M16 | P16: 33260000 | Q16: 5110000 | S16: =IFERROR(SUMPRODUCT(($E$3:$E$165=E16)*ISNUMBER($P$3:$P$165)*$P$3:$P$165*$F$3:$F$165)/SUMPRODUCT(($E$3:$E$165=E16)*ISNUMBER($P$3:$P$165)*$P$3:$P$165),"") | T16: =IFERROR(SUMPRODUCT(($D$3:$D$165=D16)*ISNUMBER($P$3:$P$165)*$P$3:$P$165*$F$3:$F$165)/SUMPRODUCT(($D$3:$D$165=D16)*ISNUMBER($P$3:$P$165)*$P$3:$P$165),"") | U16: =IFERROR(SUMPRODUCT(($C$3:$C$165=C16)*ISNUMBER($P$3:$P$165)*$P$3:$P$165*$F$3:$F$165)/SUMPRODUCT(($C$3:$C$165=C16)*ISNUMBER($P$3:$P$165)*$P$3:$P$165),"") | V16: =IF(OR(T16="",U16=""),"",T16/U16) | W16: =IF(OR(S16="",T16=""),"",S16/T16) | X16: =IF(S16="","",F16/S16) | Y16: =IF(V16="",N16,INDEX('4_UK_L1_Input'!$C$4:$C$14,MATCH($C16,'4_UK_L1_Input'!$A$4:$A$14,0))*V16*W16*X16) | Z16: =IF(V16="","BETA FALLBACK","REAL (Bloomberg UK)") | AA16: =IFERROR(SUMPRODUCT(($C$3:$C$165=C16)*ISNUMBER($R$3:$R$165)*$Q$3:$Q$165*IF(ISNUMBER($R$3:$R$165),$R$3:$R$165,0))/SUMPRODUCT(($C$3:$C$165=C16)*ISNUMBER($R$3:$R$165)*$Q$3:$Q$165),"") | AB16: =IF(OR(R16="",AA16=""),"",R16/AA16) | AC16: =IF(AB16="",O16,INDEX('4_UK_L1_Input'!$D$4:$D$14,MATCH($C16,'4_UK_L1_Input'!$A$4:$A$14,0))*AB16) | AD16: =IF(AB16="","BETA FALLBACK","REAL (Bloomberg UK)") | AE16: =Y16-N16 | AF16: =AC16-O16
A17: 15103020 | B17: Paper & Plastic Packaging Products & Materials | C17: 15 | D17: 1510 | E17: 151030 | F17: 0.801397 | G17: 1 | H17: =SUMPRODUCT(($E$3:$E$165=E17)*$G$3:$G$165*$F$3:$F$165)/SUMPRODUCT(($E$3:$E$165=E17)*$G$3:$G$165) | I17: =SUMPRODUCT(($D$3:$D$165=D17)*$G$3:$G$165*$F$3:$F$165)/SUMPRODUCT(($D$3:$D$165=D17)*$G$3:$G$165) | J17: =SUMPRODUCT(($C$3:$C$165=C17)*$G$3:$G$165*$F$3:$F$165)/SUMPRODUCT(($C$3:$C$165=C17)*$G$3:$G$165) | K17: =I17/J17 | L17: =H17/I17 | M17: =F17/H17 | N17: =INDEX('4_UK_L1_Input'!$C$4:$C$14,MATCH($C17,'4_UK_L1_Input'!$A$4:$A$14,0))*K17*L17*M17 | O17: =INDEX('4_UK_L1_Input'!$D$4:$D$14,MATCH($C17,'4_UK_L1_Input'!$A$4:$A$14,0))*K17*L17*M17 | P17: 56210000 | Q17: 20940000 | R17: 3.38 | S17: =IFERROR(SUMPRODUCT(($E$3:$E$165=E17)*ISNUMBER($P$3:$P$165)*$P$3:$P$165*$F$3:$F$165)/SUMPRODUCT(($E$3:$E$165=E17)*ISNUMBER($P$3:$P$165)*$P$3:$P$165),"") | T17: =IFERROR(SUMPRODUCT(($D$3:$D$165=D17)*ISNUMBER($P$3:$P$165)*$P$3:$P$165*$F$3:$F$165)/SUMPRODUCT(($D$3:$D$165=D17)*ISNUMBER($P$3:$P$165)*$P$3:$P$165),"") | U17: =IFERROR(SUMPRODUCT(($C$3:$C$165=C17)*ISNUMBER($P$3:$P$165)*$P$3:$P$165*$F$3:$F$165)/SUMPRODUCT(($C$3:$C$165=C17)*ISNUMBER($P$3:$P$165)*$P$3:$P$165),"") | V17: =IF(OR(T17="",U17=""),"",T17/U17) | W17: =IF(OR(S17="",T17=""),"",S17/T17) | X17: =IF(S17="","",F17/S17) | Y17: =IF(V17="",N17,INDEX('4_UK_L1_Input'!$C$4:$C$14,MATCH($C17,'4_UK_L1_Input'!$A$4:$A$14,0))*V17*W17*X17) | Z17: =IF(V17="","BETA FALLBACK","REAL (Bloomberg UK)") | AA17: =IFERROR(SUMPRODUCT(($C$3:$C$165=C17)*ISNUMBER($R$3:$R$165)*$Q$3:$Q$165*IF(ISNUMBER($R$3:$R$165),$R$3:$R$165,0))/SUMPRODUCT(($C$3:$C$165=C17)*ISNUMBER($R$3:$R$165)*$Q$3:$Q$165),"") | AB17: =IF(OR(R17="",AA17=""),"",R17/AA17) | AC17: =IF(AB17="",O17,INDEX('4_UK_L1_Input'!$D$4:$D$14,MATCH($C17,'4_UK_L1_Input'!$A$4:$A$14,0))*AB17) | AD17: =IF(AB17="","BETA FALLBACK","REAL (Bloomberg UK)") | AE17: =Y17-N17 | AF17: =AC17-O17
A18: 15104010 | B18: Aluminum | C18: 15 | D18: 1510 | E18: 151040 | F18: 0.997259 | G18: 1 | H18: =SUMPRODUCT(($E$3:$E$165=E18)*$G$3:$G$165*$F$3:$F$165)/SUMPRODUCT(($E$3:$E$165=E18)*$G$3:$G$165) | I18: =SUMPRODUCT(($D$3:$D$165=D18)*$G$3:$G$165*$F$3:$F$165)/SUMPRODUCT(($D$3:$D$165=D18)*$G$3:$G$165) | J18: =SUMPRODUCT(($C$3:$C$165=C18)*$G$3:$G$165*$F$3:$F$165)/SUMPRODUCT(($C$3:$C$165=C18)*$G$3:$G$165) | K18: =I18/J18 | L18: =H18/I18 | M18: =F18/H18 | N18: =INDEX('4_UK_L1_Input'!$C$4:$C$14,MATCH($C18,'4_UK_L1_Input'!$A$4:$A$14,0))*K18*L18*M18 | O18: =INDEX('4_UK_L1_Input'!$D$4:$D$14,MATCH($C18,'4_UK_L1_Input'!$A$4:$A$14,0))*K18*L18*M18 | S18: =IFERROR(SUMPRODUCT(($E$3:$E$165=E18)*ISNUMBER($P$3:$P$165)*$P$3:$P$165*$F$3:$F$165)/SUMPRODUCT(($E$3:$E$165=E18)*ISNUMBER($P$3:$P$165)*$P$3:$P$165),"") | T18: =IFERROR(SUMPRODUCT(($D$3:$D$165=D18)*ISNUMBER($P$3:$P$165)*$P$3:$P$165*$F$3:$F$165)/SUMPRODUCT(($D$3:$D$165=D18)*ISNUMBER($P$3:$P$165)*$P$3:$P$165),"") | U18: =IFERROR(SUMPRODUCT(($C$3:$C$165=C18)*ISNUMBER($P$3:$P$165)*$P$3:$P$165*$F$3:$F$165)/SUMPRODUCT(($C$3:$C$165=C18)*ISNUMBER($P$3:$P$165)*$P$3:$P$165),"") | V18: =IF(OR(T18="",U18=""),"",T18/U18) | W18: =IF(OR(S18="",T18=""),"",S18/T18) | X18: =IF(S18="","",F18/S18) | Y18: =IF(V18="",N18,INDEX('4_UK_L1_Input'!$C$4:$C$14,MATCH($C18,'4_UK_L1_Input'!$A$4:$A$14,0))*V18*W18*X18) | Z18: =IF(V18="","BETA FALLBACK","REAL (Bloomberg UK)") | AA18: =IFERROR(SUMPRODUCT(($C$3:$C$165=C18)*ISNUMBER($R$3:$R$165)*$Q$3:$Q$165*IF(ISNUMBER($R$3:$R$165),$R$3:$R$165,0))/SUMPRODUCT(($C$3:$C$165=C18)*ISNUMBER($R$3:$R$165)*$Q$3:$Q$165),"") | AB18: =IF(OR(R18="",AA18=""),"",R18/AA18) | AC18: =IF(AB18="",O18,INDEX('4_UK_L1_Input'!$D$4:$D$14,MATCH($C18,'4_UK_L1_Input'!$A$4:$A$14,0))*AB18) | AD18: =IF(AB18="","BETA FALLBACK","REAL (Bloomberg UK)") | AE18: =Y18-N18 | AF18: =AC18-O18
A19: 15104020 | B19: Diversified Metals & Mining | C19: 15 | D19: 1510 | E19: 151040 | F19: 0.997259 | G19: 1 | H19: =SUMPRODUCT(($E$3:$E$165=E19)*$G$3:$G$165*$F$3:$F$165)/SUMPRODUCT(($E$3:$E$165=E19)*$G$3:$G$165) | I19: =SUMPRODUCT(($D$3:$D$165=D19)*$G$3:$G$165*$F$3:$F$165)/SUMPRODUCT(($D$3:$D$165=D19)*$G$3:$G$165) | J19: =SUMPRODUCT(($C$3:$C$165=C19)*$G$3:$G$165*$F$3:$F$165)/SUMPRODUCT(($C$3:$C$165=C19)*$G$3:$G$165) | K19: =I19/J19 | L19: =H19/I19 | M19: =F19/H19 | N19: =INDEX('4_UK_L1_Input'!$C$4:$C$14,MATCH($C19,'4_UK_L1_Input'!$A$4:$A$14,0))*K19*L19*M19 | O19: =INDEX('4_UK_L1_Input'!$D$4:$D$14,MATCH($C19,'4_UK_L1_Input'!$A$4:$A$14,0))*K19*L19*M19 | P19: 1930000000 | Q19: 3860000000 | R19: 5.94 | S19: =IFERROR(SUMPRODUCT(($E$3:$E$165=E19)*ISNUMBER($P$3:$P$165)*$P$3:$P$165*$F$3:$F$165)/SUMPRODUCT(($E$3:$E$165=E19)*ISNUMBER($P$3:$P$165)*$P$3:$P$165),"") | T19: =IFERROR(SUMPRODUCT(($D$3:$D$165=D19)*ISNUMBER($P$3:$P$165)*$P$3:$P$165*$F$3:$F$165)/SUMPRODUCT(($D$3:$D$165=D19)*ISNUMBER($P$3:$P$165)*$P$3:$P$165),"") | U19: =IFERROR(SUMPRODUCT(($C$3:$C$165=C19)*ISNUMBER($P$3:$P$165)*$P$3:$P$165*$F$3:$F$165)/SUMPRODUCT(($C$3:$C$165=C19)*ISNUMBER($P$3:$P$165)*$P$3:$P$165),"") | V19: =IF(OR(T19="",U19=""),"",T19/U19) | W19: =IF(OR(S19="",T19=""),"",S19/T19) | X19: =IF(S19="","",F19/S19) | Y19: =IF(V19="",N19,INDEX('4_UK_L1_Input'!$C$4:$C$14,MATCH($C19,'4_UK_L1_Input'!$A$4:$A$14,0))*V19*W19*X19) | Z19: =IF(V19="","BETA FALLBACK","REAL (Bloomberg UK)") | AA19: =IFERROR(SUMPRODUCT(($C$3:$C$165=C19)*ISNUMBER($R$3:$R$165)*$Q$3:$Q$165*IF(ISNUMBER($R$3:$R$165),$R$3:$R$165,0))/SUMPRODUCT(($C$3:$C$165=C19)*ISNUMBER($R$3:$R$165)*$Q$3:$Q$165),"") | AB19: =IF(OR(R19="",AA19=""),"",R19/AA19) | AC19: =IF(AB19="",O19,INDEX('4_UK_L1_Input'!$D$4:$D$14,MATCH($C19,'4_UK_L1_Input'!$A$4:$A$14,0))*AB19) | AD19: =IF(AB19="","BETA FALLBACK","REAL (Bloomberg UK)") | AE19: =Y19-N19 | AF19: =AC19-O19
A20: 15104025 | B20: Copper | C20: 15 | D20: 1510 | E20: 151040 | F20: 0.997259 | G20: 1 | H20: =SUMPRODUCT(($E$3:$E$165=E20)*$G$3:$G$165*$F$3:$F$165)/SUMPRODUCT(($E$3:$E$165=E20)*$G$3:$G$165) | I20: =SUMPRODUCT(($D$3:$D$165=D20)*$G$3:$G$165*$F$3:$F$165)/SUMPRODUCT(($D$3:$D$165=D20)*$G$3:$G$165) | J20: =SUMPRODUCT(($C$3:$C$165=C20)*$G$3:$G$165*$F$3:$F$165)/SUMPRODUCT(($C$3:$C$165=C20)*$G$3:$G$165) | K20: =I20/J20 | L20: =H20/I20 | M20: =F20/H20 | N20: =INDEX('4_UK_L1_Input'!$C$4:$C$14,MATCH($C20,'4_UK_L1_Input'!$A$4:$A$14,0))*K20*L20*M20 | O20: =INDEX('4_UK_L1_Input'!$D$4:$D$14,MATCH($C20,'4_UK_L1_Input'!$A$4:$A$14,0))*K20*L20*M20 | P20: 76620000 | Q20: 98500000 | R20: 1.5 | S20: =IFERROR(SUMPRODUCT(($E$3:$E$165=E20)*ISNUMBER($P$3:$P$165)*$P$3:$P$165*$F$3:$F$165)/SUMPRODUCT(($E$3:$E$165=E20)*ISNUMBER($P$3:$P$165)*$P$3:$P$165),"") | T20: =IFERROR(SUMPRODUCT(($D$3:$D$165=D20)*ISNUMBER($P$3:$P$165)*$P$3:$P$165*$F$3:$F$165)/SUMPRODUCT(($D$3:$D$165=D20)*ISNUMBER($P$3:$P$165)*$P$3:$P$165),"") | U20: =IFERROR(SUMPRODUCT(($C$3:$C$165=C20)*ISNUMBER($P$3:$P$165)*$P$3:$P$165*$F$3:$F$165)/SUMPRODUCT(($C$3:$C$165=C20)*ISNUMBER($P$3:$P$165)*$P$3:$P$165),"") | V20: =IF(OR(T20="",U20=""),"",T20/U20) | W20: =IF(OR(S20="",T20=""),"",S20/T20) | X20: =IF(S20="","",F20/S20) | Y20: =IF(V20="",N20,INDEX('4_UK_L1_Input'!$C$4:$C$14,MATCH($C20,'4_UK_L1_Input'!$A$4:$A$14,0))*V20*W20*X20) | Z20: =IF(V20="","BETA FALLBACK","REAL (Bloomberg UK)") | AA20: =IFERROR(SUMPRODUCT(($C$3:$C$165=C20)*ISNUMBER($R$3:$R$165)*$Q$3:$Q$165*IF(ISNUMBER($R$3:$R$165),$R$3:$R$165,0))/SUMPRODUCT(($C$3:$C$165=C20)*ISNUMBER($R$3:$R$165)*$Q$3:$Q$165),"") | AB20: =IF(OR(R20="",AA20=""),"",R20/AA20) | AC20: =IF(AB20="",O20,INDEX('4_UK_L1_Input'!$D$4:$D$14,MATCH($C20,'4_UK_L1_Input'!$A$4:$A$14,0))*AB20) | AD20: =IF(AB20="","BETA FALLBACK","REAL (Bloomberg UK)") | AE20: =Y20-N20 | AF20: =AC20-O20
A21: 15104030 | B21: Gold | C21: 15 | D21: 1510 | E21: 151040 | F21: 0.841513 | G21: 1 | H21: =SUMPRODUCT(($E$3:$E$165=E21)*$G$3:$G$165*$F$3:$F$165)/SUMPRODUCT(($E$3:$E$165=E21)*$G$3:$G$165) | I21: =SUMPRODUCT(($D$3:$D$165=D21)*$G$3:$G$165*$F$3:$F$165)/SUMPRODUCT(($D$3:$D$165=D21)*$G$3:$G$165) | J21: =SUMPRODUCT(($C$3:$C$165=C21)*$G$3:$G$165*$F$3:$F$165)/SUMPRODUCT(($C$3:$C$165=C21)*$G$3:$G$165) | K21: =I21/J21 | L21: =H21/I21 | M21: =F21/H21 | N21: =INDEX('4_UK_L1_Input'!$C$4:$C$14,MATCH($C21,'4_UK_L1_Input'!$A$4:$A$14,0))*K21*L21*M21 | O21: =INDEX('4_UK_L1_Input'!$D$4:$D$14,MATCH($C21,'4_UK_L1_Input'!$A$4:$A$14,0))*K21*L21*M21 | P21: 410600000 | Q21: 1430000000 | R21: 4.23 | S21: =IFERROR(SUMPRODUCT(($E$3:$E$165=E21)*ISNUMBER($P$3:$P$165)*$P$3:$P$165*$F$3:$F$165)/SUMPRODUCT(($E$3:$E$165=E21)*ISNUMBER($P$3:$P$165)*$P$3:$P$165),"") | T21: =IFERROR(SUMPRODUCT(($D$3:$D$165=D21)*ISNUMBER($P$3:$P$165)*$P$3:$P$165*$F$3:$F$165)/SUMPRODUCT(($D$3:$D$165=D21)*ISNUMBER($P$3:$P$165)*$P$3:$P$165),"") | U21: =IFERROR(SUMPRODUCT(($C$3:$C$165=C21)*ISNUMBER($P$3:$P$165)*$P$3:$P$165*$F$3:$F$165)/SUMPRODUCT(($C$3:$C$165=C21)*ISNUMBER($P$3:$P$165)*$P$3:$P$165),"") | V21: =IF(OR(T21="",U21=""),"",T21/U21) | W21: =IF(OR(S21="",T21=""),"",S21/T21) | X21: =IF(S21="","",F21/S21) | Y21: =IF(V21="",N21,INDEX('4_UK_L1_Input'!$C$4:$C$14,MATCH($C21,'4_UK_L1_Input'!$A$4:$A$14,0))*V21*W21*X21) | Z21: =IF(V21="","BETA FALLBACK","REAL (Bloomberg UK)") | AA21: =IFERROR(SUMPRODUCT(($C$3:$C$165=C21)*ISNUMBER($R$3:$R$165)*$Q$3:$Q$165*IF(ISNUMBER($R$3:$R$165),$R$3:$R$165,0))/SUMPRODUCT(($C$3:$C$165=C21)*ISNUMBER($R$3:$R$165)*$Q$3:$Q$165),"") | AB21: =IF(OR(R21="",AA21=""),"",R21/AA21) | AC21: =IF(AB21="",O21,INDEX('4_UK_L1_Input'!$D$4:$D$14,MATCH($C21,'4_UK_L1_Input'!$A$4:$A$14,0))*AB21) | AD21: =IF(AB21="","BETA FALLBACK","REAL (Bloomberg UK)") | AE21: =Y21-N21 | AF21: =AC21-O21
A22: 15104040 | B22: Precious Metals & Minerals | C22: 15 | D22: 1510 | E22: 151040 | F22: 0.841513 | G22: 1 | H22: =SUMPRODUCT(($E$3:$E$165=E22)*$G$3:$G$165*$F$3:$F$165)/SUMPRODUCT(($E$3:$E$165=E22)*$G$3:$G$165) | I22: =SUMPRODUCT(($D$3:$D$165=D22)*$G$3:$G$165*$F$3:$F$165)/SUMPRODUCT(($D$3:$D$165=D22)*$G$3:$G$165) | J22: =SUMPRODUCT(($C$3:$C$165=C22)*$G$3:$G$165*$F$3:$F$165)/SUMPRODUCT(($C$3:$C$165=C22)*$G$3:$G$165) | K22: =I22/J22 | L22: =H22/I22 | M22: =F22/H22 | N22: =INDEX('4_UK_L1_Input'!$C$4:$C$14,MATCH($C22,'4_UK_L1_Input'!$A$4:$A$14,0))*K22*L22*M22 | O22: =INDEX('4_UK_L1_Input'!$D$4:$D$14,MATCH($C22,'4_UK_L1_Input'!$A$4:$A$14,0))*K22*L22*M22 | P22: 20970000 | Q22: 32640000 | S22: =IFERROR(SUMPRODUCT(($E$3:$E$165=E22)*ISNUMBER($P$3:$P$165)*$P$3:$P$165*$F$3:$F$165)/SUMPRODUCT(($E$3:$E$165=E22)*ISNUMBER($P$3:$P$165)*$P$3:$P$165),"") | T22: =IFERROR(SUMPRODUCT(($D$3:$D$165=D22)*ISNUMBER($P$3:$P$165)*$P$3:$P$165*$F$3:$F$165)/SUMPRODUCT(($D$3:$D$165=D22)*ISNUMBER($P$3:$P$165)*$P$3:$P$165),"") | U22: =IFERROR(SUMPRODUCT(($C$3:$C$165=C22)*ISNUMBER($P$3:$P$165)*$P$3:$P$165*$F$3:$F$165)/SUMPRODUCT(($C$3:$C$165=C22)*ISNUMBER($P$3:$P$165)*$P$3:$P$165),"") | V22: =IF(OR(T22="",U22=""),"",T22/U22) | W22: =IF(OR(S22="",T22=""),"",S22/T22) | X22: =IF(S22="","",F22/S22) | Y22: =IF(V22="",N22,INDEX('4_UK_L1_Input'!$C$4:$C$14,MATCH($C22,'4_UK_L1_Input'!$A$4:$A$14,0))*V22*W22*X22) | Z22: =IF(V22="","BETA FALLBACK","REAL (Bloomberg UK)") | AA22: =IFERROR(SUMPRODUCT(($C$3:$C$165=C22)*ISNUMBER($R$3:$R$165)*$Q$3:$Q$165*IF(ISNUMBER($R$3:$R$165),$R$3:$R$165,0))/SUMPRODUCT(($C$3:$C$165=C22)*ISNUMBER($R$3:$R$165)*$Q$3:$Q$165),"") | AB22: =IF(OR(R22="",AA22=""),"",R22/AA22) | AC22: =IF(AB22="",O22,INDEX('4_UK_L1_Input'!$D$4:$D$14,MATCH($C22,'4_UK_L1_Input'!$A$4:$A$14,0))*AB22) | AD22: =IF(AB22="","BETA FALLBACK","REAL (Bloomberg UK)") | AE22: =Y22-N22 | AF22: =AC22-O22
A23: 15104045 | B23: Silver | C23: 15 | D23: 1510 | E23: 151040 | F23: 0.841513 | G23: 1 | H23: =SUMPRODUCT(($E$3:$E$165=E23)*$G$3:$G$165*$F$3:$F$165)/SUMPRODUCT(($E$3:$E$165=E23)*$G$3:$G$165) | I23: =SUMPRODUCT(($D$3:$D$165=D23)*$G$3:$G$165*$F$3:$F$165)/SUMPRODUCT(($D$3:$D$165=D23)*$G$3:$G$165) | J23: =SUMPRODUCT(($C$3:$C$165=C23)*$G$3:$G$165*$F$3:$F$165)/SUMPRODUCT(($C$3:$C$165=C23)*$G$3:$G$165) | K23: =I23/J23 | L23: =H23/I23 | M23: =F23/H23 | N23: =INDEX('4_UK_L1_Input'!$C$4:$C$14,MATCH($C23,'4_UK_L1_Input'!$A$4:$A$14,0))*K23*L23*M23 | O23: =INDEX('4_UK_L1_Input'!$D$4:$D$14,MATCH($C23,'4_UK_L1_Input'!$A$4:$A$14,0))*K23*L23*M23 | S23: =IFERROR(SUMPRODUCT(($E$3:$E$165=E23)*ISNUMBER($P$3:$P$165)*$P$3:$P$165*$F$3:$F$165)/SUMPRODUCT(($E$3:$E$165=E23)*ISNUMBER($P$3:$P$165)*$P$3:$P$165),"") | T23: =IFERROR(SUMPRODUCT(($D$3:$D$165=D23)*ISNUMBER($P$3:$P$165)*$P$3:$P$165*$F$3:$F$165)/SUMPRODUCT(($D$3:$D$165=D23)*ISNUMBER($P$3:$P$165)*$P$3:$P$165),"") | U23: =IFERROR(SUMPRODUCT(($C$3:$C$165=C23)*ISNUMBER($P$3:$P$165)*$P$3:$P$165*$F$3:$F$165)/SUMPRODUCT(($C$3:$C$165=C23)*ISNUMBER($P$3:$P$165)*$P$3:$P$165),"") | V23: =IF(OR(T23="",U23=""),"",T23/U23) | W23: =IF(OR(S23="",T23=""),"",S23/T23) | X23: =IF(S23="","",F23/S23) | Y23: =IF(V23="",N23,INDEX('4_UK_L1_Input'!$C$4:$C$14,MATCH($C23,'4_UK_L1_Input'!$A$4:$A$14,0))*V23*W23*X23) | Z23: =IF(V23="","BETA FALLBACK","REAL (Bloomberg UK)") | AA23: =IFERROR(SUMPRODUCT(($C$3:$C$165=C23)*ISNUMBER($R$3:$R$165)*$Q$3:$Q$165*IF(ISNUMBER($R$3:$R$165),$R$3:$R$165,0))/SUMPRODUCT(($C$3:$C$165=C23)*ISNUMBER($R$3:$R$165)*$Q$3:$Q$165),"") | AB23: =IF(OR(R23="",AA23=""),"",R23/AA23) | AC23: =IF(AB23="",O23,INDEX('4_UK_L1_Input'!$D$4:$D$14,MATCH($C23,'4_UK_L1_Input'!$A$4:$A$14,0))*AB23) | AD23: =IF(AB23="","BETA FALLBACK","REAL (Bloomberg UK)") | AE23: =Y23-N23 | AF23: =AC23-O23
A24: 15104050 | B24: Steel | C24: 15 | D24: 1510 | E24: 151040 | F24: 0.929779 | G24: 1 | H24: =SUMPRODUCT(($E$3:$E$165=E24)*$G$3:$G$165*$F$3:$F$165)/SUMPRODUCT(($E$3:$E$165=E24)*$G$3:$G$165) | I24: =SUMPRODUCT(($D$3:$D$165=D24)*$G$3:$G$165*$F$3:$F$165)/SUMPRODUCT(($D$3:$D$165=D24)*$G$3:$G$165) | J24: =SUMPRODUCT(($C$3:$C$165=C24)*$G$3:$G$165*$F$3:$F$165)/SUMPRODUCT(($C$3:$C$165=C24)*$G$3:$G$165) | K24: =I24/J24 | L24: =H24/I24 | M24: =F24/H24 | N24: =INDEX('4_UK_L1_Input'!$C$4:$C$14,MATCH($C24,'4_UK_L1_Input'!$A$4:$A$14,0))*K24*L24*M24 | O24: =INDEX('4_UK_L1_Input'!$D$4:$D$14,MATCH($C24,'4_UK_L1_Input'!$A$4:$A$14,0))*K24*L24*M24 | P24: 229700000 | Q24: 509320000 | R24: 10.16 | S24: =IFERROR(SUMPRODUCT(($E$3:$E$165=E24)*ISNUMBER($P$3:$P$165)*$P$3:$P$165*$F$3:$F$165)/SUMPRODUCT(($E$3:$E$165=E24)*ISNUMBER($P$3:$P$165)*$P$3:$P$165),"") | T24: =IFERROR(SUMPRODUCT(($D$3:$D$165=D24)*ISNUMBER($P$3:$P$165)*$P$3:$P$165*$F$3:$F$165)/SUMPRODUCT(($D$3:$D$165=D24)*ISNUMBER($P$3:$P$165)*$P$3:$P$165),"") | U24: =IFERROR(SUMPRODUCT(($C$3:$C$165=C24)*ISNUMBER($P$3:$P$165)*$P$3:$P$165*$F$3:$F$165)/SUMPRODUCT(($C$3:$C$165=C24)*ISNUMBER($P$3:$P$165)*$P$3:$P$165),"") | V24: =IF(OR(T24="",U24=""),"",T24/U24) | W24: =IF(OR(S24="",T24=""),"",S24/T24) | X24: =IF(S24="","",F24/S24) | Y24: =IF(V24="",N24,INDEX('4_UK_L1_Input'!$C$4:$C$14,MATCH($C24,'4_UK_L1_Input'!$A$4:$A$14,0))*V24*W24*X24) | Z24: =IF(V24="","BETA FALLBACK","REAL (Bloomberg UK)") | AA24: =IFERROR(SUMPRODUCT(($C$3:$C$165=C24)*ISNUMBER($R$3:$R$165)*$Q$3:$Q$165*IF(ISNUMBER($R$3:$R$165),$R$3:$R$165,0))/SUMPRODUCT(($C$3:$C$165=C24)*ISNUMBER($R$3:$R$165)*$Q$3:$Q$165),"") | AB24: =IF(OR(R24="",AA24=""),"",R24/AA24) | AC24: =IF(AB24="",O24,INDEX('4_UK_L1_Input'!$D$4:$D$14,MATCH($C24,'4_UK_L1_Input'!$A$4:$A$14,0))*AB24) | AD24: =IF(AB24="","BETA FALLBACK","REAL (Bloomberg UK)") | AE24: =Y24-N24 | AF24: =AC24-O24
A25: 15105010 | B25: Forest Products | C25: 15 | D25: 1510 | E25: 151050 | F25: 0.851733 | G25: 1 | H25: =SUMPRODUCT(($E$3:$E$165=E25)*$G$3:$G$165*$F$3:$F$165)/SUMPRODUCT(($E$3:$E$165=E25)*$G$3:$G$165) | I25: =SUMPRODUCT(($D$3:$D$165=D25)*$G$3:$G$165*$F$3:$F$165)/SUMPRODUCT(($D$3:$D$165=D25)*$G$3:$G$165) | J25: =SUMPRODUCT(($C$3:$C$165=C25)*$G$3:$G$165*$F$3:$F$165)/SUMPRODUCT(($C$3:$C$165=C25)*$G$3:$G$165) | K25: =I25/J25 | L25: =H25/I25 | M25: =F25/H25 | N25: =INDEX('4_UK_L1_Input'!$C$4:$C$14,MATCH($C25,'4_UK_L1_Input'!$A$4:$A$14,0))*K25*L25*M25 | O25: =INDEX('4_UK_L1_Input'!$D$4:$D$14,MATCH($C25,'4_UK_L1_Input'!$A$4:$A$14,0))*K25*L25*M25 | P25: 153280000 | Q25: 170210000 | R25: 9.59 | S25: =IFERROR(SUMPRODUCT(($E$3:$E$165=E25)*ISNUMBER($P$3:$P$165)*$P$3:$P$165*$F$3:$F$165)/SUMPRODUCT(($E$3:$E$165=E25)*ISNUMBER($P$3:$P$165)*$P$3:$P$165),"") | T25: =IFERROR(SUMPRODUCT(($D$3:$D$165=D25)*ISNUMBER($P$3:$P$165)*$P$3:$P$165*$F$3:$F$165)/SUMPRODUCT(($D$3:$D$165=D25)*ISNUMBER($P$3:$P$165)*$P$3:$P$165),"") | U25: =IFERROR(SUMPRODUCT(($C$3:$C$165=C25)*ISNUMBER($P$3:$P$165)*$P$3:$P$165*$F$3:$F$165)/SUMPRODUCT(($C$3:$C$165=C25)*ISNUMBER($P$3:$P$165)*$P$3:$P$165),"") | V25: =IF(OR(T25="",U25=""),"",T25/U25) | W25: =IF(OR(S25="",T25=""),"",S25/T25) | X25: =IF(S25="","",F25/S25) | Y25: =IF(V25="",N25,INDEX('4_UK_L1_Input'!$C$4:$C$14,MATCH($C25,'4_UK_L1_Input'!$A$4:$A$14,0))*V25*W25*X25) | Z25: =IF(V25="","BETA FALLBACK","REAL (Bloomberg UK)") | AA25: =IFERROR(SUMPRODUCT(($C$3:$C$165=C25)*ISNUMBER($R$3:$R$165)*$Q$3:$Q$165*IF(ISNUMBER($R$3:$R$165),$R$3:$R$165,0))/SUMPRODUCT(($C$3:$C$165=C25)*ISNUMBER($R$3:$R$165)*$Q$3:$Q$165),"") | AB25: =IF(OR(R25="",AA25=""),"",R25/AA25) | AC25: =IF(AB25="",O25,INDEX('4_UK_L1_Input'!$D$4:$D$14,MATCH($C25,'4_UK_L1_Input'!$A$4:$A$14,0))*AB25) | AD25: =IF(AB25="","BETA FALLBACK","REAL (Bloomberg UK)") | AE25: =Y25-N25 | AF25: =AC25-O25
A26: 15105020 | B26: Paper Products | C26: 15 | D26: 1510 | E26: 151050 | F26: 0.851733 | G26: 1 | H26: =SUMPRODUCT(($E$3:$E$165=E26)*$G$3:$G$165*$F$3:$F$165)/SUMPRODUCT(($E$3:$E$165=E26)*$G$3:$G$165) | I26: =SUMPRODUCT(($D$3:$D$165=D26)*$G$3:$G$165*$F$3:$F$165)/SUMPRODUCT(($D$3:$D$165=D26)*$G$3:$G$165) | J26: =SUMPRODUCT(($C$3:$C$165=C26)*$G$3:$G$165*$F$3:$F$165)/SUMPRODUCT(($C$3:$C$165=C26)*$G$3:$G$165) | K26: =I26/J26 | L26: =H26/I26 | M26: =F26/H26 | N26: =INDEX('4_UK_L1_Input'!$C$4:$C$14,MATCH($C26,'4_UK_L1_Input'!$A$4:$A$14,0))*K26*L26*M26 | O26: =INDEX('4_UK_L1_Input'!$D$4:$D$14,MATCH($C26,'4_UK_L1_Input'!$A$4:$A$14,0))*K26*L26*M26 | P26: 3920000000 | Q26: 2060000000 | R26: 6.56 | S26: =IFERROR(SUMPRODUCT(($E$3:$E$165=E26)*ISNUMBER($P$3:$P$165)*$P$3:$P$165*$F$3:$F$165)/SUMPRODUCT(($E$3:$E$165=E26)*ISNUMBER($P$3:$P$165)*$P$3:$P$165),"") | T26: =IFERROR(SUMPRODUCT(($D$3:$D$165=D26)*ISNUMBER($P$3:$P$165)*$P$3:$P$165*$F$3:$F$165)/SUMPRODUCT(($D$3:$D$165=D26)*ISNUMBER($P$3:$P$165)*$P$3:$P$165),"") | U26: =IFERROR(SUMPRODUCT(($C$3:$C$165=C26)*ISNUMBER($P$3:$P$165)*$P$3:$P$165*$F$3:$F$165)/SUMPRODUCT(($C$3:$C$165=C26)*ISNUMBER($P$3:$P$165)*$P$3:$P$165),"") | V26: =IF(OR(T26="",U26=""),"",T26/U26) | W26: =IF(OR(S26="",T26=""),"",S26/T26) | X26: =IF(S26="","",F26/S26) | Y26: =IF(V26="",N26,INDEX('4_UK_L1_Input'!$C$4:$C$14,MATCH($C26,'4_UK_L1_Input'!$A$4:$A$14,0))*V26*W26*X26) | Z26: =IF(V26="","BETA FALLBACK","REAL (Bloomberg UK)") | AA26: =IFERROR(SUMPRODUCT(($C$3:$C$165=C26)*ISNUMBER($R$3:$R$165)*$Q$3:$Q$165*IF(ISNUMBER($R$3:$R$165),$R$3:$R$165,0))/SUMPRODUCT(($C$3:$C$165=C26)*ISNUMBER($R$3:$R$165)*$Q$3:$Q$165),"") | AB26: =IF(OR(R26="",AA26=""),"",R26/AA26) | AC26: =IF(AB26="",O26,INDEX('4_UK_L1_Input'!$D$4:$D$14,MATCH($C26,'4_UK_L1_Input'!$A$4:$A$14,0))*AB26) | AD26: =IF(AB26="","BETA FALLBACK","REAL (Bloomberg UK)") | AE26: =Y26-N26 | AF26: =AC26-O26
A27: 20101010 | B27: Aerospace & Defense | C27: 20 | D27: 2010 | E27: 201010 | F27: 0.872927 | G27: 1 | H27: =SUMPRODUCT(($E$3:$E$165=E27)*$G$3:$G$165*$F$3:$F$165)/SUMPRODUCT(($E$3:$E$165=E27)*$G$3:$G$165) | I27: =SUMPRODUCT(($D$3:$D$165=D27)*$G$3:$G$165*$F$3:$F$165)/SUMPRODUCT(($D$3:$D$165=D27)*$G$3:$G$165) | J27: =SUMPRODUCT(($C$3:$C$165=C27)*$G$3:$G$165*$F$3:$F$165)/SUMPRODUCT(($C$3:$C$165=C27)*$G$3:$G$165) | K27: =I27/J27 | L27: =H27/I27 | M27: =F27/H27 | N27: =INDEX('4_UK_L1_Input'!$C$4:$C$14,MATCH($C27,'4_UK_L1_Input'!$A$4:$A$14,0))*K27*L27*M27 | O27: =INDEX('4_UK_L1_Input'!$D$4:$D$14,MATCH($C27,'4_UK_L1_Input'!$A$4:$A$14,0))*K27*L27*M27 | P27: 4670000000 | Q27: 15250000000 | R27: 13.03 | S27: =IFERROR(SUMPRODUCT(($E$3:$E$165=E27)*ISNUMBER($P$3:$P$165)*$P$3:$P$165*$F$3:$F$165)/SUMPRODUCT(($E$3:$E$165=E27)*ISNUMBER($P$3:$P$165)*$P$3:$P$165),"") | T27: =IFERROR(SUMPRODUCT(($D$3:$D$165=D27)*ISNUMBER($P$3:$P$165)*$P$3:$P$165*$F$3:$F$165)/SUMPRODUCT(($D$3:$D$165=D27)*ISNUMBER($P$3:$P$165)*$P$3:$P$165),"") | U27: =IFERROR(SUMPRODUCT(($C$3:$C$165=C27)*ISNUMBER($P$3:$P$165)*$P$3:$P$165*$F$3:$F$165)/SUMPRODUCT(($C$3:$C$165=C27)*ISNUMBER($P$3:$P$165)*$P$3:$P$165),"") | V27: =IF(OR(T27="",U27=""),"",T27/U27) | W27: =IF(OR(S27="",T27=""),"",S27/T27) | X27: =IF(S27="","",F27/S27) | Y27: =IF(V27="",N27,INDEX('4_UK_L1_Input'!$C$4:$C$14,MATCH($C27,'4_UK_L1_Input'!$A$4:$A$14,0))*V27*W27*X27) | Z27: =IF(V27="","BETA FALLBACK","REAL (Bloomberg UK)") | AA27: =IFERROR(SUMPRODUCT(($C$3:$C$165=C27)*ISNUMBER($R$3:$R$165)*$Q$3:$Q$165*IF(ISNUMBER($R$3:$R$165),$R$3:$R$165,0))/SUMPRODUCT(($C$3:$C$165=C27)*ISNUMBER($R$3:$R$165)*$Q$3:$Q$165),"") | AB27: =IF(OR(R27="",AA27=""),"",R27/AA27) | AC27: =IF(AB27="",O27,INDEX('4_UK_L1_Input'!$D$4:$D$14,MATCH($C27,'4_UK_L1_Input'!$A$4:$A$14,0))*AB27) | AD27: =IF(AB27="","BETA FALLBACK","REAL (Bloomberg UK)") | AE27: =Y27-N27 | AF27: =AC27-O27
A28: 20102010 | B28: Building Products | C28: 20 | D28: 2010 | E28: 201020 | F28: 0.948849 | G28: 1 | H28: =SUMPRODUCT(($E$3:$E$165=E28)*$G$3:$G$165*$F$3:$F$165)/SUMPRODUCT(($E$3:$E$165=E28)*$G$3:$G$165) | I28: =SUMPRODUCT(($D$3:$D$165=D28)*$G$3:$G$165*$F$3:$F$165)/SUMPRODUCT(($D$3:$D$165=D28)*$G$3:$G$165) | J28: =SUMPRODUCT(($C$3:$C$165=C28)*$G$3:$G$165*$F$3:$F$165)/SUMPRODUCT(($C$3:$C$165=C28)*$G$3:$G$165) | K28: =I28/J28 | L28: =H28/I28 | M28: =F28/H28 | N28: =INDEX('4_UK_L1_Input'!$C$4:$C$14,MATCH($C28,'4_UK_L1_Input'!$A$4:$A$14,0))*K28*L28*M28 | O28: =INDEX('4_UK_L1_Input'!$D$4:$D$14,MATCH($C28,'4_UK_L1_Input'!$A$4:$A$14,0))*K28*L28*M28 | P28: 250880000 | Q28: 358510000 | R28: 7.16 | S28: =IFERROR(SUMPRODUCT(($E$3:$E$165=E28)*ISNUMBER($P$3:$P$165)*$P$3:$P$165*$F$3:$F$165)/SUMPRODUCT(($E$3:$E$165=E28)*ISNUMBER($P$3:$P$165)*$P$3:$P$165),"") | T28: =IFERROR(SUMPRODUCT(($D$3:$D$165=D28)*ISNUMBER($P$3:$P$165)*$P$3:$P$165*$F$3:$F$165)/SUMPRODUCT(($D$3:$D$165=D28)*ISNUMBER($P$3:$P$165)*$P$3:$P$165),"") | U28: =IFERROR(SUMPRODUCT(($C$3:$C$165=C28)*ISNUMBER($P$3:$P$165)*$P$3:$P$165*$F$3:$F$165)/SUMPRODUCT(($C$3:$C$165=C28)*ISNUMBER($P$3:$P$165)*$P$3:$P$165),"") | V28: =IF(OR(T28="",U28=""),"",T28/U28) | W28: =IF(OR(S28="",T28=""),"",S28/T28) | X28: =IF(S28="","",F28/S28) | Y28: =IF(V28="",N28,INDEX('4_UK_L1_Input'!$C$4:$C$14,MATCH($C28,'4_UK_L1_Input'!$A$4:$A$14,0))*V28*W28*X28) | Z28: =IF(V28="","BETA FALLBACK","REAL (Bloomberg UK)") | AA28: =IFERROR(SUMPRODUCT(($C$3:$C$165=C28)*ISNUMBER($R$3:$R$165)*$Q$3:$Q$165*IF(ISNUMBER($R$3:$R$165),$R$3:$R$165,0))/SUMPRODUCT(($C$3:$C$165=C28)*ISNUMBER($R$3:$R$165)*$Q$3:$Q$165),"") | AB28: =IF(OR(R28="",AA28=""),"",R28/AA28) | AC28: =IF(AB28="",O28,INDEX('4_UK_L1_Input'!$D$4:$D$14,MATCH($C28,'4_UK_L1_Input'!$A$4:$A$14,0))*AB28) | AD28: =IF(AB28="","BETA FALLBACK","REAL (Bloomberg UK)") | AE28: =Y28-N28 | AF28: =AC28-O28
A29: 20103010 | B29: Construction & Engineering | C29: 20 | D29: 2010 | E29: 201030 | F29: 1.096666 | G29: 1 | H29: =SUMPRODUCT(($E$3:$E$165=E29)*$G$3:$G$165*$F$3:$F$165)/SUMPRODUCT(($E$3:$E$165=E29)*$G$3:$G$165) | I29: =SUMPRODUCT(($D$3:$D$165=D29)*$G$3:$G$165*$F$3:$F$165)/SUMPRODUCT(($D$3:$D$165=D29)*$G$3:$G$165) | J29: =SUMPRODUCT(($C$3:$C$165=C29)*$G$3:$G$165*$F$3:$F$165)/SUMPRODUCT(($C$3:$C$165=C29)*$G$3:$G$165) | K29: =I29/J29 | L29: =H29/I29 | M29: =F29/H29 | N29: =INDEX('4_UK_L1_Input'!$C$4:$C$14,MATCH($C29,'4_UK_L1_Input'!$A$4:$A$14,0))*K29*L29*M29 | O29: =INDEX('4_UK_L1_Input'!$D$4:$D$14,MATCH($C29,'4_UK_L1_Input'!$A$4:$A$14,0))*K29*L29*M29 | P29: 1920000000 | Q29: 850040000 | R29: 6.91 | S29: =IFERROR(SUMPRODUCT(($E$3:$E$165=E29)*ISNUMBER($P$3:$P$165)*$P$3:$P$165*$F$3:$F$165)/SUMPRODUCT(($E$3:$E$165=E29)*ISNUMBER($P$3:$P$165)*$P$3:$P$165),"") | T29: =IFERROR(SUMPRODUCT(($D$3:$D$165=D29)*ISNUMBER($P$3:$P$165)*$P$3:$P$165*$F$3:$F$165)/SUMPRODUCT(($D$3:$D$165=D29)*ISNUMBER($P$3:$P$165)*$P$3:$P$165),"") | U29: =IFERROR(SUMPRODUCT(($C$3:$C$165=C29)*ISNUMBER($P$3:$P$165)*$P$3:$P$165*$F$3:$F$165)/SUMPRODUCT(($C$3:$C$165=C29)*ISNUMBER($P$3:$P$165)*$P$3:$P$165),"") | V29: =IF(OR(T29="",U29=""),"",T29/U29) | W29: =IF(OR(S29="",T29=""),"",S29/T29) | X29: =IF(S29="","",F29/S29) | Y29: =IF(V29="",N29,INDEX('4_UK_L1_Input'!$C$4:$C$14,MATCH($C29,'4_UK_L1_Input'!$A$4:$A$14,0))*V29*W29*X29) | Z29: =IF(V29="","BETA FALLBACK","REAL (Bloomberg UK)") | AA29: =IFERROR(SUMPRODUCT(($C$3:$C$165=C29)*ISNUMBER($R$3:$R$165)*$Q$3:$Q$165*IF(ISNUMBER($R$3:$R$165),$R$3:$R$165,0))/SUMPRODUCT(($C$3:$C$165=C29)*ISNUMBER($R$3:$R$165)*$Q$3:$Q$165),"") | AB29: =IF(OR(R29="",AA29=""),"",R29/AA29) | AC29: =IF(AB29="",O29,INDEX('4_UK_L1_Input'!$D$4:$D$14,MATCH($C29,'4_UK_L1_Input'!$A$4:$A$14,0))*AB29) | AD29: =IF(AB29="","BETA FALLBACK","REAL (Bloomberg UK)") | AE29: =Y29-N29 | AF29: =AC29-O29
A30: 20104010 | B30: Electrical Components & Equipment | C30: 20 | D30: 2010 | E30: 201040 | F30: 1.166132 | G30: 1 | H30: =SUMPRODUCT(($E$3:$E$165=E30)*$G$3:$G$165*$F$3:$F$165)/SUMPRODUCT(($E$3:$E$165=E30)*$G$3:$G$165) | I30: =SUMPRODUCT(($D$3:$D$165=D30)*$G$3:$G$165*$F$3:$F$165)/SUMPRODUCT(($D$3:$D$165=D30)*$G$3:$G$165) | J30: =SUMPRODUCT(($C$3:$C$165=C30)*$G$3:$G$165*$F$3:$F$165)/SUMPRODUCT(($C$3:$C$165=C30)*$G$3:$G$165) | K30: =I30/J30 | L30: =H30/I30 | M30: =F30/H30 | N30: =INDEX('4_UK_L1_Input'!$C$4:$C$14,MATCH($C30,'4_UK_L1_Input'!$A$4:$A$14,0))*K30*L30*M30 | O30: =INDEX('4_UK_L1_Input'!$D$4:$D$14,MATCH($C30,'4_UK_L1_Input'!$A$4:$A$14,0))*K30*L30*M30 | P30: 480480000 | Q30: 2040000000 | R30: 9.8 | S30: =IFERROR(SUMPRODUCT(($E$3:$E$165=E30)*ISNUMBER($P$3:$P$165)*$P$3:$P$165*$F$3:$F$165)/SUMPRODUCT(($E$3:$E$165=E30)*ISNUMBER($P$3:$P$165)*$P$3:$P$165),"") | T30: =IFERROR(SUMPRODUCT(($D$3:$D$165=D30)*ISNUMBER($P$3:$P$165)*$P$3:$P$165*$F$3:$F$165)/SUMPRODUCT(($D$3:$D$165=D30)*ISNUMBER($P$3:$P$165)*$P$3:$P$165),"") | U30: =IFERROR(SUMPRODUCT(($C$3:$C$165=C30)*ISNUMBER($P$3:$P$165)*$P$3:$P$165*$F$3:$F$165)/SUMPRODUCT(($C$3:$C$165=C30)*ISNUMBER($P$3:$P$165)*$P$3:$P$165),"") | V30: =IF(OR(T30="",U30=""),"",T30/U30) | W30: =IF(OR(S30="",T30=""),"",S30/T30) | X30: =IF(S30="","",F30/S30) | Y30: =IF(V30="",N30,INDEX('4_UK_L1_Input'!$C$4:$C$14,MATCH($C30,'4_UK_L1_Input'!$A$4:$A$14,0))*V30*W30*X30) | Z30: =IF(V30="","BETA FALLBACK","REAL (Bloomberg UK)") | AA30: =IFERROR(SUMPRODUCT(($C$3:$C$165=C30)*ISNUMBER($R$3:$R$165)*$Q$3:$Q$165*IF(ISNUMBER($R$3:$R$165),$R$3:$R$165,0))/SUMPRODUCT(($C$3:$C$165=C30)*ISNUMBER($R$3:$R$165)*$Q$3:$Q$165),"") | AB30: =IF(OR(R30="",AA30=""),"",R30/AA30) | AC30: =IF(AB30="",O30,INDEX('4_UK_L1_Input'!$D$4:$D$14,MATCH($C30,'4_UK_L1_Input'!$A$4:$A$14,0))*AB30) | AD30: =IF(AB30="","BETA FALLBACK","REAL (Bloomberg UK)") | AE30: =Y30-N30 | AF30: =AC30-O30
A31: 20104020 | B31: Heavy Electrical Equipment | C31: 20 | D31: 2010 | E31: 201040 | F31: 1.166132 | G31: 1 | H31: =SUMPRODUCT(($E$3:$E$165=E31)*$G$3:$G$165*$F$3:$F$165)/SUMPRODUCT(($E$3:$E$165=E31)*$G$3:$G$165) | I31: =SUMPRODUCT(($D$3:$D$165=D31)*$G$3:$G$165*$F$3:$F$165)/SUMPRODUCT(($D$3:$D$165=D31)*$G$3:$G$165) | J31: =SUMPRODUCT(($C$3:$C$165=C31)*$G$3:$G$165*$F$3:$F$165)/SUMPRODUCT(($C$3:$C$165=C31)*$G$3:$G$165) | K31: =I31/J31 | L31: =H31/I31 | M31: =F31/H31 | N31: =INDEX('4_UK_L1_Input'!$C$4:$C$14,MATCH($C31,'4_UK_L1_Input'!$A$4:$A$14,0))*K31*L31*M31 | O31: =INDEX('4_UK_L1_Input'!$D$4:$D$14,MATCH($C31,'4_UK_L1_Input'!$A$4:$A$14,0))*K31*L31*M31 | P31: 229090000 | Q31: 2180000000 | R31: 38.05 | S31: =IFERROR(SUMPRODUCT(($E$3:$E$165=E31)*ISNUMBER($P$3:$P$165)*$P$3:$P$165*$F$3:$F$165)/SUMPRODUCT(($E$3:$E$165=E31)*ISNUMBER($P$3:$P$165)*$P$3:$P$165),"") | T31: =IFERROR(SUMPRODUCT(($D$3:$D$165=D31)*ISNUMBER($P$3:$P$165)*$P$3:$P$165*$F$3:$F$165)/SUMPRODUCT(($D$3:$D$165=D31)*ISNUMBER($P$3:$P$165)*$P$3:$P$165),"") | U31: =IFERROR(SUMPRODUCT(($C$3:$C$165=C31)*ISNUMBER($P$3:$P$165)*$P$3:$P$165*$F$3:$F$165)/SUMPRODUCT(($C$3:$C$165=C31)*ISNUMBER($P$3:$P$165)*$P$3:$P$165),"") | V31: =IF(OR(T31="",U31=""),"",T31/U31) | W31: =IF(OR(S31="",T31=""),"",S31/T31) | X31: =IF(S31="","",F31/S31) | Y31: =IF(V31="",N31,INDEX('4_UK_L1_Input'!$C$4:$C$14,MATCH($C31,'4_UK_L1_Input'!$A$4:$A$14,0))*V31*W31*X31) | Z31: =IF(V31="","BETA FALLBACK","REAL (Bloomberg UK)") | AA31: =IFERROR(SUMPRODUCT(($C$3:$C$165=C31)*ISNUMBER($R$3:$R$165)*$Q$3:$Q$165*IF(ISNUMBER($R$3:$R$165),$R$3:$R$165,0))/SUMPRODUCT(($C$3:$C$165=C31)*ISNUMBER($R$3:$R$165)*$Q$3:$Q$165),"") | AB31: =IF(OR(R31="",AA31=""),"",R31/AA31) | AC31: =IF(AB31="",O31,INDEX('4_UK_L1_Input'!$D$4:$D$14,MATCH($C31,'4_UK_L1_Input'!$A$4:$A$14,0))*AB31) | AD31: =IF(AB31="","BETA FALLBACK","REAL (Bloomberg UK)") | AE31: =Y31-N31 | AF31: =AC31-O31
A32: 20105010 | B32: Industrial Conglomerates | C32: 20 | D32: 2010 | E32: 201050 | F32: 0.862387 | G32: 1 | H32: =SUMPRODUCT(($E$3:$E$165=E32)*$G$3:$G$165*$F$3:$F$165)/SUMPRODUCT(($E$3:$E$165=E32)*$G$3:$G$165) | I32: =SUMPRODUCT(($D$3:$D$165=D32)*$G$3:$G$165*$F$3:$F$165)/SUMPRODUCT(($D$3:$D$165=D32)*$G$3:$G$165) | J32: =SUMPRODUCT(($C$3:$C$165=C32)*$G$3:$G$165*$F$3:$F$165)/SUMPRODUCT(($C$3:$C$165=C32)*$G$3:$G$165) | K32: =I32/J32 | L32: =H32/I32 | M32: =F32/H32 | N32: =INDEX('4_UK_L1_Input'!$C$4:$C$14,MATCH($C32,'4_UK_L1_Input'!$A$4:$A$14,0))*K32*L32*M32 | O32: =INDEX('4_UK_L1_Input'!$D$4:$D$14,MATCH($C32,'4_UK_L1_Input'!$A$4:$A$14,0))*K32*L32*M32 | P32: 1130000000 | Q32: 3980000000 | R32: 12.91 | S32: =IFERROR(SUMPRODUCT(($E$3:$E$165=E32)*ISNUMBER($P$3:$P$165)*$P$3:$P$165*$F$3:$F$165)/SUMPRODUCT(($E$3:$E$165=E32)*ISNUMBER($P$3:$P$165)*$P$3:$P$165),"") | T32: =IFERROR(SUMPRODUCT(($D$3:$D$165=D32)*ISNUMBER($P$3:$P$165)*$P$3:$P$165*$F$3:$F$165)/SUMPRODUCT(($D$3:$D$165=D32)*ISNUMBER($P$3:$P$165)*$P$3:$P$165),"") | U32: =IFERROR(SUMPRODUCT(($C$3:$C$165=C32)*ISNUMBER($P$3:$P$165)*$P$3:$P$165*$F$3:$F$165)/SUMPRODUCT(($C$3:$C$165=C32)*ISNUMBER($P$3:$P$165)*$P$3:$P$165),"") | V32: =IF(OR(T32="",U32=""),"",T32/U32) | W32: =IF(OR(S32="",T32=""),"",S32/T32) | X32: =IF(S32="","",F32/S32) | Y32: =IF(V32="",N32,INDEX('4_UK_L1_Input'!$C$4:$C$14,MATCH($C32,'4_UK_L1_Input'!$A$4:$A$14,0))*V32*W32*X32) | Z32: =IF(V32="","BETA FALLBACK","REAL (Bloomberg UK)") | AA32: =IFERROR(SUMPRODUCT(($C$3:$C$165=C32)*ISNUMBER($R$3:$R$165)*$Q$3:$Q$165*IF(ISNUMBER($R$3:$R$165),$R$3:$R$165,0))/SUMPRODUCT(($C$3:$C$165=C32)*ISNUMBER($R$3:$R$165)*$Q$3:$Q$165),"") | AB32: =IF(OR(R32="",AA32=""),"",R32/AA32) | AC32: =IF(AB32="",O32,INDEX('4_UK_L1_Input'!$D$4:$D$14,MATCH($C32,'4_UK_L1_Input'!$A$4:$A$14,0))*AB32) | AD32: =IF(AB32="","BETA FALLBACK","REAL (Bloomberg UK)") | AE32: =Y32-N32 | AF32: =AC32-O32
A33: 20106010 | B33: Construction Machinery & Heavy Transportation Equipment | C33: 20 | D33: 2010 | E33: 201060 | F33: 0.894633 | G33: 1 | H33: =SUMPRODUCT(($E$3:$E$165=E33)*$G$3:$G$165*$F$3:$F$165)/SUMPRODUCT(($E$3:$E$165=E33)*$G$3:$G$165) | I33: =SUMPRODUCT(($D$3:$D$165=D33)*$G$3:$G$165*$F$3:$F$165)/SUMPRODUCT(($D$3:$D$165=D33)*$G$3:$G$165) | J33: =SUMPRODUCT(($C$3:$C$165=C33)*$G$3:$G$165*$F$3:$F$165)/SUMPRODUCT(($C$3:$C$165=C33)*$G$3:$G$165) | K33: =I33/J33 | L33: =H33/I33 | M33: =F33/H33 | N33: =INDEX('4_UK_L1_Input'!$C$4:$C$14,MATCH($C33,'4_UK_L1_Input'!$A$4:$A$14,0))*K33*L33*M33 | O33: =INDEX('4_UK_L1_Input'!$D$4:$D$14,MATCH($C33,'4_UK_L1_Input'!$A$4:$A$14,0))*K33*L33*M33 | S33: =IFERROR(SUMPRODUCT(($E$3:$E$165=E33)*ISNUMBER($P$3:$P$165)*$P$3:$P$165*$F$3:$F$165)/SUMPRODUCT(($E$3:$E$165=E33)*ISNUMBER($P$3:$P$165)*$P$3:$P$165),"") | T33: =IFERROR(SUMPRODUCT(($D$3:$D$165=D33)*ISNUMBER($P$3:$P$165)*$P$3:$P$165*$F$3:$F$165)/SUMPRODUCT(($D$3:$D$165=D33)*ISNUMBER($P$3:$P$165)*$P$3:$P$165),"") | U33: =IFERROR(SUMPRODUCT(($C$3:$C$165=C33)*ISNUMBER($P$3:$P$165)*$P$3:$P$165*$F$3:$F$165)/SUMPRODUCT(($C$3:$C$165=C33)*ISNUMBER($P$3:$P$165)*$P$3:$P$165),"") | V33: =IF(OR(T33="",U33=""),"",T33/U33) | W33: =IF(OR(S33="",T33=""),"",S33/T33) | X33: =IF(S33="","",F33/S33) | Y33: =IF(V33="",N33,INDEX('4_UK_L1_Input'!$C$4:$C$14,MATCH($C33,'4_UK_L1_Input'!$A$4:$A$14,0))*V33*W33*X33) | Z33: =IF(V33="","BETA FALLBACK","REAL (Bloomberg UK)") | AA33: =IFERROR(SUMPRODUCT(($C$3:$C$165=C33)*ISNUMBER($R$3:$R$165)*$Q$3:$Q$165*IF(ISNUMBER($R$3:$R$165),$R$3:$R$165,0))/SUMPRODUCT(($C$3:$C$165=C33)*ISNUMBER($R$3:$R$165)*$Q$3:$Q$165),"") | AB33: =IF(OR(R33="",AA33=""),"",R33/AA33) | AC33: =IF(AB33="",O33,INDEX('4_UK_L1_Input'!$D$4:$D$14,MATCH($C33,'4_UK_L1_Input'!$A$4:$A$14,0))*AB33) | AD33: =IF(AB33="","BETA FALLBACK","REAL (Bloomberg UK)") | AE33: =Y33-N33 | AF33: =AC33-O33
A34: 20106015 | B34: Agricultural & Farm Machinery | C34: 20 | D34: 2010 | E34: 201060 | F34: 0.894633 | G34: 1 | H34: =SUMPRODUCT(($E$3:$E$165=E34)*$G$3:$G$165*$F$3:$F$165)/SUMPRODUCT(($E$3:$E$165=E34)*$G$3:$G$165) | I34: =SUMPRODUCT(($D$3:$D$165=D34)*$G$3:$G$165*$F$3:$F$165)/SUMPRODUCT(($D$3:$D$165=D34)*$G$3:$G$165) | J34: =SUMPRODUCT(($C$3:$C$165=C34)*$G$3:$G$165*$F$3:$F$165)/SUMPRODUCT(($C$3:$C$165=C34)*$G$3:$G$165) | K34: =I34/J34 | L34: =H34/I34 | M34: =F34/H34 | N34: =INDEX('4_UK_L1_Input'!$C$4:$C$14,MATCH($C34,'4_UK_L1_Input'!$A$4:$A$14,0))*K34*L34*M34 | O34: =INDEX('4_UK_L1_Input'!$D$4:$D$14,MATCH($C34,'4_UK_L1_Input'!$A$4:$A$14,0))*K34*L34*M34 | P34: 18180000000 | Q34: 13500000000 | R34: 27.38 | S34: =IFERROR(SUMPRODUCT(($E$3:$E$165=E34)*ISNUMBER($P$3:$P$165)*$P$3:$P$165*$F$3:$F$165)/SUMPRODUCT(($E$3:$E$165=E34)*ISNUMBER($P$3:$P$165)*$P$3:$P$165),"") | T34: =IFERROR(SUMPRODUCT(($D$3:$D$165=D34)*ISNUMBER($P$3:$P$165)*$P$3:$P$165*$F$3:$F$165)/SUMPRODUCT(($D$3:$D$165=D34)*ISNUMBER($P$3:$P$165)*$P$3:$P$165),"") | U34: =IFERROR(SUMPRODUCT(($C$3:$C$165=C34)*ISNUMBER($P$3:$P$165)*$P$3:$P$165*$F$3:$F$165)/SUMPRODUCT(($C$3:$C$165=C34)*ISNUMBER($P$3:$P$165)*$P$3:$P$165),"") | V34: =IF(OR(T34="",U34=""),"",T34/U34) | W34: =IF(OR(S34="",T34=""),"",S34/T34) | X34: =IF(S34="","",F34/S34) | Y34: =IF(V34="",N34,INDEX('4_UK_L1_Input'!$C$4:$C$14,MATCH($C34,'4_UK_L1_Input'!$A$4:$A$14,0))*V34*W34*X34) | Z34: =IF(V34="","BETA FALLBACK","REAL (Bloomberg UK)") | AA34: =IFERROR(SUMPRODUCT(($C$3:$C$165=C34)*ISNUMBER($R$3:$R$165)*$Q$3:$Q$165*IF(ISNUMBER($R$3:$R$165),$R$3:$R$165,0))/SUMPRODUCT(($C$3:$C$165=C34)*ISNUMBER($R$3:$R$165)*$Q$3:$Q$165),"") | AB34: =IF(OR(R34="",AA34=""),"",R34/AA34) | AC34: =IF(AB34="",O34,INDEX('4_UK_L1_Input'!$D$4:$D$14,MATCH($C34,'4_UK_L1_Input'!$A$4:$A$14,0))*AB34) | AD34: =IF(AB34="","BETA FALLBACK","REAL (Bloomberg UK)") | AE34: =Y34-N34 | AF34: =AC34-O34
A35: 20106020 | B35: Industrial Machinery & Supplies & Components | C35: 20 | D35: 2010 | E35: 201060 | F35: 0.894633 | G35: 1 | H35: =SUMPRODUCT(($E$3:$E$165=E35)*$G$3:$G$165*$F$3:$F$165)/SUMPRODUCT(($E$3:$E$165=E35)*$G$3:$G$165) | I35: =SUMPRODUCT(($D$3:$D$165=D35)*$G$3:$G$165*$F$3:$F$165)/SUMPRODUCT(($D$3:$D$165=D35)*$G$3:$G$165) | J35: =SUMPRODUCT(($C$3:$C$165=C35)*$G$3:$G$165*$F$3:$F$165)/SUMPRODUCT(($C$3:$C$165=C35)*$G$3:$G$165) | K35: =I35/J35 | L35: =H35/I35 | M35: =F35/H35 | N35: =INDEX('4_UK_L1_Input'!$C$4:$C$14,MATCH($C35,'4_UK_L1_Input'!$A$4:$A$14,0))*K35*L35*M35 | O35: =INDEX('4_UK_L1_Input'!$D$4:$D$14,MATCH($C35,'4_UK_L1_Input'!$A$4:$A$14,0))*K35*L35*M35 | P35: 966980000 | Q35: 2440000000 | R35: 10.77 | S35: =IFERROR(SUMPRODUCT(($E$3:$E$165=E35)*ISNUMBER($P$3:$P$165)*$P$3:$P$165*$F$3:$F$165)/SUMPRODUCT(($E$3:$E$165=E35)*ISNUMBER($P$3:$P$165)*$P$3:$P$165),"") | T35: =IFERROR(SUMPRODUCT(($D$3:$D$165=D35)*ISNUMBER($P$3:$P$165)*$P$3:$P$165*$F$3:$F$165)/SUMPRODUCT(($D$3:$D$165=D35)*ISNUMBER($P$3:$P$165)*$P$3:$P$165),"") | U35: =IFERROR(SUMPRODUCT(($C$3:$C$165=C35)*ISNUMBER($P$3:$P$165)*$P$3:$P$165*$F$3:$F$165)/SUMPRODUCT(($C$3:$C$165=C35)*ISNUMBER($P$3:$P$165)*$P$3:$P$165),"") | V35: =IF(OR(T35="",U35=""),"",T35/U35) | W35: =IF(OR(S35="",T35=""),"",S35/T35) | X35: =IF(S35="","",F35/S35) | Y35: =IF(V35="",N35,INDEX('4_UK_L1_Input'!$C$4:$C$14,MATCH($C35,'4_UK_L1_Input'!$A$4:$A$14,0))*V35*W35*X35) | Z35: =IF(V35="","BETA FALLBACK","REAL (Bloomberg UK)") | AA35: =IFERROR(SUMPRODUCT(($C$3:$C$165=C35)*ISNUMBER($R$3:$R$165)*$Q$3:$Q$165*IF(ISNUMBER($R$3:$R$165),$R$3:$R$165,0))/SUMPRODUCT(($C$3:$C$165=C35)*ISNUMBER($R$3:$R$165)*$Q$3:$Q$165),"") | AB35: =IF(OR(R35="",AA35=""),"",R35/AA35) | AC35: =IF(AB35="",O35,INDEX('4_UK_L1_Input'!$D$4:$D$14,MATCH($C35,'4_UK_L1_Input'!$A$4:$A$14,0))*AB35) | AD35: =IF(AB35="","BETA FALLBACK","REAL (Bloomberg UK)") | AE35: =Y35-N35 | AF35: =AC35-O35
A36: 20107010 | B36: Trading Companies & Distributors | C36: 20 | D36: 2010 | E36: 201070 | F36: 0.815429 | G36: 1 | H36: =SUMPRODUCT(($E$3:$E$165=E36)*$G$3:$G$165*$F$3:$F$165)/SUMPRODUCT(($E$3:$E$165=E36)*$G$3:$G$165) | I36: =SUMPRODUCT(($D$3:$D$165=D36)*$G$3:$G$165*$F$3:$F$165)/SUMPRODUCT(($D$3:$D$165=D36)*$G$3:$G$165) | J36: =SUMPRODUCT(($C$3:$C$165=C36)*$G$3:$G$165*$F$3:$F$165)/SUMPRODUCT(($C$3:$C$165=C36)*$G$3:$G$165) | K36: =I36/J36 | L36: =H36/I36 | M36: =F36/H36 | N36: =INDEX('4_UK_L1_Input'!$C$4:$C$14,MATCH($C36,'4_UK_L1_Input'!$A$4:$A$14,0))*K36*L36*M36 | O36: =INDEX('4_UK_L1_Input'!$D$4:$D$14,MATCH($C36,'4_UK_L1_Input'!$A$4:$A$14,0))*K36*L36*M36 | P36: 1710000000 | Q36: 1790000000 | R36: 7.57 | S36: =IFERROR(SUMPRODUCT(($E$3:$E$165=E36)*ISNUMBER($P$3:$P$165)*$P$3:$P$165*$F$3:$F$165)/SUMPRODUCT(($E$3:$E$165=E36)*ISNUMBER($P$3:$P$165)*$P$3:$P$165),"") | T36: =IFERROR(SUMPRODUCT(($D$3:$D$165=D36)*ISNUMBER($P$3:$P$165)*$P$3:$P$165*$F$3:$F$165)/SUMPRODUCT(($D$3:$D$165=D36)*ISNUMBER($P$3:$P$165)*$P$3:$P$165),"") | U36: =IFERROR(SUMPRODUCT(($C$3:$C$165=C36)*ISNUMBER($P$3:$P$165)*$P$3:$P$165*$F$3:$F$165)/SUMPRODUCT(($C$3:$C$165=C36)*ISNUMBER($P$3:$P$165)*$P$3:$P$165),"") | V36: =IF(OR(T36="",U36=""),"",T36/U36) | W36: =IF(OR(S36="",T36=""),"",S36/T36) | X36: =IF(S36="","",F36/S36) | Y36: =IF(V36="",N36,INDEX('4_UK_L1_Input'!$C$4:$C$14,MATCH($C36,'4_UK_L1_Input'!$A$4:$A$14,0))*V36*W36*X36) | Z36: =IF(V36="","BETA FALLBACK","REAL (Bloomberg UK)") | AA36: =IFERROR(SUMPRODUCT(($C$3:$C$165=C36)*ISNUMBER($R$3:$R$165)*$Q$3:$Q$165*IF(ISNUMBER($R$3:$R$165),$R$3:$R$165,0))/SUMPRODUCT(($C$3:$C$165=C36)*ISNUMBER($R$3:$R$165)*$Q$3:$Q$165),"") | AB36: =IF(OR(R36="",AA36=""),"",R36/AA36) | AC36: =IF(AB36="",O36,INDEX('4_UK_L1_Input'!$D$4:$D$14,MATCH($C36,'4_UK_L1_Input'!$A$4:$A$14,0))*AB36) | AD36: =IF(AB36="","BETA FALLBACK","REAL (Bloomberg UK)") | AE36: =Y36-N36 | AF36: =AC36-O36
A37: 20201010 | B37: Commercial Printing | C37: 20 | D37: 2020 | E37: 202010 | F37: 0.811779 | G37: 1 | H37: =SUMPRODUCT(($E$3:$E$165=E37)*$G$3:$G$165*$F$3:$F$165)/SUMPRODUCT(($E$3:$E$165=E37)*$G$3:$G$165) | I37: =SUMPRODUCT(($D$3:$D$165=D37)*$G$3:$G$165*$F$3:$F$165)/SUMPRODUCT(($D$3:$D$165=D37)*$G$3:$G$165) | J37: =SUMPRODUCT(($C$3:$C$165=C37)*$G$3:$G$165*$F$3:$F$165)/SUMPRODUCT(($C$3:$C$165=C37)*$G$3:$G$165) | K37: =I37/J37 | L37: =H37/I37 | M37: =F37/H37 | N37: =INDEX('4_UK_L1_Input'!$C$4:$C$14,MATCH($C37,'4_UK_L1_Input'!$A$4:$A$14,0))*K37*L37*M37 | O37: =INDEX('4_UK_L1_Input'!$D$4:$D$14,MATCH($C37,'4_UK_L1_Input'!$A$4:$A$14,0))*K37*L37*M37 | P37: 22260000 | Q37: 62410000 | S37: =IFERROR(SUMPRODUCT(($E$3:$E$165=E37)*ISNUMBER($P$3:$P$165)*$P$3:$P$165*$F$3:$F$165)/SUMPRODUCT(($E$3:$E$165=E37)*ISNUMBER($P$3:$P$165)*$P$3:$P$165),"") | T37: =IFERROR(SUMPRODUCT(($D$3:$D$165=D37)*ISNUMBER($P$3:$P$165)*$P$3:$P$165*$F$3:$F$165)/SUMPRODUCT(($D$3:$D$165=D37)*ISNUMBER($P$3:$P$165)*$P$3:$P$165),"") | U37: =IFERROR(SUMPRODUCT(($C$3:$C$165=C37)*ISNUMBER($P$3:$P$165)*$P$3:$P$165*$F$3:$F$165)/SUMPRODUCT(($C$3:$C$165=C37)*ISNUMBER($P$3:$P$165)*$P$3:$P$165),"") | V37: =IF(OR(T37="",U37=""),"",T37/U37) | W37: =IF(OR(S37="",T37=""),"",S37/T37) | X37: =IF(S37="","",F37/S37) | Y37: =IF(V37="",N37,INDEX('4_UK_L1_Input'!$C$4:$C$14,MATCH($C37,'4_UK_L1_Input'!$A$4:$A$14,0))*V37*W37*X37) | Z37: =IF(V37="","BETA FALLBACK","REAL (Bloomberg UK)") | AA37: =IFERROR(SUMPRODUCT(($C$3:$C$165=C37)*ISNUMBER($R$3:$R$165)*$Q$3:$Q$165*IF(ISNUMBER($R$3:$R$165),$R$3:$R$165,0))/SUMPRODUCT(($C$3:$C$165=C37)*ISNUMBER($R$3:$R$165)*$Q$3:$Q$165),"") | AB37: =IF(OR(R37="",AA37=""),"",R37/AA37) | AC37: =IF(AB37="",O37,INDEX('4_UK_L1_Input'!$D$4:$D$14,MATCH($C37,'4_UK_L1_Input'!$A$4:$A$14,0))*AB37) | AD37: =IF(AB37="","BETA FALLBACK","REAL (Bloomberg UK)") | AE37: =Y37-N37 | AF37: =AC37-O37
A38: 20201050 | B38: Environmental & Facilities Services | C38: 20 | D38: 2020 | E38: 202010 | F38: 0.836864 | G38: 1 | H38: =SUMPRODUCT(($E$3:$E$165=E38)*$G$3:$G$165*$F$3:$F$165)/SUMPRODUCT(($E$3:$E$165=E38)*$G$3:$G$165) | I38: =SUMPRODUCT(($D$3:$D$165=D38)*$G$3:$G$165*$F$3:$F$165)/SUMPRODUCT(($D$3:$D$165=D38)*$G$3:$G$165) | J38: =SUMPRODUCT(($C$3:$C$165=C38)*$G$3:$G$165*$F$3:$F$165)/SUMPRODUCT(($C$3:$C$165=C38)*$G$3:$G$165) | K38: =I38/J38 | L38: =H38/I38 | M38: =F38/H38 | N38: =INDEX('4_UK_L1_Input'!$C$4:$C$14,MATCH($C38,'4_UK_L1_Input'!$A$4:$A$14,0))*K38*L38*M38 | O38: =INDEX('4_UK_L1_Input'!$D$4:$D$14,MATCH($C38,'4_UK_L1_Input'!$A$4:$A$14,0))*K38*L38*M38 | P38: 2970000000 | Q38: 2410000000 | R38: 8.34 | S38: =IFERROR(SUMPRODUCT(($E$3:$E$165=E38)*ISNUMBER($P$3:$P$165)*$P$3:$P$165*$F$3:$F$165)/SUMPRODUCT(($E$3:$E$165=E38)*ISNUMBER($P$3:$P$165)*$P$3:$P$165),"") | T38: =IFERROR(SUMPRODUCT(($D$3:$D$165=D38)*ISNUMBER($P$3:$P$165)*$P$3:$P$165*$F$3:$F$165)/SUMPRODUCT(($D$3:$D$165=D38)*ISNUMBER($P$3:$P$165)*$P$3:$P$165),"") | U38: =IFERROR(SUMPRODUCT(($C$3:$C$165=C38)*ISNUMBER($P$3:$P$165)*$P$3:$P$165*$F$3:$F$165)/SUMPRODUCT(($C$3:$C$165=C38)*ISNUMBER($P$3:$P$165)*$P$3:$P$165),"") | V38: =IF(OR(T38="",U38=""),"",T38/U38) | W38: =IF(OR(S38="",T38=""),"",S38/T38) | X38: =IF(S38="","",F38/S38) | Y38: =IF(V38="",N38,INDEX('4_UK_L1_Input'!$C$4:$C$14,MATCH($C38,'4_UK_L1_Input'!$A$4:$A$14,0))*V38*W38*X38) | Z38: =IF(V38="","BETA FALLBACK","REAL (Bloomberg UK)") | AA38: =IFERROR(SUMPRODUCT(($C$3:$C$165=C38)*ISNUMBER($R$3:$R$165)*$Q$3:$Q$165*IF(ISNUMBER($R$3:$R$165),$R$3:$R$165,0))/SUMPRODUCT(($C$3:$C$165=C38)*ISNUMBER($R$3:$R$165)*$Q$3:$Q$165),"") | AB38: =IF(OR(R38="",AA38=""),"",R38/AA38) | AC38: =IF(AB38="",O38,INDEX('4_UK_L1_Input'!$D$4:$D$14,MATCH($C38,'4_UK_L1_Input'!$A$4:$A$14,0))*AB38) | AD38: =IF(AB38="","BETA FALLBACK","REAL (Bloomberg UK)") | AE38: =Y38-N38 | AF38: =AC38-O38
A39: 20201060 | B39: Office Services & Supplies | C39: 20 | D39: 2020 | E39: 202010 | F39: 0.981014 | G39: 1 | H39: =SUMPRODUCT(($E$3:$E$165=E39)*$G$3:$G$165*$F$3:$F$165)/SUMPRODUCT(($E$3:$E$165=E39)*$G$3:$G$165) | I39: =SUMPRODUCT(($D$3:$D$165=D39)*$G$3:$G$165*$F$3:$F$165)/SUMPRODUCT(($D$3:$D$165=D39)*$G$3:$G$165) | J39: =SUMPRODUCT(($C$3:$C$165=C39)*$G$3:$G$165*$F$3:$F$165)/SUMPRODUCT(($C$3:$C$165=C39)*$G$3:$G$165) | K39: =I39/J39 | L39: =H39/I39 | M39: =F39/H39 | N39: =INDEX('4_UK_L1_Input'!$C$4:$C$14,MATCH($C39,'4_UK_L1_Input'!$A$4:$A$14,0))*K39*L39*M39 | O39: =INDEX('4_UK_L1_Input'!$D$4:$D$14,MATCH($C39,'4_UK_L1_Input'!$A$4:$A$14,0))*K39*L39*M39 | S39: =IFERROR(SUMPRODUCT(($E$3:$E$165=E39)*ISNUMBER($P$3:$P$165)*$P$3:$P$165*$F$3:$F$165)/SUMPRODUCT(($E$3:$E$165=E39)*ISNUMBER($P$3:$P$165)*$P$3:$P$165),"") | T39: =IFERROR(SUMPRODUCT(($D$3:$D$165=D39)*ISNUMBER($P$3:$P$165)*$P$3:$P$165*$F$3:$F$165)/SUMPRODUCT(($D$3:$D$165=D39)*ISNUMBER($P$3:$P$165)*$P$3:$P$165),"") | U39: =IFERROR(SUMPRODUCT(($C$3:$C$165=C39)*ISNUMBER($P$3:$P$165)*$P$3:$P$165*$F$3:$F$165)/SUMPRODUCT(($C$3:$C$165=C39)*ISNUMBER($P$3:$P$165)*$P$3:$P$165),"") | V39: =IF(OR(T39="",U39=""),"",T39/U39) | W39: =IF(OR(S39="",T39=""),"",S39/T39) | X39: =IF(S39="","",F39/S39) | Y39: =IF(V39="",N39,INDEX('4_UK_L1_Input'!$C$4:$C$14,MATCH($C39,'4_UK_L1_Input'!$A$4:$A$14,0))*V39*W39*X39) | Z39: =IF(V39="","BETA FALLBACK","REAL (Bloomberg UK)") | AA39: =IFERROR(SUMPRODUCT(($C$3:$C$165=C39)*ISNUMBER($R$3:$R$165)*$Q$3:$Q$165*IF(ISNUMBER($R$3:$R$165),$R$3:$R$165,0))/SUMPRODUCT(($C$3:$C$165=C39)*ISNUMBER($R$3:$R$165)*$Q$3:$Q$165),"") | AB39: =IF(OR(R39="",AA39=""),"",R39/AA39) | AC39: =IF(AB39="",O39,INDEX('4_UK_L1_Input'!$D$4:$D$14,MATCH($C39,'4_UK_L1_Input'!$A$4:$A$14,0))*AB39) | AD39: =IF(AB39="","BETA FALLBACK","REAL (Bloomberg UK)") | AE39: =Y39-N39 | AF39: =AC39-O39
A40: 20201070 | B40: Diversified Support Services | C40: 20 | D40: 2020 | E40: 202010 | F40: 0.811779 | G40: 1 | H40: =SUMPRODUCT(($E$3:$E$165=E40)*$G$3:$G$165*$F$3:$F$165)/SUMPRODUCT(($E$3:$E$165=E40)*$G$3:$G$165) | I40: =SUMPRODUCT(($D$3:$D$165=D40)*$G$3:$G$165*$F$3:$F$165)/SUMPRODUCT(($D$3:$D$165=D40)*$G$3:$G$165) | J40: =SUMPRODUCT(($C$3:$C$165=C40)*$G$3:$G$165*$F$3:$F$165)/SUMPRODUCT(($C$3:$C$165=C40)*$G$3:$G$165) | K40: =I40/J40 | L40: =H40/I40 | M40: =F40/H40 | N40: =INDEX('4_UK_L1_Input'!$C$4:$C$14,MATCH($C40,'4_UK_L1_Input'!$A$4:$A$14,0))*K40*L40*M40 | O40: =INDEX('4_UK_L1_Input'!$D$4:$D$14,MATCH($C40,'4_UK_L1_Input'!$A$4:$A$14,0))*K40*L40*M40 | P40: 272250000 | Q40: 221420000 | R40: 5.61 | S40: =IFERROR(SUMPRODUCT(($E$3:$E$165=E40)*ISNUMBER($P$3:$P$165)*$P$3:$P$165*$F$3:$F$165)/SUMPRODUCT(($E$3:$E$165=E40)*ISNUMBER($P$3:$P$165)*$P$3:$P$165),"") | T40: =IFERROR(SUMPRODUCT(($D$3:$D$165=D40)*ISNUMBER($P$3:$P$165)*$P$3:$P$165*$F$3:$F$165)/SUMPRODUCT(($D$3:$D$165=D40)*ISNUMBER($P$3:$P$165)*$P$3:$P$165),"") | U40: =IFERROR(SUMPRODUCT(($C$3:$C$165=C40)*ISNUMBER($P$3:$P$165)*$P$3:$P$165*$F$3:$F$165)/SUMPRODUCT(($C$3:$C$165=C40)*ISNUMBER($P$3:$P$165)*$P$3:$P$165),"") | V40: =IF(OR(T40="",U40=""),"",T40/U40) | W40: =IF(OR(S40="",T40=""),"",S40/T40) | X40: =IF(S40="","",F40/S40) | Y40: =IF(V40="",N40,INDEX('4_UK_L1_Input'!$C$4:$C$14,MATCH($C40,'4_UK_L1_Input'!$A$4:$A$14,0))*V40*W40*X40) | Z40: =IF(V40="","BETA FALLBACK","REAL (Bloomberg UK)") | AA40: =IFERROR(SUMPRODUCT(($C$3:$C$165=C40)*ISNUMBER($R$3:$R$165)*$Q$3:$Q$165*IF(ISNUMBER($R$3:$R$165),$R$3:$R$165,0))/SUMPRODUCT(($C$3:$C$165=C40)*ISNUMBER($R$3:$R$165)*$Q$3:$Q$165),"") | AB40: =IF(OR(R40="",AA40=""),"",R40/AA40) | AC40: =IF(AB40="",O40,INDEX('4_UK_L1_Input'!$D$4:$D$14,MATCH($C40,'4_UK_L1_Input'!$A$4:$A$14,0))*AB40) | AD40: =IF(AB40="","BETA FALLBACK","REAL (Bloomberg UK)") | AE40: =Y40-N40 | AF40: =AC40-O40
A41: 20201080 | B41: Security & Alarm Services | C41: 20 | D41: 2020 | E41: 202010 | F41: 0.811779 | G41: 1 | H41: =SUMPRODUCT(($E$3:$E$165=E41)*$G$3:$G$165*$F$3:$F$165)/SUMPRODUCT(($E$3:$E$165=E41)*$G$3:$G$165) | I41: =SUMPRODUCT(($D$3:$D$165=D41)*$G$3:$G$165*$F$3:$F$165)/SUMPRODUCT(($D$3:$D$165=D41)*$G$3:$G$165) | J41: =SUMPRODUCT(($C$3:$C$165=C41)*$G$3:$G$165*$F$3:$F$165)/SUMPRODUCT(($C$3:$C$165=C41)*$G$3:$G$165) | K41: =I41/J41 | L41: =H41/I41 | M41: =F41/H41 | N41: =INDEX('4_UK_L1_Input'!$C$4:$C$14,MATCH($C41,'4_UK_L1_Input'!$A$4:$A$14,0))*K41*L41*M41 | O41: =INDEX('4_UK_L1_Input'!$D$4:$D$14,MATCH($C41,'4_UK_L1_Input'!$A$4:$A$14,0))*K41*L41*M41 | P41: 13500000000 | Q41: 9930000000 | R41: 8.49 | S41: =IFERROR(SUMPRODUCT(($E$3:$E$165=E41)*ISNUMBER($P$3:$P$165)*$P$3:$P$165*$F$3:$F$165)/SUMPRODUCT(($E$3:$E$165=E41)*ISNUMBER($P$3:$P$165)*$P$3:$P$165),"") | T41: =IFERROR(SUMPRODUCT(($D$3:$D$165=D41)*ISNUMBER($P$3:$P$165)*$P$3:$P$165*$F$3:$F$165)/SUMPRODUCT(($D$3:$D$165=D41)*ISNUMBER($P$3:$P$165)*$P$3:$P$165),"") | U41: =IFERROR(SUMPRODUCT(($C$3:$C$165=C41)*ISNUMBER($P$3:$P$165)*$P$3:$P$165*$F$3:$F$165)/SUMPRODUCT(($C$3:$C$165=C41)*ISNUMBER($P$3:$P$165)*$P$3:$P$165),"") | V41: =IF(OR(T41="",U41=""),"",T41/U41) | W41: =IF(OR(S41="",T41=""),"",S41/T41) | X41: =IF(S41="","",F41/S41) | Y41: =IF(V41="",N41,INDEX('4_UK_L1_Input'!$C$4:$C$14,MATCH($C41,'4_UK_L1_Input'!$A$4:$A$14,0))*V41*W41*X41) | Z41: =IF(V41="","BETA FALLBACK","REAL (Bloomberg UK)") | AA41: =IFERROR(SUMPRODUCT(($C$3:$C$165=C41)*ISNUMBER($R$3:$R$165)*$Q$3:$Q$165*IF(ISNUMBER($R$3:$R$165),$R$3:$R$165,0))/SUMPRODUCT(($C$3:$C$165=C41)*ISNUMBER($R$3:$R$165)*$Q$3:$Q$165),"") | AB41: =IF(OR(R41="",AA41=""),"",R41/AA41) | AC41: =IF(AB41="",O41,INDEX('4_UK_L1_Input'!$D$4:$D$14,MATCH($C41,'4_UK_L1_Input'!$A$4:$A$14,0))*AB41) | AD41: =IF(AB41="","BETA FALLBACK","REAL (Bloomberg UK)") | AE41: =Y41-N41 | AF41: =AC41-O41
A42: 20202010 | B42: Human Resource & Employment Services | C42: 20 | D42: 2020 | E42: 202020 | F42: 0.811779 | G42: 1 | H42: =SUMPRODUCT(($E$3:$E$165=E42)*$G$3:$G$165*$F$3:$F$165)/SUMPRODUCT(($E$3:$E$165=E42)*$G$3:$G$165) | I42: =SUMPRODUCT(($D$3:$D$165=D42)*$G$3:$G$165*$F$3:$F$165)/SUMPRODUCT(($D$3:$D$165=D42)*$G$3:$G$165) | J42: =SUMPRODUCT(($C$3:$C$165=C42)*$G$3:$G$165*$F$3:$F$165)/SUMPRODUCT(($C$3:$C$165=C42)*$G$3:$G$165) | K42: =I42/J42 | L42: =H42/I42 | M42: =F42/H42 | N42: =INDEX('4_UK_L1_Input'!$C$4:$C$14,MATCH($C42,'4_UK_L1_Input'!$A$4:$A$14,0))*K42*L42*M42 | O42: =INDEX('4_UK_L1_Input'!$D$4:$D$14,MATCH($C42,'4_UK_L1_Input'!$A$4:$A$14,0))*K42*L42*M42 | P42: 1210000000 | Q42: 225530000 | R42: 9.43 | S42: =IFERROR(SUMPRODUCT(($E$3:$E$165=E42)*ISNUMBER($P$3:$P$165)*$P$3:$P$165*$F$3:$F$165)/SUMPRODUCT(($E$3:$E$165=E42)*ISNUMBER($P$3:$P$165)*$P$3:$P$165),"") | T42: =IFERROR(SUMPRODUCT(($D$3:$D$165=D42)*ISNUMBER($P$3:$P$165)*$P$3:$P$165*$F$3:$F$165)/SUMPRODUCT(($D$3:$D$165=D42)*ISNUMBER($P$3:$P$165)*$P$3:$P$165),"") | U42: =IFERROR(SUMPRODUCT(($C$3:$C$165=C42)*ISNUMBER($P$3:$P$165)*$P$3:$P$165*$F$3:$F$165)/SUMPRODUCT(($C$3:$C$165=C42)*ISNUMBER($P$3:$P$165)*$P$3:$P$165),"") | V42: =IF(OR(T42="",U42=""),"",T42/U42) | W42: =IF(OR(S42="",T42=""),"",S42/T42) | X42: =IF(S42="","",F42/S42) | Y42: =IF(V42="",N42,INDEX('4_UK_L1_Input'!$C$4:$C$14,MATCH($C42,'4_UK_L1_Input'!$A$4:$A$14,0))*V42*W42*X42) | Z42: =IF(V42="","BETA FALLBACK","REAL (Bloomberg UK)") | AA42: =IFERROR(SUMPRODUCT(($C$3:$C$165=C42)*ISNUMBER($R$3:$R$165)*$Q$3:$Q$165*IF(ISNUMBER($R$3:$R$165),$R$3:$R$165,0))/SUMPRODUCT(($C$3:$C$165=C42)*ISNUMBER($R$3:$R$165)*$Q$3:$Q$165),"") | AB42: =IF(OR(R42="",AA42=""),"",R42/AA42) | AC42: =IF(AB42="",O42,INDEX('4_UK_L1_Input'!$D$4:$D$14,MATCH($C42,'4_UK_L1_Input'!$A$4:$A$14,0))*AB42) | AD42: =IF(AB42="","BETA FALLBACK","REAL (Bloomberg UK)") | AE42: =Y42-N42 | AF42: =AC42-O42
A43: 20202020 | B43: Research & Consulting Services | C43: 20 | D43: 2020 | E43: 202020 | F43: 0.811779 | G43: 1 | H43: =SUMPRODUCT(($E$3:$E$165=E43)*$G$3:$G$165*$F$3:$F$165)/SUMPRODUCT(($E$3:$E$165=E43)*$G$3:$G$165) | I43: =SUMPRODUCT(($D$3:$D$165=D43)*$G$3:$G$165*$F$3:$F$165)/SUMPRODUCT(($D$3:$D$165=D43)*$G$3:$G$165) | J43: =SUMPRODUCT(($C$3:$C$165=C43)*$G$3:$G$165*$F$3:$F$165)/SUMPRODUCT(($C$3:$C$165=C43)*$G$3:$G$165) | K43: =I43/J43 | L43: =H43/I43 | M43: =F43/H43 | N43: =INDEX('4_UK_L1_Input'!$C$4:$C$14,MATCH($C43,'4_UK_L1_Input'!$A$4:$A$14,0))*K43*L43*M43 | O43: =INDEX('4_UK_L1_Input'!$D$4:$D$14,MATCH($C43,'4_UK_L1_Input'!$A$4:$A$14,0))*K43*L43*M43 | P43: 760740000 | Q43: 2380000000 | R43: 7.31 | S43: =IFERROR(SUMPRODUCT(($E$3:$E$165=E43)*ISNUMBER($P$3:$P$165)*$P$3:$P$165*$F$3:$F$165)/SUMPRODUCT(($E$3:$E$165=E43)*ISNUMBER($P$3:$P$165)*$P$3:$P$165),"") | T43: =IFERROR(SUMPRODUCT(($D$3:$D$165=D43)*ISNUMBER($P$3:$P$165)*$P$3:$P$165*$F$3:$F$165)/SUMPRODUCT(($D$3:$D$165=D43)*ISNUMBER($P$3:$P$165)*$P$3:$P$165),"") | U43: =IFERROR(SUMPRODUCT(($C$3:$C$165=C43)*ISNUMBER($P$3:$P$165)*$P$3:$P$165*$F$3:$F$165)/SUMPRODUCT(($C$3:$C$165=C43)*ISNUMBER($P$3:$P$165)*$P$3:$P$165),"") | V43: =IF(OR(T43="",U43=""),"",T43/U43) | W43: =IF(OR(S43="",T43=""),"",S43/T43) | X43: =IF(S43="","",F43/S43) | Y43: =IF(V43="",N43,INDEX('4_UK_L1_Input'!$C$4:$C$14,MATCH($C43,'4_UK_L1_Input'!$A$4:$A$14,0))*V43*W43*X43) | Z43: =IF(V43="","BETA FALLBACK","REAL (Bloomberg UK)") | AA43: =IFERROR(SUMPRODUCT(($C$3:$C$165=C43)*ISNUMBER($R$3:$R$165)*$Q$3:$Q$165*IF(ISNUMBER($R$3:$R$165),$R$3:$R$165,0))/SUMPRODUCT(($C$3:$C$165=C43)*ISNUMBER($R$3:$R$165)*$Q$3:$Q$165),"") | AB43: =IF(OR(R43="",AA43=""),"",R43/AA43) | AC43: =IF(AB43="",O43,INDEX('4_UK_L1_Input'!$D$4:$D$14,MATCH($C43,'4_UK_L1_Input'!$A$4:$A$14,0))*AB43) | AD43: =IF(AB43="","BETA FALLBACK","REAL (Bloomberg UK)") | AE43: =Y43-N43 | AF43: =AC43-O43
A44: 20202030 | B44: Data Processing & Outsourced Services | C44: 20 | D44: 2020 | E44: 202020 | F44: 0.953494 | G44: 1 | H44: =SUMPRODUCT(($E$3:$E$165=E44)*$G$3:$G$165*$F$3:$F$165)/SUMPRODUCT(($E$3:$E$165=E44)*$G$3:$G$165) | I44: =SUMPRODUCT(($D$3:$D$165=D44)*$G$3:$G$165*$F$3:$F$165)/SUMPRODUCT(($D$3:$D$165=D44)*$G$3:$G$165) | J44: =SUMPRODUCT(($C$3:$C$165=C44)*$G$3:$G$165*$F$3:$F$165)/SUMPRODUCT(($C$3:$C$165=C44)*$G$3:$G$165) | K44: =I44/J44 | L44: =H44/I44 | M44: =F44/H44 | N44: =INDEX('4_UK_L1_Input'!$C$4:$C$14,MATCH($C44,'4_UK_L1_Input'!$A$4:$A$14,0))*K44*L44*M44 | O44: =INDEX('4_UK_L1_Input'!$D$4:$D$14,MATCH($C44,'4_UK_L1_Input'!$A$4:$A$14,0))*K44*L44*M44 | P44: 279910000 | Q44: 318990000 | R44: 6.59 | S44: =IFERROR(SUMPRODUCT(($E$3:$E$165=E44)*ISNUMBER($P$3:$P$165)*$P$3:$P$165*$F$3:$F$165)/SUMPRODUCT(($E$3:$E$165=E44)*ISNUMBER($P$3:$P$165)*$P$3:$P$165),"") | T44: =IFERROR(SUMPRODUCT(($D$3:$D$165=D44)*ISNUMBER($P$3:$P$165)*$P$3:$P$165*$F$3:$F$165)/SUMPRODUCT(($D$3:$D$165=D44)*ISNUMBER($P$3:$P$165)*$P$3:$P$165),"") | U44: =IFERROR(SUMPRODUCT(($C$3:$C$165=C44)*ISNUMBER($P$3:$P$165)*$P$3:$P$165*$F$3:$F$165)/SUMPRODUCT(($C$3:$C$165=C44)*ISNUMBER($P$3:$P$165)*$P$3:$P$165),"") | V44: =IF(OR(T44="",U44=""),"",T44/U44) | W44: =IF(OR(S44="",T44=""),"",S44/T44) | X44: =IF(S44="","",F44/S44) | Y44: =IF(V44="",N44,INDEX('4_UK_L1_Input'!$C$4:$C$14,MATCH($C44,'4_UK_L1_Input'!$A$4:$A$14,0))*V44*W44*X44) | Z44: =IF(V44="","BETA FALLBACK","REAL (Bloomberg UK)") | AA44: =IFERROR(SUMPRODUCT(($C$3:$C$165=C44)*ISNUMBER($R$3:$R$165)*$Q$3:$Q$165*IF(ISNUMBER($R$3:$R$165),$R$3:$R$165,0))/SUMPRODUCT(($C$3:$C$165=C44)*ISNUMBER($R$3:$R$165)*$Q$3:$Q$165),"") | AB44: =IF(OR(R44="",AA44=""),"",R44/AA44) | AC44: =IF(AB44="",O44,INDEX('4_UK_L1_Input'!$D$4:$D$14,MATCH($C44,'4_UK_L1_Input'!$A$4:$A$14,0))*AB44) | AD44: =IF(AB44="","BETA FALLBACK","REAL (Bloomberg UK)") | AE44: =Y44-N44 | AF44: =AC44-O44
A45: 20301010 | B45: Air Freight & Logistics | C45: 20 | D45: 2030 | E45: 203010 | F45: 0.776851 | G45: 1 | H45: =SUMPRODUCT(($E$3:$E$165=E45)*$G$3:$G$165*$F$3:$F$165)/SUMPRODUCT(($E$3:$E$165=E45)*$G$3:$G$165) | I45: =SUMPRODUCT(($D$3:$D$165=D45)*$G$3:$G$165*$F$3:$F$165)/SUMPRODUCT(($D$3:$D$165=D45)*$G$3:$G$165) | J45: =SUMPRODUCT(($C$3:$C$165=C45)*$G$3:$G$165*$F$3:$F$165)/SUMPRODUCT(($C$3:$C$165=C45)*$G$3:$G$165) | K45: =I45/J45 | L45: =H45/I45 | M45: =F45/H45 | N45: =INDEX('4_UK_L1_Input'!$C$4:$C$14,MATCH($C45,'4_UK_L1_Input'!$A$4:$A$14,0))*K45*L45*M45 | O45: =INDEX('4_UK_L1_Input'!$D$4:$D$14,MATCH($C45,'4_UK_L1_Input'!$A$4:$A$14,0))*K45*L45*M45 | P45: 137040000 | Q45: 731310000 | R45: 6.05 | S45: =IFERROR(SUMPRODUCT(($E$3:$E$165=E45)*ISNUMBER($P$3:$P$165)*$P$3:$P$165*$F$3:$F$165)/SUMPRODUCT(($E$3:$E$165=E45)*ISNUMBER($P$3:$P$165)*$P$3:$P$165),"") | T45: =IFERROR(SUMPRODUCT(($D$3:$D$165=D45)*ISNUMBER($P$3:$P$165)*$P$3:$P$165*$F$3:$F$165)/SUMPRODUCT(($D$3:$D$165=D45)*ISNUMBER($P$3:$P$165)*$P$3:$P$165),"") | U45: =IFERROR(SUMPRODUCT(($C$3:$C$165=C45)*ISNUMBER($P$3:$P$165)*$P$3:$P$165*$F$3:$F$165)/SUMPRODUCT(($C$3:$C$165=C45)*ISNUMBER($P$3:$P$165)*$P$3:$P$165),"") | V45: =IF(OR(T45="",U45=""),"",T45/U45) | W45: =IF(OR(S45="",T45=""),"",S45/T45) | X45: =IF(S45="","",F45/S45) | Y45: =IF(V45="",N45,INDEX('4_UK_L1_Input'!$C$4:$C$14,MATCH($C45,'4_UK_L1_Input'!$A$4:$A$14,0))*V45*W45*X45) | Z45: =IF(V45="","BETA FALLBACK","REAL (Bloomberg UK)") | AA45: =IFERROR(SUMPRODUCT(($C$3:$C$165=C45)*ISNUMBER($R$3:$R$165)*$Q$3:$Q$165*IF(ISNUMBER($R$3:$R$165),$R$3:$R$165,0))/SUMPRODUCT(($C$3:$C$165=C45)*ISNUMBER($R$3:$R$165)*$Q$3:$Q$165),"") | AB45: =IF(OR(R45="",AA45=""),"",R45/AA45) | AC45: =IF(AB45="",O45,INDEX('4_UK_L1_Input'!$D$4:$D$14,MATCH($C45,'4_UK_L1_Input'!$A$4:$A$14,0))*AB45) | AD45: =IF(AB45="","BETA FALLBACK","REAL (Bloomberg UK)") | AE45: =Y45-N45 | AF45: =AC45-O45
A46: 20302010 | B46: Passenger Airlines | C46: 20 | D46: 2030 | E46: 203020 | F46: 0.801256 | G46: 1 | H46: =SUMPRODUCT(($E$3:$E$165=E46)*$G$3:$G$165*$F$3:$F$165)/SUMPRODUCT(($E$3:$E$165=E46)*$G$3:$G$165) | I46: =SUMPRODUCT(($D$3:$D$165=D46)*$G$3:$G$165*$F$3:$F$165)/SUMPRODUCT(($D$3:$D$165=D46)*$G$3:$G$165) | J46: =SUMPRODUCT(($C$3:$C$165=C46)*$G$3:$G$165*$F$3:$F$165)/SUMPRODUCT(($C$3:$C$165=C46)*$G$3:$G$165) | K46: =I46/J46 | L46: =H46/I46 | M46: =F46/H46 | N46: =INDEX('4_UK_L1_Input'!$C$4:$C$14,MATCH($C46,'4_UK_L1_Input'!$A$4:$A$14,0))*K46*L46*M46 | O46: =INDEX('4_UK_L1_Input'!$D$4:$D$14,MATCH($C46,'4_UK_L1_Input'!$A$4:$A$14,0))*K46*L46*M46 | P46: 17130000000 | Q46: 9190000000 | R46: 3.69 | S46: =IFERROR(SUMPRODUCT(($E$3:$E$165=E46)*ISNUMBER($P$3:$P$165)*$P$3:$P$165*$F$3:$F$165)/SUMPRODUCT(($E$3:$E$165=E46)*ISNUMBER($P$3:$P$165)*$P$3:$P$165),"") | T46: =IFERROR(SUMPRODUCT(($D$3:$D$165=D46)*ISNUMBER($P$3:$P$165)*$P$3:$P$165*$F$3:$F$165)/SUMPRODUCT(($D$3:$D$165=D46)*ISNUMBER($P$3:$P$165)*$P$3:$P$165),"") | U46: =IFERROR(SUMPRODUCT(($C$3:$C$165=C46)*ISNUMBER($P$3:$P$165)*$P$3:$P$165*$F$3:$F$165)/SUMPRODUCT(($C$3:$C$165=C46)*ISNUMBER($P$3:$P$165)*$P$3:$P$165),"") | V46: =IF(OR(T46="",U46=""),"",T46/U46) | W46: =IF(OR(S46="",T46=""),"",S46/T46) | X46: =IF(S46="","",F46/S46) | Y46: =IF(V46="",N46,INDEX('4_UK_L1_Input'!$C$4:$C$14,MATCH($C46,'4_UK_L1_Input'!$A$4:$A$14,0))*V46*W46*X46) | Z46: =IF(V46="","BETA FALLBACK","REAL (Bloomberg UK)") | AA46: =IFERROR(SUMPRODUCT(($C$3:$C$165=C46)*ISNUMBER($R$3:$R$165)*$Q$3:$Q$165*IF(ISNUMBER($R$3:$R$165),$R$3:$R$165,0))/SUMPRODUCT(($C$3:$C$165=C46)*ISNUMBER($R$3:$R$165)*$Q$3:$Q$165),"") | AB46: =IF(OR(R46="",AA46=""),"",R46/AA46) | AC46: =IF(AB46="",O46,INDEX('4_UK_L1_Input'!$D$4:$D$14,MATCH($C46,'4_UK_L1_Input'!$A$4:$A$14,0))*AB46) | AD46: =IF(AB46="","BETA FALLBACK","REAL (Bloomberg UK)") | AE46: =Y46-N46 | AF46: =AC46-O46
A47: 20303010 | B47: Marine Transportation | C47: 20 | D47: 2030 | E47: 203030 | F47: 0.794212 | G47: 1 | H47: =SUMPRODUCT(($E$3:$E$165=E47)*$G$3:$G$165*$F$3:$F$165)/SUMPRODUCT(($E$3:$E$165=E47)*$G$3:$G$165) | I47: =SUMPRODUCT(($D$3:$D$165=D47)*$G$3:$G$165*$F$3:$F$165)/SUMPRODUCT(($D$3:$D$165=D47)*$G$3:$G$165) | J47: =SUMPRODUCT(($C$3:$C$165=C47)*$G$3:$G$165*$F$3:$F$165)/SUMPRODUCT(($C$3:$C$165=C47)*$G$3:$G$165) | K47: =I47/J47 | L47: =H47/I47 | M47: =F47/H47 | N47: =INDEX('4_UK_L1_Input'!$C$4:$C$14,MATCH($C47,'4_UK_L1_Input'!$A$4:$A$14,0))*K47*L47*M47 | O47: =INDEX('4_UK_L1_Input'!$D$4:$D$14,MATCH($C47,'4_UK_L1_Input'!$A$4:$A$14,0))*K47*L47*M47 | P47: 1460000000 | Q47: 7130000000 | R47: 6 | S47: =IFERROR(SUMPRODUCT(($E$3:$E$165=E47)*ISNUMBER($P$3:$P$165)*$P$3:$P$165*$F$3:$F$165)/SUMPRODUCT(($E$3:$E$165=E47)*ISNUMBER($P$3:$P$165)*$P$3:$P$165),"") | T47: =IFERROR(SUMPRODUCT(($D$3:$D$165=D47)*ISNUMBER($P$3:$P$165)*$P$3:$P$165*$F$3:$F$165)/SUMPRODUCT(($D$3:$D$165=D47)*ISNUMBER($P$3:$P$165)*$P$3:$P$165),"") | U47: =IFERROR(SUMPRODUCT(($C$3:$C$165=C47)*ISNUMBER($P$3:$P$165)*$P$3:$P$165*$F$3:$F$165)/SUMPRODUCT(($C$3:$C$165=C47)*ISNUMBER($P$3:$P$165)*$P$3:$P$165),"") | V47: =IF(OR(T47="",U47=""),"",T47/U47) | W47: =IF(OR(S47="",T47=""),"",S47/T47) | X47: =IF(S47="","",F47/S47) | Y47: =IF(V47="",N47,INDEX('4_UK_L1_Input'!$C$4:$C$14,MATCH($C47,'4_UK_L1_Input'!$A$4:$A$14,0))*V47*W47*X47) | Z47: =IF(V47="","BETA FALLBACK","REAL (Bloomberg UK)") | AA47: =IFERROR(SUMPRODUCT(($C$3:$C$165=C47)*ISNUMBER($R$3:$R$165)*$Q$3:$Q$165*IF(ISNUMBER($R$3:$R$165),$R$3:$R$165,0))/SUMPRODUCT(($C$3:$C$165=C47)*ISNUMBER($R$3:$R$165)*$Q$3:$Q$165),"") | AB47: =IF(OR(R47="",AA47=""),"",R47/AA47) | AC47: =IF(AB47="",O47,INDEX('4_UK_L1_Input'!$D$4:$D$14,MATCH($C47,'4_UK_L1_Input'!$A$4:$A$14,0))*AB47) | AD47: =IF(AB47="","BETA FALLBACK","REAL (Bloomberg UK)") | AE47: =Y47-N47 | AF47: =AC47-O47
A48: 20304010 | B48: Rail Transportation | C48: 20 | D48: 2030 | E48: 203040 | F48: 0.87604 | G48: 1 | H48: =SUMPRODUCT(($E$3:$E$165=E48)*$G$3:$G$165*$F$3:$F$165)/SUMPRODUCT(($E$3:$E$165=E48)*$G$3:$G$165) | I48: =SUMPRODUCT(($D$3:$D$165=D48)*$G$3:$G$165*$F$3:$F$165)/SUMPRODUCT(($D$3:$D$165=D48)*$G$3:$G$165) | J48: =SUMPRODUCT(($C$3:$C$165=C48)*$G$3:$G$165*$F$3:$F$165)/SUMPRODUCT(($C$3:$C$165=C48)*$G$3:$G$165) | K48: =I48/J48 | L48: =H48/I48 | M48: =F48/H48 | N48: =INDEX('4_UK_L1_Input'!$C$4:$C$14,MATCH($C48,'4_UK_L1_Input'!$A$4:$A$14,0))*K48*L48*M48 | O48: =INDEX('4_UK_L1_Input'!$D$4:$D$14,MATCH($C48,'4_UK_L1_Input'!$A$4:$A$14,0))*K48*L48*M48 | P48: 4750000000 | Q48: 1010000000 | R48: 2.53 | S48: =IFERROR(SUMPRODUCT(($E$3:$E$165=E48)*ISNUMBER($P$3:$P$165)*$P$3:$P$165*$F$3:$F$165)/SUMPRODUCT(($E$3:$E$165=E48)*ISNUMBER($P$3:$P$165)*$P$3:$P$165),"") | T48: =IFERROR(SUMPRODUCT(($D$3:$D$165=D48)*ISNUMBER($P$3:$P$165)*$P$3:$P$165*$F$3:$F$165)/SUMPRODUCT(($D$3:$D$165=D48)*ISNUMBER($P$3:$P$165)*$P$3:$P$165),"") | U48: =IFERROR(SUMPRODUCT(($C$3:$C$165=C48)*ISNUMBER($P$3:$P$165)*$P$3:$P$165*$F$3:$F$165)/SUMPRODUCT(($C$3:$C$165=C48)*ISNUMBER($P$3:$P$165)*$P$3:$P$165),"") | V48: =IF(OR(T48="",U48=""),"",T48/U48) | W48: =IF(OR(S48="",T48=""),"",S48/T48) | X48: =IF(S48="","",F48/S48) | Y48: =IF(V48="",N48,INDEX('4_UK_L1_Input'!$C$4:$C$14,MATCH($C48,'4_UK_L1_Input'!$A$4:$A$14,0))*V48*W48*X48) | Z48: =IF(V48="","BETA FALLBACK","REAL (Bloomberg UK)") | AA48: =IFERROR(SUMPRODUCT(($C$3:$C$165=C48)*ISNUMBER($R$3:$R$165)*$Q$3:$Q$165*IF(ISNUMBER($R$3:$R$165),$R$3:$R$165,0))/SUMPRODUCT(($C$3:$C$165=C48)*ISNUMBER($R$3:$R$165)*$Q$3:$Q$165),"") | AB48: =IF(OR(R48="",AA48=""),"",R48/AA48) | AC48: =IF(AB48="",O48,INDEX('4_UK_L1_Input'!$D$4:$D$14,MATCH($C48,'4_UK_L1_Input'!$A$4:$A$14,0))*AB48) | AD48: =IF(AB48="","BETA FALLBACK","REAL (Bloomberg UK)") | AE48: =Y48-N48 | AF48: =AC48-O48
A49: 20304030 | B49: Cargo Ground Transportation | C49: 20 | D49: 2030 | E49: 203040 | F49: 0.877772 | G49: 1 | H49: =SUMPRODUCT(($E$3:$E$165=E49)*$G$3:$G$165*$F$3:$F$165)/SUMPRODUCT(($E$3:$E$165=E49)*$G$3:$G$165) | I49: =SUMPRODUCT(($D$3:$D$165=D49)*$G$3:$G$165*$F$3:$F$165)/SUMPRODUCT(($D$3:$D$165=D49)*$G$3:$G$165) | J49: =SUMPRODUCT(($C$3:$C$165=C49)*$G$3:$G$165*$F$3:$F$165)/SUMPRODUCT(($C$3:$C$165=C49)*$G$3:$G$165) | K49: =I49/J49 | L49: =H49/I49 | M49: =F49/H49 | N49: =INDEX('4_UK_L1_Input'!$C$4:$C$14,MATCH($C49,'4_UK_L1_Input'!$A$4:$A$14,0))*K49*L49*M49 | O49: =INDEX('4_UK_L1_Input'!$D$4:$D$14,MATCH($C49,'4_UK_L1_Input'!$A$4:$A$14,0))*K49*L49*M49 | S49: =IFERROR(SUMPRODUCT(($E$3:$E$165=E49)*ISNUMBER($P$3:$P$165)*$P$3:$P$165*$F$3:$F$165)/SUMPRODUCT(($E$3:$E$165=E49)*ISNUMBER($P$3:$P$165)*$P$3:$P$165),"") | T49: =IFERROR(SUMPRODUCT(($D$3:$D$165=D49)*ISNUMBER($P$3:$P$165)*$P$3:$P$165*$F$3:$F$165)/SUMPRODUCT(($D$3:$D$165=D49)*ISNUMBER($P$3:$P$165)*$P$3:$P$165),"") | U49: =IFERROR(SUMPRODUCT(($C$3:$C$165=C49)*ISNUMBER($P$3:$P$165)*$P$3:$P$165*$F$3:$F$165)/SUMPRODUCT(($C$3:$C$165=C49)*ISNUMBER($P$3:$P$165)*$P$3:$P$165),"") | V49: =IF(OR(T49="",U49=""),"",T49/U49) | W49: =IF(OR(S49="",T49=""),"",S49/T49) | X49: =IF(S49="","",F49/S49) | Y49: =IF(V49="",N49,INDEX('4_UK_L1_Input'!$C$4:$C$14,MATCH($C49,'4_UK_L1_Input'!$A$4:$A$14,0))*V49*W49*X49) | Z49: =IF(V49="","BETA FALLBACK","REAL (Bloomberg UK)") | AA49: =IFERROR(SUMPRODUCT(($C$3:$C$165=C49)*ISNUMBER($R$3:$R$165)*$Q$3:$Q$165*IF(ISNUMBER($R$3:$R$165),$R$3:$R$165,0))/SUMPRODUCT(($C$3:$C$165=C49)*ISNUMBER($R$3:$R$165)*$Q$3:$Q$165),"") | AB49: =IF(OR(R49="",AA49=""),"",R49/AA49) | AC49: =IF(AB49="",O49,INDEX('4_UK_L1_Input'!$D$4:$D$14,MATCH($C49,'4_UK_L1_Input'!$A$4:$A$14,0))*AB49) | AD49: =IF(AB49="","BETA FALLBACK","REAL (Bloomberg UK)") | AE49: =Y49-N49 | AF49: =AC49-O49
A50: 20304040 | B50: Passenger Ground Transportation | C50: 20 | D50: 2030 | E50: 203040 | F50: 0.776851 | G50: 1 | H50: =SUMPRODUCT(($E$3:$E$165=E50)*$G$3:$G$165*$F$3:$F$165)/SUMPRODUCT(($E$3:$E$165=E50)*$G$3:$G$165) | I50: =SUMPRODUCT(($D$3:$D$165=D50)*$G$3:$G$165*$F$3:$F$165)/SUMPRODUCT(($D$3:$D$165=D50)*$G$3:$G$165) | J50: =SUMPRODUCT(($C$3:$C$165=C50)*$G$3:$G$165*$F$3:$F$165)/SUMPRODUCT(($C$3:$C$165=C50)*$G$3:$G$165) | K50: =I50/J50 | L50: =H50/I50 | M50: =F50/H50 | N50: =INDEX('4_UK_L1_Input'!$C$4:$C$14,MATCH($C50,'4_UK_L1_Input'!$A$4:$A$14,0))*K50*L50*M50 | O50: =INDEX('4_UK_L1_Input'!$D$4:$D$14,MATCH($C50,'4_UK_L1_Input'!$A$4:$A$14,0))*K50*L50*M50 | P50: 2300000000 | Q50: 613190000 | R50: 3.68 | S50: =IFERROR(SUMPRODUCT(($E$3:$E$165=E50)*ISNUMBER($P$3:$P$165)*$P$3:$P$165*$F$3:$F$165)/SUMPRODUCT(($E$3:$E$165=E50)*ISNUMBER($P$3:$P$165)*$P$3:$P$165),"") | T50: =IFERROR(SUMPRODUCT(($D$3:$D$165=D50)*ISNUMBER($P$3:$P$165)*$P$3:$P$165*$F$3:$F$165)/SUMPRODUCT(($D$3:$D$165=D50)*ISNUMBER($P$3:$P$165)*$P$3:$P$165),"") | U50: =IFERROR(SUMPRODUCT(($C$3:$C$165=C50)*ISNUMBER($P$3:$P$165)*$P$3:$P$165*$F$3:$F$165)/SUMPRODUCT(($C$3:$C$165=C50)*ISNUMBER($P$3:$P$165)*$P$3:$P$165),"") | V50: =IF(OR(T50="",U50=""),"",T50/U50) | W50: =IF(OR(S50="",T50=""),"",S50/T50) | X50: =IF(S50="","",F50/S50) | Y50: =IF(V50="",N50,INDEX('4_UK_L1_Input'!$C$4:$C$14,MATCH($C50,'4_UK_L1_Input'!$A$4:$A$14,0))*V50*W50*X50) | Z50: =IF(V50="","BETA FALLBACK","REAL (Bloomberg UK)") | AA50: =IFERROR(SUMPRODUCT(($C$3:$C$165=C50)*ISNUMBER($R$3:$R$165)*$Q$3:$Q$165*IF(ISNUMBER($R$3:$R$165),$R$3:$R$165,0))/SUMPRODUCT(($C$3:$C$165=C50)*ISNUMBER($R$3:$R$165)*$Q$3:$Q$165),"") | AB50: =IF(OR(R50="",AA50=""),"",R50/AA50) | AC50: =IF(AB50="",O50,INDEX('4_UK_L1_Input'!$D$4:$D$14,MATCH($C50,'4_UK_L1_Input'!$A$4:$A$14,0))*AB50) | AD50: =IF(AB50="","BETA FALLBACK","REAL (Bloomberg UK)") | AE50: =Y50-N50 | AF50: =AC50-O50
A51: 20305010 | B51: Airport Services | C51: 20 | D51: 2030 | E51: 203050 | F51: 0.776851 | G51: 1 | H51: =SUMPRODUCT(($E$3:$E$165=E51)*$G$3:$G$165*$F$3:$F$165)/SUMPRODUCT(($E$3:$E$165=E51)*$G$3:$G$165) | I51: =SUMPRODUCT(($D$3:$D$165=D51)*$G$3:$G$165*$F$3:$F$165)/SUMPRODUCT(($D$3:$D$165=D51)*$G$3:$G$165) | J51: =SUMPRODUCT(($C$3:$C$165=C51)*$G$3:$G$165*$F$3:$F$165)/SUMPRODUCT(($C$3:$C$165=C51)*$G$3:$G$165) | K51: =I51/J51 | L51: =H51/I51 | M51: =F51/H51 | N51: =INDEX('4_UK_L1_Input'!$C$4:$C$14,MATCH($C51,'4_UK_L1_Input'!$A$4:$A$14,0))*K51*L51*M51 | O51: =INDEX('4_UK_L1_Input'!$D$4:$D$14,MATCH($C51,'4_UK_L1_Input'!$A$4:$A$14,0))*K51*L51*M51 | S51: =IFERROR(SUMPRODUCT(($E$3:$E$165=E51)*ISNUMBER($P$3:$P$165)*$P$3:$P$165*$F$3:$F$165)/SUMPRODUCT(($E$3:$E$165=E51)*ISNUMBER($P$3:$P$165)*$P$3:$P$165),"") | T51: =IFERROR(SUMPRODUCT(($D$3:$D$165=D51)*ISNUMBER($P$3:$P$165)*$P$3:$P$165*$F$3:$F$165)/SUMPRODUCT(($D$3:$D$165=D51)*ISNUMBER($P$3:$P$165)*$P$3:$P$165),"") | U51: =IFERROR(SUMPRODUCT(($C$3:$C$165=C51)*ISNUMBER($P$3:$P$165)*$P$3:$P$165*$F$3:$F$165)/SUMPRODUCT(($C$3:$C$165=C51)*ISNUMBER($P$3:$P$165)*$P$3:$P$165),"") | V51: =IF(OR(T51="",U51=""),"",T51/U51) | W51: =IF(OR(S51="",T51=""),"",S51/T51) | X51: =IF(S51="","",F51/S51) | Y51: =IF(V51="",N51,INDEX('4_UK_L1_Input'!$C$4:$C$14,MATCH($C51,'4_UK_L1_Input'!$A$4:$A$14,0))*V51*W51*X51) | Z51: =IF(V51="","BETA FALLBACK","REAL (Bloomberg UK)") | AA51: =IFERROR(SUMPRODUCT(($C$3:$C$165=C51)*ISNUMBER($R$3:$R$165)*$Q$3:$Q$165*IF(ISNUMBER($R$3:$R$165),$R$3:$R$165,0))/SUMPRODUCT(($C$3:$C$165=C51)*ISNUMBER($R$3:$R$165)*$Q$3:$Q$165),"") | AB51: =IF(OR(R51="",AA51=""),"",R51/AA51) | AC51: =IF(AB51="",O51,INDEX('4_UK_L1_Input'!$D$4:$D$14,MATCH($C51,'4_UK_L1_Input'!$A$4:$A$14,0))*AB51) | AD51: =IF(AB51="","BETA FALLBACK","REAL (Bloomberg UK)") | AE51: =Y51-N51 | AF51: =AC51-O51
A52: 20305020 | B52: Highways & Railtracks | C52: 20 | D52: 2030 | E52: 203050 | F52: 0.87604 | G52: 1 | H52: =SUMPRODUCT(($E$3:$E$165=E52)*$G$3:$G$165*$F$3:$F$165)/SUMPRODUCT(($E$3:$E$165=E52)*$G$3:$G$165) | I52: =SUMPRODUCT(($D$3:$D$165=D52)*$G$3:$G$165*$F$3:$F$165)/SUMPRODUCT(($D$3:$D$165=D52)*$G$3:$G$165) | J52: =SUMPRODUCT(($C$3:$C$165=C52)*$G$3:$G$165*$F$3:$F$165)/SUMPRODUCT(($C$3:$C$165=C52)*$G$3:$G$165) | K52: =I52/J52 | L52: =H52/I52 | M52: =F52/H52 | N52: =INDEX('4_UK_L1_Input'!$C$4:$C$14,MATCH($C52,'4_UK_L1_Input'!$A$4:$A$14,0))*K52*L52*M52 | O52: =INDEX('4_UK_L1_Input'!$D$4:$D$14,MATCH($C52,'4_UK_L1_Input'!$A$4:$A$14,0))*K52*L52*M52 | S52: =IFERROR(SUMPRODUCT(($E$3:$E$165=E52)*ISNUMBER($P$3:$P$165)*$P$3:$P$165*$F$3:$F$165)/SUMPRODUCT(($E$3:$E$165=E52)*ISNUMBER($P$3:$P$165)*$P$3:$P$165),"") | T52: =IFERROR(SUMPRODUCT(($D$3:$D$165=D52)*ISNUMBER($P$3:$P$165)*$P$3:$P$165*$F$3:$F$165)/SUMPRODUCT(($D$3:$D$165=D52)*ISNUMBER($P$3:$P$165)*$P$3:$P$165),"") | U52: =IFERROR(SUMPRODUCT(($C$3:$C$165=C52)*ISNUMBER($P$3:$P$165)*$P$3:$P$165*$F$3:$F$165)/SUMPRODUCT(($C$3:$C$165=C52)*ISNUMBER($P$3:$P$165)*$P$3:$P$165),"") | V52: =IF(OR(T52="",U52=""),"",T52/U52) | W52: =IF(OR(S52="",T52=""),"",S52/T52) | X52: =IF(S52="","",F52/S52) | Y52: =IF(V52="",N52,INDEX('4_UK_L1_Input'!$C$4:$C$14,MATCH($C52,'4_UK_L1_Input'!$A$4:$A$14,0))*V52*W52*X52) | Z52: =IF(V52="","BETA FALLBACK","REAL (Bloomberg UK)") | AA52: =IFERROR(SUMPRODUCT(($C$3:$C$165=C52)*ISNUMBER($R$3:$R$165)*$Q$3:$Q$165*IF(ISNUMBER($R$3:$R$165),$R$3:$R$165,0))/SUMPRODUCT(($C$3:$C$165=C52)*ISNUMBER($R$3:$R$165)*$Q$3:$Q$165),"") | AB52: =IF(OR(R52="",AA52=""),"",R52/AA52) | AC52: =IF(AB52="",O52,INDEX('4_UK_L1_Input'!$D$4:$D$14,MATCH($C52,'4_UK_L1_Input'!$A$4:$A$14,0))*AB52) | AD52: =IF(AB52="","BETA FALLBACK","REAL (Bloomberg UK)") | AE52: =Y52-N52 | AF52: =AC52-O52
A53: 20305030 | B53: Marine Ports & Services | C53: 20 | D53: 2030 | E53: 203050 | F53: 0.776851 | G53: 1 | H53: =SUMPRODUCT(($E$3:$E$165=E53)*$G$3:$G$165*$F$3:$F$165)/SUMPRODUCT(($E$3:$E$165=E53)*$G$3:$G$165) | I53: =SUMPRODUCT(($D$3:$D$165=D53)*$G$3:$G$165*$F$3:$F$165)/SUMPRODUCT(($D$3:$D$165=D53)*$G$3:$G$165) | J53: =SUMPRODUCT(($C$3:$C$165=C53)*$G$3:$G$165*$F$3:$F$165)/SUMPRODUCT(($C$3:$C$165=C53)*$G$3:$G$165) | K53: =I53/J53 | L53: =H53/I53 | M53: =F53/H53 | N53: =INDEX('4_UK_L1_Input'!$C$4:$C$14,MATCH($C53,'4_UK_L1_Input'!$A$4:$A$14,0))*K53*L53*M53 | O53: =INDEX('4_UK_L1_Input'!$D$4:$D$14,MATCH($C53,'4_UK_L1_Input'!$A$4:$A$14,0))*K53*L53*M53 | P53: 180500000 | Q53: 107990000 | R53: 4.85 | S53: =IFERROR(SUMPRODUCT(($E$3:$E$165=E53)*ISNUMBER($P$3:$P$165)*$P$3:$P$165*$F$3:$F$165)/SUMPRODUCT(($E$3:$E$165=E53)*ISNUMBER($P$3:$P$165)*$P$3:$P$165),"") | T53: =IFERROR(SUMPRODUCT(($D$3:$D$165=D53)*ISNUMBER($P$3:$P$165)*$P$3:$P$165*$F$3:$F$165)/SUMPRODUCT(($D$3:$D$165=D53)*ISNUMBER($P$3:$P$165)*$P$3:$P$165),"") | U53: =IFERROR(SUMPRODUCT(($C$3:$C$165=C53)*ISNUMBER($P$3:$P$165)*$P$3:$P$165*$F$3:$F$165)/SUMPRODUCT(($C$3:$C$165=C53)*ISNUMBER($P$3:$P$165)*$P$3:$P$165),"") | V53: =IF(OR(T53="",U53=""),"",T53/U53) | W53: =IF(OR(S53="",T53=""),"",S53/T53) | X53: =IF(S53="","",F53/S53) | Y53: =IF(V53="",N53,INDEX('4_UK_L1_Input'!$C$4:$C$14,MATCH($C53,'4_UK_L1_Input'!$A$4:$A$14,0))*V53*W53*X53) | Z53: =IF(V53="","BETA FALLBACK","REAL (Bloomberg UK)") | AA53: =IFERROR(SUMPRODUCT(($C$3:$C$165=C53)*ISNUMBER($R$3:$R$165)*$Q$3:$Q$165*IF(ISNUMBER($R$3:$R$165),$R$3:$R$165,0))/SUMPRODUCT(($C$3:$C$165=C53)*ISNUMBER($R$3:$R$165)*$Q$3:$Q$165),"") | AB53: =IF(OR(R53="",AA53=""),"",R53/AA53) | AC53: =IF(AB53="",O53,INDEX('4_UK_L1_Input'!$D$4:$D$14,MATCH($C53,'4_UK_L1_Input'!$A$4:$A$14,0))*AB53) | AD53: =IF(AB53="","BETA FALLBACK","REAL (Bloomberg UK)") | AE53: =Y53-N53 | AF53: =AC53-O53
A54: 25101010 | B54: Automotive Parts & Equipment | C54: 25 | D54: 2510 | E54: 251010 | F54: 1.077786 | G54: 1 | H54: =SUMPRODUCT(($E$3:$E$165=E54)*$G$3:$G$165*$F$3:$F$165)/SUMPRODUCT(($E$3:$E$165=E54)*$G$3:$G$165) | I54: =SUMPRODUCT(($D$3:$D$165=D54)*$G$3:$G$165*$F$3:$F$165)/SUMPRODUCT(($D$3:$D$165=D54)*$G$3:$G$165) | J54: =SUMPRODUCT(($C$3:$C$165=C54)*$G$3:$G$165*$F$3:$F$165)/SUMPRODUCT(($C$3:$C$165=C54)*$G$3:$G$165) | K54: =I54/J54 | L54: =H54/I54 | M54: =F54/H54 | N54: =INDEX('4_UK_L1_Input'!$C$4:$C$14,MATCH($C54,'4_UK_L1_Input'!$A$4:$A$14,0))*K54*L54*M54 | O54: =INDEX('4_UK_L1_Input'!$D$4:$D$14,MATCH($C54,'4_UK_L1_Input'!$A$4:$A$14,0))*K54*L54*M54 | P54: 127580000 | Q54: 86990000 | R54: 8.12 | S54: =IFERROR(SUMPRODUCT(($E$3:$E$165=E54)*ISNUMBER($P$3:$P$165)*$P$3:$P$165*$F$3:$F$165)/SUMPRODUCT(($E$3:$E$165=E54)*ISNUMBER($P$3:$P$165)*$P$3:$P$165),"") | T54: =IFERROR(SUMPRODUCT(($D$3:$D$165=D54)*ISNUMBER($P$3:$P$165)*$P$3:$P$165*$F$3:$F$165)/SUMPRODUCT(($D$3:$D$165=D54)*ISNUMBER($P$3:$P$165)*$P$3:$P$165),"") | U54: =IFERROR(SUMPRODUCT(($C$3:$C$165=C54)*ISNUMBER($P$3:$P$165)*$P$3:$P$165*$F$3:$F$165)/SUMPRODUCT(($C$3:$C$165=C54)*ISNUMBER($P$3:$P$165)*$P$3:$P$165),"") | V54: =IF(OR(T54="",U54=""),"",T54/U54) | W54: =IF(OR(S54="",T54=""),"",S54/T54) | X54: =IF(S54="","",F54/S54) | Y54: =IF(V54="",N54,INDEX('4_UK_L1_Input'!$C$4:$C$14,MATCH($C54,'4_UK_L1_Input'!$A$4:$A$14,0))*V54*W54*X54) | Z54: =IF(V54="","BETA FALLBACK","REAL (Bloomberg UK)") | AA54: =IFERROR(SUMPRODUCT(($C$3:$C$165=C54)*ISNUMBER($R$3:$R$165)*$Q$3:$Q$165*IF(ISNUMBER($R$3:$R$165),$R$3:$R$165,0))/SUMPRODUCT(($C$3:$C$165=C54)*ISNUMBER($R$3:$R$165)*$Q$3:$Q$165),"") | AB54: =IF(OR(R54="",AA54=""),"",R54/AA54) | AC54: =IF(AB54="",O54,INDEX('4_UK_L1_Input'!$D$4:$D$14,MATCH($C54,'4_UK_L1_Input'!$A$4:$A$14,0))*AB54) | AD54: =IF(AB54="","BETA FALLBACK","REAL (Bloomberg UK)") | AE54: =Y54-N54 | AF54: =AC54-O54
A55: 25101020 | B55: Tires & Rubber | C55: 25 | D55: 2510 | E55: 251010 | F55: 0.728673 | G55: 1 | H55: =SUMPRODUCT(($E$3:$E$165=E55)*$G$3:$G$165*$F$3:$F$165)/SUMPRODUCT(($E$3:$E$165=E55)*$G$3:$G$165) | I55: =SUMPRODUCT(($D$3:$D$165=D55)*$G$3:$G$165*$F$3:$F$165)/SUMPRODUCT(($D$3:$D$165=D55)*$G$3:$G$165) | J55: =SUMPRODUCT(($C$3:$C$165=C55)*$G$3:$G$165*$F$3:$F$165)/SUMPRODUCT(($C$3:$C$165=C55)*$G$3:$G$165) | K55: =I55/J55 | L55: =H55/I55 | M55: =F55/H55 | N55: =INDEX('4_UK_L1_Input'!$C$4:$C$14,MATCH($C55,'4_UK_L1_Input'!$A$4:$A$14,0))*K55*L55*M55 | O55: =INDEX('4_UK_L1_Input'!$D$4:$D$14,MATCH($C55,'4_UK_L1_Input'!$A$4:$A$14,0))*K55*L55*M55 | S55: =IFERROR(SUMPRODUCT(($E$3:$E$165=E55)*ISNUMBER($P$3:$P$165)*$P$3:$P$165*$F$3:$F$165)/SUMPRODUCT(($E$3:$E$165=E55)*ISNUMBER($P$3:$P$165)*$P$3:$P$165),"") | T55: =IFERROR(SUMPRODUCT(($D$3:$D$165=D55)*ISNUMBER($P$3:$P$165)*$P$3:$P$165*$F$3:$F$165)/SUMPRODUCT(($D$3:$D$165=D55)*ISNUMBER($P$3:$P$165)*$P$3:$P$165),"") | U55: =IFERROR(SUMPRODUCT(($C$3:$C$165=C55)*ISNUMBER($P$3:$P$165)*$P$3:$P$165*$F$3:$F$165)/SUMPRODUCT(($C$3:$C$165=C55)*ISNUMBER($P$3:$P$165)*$P$3:$P$165),"") | V55: =IF(OR(T55="",U55=""),"",T55/U55) | W55: =IF(OR(S55="",T55=""),"",S55/T55) | X55: =IF(S55="","",F55/S55) | Y55: =IF(V55="",N55,INDEX('4_UK_L1_Input'!$C$4:$C$14,MATCH($C55,'4_UK_L1_Input'!$A$4:$A$14,0))*V55*W55*X55) | Z55: =IF(V55="","BETA FALLBACK","REAL (Bloomberg UK)") | AA55: =IFERROR(SUMPRODUCT(($C$3:$C$165=C55)*ISNUMBER($R$3:$R$165)*$Q$3:$Q$165*IF(ISNUMBER($R$3:$R$165),$R$3:$R$165,0))/SUMPRODUCT(($C$3:$C$165=C55)*ISNUMBER($R$3:$R$165)*$Q$3:$Q$165),"") | AB55: =IF(OR(R55="",AA55=""),"",R55/AA55) | AC55: =IF(AB55="",O55,INDEX('4_UK_L1_Input'!$D$4:$D$14,MATCH($C55,'4_UK_L1_Input'!$A$4:$A$14,0))*AB55) | AD55: =IF(AB55="","BETA FALLBACK","REAL (Bloomberg UK)") | AE55: =Y55-N55 | AF55: =AC55-O55
A56: 25102010 | B56: Automobile Manufacturers | C56: 25 | D56: 2510 | E56: 251020 | F56: 1.213468 | G56: 1 | H56: =SUMPRODUCT(($E$3:$E$165=E56)*$G$3:$G$165*$F$3:$F$165)/SUMPRODUCT(($E$3:$E$165=E56)*$G$3:$G$165) | I56: =SUMPRODUCT(($D$3:$D$165=D56)*$G$3:$G$165*$F$3:$F$165)/SUMPRODUCT(($D$3:$D$165=D56)*$G$3:$G$165) | J56: =SUMPRODUCT(($C$3:$C$165=C56)*$G$3:$G$165*$F$3:$F$165)/SUMPRODUCT(($C$3:$C$165=C56)*$G$3:$G$165) | K56: =I56/J56 | L56: =H56/I56 | M56: =F56/H56 | N56: =INDEX('4_UK_L1_Input'!$C$4:$C$14,MATCH($C56,'4_UK_L1_Input'!$A$4:$A$14,0))*K56*L56*M56 | O56: =INDEX('4_UK_L1_Input'!$D$4:$D$14,MATCH($C56,'4_UK_L1_Input'!$A$4:$A$14,0))*K56*L56*M56 | P56: 1430000000 | Q56: 357390000 | R56: 6.3 | S56: =IFERROR(SUMPRODUCT(($E$3:$E$165=E56)*ISNUMBER($P$3:$P$165)*$P$3:$P$165*$F$3:$F$165)/SUMPRODUCT(($E$3:$E$165=E56)*ISNUMBER($P$3:$P$165)*$P$3:$P$165),"") | T56: =IFERROR(SUMPRODUCT(($D$3:$D$165=D56)*ISNUMBER($P$3:$P$165)*$P$3:$P$165*$F$3:$F$165)/SUMPRODUCT(($D$3:$D$165=D56)*ISNUMBER($P$3:$P$165)*$P$3:$P$165),"") | U56: =IFERROR(SUMPRODUCT(($C$3:$C$165=C56)*ISNUMBER($P$3:$P$165)*$P$3:$P$165*$F$3:$F$165)/SUMPRODUCT(($C$3:$C$165=C56)*ISNUMBER($P$3:$P$165)*$P$3:$P$165),"") | V56: =IF(OR(T56="",U56=""),"",T56/U56) | W56: =IF(OR(S56="",T56=""),"",S56/T56) | X56: =IF(S56="","",F56/S56) | Y56: =IF(V56="",N56,INDEX('4_UK_L1_Input'!$C$4:$C$14,MATCH($C56,'4_UK_L1_Input'!$A$4:$A$14,0))*V56*W56*X56) | Z56: =IF(V56="","BETA FALLBACK","REAL (Bloomberg UK)") | AA56: =IFERROR(SUMPRODUCT(($C$3:$C$165=C56)*ISNUMBER($R$3:$R$165)*$Q$3:$Q$165*IF(ISNUMBER($R$3:$R$165),$R$3:$R$165,0))/SUMPRODUCT(($C$3:$C$165=C56)*ISNUMBER($R$3:$R$165)*$Q$3:$Q$165),"") | AB56: =IF(OR(R56="",AA56=""),"",R56/AA56) | AC56: =IF(AB56="",O56,INDEX('4_UK_L1_Input'!$D$4:$D$14,MATCH($C56,'4_UK_L1_Input'!$A$4:$A$14,0))*AB56) | AD56: =IF(AB56="","BETA FALLBACK","REAL (Bloomberg UK)") | AE56: =Y56-N56 | AF56: =AC56-O56
A57: 25102020 | B57: Motorcycle Manufacturers | C57: 25 | D57: 2510 | E57: 251020 | F57: 1.213468 | G57: 1 | H57: =SUMPRODUCT(($E$3:$E$165=E57)*$G$3:$G$165*$F$3:$F$165)/SUMPRODUCT(($E$3:$E$165=E57)*$G$3:$G$165) | I57: =SUMPRODUCT(($D$3:$D$165=D57)*$G$3:$G$165*$F$3:$F$165)/SUMPRODUCT(($D$3:$D$165=D57)*$G$3:$G$165) | J57: =SUMPRODUCT(($C$3:$C$165=C57)*$G$3:$G$165*$F$3:$F$165)/SUMPRODUCT(($C$3:$C$165=C57)*$G$3:$G$165) | K57: =I57/J57 | L57: =H57/I57 | M57: =F57/H57 | N57: =INDEX('4_UK_L1_Input'!$C$4:$C$14,MATCH($C57,'4_UK_L1_Input'!$A$4:$A$14,0))*K57*L57*M57 | O57: =INDEX('4_UK_L1_Input'!$D$4:$D$14,MATCH($C57,'4_UK_L1_Input'!$A$4:$A$14,0))*K57*L57*M57 | Q57: 651000 | S57: =IFERROR(SUMPRODUCT(($E$3:$E$165=E57)*ISNUMBER($P$3:$P$165)*$P$3:$P$165*$F$3:$F$165)/SUMPRODUCT(($E$3:$E$165=E57)*ISNUMBER($P$3:$P$165)*$P$3:$P$165),"") | T57: =IFERROR(SUMPRODUCT(($D$3:$D$165=D57)*ISNUMBER($P$3:$P$165)*$P$3:$P$165*$F$3:$F$165)/SUMPRODUCT(($D$3:$D$165=D57)*ISNUMBER($P$3:$P$165)*$P$3:$P$165),"") | U57: =IFERROR(SUMPRODUCT(($C$3:$C$165=C57)*ISNUMBER($P$3:$P$165)*$P$3:$P$165*$F$3:$F$165)/SUMPRODUCT(($C$3:$C$165=C57)*ISNUMBER($P$3:$P$165)*$P$3:$P$165),"") | V57: =IF(OR(T57="",U57=""),"",T57/U57) | W57: =IF(OR(S57="",T57=""),"",S57/T57) | X57: =IF(S57="","",F57/S57) | Y57: =IF(V57="",N57,INDEX('4_UK_L1_Input'!$C$4:$C$14,MATCH($C57,'4_UK_L1_Input'!$A$4:$A$14,0))*V57*W57*X57) | Z57: =IF(V57="","BETA FALLBACK","REAL (Bloomberg UK)") | AA57: =IFERROR(SUMPRODUCT(($C$3:$C$165=C57)*ISNUMBER($R$3:$R$165)*$Q$3:$Q$165*IF(ISNUMBER($R$3:$R$165),$R$3:$R$165,0))/SUMPRODUCT(($C$3:$C$165=C57)*ISNUMBER($R$3:$R$165)*$Q$3:$Q$165),"") | AB57: =IF(OR(R57="",AA57=""),"",R57/AA57) | AC57: =IF(AB57="",O57,INDEX('4_UK_L1_Input'!$D$4:$D$14,MATCH($C57,'4_UK_L1_Input'!$A$4:$A$14,0))*AB57) | AD57: =IF(AB57="","BETA FALLBACK","REAL (Bloomberg UK)") | AE57: =Y57-N57 | AF57: =AC57-O57
A58: 25201010 | B58: Consumer Electronics | C58: 25 | D58: 2520 | E58: 252010 | F58: 0.912705 | G58: 1 | H58: =SUMPRODUCT(($E$3:$E$165=E58)*$G$3:$G$165*$F$3:$F$165)/SUMPRODUCT(($E$3:$E$165=E58)*$G$3:$G$165) | I58: =SUMPRODUCT(($D$3:$D$165=D58)*$G$3:$G$165*$F$3:$F$165)/SUMPRODUCT(($D$3:$D$165=D58)*$G$3:$G$165) | J58: =SUMPRODUCT(($C$3:$C$165=C58)*$G$3:$G$165*$F$3:$F$165)/SUMPRODUCT(($C$3:$C$165=C58)*$G$3:$G$165) | K58: =I58/J58 | L58: =H58/I58 | M58: =F58/H58 | N58: =INDEX('4_UK_L1_Input'!$C$4:$C$14,MATCH($C58,'4_UK_L1_Input'!$A$4:$A$14,0))*K58*L58*M58 | O58: =INDEX('4_UK_L1_Input'!$D$4:$D$14,MATCH($C58,'4_UK_L1_Input'!$A$4:$A$14,0))*K58*L58*M58 | P58: 196060000 | Q58: 117000000 | R58: 7.26 | S58: =IFERROR(SUMPRODUCT(($E$3:$E$165=E58)*ISNUMBER($P$3:$P$165)*$P$3:$P$165*$F$3:$F$165)/SUMPRODUCT(($E$3:$E$165=E58)*ISNUMBER($P$3:$P$165)*$P$3:$P$165),"") | T58: =IFERROR(SUMPRODUCT(($D$3:$D$165=D58)*ISNUMBER($P$3:$P$165)*$P$3:$P$165*$F$3:$F$165)/SUMPRODUCT(($D$3:$D$165=D58)*ISNUMBER($P$3:$P$165)*$P$3:$P$165),"") | U58: =IFERROR(SUMPRODUCT(($C$3:$C$165=C58)*ISNUMBER($P$3:$P$165)*$P$3:$P$165*$F$3:$F$165)/SUMPRODUCT(($C$3:$C$165=C58)*ISNUMBER($P$3:$P$165)*$P$3:$P$165),"") | V58: =IF(OR(T58="",U58=""),"",T58/U58) | W58: =IF(OR(S58="",T58=""),"",S58/T58) | X58: =IF(S58="","",F58/S58) | Y58: =IF(V58="",N58,INDEX('4_UK_L1_Input'!$C$4:$C$14,MATCH($C58,'4_UK_L1_Input'!$A$4:$A$14,0))*V58*W58*X58) | Z58: =IF(V58="","BETA FALLBACK","REAL (Bloomberg UK)") | AA58: =IFERROR(SUMPRODUCT(($C$3:$C$165=C58)*ISNUMBER($R$3:$R$165)*$Q$3:$Q$165*IF(ISNUMBER($R$3:$R$165),$R$3:$R$165,0))/SUMPRODUCT(($C$3:$C$165=C58)*ISNUMBER($R$3:$R$165)*$Q$3:$Q$165),"") | AB58: =IF(OR(R58="",AA58=""),"",R58/AA58) | AC58: =IF(AB58="",O58,INDEX('4_UK_L1_Input'!$D$4:$D$14,MATCH($C58,'4_UK_L1_Input'!$A$4:$A$14,0))*AB58) | AD58: =IF(AB58="","BETA FALLBACK","REAL (Bloomberg UK)") | AE58: =Y58-N58 | AF58: =AC58-O58
A59: 25201020 | B59: Home Furnishings | C59: 25 | D59: 2520 | E59: 252010 | F59: 0.719384 | G59: 1 | H59: =SUMPRODUCT(($E$3:$E$165=E59)*$G$3:$G$165*$F$3:$F$165)/SUMPRODUCT(($E$3:$E$165=E59)*$G$3:$G$165) | I59: =SUMPRODUCT(($D$3:$D$165=D59)*$G$3:$G$165*$F$3:$F$165)/SUMPRODUCT(($D$3:$D$165=D59)*$G$3:$G$165) | J59: =SUMPRODUCT(($C$3:$C$165=C59)*$G$3:$G$165*$F$3:$F$165)/SUMPRODUCT(($C$3:$C$165=C59)*$G$3:$G$165) | K59: =I59/J59 | L59: =H59/I59 | M59: =F59/H59 | N59: =INDEX('4_UK_L1_Input'!$C$4:$C$14,MATCH($C59,'4_UK_L1_Input'!$A$4:$A$14,0))*K59*L59*M59 | O59: =INDEX('4_UK_L1_Input'!$D$4:$D$14,MATCH($C59,'4_UK_L1_Input'!$A$4:$A$14,0))*K59*L59*M59 | P59: 321410000 | Q59: 52820000 | R59: 6.76 | S59: =IFERROR(SUMPRODUCT(($E$3:$E$165=E59)*ISNUMBER($P$3:$P$165)*$P$3:$P$165*$F$3:$F$165)/SUMPRODUCT(($E$3:$E$165=E59)*ISNUMBER($P$3:$P$165)*$P$3:$P$165),"") | T59: =IFERROR(SUMPRODUCT(($D$3:$D$165=D59)*ISNUMBER($P$3:$P$165)*$P$3:$P$165*$F$3:$F$165)/SUMPRODUCT(($D$3:$D$165=D59)*ISNUMBER($P$3:$P$165)*$P$3:$P$165),"") | U59: =IFERROR(SUMPRODUCT(($C$3:$C$165=C59)*ISNUMBER($P$3:$P$165)*$P$3:$P$165*$F$3:$F$165)/SUMPRODUCT(($C$3:$C$165=C59)*ISNUMBER($P$3:$P$165)*$P$3:$P$165),"") | V59: =IF(OR(T59="",U59=""),"",T59/U59) | W59: =IF(OR(S59="",T59=""),"",S59/T59) | X59: =IF(S59="","",F59/S59) | Y59: =IF(V59="",N59,INDEX('4_UK_L1_Input'!$C$4:$C$14,MATCH($C59,'4_UK_L1_Input'!$A$4:$A$14,0))*V59*W59*X59) | Z59: =IF(V59="","BETA FALLBACK","REAL (Bloomberg UK)") | AA59: =IFERROR(SUMPRODUCT(($C$3:$C$165=C59)*ISNUMBER($R$3:$R$165)*$Q$3:$Q$165*IF(ISNUMBER($R$3:$R$165),$R$3:$R$165,0))/SUMPRODUCT(($C$3:$C$165=C59)*ISNUMBER($R$3:$R$165)*$Q$3:$Q$165),"") | AB59: =IF(OR(R59="",AA59=""),"",R59/AA59) | AC59: =IF(AB59="",O59,INDEX('4_UK_L1_Input'!$D$4:$D$14,MATCH($C59,'4_UK_L1_Input'!$A$4:$A$14,0))*AB59) | AD59: =IF(AB59="","BETA FALLBACK","REAL (Bloomberg UK)") | AE59: =Y59-N59 | AF59: =AC59-O59
A60: 25201030 | B60: Homebuilding | C60: 25 | D60: 2520 | E60: 252010 | F60: 0.865159 | G60: 1 | H60: =SUMPRODUCT(($E$3:$E$165=E60)*$G$3:$G$165*$F$3:$F$165)/SUMPRODUCT(($E$3:$E$165=E60)*$G$3:$G$165) | I60: =SUMPRODUCT(($D$3:$D$165=D60)*$G$3:$G$165*$F$3:$F$165)/SUMPRODUCT(($D$3:$D$165=D60)*$G$3:$G$165) | J60: =SUMPRODUCT(($C$3:$C$165=C60)*$G$3:$G$165*$F$3:$F$165)/SUMPRODUCT(($C$3:$C$165=C60)*$G$3:$G$165) | K60: =I60/J60 | L60: =H60/I60 | M60: =F60/H60 | N60: =INDEX('4_UK_L1_Input'!$C$4:$C$14,MATCH($C60,'4_UK_L1_Input'!$A$4:$A$14,0))*K60*L60*M60 | O60: =INDEX('4_UK_L1_Input'!$D$4:$D$14,MATCH($C60,'4_UK_L1_Input'!$A$4:$A$14,0))*K60*L60*M60 | P60: 2020000000 | Q60: 1550000000 | R60: 7.39 | S60: =IFERROR(SUMPRODUCT(($E$3:$E$165=E60)*ISNUMBER($P$3:$P$165)*$P$3:$P$165*$F$3:$F$165)/SUMPRODUCT(($E$3:$E$165=E60)*ISNUMBER($P$3:$P$165)*$P$3:$P$165),"") | T60: =IFERROR(SUMPRODUCT(($D$3:$D$165=D60)*ISNUMBER($P$3:$P$165)*$P$3:$P$165*$F$3:$F$165)/SUMPRODUCT(($D$3:$D$165=D60)*ISNUMBER($P$3:$P$165)*$P$3:$P$165),"") | U60: =IFERROR(SUMPRODUCT(($C$3:$C$165=C60)*ISNUMBER($P$3:$P$165)*$P$3:$P$165*$F$3:$F$165)/SUMPRODUCT(($C$3:$C$165=C60)*ISNUMBER($P$3:$P$165)*$P$3:$P$165),"") | V60: =IF(OR(T60="",U60=""),"",T60/U60) | W60: =IF(OR(S60="",T60=""),"",S60/T60) | X60: =IF(S60="","",F60/S60) | Y60: =IF(V60="",N60,INDEX('4_UK_L1_Input'!$C$4:$C$14,MATCH($C60,'4_UK_L1_Input'!$A$4:$A$14,0))*V60*W60*X60) | Z60: =IF(V60="","BETA FALLBACK","REAL (Bloomberg UK)") | AA60: =IFERROR(SUMPRODUCT(($C$3:$C$165=C60)*ISNUMBER($R$3:$R$165)*$Q$3:$Q$165*IF(ISNUMBER($R$3:$R$165),$R$3:$R$165,0))/SUMPRODUCT(($C$3:$C$165=C60)*ISNUMBER($R$3:$R$165)*$Q$3:$Q$165),"") | AB60: =IF(OR(R60="",AA60=""),"",R60/AA60) | AC60: =IF(AB60="",O60,INDEX('4_UK_L1_Input'!$D$4:$D$14,MATCH($C60,'4_UK_L1_Input'!$A$4:$A$14,0))*AB60) | AD60: =IF(AB60="","BETA FALLBACK","REAL (Bloomberg UK)") | AE60: =Y60-N60 | AF60: =AC60-O60
A61: 25201040 | B61: Household Appliances | C61: 25 | D61: 2520 | E61: 252010 | F61: 0.719384 | G61: 1 | H61: =SUMPRODUCT(($E$3:$E$165=E61)*$G$3:$G$165*$F$3:$F$165)/SUMPRODUCT(($E$3:$E$165=E61)*$G$3:$G$165) | I61: =SUMPRODUCT(($D$3:$D$165=D61)*$G$3:$G$165*$F$3:$F$165)/SUMPRODUCT(($D$3:$D$165=D61)*$G$3:$G$165) | J61: =SUMPRODUCT(($C$3:$C$165=C61)*$G$3:$G$165*$F$3:$F$165)/SUMPRODUCT(($C$3:$C$165=C61)*$G$3:$G$165) | K61: =I61/J61 | L61: =H61/I61 | M61: =F61/H61 | N61: =INDEX('4_UK_L1_Input'!$C$4:$C$14,MATCH($C61,'4_UK_L1_Input'!$A$4:$A$14,0))*K61*L61*M61 | O61: =INDEX('4_UK_L1_Input'!$D$4:$D$14,MATCH($C61,'4_UK_L1_Input'!$A$4:$A$14,0))*K61*L61*M61 | P61: 426540000 | Q61: 300730000 | R61: 7.75 | S61: =IFERROR(SUMPRODUCT(($E$3:$E$165=E61)*ISNUMBER($P$3:$P$165)*$P$3:$P$165*$F$3:$F$165)/SUMPRODUCT(($E$3:$E$165=E61)*ISNUMBER($P$3:$P$165)*$P$3:$P$165),"") | T61: =IFERROR(SUMPRODUCT(($D$3:$D$165=D61)*ISNUMBER($P$3:$P$165)*$P$3:$P$165*$F$3:$F$165)/SUMPRODUCT(($D$3:$D$165=D61)*ISNUMBER($P$3:$P$165)*$P$3:$P$165),"") | U61: =IFERROR(SUMPRODUCT(($C$3:$C$165=C61)*ISNUMBER($P$3:$P$165)*$P$3:$P$165*$F$3:$F$165)/SUMPRODUCT(($C$3:$C$165=C61)*ISNUMBER($P$3:$P$165)*$P$3:$P$165),"") | V61: =IF(OR(T61="",U61=""),"",T61/U61) | W61: =IF(OR(S61="",T61=""),"",S61/T61) | X61: =IF(S61="","",F61/S61) | Y61: =IF(V61="",N61,INDEX('4_UK_L1_Input'!$C$4:$C$14,MATCH($C61,'4_UK_L1_Input'!$A$4:$A$14,0))*V61*W61*X61) | Z61: =IF(V61="","BETA FALLBACK","REAL (Bloomberg UK)") | AA61: =IFERROR(SUMPRODUCT(($C$3:$C$165=C61)*ISNUMBER($R$3:$R$165)*$Q$3:$Q$165*IF(ISNUMBER($R$3:$R$165),$R$3:$R$165,0))/SUMPRODUCT(($C$3:$C$165=C61)*ISNUMBER($R$3:$R$165)*$Q$3:$Q$165),"") | AB61: =IF(OR(R61="",AA61=""),"",R61/AA61) | AC61: =IF(AB61="",O61,INDEX('4_UK_L1_Input'!$D$4:$D$14,MATCH($C61,'4_UK_L1_Input'!$A$4:$A$14,0))*AB61) | AD61: =IF(AB61="","BETA FALLBACK","REAL (Bloomberg UK)") | AE61: =Y61-N61 | AF61: =AC61-O61
A62: 25201050 | B62: Housewares & Specialties | C62: 25 | D62: 2520 | E62: 252010 | F62: 0.719384 | G62: 1 | H62: =SUMPRODUCT(($E$3:$E$165=E62)*$G$3:$G$165*$F$3:$F$165)/SUMPRODUCT(($E$3:$E$165=E62)*$G$3:$G$165) | I62: =SUMPRODUCT(($D$3:$D$165=D62)*$G$3:$G$165*$F$3:$F$165)/SUMPRODUCT(($D$3:$D$165=D62)*$G$3:$G$165) | J62: =SUMPRODUCT(($C$3:$C$165=C62)*$G$3:$G$165*$F$3:$F$165)/SUMPRODUCT(($C$3:$C$165=C62)*$G$3:$G$165) | K62: =I62/J62 | L62: =H62/I62 | M62: =F62/H62 | N62: =INDEX('4_UK_L1_Input'!$C$4:$C$14,MATCH($C62,'4_UK_L1_Input'!$A$4:$A$14,0))*K62*L62*M62 | O62: =INDEX('4_UK_L1_Input'!$D$4:$D$14,MATCH($C62,'4_UK_L1_Input'!$A$4:$A$14,0))*K62*L62*M62 | P62: 128400000 | Q62: 55210000 | R62: 6.28 | S62: =IFERROR(SUMPRODUCT(($E$3:$E$165=E62)*ISNUMBER($P$3:$P$165)*$P$3:$P$165*$F$3:$F$165)/SUMPRODUCT(($E$3:$E$165=E62)*ISNUMBER($P$3:$P$165)*$P$3:$P$165),"") | T62: =IFERROR(SUMPRODUCT(($D$3:$D$165=D62)*ISNUMBER($P$3:$P$165)*$P$3:$P$165*$F$3:$F$165)/SUMPRODUCT(($D$3:$D$165=D62)*ISNUMBER($P$3:$P$165)*$P$3:$P$165),"") | U62: =IFERROR(SUMPRODUCT(($C$3:$C$165=C62)*ISNUMBER($P$3:$P$165)*$P$3:$P$165*$F$3:$F$165)/SUMPRODUCT(($C$3:$C$165=C62)*ISNUMBER($P$3:$P$165)*$P$3:$P$165),"") | V62: =IF(OR(T62="",U62=""),"",T62/U62) | W62: =IF(OR(S62="",T62=""),"",S62/T62) | X62: =IF(S62="","",F62/S62) | Y62: =IF(V62="",N62,INDEX('4_UK_L1_Input'!$C$4:$C$14,MATCH($C62,'4_UK_L1_Input'!$A$4:$A$14,0))*V62*W62*X62) | Z62: =IF(V62="","BETA FALLBACK","REAL (Bloomberg UK)") | AA62: =IFERROR(SUMPRODUCT(($C$3:$C$165=C62)*ISNUMBER($R$3:$R$165)*$Q$3:$Q$165*IF(ISNUMBER($R$3:$R$165),$R$3:$R$165,0))/SUMPRODUCT(($C$3:$C$165=C62)*ISNUMBER($R$3:$R$165)*$Q$3:$Q$165),"") | AB62: =IF(OR(R62="",AA62=""),"",R62/AA62) | AC62: =IF(AB62="",O62,INDEX('4_UK_L1_Input'!$D$4:$D$14,MATCH($C62,'4_UK_L1_Input'!$A$4:$A$14,0))*AB62) | AD62: =IF(AB62="","BETA FALLBACK","REAL (Bloomberg UK)") | AE62: =Y62-N62 | AF62: =AC62-O62
A63: 25202010 | B63: Leisure Products | C63: 25 | D63: 2520 | E63: 252020 | F63: 0.764375 | G63: 1 | H63: =SUMPRODUCT(($E$3:$E$165=E63)*$G$3:$G$165*$F$3:$F$165)/SUMPRODUCT(($E$3:$E$165=E63)*$G$3:$G$165) | I63: =SUMPRODUCT(($D$3:$D$165=D63)*$G$3:$G$165*$F$3:$F$165)/SUMPRODUCT(($D$3:$D$165=D63)*$G$3:$G$165) | J63: =SUMPRODUCT(($C$3:$C$165=C63)*$G$3:$G$165*$F$3:$F$165)/SUMPRODUCT(($C$3:$C$165=C63)*$G$3:$G$165) | K63: =I63/J63 | L63: =H63/I63 | M63: =F63/H63 | N63: =INDEX('4_UK_L1_Input'!$C$4:$C$14,MATCH($C63,'4_UK_L1_Input'!$A$4:$A$14,0))*K63*L63*M63 | O63: =INDEX('4_UK_L1_Input'!$D$4:$D$14,MATCH($C63,'4_UK_L1_Input'!$A$4:$A$14,0))*K63*L63*M63 | P63: 260530000 | Q63: 2100000000 | R63: 11.68 | S63: =IFERROR(SUMPRODUCT(($E$3:$E$165=E63)*ISNUMBER($P$3:$P$165)*$P$3:$P$165*$F$3:$F$165)/SUMPRODUCT(($E$3:$E$165=E63)*ISNUMBER($P$3:$P$165)*$P$3:$P$165),"") | T63: =IFERROR(SUMPRODUCT(($D$3:$D$165=D63)*ISNUMBER($P$3:$P$165)*$P$3:$P$165*$F$3:$F$165)/SUMPRODUCT(($D$3:$D$165=D63)*ISNUMBER($P$3:$P$165)*$P$3:$P$165),"") | U63: =IFERROR(SUMPRODUCT(($C$3:$C$165=C63)*ISNUMBER($P$3:$P$165)*$P$3:$P$165*$F$3:$F$165)/SUMPRODUCT(($C$3:$C$165=C63)*ISNUMBER($P$3:$P$165)*$P$3:$P$165),"") | V63: =IF(OR(T63="",U63=""),"",T63/U63) | W63: =IF(OR(S63="",T63=""),"",S63/T63) | X63: =IF(S63="","",F63/S63) | Y63: =IF(V63="",N63,INDEX('4_UK_L1_Input'!$C$4:$C$14,MATCH($C63,'4_UK_L1_Input'!$A$4:$A$14,0))*V63*W63*X63) | Z63: =IF(V63="","BETA FALLBACK","REAL (Bloomberg UK)") | AA63: =IFERROR(SUMPRODUCT(($C$3:$C$165=C63)*ISNUMBER($R$3:$R$165)*$Q$3:$Q$165*IF(ISNUMBER($R$3:$R$165),$R$3:$R$165,0))/SUMPRODUCT(($C$3:$C$165=C63)*ISNUMBER($R$3:$R$165)*$Q$3:$Q$165),"") | AB63: =IF(OR(R63="",AA63=""),"",R63/AA63) | AC63: =IF(AB63="",O63,INDEX('4_UK_L1_Input'!$D$4:$D$14,MATCH($C63,'4_UK_L1_Input'!$A$4:$A$14,0))*AB63) | AD63: =IF(AB63="","BETA FALLBACK","REAL (Bloomberg UK)") | AE63: =Y63-N63 | AF63: =AC63-O63
A64: 25203010 | B64: Apparel, Accessories & Luxury Goods | C64: 25 | D64: 2520 | E64: 252030 | F64: 0.818209 | G64: 1 | H64: =SUMPRODUCT(($E$3:$E$165=E64)*$G$3:$G$165*$F$3:$F$165)/SUMPRODUCT(($E$3:$E$165=E64)*$G$3:$G$165) | I64: =SUMPRODUCT(($D$3:$D$165=D64)*$G$3:$G$165*$F$3:$F$165)/SUMPRODUCT(($D$3:$D$165=D64)*$G$3:$G$165) | J64: =SUMPRODUCT(($C$3:$C$165=C64)*$G$3:$G$165*$F$3:$F$165)/SUMPRODUCT(($C$3:$C$165=C64)*$G$3:$G$165) | K64: =I64/J64 | L64: =H64/I64 | M64: =F64/H64 | N64: =INDEX('4_UK_L1_Input'!$C$4:$C$14,MATCH($C64,'4_UK_L1_Input'!$A$4:$A$14,0))*K64*L64*M64 | O64: =INDEX('4_UK_L1_Input'!$D$4:$D$14,MATCH($C64,'4_UK_L1_Input'!$A$4:$A$14,0))*K64*L64*M64 | P64: 1210000000 | Q64: 1020000000 | R64: 7.24 | S64: =IFERROR(SUMPRODUCT(($E$3:$E$165=E64)*ISNUMBER($P$3:$P$165)*$P$3:$P$165*$F$3:$F$165)/SUMPRODUCT(($E$3:$E$165=E64)*ISNUMBER($P$3:$P$165)*$P$3:$P$165),"") | T64: =IFERROR(SUMPRODUCT(($D$3:$D$165=D64)*ISNUMBER($P$3:$P$165)*$P$3:$P$165*$F$3:$F$165)/SUMPRODUCT(($D$3:$D$165=D64)*ISNUMBER($P$3:$P$165)*$P$3:$P$165),"") | U64: =IFERROR(SUMPRODUCT(($C$3:$C$165=C64)*ISNUMBER($P$3:$P$165)*$P$3:$P$165*$F$3:$F$165)/SUMPRODUCT(($C$3:$C$165=C64)*ISNUMBER($P$3:$P$165)*$P$3:$P$165),"") | V64: =IF(OR(T64="",U64=""),"",T64/U64) | W64: =IF(OR(S64="",T64=""),"",S64/T64) | X64: =IF(S64="","",F64/S64) | Y64: =IF(V64="",N64,INDEX('4_UK_L1_Input'!$C$4:$C$14,MATCH($C64,'4_UK_L1_Input'!$A$4:$A$14,0))*V64*W64*X64) | Z64: =IF(V64="","BETA FALLBACK","REAL (Bloomberg UK)") | AA64: =IFERROR(SUMPRODUCT(($C$3:$C$165=C64)*ISNUMBER($R$3:$R$165)*$Q$3:$Q$165*IF(ISNUMBER($R$3:$R$165),$R$3:$R$165,0))/SUMPRODUCT(($C$3:$C$165=C64)*ISNUMBER($R$3:$R$165)*$Q$3:$Q$165),"") | AB64: =IF(OR(R64="",AA64=""),"",R64/AA64) | AC64: =IF(AB64="",O64,INDEX('4_UK_L1_Input'!$D$4:$D$14,MATCH($C64,'4_UK_L1_Input'!$A$4:$A$14,0))*AB64) | AD64: =IF(AB64="","BETA FALLBACK","REAL (Bloomberg UK)") | AE64: =Y64-N64 | AF64: =AC64-O64
A65: 25203020 | B65: Footwear | C65: 25 | D65: 2520 | E65: 252030 | F65: 0.95294 | G65: 1 | H65: =SUMPRODUCT(($E$3:$E$165=E65)*$G$3:$G$165*$F$3:$F$165)/SUMPRODUCT(($E$3:$E$165=E65)*$G$3:$G$165) | I65: =SUMPRODUCT(($D$3:$D$165=D65)*$G$3:$G$165*$F$3:$F$165)/SUMPRODUCT(($D$3:$D$165=D65)*$G$3:$G$165) | J65: =SUMPRODUCT(($C$3:$C$165=C65)*$G$3:$G$165*$F$3:$F$165)/SUMPRODUCT(($C$3:$C$165=C65)*$G$3:$G$165) | K65: =I65/J65 | L65: =H65/I65 | M65: =F65/H65 | N65: =INDEX('4_UK_L1_Input'!$C$4:$C$14,MATCH($C65,'4_UK_L1_Input'!$A$4:$A$14,0))*K65*L65*M65 | O65: =INDEX('4_UK_L1_Input'!$D$4:$D$14,MATCH($C65,'4_UK_L1_Input'!$A$4:$A$14,0))*K65*L65*M65 | P65: 1470000000 | Q65: 3940000000 | R65: 7.46 | S65: =IFERROR(SUMPRODUCT(($E$3:$E$165=E65)*ISNUMBER($P$3:$P$165)*$P$3:$P$165*$F$3:$F$165)/SUMPRODUCT(($E$3:$E$165=E65)*ISNUMBER($P$3:$P$165)*$P$3:$P$165),"") | T65: =IFERROR(SUMPRODUCT(($D$3:$D$165=D65)*ISNUMBER($P$3:$P$165)*$P$3:$P$165*$F$3:$F$165)/SUMPRODUCT(($D$3:$D$165=D65)*ISNUMBER($P$3:$P$165)*$P$3:$P$165),"") | U65: =IFERROR(SUMPRODUCT(($C$3:$C$165=C65)*ISNUMBER($P$3:$P$165)*$P$3:$P$165*$F$3:$F$165)/SUMPRODUCT(($C$3:$C$165=C65)*ISNUMBER($P$3:$P$165)*$P$3:$P$165),"") | V65: =IF(OR(T65="",U65=""),"",T65/U65) | W65: =IF(OR(S65="",T65=""),"",S65/T65) | X65: =IF(S65="","",F65/S65) | Y65: =IF(V65="",N65,INDEX('4_UK_L1_Input'!$C$4:$C$14,MATCH($C65,'4_UK_L1_Input'!$A$4:$A$14,0))*V65*W65*X65) | Z65: =IF(V65="","BETA FALLBACK","REAL (Bloomberg UK)") | AA65: =IFERROR(SUMPRODUCT(($C$3:$C$165=C65)*ISNUMBER($R$3:$R$165)*$Q$3:$Q$165*IF(ISNUMBER($R$3:$R$165),$R$3:$R$165,0))/SUMPRODUCT(($C$3:$C$165=C65)*ISNUMBER($R$3:$R$165)*$Q$3:$Q$165),"") | AB65: =IF(OR(R65="",AA65=""),"",R65/AA65) | AC65: =IF(AB65="",O65,INDEX('4_UK_L1_Input'!$D$4:$D$14,MATCH($C65,'4_UK_L1_Input'!$A$4:$A$14,0))*AB65) | AD65: =IF(AB65="","BETA FALLBACK","REAL (Bloomberg UK)") | AE65: =Y65-N65 | AF65: =AC65-O65
A66: 25203030 | B66: Textiles | C66: 25 | D66: 2520 | E66: 252030 | F66: 0.818209 | G66: 1 | H66: =SUMPRODUCT(($E$3:$E$165=E66)*$G$3:$G$165*$F$3:$F$165)/SUMPRODUCT(($E$3:$E$165=E66)*$G$3:$G$165) | I66: =SUMPRODUCT(($D$3:$D$165=D66)*$G$3:$G$165*$F$3:$F$165)/SUMPRODUCT(($D$3:$D$165=D66)*$G$3:$G$165) | J66: =SUMPRODUCT(($C$3:$C$165=C66)*$G$3:$G$165*$F$3:$F$165)/SUMPRODUCT(($C$3:$C$165=C66)*$G$3:$G$165) | K66: =I66/J66 | L66: =H66/I66 | M66: =F66/H66 | N66: =INDEX('4_UK_L1_Input'!$C$4:$C$14,MATCH($C66,'4_UK_L1_Input'!$A$4:$A$14,0))*K66*L66*M66 | O66: =INDEX('4_UK_L1_Input'!$D$4:$D$14,MATCH($C66,'4_UK_L1_Input'!$A$4:$A$14,0))*K66*L66*M66 | P66: 1600000000 | Q66: 1660000000 | R66: 7.15 | S66: =IFERROR(SUMPRODUCT(($E$3:$E$165=E66)*ISNUMBER($P$3:$P$165)*$P$3:$P$165*$F$3:$F$165)/SUMPRODUCT(($E$3:$E$165=E66)*ISNUMBER($P$3:$P$165)*$P$3:$P$165),"") | T66: =IFERROR(SUMPRODUCT(($D$3:$D$165=D66)*ISNUMBER($P$3:$P$165)*$P$3:$P$165*$F$3:$F$165)/SUMPRODUCT(($D$3:$D$165=D66)*ISNUMBER($P$3:$P$165)*$P$3:$P$165),"") | U66: =IFERROR(SUMPRODUCT(($C$3:$C$165=C66)*ISNUMBER($P$3:$P$165)*$P$3:$P$165*$F$3:$F$165)/SUMPRODUCT(($C$3:$C$165=C66)*ISNUMBER($P$3:$P$165)*$P$3:$P$165),"") | V66: =IF(OR(T66="",U66=""),"",T66/U66) | W66: =IF(OR(S66="",T66=""),"",S66/T66) | X66: =IF(S66="","",F66/S66) | Y66: =IF(V66="",N66,INDEX('4_UK_L1_Input'!$C$4:$C$14,MATCH($C66,'4_UK_L1_Input'!$A$4:$A$14,0))*V66*W66*X66) | Z66: =IF(V66="","BETA FALLBACK","REAL (Bloomberg UK)") | AA66: =IFERROR(SUMPRODUCT(($C$3:$C$165=C66)*ISNUMBER($R$3:$R$165)*$Q$3:$Q$165*IF(ISNUMBER($R$3:$R$165),$R$3:$R$165,0))/SUMPRODUCT(($C$3:$C$165=C66)*ISNUMBER($R$3:$R$165)*$Q$3:$Q$165),"") | AB66: =IF(OR(R66="",AA66=""),"",R66/AA66) | AC66: =IF(AB66="",O66,INDEX('4_UK_L1_Input'!$D$4:$D$14,MATCH($C66,'4_UK_L1_Input'!$A$4:$A$14,0))*AB66) | AD66: =IF(AB66="","BETA FALLBACK","REAL (Bloomberg UK)") | AE66: =Y66-N66 | AF66: =AC66-O66
A67: 25301010 | B67: Casinos & Gaming | C67: 25 | D67: 2530 | E67: 253010 | F67: 0.879151 | G67: 1 | H67: =SUMPRODUCT(($E$3:$E$165=E67)*$G$3:$G$165*$F$3:$F$165)/SUMPRODUCT(($E$3:$E$165=E67)*$G$3:$G$165) | I67: =SUMPRODUCT(($D$3:$D$165=D67)*$G$3:$G$165*$F$3:$F$165)/SUMPRODUCT(($D$3:$D$165=D67)*$G$3:$G$165) | J67: =SUMPRODUCT(($C$3:$C$165=C67)*$G$3:$G$165*$F$3:$F$165)/SUMPRODUCT(($C$3:$C$165=C67)*$G$3:$G$165) | K67: =I67/J67 | L67: =H67/I67 | M67: =F67/H67 | N67: =INDEX('4_UK_L1_Input'!$C$4:$C$14,MATCH($C67,'4_UK_L1_Input'!$A$4:$A$14,0))*K67*L67*M67 | O67: =INDEX('4_UK_L1_Input'!$D$4:$D$14,MATCH($C67,'4_UK_L1_Input'!$A$4:$A$14,0))*K67*L67*M67 | P67: 1740000000 | Q67: 1610000000 | R67: 7.29 | S67: =IFERROR(SUMPRODUCT(($E$3:$E$165=E67)*ISNUMBER($P$3:$P$165)*$P$3:$P$165*$F$3:$F$165)/SUMPRODUCT(($E$3:$E$165=E67)*ISNUMBER($P$3:$P$165)*$P$3:$P$165),"") | T67: =IFERROR(SUMPRODUCT(($D$3:$D$165=D67)*ISNUMBER($P$3:$P$165)*$P$3:$P$165*$F$3:$F$165)/SUMPRODUCT(($D$3:$D$165=D67)*ISNUMBER($P$3:$P$165)*$P$3:$P$165),"") | U67: =IFERROR(SUMPRODUCT(($C$3:$C$165=C67)*ISNUMBER($P$3:$P$165)*$P$3:$P$165*$F$3:$F$165)/SUMPRODUCT(($C$3:$C$165=C67)*ISNUMBER($P$3:$P$165)*$P$3:$P$165),"") | V67: =IF(OR(T67="",U67=""),"",T67/U67) | W67: =IF(OR(S67="",T67=""),"",S67/T67) | X67: =IF(S67="","",F67/S67) | Y67: =IF(V67="",N67,INDEX('4_UK_L1_Input'!$C$4:$C$14,MATCH($C67,'4_UK_L1_Input'!$A$4:$A$14,0))*V67*W67*X67) | Z67: =IF(V67="","BETA FALLBACK","REAL (Bloomberg UK)") | AA67: =IFERROR(SUMPRODUCT(($C$3:$C$165=C67)*ISNUMBER($R$3:$R$165)*$Q$3:$Q$165*IF(ISNUMBER($R$3:$R$165),$R$3:$R$165,0))/SUMPRODUCT(($C$3:$C$165=C67)*ISNUMBER($R$3:$R$165)*$Q$3:$Q$165),"") | AB67: =IF(OR(R67="",AA67=""),"",R67/AA67) | AC67: =IF(AB67="",O67,INDEX('4_UK_L1_Input'!$D$4:$D$14,MATCH($C67,'4_UK_L1_Input'!$A$4:$A$14,0))*AB67) | AD67: =IF(AB67="","BETA FALLBACK","REAL (Bloomberg UK)") | AE67: =Y67-N67 | AF67: =AC67-O67
A68: 25301020 | B68: Hotels, Resorts & Cruise Lines | C68: 25 | D68: 2530 | E68: 253010 | F68: 0.879151 | G68: 1 | H68: =SUMPRODUCT(($E$3:$E$165=E68)*$G$3:$G$165*$F$3:$F$165)/SUMPRODUCT(($E$3:$E$165=E68)*$G$3:$G$165) | I68: =SUMPRODUCT(($D$3:$D$165=D68)*$G$3:$G$165*$F$3:$F$165)/SUMPRODUCT(($D$3:$D$165=D68)*$G$3:$G$165) | J68: =SUMPRODUCT(($C$3:$C$165=C68)*$G$3:$G$165*$F$3:$F$165)/SUMPRODUCT(($C$3:$C$165=C68)*$G$3:$G$165) | K68: =I68/J68 | L68: =H68/I68 | M68: =F68/H68 | N68: =INDEX('4_UK_L1_Input'!$C$4:$C$14,MATCH($C68,'4_UK_L1_Input'!$A$4:$A$14,0))*K68*L68*M68 | O68: =INDEX('4_UK_L1_Input'!$D$4:$D$14,MATCH($C68,'4_UK_L1_Input'!$A$4:$A$14,0))*K68*L68*M68 | P68: 1270000000 | Q68: 4130000000 | R68: 9.21 | S68: =IFERROR(SUMPRODUCT(($E$3:$E$165=E68)*ISNUMBER($P$3:$P$165)*$P$3:$P$165*$F$3:$F$165)/SUMPRODUCT(($E$3:$E$165=E68)*ISNUMBER($P$3:$P$165)*$P$3:$P$165),"") | T68: =IFERROR(SUMPRODUCT(($D$3:$D$165=D68)*ISNUMBER($P$3:$P$165)*$P$3:$P$165*$F$3:$F$165)/SUMPRODUCT(($D$3:$D$165=D68)*ISNUMBER($P$3:$P$165)*$P$3:$P$165),"") | U68: =IFERROR(SUMPRODUCT(($C$3:$C$165=C68)*ISNUMBER($P$3:$P$165)*$P$3:$P$165*$F$3:$F$165)/SUMPRODUCT(($C$3:$C$165=C68)*ISNUMBER($P$3:$P$165)*$P$3:$P$165),"") | V68: =IF(OR(T68="",U68=""),"",T68/U68) | W68: =IF(OR(S68="",T68=""),"",S68/T68) | X68: =IF(S68="","",F68/S68) | Y68: =IF(V68="",N68,INDEX('4_UK_L1_Input'!$C$4:$C$14,MATCH($C68,'4_UK_L1_Input'!$A$4:$A$14,0))*V68*W68*X68) | Z68: =IF(V68="","BETA FALLBACK","REAL (Bloomberg UK)") | AA68: =IFERROR(SUMPRODUCT(($C$3:$C$165=C68)*ISNUMBER($R$3:$R$165)*$Q$3:$Q$165*IF(ISNUMBER($R$3:$R$165),$R$3:$R$165,0))/SUMPRODUCT(($C$3:$C$165=C68)*ISNUMBER($R$3:$R$165)*$Q$3:$Q$165),"") | AB68: =IF(OR(R68="",AA68=""),"",R68/AA68) | AC68: =IF(AB68="",O68,INDEX('4_UK_L1_Input'!$D$4:$D$14,MATCH($C68,'4_UK_L1_Input'!$A$4:$A$14,0))*AB68) | AD68: =IF(AB68="","BETA FALLBACK","REAL (Bloomberg UK)") | AE68: =Y68-N68 | AF68: =AC68-O68
A69: 25301030 | B69: Leisure Facilities | C69: 25 | D69: 2530 | E69: 253010 | F69: 0.764375 | G69: 1 | H69: =SUMPRODUCT(($E$3:$E$165=E69)*$G$3:$G$165*$F$3:$F$165)/SUMPRODUCT(($E$3:$E$165=E69)*$G$3:$G$165) | I69: =SUMPRODUCT(($D$3:$D$165=D69)*$G$3:$G$165*$F$3:$F$165)/SUMPRODUCT(($D$3:$D$165=D69)*$G$3:$G$165) | J69: =SUMPRODUCT(($C$3:$C$165=C69)*$G$3:$G$165*$F$3:$F$165)/SUMPRODUCT(($C$3:$C$165=C69)*$G$3:$G$165) | K69: =I69/J69 | L69: =H69/I69 | M69: =F69/H69 | N69: =INDEX('4_UK_L1_Input'!$C$4:$C$14,MATCH($C69,'4_UK_L1_Input'!$A$4:$A$14,0))*K69*L69*M69 | O69: =INDEX('4_UK_L1_Input'!$D$4:$D$14,MATCH($C69,'4_UK_L1_Input'!$A$4:$A$14,0))*K69*L69*M69 | P69: 148090000 | Q69: 223280000 | R69: 6.4 | S69: =IFERROR(SUMPRODUCT(($E$3:$E$165=E69)*ISNUMBER($P$3:$P$165)*$P$3:$P$165*$F$3:$F$165)/SUMPRODUCT(($E$3:$E$165=E69)*ISNUMBER($P$3:$P$165)*$P$3:$P$165),"") | T69: =IFERROR(SUMPRODUCT(($D$3:$D$165=D69)*ISNUMBER($P$3:$P$165)*$P$3:$P$165*$F$3:$F$165)/SUMPRODUCT(($D$3:$D$165=D69)*ISNUMBER($P$3:$P$165)*$P$3:$P$165),"") | U69: =IFERROR(SUMPRODUCT(($C$3:$C$165=C69)*ISNUMBER($P$3:$P$165)*$P$3:$P$165*$F$3:$F$165)/SUMPRODUCT(($C$3:$C$165=C69)*ISNUMBER($P$3:$P$165)*$P$3:$P$165),"") | V69: =IF(OR(T69="",U69=""),"",T69/U69) | W69: =IF(OR(S69="",T69=""),"",S69/T69) | X69: =IF(S69="","",F69/S69) | Y69: =IF(V69="",N69,INDEX('4_UK_L1_Input'!$C$4:$C$14,MATCH($C69,'4_UK_L1_Input'!$A$4:$A$14,0))*V69*W69*X69) | Z69: =IF(V69="","BETA FALLBACK","REAL (Bloomberg UK)") | AA69: =IFERROR(SUMPRODUCT(($C$3:$C$165=C69)*ISNUMBER($R$3:$R$165)*$Q$3:$Q$165*IF(ISNUMBER($R$3:$R$165),$R$3:$R$165,0))/SUMPRODUCT(($C$3:$C$165=C69)*ISNUMBER($R$3:$R$165)*$Q$3:$Q$165),"") | AB69: =IF(OR(R69="",AA69=""),"",R69/AA69) | AC69: =IF(AB69="",O69,INDEX('4_UK_L1_Input'!$D$4:$D$14,MATCH($C69,'4_UK_L1_Input'!$A$4:$A$14,0))*AB69) | AD69: =IF(AB69="","BETA FALLBACK","REAL (Bloomberg UK)") | AE69: =Y69-N69 | AF69: =AC69-O69
... A80: 25504060 | B80: Homefurnishing Retail | C80: 25 | D80: 2550 | E80: 255040 | F80: 0.992175 | G80: 1 | H80: =SUMPRODUCT(($E$3:$E$165=E80)*$G$3:$G$165*$F$3:$F$165)/SUMPRODUCT(($E$3:$E$165=E80)*$G$3:$G$165) | I80: =SUMPRODUCT(($D$3:$D$165=D80)*$G$3:$G$165*$F$3:$F$165)/SUMPRODUCT(($D$3:$D$165=D80)*$G$3:$G$165) | J80: =SUMPRODUCT(($C$3:$C$165=C80)*$G$3:$G$165*$F$3:$F$165)/SUMPRODUCT(($C$3:$C$165=C80)*$G$3:$G$165) | K80: =I80/J80 | L80: =H80/I80 | M80: =F80/H80 | N80: =INDEX('4_UK_L1_Input'!$C$4:$C$14,MATCH($C80,'4_UK_L1_Input'!$A$4:$A$14,0))*K80*L80*M80 | O80: =INDEX('4_UK_L1_Input'!$D$4:$D$14,MATCH($C80,'4_UK_L1_Input'!$A$4:$A$14,0))*K80*L80*M80 | P80: 359370000 | Q80: 740720000 | R80: 4.6 | S80: =IFERROR(SUMPRODUCT(($E$3:$E$165=E80)*ISNUMBER($P$3:$P$165)*$P$3:$P$165*$F$3:$F$165)/SUMPRODUCT(($E$3:$E$165=E80)*ISNUMBER($P$3:$P$165)*$P$3:$P$165),"") | T80: =IFERROR(SUMPRODUCT(($D$3:$D$165=D80)*ISNUMBER($P$3:$P$165)*$P$3:$P$165*$F$3:$F$165)/SUMPRODUCT(($D$3:$D$165=D80)*ISNUMBER($P$3:$P$165)*$P$3:$P$165),"") | U80: =IFERROR(SUMPRODUCT(($C$3:$C$165=C80)*ISNUMBER($P$3:$P$165)*$P$3:$P$165*$F$3:$F$165)/SUMPRODUCT(($C$3:$C$165=C80)*ISNUMBER($P$3:$P$165)*$P$3:$P$165),"") | V80: =IF(OR(T80="",U80=""),"",T80/U80) | W80: =IF(OR(S80="",T80=""),"",S80/T80) | X80: =IF(S80="","",F80/S80) | Y80: =IF(V80="",N80,INDEX('4_UK_L1_Input'!$C$4:$C$14,MATCH($C80,'4_UK_L1_Input'!$A$4:$A$14,0))*V80*W80*X80) | Z80: =IF(V80="","BETA FALLBACK","REAL (Bloomberg UK)") | AA80: =IFERROR(SUMPRODUCT(($C$3:$C$165=C80)*ISNUMBER($R$3:$R$165)*$Q$3:$Q$165*IF(ISNUMBER($R$3:$R$165),$R$3:$R$165,0))/SUMPRODUCT(($C$3:$C$165=C80)*ISNUMBER($R$3:$R$165)*$Q$3:$Q$165),"") | AB80: =IF(OR(R80="",AA80=""),"",R80/AA80) | AC80: =IF(AB80="",O80,INDEX('4_UK_L1_Input'!$D$4:$D$14,MATCH($C80,'4_UK_L1_Input'!$A$4:$A$14,0))*AB80) | AD80: =IF(AB80="","BETA FALLBACK","REAL (Bloomberg UK)") | AE80: =Y80-N80 | AF80: =AC80-O80
A81: 30101010 | B81: Drug Retail | C81: 30 | D81: 3010 | E81: 301010 | F81: 0.869404 | G81: 1 | H81: =SUMPRODUCT(($E$3:$E$165=E81)*$G$3:$G$165*$F$3:$F$165)/SUMPRODUCT(($E$3:$E$165=E81)*$G$3:$G$165) | I81: =SUMPRODUCT(($D$3:$D$165=D81)*$G$3:$G$165*$F$3:$F$165)/SUMPRODUCT(($D$3:$D$165=D81)*$G$3:$G$165) | J81: =SUMPRODUCT(($C$3:$C$165=C81)*$G$3:$G$165*$F$3:$F$165)/SUMPRODUCT(($C$3:$C$165=C81)*$G$3:$G$165) | K81: =I81/J81 | L81: =H81/I81 | M81: =F81/H81 | N81: =INDEX('4_UK_L1_Input'!$C$4:$C$14,MATCH($C81,'4_UK_L1_Input'!$A$4:$A$14,0))*K81*L81*M81 | O81: =INDEX('4_UK_L1_Input'!$D$4:$D$14,MATCH($C81,'4_UK_L1_Input'!$A$4:$A$14,0))*K81*L81*M81 | Q81: 55230000 | S81: =IFERROR(SUMPRODUCT(($E$3:$E$165=E81)*ISNUMBER($P$3:$P$165)*$P$3:$P$165*$F$3:$F$165)/SUMPRODUCT(($E$3:$E$165=E81)*ISNUMBER($P$3:$P$165)*$P$3:$P$165),"") | T81: =IFERROR(SUMPRODUCT(($D$3:$D$165=D81)*ISNUMBER($P$3:$P$165)*$P$3:$P$165*$F$3:$F$165)/SUMPRODUCT(($D$3:$D$165=D81)*ISNUMBER($P$3:$P$165)*$P$3:$P$165),"") | U81: =IFERROR(SUMPRODUCT(($C$3:$C$165=C81)*ISNUMBER($P$3:$P$165)*$P$3:$P$165*$F$3:$F$165)/SUMPRODUCT(($C$3:$C$165=C81)*ISNUMBER($P$3:$P$165)*$P$3:$P$165),"") | V81: =IF(OR(T81="",U81=""),"",T81/U81) | W81: =IF(OR(S81="",T81=""),"",S81/T81) | X81: =IF(S81="","",F81/S81) | Y81: =IF(V81="",N81,INDEX('4_UK_L1_Input'!$C$4:$C$14,MATCH($C81,'4_UK_L1_Input'!$A$4:$A$14,0))*V81*W81*X81) | Z81: =IF(V81="","BETA FALLBACK","REAL (Bloomberg UK)") | AA81: =IFERROR(SUMPRODUCT(($C$3:$C$165=C81)*ISNUMBER($R$3:$R$165)*$Q$3:$Q$165*IF(ISNUMBER($R$3:$R$165),$R$3:$R$165,0))/SUMPRODUCT(($C$3:$C$165=C81)*ISNUMBER($R$3:$R$165)*$Q$3:$Q$165),"") | AB81: =IF(OR(R81="",AA81=""),"",R81/AA81) | AC81: =IF(AB81="",O81,INDEX('4_UK_L1_Input'!$D$4:$D$14,MATCH($C81,'4_UK_L1_Input'!$A$4:$A$14,0))*AB81) | AD81: =IF(AB81="","BETA FALLBACK","REAL (Bloomberg UK)") | AE81: =Y81-N81 | AF81: =AC81-O81
A82: 30101020 | B82: Food Distributors | C82: 30 | D82: 3010 | E82: 301010 | F82: 0.75785 | G82: 1 | H82: =SUMPRODUCT(($E$3:$E$165=E82)*$G$3:$G$165*$F$3:$F$165)/SUMPRODUCT(($E$3:$E$165=E82)*$G$3:$G$165) | I82: =SUMPRODUCT(($D$3:$D$165=D82)*$G$3:$G$165*$F$3:$F$165)/SUMPRODUCT(($D$3:$D$165=D82)*$G$3:$G$165) | J82: =SUMPRODUCT(($C$3:$C$165=C82)*$G$3:$G$165*$F$3:$F$165)/SUMPRODUCT(($C$3:$C$165=C82)*$G$3:$G$165) | K82: =I82/J82 | L82: =H82/I82 | M82: =F82/H82 | N82: =INDEX('4_UK_L1_Input'!$C$4:$C$14,MATCH($C82,'4_UK_L1_Input'!$A$4:$A$14,0))*K82*L82*M82 | O82: =INDEX('4_UK_L1_Input'!$D$4:$D$14,MATCH($C82,'4_UK_L1_Input'!$A$4:$A$14,0))*K82*L82*M82 | S82: =IFERROR(SUMPRODUCT(($E$3:$E$165=E82)*ISNUMBER($P$3:$P$165)*$P$3:$P$165*$F$3:$F$165)/SUMPRODUCT(($E$3:$E$165=E82)*ISNUMBER($P$3:$P$165)*$P$3:$P$165),"") | T82: =IFERROR(SUMPRODUCT(($D$3:$D$165=D82)*ISNUMBER($P$3:$P$165)*$P$3:$P$165*$F$3:$F$165)/SUMPRODUCT(($D$3:$D$165=D82)*ISNUMBER($P$3:$P$165)*$P$3:$P$165),"") | U82: =IFERROR(SUMPRODUCT(($C$3:$C$165=C82)*ISNUMBER($P$3:$P$165)*$P$3:$P$165*$F$3:$F$165)/SUMPRODUCT(($C$3:$C$165=C82)*ISNUMBER($P$3:$P$165)*$P$3:$P$165),"") | V82: =IF(OR(T82="",U82=""),"",T82/U82) | W82: =IF(OR(S82="",T82=""),"",S82/T82) | X82: =IF(S82="","",F82/S82) | Y82: =IF(V82="",N82,INDEX('4_UK_L1_Input'!$C$4:$C$14,MATCH($C82,'4_UK_L1_Input'!$A$4:$A$14,0))*V82*W82*X82) | Z82: =IF(V82="","BETA FALLBACK","REAL (Bloomberg UK)") | AA82: =IFERROR(SUMPRODUCT(($C$3:$C$165=C82)*ISNUMBER($R$3:$R$165)*$Q$3:$Q$165*IF(ISNUMBER($R$3:$R$165),$R$3:$R$165,0))/SUMPRODUCT(($C$3:$C$165=C82)*ISNUMBER($R$3:$R$165)*$Q$3:$Q$165),"") | AB82: =IF(OR(R82="",AA82=""),"",R82/AA82) | AC82: =IF(AB82="",O82,INDEX('4_UK_L1_Input'!$D$4:$D$14,MATCH($C82,'4_UK_L1_Input'!$A$4:$A$14,0))*AB82) | AD82: =IF(AB82="","BETA FALLBACK","REAL (Bloomberg UK)") | AE82: =Y82-N82 | AF82: =AC82-O82
A83: 30101030 | B83: Food Retail | C83: 30 | D83: 3010 | E83: 301010 | F83: 0.869404 | G83: 1 | H83: =SUMPRODUCT(($E$3:$E$165=E83)*$G$3:$G$165*$F$3:$F$165)/SUMPRODUCT(($E$3:$E$165=E83)*$G$3:$G$165) | I83: =SUMPRODUCT(($D$3:$D$165=D83)*$G$3:$G$165*$F$3:$F$165)/SUMPRODUCT(($D$3:$D$165=D83)*$G$3:$G$165) | J83: =SUMPRODUCT(($C$3:$C$165=C83)*$G$3:$G$165*$F$3:$F$165)/SUMPRODUCT(($C$3:$C$165=C83)*$G$3:$G$165) | K83: =I83/J83 | L83: =H83/I83 | M83: =F83/H83 | N83: =INDEX('4_UK_L1_Input'!$C$4:$C$14,MATCH($C83,'4_UK_L1_Input'!$A$4:$A$14,0))*K83*L83*M83 | O83: =INDEX('4_UK_L1_Input'!$D$4:$D$14,MATCH($C83,'4_UK_L1_Input'!$A$4:$A$14,0))*K83*L83*M83 | P83: 18100000000 | Q83: 6860000000 | R83: 5.77 | S83: =IFERROR(SUMPRODUCT(($E$3:$E$165=E83)*ISNUMBER($P$3:$P$165)*$P$3:$P$165*$F$3:$F$165)/SUMPRODUCT(($E$3:$E$165=E83)*ISNUMBER($P$3:$P$165)*$P$3:$P$165),"") | T83: =IFERROR(SUMPRODUCT(($D$3:$D$165=D83)*ISNUMBER($P$3:$P$165)*$P$3:$P$165*$F$3:$F$165)/SUMPRODUCT(($D$3:$D$165=D83)*ISNUMBER($P$3:$P$165)*$P$3:$P$165),"") | U83: =IFERROR(SUMPRODUCT(($C$3:$C$165=C83)*ISNUMBER($P$3:$P$165)*$P$3:$P$165*$F$3:$F$165)/SUMPRODUCT(($C$3:$C$165=C83)*ISNUMBER($P$3:$P$165)*$P$3:$P$165),"") | V83: =IF(OR(T83="",U83=""),"",T83/U83) | W83: =IF(OR(S83="",T83=""),"",S83/T83) | X83: =IF(S83="","",F83/S83) | Y83: =IF(V83="",N83,INDEX('4_UK_L1_Input'!$C$4:$C$14,MATCH($C83,'4_UK_L1_Input'!$A$4:$A$14,0))*V83*W83*X83) | Z83: =IF(V83="","BETA FALLBACK","REAL (Bloomberg UK)") | AA83: =IFERROR(SUMPRODUCT(($C$3:$C$165=C83)*ISNUMBER($R$3:$R$165)*$Q$3:$Q$165*IF(ISNUMBER($R$3:$R$165),$R$3:$R$165,0))/SUMPRODUCT(($C$3:$C$165=C83)*ISNUMBER($R$3:$R$165)*$Q$3:$Q$165),"") | AB83: =IF(OR(R83="",AA83=""),"",R83/AA83) | AC83: =IF(AB83="",O83,INDEX('4_UK_L1_Input'!$D$4:$D$14,MATCH($C83,'4_UK_L1_Input'!$A$4:$A$14,0))*AB83) | AD83: =IF(AB83="","BETA FALLBACK","REAL (Bloomberg UK)") | AE83: =Y83-N83 | AF83: =AC83-O83
A84: 30101040 | B84: Consumer Staples Merchandise Retail | C84: 30 | D84: 3010 | E84: 301010 | F84: 0.869404 | G84: 1 | H84: =SUMPRODUCT(($E$3:$E$165=E84)*$G$3:$G$165*$F$3:$F$165)/SUMPRODUCT(($E$3:$E$165=E84)*$G$3:$G$165) | I84: =SUMPRODUCT(($D$3:$D$165=D84)*$G$3:$G$165*$F$3:$F$165)/SUMPRODUCT(($D$3:$D$165=D84)*$G$3:$G$165) | J84: =SUMPRODUCT(($C$3:$C$165=C84)*$G$3:$G$165*$F$3:$F$165)/SUMPRODUCT(($C$3:$C$165=C84)*$G$3:$G$165) | K84: =I84/J84 | L84: =H84/I84 | M84: =F84/H84 | N84: =INDEX('4_UK_L1_Input'!$C$4:$C$14,MATCH($C84,'4_UK_L1_Input'!$A$4:$A$14,0))*K84*L84*M84 | O84: =INDEX('4_UK_L1_Input'!$D$4:$D$14,MATCH($C84,'4_UK_L1_Input'!$A$4:$A$14,0))*K84*L84*M84 | S84: =IFERROR(SUMPRODUCT(($E$3:$E$165=E84)*ISNUMBER($P$3:$P$165)*$P$3:$P$165*$F$3:$F$165)/SUMPRODUCT(($E$3:$E$165=E84)*ISNUMBER($P$3:$P$165)*$P$3:$P$165),"") | T84: =IFERROR(SUMPRODUCT(($D$3:$D$165=D84)*ISNUMBER($P$3:$P$165)*$P$3:$P$165*$F$3:$F$165)/SUMPRODUCT(($D$3:$D$165=D84)*ISNUMBER($P$3:$P$165)*$P$3:$P$165),"") | U84: =IFERROR(SUMPRODUCT(($C$3:$C$165=C84)*ISNUMBER($P$3:$P$165)*$P$3:$P$165*$F$3:$F$165)/SUMPRODUCT(($C$3:$C$165=C84)*ISNUMBER($P$3:$P$165)*$P$3:$P$165),"") | V84: =IF(OR(T84="",U84=""),"",T84/U84) | W84: =IF(OR(S84="",T84=""),"",S84/T84) | X84: =IF(S84="","",F84/S84) | Y84: =IF(V84="",N84,INDEX('4_UK_L1_Input'!$C$4:$C$14,MATCH($C84,'4_UK_L1_Input'!$A$4:$A$14,0))*V84*W84*X84) | Z84: =IF(V84="","BETA FALLBACK","REAL (Bloomberg UK)") | AA84: =IFERROR(SUMPRODUCT(($C$3:$C$165=C84)*ISNUMBER($R$3:$R$165)*$Q$3:$Q$165*IF(ISNUMBER($R$3:$R$165),$R$3:$R$165,0))/SUMPRODUCT(($C$3:$C$165=C84)*ISNUMBER($R$3:$R$165)*$Q$3:$Q$165),"") | AB84: =IF(OR(R84="",AA84=""),"",R84/AA84) | AC84: =IF(AB84="",O84,INDEX('4_UK_L1_Input'!$D$4:$D$14,MATCH($C84,'4_UK_L1_Input'!$A$4:$A$14,0))*AB84) | AD84: =IF(AB84="","BETA FALLBACK","REAL (Bloomberg UK)") | AE84: =Y84-N84 | AF84: =AC84-O84
A85: 30201010 | B85: Brewers | C85: 30 | D85: 3020 | E85: 302010 | F85: 0.741764 | G85: 1 | H85: =SUMPRODUCT(($E$3:$E$165=E85)*$G$3:$G$165*$F$3:$F$165)/SUMPRODUCT(($E$3:$E$165=E85)*$G$3:$G$165) | I85: =SUMPRODUCT(($D$3:$D$165=D85)*$G$3:$G$165*$F$3:$F$165)/SUMPRODUCT(($D$3:$D$165=D85)*$G$3:$G$165) | J85: =SUMPRODUCT(($C$3:$C$165=C85)*$G$3:$G$165*$F$3:$F$165)/SUMPRODUCT(($C$3:$C$165=C85)*$G$3:$G$165) | K85: =I85/J85 | L85: =H85/I85 | M85: =F85/H85 | N85: =INDEX('4_UK_L1_Input'!$C$4:$C$14,MATCH($C85,'4_UK_L1_Input'!$A$4:$A$14,0))*K85*L85*M85 | O85: =INDEX('4_UK_L1_Input'!$D$4:$D$14,MATCH($C85,'4_UK_L1_Input'!$A$4:$A$14,0))*K85*L85*M85 | P85: 113830000 | Q85: 44350000 | R85: 6.18 | S85: =IFERROR(SUMPRODUCT(($E$3:$E$165=E85)*ISNUMBER($P$3:$P$165)*$P$3:$P$165*$F$3:$F$165)/SUMPRODUCT(($E$3:$E$165=E85)*ISNUMBER($P$3:$P$165)*$P$3:$P$165),"") | T85: =IFERROR(SUMPRODUCT(($D$3:$D$165=D85)*ISNUMBER($P$3:$P$165)*$P$3:$P$165*$F$3:$F$165)/SUMPRODUCT(($D$3:$D$165=D85)*ISNUMBER($P$3:$P$165)*$P$3:$P$165),"") | U85: =IFERROR(SUMPRODUCT(($C$3:$C$165=C85)*ISNUMBER($P$3:$P$165)*$P$3:$P$165*$F$3:$F$165)/SUMPRODUCT(($C$3:$C$165=C85)*ISNUMBER($P$3:$P$165)*$P$3:$P$165),"") | V85: =IF(OR(T85="",U85=""),"",T85/U85) | W85: =IF(OR(S85="",T85=""),"",S85/T85) | X85: =IF(S85="","",F85/S85) | Y85: =IF(V85="",N85,INDEX('4_UK_L1_Input'!$C$4:$C$14,MATCH($C85,'4_UK_L1_Input'!$A$4:$A$14,0))*V85*W85*X85) | Z85: =IF(V85="","BETA FALLBACK","REAL (Bloomberg UK)") | AA85: =IFERROR(SUMPRODUCT(($C$3:$C$165=C85)*ISNUMBER($R$3:$R$165)*$Q$3:$Q$165*IF(ISNUMBER($R$3:$R$165),$R$3:$R$165,0))/SUMPRODUCT(($C$3:$C$165=C85)*ISNUMBER($R$3:$R$165)*$Q$3:$Q$165),"") | AB85: =IF(OR(R85="",AA85=""),"",R85/AA85) | AC85: =IF(AB85="",O85,INDEX('4_UK_L1_Input'!$D$4:$D$14,MATCH($C85,'4_UK_L1_Input'!$A$4:$A$14,0))*AB85) | AD85: =IF(AB85="","BETA FALLBACK","REAL (Bloomberg UK)") | AE85: =Y85-N85 | AF85: =AC85-O85
A86: 30201020 | B86: Distillers & Vintners | C86: 30 | D86: 3020 | E86: 302010 | F86: 0.741764 | G86: 1 | H86: =SUMPRODUCT(($E$3:$E$165=E86)*$G$3:$G$165*$F$3:$F$165)/SUMPRODUCT(($E$3:$E$165=E86)*$G$3:$G$165) | I86: =SUMPRODUCT(($D$3:$D$165=D86)*$G$3:$G$165*$F$3:$F$165)/SUMPRODUCT(($D$3:$D$165=D86)*$G$3:$G$165) | J86: =SUMPRODUCT(($C$3:$C$165=C86)*$G$3:$G$165*$F$3:$F$165)/SUMPRODUCT(($C$3:$C$165=C86)*$G$3:$G$165) | K86: =I86/J86 | L86: =H86/I86 | M86: =F86/H86 | N86: =INDEX('4_UK_L1_Input'!$C$4:$C$14,MATCH($C86,'4_UK_L1_Input'!$A$4:$A$14,0))*K86*L86*M86 | O86: =INDEX('4_UK_L1_Input'!$D$4:$D$14,MATCH($C86,'4_UK_L1_Input'!$A$4:$A$14,0))*K86*L86*M86 | P86: 4920000000 | Q86: 9990000000 | R86: 19.57 | S86: =IFERROR(SUMPRODUCT(($E$3:$E$165=E86)*ISNUMBER($P$3:$P$165)*$P$3:$P$165*$F$3:$F$165)/SUMPRODUCT(($E$3:$E$165=E86)*ISNUMBER($P$3:$P$165)*$P$3:$P$165),"") | T86: =IFERROR(SUMPRODUCT(($D$3:$D$165=D86)*ISNUMBER($P$3:$P$165)*$P$3:$P$165*$F$3:$F$165)/SUMPRODUCT(($D$3:$D$165=D86)*ISNUMBER($P$3:$P$165)*$P$3:$P$165),"") | U86: =IFERROR(SUMPRODUCT(($C$3:$C$165=C86)*ISNUMBER($P$3:$P$165)*$P$3:$P$165*$F$3:$F$165)/SUMPRODUCT(($C$3:$C$165=C86)*ISNUMBER($P$3:$P$165)*$P$3:$P$165),"") | V86: =IF(OR(T86="",U86=""),"",T86/U86) | W86: =IF(OR(S86="",T86=""),"",S86/T86) | X86: =IF(S86="","",F86/S86) | Y86: =IF(V86="",N86,INDEX('4_UK_L1_Input'!$C$4:$C$14,MATCH($C86,'4_UK_L1_Input'!$A$4:$A$14,0))*V86*W86*X86) | Z86: =IF(V86="","BETA FALLBACK","REAL (Bloomberg UK)") | AA86: =IFERROR(SUMPRODUCT(($C$3:$C$165=C86)*ISNUMBER($R$3:$R$165)*$Q$3:$Q$165*IF(ISNUMBER($R$3:$R$165),$R$3:$R$165,0))/SUMPRODUCT(($C$3:$C$165=C86)*ISNUMBER($R$3:$R$165)*$Q$3:$Q$165),"") | AB86: =IF(OR(R86="",AA86=""),"",R86/AA86) | AC86: =IF(AB86="",O86,INDEX('4_UK_L1_Input'!$D$4:$D$14,MATCH($C86,'4_UK_L1_Input'!$A$4:$A$14,0))*AB86) | AD86: =IF(AB86="","BETA FALLBACK","REAL (Bloomberg UK)") | AE86: =Y86-N86 | AF86: =AC86-O86
A87: 30201030 | B87: Soft Drinks & Non-alcoholic Beverages | C87: 30 | D87: 3020 | E87: 302010 | F87: 0.663439 | G87: 1 | H87: =SUMPRODUCT(($E$3:$E$165=E87)*$G$3:$G$165*$F$3:$F$165)/SUMPRODUCT(($E$3:$E$165=E87)*$G$3:$G$165) | I87: =SUMPRODUCT(($D$3:$D$165=D87)*$G$3:$G$165*$F$3:$F$165)/SUMPRODUCT(($D$3:$D$165=D87)*$G$3:$G$165) | J87: =SUMPRODUCT(($C$3:$C$165=C87)*$G$3:$G$165*$F$3:$F$165)/SUMPRODUCT(($C$3:$C$165=C87)*$G$3:$G$165) | K87: =I87/J87 | L87: =H87/I87 | M87: =F87/H87 | N87: =INDEX('4_UK_L1_Input'!$C$4:$C$14,MATCH($C87,'4_UK_L1_Input'!$A$4:$A$14,0))*K87*L87*M87 | O87: =INDEX('4_UK_L1_Input'!$D$4:$D$14,MATCH($C87,'4_UK_L1_Input'!$A$4:$A$14,0))*K87*L87*M87 | P87: 5570000000 | Q87: 12510000000 | R87: 11.96 | S87: =IFERROR(SUMPRODUCT(($E$3:$E$165=E87)*ISNUMBER($P$3:$P$165)*$P$3:$P$165*$F$3:$F$165)/SUMPRODUCT(($E$3:$E$165=E87)*ISNUMBER($P$3:$P$165)*$P$3:$P$165),"") | T87: =IFERROR(SUMPRODUCT(($D$3:$D$165=D87)*ISNUMBER($P$3:$P$165)*$P$3:$P$165*$F$3:$F$165)/SUMPRODUCT(($D$3:$D$165=D87)*ISNUMBER($P$3:$P$165)*$P$3:$P$165),"") | U87: =IFERROR(SUMPRODUCT(($C$3:$C$165=C87)*ISNUMBER($P$3:$P$165)*$P$3:$P$165*$F$3:$F$165)/SUMPRODUCT(($C$3:$C$165=C87)*ISNUMBER($P$3:$P$165)*$P$3:$P$165),"") | V87: =IF(OR(T87="",U87=""),"",T87/U87) | W87: =IF(OR(S87="",T87=""),"",S87/T87) | X87: =IF(S87="","",F87/S87) | Y87: =IF(V87="",N87,INDEX('4_UK_L1_Input'!$C$4:$C$14,MATCH($C87,'4_UK_L1_Input'!$A$4:$A$14,0))*V87*W87*X87) | Z87: =IF(V87="","BETA FALLBACK","REAL (Bloomberg UK)") | AA87: =IFERROR(SUMPRODUCT(($C$3:$C$165=C87)*ISNUMBER($R$3:$R$165)*$Q$3:$Q$165*IF(ISNUMBER($R$3:$R$165),$R$3:$R$165,0))/SUMPRODUCT(($C$3:$C$165=C87)*ISNUMBER($R$3:$R$165)*$Q$3:$Q$165),"") | AB87: =IF(OR(R87="",AA87=""),"",R87/AA87) | AC87: =IF(AB87="",O87,INDEX('4_UK_L1_Input'!$D$4:$D$14,MATCH($C87,'4_UK_L1_Input'!$A$4:$A$14,0))*AB87) | AD87: =IF(AB87="","BETA FALLBACK","REAL (Bloomberg UK)") | AE87: =Y87-N87 | AF87: =AC87-O87
A88: 30202010 | B88: Agricultural Products & Services | C88: 30 | D88: 3020 | E88: 302020 | F88: 0.858047 | G88: 1 | H88: =SUMPRODUCT(($E$3:$E$165=E88)*$G$3:$G$165*$F$3:$F$165)/SUMPRODUCT(($E$3:$E$165=E88)*$G$3:$G$165) | I88: =SUMPRODUCT(($D$3:$D$165=D88)*$G$3:$G$165*$F$3:$F$165)/SUMPRODUCT(($D$3:$D$165=D88)*$G$3:$G$165) | J88: =SUMPRODUCT(($C$3:$C$165=C88)*$G$3:$G$165*$F$3:$F$165)/SUMPRODUCT(($C$3:$C$165=C88)*$G$3:$G$165) | K88: =I88/J88 | L88: =H88/I88 | M88: =F88/H88 | N88: =INDEX('4_UK_L1_Input'!$C$4:$C$14,MATCH($C88,'4_UK_L1_Input'!$A$4:$A$14,0))*K88*L88*M88 | O88: =INDEX('4_UK_L1_Input'!$D$4:$D$14,MATCH($C88,'4_UK_L1_Input'!$A$4:$A$14,0))*K88*L88*M88 | P88: 700400000 | Q88: 316950000 | R88: 5.8 | S88: =IFERROR(SUMPRODUCT(($E$3:$E$165=E88)*ISNUMBER($P$3:$P$165)*$P$3:$P$165*$F$3:$F$165)/SUMPRODUCT(($E$3:$E$165=E88)*ISNUMBER($P$3:$P$165)*$P$3:$P$165),"") | T88: =IFERROR(SUMPRODUCT(($D$3:$D$165=D88)*ISNUMBER($P$3:$P$165)*$P$3:$P$165*$F$3:$F$165)/SUMPRODUCT(($D$3:$D$165=D88)*ISNUMBER($P$3:$P$165)*$P$3:$P$165),"") | U88: =IFERROR(SUMPRODUCT(($C$3:$C$165=C88)*ISNUMBER($P$3:$P$165)*$P$3:$P$165*$F$3:$F$165)/SUMPRODUCT(($C$3:$C$165=C88)*ISNUMBER($P$3:$P$165)*$P$3:$P$165),"") | V88: =IF(OR(T88="",U88=""),"",T88/U88) | W88: =IF(OR(S88="",T88=""),"",S88/T88) | X88: =IF(S88="","",F88/S88) | Y88: =IF(V88="",N88,INDEX('4_UK_L1_Input'!$C$4:$C$14,MATCH($C88,'4_UK_L1_Input'!$A$4:$A$14,0))*V88*W88*X88) | Z88: =IF(V88="","BETA FALLBACK","REAL (Bloomberg UK)") | AA88: =IFERROR(SUMPRODUCT(($C$3:$C$165=C88)*ISNUMBER($R$3:$R$165)*$Q$3:$Q$165*IF(ISNUMBER($R$3:$R$165),$R$3:$R$165,0))/SUMPRODUCT(($C$3:$C$165=C88)*ISNUMBER($R$3:$R$165)*$Q$3:$Q$165),"") | AB88: =IF(OR(R88="",AA88=""),"",R88/AA88) | AC88: =IF(AB88="",O88,INDEX('4_UK_L1_Input'!$D$4:$D$14,MATCH($C88,'4_UK_L1_Input'!$A$4:$A$14,0))*AB88) | AD88: =IF(AB88="","BETA FALLBACK","REAL (Bloomberg UK)") | AE88: =Y88-N88 | AF88: =AC88-O88
A89: 30202030 | B89: Packaged Foods & Meats | C89: 30 | D89: 3020 | E89: 302020 | F89: 0.518463 | G89: 1 | H89: =SUMPRODUCT(($E$3:$E$165=E89)*$G$3:$G$165*$F$3:$F$165)/SUMPRODUCT(($E$3:$E$165=E89)*$G$3:$G$165) | I89: =SUMPRODUCT(($D$3:$D$165=D89)*$G$3:$G$165*$F$3:$F$165)/SUMPRODUCT(($D$3:$D$165=D89)*$G$3:$G$165) | J89: =SUMPRODUCT(($C$3:$C$165=C89)*$G$3:$G$165*$F$3:$F$165)/SUMPRODUCT(($C$3:$C$165=C89)*$G$3:$G$165) | K89: =I89/J89 | L89: =H89/I89 | M89: =F89/H89 | N89: =INDEX('4_UK_L1_Input'!$C$4:$C$14,MATCH($C89,'4_UK_L1_Input'!$A$4:$A$14,0))*K89*L89*M89 | O89: =INDEX('4_UK_L1_Input'!$D$4:$D$14,MATCH($C89,'4_UK_L1_Input'!$A$4:$A$14,0))*K89*L89*M89 | P89: 3470000000 | Q89: 2520000000 | R89: 7.49 | S89: =IFERROR(SUMPRODUCT(($E$3:$E$165=E89)*ISNUMBER($P$3:$P$165)*$P$3:$P$165*$F$3:$F$165)/SUMPRODUCT(($E$3:$E$165=E89)*ISNUMBER($P$3:$P$165)*$P$3:$P$165),"") | T89: =IFERROR(SUMPRODUCT(($D$3:$D$165=D89)*ISNUMBER($P$3:$P$165)*$P$3:$P$165*$F$3:$F$165)/SUMPRODUCT(($D$3:$D$165=D89)*ISNUMBER($P$3:$P$165)*$P$3:$P$165),"") | U89: =IFERROR(SUMPRODUCT(($C$3:$C$165=C89)*ISNUMBER($P$3:$P$165)*$P$3:$P$165*$F$3:$F$165)/SUMPRODUCT(($C$3:$C$165=C89)*ISNUMBER($P$3:$P$165)*$P$3:$P$165),"") | V89: =IF(OR(T89="",U89=""),"",T89/U89) | W89: =IF(OR(S89="",T89=""),"",S89/T89) | X89: =IF(S89="","",F89/S89) | Y89: =IF(V89="",N89,INDEX('4_UK_L1_Input'!$C$4:$C$14,MATCH($C89,'4_UK_L1_Input'!$A$4:$A$14,0))*V89*W89*X89) | Z89: =IF(V89="","BETA FALLBACK","REAL (Bloomberg UK)") | AA89: =IFERROR(SUMPRODUCT(($C$3:$C$165=C89)*ISNUMBER($R$3:$R$165)*$Q$3:$Q$165*IF(ISNUMBER($R$3:$R$165),$R$3:$R$165,0))/SUMPRODUCT(($C$3:$C$165=C89)*ISNUMBER($R$3:$R$165)*$Q$3:$Q$165),"") | AB89: =IF(OR(R89="",AA89=""),"",R89/AA89) | AC89: =IF(AB89="",O89,INDEX('4_UK_L1_Input'!$D$4:$D$14,MATCH($C89,'4_UK_L1_Input'!$A$4:$A$14,0))*AB89) | AD89: =IF(AB89="","BETA FALLBACK","REAL (Bloomberg UK)") | AE89: =Y89-N89 | AF89: =AC89-O89
A90: 30203010 | B90: Tobacco | C90: 30 | D90: 3020 | E90: 302030 | F90: 0.795633 | G90: 1 | H90: =SUMPRODUCT(($E$3:$E$165=E90)*$G$3:$G$165*$F$3:$F$165)/SUMPRODUCT(($E$3:$E$165=E90)*$G$3:$G$165) | I90: =SUMPRODUCT(($D$3:$D$165=D90)*$G$3:$G$165*$F$3:$F$165)/SUMPRODUCT(($D$3:$D$165=D90)*$G$3:$G$165) | J90: =SUMPRODUCT(($C$3:$C$165=C90)*$G$3:$G$165*$F$3:$F$165)/SUMPRODUCT(($C$3:$C$165=C90)*$G$3:$G$165) | K90: =I90/J90 | L90: =H90/I90 | M90: =F90/H90 | N90: =INDEX('4_UK_L1_Input'!$C$4:$C$14,MATCH($C90,'4_UK_L1_Input'!$A$4:$A$14,0))*K90*L90*M90 | O90: =INDEX('4_UK_L1_Input'!$D$4:$D$14,MATCH($C90,'4_UK_L1_Input'!$A$4:$A$14,0))*K90*L90*M90 | P90: 26210000000 | Q90: 58530000000 | R90: 8.57 | S90: =IFERROR(SUMPRODUCT(($E$3:$E$165=E90)*ISNUMBER($P$3:$P$165)*$P$3:$P$165*$F$3:$F$165)/SUMPRODUCT(($E$3:$E$165=E90)*ISNUMBER($P$3:$P$165)*$P$3:$P$165),"") | T90: =IFERROR(SUMPRODUCT(($D$3:$D$165=D90)*ISNUMBER($P$3:$P$165)*$P$3:$P$165*$F$3:$F$165)/SUMPRODUCT(($D$3:$D$165=D90)*ISNUMBER($P$3:$P$165)*$P$3:$P$165),"") | U90: =IFERROR(SUMPRODUCT(($C$3:$C$165=C90)*ISNUMBER($P$3:$P$165)*$P$3:$P$165*$F$3:$F$165)/SUMPRODUCT(($C$3:$C$165=C90)*ISNUMBER($P$3:$P$165)*$P$3:$P$165),"") | V90: =IF(OR(T90="",U90=""),"",T90/U90) | W90: =IF(OR(S90="",T90=""),"",S90/T90) | X90: =IF(S90="","",F90/S90) | Y90: =IF(V90="",N90,INDEX('4_UK_L1_Input'!$C$4:$C$14,MATCH($C90,'4_UK_L1_Input'!$A$4:$A$14,0))*V90*W90*X90) | Z90: =IF(V90="","BETA FALLBACK","REAL (Bloomberg UK)") | AA90: =IFERROR(SUMPRODUCT(($C$3:$C$165=C90)*ISNUMBER($R$3:$R$165)*$Q$3:$Q$165*IF(ISNUMBER($R$3:$R$165),$R$3:$R$165,0))/SUMPRODUCT(($C$3:$C$165=C90)*ISNUMBER($R$3:$R$165)*$Q$3:$Q$165),"") | AB90: =IF(OR(R90="",AA90=""),"",R90/AA90) | AC90: =IF(AB90="",O90,INDEX('4_UK_L1_Input'!$D$4:$D$14,MATCH($C90,'4_UK_L1_Input'!$A$4:$A$14,0))*AB90) | AD90: =IF(AB90="","BETA FALLBACK","REAL (Bloomberg UK)") | AE90: =Y90-N90 | AF90: =AC90-O90
A91: 30301010 | B91: Household Products | C91: 30 | D91: 3030 | E91: 303010 | F91: 0.754401 | G91: 1 | H91: =SUMPRODUCT(($E$3:$E$165=E91)*$G$3:$G$165*$F$3:$F$165)/SUMPRODUCT(($E$3:$E$165=E91)*$G$3:$G$165) | I91: =SUMPRODUCT(($D$3:$D$165=D91)*$G$3:$G$165*$F$3:$F$165)/SUMPRODUCT(($D$3:$D$165=D91)*$G$3:$G$165) | J91: =SUMPRODUCT(($C$3:$C$165=C91)*$G$3:$G$165*$F$3:$F$165)/SUMPRODUCT(($C$3:$C$165=C91)*$G$3:$G$165) | K91: =I91/J91 | L91: =H91/I91 | M91: =F91/H91 | N91: =INDEX('4_UK_L1_Input'!$C$4:$C$14,MATCH($C91,'4_UK_L1_Input'!$A$4:$A$14,0))*K91*L91*M91 | O91: =INDEX('4_UK_L1_Input'!$D$4:$D$14,MATCH($C91,'4_UK_L1_Input'!$A$4:$A$14,0))*K91*L91*M91 | P91: 7280000000 | Q91: 16990000000 | R91: 8.12 | S91: =IFERROR(SUMPRODUCT(($E$3:$E$165=E91)*ISNUMBER($P$3:$P$165)*$P$3:$P$165*$F$3:$F$165)/SUMPRODUCT(($E$3:$E$165=E91)*ISNUMBER($P$3:$P$165)*$P$3:$P$165),"") | T91: =IFERROR(SUMPRODUCT(($D$3:$D$165=D91)*ISNUMBER($P$3:$P$165)*$P$3:$P$165*$F$3:$F$165)/SUMPRODUCT(($D$3:$D$165=D91)*ISNUMBER($P$3:$P$165)*$P$3:$P$165),"") | U91: =IFERROR(SUMPRODUCT(($C$3:$C$165=C91)*ISNUMBER($P$3:$P$165)*$P$3:$P$165*$F$3:$F$165)/SUMPRODUCT(($C$3:$C$165=C91)*ISNUMBER($P$3:$P$165)*$P$3:$P$165),"") | V91: =IF(OR(T91="",U91=""),"",T91/U91) | W91: =IF(OR(S91="",T91=""),"",S91/T91) | X91: =IF(S91="","",F91/S91) | Y91: =IF(V91="",N91,INDEX('4_UK_L1_Input'!$C$4:$C$14,MATCH($C91,'4_UK_L1_Input'!$A$4:$A$14,0))*V91*W91*X91) | Z91: =IF(V91="","BETA FALLBACK","REAL (Bloomberg UK)") | AA91: =IFERROR(SUMPRODUCT(($C$3:$C$165=C91)*ISNUMBER($R$3:$R$165)*$Q$3:$Q$165*IF(ISNUMBER($R$3:$R$165),$R$3:$R$165,0))/SUMPRODUCT(($C$3:$C$165=C91)*ISNUMBER($R$3:$R$165)*$Q$3:$Q$165),"") | AB91: =IF(OR(R91="",AA91=""),"",R91/AA91) | AC91: =IF(AB91="",O91,INDEX('4_UK_L1_Input'!$D$4:$D$14,MATCH($C91,'4_UK_L1_Input'!$A$4:$A$14,0))*AB91) | AD91: =IF(AB91="","BETA FALLBACK","REAL (Bloomberg UK)") | AE91: =Y91-N91 | AF91: =AC91-O91
A92: 30302010 | B92: Personal Care Products | C92: 30 | D92: 3030 | E92: 303020 | F92: 0.754401 | G92: 1 | H92: =SUMPRODUCT(($E$3:$E$165=E92)*$G$3:$G$165*$F$3:$F$165)/SUMPRODUCT(($E$3:$E$165=E92)*$G$3:$G$165) | I92: =SUMPRODUCT(($D$3:$D$165=D92)*$G$3:$G$165*$F$3:$F$165)/SUMPRODUCT(($D$3:$D$165=D92)*$G$3:$G$165) | J92: =SUMPRODUCT(($C$3:$C$165=C92)*$G$3:$G$165*$F$3:$F$165)/SUMPRODUCT(($C$3:$C$165=C92)*$G$3:$G$165) | K92: =I92/J92 | L92: =H92/I92 | M92: =F92/H92 | N92: =INDEX('4_UK_L1_Input'!$C$4:$C$14,MATCH($C92,'4_UK_L1_Input'!$A$4:$A$14,0))*K92*L92*M92 | O92: =INDEX('4_UK_L1_Input'!$D$4:$D$14,MATCH($C92,'4_UK_L1_Input'!$A$4:$A$14,0))*K92*L92*M92 | P92: 4710000000 | Q92: 10240000000 | R92: 10.41 | S92: =IFERROR(SUMPRODUCT(($E$3:$E$165=E92)*ISNUMBER($P$3:$P$165)*$P$3:$P$165*$F$3:$F$165)/SUMPRODUCT(($E$3:$E$165=E92)*ISNUMBER($P$3:$P$165)*$P$3:$P$165),"") | T92: =IFERROR(SUMPRODUCT(($D$3:$D$165=D92)*ISNUMBER($P$3:$P$165)*$P$3:$P$165*$F$3:$F$165)/SUMPRODUCT(($D$3:$D$165=D92)*ISNUMBER($P$3:$P$165)*$P$3:$P$165),"") | U92: =IFERROR(SUMPRODUCT(($C$3:$C$165=C92)*ISNUMBER($P$3:$P$165)*$P$3:$P$165*$F$3:$F$165)/SUMPRODUCT(($C$3:$C$165=C92)*ISNUMBER($P$3:$P$165)*$P$3:$P$165),"") | V92: =IF(OR(T92="",U92=""),"",T92/U92) | W92: =IF(OR(S92="",T92=""),"",S92/T92) | X92: =IF(S92="","",F92/S92) | Y92: =IF(V92="",N92,INDEX('4_UK_L1_Input'!$C$4:$C$14,MATCH($C92,'4_UK_L1_Input'!$A$4:$A$14,0))*V92*W92*X92) | Z92: =IF(V92="","BETA FALLBACK","REAL (Bloomberg UK)") | AA92: =IFERROR(SUMPRODUCT(($C$3:$C$165=C92)*ISNUMBER($R$3:$R$165)*$Q$3:$Q$165*IF(ISNUMBER($R$3:$R$165),$R$3:$R$165,0))/SUMPRODUCT(($C$3:$C$165=C92)*ISNUMBER($R$3:$R$165)*$Q$3:$Q$165),"") | AB92: =IF(OR(R92="",AA92=""),"",R92/AA92) | AC92: =IF(AB92="",O92,INDEX('4_UK_L1_Input'!$D$4:$D$14,MATCH($C92,'4_UK_L1_Input'!$A$4:$A$14,0))*AB92) | AD92: =IF(AB92="","BETA FALLBACK","REAL (Bloomberg UK)") | AE92: =Y92-N92 | AF92: =AC92-O92
A93: 35101010 | B93: Health Care Equipment | C93: 35 | D93: 3510 | E93: 351010 | F93: 0.859005 | G93: 1 | H93: =SUMPRODUCT(($E$3:$E$165=E93)*$G$3:$G$165*$F$3:$F$165)/SUMPRODUCT(($E$3:$E$165=E93)*$G$3:$G$165) | I93: =SUMPRODUCT(($D$3:$D$165=D93)*$G$3:$G$165*$F$3:$F$165)/SUMPRODUCT(($D$3:$D$165=D93)*$G$3:$G$165) | J93: =SUMPRODUCT(($C$3:$C$165=C93)*$G$3:$G$165*$F$3:$F$165)/SUMPRODUCT(($C$3:$C$165=C93)*$G$3:$G$165) | K93: =I93/J93 | L93: =H93/I93 | M93: =F93/H93 | N93: =INDEX('4_UK_L1_Input'!$C$4:$C$14,MATCH($C93,'4_UK_L1_Input'!$A$4:$A$14,0))*K93*L93*M93 | O93: =INDEX('4_UK_L1_Input'!$D$4:$D$14,MATCH($C93,'4_UK_L1_Input'!$A$4:$A$14,0))*K93*L93*M93 | P93: 795190000 | Q93: 1400000000 | R93: 13.59 | S93: =IFERROR(SUMPRODUCT(($E$3:$E$165=E93)*ISNUMBER($P$3:$P$165)*$P$3:$P$165*$F$3:$F$165)/SUMPRODUCT(($E$3:$E$165=E93)*ISNUMBER($P$3:$P$165)*$P$3:$P$165),"") | T93: =IFERROR(SUMPRODUCT(($D$3:$D$165=D93)*ISNUMBER($P$3:$P$165)*$P$3:$P$165*$F$3:$F$165)/SUMPRODUCT(($D$3:$D$165=D93)*ISNUMBER($P$3:$P$165)*$P$3:$P$165),"") | U93: =IFERROR(SUMPRODUCT(($C$3:$C$165=C93)*ISNUMBER($P$3:$P$165)*$P$3:$P$165*$F$3:$F$165)/SUMPRODUCT(($C$3:$C$165=C93)*ISNUMBER($P$3:$P$165)*$P$3:$P$165),"") | V93: =IF(OR(T93="",U93=""),"",T93/U93) | W93: =IF(OR(S93="",T93=""),"",S93/T93) | X93: =IF(S93="","",F93/S93) | Y93: =IF(V93="",N93,INDEX('4_UK_L1_Input'!$C$4:$C$14,MATCH($C93,'4_UK_L1_Input'!$A$4:$A$14,0))*V93*W93*X93) | Z93: =IF(V93="","BETA FALLBACK","REAL (Bloomberg UK)") | AA93: =IFERROR(SUMPRODUCT(($C$3:$C$165=C93)*ISNUMBER($R$3:$R$165)*$Q$3:$Q$165*IF(ISNUMBER($R$3:$R$165),$R$3:$R$165,0))/SUMPRODUCT(($C$3:$C$165=C93)*ISNUMBER($R$3:$R$165)*$Q$3:$Q$165),"") | AB93: =IF(OR(R93="",AA93=""),"",R93/AA93) | AC93: =IF(AB93="",O93,INDEX('4_UK_L1_Input'!$D$4:$D$14,MATCH($C93,'4_UK_L1_Input'!$A$4:$A$14,0))*AB93) | AD93: =IF(AB93="","BETA FALLBACK","REAL (Bloomberg UK)") | AE93: =Y93-N93 | AF93: =AC93-O93
A94: 35101020 | B94: Health Care Supplies | C94: 35 | D94: 3510 | E94: 351010 | F94: 0.859005 | G94: 1 | H94: =SUMPRODUCT(($E$3:$E$165=E94)*$G$3:$G$165*$F$3:$F$165)/SUMPRODUCT(($E$3:$E$165=E94)*$G$3:$G$165) | I94: =SUMPRODUCT(($D$3:$D$165=D94)*$G$3:$G$165*$F$3:$F$165)/SUMPRODUCT(($D$3:$D$165=D94)*$G$3:$G$165) | J94: =SUMPRODUCT(($C$3:$C$165=C94)*$G$3:$G$165*$F$3:$F$165)/SUMPRODUCT(($C$3:$C$165=C94)*$G$3:$G$165) | K94: =I94/J94 | L94: =H94/I94 | M94: =F94/H94 | N94: =INDEX('4_UK_L1_Input'!$C$4:$C$14,MATCH($C94,'4_UK_L1_Input'!$A$4:$A$14,0))*K94*L94*M94 | O94: =INDEX('4_UK_L1_Input'!$D$4:$D$14,MATCH($C94,'4_UK_L1_Input'!$A$4:$A$14,0))*K94*L94*M94 | P94: 112670000 | Q94: 787430000 | R94: 12.07 | S94: =IFERROR(SUMPRODUCT(($E$3:$E$165=E94)*ISNUMBER($P$3:$P$165)*$P$3:$P$165*$F$3:$F$165)/SUMPRODUCT(($E$3:$E$165=E94)*ISNUMBER($P$3:$P$165)*$P$3:$P$165),"") | T94: =IFERROR(SUMPRODUCT(($D$3:$D$165=D94)*ISNUMBER($P$3:$P$165)*$P$3:$P$165*$F$3:$F$165)/SUMPRODUCT(($D$3:$D$165=D94)*ISNUMBER($P$3:$P$165)*$P$3:$P$165),"") | U94: =IFERROR(SUMPRODUCT(($C$3:$C$165=C94)*ISNUMBER($P$3:$P$165)*$P$3:$P$165*$F$3:$F$165)/SUMPRODUCT(($C$3:$C$165=C94)*ISNUMBER($P$3:$P$165)*$P$3:$P$165),"") | V94: =IF(OR(T94="",U94=""),"",T94/U94) | W94: =IF(OR(S94="",T94=""),"",S94/T94) | X94: =IF(S94="","",F94/S94) | Y94: =IF(V94="",N94,INDEX('4_UK_L1_Input'!$C$4:$C$14,MATCH($C94,'4_UK_L1_Input'!$A$4:$A$14,0))*V94*W94*X94) | Z94: =IF(V94="","BETA FALLBACK","REAL (Bloomberg UK)") | AA94: =IFERROR(SUMPRODUCT(($C$3:$C$165=C94)*ISNUMBER($R$3:$R$165)*$Q$3:$Q$165*IF(ISNUMBER($R$3:$R$165),$R$3:$R$165,0))/SUMPRODUCT(($C$3:$C$165=C94)*ISNUMBER($R$3:$R$165)*$Q$3:$Q$165),"") | AB94: =IF(OR(R94="",AA94=""),"",R94/AA94) | AC94: =IF(AB94="",O94,INDEX('4_UK_L1_Input'!$D$4:$D$14,MATCH($C94,'4_UK_L1_Input'!$A$4:$A$14,0))*AB94) | AD94: =IF(AB94="","BETA FALLBACK","REAL (Bloomberg UK)") | AE94: =Y94-N94 | AF94: =AC94-O94
A95: 35102010 | B95: Health Care Distributors | C95: 35 | D95: 3510 | E95: 351020 | F95: 0.758567 | G95: 1 | H95: =SUMPRODUCT(($E$3:$E$165=E95)*$G$3:$G$165*$F$3:$F$165)/SUMPRODUCT(($E$3:$E$165=E95)*$G$3:$G$165) | I95: =SUMPRODUCT(($D$3:$D$165=D95)*$G$3:$G$165*$F$3:$F$165)/SUMPRODUCT(($D$3:$D$165=D95)*$G$3:$G$165) | J95: =SUMPRODUCT(($C$3:$C$165=C95)*$G$3:$G$165*$F$3:$F$165)/SUMPRODUCT(($C$3:$C$165=C95)*$G$3:$G$165) | K95: =I95/J95 | L95: =H95/I95 | M95: =F95/H95 | N95: =INDEX('4_UK_L1_Input'!$C$4:$C$14,MATCH($C95,'4_UK_L1_Input'!$A$4:$A$14,0))*K95*L95*M95 | O95: =INDEX('4_UK_L1_Input'!$D$4:$D$14,MATCH($C95,'4_UK_L1_Input'!$A$4:$A$14,0))*K95*L95*M95 | P95: 12420 | Q95: 2380000 | S95: =IFERROR(SUMPRODUCT(($E$3:$E$165=E95)*ISNUMBER($P$3:$P$165)*$P$3:$P$165*$F$3:$F$165)/SUMPRODUCT(($E$3:$E$165=E95)*ISNUMBER($P$3:$P$165)*$P$3:$P$165),"") | T95: =IFERROR(SUMPRODUCT(($D$3:$D$165=D95)*ISNUMBER($P$3:$P$165)*$P$3:$P$165*$F$3:$F$165)/SUMPRODUCT(($D$3:$D$165=D95)*ISNUMBER($P$3:$P$165)*$P$3:$P$165),"") | U95: =IFERROR(SUMPRODUCT(($C$3:$C$165=C95)*ISNUMBER($P$3:$P$165)*$P$3:$P$165*$F$3:$F$165)/SUMPRODUCT(($C$3:$C$165=C95)*ISNUMBER($P$3:$P$165)*$P$3:$P$165),"") | V95: =IF(OR(T95="",U95=""),"",T95/U95) | W95: =IF(OR(S95="",T95=""),"",S95/T95) | X95: =IF(S95="","",F95/S95) | Y95: =IF(V95="",N95,INDEX('4_UK_L1_Input'!$C$4:$C$14,MATCH($C95,'4_UK_L1_Input'!$A$4:$A$14,0))*V95*W95*X95) | Z95: =IF(V95="","BETA FALLBACK","REAL (Bloomberg UK)") | AA95: =IFERROR(SUMPRODUCT(($C$3:$C$165=C95)*ISNUMBER($R$3:$R$165)*$Q$3:$Q$165*IF(ISNUMBER($R$3:$R$165),$R$3:$R$165,0))/SUMPRODUCT(($C$3:$C$165=C95)*ISNUMBER($R$3:$R$165)*$Q$3:$Q$165),"") | AB95: =IF(OR(R95="",AA95=""),"",R95/AA95) | AC95: =IF(AB95="",O95,INDEX('4_UK_L1_Input'!$D$4:$D$14,MATCH($C95,'4_UK_L1_Input'!$A$4:$A$14,0))*AB95) | AD95: =IF(AB95="","BETA FALLBACK","REAL (Bloomberg UK)") | AE95: =Y95-N95 | AF95: =AC95-O95
A96: 35102015 | B96: Health Care Services | C96: 35 | D96: 3510 | E96: 351020 | F96: 0.758567 | G96: 1 | H96: =SUMPRODUCT(($E$3:$E$165=E96)*$G$3:$G$165*$F$3:$F$165)/SUMPRODUCT(($E$3:$E$165=E96)*$G$3:$G$165) | I96: =SUMPRODUCT(($D$3:$D$165=D96)*$G$3:$G$165*$F$3:$F$165)/SUMPRODUCT(($D$3:$D$165=D96)*$G$3:$G$165) | J96: =SUMPRODUCT(($C$3:$C$165=C96)*$G$3:$G$165*$F$3:$F$165)/SUMPRODUCT(($C$3:$C$165=C96)*$G$3:$G$165) | K96: =I96/J96 | L96: =H96/I96 | M96: =F96/H96 | N96: =INDEX('4_UK_L1_Input'!$C$4:$C$14,MATCH($C96,'4_UK_L1_Input'!$A$4:$A$14,0))*K96*L96*M96 | O96: =INDEX('4_UK_L1_Input'!$D$4:$D$14,MATCH($C96,'4_UK_L1_Input'!$A$4:$A$14,0))*K96*L96*M96 | P96: 26960000 | Q96: 57660000 | R96: 4.62 | S96: =IFERROR(SUMPRODUCT(($E$3:$E$165=E96)*ISNUMBER($P$3:$P$165)*$P$3:$P$165*$F$3:$F$165)/SUMPRODUCT(($E$3:$E$165=E96)*ISNUMBER($P$3:$P$165)*$P$3:$P$165),"") | T96: =IFERROR(SUMPRODUCT(($D$3:$D$165=D96)*ISNUMBER($P$3:$P$165)*$P$3:$P$165*$F$3:$F$165)/SUMPRODUCT(($D$3:$D$165=D96)*ISNUMBER($P$3:$P$165)*$P$3:$P$165),"") | U96: =IFERROR(SUMPRODUCT(($C$3:$C$165=C96)*ISNUMBER($P$3:$P$165)*$P$3:$P$165*$F$3:$F$165)/SUMPRODUCT(($C$3:$C$165=C96)*ISNUMBER($P$3:$P$165)*$P$3:$P$165),"") | V96: =IF(OR(T96="",U96=""),"",T96/U96) | W96: =IF(OR(S96="",T96=""),"",S96/T96) | X96: =IF(S96="","",F96/S96) | Y96: =IF(V96="",N96,INDEX('4_UK_L1_Input'!$C$4:$C$14,MATCH($C96,'4_UK_L1_Input'!$A$4:$A$14,0))*V96*W96*X96) | Z96: =IF(V96="","BETA FALLBACK","REAL (Bloomberg UK)") | AA96: =IFERROR(SUMPRODUCT(($C$3:$C$165=C96)*ISNUMBER($R$3:$R$165)*$Q$3:$Q$165*IF(ISNUMBER($R$3:$R$165),$R$3:$R$165,0))/SUMPRODUCT(($C$3:$C$165=C96)*ISNUMBER($R$3:$R$165)*$Q$3:$Q$165),"") | AB96: =IF(OR(R96="",AA96=""),"",R96/AA96) | AC96: =IF(AB96="",O96,INDEX('4_UK_L1_Input'!$D$4:$D$14,MATCH($C96,'4_UK_L1_Input'!$A$4:$A$14,0))*AB96) | AD96: =IF(AB96="","BETA FALLBACK","REAL (Bloomberg UK)") | AE96: =Y96-N96 | AF96: =AC96-O96
A97: 35102020 | B97: Health Care Facilities | C97: 35 | D97: 3510 | E97: 351020 | F97: 0.646837 | G97: 1 | H97: =SUMPRODUCT(($E$3:$E$165=E97)*$G$3:$G$165*$F$3:$F$165)/SUMPRODUCT(($E$3:$E$165=E97)*$G$3:$G$165) | I97: =SUMPRODUCT(($D$3:$D$165=D97)*$G$3:$G$165*$F$3:$F$165)/SUMPRODUCT(($D$3:$D$165=D97)*$G$3:$G$165) | J97: =SUMPRODUCT(($C$3:$C$165=C97)*$G$3:$G$165*$F$3:$F$165)/SUMPRODUCT(($C$3:$C$165=C97)*$G$3:$G$165) | K97: =I97/J97 | L97: =H97/I97 | M97: =F97/H97 | N97: =INDEX('4_UK_L1_Input'!$C$4:$C$14,MATCH($C97,'4_UK_L1_Input'!$A$4:$A$14,0))*K97*L97*M97 | O97: =INDEX('4_UK_L1_Input'!$D$4:$D$14,MATCH($C97,'4_UK_L1_Input'!$A$4:$A$14,0))*K97*L97*M97 | P97: 756150000 | Q97: 610570000 | R97: 7.33 | S97: =IFERROR(SUMPRODUCT(($E$3:$E$165=E97)*ISNUMBER($P$3:$P$165)*$P$3:$P$165*$F$3:$F$165)/SUMPRODUCT(($E$3:$E$165=E97)*ISNUMBER($P$3:$P$165)*$P$3:$P$165),"") | T97: =IFERROR(SUMPRODUCT(($D$3:$D$165=D97)*ISNUMBER($P$3:$P$165)*$P$3:$P$165*$F$3:$F$165)/SUMPRODUCT(($D$3:$D$165=D97)*ISNUMBER($P$3:$P$165)*$P$3:$P$165),"") | U97: =IFERROR(SUMPRODUCT(($C$3:$C$165=C97)*ISNUMBER($P$3:$P$165)*$P$3:$P$165*$F$3:$F$165)/SUMPRODUCT(($C$3:$C$165=C97)*ISNUMBER($P$3:$P$165)*$P$3:$P$165),"") | V97: =IF(OR(T97="",U97=""),"",T97/U97) | W97: =IF(OR(S97="",T97=""),"",S97/T97) | X97: =IF(S97="","",F97/S97) | Y97: =IF(V97="",N97,INDEX('4_UK_L1_Input'!$C$4:$C$14,MATCH($C97,'4_UK_L1_Input'!$A$4:$A$14,0))*V97*W97*X97) | Z97: =IF(V97="","BETA FALLBACK","REAL (Bloomberg UK)") | AA97: =IFERROR(SUMPRODUCT(($C$3:$C$165=C97)*ISNUMBER($R$3:$R$165)*$Q$3:$Q$165*IF(ISNUMBER($R$3:$R$165),$R$3:$R$165,0))/SUMPRODUCT(($C$3:$C$165=C97)*ISNUMBER($R$3:$R$165)*$Q$3:$Q$165),"") | AB97: =IF(OR(R97="",AA97=""),"",R97/AA97) | AC97: =IF(AB97="",O97,INDEX('4_UK_L1_Input'!$D$4:$D$14,MATCH($C97,'4_UK_L1_Input'!$A$4:$A$14,0))*AB97) | AD97: =IF(AB97="","BETA FALLBACK","REAL (Bloomberg UK)") | AE97: =Y97-N97 | AF97: =AC97-O97
A98: 35102030 | B98: Managed Health Care | C98: 35 | D98: 3510 | E98: 351020 | F98: 0.758567 | G98: 1 | H98: =SUMPRODUCT(($E$3:$E$165=E98)*$G$3:$G$165*$F$3:$F$165)/SUMPRODUCT(($E$3:$E$165=E98)*$G$3:$G$165) | I98: =SUMPRODUCT(($D$3:$D$165=D98)*$G$3:$G$165*$F$3:$F$165)/SUMPRODUCT(($D$3:$D$165=D98)*$G$3:$G$165) | J98: =SUMPRODUCT(($C$3:$C$165=C98)*$G$3:$G$165*$F$3:$F$165)/SUMPRODUCT(($C$3:$C$165=C98)*$G$3:$G$165) | K98: =I98/J98 | L98: =H98/I98 | M98: =F98/H98 | N98: =INDEX('4_UK_L1_Input'!$C$4:$C$14,MATCH($C98,'4_UK_L1_Input'!$A$4:$A$14,0))*K98*L98*M98 | O98: =INDEX('4_UK_L1_Input'!$D$4:$D$14,MATCH($C98,'4_UK_L1_Input'!$A$4:$A$14,0))*K98*L98*M98 | S98: =IFERROR(SUMPRODUCT(($E$3:$E$165=E98)*ISNUMBER($P$3:$P$165)*$P$3:$P$165*$F$3:$F$165)/SUMPRODUCT(($E$3:$E$165=E98)*ISNUMBER($P$3:$P$165)*$P$3:$P$165),"") | T98: =IFERROR(SUMPRODUCT(($D$3:$D$165=D98)*ISNUMBER($P$3:$P$165)*$P$3:$P$165*$F$3:$F$165)/SUMPRODUCT(($D$3:$D$165=D98)*ISNUMBER($P$3:$P$165)*$P$3:$P$165),"") | U98: =IFERROR(SUMPRODUCT(($C$3:$C$165=C98)*ISNUMBER($P$3:$P$165)*$P$3:$P$165*$F$3:$F$165)/SUMPRODUCT(($C$3:$C$165=C98)*ISNUMBER($P$3:$P$165)*$P$3:$P$165),"") | V98: =IF(OR(T98="",U98=""),"",T98/U98) | W98: =IF(OR(S98="",T98=""),"",S98/T98) | X98: =IF(S98="","",F98/S98) | Y98: =IF(V98="",N98,INDEX('4_UK_L1_Input'!$C$4:$C$14,MATCH($C98,'4_UK_L1_Input'!$A$4:$A$14,0))*V98*W98*X98) | Z98: =IF(V98="","BETA FALLBACK","REAL (Bloomberg UK)") | AA98: =IFERROR(SUMPRODUCT(($C$3:$C$165=C98)*ISNUMBER($R$3:$R$165)*$Q$3:$Q$165*IF(ISNUMBER($R$3:$R$165),$R$3:$R$165,0))/SUMPRODUCT(($C$3:$C$165=C98)*ISNUMBER($R$3:$R$165)*$Q$3:$Q$165),"") | AB98: =IF(OR(R98="",AA98=""),"",R98/AA98) | AC98: =IF(AB98="",O98,INDEX('4_UK_L1_Input'!$D$4:$D$14,MATCH($C98,'4_UK_L1_Input'!$A$4:$A$14,0))*AB98) | AD98: =IF(AB98="","BETA FALLBACK","REAL (Bloomberg UK)") | AE98: =Y98-N98 | AF98: =AC98-O98
A99: 35103010 | B99: Health Care Technology | C99: 35 | D99: 3510 | E99: 351030 | F99: 1.007096 | G99: 1 | H99: =SUMPRODUCT(($E$3:$E$165=E99)*$G$3:$G$165*$F$3:$F$165)/SUMPRODUCT(($E$3:$E$165=E99)*$G$3:$G$165) | I99: =SUMPRODUCT(($D$3:$D$165=D99)*$G$3:$G$165*$F$3:$F$165)/SUMPRODUCT(($D$3:$D$165=D99)*$G$3:$G$165) | J99: =SUMPRODUCT(($C$3:$C$165=C99)*$G$3:$G$165*$F$3:$F$165)/SUMPRODUCT(($C$3:$C$165=C99)*$G$3:$G$165) | K99: =I99/J99 | L99: =H99/I99 | M99: =F99/H99 | N99: =INDEX('4_UK_L1_Input'!$C$4:$C$14,MATCH($C99,'4_UK_L1_Input'!$A$4:$A$14,0))*K99*L99*M99 | O99: =INDEX('4_UK_L1_Input'!$D$4:$D$14,MATCH($C99,'4_UK_L1_Input'!$A$4:$A$14,0))*K99*L99*M99 | P99: 173230000 | Q99: 82100000 | R99: 8.13 | S99: =IFERROR(SUMPRODUCT(($E$3:$E$165=E99)*ISNUMBER($P$3:$P$165)*$P$3:$P$165*$F$3:$F$165)/SUMPRODUCT(($E$3:$E$165=E99)*ISNUMBER($P$3:$P$165)*$P$3:$P$165),"") | T99: =IFERROR(SUMPRODUCT(($D$3:$D$165=D99)*ISNUMBER($P$3:$P$165)*$P$3:$P$165*$F$3:$F$165)/SUMPRODUCT(($D$3:$D$165=D99)*ISNUMBER($P$3:$P$165)*$P$3:$P$165),"") | U99: =IFERROR(SUMPRODUCT(($C$3:$C$165=C99)*ISNUMBER($P$3:$P$165)*$P$3:$P$165*$F$3:$F$165)/SUMPRODUCT(($C$3:$C$165=C99)*ISNUMBER($P$3:$P$165)*$P$3:$P$165),"") | V99: =IF(OR(T99="",U99=""),"",T99/U99) | W99: =IF(OR(S99="",T99=""),"",S99/T99) | X99: =IF(S99="","",F99/S99) | Y99: =IF(V99="",N99,INDEX('4_UK_L1_Input'!$C$4:$C$14,MATCH($C99,'4_UK_L1_Input'!$A$4:$A$14,0))*V99*W99*X99) | Z99: =IF(V99="","BETA FALLBACK","REAL (Bloomberg UK)") | AA99: =IFERROR(SUMPRODUCT(($C$3:$C$165=C99)*ISNUMBER($R$3:$R$165)*$Q$3:$Q$165*IF(ISNUMBER($R$3:$R$165),$R$3:$R$165,0))/SUMPRODUCT(($C$3:$C$165=C99)*ISNUMBER($R$3:$R$165)*$Q$3:$Q$165),"") | AB99: =IF(OR(R99="",AA99=""),"",R99/AA99) | AC99: =IF(AB99="",O99,INDEX('4_UK_L1_Input'!$D$4:$D$14,MATCH($C99,'4_UK_L1_Input'!$A$4:$A$14,0))*AB99) | AD99: =IF(AB99="","BETA FALLBACK","REAL (Bloomberg UK)") | AE99: =Y99-N99 | AF99: =AC99-O99
A100: 35201010 | B100: Biotechnology | C100: 35 | D100: 3520 | E100: 352010 | F100: 1.075926 | G100: 1 | H100: =SUMPRODUCT(($E$3:$E$165=E100)*$G$3:$G$165*$F$3:$F$165)/SUMPRODUCT(($E$3:$E$165=E100)*$G$3:$G$165) | I100: =SUMPRODUCT(($D$3:$D$165=D100)*$G$3:$G$165*$F$3:$F$165)/SUMPRODUCT(($D$3:$D$165=D100)*$G$3:$G$165) | J100: =SUMPRODUCT(($C$3:$C$165=C100)*$G$3:$G$165*$F$3:$F$165)/SUMPRODUCT(($C$3:$C$165=C100)*$G$3:$G$165) | K100: =I100/J100 | L100: =H100/I100 | M100: =F100/H100 | N100: =INDEX('4_UK_L1_Input'!$C$4:$C$14,MATCH($C100,'4_UK_L1_Input'!$A$4:$A$14,0))*K100*L100*M100 | O100: =INDEX('4_UK_L1_Input'!$D$4:$D$14,MATCH($C100,'4_UK_L1_Input'!$A$4:$A$14,0))*K100*L100*M100 | P100: 72750000 | Q100: 407840000 | R100: 25.22 | S100: =IFERROR(SUMPRODUCT(($E$3:$E$165=E100)*ISNUMBER($P$3:$P$165)*$P$3:$P$165*$F$3:$F$165)/SUMPRODUCT(($E$3:$E$165=E100)*ISNUMBER($P$3:$P$165)*$P$3:$P$165),"") | T100: =IFERROR(SUMPRODUCT(($D$3:$D$165=D100)*ISNUMBER($P$3:$P$165)*$P$3:$P$165*$F$3:$F$165)/SUMPRODUCT(($D$3:$D$165=D100)*ISNUMBER($P$3:$P$165)*$P$3:$P$165),"") | U100: =IFERROR(SUMPRODUCT(($C$3:$C$165=C100)*ISNUMBER($P$3:$P$165)*$P$3:$P$165*$F$3:$F$165)/SUMPRODUCT(($C$3:$C$165=C100)*ISNUMBER($P$3:$P$165)*$P$3:$P$165),"") | V100: =IF(OR(T100="",U100=""),"",T100/U100) | W100: =IF(OR(S100="",T100=""),"",S100/T100) | X100: =IF(S100="","",F100/S100) | Y100: =IF(V100="",N100,INDEX('4_UK_L1_Input'!$C$4:$C$14,MATCH($C100,'4_UK_L1_Input'!$A$4:$A$14,0))*V100*W100*X100) | Z100: =IF(V100="","BETA FALLBACK","REAL (Bloomberg UK)") | AA100: =IFERROR(SUMPRODUCT(($C$3:$C$165=C100)*ISNUMBER($R$3:$R$165)*$Q$3:$Q$165*IF(ISNUMBER($R$3:$R$165),$R$3:$R$165,0))/SUMPRODUCT(($C$3:$C$165=C100)*ISNUMBER($R$3:$R$165)*$Q$3:$Q$165),"") | AB100: =IF(OR(R100="",AA100=""),"",R100/AA100) | AC100: =IF(AB100="",O100,INDEX('4_UK_L1_Input'!$D$4:$D$14,MATCH($C100,'4_UK_L1_Input'!$A$4:$A$14,0))*AB100) | AD100: =IF(AB100="","BETA FALLBACK","REAL (Bloomberg UK)") | AE100: =Y100-N100 | AF100: =AC100-O100
A101: 35202010 | B101: Pharmaceuticals | C101: 35 | D101: 3520 | E101: 352020 | F101: 0.914541 | G101: 1 | H101: =SUMPRODUCT(($E$3:$E$165=E101)*$G$3:$G$165*$F$3:$F$165)/SUMPRODUCT(($E$3:$E$165=E101)*$G$3:$G$165) | I101: =SUMPRODUCT(($D$3:$D$165=D101)*$G$3:$G$165*$F$3:$F$165)/SUMPRODUCT(($D$3:$D$165=D101)*$G$3:$G$165) | J101: =SUMPRODUCT(($C$3:$C$165=C101)*$G$3:$G$165*$F$3:$F$165)/SUMPRODUCT(($C$3:$C$165=C101)*$G$3:$G$165) | K101: =I101/J101 | L101: =H101/I101 | M101: =F101/H101 | N101: =INDEX('4_UK_L1_Input'!$C$4:$C$14,MATCH($C101,'4_UK_L1_Input'!$A$4:$A$14,0))*K101*L101*M101 | O101: =INDEX('4_UK_L1_Input'!$D$4:$D$14,MATCH($C101,'4_UK_L1_Input'!$A$4:$A$14,0))*K101*L101*M101 | P101: 7290000000 | Q101: 21460000000 | R101: 9.18 | S101: =IFERROR(SUMPRODUCT(($E$3:$E$165=E101)*ISNUMBER($P$3:$P$165)*$P$3:$P$165*$F$3:$F$165)/SUMPRODUCT(($E$3:$E$165=E101)*ISNUMBER($P$3:$P$165)*$P$3:$P$165),"") | T101: =IFERROR(SUMPRODUCT(($D$3:$D$165=D101)*ISNUMBER($P$3:$P$165)*$P$3:$P$165*$F$3:$F$165)/SUMPRODUCT(($D$3:$D$165=D101)*ISNUMBER($P$3:$P$165)*$P$3:$P$165),"") | U101: =IFERROR(SUMPRODUCT(($C$3:$C$165=C101)*ISNUMBER($P$3:$P$165)*$P$3:$P$165*$F$3:$F$165)/SUMPRODUCT(($C$3:$C$165=C101)*ISNUMBER($P$3:$P$165)*$P$3:$P$165),"") | V101: =IF(OR(T101="",U101=""),"",T101/U101) | W101: =IF(OR(S101="",T101=""),"",S101/T101) | X101: =IF(S101="","",F101/S101) | Y101: =IF(V101="",N101,INDEX('4_UK_L1_Input'!$C$4:$C$14,MATCH($C101,'4_UK_L1_Input'!$A$4:$A$14,0))*V101*W101*X101) | Z101: =IF(V101="","BETA FALLBACK","REAL (Bloomberg UK)") | AA101: =IFERROR(SUMPRODUCT(($C$3:$C$165=C101)*ISNUMBER($R$3:$R$165)*$Q$3:$Q$165*IF(ISNUMBER($R$3:$R$165),$R$3:$R$165,0))/SUMPRODUCT(($C$3:$C$165=C101)*ISNUMBER($R$3:$R$165)*$Q$3:$Q$165),"") | AB101: =IF(OR(R101="",AA101=""),"",R101/AA101) | AC101: =IF(AB101="",O101,INDEX('4_UK_L1_Input'!$D$4:$D$14,MATCH($C101,'4_UK_L1_Input'!$A$4:$A$14,0))*AB101) | AD101: =IF(AB101="","BETA FALLBACK","REAL (Bloomberg UK)") | AE101: =Y101-N101 | AF101: =AC101-O101
A102: 35203010 | B102: Life Sciences Tools & Services | C102: 35 | D102: 3520 | E102: 352030 | F102: 0.859005 | G102: 1 | H102: =SUMPRODUCT(($E$3:$E$165=E102)*$G$3:$G$165*$F$3:$F$165)/SUMPRODUCT(($E$3:$E$165=E102)*$G$3:$G$165) | I102: =SUMPRODUCT(($D$3:$D$165=D102)*$G$3:$G$165*$F$3:$F$165)/SUMPRODUCT(($D$3:$D$165=D102)*$G$3:$G$165) | J102: =SUMPRODUCT(($C$3:$C$165=C102)*$G$3:$G$165*$F$3:$F$165)/SUMPRODUCT(($C$3:$C$165=C102)*$G$3:$G$165) | K102: =I102/J102 | L102: =H102/I102 | M102: =F102/H102 | N102: =INDEX('4_UK_L1_Input'!$C$4:$C$14,MATCH($C102,'4_UK_L1_Input'!$A$4:$A$14,0))*K102*L102*M102 | O102: =INDEX('4_UK_L1_Input'!$D$4:$D$14,MATCH($C102,'4_UK_L1_Input'!$A$4:$A$14,0))*K102*L102*M102 | P102: 36120000 | Q102: 162120000 | R102: 16.2 | S102: =IFERROR(SUMPRODUCT(($E$3:$E$165=E102)*ISNUMBER($P$3:$P$165)*$P$3:$P$165*$F$3:$F$165)/SUMPRODUCT(($E$3:$E$165=E102)*ISNUMBER($P$3:$P$165)*$P$3:$P$165),"") | T102: =IFERROR(SUMPRODUCT(($D$3:$D$165=D102)*ISNUMBER($P$3:$P$165)*$P$3:$P$165*$F$3:$F$165)/SUMPRODUCT(($D$3:$D$165=D102)*ISNUMBER($P$3:$P$165)*$P$3:$P$165),"") | U102: =IFERROR(SUMPRODUCT(($C$3:$C$165=C102)*ISNUMBER($P$3:$P$165)*$P$3:$P$165*$F$3:$F$165)/SUMPRODUCT(($C$3:$C$165=C102)*ISNUMBER($P$3:$P$165)*$P$3:$P$165),"") | V102: =IF(OR(T102="",U102=""),"",T102/U102) | W102: =IF(OR(S102="",T102=""),"",S102/T102) | X102: =IF(S102="","",F102/S102) | Y102: =IF(V102="",N102,INDEX('4_UK_L1_Input'!$C$4:$C$14,MATCH($C102,'4_UK_L1_Input'!$A$4:$A$14,0))*V102*W102*X102) | Z102: =IF(V102="","BETA FALLBACK","REAL (Bloomberg UK)") | AA102: =IFERROR(SUMPRODUCT(($C$3:$C$165=C102)*ISNUMBER($R$3:$R$165)*$Q$3:$Q$165*IF(ISNUMBER($R$3:$R$165),$R$3:$R$165,0))/SUMPRODUCT(($C$3:$C$165=C102)*ISNUMBER($R$3:$R$165)*$Q$3:$Q$165),"") | AB102: =IF(OR(R102="",AA102=""),"",R102/AA102) | AC102: =IF(AB102="",O102,INDEX('4_UK_L1_Input'!$D$4:$D$14,MATCH($C102,'4_UK_L1_Input'!$A$4:$A$14,0))*AB102) | AD102: =IF(AB102="","BETA FALLBACK","REAL (Bloomberg UK)") | AE102: =Y102-N102 | AF102: =AC102-O102
A103: 40101010 | B103: Diversified Banks | C103: 40 | D103: 4010 | E103: 401010 | F103: 0.626722 | G103: 1 | H103: =SUMPRODUCT(($E$3:$E$165=E103)*$G$3:$G$165*$F$3:$F$165)/SUMPRODUCT(($E$3:$E$165=E103)*$G$3:$G$165) | I103: =SUMPRODUCT(($D$3:$D$165=D103)*$G$3:$G$165*$F$3:$F$165)/SUMPRODUCT(($D$3:$D$165=D103)*$G$3:$G$165) | J103: =SUMPRODUCT(($C$3:$C$165=C103)*$G$3:$G$165*$F$3:$F$165)/SUMPRODUCT(($C$3:$C$165=C103)*$G$3:$G$165) | K103: =I103/J103 | L103: =H103/I103 | M103: =F103/H103 | N103: =INDEX('4_UK_L1_Input'!$C$4:$C$14,MATCH($C103,'4_UK_L1_Input'!$A$4:$A$14,0))*K103*L103*M103 | O103: =INDEX('4_UK_L1_Input'!$D$4:$D$14,MATCH($C103,'4_UK_L1_Input'!$A$4:$A$14,0))*K103*L103*M103 | P103: 28150000000 | Q103: 56790000000 | S103: =IFERROR(SUMPRODUCT(($E$3:$E$165=E103)*ISNUMBER($P$3:$P$165)*$P$3:$P$165*$F$3:$F$165)/SUMPRODUCT(($E$3:$E$165=E103)*ISNUMBER($P$3:$P$165)*$P$3:$P$165),"") | T103: =IFERROR(SUMPRODUCT(($D$3:$D$165=D103)*ISNUMBER($P$3:$P$165)*$P$3:$P$165*$F$3:$F$165)/SUMPRODUCT(($D$3:$D$165=D103)*ISNUMBER($P$3:$P$165)*$P$3:$P$165),"") | U103: =IFERROR(SUMPRODUCT(($C$3:$C$165=C103)*ISNUMBER($P$3:$P$165)*$P$3:$P$165*$F$3:$F$165)/SUMPRODUCT(($C$3:$C$165=C103)*ISNUMBER($P$3:$P$165)*$P$3:$P$165),"") | V103: =IF(OR(T103="",U103=""),"",T103/U103) | W103: =IF(OR(S103="",T103=""),"",S103/T103) | X103: =IF(S103="","",F103/S103) | Y103: =IF(V103="",N103,INDEX('4_UK_L1_Input'!$C$4:$C$14,MATCH($C103,'4_UK_L1_Input'!$A$4:$A$14,0))*V103*W103*X103) | Z103: =IF(V103="","BETA FALLBACK","REAL (Bloomberg UK)") | AA103: =IFERROR(SUMPRODUCT(($C$3:$C$165=C103)*ISNUMBER($R$3:$R$165)*$Q$3:$Q$165*IF(ISNUMBER($R$3:$R$165),$R$3:$R$165,0))/SUMPRODUCT(($C$3:$C$165=C103)*ISNUMBER($R$3:$R$165)*$Q$3:$Q$165),"") | AB103: =IF(OR(R103="",AA103=""),"",R103/AA103) | AC103: =IF(AB103="",O103,INDEX('4_UK_L1_Input'!$D$4:$D$14,MATCH($C103,'4_UK_L1_Input'!$A$4:$A$14,0))*AB103) | AD103: =IF(AB103="","BETA FALLBACK","REAL (Bloomberg UK)") | AE103: =Y103-N103 | AF103: =AC103-O103
A104: 40101015 | B104: Regional Banks | C104: 40 | D104: 4010 | E104: 401010 | F104: 0.383549 | G104: 1 | H104: =SUMPRODUCT(($E$3:$E$165=E104)*$G$3:$G$165*$F$3:$F$165)/SUMPRODUCT(($E$3:$E$165=E104)*$G$3:$G$165) | I104: =SUMPRODUCT(($D$3:$D$165=D104)*$G$3:$G$165*$F$3:$F$165)/SUMPRODUCT(($D$3:$D$165=D104)*$G$3:$G$165) | J104: =SUMPRODUCT(($C$3:$C$165=C104)*$G$3:$G$165*$F$3:$F$165)/SUMPRODUCT(($C$3:$C$165=C104)*$G$3:$G$165) | K104: =I104/J104 | L104: =H104/I104 | M104: =F104/H104 | N104: =INDEX('4_UK_L1_Input'!$C$4:$C$14,MATCH($C104,'4_UK_L1_Input'!$A$4:$A$14,0))*K104*L104*M104 | O104: =INDEX('4_UK_L1_Input'!$D$4:$D$14,MATCH($C104,'4_UK_L1_Input'!$A$4:$A$14,0))*K104*L104*M104 | P104: 410600000 | Q104: 1450000000 | S104: =IFERROR(SUMPRODUCT(($E$3:$E$165=E104)*ISNUMBER($P$3:$P$165)*$P$3:$P$165*$F$3:$F$165)/SUMPRODUCT(($E$3:$E$165=E104)*ISNUMBER($P$3:$P$165)*$P$3:$P$165),"") | T104: =IFERROR(SUMPRODUCT(($D$3:$D$165=D104)*ISNUMBER($P$3:$P$165)*$P$3:$P$165*$F$3:$F$165)/SUMPRODUCT(($D$3:$D$165=D104)*ISNUMBER($P$3:$P$165)*$P$3:$P$165),"") | U104: =IFERROR(SUMPRODUCT(($C$3:$C$165=C104)*ISNUMBER($P$3:$P$165)*$P$3:$P$165*$F$3:$F$165)/SUMPRODUCT(($C$3:$C$165=C104)*ISNUMBER($P$3:$P$165)*$P$3:$P$165),"") | V104: =IF(OR(T104="",U104=""),"",T104/U104) | W104: =IF(OR(S104="",T104=""),"",S104/T104) | X104: =IF(S104="","",F104/S104) | Y104: =IF(V104="",N104,INDEX('4_UK_L1_Input'!$C$4:$C$14,MATCH($C104,'4_UK_L1_Input'!$A$4:$A$14,0))*V104*W104*X104) | Z104: =IF(V104="","BETA FALLBACK","REAL (Bloomberg UK)") | AA104: =IFERROR(SUMPRODUCT(($C$3:$C$165=C104)*ISNUMBER($R$3:$R$165)*$Q$3:$Q$165*IF(ISNUMBER($R$3:$R$165),$R$3:$R$165,0))/SUMPRODUCT(($C$3:$C$165=C104)*ISNUMBER($R$3:$R$165)*$Q$3:$Q$165),"") | AB104: =IF(OR(R104="",AA104=""),"",R104/AA104) | AC104: =IF(AB104="",O104,INDEX('4_UK_L1_Input'!$D$4:$D$14,MATCH($C104,'4_UK_L1_Input'!$A$4:$A$14,0))*AB104) | AD104: =IF(AB104="","BETA FALLBACK","REAL (Bloomberg UK)") | AE104: =Y104-N104 | AF104: =AC104-O104
A105: 40201020 | B105: Diversified Financial Services | C105: 40 | D105: 4020 | E105: 402010 | F105: 0.358529 | G105: 1 | H105: =SUMPRODUCT(($E$3:$E$165=E105)*$G$3:$G$165*$F$3:$F$165)/SUMPRODUCT(($E$3:$E$165=E105)*$G$3:$G$165) | I105: =SUMPRODUCT(($D$3:$D$165=D105)*$G$3:$G$165*$F$3:$F$165)/SUMPRODUCT(($D$3:$D$165=D105)*$G$3:$G$165) | J105: =SUMPRODUCT(($C$3:$C$165=C105)*$G$3:$G$165*$F$3:$F$165)/SUMPRODUCT(($C$3:$C$165=C105)*$G$3:$G$165) | K105: =I105/J105 | L105: =H105/I105 | M105: =F105/H105 | N105: =INDEX('4_UK_L1_Input'!$C$4:$C$14,MATCH($C105,'4_UK_L1_Input'!$A$4:$A$14,0))*K105*L105*M105 | O105: =INDEX('4_UK_L1_Input'!$D$4:$D$14,MATCH($C105,'4_UK_L1_Input'!$A$4:$A$14,0))*K105*L105*M105 | P105: 18230000000 | Q105: 8750000000 | S105: =IFERROR(SUMPRODUCT(($E$3:$E$165=E105)*ISNUMBER($P$3:$P$165)*$P$3:$P$165*$F$3:$F$165)/SUMPRODUCT(($E$3:$E$165=E105)*ISNUMBER($P$3:$P$165)*$P$3:$P$165),"") | T105: =IFERROR(SUMPRODUCT(($D$3:$D$165=D105)*ISNUMBER($P$3:$P$165)*$P$3:$P$165*$F$3:$F$165)/SUMPRODUCT(($D$3:$D$165=D105)*ISNUMBER($P$3:$P$165)*$P$3:$P$165),"") | U105: =IFERROR(SUMPRODUCT(($C$3:$C$165=C105)*ISNUMBER($P$3:$P$165)*$P$3:$P$165*$F$3:$F$165)/SUMPRODUCT(($C$3:$C$165=C105)*ISNUMBER($P$3:$P$165)*$P$3:$P$165),"") | V105: =IF(OR(T105="",U105=""),"",T105/U105) | W105: =IF(OR(S105="",T105=""),"",S105/T105) | X105: =IF(S105="","",F105/S105) | Y105: =IF(V105="",N105,INDEX('4_UK_L1_Input'!$C$4:$C$14,MATCH($C105,'4_UK_L1_Input'!$A$4:$A$14,0))*V105*W105*X105) | Z105: =IF(V105="","BETA FALLBACK","REAL (Bloomberg UK)") | AA105: =IFERROR(SUMPRODUCT(($C$3:$C$165=C105)*ISNUMBER($R$3:$R$165)*$Q$3:$Q$165*IF(ISNUMBER($R$3:$R$165),$R$3:$R$165,0))/SUMPRODUCT(($C$3:$C$165=C105)*ISNUMBER($R$3:$R$165)*$Q$3:$Q$165),"") | AB105: =IF(OR(R105="",AA105=""),"",R105/AA105) | AC105: =IF(AB105="",O105,INDEX('4_UK_L1_Input'!$D$4:$D$14,MATCH($C105,'4_UK_L1_Input'!$A$4:$A$14,0))*AB105) | AD105: =IF(AB105="","BETA FALLBACK","REAL (Bloomberg UK)") | AE105: =Y105-N105 | AF105: =AC105-O105
A106: 40201030 | B106: Multi-Sector Holdings | C106: 40 | D106: 4020 | E106: 402010 | F106: 0.358529 | G106: 1 | H106: =SUMPRODUCT(($E$3:$E$165=E106)*$G$3:$G$165*$F$3:$F$165)/SUMPRODUCT(($E$3:$E$165=E106)*$G$3:$G$165) | I106: =SUMPRODUCT(($D$3:$D$165=D106)*$G$3:$G$165*$F$3:$F$165)/SUMPRODUCT(($D$3:$D$165=D106)*$G$3:$G$165) | J106: =SUMPRODUCT(($C$3:$C$165=C106)*$G$3:$G$165*$F$3:$F$165)/SUMPRODUCT(($C$3:$C$165=C106)*$G$3:$G$165) | K106: =I106/J106 | L106: =H106/I106 | M106: =F106/H106 | N106: =INDEX('4_UK_L1_Input'!$C$4:$C$14,MATCH($C106,'4_UK_L1_Input'!$A$4:$A$14,0))*K106*L106*M106 | O106: =INDEX('4_UK_L1_Input'!$D$4:$D$14,MATCH($C106,'4_UK_L1_Input'!$A$4:$A$14,0))*K106*L106*M106 | S106: =IFERROR(SUMPRODUCT(($E$3:$E$165=E106)*ISNUMBER($P$3:$P$165)*$P$3:$P$165*$F$3:$F$165)/SUMPRODUCT(($E$3:$E$165=E106)*ISNUMBER($P$3:$P$165)*$P$3:$P$165),"") | T106: =IFERROR(SUMPRODUCT(($D$3:$D$165=D106)*ISNUMBER($P$3:$P$165)*$P$3:$P$165*$F$3:$F$165)/SUMPRODUCT(($D$3:$D$165=D106)*ISNUMBER($P$3:$P$165)*$P$3:$P$165),"") | U106: =IFERROR(SUMPRODUCT(($C$3:$C$165=C106)*ISNUMBER($P$3:$P$165)*$P$3:$P$165*$F$3:$F$165)/SUMPRODUCT(($C$3:$C$165=C106)*ISNUMBER($P$3:$P$165)*$P$3:$P$165),"") | V106: =IF(OR(T106="",U106=""),"",T106/U106) | W106: =IF(OR(S106="",T106=""),"",S106/T106) | X106: =IF(S106="","",F106/S106) | Y106: =IF(V106="",N106,INDEX('4_UK_L1_Input'!$C$4:$C$14,MATCH($C106,'4_UK_L1_Input'!$A$4:$A$14,0))*V106*W106*X106) | Z106: =IF(V106="","BETA FALLBACK","REAL (Bloomberg UK)") | AA106: =IFERROR(SUMPRODUCT(($C$3:$C$165=C106)*ISNUMBER($R$3:$R$165)*$Q$3:$Q$165*IF(ISNUMBER($R$3:$R$165),$R$3:$R$165,0))/SUMPRODUCT(($C$3:$C$165=C106)*ISNUMBER($R$3:$R$165)*$Q$3:$Q$165),"") | AB106: =IF(OR(R106="",AA106=""),"",R106/AA106) | AC106: =IF(AB106="",O106,INDEX('4_UK_L1_Input'!$D$4:$D$14,MATCH($C106,'4_UK_L1_Input'!$A$4:$A$14,0))*AB106) | AD106: =IF(AB106="","BETA FALLBACK","REAL (Bloomberg UK)") | AE106: =Y106-N106 | AF106: =AC106-O106
