Workbook

Sheet 0_ReadMe
A1: PC STRESS FRAMEWORK — BOTTOM-UP DEAL-LEVEL SCENARIO MODEL
A2: 30 fictional sponsor-backed direct-lending deals, GICS-tagged, run through Engine B (bottom-up fundamental) of PC_Stress_Framework.html
A5: SCOPE
A6: This is the bottom-up, deal-level half of the internal PC Stress Framework only (Engine B: revenue -> EBITDA ->
A7: coverage -> LTV, Section 5 of PC_Stress_Framework.html). It does not include Engine A (market/APT marks), Engine C
A8: (Vasicek/Monte Carlo loss distribution) or Lens D (fund-level liquidity) -- those operate at portfolio level and are
A9: out of scope for a deal-by-deal build. All company names, sponsors and financials are fictional but internally
A10: consistent (see 2_Deal_Tape for the construction).
A12: THE FORMULA CHAIN (identical to the Northwind worked example, PC_Stress_Framework.html Section 5)
A13: [B1] EBITDA after operating leverage: E_s = E0 x (1 + Rev_shock% x OperatingLeverage)
A14: [B3] Cash interest, on gross drawn debt: Int_s = NetDebt x (StressedRefRate% + CouponMargin%)
A15: [B4] Leverage test: Lev_s = NetDebt / E_s vs Leverage Covenant
... A51: industries. All deal financials, sponsors and descriptions are fictional and internally consistent, not real names.

Sheet 1_GICS_Shock_Input
A1: PASTE ZONE / VALUES ONLY. GICS Sub-Industry level, all 163 official categories. Revenue Shock and EV/EBITDA Multiple Shock are the systematic scenario; Emerging Risk Revenue Overlay is an ADDITIVE second revenue shock for a thematic/idiosyncratic risk (e.g. AI displacement) layered on top, per PC_Stress_Framework.html Section 14. Spread Widening feeds the mark-to-market column via each deal's own spread duration. The 30 rows the deals actually use are pre-filled with an illustrative moderate-recession scenario — overwrite freely; the other 133 default to 0%.
A3: Sub-Ind Code | B3: Sub-Industry | C3: Industry | D3: Sector | E3: Revenue Shock % | F3: EV/EBITDA Multiple Shock % | G3: Spread Widening (bps) | H3: Emerging Risk Revenue Overlay %
A4: 10101010 | B4: Oil & Gas Drilling | C4: Energy Equipment & Services | D4: Energy | E4: 0 | F4: 0 | G4: 0 | H4: 0
A5: 10101020 | B5: Oil & Gas Equipment & Services | C5: Energy Equipment & Services | D5: Energy | E5: 0 | F5: 0 | G5: 0 | H5: 0
A6: 10102010 | B6: Integrated Oil & Gas | C6: Oil, Gas & Consumable Fuels | D6: Energy | E6: 0 | F6: 0 | G6: 0 | H6: 0
A7: 10102020 | B7: Oil & Gas Exploration & Production | C7: Oil, Gas & Consumable Fuels | D7: Energy | E7: 0 | F7: 0 | G7: 0 | H7: 0
A8: 10102030 | B8: Oil & Gas Refining & Marketing | C8: Oil, Gas & Consumable Fuels | D8: Energy | E8: 0 | F8: 0 | G8: 0 | H8: 0
A9: 10102040 | B9: Oil & Gas Storage & Transportation | C9: Oil, Gas & Consumable Fuels | D9: Energy | E9: 0 | F9: 0 | G9: 0 | H9: 0
A10: 10102050 | B10: Coal & Consumable Fuels | C10: Oil, Gas & Consumable Fuels | D10: Energy | E10: 0 | F10: 0 | G10: 0 | H10: 0
A11: 15101010 | B11: Commodity Chemicals | C11: Chemicals | D11: Materials | E11: 0 | F11: 0 | G11: 0 | H11: 0
A12: 15101020 | B12: Diversified Chemicals | C12: Chemicals | D12: Materials | E12: 0 | F12: 0 | G12: 0 | H12: 0
A13: 15101030 | B13: Fertilizers & Agricultural Chemicals | C13: Chemicals | D13: Materials | E13: 0 | F13: 0 | G13: 0 | H13: 0
A14: 15101040 | B14: Industrial Gases | C14: Chemicals | D14: Materials | E14: 0 | F14: 0 | G14: 0 | H14: 0
A15: 15101050 | B15: Specialty Chemicals | C15: Chemicals | D15: Materials | E15: -0.07 | F15: -0.16 | G15: 160 | H15: 0
... A166: 60201040 | B166: Real Estate Services | C166: Real Estate Management & Development | D166: Real Estate | E166: 0 | F166: 0 | G166: 0 | H166: 0
A168: GLOBAL ASSUMPTIONS (portfolio-wide, not GICS-specific — a rate shock is macro, matching the Northwind worked example)
A169: Current Reference Rate % | B169: 0.0525
A170: Reference Rate Shock (bps) | B170: 200

Sheet 2_Deal_Tape
A1: VALUES ONLY. Columns A-Y are your requested fields. Columns Z-AE (blue) are framework-required assumptions the B1-B5 formula chain needs but weren't on the original list — illustrative sector-based defaults, override per name as real data becomes available. All deals fictional; sponsor, LTM revenue, structuring/current EBITDA, opening/current leverage, opening/current LTV are internally consistent (Net Debt held constant from close to today; Current Leverage = Net Debt / Current EBITDA, derived).
A3: Deal Name | B3: Sponsor | C3: GICS Sub-Ind Code | D3: GICS Sub-Industry | E3: GICS Industry | F3: GICS Sector | G3: Company Description | H3: Investment Thesis | I3: LTM Revenue ($m) | J3: EBITDA Margin % | K3: Structuring EBITDA ($m) | L3: Current EBITDA ($m) | M3: Net Debt ($m) | N3: Opening Leverage (net, x) | O3: Current Leverage (net, x) | P3: Entry EV/EBITDA Multiple (x) | Q3: Current EV/EBITDA Multiple (x) | R3: Opening EV ($m) | S3: Current EV ($m) | T3: Opening LTV % | U3: Current LTV % | V3: Invested Amount at Cost ($m) | W3: Margin over Floating (coupon, bps) | X3: Spread Duration (yrs) | Y3: Current Z-spread (bps) | Z3: Operating Leverage (x) | AA3: Leverage Covenant (x) | AB3: FCCR Covenant (x) | AC3: Capex (% of revenue) | AD3: Cash Tax (% of EBITDA) | AE3: Scheduled Amort. (% debt p.a.)
A4: Meridian Clinical Partners | B4: Northbridge Capital | C4: 35102015 | D4: Health Care Services | E4: Health Care Providers & Services | F4: Health Care | G4: Multi-site outpatient physical therapy and rehabilitation platform across the US Southeast, 44 clinics. | H4: Roll-up of fragmented single-site PT practices; consolidate billing/scheduling, cross-sell into ortho referral networks. | I4: 118 | J4: 0.19 | K4: 21.5 | L4: 22.79 | M4: 112.875 | N4: 5.25 | O4: 4.953 | P4: 9.5 | Q4: 9 | R4: 204.25 | S4: 205.11 | T4: 0.55263158 | U4: 0.55031447 | V4: 107.23125 | W4: 550 | X4: 3.2 | Y4: 520 | Z4: 1.5 | AA4: 6.6 | AB4: 1 | AC4: 0.02 | AD4: 0.1 | AE4: 0.01
A5: Alderwood Behavioral Health | B5: Northbridge Capital | C5: 35102020 | D5: Health Care Facilities | E5: Health Care Providers & Services | F5: Health Care | G5: Inpatient and outpatient behavioral health facilities operator, 12 facilities across three states. | H5: Demand-inelastic acute behavioral health capacity in undersupplied markets; payor mix skewed commercial. | I5: 96 | J5: 0.22 | K5: 19.8 | L5: 19.008 | M5: 113.85 | N5: 5.75 | O5: 5.99 | P5: 10 | Q5: 9.2 | R5: 198 | S5: 174.8736 | T5: 0.575 | U5: 0.65104167 | V5: 113.85 | W5: 575 | X5: 3.4 | Y5: 560 | Z5: 1.5 | AA5: 7.1 | AB5: 1 | AC5: 0.02 | AD5: 0.1 | AE5: 0.01
A6: Cascade MedSupply | B6: Ferrow Street Partners | C6: 35101020 | D6: Health Care Supplies | E6: Health Care Equipment & Supplies | F6: Health Care | G6: Distributor of disposable medical supplies to ambulatory surgical centers and physician offices. | H6: Sticky vendor-of-record relationships; consolidate a fragmented distributor base via bolt-ons. | I6: 142 | J6: 0.14 | K6: 17.9 | L6: 19.69 | M6: 85.025 | N6: 4.75 | O6: 4.318 | P6: 8.5 | Q6: 8.5 | R6: 152.15 | S6: 167.365 | T6: 0.55882353 | U6: 0.50802139 | V6: 76.5225 | W6: 525 | X6: 3 | Y6: 490 | Z6: 1.5 | AA6: 6.1 | AB6: 1 | AC6: 0.02 | AD6: 0.1 | AE6: 0.01
A7: Vantage Field Services | B7: Ridgeline Partners | C7: 20201050 | D7: Environmental & Facilities Services | E7: Commercial Services & Supplies | F7: Industrials | G7: Environmental remediation and industrial facilities services provider to energy and manufacturing clients. | H7: Regulatory tailwind (remediation mandates); recurring maintenance contracts underpin revenue visibility. | I7: 87 | J7: 0.16 | K7: 13.6 | L7: 13.328 | M7: 68 | N7: 5 | O7: 5.102 | P7: 8 | Q7: 7.5 | R7: 108.8 | S7: 99.96 | T7: 0.625 | U7: 0.68027211 | V7: 68 | W7: 600 | X7: 3.3 | Y7: 610 | Z7: 2 | AA7: 6.35 | AB7: 1 | AC7: 0.03 | AD7: 0.09 | AE7: 0.01
A8: Coldharbour Security Group | B8: Ferrow Street Partners | C8: 20201080 | D8: Security & Alarm Services | E8: Commercial Services & Supplies | F8: Industrials | G8: Commercial monitored security and access-control installer/servicer across the UK South East. | H8: Contracted recurring monitoring revenue (~70% of total); consolidation platform in a fragmented market. | I8: 64 | J8: 0.21 | K8: 13.1 | L8: 13.493 | M8: 72.05 | N8: 5.5 | O8: 5.34 | P8: 9 | Q8: 8.7 | R8: 117.9 | S8: 117.3891 | T8: 0.61111111 | U8: 0.61377078 | V8: 72.05 | W8: 575 | X8: 3.1 | Y8: 545 | Z8: 2 | AA8: 6.85 | AB8: 1 | AC8: 0.03 | AD8: 0.09 | AE8: 0.01
A9: Bramwell Specialty Chemicals | B9: Iron Gate Capital | C9: 15101050 | D9: Specialty Chemicals | E9: Chemicals | F9: Materials | G9: Formulator of specialty coatings and adhesives for industrial and construction end-markets. | H9: Niche formulation IP with high customer switching costs; margin resilience through raw-material cycles. | I9: 176 | J9: 0.17 | K9: 28.9 | L9: 26.299 | M9: 144.5 | N9: 5 | O9: 5.495 | P9: 8 | Q9: 7.2 | R9: 231.2 | S9: 189.3528 | T9: 0.625 | U9: 0.76312576 | V9: 122.825 | W9: 550 | X9: 3.5 | Y9: 575 | Z9: 2.2 | AA9: 6.35 | AB9: 1 | AC9: 0.045 | AD9: 0.1 | AE9: 0.01
A10: Portobello Machine Works | B10: Ridgeline Partners | C10: 20106020 | D10: Industrial Machinery & Supplies & Components | E10: Machinery | F10: Industrials | G10: Precision-machined components manufacturer for aerospace and industrial equipment OEMs. | H10: Long-term sole-source qualifications with OEMs create multi-year revenue visibility and pricing power. | I10: 103 | J10: 0.2 | K10: 20.1 | L10: 20.502 | M10: 90.45 | N10: 4.5 | O10: 4.412 | P10: 8.5 | Q10: 8 | R10: 170.85 | S10: 164.016 | T10: 0.52941176 | U10: 0.55147059 | V10: 90.45 | W10: 525 | X10: 3.4 | Y10: 505 | Z10: 2 | AA10: 5.85 | AB10: 1 | AC10: 0.03 | AD10: 0.09 | AE10: 0.01
A11: Thistledown Building Products | B11: Iron Gate Capital | C11: 20102010 | D11: Building Products | E11: Building Products | F11: Industrials | G11: Manufacturer of engineered building envelope products (windows, doors) for the RMI and new-build market. | H11: RMI demand is less cyclical than new-build; product mix shift toward higher-margin engineered lines. | I11: 134 | J11: 0.15 | K11: 19.6 | L11: 17.248 | M11: 102.9 | N11: 5.25 | O11: 5.966 | P11: 7.5 | Q11: 6.8 | R11: 147 | S11: 117.2864 | T11: 0.7 | U11: 0.87733957 | V11: 92.61 | W11: 575 | X11: 3.2 | Y11: 595 | Z11: 2 | AA11: 6.6 | AB11: 1 | AC11: 0.03 | AD11: 0.09 | AE11: 0.01
A12: Northgate Trading Co. | B12: Ferrow Street Partners | C12: 20107010 | D12: Trading Companies & Distributors | E12: Trading Companies & Distributors | F12: Industrials | G12: Value-added distributor of MRO (maintenance, repair, operations) products to industrial end-users. | H12: Sticky, high-frequency reorder relationships; scale advantages in a highly fragmented distribution channel. | I12: 211 | J12: 0.1 | K12: 20.4 | L12: 21.216 | M12: 96.9 | N12: 4.75 | O12: 4.567 | P12: 8 | Q12: 7.8 | R12: 163.2 | S12: 165.4848 | T12: 0.59375 | U12: 0.58555227 | V12: 96.9 | W12: 500 | X12: 2.9 | Y12: 470 | Z12: 2 | AA12: 6.1 | AB12: 1 | AC12: 0.03 | AD12: 0.09 | AE12: 0.01
A13: Wrenfield Foods | B13: Northbridge Capital | C13: 30202030 | D13: Packaged Foods & Meats | E13: Food Products | F13: Consumer Staples | G13: Branded and private-label packaged snack foods manufacturer serving grocery and convenience channels. | H13: Private-label penetration into a growing category; capacity investment supports volume growth ahead of peers. | I13: 189 | J13: 0.13 | K13: 23.6 | L13: 23.836 | M13: 118 | N13: 5 | O13: 4.95 | P13: 9 | Q13: 8.8 | R13: 212.4 | S13: 209.7568 | T13: 0.55555556 | U13: 0.56255626 | V13: 112.1 | W13: 500 | X13: 3.1 | Y13: 460 | Z13: 1.5 | AA13: 6.35 | AB13: 1 | AC13: 0.02 | AD13: 0.11 | AE13: 0.01
A14: Stavros Hospitality Group | B14: Iron Gate Capital | C14: 25301040 | D14: Restaurants | E14: Hotels, Restaurants & Leisure | F14: Consumer Discretionary | G14: Regional casual-dining restaurant operator, 68 company-owned locations across the Midwest. | H14: Menu simplification and labor-scheduling technology drive margin recovery from pandemic-era trough. | I14: 156 | J14: 0.11 | K14: 15.9 | L14: 13.515 | M14: 87.45 | N14: 5.5 | O14: 6.471 | P14: 7 | Q14: 6.2 | R14: 111.3 | S14: 83.793 | T14: 0.78571429 | U14: 1.0436433 | V14: 87.45 | W14: 650 | X14: 2.8 | Y14: 690 | Z14: 2.4 | AA14: 6.85 | AB14: 1 | AC14: 0.025 | AD14: 0.08 | AE14: 0.01
A15: Aldergate Learning Partners | B15: Northbridge Capital | C15: 25302010 | D15: Education Services | E15: Diversified Consumer Services | F15: Consumer Discretionary | G15: Operator of accredited vocational and professional certification schools across allied-health disciplines. | H15: Title IV-eligible programs feed placement-driven enrollment; low capex, high incremental margin on new campuses. | I15: 79 | J15: 0.23 | K15: 16.8 | L15: 18.144 | M15: 75.6 | N15: 4.5 | O15: 4.167 | P15: 8.5 | Q15: 8.3 | R15: 142.8 | S15: 150.5952 | T15: 0.52941176 | U15: 0.50200803 | V15: 75.6 | W15: 550 | X15: 3.3 | Y15: 530 | Z15: 2.4 | AA15: 5.85 | AB15: 1 | AC15: 0.025 | AD15: 0.08 | AE15: 0.01
... A33: Tanglewood Support Services | B33: Northbridge Capital | C33: 20201070 | D33: Diversified Support Services | E33: Commercial Services & Supplies | F33: Industrials | G33: Outsourced facilities and support-services provider to healthcare and education campuses. | H33: Multi-year contracted revenue with inflation-linked escalators; consolidation of a fragmented regional base. | I33: 91 | J33: 0.11 | K33: 10 | L33: 9.5 | M33: 50 | N33: 5 | O33: 5.263 | P33: 7.5 | Q33: 7 | R33: 75 | S33: 66.5 | T33: 0.66666667 | U33: 0.7518797 | V33: 47.5 | W33: 575 | X33: 3 | Y33: 580 | Z33: 2 | AA33: 6.35 | AB33: 1 | AC33: 0.03 | AD33: 0.09 | AE33: 0.01

Sheet 3_Scenario_Engine
A1: STEP 3 — the B1/B3/B4/B5 formula chain (PC_Stress_Framework.html Section 5) run on all 30 deals. Columns D-G: GICS shock, looked up by each deal's own Sub-Industry code against 1_GICS_Shock_Input. Columns H-U: deal statics pulled from 2_Deal_Tape. Columns V onward: the live cascade — stressed EBITDA, interest, leverage, FCCR, EV, LTV, covenant headroom, Flatline (distance-to-covenant), and spread-duration MTM impact.
A2: Deal Name | B2: Sub-Ind Code | C2: Sector | D2: Revenue Shock % | E2: EV/EBITDA Mult Shock % | F2: Spread Widening (bps) | G2: Emerging Risk Overlay % | H2: Structuring EBITDA | I2: Current EBITDA | J2: Net Debt | K2: Current Multiple | L2: Operating Leverage | M2: Leverage Covenant | N2: FCCR Covenant | O2: Capex % Rev | P2: Cash Tax % EBITDA | Q2: Sched Amort % Debt | R2: LTM Revenue | S2: Coupon (bps) | T2: Spread Duration | U2: Invested Amount | V2: Total Revenue Shock % [B1] | W2: Stressed EBITDA [B1] | X2: Stressed Ref Rate % [B3] | Y2: Stressed Cash Interest [B3] | Z2: Stressed Leverage [B4] | AA2: Stressed Capex $ | AB2: Stressed Cash Tax $ | AC2: Sched Amort $ | AD2: Stressed FCCR [B4] | AE2: Stressed Multiple [B5] | AF2: Stressed EV [B5] | AG2: Stressed LTV [B5] | AH2: Leverage Headroom (x) | AI2: Leverage Breach? | AJ2: FCCR Headroom (x) | AK2: FCCR Breach? | AL2: Leverage E* (breakeven EBITDA) | AM2: Leverage Flatline % | AN2: FCCR E* (breakeven EBITDA) | AO2: FCCR Flatline % | AP2: Price Impact % [Engine A] | AQ2: MTM $ Impact
A3: ='2_Deal_Tape'!A4 | B3: ='2_Deal_Tape'!C4 | C3: ='2_Deal_Tape'!F4 | D3: =INDEX('1_GICS_Shock_Input'!$E$4:$E$166,MATCH($B3,'1_GICS_Shock_Input'!$A$4:$A$166,0)) | E3: =INDEX('1_GICS_Shock_Input'!$F$4:$F$166,MATCH($B3,'1_GICS_Shock_Input'!$A$4:$A$166,0)) | F3: =INDEX('1_GICS_Shock_Input'!$G$4:$G$166,MATCH($B3,'1_GICS_Shock_Input'!$A$4:$A$166,0)) | G3: =INDEX('1_GICS_Shock_Input'!$H$4:$H$166,MATCH($B3,'1_GICS_Shock_Input'!$A$4:$A$166,0)) | H3: ='2_Deal_Tape'!K4 | I3: ='2_Deal_Tape'!L4 | J3: ='2_Deal_Tape'!M4 | K3: ='2_Deal_Tape'!Q4 | L3: ='2_Deal_Tape'!Z4 | M3: ='2_Deal_Tape'!AA4 | N3: ='2_Deal_Tape'!AB4 | O3: ='2_Deal_Tape'!AC4 | P3: ='2_Deal_Tape'!AD4 | Q3: ='2_Deal_Tape'!AE4 | R3: ='2_Deal_Tape'!I4 | S3: ='2_Deal_Tape'!W4 | T3: ='2_Deal_Tape'!X4 | U3: ='2_Deal_Tape'!V4 | V3: =D3+G3 | W3: =I3*(1+V3*L3) | X3: ='1_GICS_Shock_Input'!$B$169+'1_GICS_Shock_Input'!$B$170/10000 | Y3: =J3*(X3+S3/10000) | Z3: =J3/W3 | AA3: =O3*R3 | AB3: =P3*W3 | AC3: =Q3*J3 | AD3: =(W3-AA3-AB3)/(Y3+AC3) | AE3: =K3*(1+E3) | AF3: =W3*AE3 | AG3: =J3/AF3 | AH3: =M3-Z3 | AI3: =IF(Z3>M3,"BREACH","") | AJ3: =AD3-N3 | AK3: =IF(AD3<N3,"BREACH","") | AL3: =J3/M3 | AM3: =(W3-AL3)/W3 | AN3: =N3*(Y3+AC3)+AA3+AB3 | AO3: =(W3-AN3)/W3 | AP3: =-T3*(F3/10000) | AQ3: =U3*AP3
A4: ='2_Deal_Tape'!A5 | B4: ='2_Deal_Tape'!C5 | C4: ='2_Deal_Tape'!F5 | D4: =INDEX('1_GICS_Shock_Input'!$E$4:$E$166,MATCH($B4,'1_GICS_Shock_Input'!$A$4:$A$166,0)) | E4: =INDEX('1_GICS_Shock_Input'!$F$4:$F$166,MATCH($B4,'1_GICS_Shock_Input'!$A$4:$A$166,0)) | F4: =INDEX('1_GICS_Shock_Input'!$G$4:$G$166,MATCH($B4,'1_GICS_Shock_Input'!$A$4:$A$166,0)) | G4: =INDEX('1_GICS_Shock_Input'!$H$4:$H$166,MATCH($B4,'1_GICS_Shock_Input'!$A$4:$A$166,0)) | H4: ='2_Deal_Tape'!K5 | I4: ='2_Deal_Tape'!L5 | J4: ='2_Deal_Tape'!M5 | K4: ='2_Deal_Tape'!Q5 | L4: ='2_Deal_Tape'!Z5 | M4: ='2_Deal_Tape'!AA5 | N4: ='2_Deal_Tape'!AB5 | O4: ='2_Deal_Tape'!AC5 | P4: ='2_Deal_Tape'!AD5 | Q4: ='2_Deal_Tape'!AE5 | R4: ='2_Deal_Tape'!I5 | S4: ='2_Deal_Tape'!W5 | T4: ='2_Deal_Tape'!X5 | U4: ='2_Deal_Tape'!V5 | V4: =D4+G4 | W4: =I4*(1+V4*L4) | X4: ='1_GICS_Shock_Input'!$B$169+'1_GICS_Shock_Input'!$B$170/10000 | Y4: =J4*(X4+S4/10000) | Z4: =J4/W4 | AA4: =O4*R4 | AB4: =P4*W4 | AC4: =Q4*J4 | AD4: =(W4-AA4-AB4)/(Y4+AC4) | AE4: =K4*(1+E4) | AF4: =W4*AE4 | AG4: =J4/AF4 | AH4: =M4-Z4 | AI4: =IF(Z4>M4,"BREACH","") | AJ4: =AD4-N4 | AK4: =IF(AD4<N4,"BREACH","") | AL4: =J4/M4 | AM4: =(W4-AL4)/W4 | AN4: =N4*(Y4+AC4)+AA4+AB4 | AO4: =(W4-AN4)/W4 | AP4: =-T4*(F4/10000) | AQ4: =U4*AP4
A5: ='2_Deal_Tape'!A6 | B5: ='2_Deal_Tape'!C6 | C5: ='2_Deal_Tape'!F6 | D5: =INDEX('1_GICS_Shock_Input'!$E$4:$E$166,MATCH($B5,'1_GICS_Shock_Input'!$A$4:$A$166,0)) | E5: =INDEX('1_GICS_Shock_Input'!$F$4:$F$166,MATCH($B5,'1_GICS_Shock_Input'!$A$4:$A$166,0)) | F5: =INDEX('1_GICS_Shock_Input'!$G$4:$G$166,MATCH($B5,'1_GICS_Shock_Input'!$A$4:$A$166,0)) | G5: =INDEX('1_GICS_Shock_Input'!$H$4:$H$166,MATCH($B5,'1_GICS_Shock_Input'!$A$4:$A$166,0)) | H5: ='2_Deal_Tape'!K6 | I5: ='2_Deal_Tape'!L6 | J5: ='2_Deal_Tape'!M6 | K5: ='2_Deal_Tape'!Q6 | L5: ='2_Deal_Tape'!Z6 | M5: ='2_Deal_Tape'!AA6 | N5: ='2_Deal_Tape'!AB6 | O5: ='2_Deal_Tape'!AC6 | P5: ='2_Deal_Tape'!AD6 | Q5: ='2_Deal_Tape'!AE6 | R5: ='2_Deal_Tape'!I6 | S5: ='2_Deal_Tape'!W6 | T5: ='2_Deal_Tape'!X6 | U5: ='2_Deal_Tape'!V6 | V5: =D5+G5 | W5: =I5*(1+V5*L5) | X5: ='1_GICS_Shock_Input'!$B$169+'1_GICS_Shock_Input'!$B$170/10000 | Y5: =J5*(X5+S5/10000) | Z5: =J5/W5 | AA5: =O5*R5 | AB5: =P5*W5 | AC5: =Q5*J5 | AD5: =(W5-AA5-AB5)/(Y5+AC5) | AE5: =K5*(1+E5) | AF5: =W5*AE5 | AG5: =J5/AF5 | AH5: =M5-Z5 | AI5: =IF(Z5>M5,"BREACH","") | AJ5: =AD5-N5 | AK5: =IF(AD5<N5,"BREACH","") | AL5: =J5/M5 | AM5: =(W5-AL5)/W5 | AN5: =N5*(Y5+AC5)+AA5+AB5 | AO5: =(W5-AN5)/W5 | AP5: =-T5*(F5/10000) | AQ5: =U5*AP5
A6: ='2_Deal_Tape'!A7 | B6: ='2_Deal_Tape'!C7 | C6: ='2_Deal_Tape'!F7 | D6: =INDEX('1_GICS_Shock_Input'!$E$4:$E$166,MATCH($B6,'1_GICS_Shock_Input'!$A$4:$A$166,0)) | E6: =INDEX('1_GICS_Shock_Input'!$F$4:$F$166,MATCH($B6,'1_GICS_Shock_Input'!$A$4:$A$166,0)) | F6: =INDEX('1_GICS_Shock_Input'!$G$4:$G$166,MATCH($B6,'1_GICS_Shock_Input'!$A$4:$A$166,0)) | G6: =INDEX('1_GICS_Shock_Input'!$H$4:$H$166,MATCH($B6,'1_GICS_Shock_Input'!$A$4:$A$166,0)) | H6: ='2_Deal_Tape'!K7 | I6: ='2_Deal_Tape'!L7 | J6: ='2_Deal_Tape'!M7 | K6: ='2_Deal_Tape'!Q7 | L6: ='2_Deal_Tape'!Z7 | M6: ='2_Deal_Tape'!AA7 | N6: ='2_Deal_Tape'!AB7 | O6: ='2_Deal_Tape'!AC7 | P6: ='2_Deal_Tape'!AD7 | Q6: ='2_Deal_Tape'!AE7 | R6: ='2_Deal_Tape'!I7 | S6: ='2_Deal_Tape'!W7 | T6: ='2_Deal_Tape'!X7 | U6: ='2_Deal_Tape'!V7 | V6: =D6+G6 | W6: =I6*(1+V6*L6) | X6: ='1_GICS_Shock_Input'!$B$169+'1_GICS_Shock_Input'!$B$170/10000 | Y6: =J6*(X6+S6/10000) | Z6: =J6/W6 | AA6: =O6*R6 | AB6: =P6*W6 | AC6: =Q6*J6 | AD6: =(W6-AA6-AB6)/(Y6+AC6) | AE6: =K6*(1+E6) | AF6: =W6*AE6 | AG6: =J6/AF6 | AH6: =M6-Z6 | AI6: =IF(Z6>M6,"BREACH","") | AJ6: =AD6-N6 | AK6: =IF(AD6<N6,"BREACH","") | AL6: =J6/M6 | AM6: =(W6-AL6)/W6 | AN6: =N6*(Y6+AC6)+AA6+AB6 | AO6: =(W6-AN6)/W6 | AP6: =-T6*(F6/10000) | AQ6: =U6*AP6
A7: ='2_Deal_Tape'!A8 | B7: ='2_Deal_Tape'!C8 | C7: ='2_Deal_Tape'!F8 | D7: =INDEX('1_GICS_Shock_Input'!$E$4:$E$166,MATCH($B7,'1_GICS_Shock_Input'!$A$4:$A$166,0)) | E7: =INDEX('1_GICS_Shock_Input'!$F$4:$F$166,MATCH($B7,'1_GICS_Shock_Input'!$A$4:$A$166,0)) | F7: =INDEX('1_GICS_Shock_Input'!$G$4:$G$166,MATCH($B7,'1_GICS_Shock_Input'!$A$4:$A$166,0)) | G7: =INDEX('1_GICS_Shock_Input'!$H$4:$H$166,MATCH($B7,'1_GICS_Shock_Input'!$A$4:$A$166,0)) | H7: ='2_Deal_Tape'!K8 | I7: ='2_Deal_Tape'!L8 | J7: ='2_Deal_Tape'!M8 | K7: ='2_Deal_Tape'!Q8 | L7: ='2_Deal_Tape'!Z8 | M7: ='2_Deal_Tape'!AA8 | N7: ='2_Deal_Tape'!AB8 | O7: ='2_Deal_Tape'!AC8 | P7: ='2_Deal_Tape'!AD8 | Q7: ='2_Deal_Tape'!AE8 | R7: ='2_Deal_Tape'!I8 | S7: ='2_Deal_Tape'!W8 | T7: ='2_Deal_Tape'!X8 | U7: ='2_Deal_Tape'!V8 | V7: =D7+G7 | W7: =I7*(1+V7*L7) | X7: ='1_GICS_Shock_Input'!$B$169+'1_GICS_Shock_Input'!$B$170/10000 | Y7: =J7*(X7+S7/10000) | Z7: =J7/W7 | AA7: =O7*R7 | AB7: =P7*W7 | AC7: =Q7*J7 | AD7: =(W7-AA7-AB7)/(Y7+AC7) | AE7: =K7*(1+E7) | AF7: =W7*AE7 | AG7: =J7/AF7 | AH7: =M7-Z7 | AI7: =IF(Z7>M7,"BREACH","") | AJ7: =AD7-N7 | AK7: =IF(AD7<N7,"BREACH","") | AL7: =J7/M7 | AM7: =(W7-AL7)/W7 | AN7: =N7*(Y7+AC7)+AA7+AB7 | AO7: =(W7-AN7)/W7 | AP7: =-T7*(F7/10000) | AQ7: =U7*AP7
A8: ='2_Deal_Tape'!A9 | B8: ='2_Deal_Tape'!C9 | C8: ='2_Deal_Tape'!F9 | D8: =INDEX('1_GICS_Shock_Input'!$E$4:$E$166,MATCH($B8,'1_GICS_Shock_Input'!$A$4:$A$166,0)) | E8: =INDEX('1_GICS_Shock_Input'!$F$4:$F$166,MATCH($B8,'1_GICS_Shock_Input'!$A$4:$A$166,0)) | F8: =INDEX('1_GICS_Shock_Input'!$G$4:$G$166,MATCH($B8,'1_GICS_Shock_Input'!$A$4:$A$166,0)) | G8: =INDEX('1_GICS_Shock_Input'!$H$4:$H$166,MATCH($B8,'1_GICS_Shock_Input'!$A$4:$A$166,0)) | H8: ='2_Deal_Tape'!K9 | I8: ='2_Deal_Tape'!L9 | J8: ='2_Deal_Tape'!M9 | K8: ='2_Deal_Tape'!Q9 | L8: ='2_Deal_Tape'!Z9 | M8: ='2_Deal_Tape'!AA9 | N8: ='2_Deal_Tape'!AB9 | O8: ='2_Deal_Tape'!AC9 | P8: ='2_Deal_Tape'!AD9 | Q8: ='2_Deal_Tape'!AE9 | R8: ='2_Deal_Tape'!I9 | S8: ='2_Deal_Tape'!W9 | T8: ='2_Deal_Tape'!X9 | U8: ='2_Deal_Tape'!V9 | V8: =D8+G8 | W8: =I8*(1+V8*L8) | X8: ='1_GICS_Shock_Input'!$B$169+'1_GICS_Shock_Input'!$B$170/10000 | Y8: =J8*(X8+S8/10000) | Z8: =J8/W8 | AA8: =O8*R8 | AB8: =P8*W8 | AC8: =Q8*J8 | AD8: =(W8-AA8-AB8)/(Y8+AC8) | AE8: =K8*(1+E8) | AF8: =W8*AE8 | AG8: =J8/AF8 | AH8: =M8-Z8 | AI8: =IF(Z8>M8,"BREACH","") | AJ8: =AD8-N8 | AK8: =IF(AD8<N8,"BREACH","") | AL8: =J8/M8 | AM8: =(W8-AL8)/W8 | AN8: =N8*(Y8+AC8)+AA8+AB8 | AO8: =(W8-AN8)/W8 | AP8: =-T8*(F8/10000) | AQ8: =U8*AP8
A9: ='2_Deal_Tape'!A10 | B9: ='2_Deal_Tape'!C10 | C9: ='2_Deal_Tape'!F10 | D9: =INDEX('1_GICS_Shock_Input'!$E$4:$E$166,MATCH($B9,'1_GICS_Shock_Input'!$A$4:$A$166,0)) | E9: =INDEX('1_GICS_Shock_Input'!$F$4:$F$166,MATCH($B9,'1_GICS_Shock_Input'!$A$4:$A$166,0)) | F9: =INDEX('1_GICS_Shock_Input'!$G$4:$G$166,MATCH($B9,'1_GICS_Shock_Input'!$A$4:$A$166,0)) | G9: =INDEX('1_GICS_Shock_Input'!$H$4:$H$166,MATCH($B9,'1_GICS_Shock_Input'!$A$4:$A$166,0)) | H9: ='2_Deal_Tape'!K10 | I9: ='2_Deal_Tape'!L10 | J9: ='2_Deal_Tape'!M10 | K9: ='2_Deal_Tape'!Q10 | L9: ='2_Deal_Tape'!Z10 | M9: ='2_Deal_Tape'!AA10 | N9: ='2_Deal_Tape'!AB10 | O9: ='2_Deal_Tape'!AC10 | P9: ='2_Deal_Tape'!AD10 | Q9: ='2_Deal_Tape'!AE10 | R9: ='2_Deal_Tape'!I10 | S9: ='2_Deal_Tape'!W10 | T9: ='2_Deal_Tape'!X10 | U9: ='2_Deal_Tape'!V10 | V9: =D9+G9 | W9: =I9*(1+V9*L9) | X9: ='1_GICS_Shock_Input'!$B$169+'1_GICS_Shock_Input'!$B$170/10000 | Y9: =J9*(X9+S9/10000) | Z9: =J9/W9 | AA9: =O9*R9 | AB9: =P9*W9 | AC9: =Q9*J9 | AD9: =(W9-AA9-AB9)/(Y9+AC9) | AE9: =K9*(1+E9) | AF9: =W9*AE9 | AG9: =J9/AF9 | AH9: =M9-Z9 | AI9: =IF(Z9>M9,"BREACH","") | AJ9: =AD9-N9 | AK9: =IF(AD9<N9,"BREACH","") | AL9: =J9/M9 | AM9: =(W9-AL9)/W9 | AN9: =N9*(Y9+AC9)+AA9+AB9 | AO9: =(W9-AN9)/W9 | AP9: =-T9*(F9/10000) | AQ9: =U9*AP9
A10: ='2_Deal_Tape'!A11 | B10: ='2_Deal_Tape'!C11 | C10: ='2_Deal_Tape'!F11 | D10: =INDEX('1_GICS_Shock_Input'!$E$4:$E$166,MATCH($B10,'1_GICS_Shock_Input'!$A$4:$A$166,0)) | E10: =INDEX('1_GICS_Shock_Input'!$F$4:$F$166,MATCH($B10,'1_GICS_Shock_Input'!$A$4:$A$166,0)) | F10: =INDEX('1_GICS_Shock_Input'!$G$4:$G$166,MATCH($B10,'1_GICS_Shock_Input'!$A$4:$A$166,0)) | G10: =INDEX('1_GICS_Shock_Input'!$H$4:$H$166,MATCH($B10,'1_GICS_Shock_Input'!$A$4:$A$166,0)) | H10: ='2_Deal_Tape'!K11 | I10: ='2_Deal_Tape'!L11 | J10: ='2_Deal_Tape'!M11 | K10: ='2_Deal_Tape'!Q11 | L10: ='2_Deal_Tape'!Z11 | M10: ='2_Deal_Tape'!AA11 | N10: ='2_Deal_Tape'!AB11 | O10: ='2_Deal_Tape'!AC11 | P10: ='2_Deal_Tape'!AD11 | Q10: ='2_Deal_Tape'!AE11 | R10: ='2_Deal_Tape'!I11 | S10: ='2_Deal_Tape'!W11 | T10: ='2_Deal_Tape'!X11 | U10: ='2_Deal_Tape'!V11 | V10: =D10+G10 | W10: =I10*(1+V10*L10) | X10: ='1_GICS_Shock_Input'!$B$169+'1_GICS_Shock_Input'!$B$170/10000 | Y10: =J10*(X10+S10/10000) | Z10: =J10/W10 | AA10: =O10*R10 | AB10: =P10*W10 | AC10: =Q10*J10 | AD10: =(W10-AA10-AB10)/(Y10+AC10) | AE10: =K10*(1+E10) | AF10: =W10*AE10 | AG10: =J10/AF10 | AH10: =M10-Z10 | AI10: =IF(Z10>M10,"BREACH","") | AJ10: =AD10-N10 | AK10: =IF(AD10<N10,"BREACH","") | AL10: =J10/M10 | AM10: =(W10-AL10)/W10 | AN10: =N10*(Y10+AC10)+AA10+AB10 | AO10: =(W10-AN10)/W10 | AP10: =-T10*(F10/10000) | AQ10: =U10*AP10
A11: ='2_Deal_Tape'!A12 | B11: ='2_Deal_Tape'!C12 | C11: ='2_Deal_Tape'!F12 | D11: =INDEX('1_GICS_Shock_Input'!$E$4:$E$166,MATCH($B11,'1_GICS_Shock_Input'!$A$4:$A$166,0)) | E11: =INDEX('1_GICS_Shock_Input'!$F$4:$F$166,MATCH($B11,'1_GICS_Shock_Input'!$A$4:$A$166,0)) | F11: =INDEX('1_GICS_Shock_Input'!$G$4:$G$166,MATCH($B11,'1_GICS_Shock_Input'!$A$4:$A$166,0)) | G11: =INDEX('1_GICS_Shock_Input'!$H$4:$H$166,MATCH($B11,'1_GICS_Shock_Input'!$A$4:$A$166,0)) | H11: ='2_Deal_Tape'!K12 | I11: ='2_Deal_Tape'!L12 | J11: ='2_Deal_Tape'!M12 | K11: ='2_Deal_Tape'!Q12 | L11: ='2_Deal_Tape'!Z12 | M11: ='2_Deal_Tape'!AA12 | N11: ='2_Deal_Tape'!AB12 | O11: ='2_Deal_Tape'!AC12 | P11: ='2_Deal_Tape'!AD12 | Q11: ='2_Deal_Tape'!AE12 | R11: ='2_Deal_Tape'!I12 | S11: ='2_Deal_Tape'!W12 | T11: ='2_Deal_Tape'!X12 | U11: ='2_Deal_Tape'!V12 | V11: =D11+G11 | W11: =I11*(1+V11*L11) | X11: ='1_GICS_Shock_Input'!$B$169+'1_GICS_Shock_Input'!$B$170/10000 | Y11: =J11*(X11+S11/10000) | Z11: =J11/W11 | AA11: =O11*R11 | AB11: =P11*W11 | AC11: =Q11*J11 | AD11: =(W11-AA11-AB11)/(Y11+AC11) | AE11: =K11*(1+E11) | AF11: =W11*AE11 | AG11: =J11/AF11 | AH11: =M11-Z11 | AI11: =IF(Z11>M11,"BREACH","") | AJ11: =AD11-N11 | AK11: =IF(AD11<N11,"BREACH","") | AL11: =J11/M11 | AM11: =(W11-AL11)/W11 | AN11: =N11*(Y11+AC11)+AA11+AB11 | AO11: =(W11-AN11)/W11 | AP11: =-T11*(F11/10000) | AQ11: =U11*AP11
A12: ='2_Deal_Tape'!A13 | B12: ='2_Deal_Tape'!C13 | C12: ='2_Deal_Tape'!F13 | D12: =INDEX('1_GICS_Shock_Input'!$E$4:$E$166,MATCH($B12,'1_GICS_Shock_Input'!$A$4:$A$166,0)) | E12: =INDEX('1_GICS_Shock_Input'!$F$4:$F$166,MATCH($B12,'1_GICS_Shock_Input'!$A$4:$A$166,0)) | F12: =INDEX('1_GICS_Shock_Input'!$G$4:$G$166,MATCH($B12,'1_GICS_Shock_Input'!$A$4:$A$166,0)) | G12: =INDEX('1_GICS_Shock_Input'!$H$4:$H$166,MATCH($B12,'1_GICS_Shock_Input'!$A$4:$A$166,0)) | H12: ='2_Deal_Tape'!K13 | I12: ='2_Deal_Tape'!L13 | J12: ='2_Deal_Tape'!M13 | K12: ='2_Deal_Tape'!Q13 | L12: ='2_Deal_Tape'!Z13 | M12: ='2_Deal_Tape'!AA13 | N12: ='2_Deal_Tape'!AB13 | O12: ='2_Deal_Tape'!AC13 | P12: ='2_Deal_Tape'!AD13 | Q12: ='2_Deal_Tape'!AE13 | R12: ='2_Deal_Tape'!I13 | S12: ='2_Deal_Tape'!W13 | T12: ='2_Deal_Tape'!X13 | U12: ='2_Deal_Tape'!V13 | V12: =D12+G12 | W12: =I12*(1+V12*L12) | X12: ='1_GICS_Shock_Input'!$B$169+'1_GICS_Shock_Input'!$B$170/10000 | Y12: =J12*(X12+S12/10000) | Z12: =J12/W12 | AA12: =O12*R12 | AB12: =P12*W12 | AC12: =Q12*J12 | AD12: =(W12-AA12-AB12)/(Y12+AC12) | AE12: =K12*(1+E12) | AF12: =W12*AE12 | AG12: =J12/AF12 | AH12: =M12-Z12 | AI12: =IF(Z12>M12,"BREACH","") | AJ12: =AD12-N12 | AK12: =IF(AD12<N12,"BREACH","") | AL12: =J12/M12 | AM12: =(W12-AL12)/W12 | AN12: =N12*(Y12+AC12)+AA12+AB12 | AO12: =(W12-AN12)/W12 | AP12: =-T12*(F12/10000) | AQ12: =U12*AP12
A13: ='2_Deal_Tape'!A14 | B13: ='2_Deal_Tape'!C14 | C13: ='2_Deal_Tape'!F14 | D13: =INDEX('1_GICS_Shock_Input'!$E$4:$E$166,MATCH($B13,'1_GICS_Shock_Input'!$A$4:$A$166,0)) | E13: =INDEX('1_GICS_Shock_Input'!$F$4:$F$166,MATCH($B13,'1_GICS_Shock_Input'!$A$4:$A$166,0)) | F13: =INDEX('1_GICS_Shock_Input'!$G$4:$G$166,MATCH($B13,'1_GICS_Shock_Input'!$A$4:$A$166,0)) | G13: =INDEX('1_GICS_Shock_Input'!$H$4:$H$166,MATCH($B13,'1_GICS_Shock_Input'!$A$4:$A$166,0)) | H13: ='2_Deal_Tape'!K14 | I13: ='2_Deal_Tape'!L14 | J13: ='2_Deal_Tape'!M14 | K13: ='2_Deal_Tape'!Q14 | L13: ='2_Deal_Tape'!Z14 | M13: ='2_Deal_Tape'!AA14 | N13: ='2_Deal_Tape'!AB14 | O13: ='2_Deal_Tape'!AC14 | P13: ='2_Deal_Tape'!AD14 | Q13: ='2_Deal_Tape'!AE14 | R13: ='2_Deal_Tape'!I14 | S13: ='2_Deal_Tape'!W14 | T13: ='2_Deal_Tape'!X14 | U13: ='2_Deal_Tape'!V14 | V13: =D13+G13 | W13: =I13*(1+V13*L13) | X13: ='1_GICS_Shock_Input'!$B$169+'1_GICS_Shock_Input'!$B$170/10000 | Y13: =J13*(X13+S13/10000) | Z13: =J13/W13 | AA13: =O13*R13 | AB13: =P13*W13 | AC13: =Q13*J13 | AD13: =(W13-AA13-AB13)/(Y13+AC13) | AE13: =K13*(1+E13) | AF13: =W13*AE13 | AG13: =J13/AF13 | AH13: =M13-Z13 | AI13: =IF(Z13>M13,"BREACH","") | AJ13: =AD13-N13 | AK13: =IF(AD13<N13,"BREACH","") | AL13: =J13/M13 | AM13: =(W13-AL13)/W13 | AN13: =N13*(Y13+AC13)+AA13+AB13 | AO13: =(W13-AN13)/W13 | AP13: =-T13*(F13/10000) | AQ13: =U13*AP13
A14: ='2_Deal_Tape'!A15 | B14: ='2_Deal_Tape'!C15 | C14: ='2_Deal_Tape'!F15 | D14: =INDEX('1_GICS_Shock_Input'!$E$4:$E$166,MATCH($B14,'1_GICS_Shock_Input'!$A$4:$A$166,0)) | E14: =INDEX('1_GICS_Shock_Input'!$F$4:$F$166,MATCH($B14,'1_GICS_Shock_Input'!$A$4:$A$166,0)) | F14: =INDEX('1_GICS_Shock_Input'!$G$4:$G$166,MATCH($B14,'1_GICS_Shock_Input'!$A$4:$A$166,0)) | G14: =INDEX('1_GICS_Shock_Input'!$H$4:$H$166,MATCH($B14,'1_GICS_Shock_Input'!$A$4:$A$166,0)) | H14: ='2_Deal_Tape'!K15 | I14: ='2_Deal_Tape'!L15 | J14: ='2_Deal_Tape'!M15 | K14: ='2_Deal_Tape'!Q15 | L14: ='2_Deal_Tape'!Z15 | M14: ='2_Deal_Tape'!AA15 | N14: ='2_Deal_Tape'!AB15 | O14: ='2_Deal_Tape'!AC15 | P14: ='2_Deal_Tape'!AD15 | Q14: ='2_Deal_Tape'!AE15 | R14: ='2_Deal_Tape'!I15 | S14: ='2_Deal_Tape'!W15 | T14: ='2_Deal_Tape'!X15 | U14: ='2_Deal_Tape'!V15 | V14: =D14+G14 | W14: =I14*(1+V14*L14) | X14: ='1_GICS_Shock_Input'!$B$169+'1_GICS_Shock_Input'!$B$170/10000 | Y14: =J14*(X14+S14/10000) | Z14: =J14/W14 | AA14: =O14*R14 | AB14: =P14*W14 | AC14: =Q14*J14 | AD14: =(W14-AA14-AB14)/(Y14+AC14) | AE14: =K14*(1+E14) | AF14: =W14*AE14 | AG14: =J14/AF14 | AH14: =M14-Z14 | AI14: =IF(Z14>M14,"BREACH","") | AJ14: =AD14-N14 | AK14: =IF(AD14<N14,"BREACH","") | AL14: =J14/M14 | AM14: =(W14-AL14)/W14 | AN14: =N14*(Y14+AC14)+AA14+AB14 | AO14: =(W14-AN14)/W14 | AP14: =-T14*(F14/10000) | AQ14: =U14*AP14
... A32: ='2_Deal_Tape'!A33 | B32: ='2_Deal_Tape'!C33 | C32: ='2_Deal_Tape'!F33 | D32: =INDEX('1_GICS_Shock_Input'!$E$4:$E$166,MATCH($B32,'1_GICS_Shock_Input'!$A$4:$A$166,0)) | E32: =INDEX('1_GICS_Shock_Input'!$F$4:$F$166,MATCH($B32,'1_GICS_Shock_Input'!$A$4:$A$166,0)) | F32: =INDEX('1_GICS_Shock_Input'!$G$4:$G$166,MATCH($B32,'1_GICS_Shock_Input'!$A$4:$A$166,0)) | G32: =INDEX('1_GICS_Shock_Input'!$H$4:$H$166,MATCH($B32,'1_GICS_Shock_Input'!$A$4:$A$166,0)) | H32: ='2_Deal_Tape'!K33 | I32: ='2_Deal_Tape'!L33 | J32: ='2_Deal_Tape'!M33 | K32: ='2_Deal_Tape'!Q33 | L32: ='2_Deal_Tape'!Z33 | M32: ='2_Deal_Tape'!AA33 | N32: ='2_Deal_Tape'!AB33 | O32: ='2_Deal_Tape'!AC33 | P32: ='2_Deal_Tape'!AD33 | Q32: ='2_Deal_Tape'!AE33 | R32: ='2_Deal_Tape'!I33 | S32: ='2_Deal_Tape'!W33 | T32: ='2_Deal_Tape'!X33 | U32: ='2_Deal_Tape'!V33 | V32: =D32+G32 | W32: =I32*(1+V32*L32) | X32: ='1_GICS_Shock_Input'!$B$169+'1_GICS_Shock_Input'!$B$170/10000 | Y32: =J32*(X32+S32/10000) | Z32: =J32/W32 | AA32: =O32*R32 | AB32: =P32*W32 | AC32: =Q32*J32 | AD32: =(W32-AA32-AB32)/(Y32+AC32) | AE32: =K32*(1+E32) | AF32: =W32*AE32 | AG32: =J32/AF32 | AH32: =M32-Z32 | AI32: =IF(Z32>M32,"BREACH","") | AJ32: =AD32-N32 | AK32: =IF(AD32<N32,"BREACH","") | AL32: =J32/M32 | AM32: =(W32-AL32)/W32 | AN32: =N32*(Y32+AC32)+AA32+AB32 | AO32: =(W32-AN32)/W32 | AP32: =-T32*(F32/10000) | AQ32: =U32*AP32

Sheet 4_Portfolio_Summary
A1: STEP 4 — Portfolio roll-up, live formulas over 3_Scenario_Engine.
A3: PORTFOLIO SIZE
A4: Number of deals | B4: =COUNTA('3_Scenario_Engine'!$A$3:$A$32)
A5: Total invested at cost ($m) | B5: =SUM('3_Scenario_Engine'!$U$3:$U$32)
A7: STRESSED PORTFOLIO METRICS (invested-amount-weighted)
A8: Weighted-average stressed leverage (net, x) | B8: =SUMPRODUCT('3_Scenario_Engine'!$U$3:$U$32,'3_Scenario_Engine'!$Z$3:$Z$32)/SUM('3_Scenario_Engine'!$U$3:$U$32)
A9: Weighted-average stressed LTV % | B9: =SUMPRODUCT('3_Scenario_Engine'!$U$3:$U$32,'3_Scenario_Engine'!$AG$3:$AG$32)/SUM('3_Scenario_Engine'!$U$3:$U$32)
A10: Weighted-average Leverage Flatline % | B10: =SUMPRODUCT('3_Scenario_Engine'!$U$3:$U$32,'3_Scenario_Engine'!$AM$3:$AM$32)/SUM('3_Scenario_Engine'!$U$3:$U$32)
A11: Weighted-average FCCR Flatline % | B11: =SUMPRODUCT('3_Scenario_Engine'!$U$3:$U$32,'3_Scenario_Engine'!$AO$3:$AO$32)/SUM('3_Scenario_Engine'!$U$3:$U$32)
A13: COVENANT BREACHES (post-scenario)
A14: Deals breaching Leverage covenant | B14: =COUNTIF('3_Scenario_Engine'!$AI$3:$AI$32,"BREACH")
A15: Deals breaching FCCR covenant | B15: =COUNTIF('3_Scenario_Engine'!$AK$3:$AK$32,"BREACH")
A16: Deals breaching either covenant | B16: =SUMPRODUCT((('3_Scenario_Engine'!$AI$3:$AI$32<>"")+('3_Scenario_Engine'!$AK$3:$AK$32<>"")>0)*1)
A17: Invested amount in a covenant breach ($m) | B17: =SUMPRODUCT((('3_Scenario_Engine'!$AI$3:$AI$32<>"")+('3_Scenario_Engine'!$AK$3:$AK$32<>"")>0)*'3_Scenario_Engine'!$U$3:$U$32)
A18: % of invested amount in a covenant breach | B18: =SUMPRODUCT((('3_Scenario_Engine'!$AI$3:$AI$32<>"")+('3_Scenario_Engine'!$AK$3:$AK$32<>"")>0)*'3_Scenario_Engine'!$U$3:$U$32)/SUM('3_Scenario_Engine'!$U$3:$U$32)
A20: MARK-TO-MARKET (Engine A: spread duration x spread widening)
A21: Total MTM impact ($m) | B21: =SUM('3_Scenario_Engine'!$AQ$3:$AQ$32)
A22: Total MTM impact (% of invested) | B22: =SUM('3_Scenario_Engine'!$AQ$3:$AQ$32)/SUM('3_Scenario_Engine'!$U$3:$U$32)
A24: FRAGILITY — invested amount within a given Flatline band of EITHER covenant
A25: Within 0% of breach (already breached) | B25: =SUMPRODUCT((MIN(1,('3_Scenario_Engine'!$AM$3:$AM$32<0)+('3_Scenario_Engine'!$AO$3:$AO$32<0))>0)*'3_Scenario_Engine'!$U$3:$U$32)/SUM('3_Scenario_Engine'!$U$3:$U$32)
A26: Within 10% Flatline of breach | B26: =SUMPRODUCT((MIN(1,(('3_Scenario_Engine'!$AM$3:$AM$32>=0)*('3_Scenario_Engine'!$AM$3:$AM$32<0.10))+(('3_Scenario_Engine'!$AO$3:$AO$32>=0)*('3_Scenario_Engine'!$AO$3:$AO$32<0.10)))>0)*'3_Scenario_Engine'!$U$3:$U$32)/SUM('3_Scenario_Engine'!$U$3:$U$32)
A27: Within 20% Flatline of breach | B27: =SUMPRODUCT((MIN(1,(('3_Scenario_Engine'!$AM$3:$AM$32>=0)*('3_Scenario_Engine'!$AM$3:$AM$32<0.20))+(('3_Scenario_Engine'!$AO$3:$AO$32>=0)*('3_Scenario_Engine'!$AO$3:$AO$32<0.20)))>0)*'3_Scenario_Engine'!$U$3:$U$32)/SUM('3_Scenario_Engine'!$U$3:$U$32)
A29: The C5 'distance-to-covenant surface' from PC_Stress_Framework.html Section 8/11 — the fragility bands above are that standing metric applied to this tape.

Sheet 5_CreditBridge_ReadMe
A1: CREDIT RISK BRIDGE — SWES SHOCKS TO PD / LGD / EL AND CREDIT-DERIVED SPREAD
A2: Bottom-up (PD/LGD/EL) and top-down (spread widening, MTM) transmission of the same SWES scenario already in 1_GICS_Shock_Input / 3_Scenario_Engine. Beta and spread inputs are real-UK-data-ready (dummy for now), no Damodaran.
A5: WHY MERTON / VASICEK, NOT A BESPOKE MODEL
A6: Vasicek's (1987) single-factor model is the large-portfolio limit of Merton's (1974) firm-level structural model, and
A7: it is the literal mathematical basis of the Basel II/III IRB capital formula (Gordy 2003, Asymptotic Single Risk Factor).
A8: Using the firm-level Merton form here — one systematic factor (the SWES scenario) moving a distance-to-default —
A9: means this bridge is built on the same math a PRA/EBA/Basel model validator already recognises. It also needs
A10: almost no new inputs: Stressed EV is already computed in 3_Scenario_Engine (column AF) by the existing SWES
A11: chain — that number IS the Merton 'asset value under stress'. No separate shock-transmission step is invented.
A13: BOTTOM-UP CHAIN
A14: Distance to Default: DD = [ln(V/F) + (r - sigma^2/2)T] / (sigma x sqrt(T)) PD = Phi(-DD)
A15: V = Enterprise Value — Current EV (baseline) or Stressed EV (post-scenario), both already computed elsewhere
... A91: 12_Reconciliation Portfolio roll-up, 4 methods side by side, sensitivity, rating cross-check.

Sheet 6_Credit_Bridge_Assumptions
A1: Credit Risk Bridge parameters. Green = real/sourced data. Blue = disclosed judgement/calibration, editable.
A3: MERTON MODEL PARAMETERS
A4: Time Horizon T (years) | B4: 1 | C4: Standard PRA/EBA/CCAR 1-year stress horizon.
A5: Risk-Free Rate | B5: 0.0525 | C5: Matches Current Reference Rate on 1_GICS_Shock_Input. Used as asset drift proxy (mu=r) — disclosed simplification, see 5_CreditBridge_ReadMe.
A7: ASSET VOLATILITY (UK data-based, replaces Damodaran)
A8: UK Market Volatility (annualised) | B8: 0.16 | C8: Illustrative — replace with your own measured UK market volatility (e.g. trailing realised vol of FTSE All-Share). Used ONLY for the beta-based CROSS-CHECK sigma (sigma ~= beta_unlevered x this figure) — the PRIMARY sigma uses real delevered 1Y equity vol directly, no market-vol assumption needed.
A10: LGD PARAMETERS (collateral-coverage / stressed LTV based)
A11: LGD Floor (fully collateralised) | B11: 0.3 | C11: ~65-70% avg recovery for senior secured leveraged loans (Moody's Ultimate Recovery Database / S&P LCD).
A12: LGD Ceiling (soft cap) | B12: 0.9 | C12: Even a heavily underwater loan retains some workout/collateral value.
A14: RATING CROSS-CHECK GRID (leverage bucket -> implied rating -> S&P long-run 1yr default rate)
A15: Leverage threshold: BB / B boundary (x) | B15: 4 | C15: Standard leveraged-finance credit-stats-to-rating grid.
A16: Leverage threshold: B / CCC boundary (x) | B16: 6 | C16: Standard leveraged-finance credit-stats-to-rating grid.
A17: BB 1-year default rate | B17: 0.0097 | C17: S&P Global, Annual Global Corporate Default Study, 1981-2009 period average.
A18: B 1-year default rate | B18: 0.0493 | C18: S&P Global, Annual Global Corporate Default Study, 1981-2009 period average.
A19: CCC/C 1-year default rate | B19: 0.2798 | C19: S&P Global, Annual Global Corporate Default Study, 1981-2009 period average.
A21: TOP-DOWN RISK PREMIUM MULTIPLIER (judgement — market spread / EL-implied spread, by rating band)
A22: BB multiplier | B22: 2.5 | C22: Corporate-spread-decomposition literature (e.g. Elton/Gruber/Agrawal/Mann 2001): risk premium/liquidity dominate for higher-quality credits.
A23: B multiplier | B23: 1.8 | C23: Narrowing toward actuarial value as credit quality deteriorates.
A24: CCC/C multiplier | B24: 1.2 | C24: Near-distress: market spread converges toward actuarial expected loss.

Sheet 7_UK_Beta_Input
A1: PASTE ZONE — DUMMY VALUES. Unlevered beta at each of the four GICS levels independently. Used as a CROSS-CHECK sigma estimate on 10_GICS_Asset_Vol (sigma ~= beta x UK market vol), alongside the PRIMARY sigma from real delevered equity volatility (9_UK_Vol_Input). Replace with real data — every downstream formula recalculates automatically. Dummy values follow a varied, clearly-synthetic pattern.
A3: SECTOR (11)
A4: Code | B4: Name | D4: Unlevered Beta (DUMMY)
A5: 10 | B5: Energy | D5: 0.7
A6: 15 | B6: Materials | D6: 1
A7: 20 | B7: Industrials | D7: 1.3
A8: 25 | B8: Consumer Discretionary | D8: 0.85
A9: 30 | B9: Consumer Staples | D9: 1.15
A10: 35 | B10: Health Care | D10: 0.7
A11: 40 | B11: Financials | D11: 1
A12: 45 | B12: Information Technology | D12: 1.3
A13: 50 | B13: Communication Services | D13: 0.85
A14: 55 | B14: Utilities | D14: 1.15
A15: 60 | B15: Real Estate | D15: 1.3
A18: INDUSTRY GROUP (25)
A19: Code | B19: Name | D19: Unlevered Beta (DUMMY)
A20: 1010 | B20: Energy | D20: 1
A21: 1510 | B21: Materials | D21: 1.15
A22: 2010 | B22: Capital Goods | D22: 1.3
A23: 2020 | B23: Commercial & Professional Services | D23: 1.15
A24: 2030 | B24: Transportation | D24: 1
A25: 2510 | B25: Automobiles & Components | D25: 0.7
A26: 2520 | B26: Consumer Durables & Apparel | D26: 1.3
A27: 2530 | B27: Consumer Services | D27: 1.15
A28: 2550 | B28: Consumer Discretionary Distribution & Retail | D28: 0.85
A29: 3010 | B29: Consumer Staples Distribution & Retail | D29: 0.85
A30: 3020 | B30: Food, Beverage & Tobacco | D30: 0.7
A31: 3030 | B31: Household & Personal Products | D31: 1.3
... A44: 6020 | B44: Real Estate Management & Development | D44: 0.85
A47: INDUSTRY (74)
A48: Code | B48: Name | D48: Unlevered Beta (DUMMY)
A49: 101010 | B49: Energy Equipment & Services | D49: 1.3
A50: 101020 | B50: Oil, Gas & Consumable Fuels | D50: 1.15
A51: 151010 | B51: Chemicals | D51: 1
A52: 151020 | B52: Construction Materials | D52: 0.85
A53: 151030 | B53: Containers & Packaging | D53: 0.7
A54: 151040 | B54: Metals & Mining | D54: 1.3
A55: 151050 | B55: Paper & Forest Products | D55: 1
A56: 201010 | B56: Aerospace & Defense | D56: 0.7
A57: 201020 | B57: Building Products | D57: 1.3
A58: 201030 | B58: Construction & Engineering | D58: 1.15
A59: 201040 | B59: Electrical Equipment | D59: 1
A60: 201050 | B60: Industrial Conglomerates | D60: 0.85
... A122: 602010 | B122: Real Estate Management & Development | D122: 1.3
A125: SUB-INDUSTRY (163)
A126: Code | B126: Name | D126: Unlevered Beta (DUMMY)
A127: 10101010 | B127: Oil & Gas Drilling | D127: 1.3
A128: 10101020 | B128: Oil & Gas Equipment & Services | D128: 1.15
A129: 10102010 | B129: Integrated Oil & Gas | D129: 0.85
A130: 10102020 | B130: Oil & Gas Exploration & Production | D130: 0.7
A131: 10102030 | B131: Oil & Gas Refining & Marketing | D131: 1.3
A132: 10102040 | B132: Oil & Gas Storage & Transportation | D132: 1
A133: 10102050 | B133: Coal & Consumable Fuels | D133: 0.85
A134: 15101010 | B134: Commodity Chemicals | D134: 1.3
A135: 15101020 | B135: Diversified Chemicals | D135: 1.15
A136: 15101030 | B136: Fertilizers & Agricultural Chemicals | D136: 1
A137: 15101040 | B137: Industrial Gases | D137: 0.85
A138: 15101050 | B138: Specialty Chemicals | D138: 1.3
... A289: 60201040 | B289: Real Estate Services | D289: 1.15

Sheet 8_UK_Spread_Input
A1: PASTE ZONE — DUMMY VALUES. Bloomberg issuer default-risk spread (bps, e.g. DRSK-implied CDS-equivalent spread) at each of the four GICS levels independently. Used to differentiate the exogenous spread-widening input on 11_TopDown_Spread_Engine via a RelSpread cascade. Replace with real data.
A3: SECTOR (11)
A4: Code | B4: Name | D4: Default Risk Spread bps (DUMMY)
A5: 10 | B5: Energy | D5: 220
A6: 15 | B6: Materials | D6: 420
A7: 20 | B7: Industrials | D7: 120
A8: 25 | B8: Consumer Discretionary | D8: 320
A9: 30 | B9: Consumer Staples | D9: 520
A10: 35 | B10: Health Care | D10: 220
A11: 40 | B11: Financials | D11: 420
A12: 45 | B12: Information Technology | D12: 120
A13: 50 | B13: Communication Services | D13: 320
A14: 55 | B14: Utilities | D14: 520
A15: 60 | B15: Real Estate | D15: 120
A18: INDUSTRY GROUP (25)
A19: Code | B19: Name | D19: Default Risk Spread bps (DUMMY)
A20: 1010 | B20: Energy | D20: 420
A21: 1510 | B21: Materials | D21: 520
A22: 2010 | B22: Capital Goods | D22: 120
A23: 2020 | B23: Commercial & Professional Services | D23: 520
A24: 2030 | B24: Transportation | D24: 420
A25: 2510 | B25: Automobiles & Components | D25: 220
A26: 2520 | B26: Consumer Durables & Apparel | D26: 120
A27: 2530 | B27: Consumer Services | D27: 520
A28: 2550 | B28: Consumer Discretionary Distribution & Retail | D28: 320
A29: 3010 | B29: Consumer Staples Distribution & Retail | D29: 320
A30: 3020 | B30: Food, Beverage & Tobacco | D30: 220
A31: 3030 | B31: Household & Personal Products | D31: 120
... A44: 6020 | B44: Real Estate Management & Development | D44: 320
A47: INDUSTRY (74)
A48: Code | B48: Name | D48: Default Risk Spread bps (DUMMY)
A49: 101010 | B49: Energy Equipment & Services | D49: 120
A50: 101020 | B50: Oil, Gas & Consumable Fuels | D50: 520
A51: 151010 | B51: Chemicals | D51: 420
A52: 151020 | B52: Construction Materials | D52: 320
A53: 151030 | B53: Containers & Packaging | D53: 220
A54: 151040 | B54: Metals & Mining | D54: 120
A55: 151050 | B55: Paper & Forest Products | D55: 420
A56: 201010 | B56: Aerospace & Defense | D56: 220
A57: 201020 | B57: Building Products | D57: 120
A58: 201030 | B58: Construction & Engineering | D58: 520
A59: 201040 | B59: Electrical Equipment | D59: 420
A60: 201050 | B60: Industrial Conglomerates | D60: 320
... A122: 602010 | B122: Real Estate Management & Development | D122: 120
A125: SUB-INDUSTRY (163)
A126: Code | B126: Name | D126: Default Risk Spread bps (DUMMY)
A127: 10101010 | B127: Oil & Gas Drilling | D127: 120
A128: 10101020 | B128: Oil & Gas Equipment & Services | D128: 520
A129: 10102010 | B129: Integrated Oil & Gas | D129: 320
A130: 10102020 | B130: Oil & Gas Exploration & Production | D130: 220
A131: 10102030 | B131: Oil & Gas Refining & Marketing | D131: 120
A132: 10102040 | B132: Oil & Gas Storage & Transportation | D132: 420
A133: 10102050 | B133: Coal & Consumable Fuels | D133: 320
A134: 15101010 | B134: Commodity Chemicals | D134: 120
A135: 15101020 | B135: Diversified Chemicals | D135: 520
A136: 15101030 | B136: Fertilizers & Agricultural Chemicals | D136: 420
A137: 15101040 | B137: Industrial Gases | D137: 320
A138: 15101050 | B138: Specialty Chemicals | D138: 120
... A289: 60201040 | B289: Real Estate Services | D289: 520

Sheet 9_UK_Vol_Input
A1: PASTE ZONE — DUMMY VALUES. Real Bloomberg 1Y equity volatility and D/E ratio (total debt / total equity) at each of the four GICS levels. This is the PRIMARY sigma source on 10_GICS_Asset_Vol: sigma_asset = 1Y Equity Vol / (1 + D/E) — the same delevering formula Damodaran's data used, now real UK data instead of a US dataset. More precise than the beta-based cross-check: a direct measurement, not a beta x market-vol shortcut that assumes all volatility is market-driven. Replace with real data.
A3: SECTOR (11)
A4: Code | B4: Name | D4: 1Y Equity Vol (DUMMY) | E4: D/E Ratio (DUMMY)
A5: 10 | B5: Energy | D5: 0.45 | E5: 0.2
A6: 15 | B6: Materials | D6: 0.65 | E6: 0.8
A7: 20 | B7: Industrials | D7: 0.35 | E7: 1.4
A8: 25 | B8: Consumer Discretionary | D8: 0.55 | E8: 0.5
A9: 30 | B9: Consumer Staples | D9: 0.25 | E9: 1.1
A10: 35 | B10: Health Care | D10: 0.45 | E10: 0.2
A11: 40 | B11: Financials | D11: 0.65 | E11: 0.8
A12: 45 | B12: Information Technology | D12: 0.35 | E12: 1.4
A13: 50 | B13: Communication Services | D13: 0.55 | E13: 0.5
A14: 55 | B14: Utilities | D14: 0.25 | E14: 1.1
A15: 60 | B15: Real Estate | D15: 0.35 | E15: 1.4
A18: INDUSTRY GROUP (25)
A19: Code | B19: Name | D19: 1Y Equity Vol (DUMMY) | E19: D/E Ratio (DUMMY)
A20: 1010 | B20: Energy | D20: 0.65 | E20: 0.8
A21: 1510 | B21: Materials | D21: 0.25 | E21: 1.1
A22: 2010 | B22: Capital Goods | D22: 0.35 | E22: 1.4
A23: 2020 | B23: Commercial & Professional Services | D23: 0.25 | E23: 1.1
A24: 2030 | B24: Transportation | D24: 0.65 | E24: 0.8
A25: 2510 | B25: Automobiles & Components | D25: 0.45 | E25: 0.2
A26: 2520 | B26: Consumer Durables & Apparel | D26: 0.35 | E26: 1.4
A27: 2530 | B27: Consumer Services | D27: 0.25 | E27: 1.1
A28: 2550 | B28: Consumer Discretionary Distribution & Retail | D28: 0.55 | E28: 0.5
A29: 3010 | B29: Consumer Staples Distribution & Retail | D29: 0.55 | E29: 0.5
A30: 3020 | B30: Food, Beverage & Tobacco | D30: 0.45 | E30: 0.2
A31: 3030 | B31: Household & Personal Products | D31: 0.35 | E31: 1.4
... A44: 6020 | B44: Real Estate Management & Development | D44: 0.55 | E44: 0.5
A47: INDUSTRY (74)
A48: Code | B48: Name | D48: 1Y Equity Vol (DUMMY) | E48: D/E Ratio (DUMMY)
A49: 101010 | B49: Energy Equipment & Services | D49: 0.35 | E49: 1.4
A50: 101020 | B50: Oil, Gas & Consumable Fuels | D50: 0.25 | E50: 1.1
A51: 151010 | B51: Chemicals | D51: 0.65 | E51: 0.8
A52: 151020 | B52: Construction Materials | D52: 0.55 | E52: 0.5
A53: 151030 | B53: Containers & Packaging | D53: 0.45 | E53: 0.2
A54: 151040 | B54: Metals & Mining | D54: 0.35 | E54: 1.4
A55: 151050 | B55: Paper & Forest Products | D55: 0.65 | E55: 0.8
A56: 201010 | B56: Aerospace & Defense | D56: 0.45 | E56: 0.2
A57: 201020 | B57: Building Products | D57: 0.35 | E57: 1.4
A58: 201030 | B58: Construction & Engineering | D58: 0.25 | E58: 1.1
A59: 201040 | B59: Electrical Equipment | D59: 0.65 | E59: 0.8
A60: 201050 | B60: Industrial Conglomerates | D60: 0.55 | E60: 0.5
... A122: 602010 | B122: Real Estate Management & Development | D122: 0.35 | E122: 1.4
A125: SUB-INDUSTRY (163)
A126: Code | B126: Name | D126: 1Y Equity Vol (DUMMY) | E126: D/E Ratio (DUMMY)
A127: 10101010 | B127: Oil & Gas Drilling | D127: 0.35 | E127: 1.4
A128: 10101020 | B128: Oil & Gas Equipment & Services | D128: 0.25 | E128: 1.1
A129: 10102010 | B129: Integrated Oil & Gas | D129: 0.55 | E129: 0.5
A130: 10102020 | B130: Oil & Gas Exploration & Production | D130: 0.45 | E130: 0.2
A131: 10102030 | B131: Oil & Gas Refining & Marketing | D131: 0.35 | E131: 1.4
A132: 10102040 | B132: Oil & Gas Storage & Transportation | D132: 0.65 | E132: 0.8
A133: 10102050 | B133: Coal & Consumable Fuels | D133: 0.55 | E133: 0.5
A134: 15101010 | B134: Commodity Chemicals | D134: 0.35 | E134: 1.4
A135: 15101020 | B135: Diversified Chemicals | D135: 0.25 | E135: 1.1
A136: 15101030 | B136: Fertilizers & Agricultural Chemicals | D136: 0.65 | E136: 0.8
A137: 15101040 | B137: Industrial Gases | D137: 0.55 | E137: 0.5
A138: 15101050 | B138: Specialty Chemicals | D138: 0.35 | E138: 1.4
... A289: 60201040 | B289: Real Estate Services | D289: 0.25 | E289: 1.1

Sheet 10_GICS_Asset_Vol
A1: STEP 10 — 163 sub-industries, live formulas only. PRIMARY sigma (column N): 1Y Equity Vol / (1+D/E), looked up at Sub-Industry level with fallback to Industry -> Industry Group -> Sector if blank (IFERROR chain, ready for real data with coverage gaps). CROSS-CHECK sigma (column S): beta x UK market vol, same fallback chain, independent data source — compare the two before trusting either into the Merton engine. Column T is what 11_Credit_Risk_Engine actually uses (PRIMARY, falling back to CROSS-CHECK only if PRIMARY is entirely unavailable for that sub-industry).
A2: Sub-Ind Code | B2: Sub-Industry | C2: Sector Code | D2: Industry Code | E2: IG Code | F2: 1Y EqVol (Sub-Ind) | G2: D/E (Sub-Ind) | H2: 1Y EqVol (Industry) | I2: D/E (Industry) | J2: 1Y EqVol (IG) | K2: D/E (IG) | L2: 1Y EqVol (Sector) | M2: D/E (Sector) | N2: PRIMARY sigma (delevered EqVol) | O2: Beta (Sub-Ind) | P2: Beta (Industry) | Q2: Beta (IG) | R2: Beta (Sector) | S2: CROSS-CHECK sigma (beta x mkt vol) | T2: Sigma USED (primary, else cross-check)
A3: 10101010 | B3: Oil & Gas Drilling | C3: 10 | D3: 101010 | E3: 1010 | F3: =IFERROR(INDEX('9_UK_Vol_Input'!$D$127:$D$289,MATCH($A3,'9_UK_Vol_Input'!$A$127:$A$289,0)),"") | G3: =IFERROR(INDEX('9_UK_Vol_Input'!$E$127:$E$289,MATCH($A3,'9_UK_Vol_Input'!$A$127:$A$289,0)),"") | H3: =IFERROR(INDEX('9_UK_Vol_Input'!$D$49:$D$122,MATCH($D3,'9_UK_Vol_Input'!$A$49:$A$122,0)),"") | I3: =IFERROR(INDEX('9_UK_Vol_Input'!$E$49:$E$122,MATCH($D3,'9_UK_Vol_Input'!$A$49:$A$122,0)),"") | J3: =IFERROR(INDEX('9_UK_Vol_Input'!$D$20:$D$44,MATCH($E3,'9_UK_Vol_Input'!$A$20:$A$44,0)),"") | K3: =IFERROR(INDEX('9_UK_Vol_Input'!$E$20:$E$44,MATCH($E3,'9_UK_Vol_Input'!$A$20:$A$44,0)),"") | L3: =IFERROR(INDEX('9_UK_Vol_Input'!$D$5:$D$15,MATCH($C3,'9_UK_Vol_Input'!$A$5:$A$15,0)),"") | M3: =IFERROR(INDEX('9_UK_Vol_Input'!$E$5:$E$15,MATCH($C3,'9_UK_Vol_Input'!$A$5:$A$15,0)),"") | N3: =IF(F3<>"",F3/(1+G3),IF(H3<>"",H3/(1+I3),IF(J3<>"",J3/(1+K3),IF(L3<>"",L3/(1+M3),"")))) | O3: =IFERROR(INDEX('7_UK_Beta_Input'!$D$127:$D$289,MATCH($A3,'7_UK_Beta_Input'!$A$127:$A$289,0)),"") | P3: =IFERROR(INDEX('7_UK_Beta_Input'!$D$49:$D$122,MATCH($D3,'7_UK_Beta_Input'!$A$49:$A$122,0)),"") | Q3: =IFERROR(INDEX('7_UK_Beta_Input'!$D$20:$D$44,MATCH($E3,'7_UK_Beta_Input'!$A$20:$A$44,0)),"") | R3: =IFERROR(INDEX('7_UK_Beta_Input'!$D$5:$D$15,MATCH($C3,'7_UK_Beta_Input'!$A$5:$A$15,0)),"") | S3: =IF(O3<>"",O3*'6_Credit_Bridge_Assumptions'!$B$8,IF(P3<>"",P3*'6_Credit_Bridge_Assumptions'!$B$8,IF(Q3<>"",Q3*'6_Credit_Bridge_Assumptions'!$B$8,IF(R3<>"",R3*'6_Credit_Bridge_Assumptions'!$B$8,"")))) | T3: =IF(N3<>"",N3,S3)
A4: 10101020 | B4: Oil & Gas Equipment & Services | C4: 10 | D4: 101010 | E4: 1010 | F4: =IFERROR(INDEX('9_UK_Vol_Input'!$D$127:$D$289,MATCH($A4,'9_UK_Vol_Input'!$A$127:$A$289,0)),"") | G4: =IFERROR(INDEX('9_UK_Vol_Input'!$E$127:$E$289,MATCH($A4,'9_UK_Vol_Input'!$A$127:$A$289,0)),"") | H4: =IFERROR(INDEX('9_UK_Vol_Input'!$D$49:$D$122,MATCH($D4,'9_UK_Vol_Input'!$A$49:$A$122,0)),"") | I4: =IFERROR(INDEX('9_UK_Vol_Input'!$E$49:$E$122,MATCH($D4,'9_UK_Vol_Input'!$A$49:$A$122,0)),"") | J4: =IFERROR(INDEX('9_UK_Vol_Input'!$D$20:$D$44,MATCH($E4,'9_UK_Vol_Input'!$A$20:$A$44,0)),"") | K4: =IFERROR(INDEX('9_UK_Vol_Input'!$E$20:$E$44,MATCH($E4,'9_UK_Vol_Input'!$A$20:$A$44,0)),"") | L4: =IFERROR(INDEX('9_UK_Vol_Input'!$D$5:$D$15,MATCH($C4,'9_UK_Vol_Input'!$A$5:$A$15,0)),"") | M4: =IFERROR(INDEX('9_UK_Vol_Input'!$E$5:$E$15,MATCH($C4,'9_UK_Vol_Input'!$A$5:$A$15,0)),"") | N4: =IF(F4<>"",F4/(1+G4),IF(H4<>"",H4/(1+I4),IF(J4<>"",J4/(1+K4),IF(L4<>"",L4/(1+M4),"")))) | O4: =IFERROR(INDEX('7_UK_Beta_Input'!$D$127:$D$289,MATCH($A4,'7_UK_Beta_Input'!$A$127:$A$289,0)),"") | P4: =IFERROR(INDEX('7_UK_Beta_Input'!$D$49:$D$122,MATCH($D4,'7_UK_Beta_Input'!$A$49:$A$122,0)),"") | Q4: =IFERROR(INDEX('7_UK_Beta_Input'!$D$20:$D$44,MATCH($E4,'7_UK_Beta_Input'!$A$20:$A$44,0)),"") | R4: =IFERROR(INDEX('7_UK_Beta_Input'!$D$5:$D$15,MATCH($C4,'7_UK_Beta_Input'!$A$5:$A$15,0)),"") | S4: =IF(O4<>"",O4*'6_Credit_Bridge_Assumptions'!$B$8,IF(P4<>"",P4*'6_Credit_Bridge_Assumptions'!$B$8,IF(Q4<>"",Q4*'6_Credit_Bridge_Assumptions'!$B$8,IF(R4<>"",R4*'6_Credit_Bridge_Assumptions'!$B$8,"")))) | T4: =IF(N4<>"",N4,S4)
A5: 10102010 | B5: Integrated Oil & Gas | C5: 10 | D5: 101020 | E5: 1010 | F5: =IFERROR(INDEX('9_UK_Vol_Input'!$D$127:$D$289,MATCH($A5,'9_UK_Vol_Input'!$A$127:$A$289,0)),"") | G5: =IFERROR(INDEX('9_UK_Vol_Input'!$E$127:$E$289,MATCH($A5,'9_UK_Vol_Input'!$A$127:$A$289,0)),"") | H5: =IFERROR(INDEX('9_UK_Vol_Input'!$D$49:$D$122,MATCH($D5,'9_UK_Vol_Input'!$A$49:$A$122,0)),"") | I5: =IFERROR(INDEX('9_UK_Vol_Input'!$E$49:$E$122,MATCH($D5,'9_UK_Vol_Input'!$A$49:$A$122,0)),"") | J5: =IFERROR(INDEX('9_UK_Vol_Input'!$D$20:$D$44,MATCH($E5,'9_UK_Vol_Input'!$A$20:$A$44,0)),"") | K5: =IFERROR(INDEX('9_UK_Vol_Input'!$E$20:$E$44,MATCH($E5,'9_UK_Vol_Input'!$A$20:$A$44,0)),"") | L5: =IFERROR(INDEX('9_UK_Vol_Input'!$D$5:$D$15,MATCH($C5,'9_UK_Vol_Input'!$A$5:$A$15,0)),"") | M5: =IFERROR(INDEX('9_UK_Vol_Input'!$E$5:$E$15,MATCH($C5,'9_UK_Vol_Input'!$A$5:$A$15,0)),"") | N5: =IF(F5<>"",F5/(1+G5),IF(H5<>"",H5/(1+I5),IF(J5<>"",J5/(1+K5),IF(L5<>"",L5/(1+M5),"")))) | O5: =IFERROR(INDEX('7_UK_Beta_Input'!$D$127:$D$289,MATCH($A5,'7_UK_Beta_Input'!$A$127:$A$289,0)),"") | P5: =IFERROR(INDEX('7_UK_Beta_Input'!$D$49:$D$122,MATCH($D5,'7_UK_Beta_Input'!$A$49:$A$122,0)),"") | Q5: =IFERROR(INDEX('7_UK_Beta_Input'!$D$20:$D$44,MATCH($E5,'7_UK_Beta_Input'!$A$20:$A$44,0)),"") | R5: =IFERROR(INDEX('7_UK_Beta_Input'!$D$5:$D$15,MATCH($C5,'7_UK_Beta_Input'!$A$5:$A$15,0)),"") | S5: =IF(O5<>"",O5*'6_Credit_Bridge_Assumptions'!$B$8,IF(P5<>"",P5*'6_Credit_Bridge_Assumptions'!$B$8,IF(Q5<>"",Q5*'6_Credit_Bridge_Assumptions'!$B$8,IF(R5<>"",R5*'6_Credit_Bridge_Assumptions'!$B$8,"")))) | T5: =IF(N5<>"",N5,S5)
A6: 10102020 | B6: Oil & Gas Exploration & Production | C6: 10 | D6: 101020 | E6: 1010 | F6: =IFERROR(INDEX('9_UK_Vol_Input'!$D$127:$D$289,MATCH($A6,'9_UK_Vol_Input'!$A$127:$A$289,0)),"") | G6: =IFERROR(INDEX('9_UK_Vol_Input'!$E$127:$E$289,MATCH($A6,'9_UK_Vol_Input'!$A$127:$A$289,0)),"") | H6: =IFERROR(INDEX('9_UK_Vol_Input'!$D$49:$D$122,MATCH($D6,'9_UK_Vol_Input'!$A$49:$A$122,0)),"") | I6: =IFERROR(INDEX('9_UK_Vol_Input'!$E$49:$E$122,MATCH($D6,'9_UK_Vol_Input'!$A$49:$A$122,0)),"") | J6: =IFERROR(INDEX('9_UK_Vol_Input'!$D$20:$D$44,MATCH($E6,'9_UK_Vol_Input'!$A$20:$A$44,0)),"") | K6: =IFERROR(INDEX('9_UK_Vol_Input'!$E$20:$E$44,MATCH($E6,'9_UK_Vol_Input'!$A$20:$A$44,0)),"") | L6: =IFERROR(INDEX('9_UK_Vol_Input'!$D$5:$D$15,MATCH($C6,'9_UK_Vol_Input'!$A$5:$A$15,0)),"") | M6: =IFERROR(INDEX('9_UK_Vol_Input'!$E$5:$E$15,MATCH($C6,'9_UK_Vol_Input'!$A$5:$A$15,0)),"") | N6: =IF(F6<>"",F6/(1+G6),IF(H6<>"",H6/(1+I6),IF(J6<>"",J6/(1+K6),IF(L6<>"",L6/(1+M6),"")))) | O6: =IFERROR(INDEX('7_UK_Beta_Input'!$D$127:$D$289,MATCH($A6,'7_UK_Beta_Input'!$A$127:$A$289,0)),"") | P6: =IFERROR(INDEX('7_UK_Beta_Input'!$D$49:$D$122,MATCH($D6,'7_UK_Beta_Input'!$A$49:$A$122,0)),"") | Q6: =IFERROR(INDEX('7_UK_Beta_Input'!$D$20:$D$44,MATCH($E6,'7_UK_Beta_Input'!$A$20:$A$44,0)),"") | R6: =IFERROR(INDEX('7_UK_Beta_Input'!$D$5:$D$15,MATCH($C6,'7_UK_Beta_Input'!$A$5:$A$15,0)),"") | S6: =IF(O6<>"",O6*'6_Credit_Bridge_Assumptions'!$B$8,IF(P6<>"",P6*'6_Credit_Bridge_Assumptions'!$B$8,IF(Q6<>"",Q6*'6_Credit_Bridge_Assumptions'!$B$8,IF(R6<>"",R6*'6_Credit_Bridge_Assumptions'!$B$8,"")))) | T6: =IF(N6<>"",N6,S6)
A7: 10102030 | B7: Oil & Gas Refining & Marketing | C7: 10 | D7: 101020 | E7: 1010 | F7: =IFERROR(INDEX('9_UK_Vol_Input'!$D$127:$D$289,MATCH($A7,'9_UK_Vol_Input'!$A$127:$A$289,0)),"") | G7: =IFERROR(INDEX('9_UK_Vol_Input'!$E$127:$E$289,MATCH($A7,'9_UK_Vol_Input'!$A$127:$A$289,0)),"") | H7: =IFERROR(INDEX('9_UK_Vol_Input'!$D$49:$D$122,MATCH($D7,'9_UK_Vol_Input'!$A$49:$A$122,0)),"") | I7: =IFERROR(INDEX('9_UK_Vol_Input'!$E$49:$E$122,MATCH($D7,'9_UK_Vol_Input'!$A$49:$A$122,0)),"") | J7: =IFERROR(INDEX('9_UK_Vol_Input'!$D$20:$D$44,MATCH($E7,'9_UK_Vol_Input'!$A$20:$A$44,0)),"") | K7: =IFERROR(INDEX('9_UK_Vol_Input'!$E$20:$E$44,MATCH($E7,'9_UK_Vol_Input'!$A$20:$A$44,0)),"") | L7: =IFERROR(INDEX('9_UK_Vol_Input'!$D$5:$D$15,MATCH($C7,'9_UK_Vol_Input'!$A$5:$A$15,0)),"") | M7: =IFERROR(INDEX('9_UK_Vol_Input'!$E$5:$E$15,MATCH($C7,'9_UK_Vol_Input'!$A$5:$A$15,0)),"") | N7: =IF(F7<>"",F7/(1+G7),IF(H7<>"",H7/(1+I7),IF(J7<>"",J7/(1+K7),IF(L7<>"",L7/(1+M7),"")))) | O7: =IFERROR(INDEX('7_UK_Beta_Input'!$D$127:$D$289,MATCH($A7,'7_UK_Beta_Input'!$A$127:$A$289,0)),"") | P7: =IFERROR(INDEX('7_UK_Beta_Input'!$D$49:$D$122,MATCH($D7,'7_UK_Beta_Input'!$A$49:$A$122,0)),"") | Q7: =IFERROR(INDEX('7_UK_Beta_Input'!$D$20:$D$44,MATCH($E7,'7_UK_Beta_Input'!$A$20:$A$44,0)),"") | R7: =IFERROR(INDEX('7_UK_Beta_Input'!$D$5:$D$15,MATCH($C7,'7_UK_Beta_Input'!$A$5:$A$15,0)),"") | S7: =IF(O7<>"",O7*'6_Credit_Bridge_Assumptions'!$B$8,IF(P7<>"",P7*'6_Credit_Bridge_Assumptions'!$B$8,IF(Q7<>"",Q7*'6_Credit_Bridge_Assumptions'!$B$8,IF(R7<>"",R7*'6_Credit_Bridge_Assumptions'!$B$8,"")))) | T7: =IF(N7<>"",N7,S7)
A8: 10102040 | B8: Oil & Gas Storage & Transportation | C8: 10 | D8: 101020 | E8: 1010 | F8: =IFERROR(INDEX('9_UK_Vol_Input'!$D$127:$D$289,MATCH($A8,'9_UK_Vol_Input'!$A$127:$A$289,0)),"") | G8: =IFERROR(INDEX('9_UK_Vol_Input'!$E$127:$E$289,MATCH($A8,'9_UK_Vol_Input'!$A$127:$A$289,0)),"") | H8: =IFERROR(INDEX('9_UK_Vol_Input'!$D$49:$D$122,MATCH($D8,'9_UK_Vol_Input'!$A$49:$A$122,0)),"") | I8: =IFERROR(INDEX('9_UK_Vol_Input'!$E$49:$E$122,MATCH($D8,'9_UK_Vol_Input'!$A$49:$A$122,0)),"") | J8: =IFERROR(INDEX('9_UK_Vol_Input'!$D$20:$D$44,MATCH($E8,'9_UK_Vol_Input'!$A$20:$A$44,0)),"") | K8: =IFERROR(INDEX('9_UK_Vol_Input'!$E$20:$E$44,MATCH($E8,'9_UK_Vol_Input'!$A$20:$A$44,0)),"") | L8: =IFERROR(INDEX('9_UK_Vol_Input'!$D$5:$D$15,MATCH($C8,'9_UK_Vol_Input'!$A$5:$A$15,0)),"") | M8: =IFERROR(INDEX('9_UK_Vol_Input'!$E$5:$E$15,MATCH($C8,'9_UK_Vol_Input'!$A$5:$A$15,0)),"") | N8: =IF(F8<>"",F8/(1+G8),IF(H8<>"",H8/(1+I8),IF(J8<>"",J8/(1+K8),IF(L8<>"",L8/(1+M8),"")))) | O8: =IFERROR(INDEX('7_UK_Beta_Input'!$D$127:$D$289,MATCH($A8,'7_UK_Beta_Input'!$A$127:$A$289,0)),"") | P8: =IFERROR(INDEX('7_UK_Beta_Input'!$D$49:$D$122,MATCH($D8,'7_UK_Beta_Input'!$A$49:$A$122,0)),"") | Q8: =IFERROR(INDEX('7_UK_Beta_Input'!$D$20:$D$44,MATCH($E8,'7_UK_Beta_Input'!$A$20:$A$44,0)),"") | R8: =IFERROR(INDEX('7_UK_Beta_Input'!$D$5:$D$15,MATCH($C8,'7_UK_Beta_Input'!$A$5:$A$15,0)),"") | S8: =IF(O8<>"",O8*'6_Credit_Bridge_Assumptions'!$B$8,IF(P8<>"",P8*'6_Credit_Bridge_Assumptions'!$B$8,IF(Q8<>"",Q8*'6_Credit_Bridge_Assumptions'!$B$8,IF(R8<>"",R8*'6_Credit_Bridge_Assumptions'!$B$8,"")))) | T8: =IF(N8<>"",N8,S8)
A9: 10102050 | B9: Coal & Consumable Fuels | C9: 10 | D9: 101020 | E9: 1010 | F9: =IFERROR(INDEX('9_UK_Vol_Input'!$D$127:$D$289,MATCH($A9,'9_UK_Vol_Input'!$A$127:$A$289,0)),"") | G9: =IFERROR(INDEX('9_UK_Vol_Input'!$E$127:$E$289,MATCH($A9,'9_UK_Vol_Input'!$A$127:$A$289,0)),"") | H9: =IFERROR(INDEX('9_UK_Vol_Input'!$D$49:$D$122,MATCH($D9,'9_UK_Vol_Input'!$A$49:$A$122,0)),"") | I9: =IFERROR(INDEX('9_UK_Vol_Input'!$E$49:$E$122,MATCH($D9,'9_UK_Vol_Input'!$A$49:$A$122,0)),"") | J9: =IFERROR(INDEX('9_UK_Vol_Input'!$D$20:$D$44,MATCH($E9,'9_UK_Vol_Input'!$A$20:$A$44,0)),"") | K9: =IFERROR(INDEX('9_UK_Vol_Input'!$E$20:$E$44,MATCH($E9,'9_UK_Vol_Input'!$A$20:$A$44,0)),"") | L9: =IFERROR(INDEX('9_UK_Vol_Input'!$D$5:$D$15,MATCH($C9,'9_UK_Vol_Input'!$A$5:$A$15,0)),"") | M9: =IFERROR(INDEX('9_UK_Vol_Input'!$E$5:$E$15,MATCH($C9,'9_UK_Vol_Input'!$A$5:$A$15,0)),"") | N9: =IF(F9<>"",F9/(1+G9),IF(H9<>"",H9/(1+I9),IF(J9<>"",J9/(1+K9),IF(L9<>"",L9/(1+M9),"")))) | O9: =IFERROR(INDEX('7_UK_Beta_Input'!$D$127:$D$289,MATCH($A9,'7_UK_Beta_Input'!$A$127:$A$289,0)),"") | P9: =IFERROR(INDEX('7_UK_Beta_Input'!$D$49:$D$122,MATCH($D9,'7_UK_Beta_Input'!$A$49:$A$122,0)),"") | Q9: =IFERROR(INDEX('7_UK_Beta_Input'!$D$20:$D$44,MATCH($E9,'7_UK_Beta_Input'!$A$20:$A$44,0)),"") | R9: =IFERROR(INDEX('7_UK_Beta_Input'!$D$5:$D$15,MATCH($C9,'7_UK_Beta_Input'!$A$5:$A$15,0)),"") | S9: =IF(O9<>"",O9*'6_Credit_Bridge_Assumptions'!$B$8,IF(P9<>"",P9*'6_Credit_Bridge_Assumptions'!$B$8,IF(Q9<>"",Q9*'6_Credit_Bridge_Assumptions'!$B$8,IF(R9<>"",R9*'6_Credit_Bridge_Assumptions'!$B$8,"")))) | T9: =IF(N9<>"",N9,S9)
A10: 15101010 | B10: Commodity Chemicals | C10: 15 | D10: 151010 | E10: 1510 | F10: =IFERROR(INDEX('9_UK_Vol_Input'!$D$127:$D$289,MATCH($A10,'9_UK_Vol_Input'!$A$127:$A$289,0)),"") | G10: =IFERROR(INDEX('9_UK_Vol_Input'!$E$127:$E$289,MATCH($A10,'9_UK_Vol_Input'!$A$127:$A$289,0)),"") | H10: =IFERROR(INDEX('9_UK_Vol_Input'!$D$49:$D$122,MATCH($D10,'9_UK_Vol_Input'!$A$49:$A$122,0)),"") | I10: =IFERROR(INDEX('9_UK_Vol_Input'!$E$49:$E$122,MATCH($D10,'9_UK_Vol_Input'!$A$49:$A$122,0)),"") | J10: =IFERROR(INDEX('9_UK_Vol_Input'!$D$20:$D$44,MATCH($E10,'9_UK_Vol_Input'!$A$20:$A$44,0)),"") | K10: =IFERROR(INDEX('9_UK_Vol_Input'!$E$20:$E$44,MATCH($E10,'9_UK_Vol_Input'!$A$20:$A$44,0)),"") | L10: =IFERROR(INDEX('9_UK_Vol_Input'!$D$5:$D$15,MATCH($C10,'9_UK_Vol_Input'!$A$5:$A$15,0)),"") | M10: =IFERROR(INDEX('9_UK_Vol_Input'!$E$5:$E$15,MATCH($C10,'9_UK_Vol_Input'!$A$5:$A$15,0)),"") | N10: =IF(F10<>"",F10/(1+G10),IF(H10<>"",H10/(1+I10),IF(J10<>"",J10/(1+K10),IF(L10<>"",L10/(1+M10),"")))) | O10: =IFERROR(INDEX('7_UK_Beta_Input'!$D$127:$D$289,MATCH($A10,'7_UK_Beta_Input'!$A$127:$A$289,0)),"") | P10: =IFERROR(INDEX('7_UK_Beta_Input'!$D$49:$D$122,MATCH($D10,'7_UK_Beta_Input'!$A$49:$A$122,0)),"") | Q10: =IFERROR(INDEX('7_UK_Beta_Input'!$D$20:$D$44,MATCH($E10,'7_UK_Beta_Input'!$A$20:$A$44,0)),"") | R10: =IFERROR(INDEX('7_UK_Beta_Input'!$D$5:$D$15,MATCH($C10,'7_UK_Beta_Input'!$A$5:$A$15,0)),"") | S10: =IF(O10<>"",O10*'6_Credit_Bridge_Assumptions'!$B$8,IF(P10<>"",P10*'6_Credit_Bridge_Assumptions'!$B$8,IF(Q10<>"",Q10*'6_Credit_Bridge_Assumptions'!$B$8,IF(R10<>"",R10*'6_Credit_Bridge_Assumptions'!$B$8,"")))) | T10: =IF(N10<>"",N10,S10)
A11: 15101020 | B11: Diversified Chemicals | C11: 15 | D11: 151010 | E11: 1510 | F11: =IFERROR(INDEX('9_UK_Vol_Input'!$D$127:$D$289,MATCH($A11,'9_UK_Vol_Input'!$A$127:$A$289,0)),"") | G11: =IFERROR(INDEX('9_UK_Vol_Input'!$E$127:$E$289,MATCH($A11,'9_UK_Vol_Input'!$A$127:$A$289,0)),"") | H11: =IFERROR(INDEX('9_UK_Vol_Input'!$D$49:$D$122,MATCH($D11,'9_UK_Vol_Input'!$A$49:$A$122,0)),"") | I11: =IFERROR(INDEX('9_UK_Vol_Input'!$E$49:$E$122,MATCH($D11,'9_UK_Vol_Input'!$A$49:$A$122,0)),"") | J11: =IFERROR(INDEX('9_UK_Vol_Input'!$D$20:$D$44,MATCH($E11,'9_UK_Vol_Input'!$A$20:$A$44,0)),"") | K11: =IFERROR(INDEX('9_UK_Vol_Input'!$E$20:$E$44,MATCH($E11,'9_UK_Vol_Input'!$A$20:$A$44,0)),"") | L11: =IFERROR(INDEX('9_UK_Vol_Input'!$D$5:$D$15,MATCH($C11,'9_UK_Vol_Input'!$A$5:$A$15,0)),"") | M11: =IFERROR(INDEX('9_UK_Vol_Input'!$E$5:$E$15,MATCH($C11,'9_UK_Vol_Input'!$A$5:$A$15,0)),"") | N11: =IF(F11<>"",F11/(1+G11),IF(H11<>"",H11/(1+I11),IF(J11<>"",J11/(1+K11),IF(L11<>"",L11/(1+M11),"")))) | O11: =IFERROR(INDEX('7_UK_Beta_Input'!$D$127:$D$289,MATCH($A11,'7_UK_Beta_Input'!$A$127:$A$289,0)),"") | P11: =IFERROR(INDEX('7_UK_Beta_Input'!$D$49:$D$122,MATCH($D11,'7_UK_Beta_Input'!$A$49:$A$122,0)),"") | Q11: =IFERROR(INDEX('7_UK_Beta_Input'!$D$20:$D$44,MATCH($E11,'7_UK_Beta_Input'!$A$20:$A$44,0)),"") | R11: =IFERROR(INDEX('7_UK_Beta_Input'!$D$5:$D$15,MATCH($C11,'7_UK_Beta_Input'!$A$5:$A$15,0)),"") | S11: =IF(O11<>"",O11*'6_Credit_Bridge_Assumptions'!$B$8,IF(P11<>"",P11*'6_Credit_Bridge_Assumptions'!$B$8,IF(Q11<>"",Q11*'6_Credit_Bridge_Assumptions'!$B$8,IF(R11<>"",R11*'6_Credit_Bridge_Assumptions'!$B$8,"")))) | T11: =IF(N11<>"",N11,S11)
A12: 15101030 | B12: Fertilizers & Agricultural Chemicals | C12: 15 | D12: 151010 | E12: 1510 | F12: =IFERROR(INDEX('9_UK_Vol_Input'!$D$127:$D$289,MATCH($A12,'9_UK_Vol_Input'!$A$127:$A$289,0)),"") | G12: =IFERROR(INDEX('9_UK_Vol_Input'!$E$127:$E$289,MATCH($A12,'9_UK_Vol_Input'!$A$127:$A$289,0)),"") | H12: =IFERROR(INDEX('9_UK_Vol_Input'!$D$49:$D$122,MATCH($D12,'9_UK_Vol_Input'!$A$49:$A$122,0)),"") | I12: =IFERROR(INDEX('9_UK_Vol_Input'!$E$49:$E$122,MATCH($D12,'9_UK_Vol_Input'!$A$49:$A$122,0)),"") | J12: =IFERROR(INDEX('9_UK_Vol_Input'!$D$20:$D$44,MATCH($E12,'9_UK_Vol_Input'!$A$20:$A$44,0)),"") | K12: =IFERROR(INDEX('9_UK_Vol_Input'!$E$20:$E$44,MATCH($E12,'9_UK_Vol_Input'!$A$20:$A$44,0)),"") | L12: =IFERROR(INDEX('9_UK_Vol_Input'!$D$5:$D$15,MATCH($C12,'9_UK_Vol_Input'!$A$5:$A$15,0)),"") | M12: =IFERROR(INDEX('9_UK_Vol_Input'!$E$5:$E$15,MATCH($C12,'9_UK_Vol_Input'!$A$5:$A$15,0)),"") | N12: =IF(F12<>"",F12/(1+G12),IF(H12<>"",H12/(1+I12),IF(J12<>"",J12/(1+K12),IF(L12<>"",L12/(1+M12),"")))) | O12: =IFERROR(INDEX('7_UK_Beta_Input'!$D$127:$D$289,MATCH($A12,'7_UK_Beta_Input'!$A$127:$A$289,0)),"") | P12: =IFERROR(INDEX('7_UK_Beta_Input'!$D$49:$D$122,MATCH($D12,'7_UK_Beta_Input'!$A$49:$A$122,0)),"") | Q12: =IFERROR(INDEX('7_UK_Beta_Input'!$D$20:$D$44,MATCH($E12,'7_UK_Beta_Input'!$A$20:$A$44,0)),"") | R12: =IFERROR(INDEX('7_UK_Beta_Input'!$D$5:$D$15,MATCH($C12,'7_UK_Beta_Input'!$A$5:$A$15,0)),"") | S12: =IF(O12<>"",O12*'6_Credit_Bridge_Assumptions'!$B$8,IF(P12<>"",P12*'6_Credit_Bridge_Assumptions'!$B$8,IF(Q12<>"",Q12*'6_Credit_Bridge_Assumptions'!$B$8,IF(R12<>"",R12*'6_Credit_Bridge_Assumptions'!$B$8,"")))) | T12: =IF(N12<>"",N12,S12)
A13: 15101040 | B13: Industrial Gases | C13: 15 | D13: 151010 | E13: 1510 | F13: =IFERROR(INDEX('9_UK_Vol_Input'!$D$127:$D$289,MATCH($A13,'9_UK_Vol_Input'!$A$127:$A$289,0)),"") | G13: =IFERROR(INDEX('9_UK_Vol_Input'!$E$127:$E$289,MATCH($A13,'9_UK_Vol_Input'!$A$127:$A$289,0)),"") | H13: =IFERROR(INDEX('9_UK_Vol_Input'!$D$49:$D$122,MATCH($D13,'9_UK_Vol_Input'!$A$49:$A$122,0)),"") | I13: =IFERROR(INDEX('9_UK_Vol_Input'!$E$49:$E$122,MATCH($D13,'9_UK_Vol_Input'!$A$49:$A$122,0)),"") | J13: =IFERROR(INDEX('9_UK_Vol_Input'!$D$20:$D$44,MATCH($E13,'9_UK_Vol_Input'!$A$20:$A$44,0)),"") | K13: =IFERROR(INDEX('9_UK_Vol_Input'!$E$20:$E$44,MATCH($E13,'9_UK_Vol_Input'!$A$20:$A$44,0)),"") | L13: =IFERROR(INDEX('9_UK_Vol_Input'!$D$5:$D$15,MATCH($C13,'9_UK_Vol_Input'!$A$5:$A$15,0)),"") | M13: =IFERROR(INDEX('9_UK_Vol_Input'!$E$5:$E$15,MATCH($C13,'9_UK_Vol_Input'!$A$5:$A$15,0)),"") | N13: =IF(F13<>"",F13/(1+G13),IF(H13<>"",H13/(1+I13),IF(J13<>"",J13/(1+K13),IF(L13<>"",L13/(1+M13),"")))) | O13: =IFERROR(INDEX('7_UK_Beta_Input'!$D$127:$D$289,MATCH($A13,'7_UK_Beta_Input'!$A$127:$A$289,0)),"") | P13: =IFERROR(INDEX('7_UK_Beta_Input'!$D$49:$D$122,MATCH($D13,'7_UK_Beta_Input'!$A$49:$A$122,0)),"") | Q13: =IFERROR(INDEX('7_UK_Beta_Input'!$D$20:$D$44,MATCH($E13,'7_UK_Beta_Input'!$A$20:$A$44,0)),"") | R13: =IFERROR(INDEX('7_UK_Beta_Input'!$D$5:$D$15,MATCH($C13,'7_UK_Beta_Input'!$A$5:$A$15,0)),"") | S13: =IF(O13<>"",O13*'6_Credit_Bridge_Assumptions'!$B$8,IF(P13<>"",P13*'6_Credit_Bridge_Assumptions'!$B$8,IF(Q13<>"",Q13*'6_Credit_Bridge_Assumptions'!$B$8,IF(R13<>"",R13*'6_Credit_Bridge_Assumptions'!$B$8,"")))) | T13: =IF(N13<>"",N13,S13)
A14: 15101050 | B14: Specialty Chemicals | C14: 15 | D14: 151010 | E14: 1510 | F14: =IFERROR(INDEX('9_UK_Vol_Input'!$D$127:$D$289,MATCH($A14,'9_UK_Vol_Input'!$A$127:$A$289,0)),"") | G14: =IFERROR(INDEX('9_UK_Vol_Input'!$E$127:$E$289,MATCH($A14,'9_UK_Vol_Input'!$A$127:$A$289,0)),"") | H14: =IFERROR(INDEX('9_UK_Vol_Input'!$D$49:$D$122,MATCH($D14,'9_UK_Vol_Input'!$A$49:$A$122,0)),"") | I14: =IFERROR(INDEX('9_UK_Vol_Input'!$E$49:$E$122,MATCH($D14,'9_UK_Vol_Input'!$A$49:$A$122,0)),"") | J14: =IFERROR(INDEX('9_UK_Vol_Input'!$D$20:$D$44,MATCH($E14,'9_UK_Vol_Input'!$A$20:$A$44,0)),"") | K14: =IFERROR(INDEX('9_UK_Vol_Input'!$E$20:$E$44,MATCH($E14,'9_UK_Vol_Input'!$A$20:$A$44,0)),"") | L14: =IFERROR(INDEX('9_UK_Vol_Input'!$D$5:$D$15,MATCH($C14,'9_UK_Vol_Input'!$A$5:$A$15,0)),"") | M14: =IFERROR(INDEX('9_UK_Vol_Input'!$E$5:$E$15,MATCH($C14,'9_UK_Vol_Input'!$A$5:$A$15,0)),"") | N14: =IF(F14<>"",F14/(1+G14),IF(H14<>"",H14/(1+I14),IF(J14<>"",J14/(1+K14),IF(L14<>"",L14/(1+M14),"")))) | O14: =IFERROR(INDEX('7_UK_Beta_Input'!$D$127:$D$289,MATCH($A14,'7_UK_Beta_Input'!$A$127:$A$289,0)),"") | P14: =IFERROR(INDEX('7_UK_Beta_Input'!$D$49:$D$122,MATCH($D14,'7_UK_Beta_Input'!$A$49:$A$122,0)),"") | Q14: =IFERROR(INDEX('7_UK_Beta_Input'!$D$20:$D$44,MATCH($E14,'7_UK_Beta_Input'!$A$20:$A$44,0)),"") | R14: =IFERROR(INDEX('7_UK_Beta_Input'!$D$5:$D$15,MATCH($C14,'7_UK_Beta_Input'!$A$5:$A$15,0)),"") | S14: =IF(O14<>"",O14*'6_Credit_Bridge_Assumptions'!$B$8,IF(P14<>"",P14*'6_Credit_Bridge_Assumptions'!$B$8,IF(Q14<>"",Q14*'6_Credit_Bridge_Assumptions'!$B$8,IF(R14<>"",R14*'6_Credit_Bridge_Assumptions'!$B$8,"")))) | T14: =IF(N14<>"",N14,S14)
... A165: 60201040 | B165: Real Estate Services | C165: 60 | D165: 602010 | E165: 6020 | F165: =IFERROR(INDEX('9_UK_Vol_Input'!$D$127:$D$289,MATCH($A165,'9_UK_Vol_Input'!$A$127:$A$289,0)),"") | G165: =IFERROR(INDEX('9_UK_Vol_Input'!$E$127:$E$289,MATCH($A165,'9_UK_Vol_Input'!$A$127:$A$289,0)),"") | H165: =IFERROR(INDEX('9_UK_Vol_Input'!$D$49:$D$122,MATCH($D165,'9_UK_Vol_Input'!$A$49:$A$122,0)),"") | I165: =IFERROR(INDEX('9_UK_Vol_Input'!$E$49:$E$122,MATCH($D165,'9_UK_Vol_Input'!$A$49:$A$122,0)),"") | J165: =IFERROR(INDEX('9_UK_Vol_Input'!$D$20:$D$44,MATCH($E165,'9_UK_Vol_Input'!$A$20:$A$44,0)),"") | K165: =IFERROR(INDEX('9_UK_Vol_Input'!$E$20:$E$44,MATCH($E165,'9_UK_Vol_Input'!$A$20:$A$44,0)),"") | L165: =IFERROR(INDEX('9_UK_Vol_Input'!$D$5:$D$15,MATCH($C165,'9_UK_Vol_Input'!$A$5:$A$15,0)),"") | M165: =IFERROR(INDEX('9_UK_Vol_Input'!$E$5:$E$15,MATCH($C165,'9_UK_Vol_Input'!$A$5:$A$15,0)),"") | N165: =IF(F165<>"",F165/(1+G165),IF(H165<>"",H165/(1+I165),IF(J165<>"",J165/(1+K165),IF(L165<>"",L165/(1+M165),"")))) | O165: =IFERROR(INDEX('7_UK_Beta_Input'!$D$127:$D$289,MATCH($A165,'7_UK_Beta_Input'!$A$127:$A$289,0)),"") | P165: =IFERROR(INDEX('7_UK_Beta_Input'!$D$49:$D$122,MATCH($D165,'7_UK_Beta_Input'!$A$49:$A$122,0)),"") | Q165: =IFERROR(INDEX('7_UK_Beta_Input'!$D$20:$D$44,MATCH($E165,'7_UK_Beta_Input'!$A$20:$A$44,0)),"") | R165: =IFERROR(INDEX('7_UK_Beta_Input'!$D$5:$D$15,MATCH($C165,'7_UK_Beta_Input'!$A$5:$A$15,0)),"") | S165: =IF(O165<>"",O165*'6_Credit_Bridge_Assumptions'!$B$8,IF(P165<>"",P165*'6_Credit_Bridge_Assumptions'!$B$8,IF(Q165<>"",Q165*'6_Credit_Bridge_Assumptions'!$B$8,IF(R165<>"",R165*'6_Credit_Bridge_Assumptions'!$B$8,"")))) | T165: =IF(N165<>"",N165,S165)

Sheet 11_Credit_Risk_Engine
A1: STEP 11 — bottom-up Merton distance-to-default PD, collateral-coverage LGD, and Expected Loss, baseline vs stressed. Pulls Stressed EV, Net Debt, Stressed LTV from 3_Scenario_Engine, and Asset Vol (Sigma Used, primary real-vol-based, cross-checked against beta) from 10_GICS_Asset_Vol via each deal's own Sub-Industry code.
A2: Deal Name | B2: Sub-Ind Code | C2: Asset Vol (sigma) | D2: Net Debt (F) | E2: Baseline EV (V0) | F2: Stressed EV (V1) | G2: Baseline DD | H2: Baseline PD | I2: Stressed DD | J2: Stressed PD | K2: Delta PD | L2: Stressed Leverage (x) | M2: Implied Rating | N2: S&P Cross-Check PD (real) | O2: Merton vs S&P Gap (pp) | P2: Stressed LTV | Q2: Stressed LGD | R2: Current LTV (baseline) | S2: Baseline LGD | T2: EAD (Invested) | U2: EL Baseline ($m) | V2: EL Stressed ($m) | W2: Delta EL ($m)
A3: ='3_Scenario_Engine'!A3 | B3: ='3_Scenario_Engine'!B3 | C3: =INDEX('10_GICS_Asset_Vol'!$T$3:$T$165,MATCH(B3,'10_GICS_Asset_Vol'!$A$3:$A$165,0)) | D3: ='3_Scenario_Engine'!J3 | E3: ='2_Deal_Tape'!S4 | F3: ='3_Scenario_Engine'!AF3 | G3: =(LN(E3/D3)+('6_Credit_Bridge_Assumptions'!$B$5-C3^2/2)*'6_Credit_Bridge_Assumptions'!$B$4)/(C3*SQRT('6_Credit_Bridge_Assumptions'!$B$4)) | H3: =NORMSDIST(-G3) | I3: =(LN(F3/D3)+('6_Credit_Bridge_Assumptions'!$B$5-C3^2/2)*'6_Credit_Bridge_Assumptions'!$B$4)/(C3*SQRT('6_Credit_Bridge_Assumptions'!$B$4)) | J3: =NORMSDIST(-I3) | K3: =J3-H3 | L3: ='3_Scenario_Engine'!Z3 | M3: =IF(L3<'6_Credit_Bridge_Assumptions'!$B$15,"BB",IF(L3<'6_Credit_Bridge_Assumptions'!$B$16,"B","CCC/C")) | N3: =IF(L3<'6_Credit_Bridge_Assumptions'!$B$15,'6_Credit_Bridge_Assumptions'!$B$17,IF(L3<'6_Credit_Bridge_Assumptions'!$B$16,'6_Credit_Bridge_Assumptions'!$B$18,'6_Credit_Bridge_Assumptions'!$B$19)) | O3: =(J3-N3)*100 | P3: ='3_Scenario_Engine'!AG3 | Q3: =IF(P3<=1,'6_Credit_Bridge_Assumptions'!$B$11,MIN('6_Credit_Bridge_Assumptions'!$B$12,MAX('6_Credit_Bridge_Assumptions'!$B$11,1-1/P3))) | R3: ='2_Deal_Tape'!U4 | S3: =IF(R3<=1,'6_Credit_Bridge_Assumptions'!$B$11,MIN('6_Credit_Bridge_Assumptions'!$B$12,MAX('6_Credit_Bridge_Assumptions'!$B$11,1-1/R3))) | T3: ='3_Scenario_Engine'!U3 | U3: =H3*S3*T3 | V3: =J3*Q3*T3 | W3: =V3-U3
A4: ='3_Scenario_Engine'!A4 | B4: ='3_Scenario_Engine'!B4 | C4: =INDEX('10_GICS_Asset_Vol'!$T$3:$T$165,MATCH(B4,'10_GICS_Asset_Vol'!$A$3:$A$165,0)) | D4: ='3_Scenario_Engine'!J4 | E4: ='2_Deal_Tape'!S5 | F4: ='3_Scenario_Engine'!AF4 | G4: =(LN(E4/D4)+('6_Credit_Bridge_Assumptions'!$B$5-C4^2/2)*'6_Credit_Bridge_Assumptions'!$B$4)/(C4*SQRT('6_Credit_Bridge_Assumptions'!$B$4)) | H4: =NORMSDIST(-G4) | I4: =(LN(F4/D4)+('6_Credit_Bridge_Assumptions'!$B$5-C4^2/2)*'6_Credit_Bridge_Assumptions'!$B$4)/(C4*SQRT('6_Credit_Bridge_Assumptions'!$B$4)) | J4: =NORMSDIST(-I4) | K4: =J4-H4 | L4: ='3_Scenario_Engine'!Z4 | M4: =IF(L4<'6_Credit_Bridge_Assumptions'!$B$15,"BB",IF(L4<'6_Credit_Bridge_Assumptions'!$B$16,"B","CCC/C")) | N4: =IF(L4<'6_Credit_Bridge_Assumptions'!$B$15,'6_Credit_Bridge_Assumptions'!$B$17,IF(L4<'6_Credit_Bridge_Assumptions'!$B$16,'6_Credit_Bridge_Assumptions'!$B$18,'6_Credit_Bridge_Assumptions'!$B$19)) | O4: =(J4-N4)*100 | P4: ='3_Scenario_Engine'!AG4 | Q4: =IF(P4<=1,'6_Credit_Bridge_Assumptions'!$B$11,MIN('6_Credit_Bridge_Assumptions'!$B$12,MAX('6_Credit_Bridge_Assumptions'!$B$11,1-1/P4))) | R4: ='2_Deal_Tape'!U5 | S4: =IF(R4<=1,'6_Credit_Bridge_Assumptions'!$B$11,MIN('6_Credit_Bridge_Assumptions'!$B$12,MAX('6_Credit_Bridge_Assumptions'!$B$11,1-1/R4))) | T4: ='3_Scenario_Engine'!U4 | U4: =H4*S4*T4 | V4: =J4*Q4*T4 | W4: =V4-U4
A5: ='3_Scenario_Engine'!A5 | B5: ='3_Scenario_Engine'!B5 | C5: =INDEX('10_GICS_Asset_Vol'!$T$3:$T$165,MATCH(B5,'10_GICS_Asset_Vol'!$A$3:$A$165,0)) | D5: ='3_Scenario_Engine'!J5 | E5: ='2_Deal_Tape'!S6 | F5: ='3_Scenario_Engine'!AF5 | G5: =(LN(E5/D5)+('6_Credit_Bridge_Assumptions'!$B$5-C5^2/2)*'6_Credit_Bridge_Assumptions'!$B$4)/(C5*SQRT('6_Credit_Bridge_Assumptions'!$B$4)) | H5: =NORMSDIST(-G5) | I5: =(LN(F5/D5)+('6_Credit_Bridge_Assumptions'!$B$5-C5^2/2)*'6_Credit_Bridge_Assumptions'!$B$4)/(C5*SQRT('6_Credit_Bridge_Assumptions'!$B$4)) | J5: =NORMSDIST(-I5) | K5: =J5-H5 | L5: ='3_Scenario_Engine'!Z5 | M5: =IF(L5<'6_Credit_Bridge_Assumptions'!$B$15,"BB",IF(L5<'6_Credit_Bridge_Assumptions'!$B$16,"B","CCC/C")) | N5: =IF(L5<'6_Credit_Bridge_Assumptions'!$B$15,'6_Credit_Bridge_Assumptions'!$B$17,IF(L5<'6_Credit_Bridge_Assumptions'!$B$16,'6_Credit_Bridge_Assumptions'!$B$18,'6_Credit_Bridge_Assumptions'!$B$19)) | O5: =(J5-N5)*100 | P5: ='3_Scenario_Engine'!AG5 | Q5: =IF(P5<=1,'6_Credit_Bridge_Assumptions'!$B$11,MIN('6_Credit_Bridge_Assumptions'!$B$12,MAX('6_Credit_Bridge_Assumptions'!$B$11,1-1/P5))) | R5: ='2_Deal_Tape'!U6 | S5: =IF(R5<=1,'6_Credit_Bridge_Assumptions'!$B$11,MIN('6_Credit_Bridge_Assumptions'!$B$12,MAX('6_Credit_Bridge_Assumptions'!$B$11,1-1/R5))) | T5: ='3_Scenario_Engine'!U5 | U5: =H5*S5*T5 | V5: =J5*Q5*T5 | W5: =V5-U5
A6: ='3_Scenario_Engine'!A6 | B6: ='3_Scenario_Engine'!B6 | C6: =INDEX('10_GICS_Asset_Vol'!$T$3:$T$165,MATCH(B6,'10_GICS_Asset_Vol'!$A$3:$A$165,0)) | D6: ='3_Scenario_Engine'!J6 | E6: ='2_Deal_Tape'!S7 | F6: ='3_Scenario_Engine'!AF6 | G6: =(LN(E6/D6)+('6_Credit_Bridge_Assumptions'!$B$5-C6^2/2)*'6_Credit_Bridge_Assumptions'!$B$4)/(C6*SQRT('6_Credit_Bridge_Assumptions'!$B$4)) | H6: =NORMSDIST(-G6) | I6: =(LN(F6/D6)+('6_Credit_Bridge_Assumptions'!$B$5-C6^2/2)*'6_Credit_Bridge_Assumptions'!$B$4)/(C6*SQRT('6_Credit_Bridge_Assumptions'!$B$4)) | J6: =NORMSDIST(-I6) | K6: =J6-H6 | L6: ='3_Scenario_Engine'!Z6 | M6: =IF(L6<'6_Credit_Bridge_Assumptions'!$B$15,"BB",IF(L6<'6_Credit_Bridge_Assumptions'!$B$16,"B","CCC/C")) | N6: =IF(L6<'6_Credit_Bridge_Assumptions'!$B$15,'6_Credit_Bridge_Assumptions'!$B$17,IF(L6<'6_Credit_Bridge_Assumptions'!$B$16,'6_Credit_Bridge_Assumptions'!$B$18,'6_Credit_Bridge_Assumptions'!$B$19)) | O6: =(J6-N6)*100 | P6: ='3_Scenario_Engine'!AG6 | Q6: =IF(P6<=1,'6_Credit_Bridge_Assumptions'!$B$11,MIN('6_Credit_Bridge_Assumptions'!$B$12,MAX('6_Credit_Bridge_Assumptions'!$B$11,1-1/P6))) | R6: ='2_Deal_Tape'!U7 | S6: =IF(R6<=1,'6_Credit_Bridge_Assumptions'!$B$11,MIN('6_Credit_Bridge_Assumptions'!$B$12,MAX('6_Credit_Bridge_Assumptions'!$B$11,1-1/R6))) | T6: ='3_Scenario_Engine'!U6 | U6: =H6*S6*T6 | V6: =J6*Q6*T6 | W6: =V6-U6
A7: ='3_Scenario_Engine'!A7 | B7: ='3_Scenario_Engine'!B7 | C7: =INDEX('10_GICS_Asset_Vol'!$T$3:$T$165,MATCH(B7,'10_GICS_Asset_Vol'!$A$3:$A$165,0)) | D7: ='3_Scenario_Engine'!J7 | E7: ='2_Deal_Tape'!S8 | F7: ='3_Scenario_Engine'!AF7 | G7: =(LN(E7/D7)+('6_Credit_Bridge_Assumptions'!$B$5-C7^2/2)*'6_Credit_Bridge_Assumptions'!$B$4)/(C7*SQRT('6_Credit_Bridge_Assumptions'!$B$4)) | H7: =NORMSDIST(-G7) | I7: =(LN(F7/D7)+('6_Credit_Bridge_Assumptions'!$B$5-C7^2/2)*'6_Credit_Bridge_Assumptions'!$B$4)/(C7*SQRT('6_Credit_Bridge_Assumptions'!$B$4)) | J7: =NORMSDIST(-I7) | K7: =J7-H7 | L7: ='3_Scenario_Engine'!Z7 | M7: =IF(L7<'6_Credit_Bridge_Assumptions'!$B$15,"BB",IF(L7<'6_Credit_Bridge_Assumptions'!$B$16,"B","CCC/C")) | N7: =IF(L7<'6_Credit_Bridge_Assumptions'!$B$15,'6_Credit_Bridge_Assumptions'!$B$17,IF(L7<'6_Credit_Bridge_Assumptions'!$B$16,'6_Credit_Bridge_Assumptions'!$B$18,'6_Credit_Bridge_Assumptions'!$B$19)) | O7: =(J7-N7)*100 | P7: ='3_Scenario_Engine'!AG7 | Q7: =IF(P7<=1,'6_Credit_Bridge_Assumptions'!$B$11,MIN('6_Credit_Bridge_Assumptions'!$B$12,MAX('6_Credit_Bridge_Assumptions'!$B$11,1-1/P7))) | R7: ='2_Deal_Tape'!U8 | S7: =IF(R7<=1,'6_Credit_Bridge_Assumptions'!$B$11,MIN('6_Credit_Bridge_Assumptions'!$B$12,MAX('6_Credit_Bridge_Assumptions'!$B$11,1-1/R7))) | T7: ='3_Scenario_Engine'!U7 | U7: =H7*S7*T7 | V7: =J7*Q7*T7 | W7: =V7-U7
A8: ='3_Scenario_Engine'!A8 | B8: ='3_Scenario_Engine'!B8 | C8: =INDEX('10_GICS_Asset_Vol'!$T$3:$T$165,MATCH(B8,'10_GICS_Asset_Vol'!$A$3:$A$165,0)) | D8: ='3_Scenario_Engine'!J8 | E8: ='2_Deal_Tape'!S9 | F8: ='3_Scenario_Engine'!AF8 | G8: =(LN(E8/D8)+('6_Credit_Bridge_Assumptions'!$B$5-C8^2/2)*'6_Credit_Bridge_Assumptions'!$B$4)/(C8*SQRT('6_Credit_Bridge_Assumptions'!$B$4)) | H8: =NORMSDIST(-G8) | I8: =(LN(F8/D8)+('6_Credit_Bridge_Assumptions'!$B$5-C8^2/2)*'6_Credit_Bridge_Assumptions'!$B$4)/(C8*SQRT('6_Credit_Bridge_Assumptions'!$B$4)) | J8: =NORMSDIST(-I8) | K8: =J8-H8 | L8: ='3_Scenario_Engine'!Z8 | M8: =IF(L8<'6_Credit_Bridge_Assumptions'!$B$15,"BB",IF(L8<'6_Credit_Bridge_Assumptions'!$B$16,"B","CCC/C")) | N8: =IF(L8<'6_Credit_Bridge_Assumptions'!$B$15,'6_Credit_Bridge_Assumptions'!$B$17,IF(L8<'6_Credit_Bridge_Assumptions'!$B$16,'6_Credit_Bridge_Assumptions'!$B$18,'6_Credit_Bridge_Assumptions'!$B$19)) | O8: =(J8-N8)*100 | P8: ='3_Scenario_Engine'!AG8 | Q8: =IF(P8<=1,'6_Credit_Bridge_Assumptions'!$B$11,MIN('6_Credit_Bridge_Assumptions'!$B$12,MAX('6_Credit_Bridge_Assumptions'!$B$11,1-1/P8))) | R8: ='2_Deal_Tape'!U9 | S8: =IF(R8<=1,'6_Credit_Bridge_Assumptions'!$B$11,MIN('6_Credit_Bridge_Assumptions'!$B$12,MAX('6_Credit_Bridge_Assumptions'!$B$11,1-1/R8))) | T8: ='3_Scenario_Engine'!U8 | U8: =H8*S8*T8 | V8: =J8*Q8*T8 | W8: =V8-U8
A9: ='3_Scenario_Engine'!A9 | B9: ='3_Scenario_Engine'!B9 | C9: =INDEX('10_GICS_Asset_Vol'!$T$3:$T$165,MATCH(B9,'10_GICS_Asset_Vol'!$A$3:$A$165,0)) | D9: ='3_Scenario_Engine'!J9 | E9: ='2_Deal_Tape'!S10 | F9: ='3_Scenario_Engine'!AF9 | G9: =(LN(E9/D9)+('6_Credit_Bridge_Assumptions'!$B$5-C9^2/2)*'6_Credit_Bridge_Assumptions'!$B$4)/(C9*SQRT('6_Credit_Bridge_Assumptions'!$B$4)) | H9: =NORMSDIST(-G9) | I9: =(LN(F9/D9)+('6_Credit_Bridge_Assumptions'!$B$5-C9^2/2)*'6_Credit_Bridge_Assumptions'!$B$4)/(C9*SQRT('6_Credit_Bridge_Assumptions'!$B$4)) | J9: =NORMSDIST(-I9) | K9: =J9-H9 | L9: ='3_Scenario_Engine'!Z9 | M9: =IF(L9<'6_Credit_Bridge_Assumptions'!$B$15,"BB",IF(L9<'6_Credit_Bridge_Assumptions'!$B$16,"B","CCC/C")) | N9: =IF(L9<'6_Credit_Bridge_Assumptions'!$B$15,'6_Credit_Bridge_Assumptions'!$B$17,IF(L9<'6_Credit_Bridge_Assumptions'!$B$16,'6_Credit_Bridge_Assumptions'!$B$18,'6_Credit_Bridge_Assumptions'!$B$19)) | O9: =(J9-N9)*100 | P9: ='3_Scenario_Engine'!AG9 | Q9: =IF(P9<=1,'6_Credit_Bridge_Assumptions'!$B$11,MIN('6_Credit_Bridge_Assumptions'!$B$12,MAX('6_Credit_Bridge_Assumptions'!$B$11,1-1/P9))) | R9: ='2_Deal_Tape'!U10 | S9: =IF(R9<=1,'6_Credit_Bridge_Assumptions'!$B$11,MIN('6_Credit_Bridge_Assumptions'!$B$12,MAX('6_Credit_Bridge_Assumptions'!$B$11,1-1/R9))) | T9: ='3_Scenario_Engine'!U9 | U9: =H9*S9*T9 | V9: =J9*Q9*T9 | W9: =V9-U9
A10: ='3_Scenario_Engine'!A10 | B10: ='3_Scenario_Engine'!B10 | C10: =INDEX('10_GICS_Asset_Vol'!$T$3:$T$165,MATCH(B10,'10_GICS_Asset_Vol'!$A$3:$A$165,0)) | D10: ='3_Scenario_Engine'!J10 | E10: ='2_Deal_Tape'!S11 | F10: ='3_Scenario_Engine'!AF10 | G10: =(LN(E10/D10)+('6_Credit_Bridge_Assumptions'!$B$5-C10^2/2)*'6_Credit_Bridge_Assumptions'!$B$4)/(C10*SQRT('6_Credit_Bridge_Assumptions'!$B$4)) | H10: =NORMSDIST(-G10) | I10: =(LN(F10/D10)+('6_Credit_Bridge_Assumptions'!$B$5-C10^2/2)*'6_Credit_Bridge_Assumptions'!$B$4)/(C10*SQRT('6_Credit_Bridge_Assumptions'!$B$4)) | J10: =NORMSDIST(-I10) | K10: =J10-H10 | L10: ='3_Scenario_Engine'!Z10 | M10: =IF(L10<'6_Credit_Bridge_Assumptions'!$B$15,"BB",IF(L10<'6_Credit_Bridge_Assumptions'!$B$16,"B","CCC/C")) | N10: =IF(L10<'6_Credit_Bridge_Assumptions'!$B$15,'6_Credit_Bridge_Assumptions'!$B$17,IF(L10<'6_Credit_Bridge_Assumptions'!$B$16,'6_Credit_Bridge_Assumptions'!$B$18,'6_Credit_Bridge_Assumptions'!$B$19)) | O10: =(J10-N10)*100 | P10: ='3_Scenario_Engine'!AG10 | Q10: =IF(P10<=1,'6_Credit_Bridge_Assumptions'!$B$11,MIN('6_Credit_Bridge_Assumptions'!$B$12,MAX('6_Credit_Bridge_Assumptions'!$B$11,1-1/P10))) | R10: ='2_Deal_Tape'!U11 | S10: =IF(R10<=1,'6_Credit_Bridge_Assumptions'!$B$11,MIN('6_Credit_Bridge_Assumptions'!$B$12,MAX('6_Credit_Bridge_Assumptions'!$B$11,1-1/R10))) | T10: ='3_Scenario_Engine'!U10 | U10: =H10*S10*T10 | V10: =J10*Q10*T10 | W10: =V10-U10
A11: ='3_Scenario_Engine'!A11 | B11: ='3_Scenario_Engine'!B11 | C11: =INDEX('10_GICS_Asset_Vol'!$T$3:$T$165,MATCH(B11,'10_GICS_Asset_Vol'!$A$3:$A$165,0)) | D11: ='3_Scenario_Engine'!J11 | E11: ='2_Deal_Tape'!S12 | F11: ='3_Scenario_Engine'!AF11 | G11: =(LN(E11/D11)+('6_Credit_Bridge_Assumptions'!$B$5-C11^2/2)*'6_Credit_Bridge_Assumptions'!$B$4)/(C11*SQRT('6_Credit_Bridge_Assumptions'!$B$4)) | H11: =NORMSDIST(-G11) | I11: =(LN(F11/D11)+('6_Credit_Bridge_Assumptions'!$B$5-C11^2/2)*'6_Credit_Bridge_Assumptions'!$B$4)/(C11*SQRT('6_Credit_Bridge_Assumptions'!$B$4)) | J11: =NORMSDIST(-I11) | K11: =J11-H11 | L11: ='3_Scenario_Engine'!Z11 | M11: =IF(L11<'6_Credit_Bridge_Assumptions'!$B$15,"BB",IF(L11<'6_Credit_Bridge_Assumptions'!$B$16,"B","CCC/C")) | N11: =IF(L11<'6_Credit_Bridge_Assumptions'!$B$15,'6_Credit_Bridge_Assumptions'!$B$17,IF(L11<'6_Credit_Bridge_Assumptions'!$B$16,'6_Credit_Bridge_Assumptions'!$B$18,'6_Credit_Bridge_Assumptions'!$B$19)) | O11: =(J11-N11)*100 | P11: ='3_Scenario_Engine'!AG11 | Q11: =IF(P11<=1,'6_Credit_Bridge_Assumptions'!$B$11,MIN('6_Credit_Bridge_Assumptions'!$B$12,MAX('6_Credit_Bridge_Assumptions'!$B$11,1-1/P11))) | R11: ='2_Deal_Tape'!U12 | S11: =IF(R11<=1,'6_Credit_Bridge_Assumptions'!$B$11,MIN('6_Credit_Bridge_Assumptions'!$B$12,MAX('6_Credit_Bridge_Assumptions'!$B$11,1-1/R11))) | T11: ='3_Scenario_Engine'!U11 | U11: =H11*S11*T11 | V11: =J11*Q11*T11 | W11: =V11-U11
A12: ='3_Scenario_Engine'!A12 | B12: ='3_Scenario_Engine'!B12 | C12: =INDEX('10_GICS_Asset_Vol'!$T$3:$T$165,MATCH(B12,'10_GICS_Asset_Vol'!$A$3:$A$165,0)) | D12: ='3_Scenario_Engine'!J12 | E12: ='2_Deal_Tape'!S13 | F12: ='3_Scenario_Engine'!AF12 | G12: =(LN(E12/D12)+('6_Credit_Bridge_Assumptions'!$B$5-C12^2/2)*'6_Credit_Bridge_Assumptions'!$B$4)/(C12*SQRT('6_Credit_Bridge_Assumptions'!$B$4)) | H12: =NORMSDIST(-G12) | I12: =(LN(F12/D12)+('6_Credit_Bridge_Assumptions'!$B$5-C12^2/2)*'6_Credit_Bridge_Assumptions'!$B$4)/(C12*SQRT('6_Credit_Bridge_Assumptions'!$B$4)) | J12: =NORMSDIST(-I12) | K12: =J12-H12 | L12: ='3_Scenario_Engine'!Z12 | M12: =IF(L12<'6_Credit_Bridge_Assumptions'!$B$15,"BB",IF(L12<'6_Credit_Bridge_Assumptions'!$B$16,"B","CCC/C")) | N12: =IF(L12<'6_Credit_Bridge_Assumptions'!$B$15,'6_Credit_Bridge_Assumptions'!$B$17,IF(L12<'6_Credit_Bridge_Assumptions'!$B$16,'6_Credit_Bridge_Assumptions'!$B$18,'6_Credit_Bridge_Assumptions'!$B$19)) | O12: =(J12-N12)*100 | P12: ='3_Scenario_Engine'!AG12 | Q12: =IF(P12<=1,'6_Credit_Bridge_Assumptions'!$B$11,MIN('6_Credit_Bridge_Assumptions'!$B$12,MAX('6_Credit_Bridge_Assumptions'!$B$11,1-1/P12))) | R12: ='2_Deal_Tape'!U13 | S12: =IF(R12<=1,'6_Credit_Bridge_Assumptions'!$B$11,MIN('6_Credit_Bridge_Assumptions'!$B$12,MAX('6_Credit_Bridge_Assumptions'!$B$11,1-1/R12))) | T12: ='3_Scenario_Engine'!U12 | U12: =H12*S12*T12 | V12: =J12*Q12*T12 | W12: =V12-U12
A13: ='3_Scenario_Engine'!A13 | B13: ='3_Scenario_Engine'!B13 | C13: =INDEX('10_GICS_Asset_Vol'!$T$3:$T$165,MATCH(B13,'10_GICS_Asset_Vol'!$A$3:$A$165,0)) | D13: ='3_Scenario_Engine'!J13 | E13: ='2_Deal_Tape'!S14 | F13: ='3_Scenario_Engine'!AF13 | G13: =(LN(E13/D13)+('6_Credit_Bridge_Assumptions'!$B$5-C13^2/2)*'6_Credit_Bridge_Assumptions'!$B$4)/(C13*SQRT('6_Credit_Bridge_Assumptions'!$B$4)) | H13: =NORMSDIST(-G13) | I13: =(LN(F13/D13)+('6_Credit_Bridge_Assumptions'!$B$5-C13^2/2)*'6_Credit_Bridge_Assumptions'!$B$4)/(C13*SQRT('6_Credit_Bridge_Assumptions'!$B$4)) | J13: =NORMSDIST(-I13) | K13: =J13-H13 | L13: ='3_Scenario_Engine'!Z13 | M13: =IF(L13<'6_Credit_Bridge_Assumptions'!$B$15,"BB",IF(L13<'6_Credit_Bridge_Assumptions'!$B$16,"B","CCC/C")) | N13: =IF(L13<'6_Credit_Bridge_Assumptions'!$B$15,'6_Credit_Bridge_Assumptions'!$B$17,IF(L13<'6_Credit_Bridge_Assumptions'!$B$16,'6_Credit_Bridge_Assumptions'!$B$18,'6_Credit_Bridge_Assumptions'!$B$19)) | O13: =(J13-N13)*100 | P13: ='3_Scenario_Engine'!AG13 | Q13: =IF(P13<=1,'6_Credit_Bridge_Assumptions'!$B$11,MIN('6_Credit_Bridge_Assumptions'!$B$12,MAX('6_Credit_Bridge_Assumptions'!$B$11,1-1/P13))) | R13: ='2_Deal_Tape'!U14 | S13: =IF(R13<=1,'6_Credit_Bridge_Assumptions'!$B$11,MIN('6_Credit_Bridge_Assumptions'!$B$12,MAX('6_Credit_Bridge_Assumptions'!$B$11,1-1/R13))) | T13: ='3_Scenario_Engine'!U13 | U13: =H13*S13*T13 | V13: =J13*Q13*T13 | W13: =V13-U13
A14: ='3_Scenario_Engine'!A14 | B14: ='3_Scenario_Engine'!B14 | C14: =INDEX('10_GICS_Asset_Vol'!$T$3:$T$165,MATCH(B14,'10_GICS_Asset_Vol'!$A$3:$A$165,0)) | D14: ='3_Scenario_Engine'!J14 | E14: ='2_Deal_Tape'!S15 | F14: ='3_Scenario_Engine'!AF14 | G14: =(LN(E14/D14)+('6_Credit_Bridge_Assumptions'!$B$5-C14^2/2)*'6_Credit_Bridge_Assumptions'!$B$4)/(C14*SQRT('6_Credit_Bridge_Assumptions'!$B$4)) | H14: =NORMSDIST(-G14) | I14: =(LN(F14/D14)+('6_Credit_Bridge_Assumptions'!$B$5-C14^2/2)*'6_Credit_Bridge_Assumptions'!$B$4)/(C14*SQRT('6_Credit_Bridge_Assumptions'!$B$4)) | J14: =NORMSDIST(-I14) | K14: =J14-H14 | L14: ='3_Scenario_Engine'!Z14 | M14: =IF(L14<'6_Credit_Bridge_Assumptions'!$B$15,"BB",IF(L14<'6_Credit_Bridge_Assumptions'!$B$16,"B","CCC/C")) | N14: =IF(L14<'6_Credit_Bridge_Assumptions'!$B$15,'6_Credit_Bridge_Assumptions'!$B$17,IF(L14<'6_Credit_Bridge_Assumptions'!$B$16,'6_Credit_Bridge_Assumptions'!$B$18,'6_Credit_Bridge_Assumptions'!$B$19)) | O14: =(J14-N14)*100 | P14: ='3_Scenario_Engine'!AG14 | Q14: =IF(P14<=1,'6_Credit_Bridge_Assumptions'!$B$11,MIN('6_Credit_Bridge_Assumptions'!$B$12,MAX('6_Credit_Bridge_Assumptions'!$B$11,1-1/P14))) | R14: ='2_Deal_Tape'!U15 | S14: =IF(R14<=1,'6_Credit_Bridge_Assumptions'!$B$11,MIN('6_Credit_Bridge_Assumptions'!$B$12,MAX('6_Credit_Bridge_Assumptions'!$B$11,1-1/R14))) | T14: ='3_Scenario_Engine'!U14 | U14: =H14*S14*T14 | V14: =J14*Q14*T14 | W14: =V14-U14
... A32: ='3_Scenario_Engine'!A32 | B32: ='3_Scenario_Engine'!B32 | C32: =INDEX('10_GICS_Asset_Vol'!$T$3:$T$165,MATCH(B32,'10_GICS_Asset_Vol'!$A$3:$A$165,0)) | D32: ='3_Scenario_Engine'!J32 | E32: ='2_Deal_Tape'!S33 | F32: ='3_Scenario_Engine'!AF32 | G32: =(LN(E32/D32)+('6_Credit_Bridge_Assumptions'!$B$5-C32^2/2)*'6_Credit_Bridge_Assumptions'!$B$4)/(C32*SQRT('6_Credit_Bridge_Assumptions'!$B$4)) | H32: =NORMSDIST(-G32) | I32: =(LN(F32/D32)+('6_Credit_Bridge_Assumptions'!$B$5-C32^2/2)*'6_Credit_Bridge_Assumptions'!$B$4)/(C32*SQRT('6_Credit_Bridge_Assumptions'!$B$4)) | J32: =NORMSDIST(-I32) | K32: =J32-H32 | L32: ='3_Scenario_Engine'!Z32 | M32: =IF(L32<'6_Credit_Bridge_Assumptions'!$B$15,"BB",IF(L32<'6_Credit_Bridge_Assumptions'!$B$16,"B","CCC/C")) | N32: =IF(L32<'6_Credit_Bridge_Assumptions'!$B$15,'6_Credit_Bridge_Assumptions'!$B$17,IF(L32<'6_Credit_Bridge_Assumptions'!$B$16,'6_Credit_Bridge_Assumptions'!$B$18,'6_Credit_Bridge_Assumptions'!$B$19)) | O32: =(J32-N32)*100 | P32: ='3_Scenario_Engine'!AG32 | Q32: =IF(P32<=1,'6_Credit_Bridge_Assumptions'!$B$11,MIN('6_Credit_Bridge_Assumptions'!$B$12,MAX('6_Credit_Bridge_Assumptions'!$B$11,1-1/P32))) | R32: ='2_Deal_Tape'!U33 | S32: =IF(R32<=1,'6_Credit_Bridge_Assumptions'!$B$11,MIN('6_Credit_Bridge_Assumptions'!$B$12,MAX('6_Credit_Bridge_Assumptions'!$B$11,1-1/R32))) | T32: ='3_Scenario_Engine'!U32 | U32: =H32*S32*T32 | V32: =J32*Q32*T32 | W32: =V32-U32

Sheet 12_TopDown_Spread_Engine
A1: STEP 12 — THREE top-down spread bases, all feeding the same spread-duration MTM formula. (1) Credit-derived: EL-implied spread x Risk Premium Multiplier. (2) Exogenous: original GICS-level input, unchanged. (3) NEW — Spread-cascade-adjusted: the SAME exogenous input, rescaled by a REAL (dummy) RelSpread ratio from 8_UK_Spread_Input — this deal's GICS position's own default-risk spread relative to its sector, cascaded through Industry and Industry Group (columns S-Z), same telescoping mechanic as the beta cascade used in UK_Shock_Propagation_RealData_Only.xlsx. Every lookup is single-cell (deal's Sector/Industry/IG code resolved once each in columns S-U, then reused) — no nested lookups.
A2: Deal Name | B2: Sub-Ind Code | C2: Delta PD (from sheet 11) | D2: Stressed LGD (from sheet 11) | E2: EL-Implied Spread (bps) | F2: Stressed Leverage (x) | G2: Risk Premium Multiplier | H2: Credit-Derived Spread (bps) | I2: Spread Duration | J2: Invested Amount | K2: Price Impact % (credit-derived) | L2: MTM $ (credit-derived) | M2: Exogenous SWES Spread (bps) | N2: Exogenous MTM $ (3_Scenario_Engine) | O2: Gap: credit-derived minus exogenous ($m) | P2: Bottom-Up Delta EL ($m, from sheet 11) | Q2: Bottom-Up Delta EL (% of invested) | R2: SAME-BASIS GAP: |Top-Down %| minus Bottom-Up % (pp) | S2: Deal's Sector Code | T2: Deal's Industry Code | U2: Deal's IG Code | V2: Sector Spread bps | W2: IG Spread bps | X2: Industry Spread bps | Y2: Sub-Ind Spread bps | Z2: RelSpread L2 x L3 x L4 | AA2: Spread-Cascade-Adjusted MTM $ (dummy)
A3: ='3_Scenario_Engine'!A3 | B3: ='3_Scenario_Engine'!B3 | C3: ='11_Credit_Risk_Engine'!K3 | D3: ='11_Credit_Risk_Engine'!Q3 | E3: =C3*D3*10000 | F3: ='3_Scenario_Engine'!Z3 | G3: =IF(F3<'6_Credit_Bridge_Assumptions'!$B$15,'6_Credit_Bridge_Assumptions'!$B$22,IF(F3<'6_Credit_Bridge_Assumptions'!$B$16,'6_Credit_Bridge_Assumptions'!$B$23,'6_Credit_Bridge_Assumptions'!$B$24)) | H3: =E3*G3 | I3: ='3_Scenario_Engine'!T3 | J3: ='3_Scenario_Engine'!U3 | K3: =-I3*(H3/10000) | L3: =J3*K3 | M3: ='3_Scenario_Engine'!F3 | N3: ='3_Scenario_Engine'!AQ3 | O3: =L3-N3 | P3: ='11_Credit_Risk_Engine'!W3 | Q3: =P3/J3 | R3: =(ABS(K3)-Q3)*100 | S3: =INDEX('10_GICS_Asset_Vol'!$C$3:$C$165,MATCH(B3,'10_GICS_Asset_Vol'!$A$3:$A$165,0)) | T3: =INDEX('10_GICS_Asset_Vol'!$D$3:$D$165,MATCH(B3,'10_GICS_Asset_Vol'!$A$3:$A$165,0)) | U3: =INDEX('10_GICS_Asset_Vol'!$E$3:$E$165,MATCH(B3,'10_GICS_Asset_Vol'!$A$3:$A$165,0)) | V3: =INDEX('8_UK_Spread_Input'!$D$5:$D$15,MATCH(S3,'8_UK_Spread_Input'!$A$5:$A$15,0)) | W3: =INDEX('8_UK_Spread_Input'!$D$20:$D$44,MATCH(U3,'8_UK_Spread_Input'!$A$20:$A$44,0)) | X3: =INDEX('8_UK_Spread_Input'!$D$49:$D$122,MATCH(T3,'8_UK_Spread_Input'!$A$49:$A$122,0)) | Y3: =INDEX('8_UK_Spread_Input'!$D$127:$D$289,MATCH(B3,'8_UK_Spread_Input'!$A$127:$A$289,0)) | Z3: =(W3/V3)*(X3/W3)*(Y3/X3) | AA3: =J3*(-I3*((M3*Z3)/10000))
A4: ='3_Scenario_Engine'!A4 | B4: ='3_Scenario_Engine'!B4 | C4: ='11_Credit_Risk_Engine'!K4 | D4: ='11_Credit_Risk_Engine'!Q4 | E4: =C4*D4*10000 | F4: ='3_Scenario_Engine'!Z4 | G4: =IF(F4<'6_Credit_Bridge_Assumptions'!$B$15,'6_Credit_Bridge_Assumptions'!$B$22,IF(F4<'6_Credit_Bridge_Assumptions'!$B$16,'6_Credit_Bridge_Assumptions'!$B$23,'6_Credit_Bridge_Assumptions'!$B$24)) | H4: =E4*G4 | I4: ='3_Scenario_Engine'!T4 | J4: ='3_Scenario_Engine'!U4 | K4: =-I4*(H4/10000) | L4: =J4*K4 | M4: ='3_Scenario_Engine'!F4 | N4: ='3_Scenario_Engine'!AQ4 | O4: =L4-N4 | P4: ='11_Credit_Risk_Engine'!W4 | Q4: =P4/J4 | R4: =(ABS(K4)-Q4)*100 | S4: =INDEX('10_GICS_Asset_Vol'!$C$3:$C$165,MATCH(B4,'10_GICS_Asset_Vol'!$A$3:$A$165,0)) | T4: =INDEX('10_GICS_Asset_Vol'!$D$3:$D$165,MATCH(B4,'10_GICS_Asset_Vol'!$A$3:$A$165,0)) | U4: =INDEX('10_GICS_Asset_Vol'!$E$3:$E$165,MATCH(B4,'10_GICS_Asset_Vol'!$A$3:$A$165,0)) | V4: =INDEX('8_UK_Spread_Input'!$D$5:$D$15,MATCH(S4,'8_UK_Spread_Input'!$A$5:$A$15,0)) | W4: =INDEX('8_UK_Spread_Input'!$D$20:$D$44,MATCH(U4,'8_UK_Spread_Input'!$A$20:$A$44,0)) | X4: =INDEX('8_UK_Spread_Input'!$D$49:$D$122,MATCH(T4,'8_UK_Spread_Input'!$A$49:$A$122,0)) | Y4: =INDEX('8_UK_Spread_Input'!$D$127:$D$289,MATCH(B4,'8_UK_Spread_Input'!$A$127:$A$289,0)) | Z4: =(W4/V4)*(X4/W4)*(Y4/X4) | AA4: =J4*(-I4*((M4*Z4)/10000))
A5: ='3_Scenario_Engine'!A5 | B5: ='3_Scenario_Engine'!B5 | C5: ='11_Credit_Risk_Engine'!K5 | D5: ='11_Credit_Risk_Engine'!Q5 | E5: =C5*D5*10000 | F5: ='3_Scenario_Engine'!Z5 | G5: =IF(F5<'6_Credit_Bridge_Assumptions'!$B$15,'6_Credit_Bridge_Assumptions'!$B$22,IF(F5<'6_Credit_Bridge_Assumptions'!$B$16,'6_Credit_Bridge_Assumptions'!$B$23,'6_Credit_Bridge_Assumptions'!$B$24)) | H5: =E5*G5 | I5: ='3_Scenario_Engine'!T5 | J5: ='3_Scenario_Engine'!U5 | K5: =-I5*(H5/10000) | L5: =J5*K5 | M5: ='3_Scenario_Engine'!F5 | N5: ='3_Scenario_Engine'!AQ5 | O5: =L5-N5 | P5: ='11_Credit_Risk_Engine'!W5 | Q5: =P5/J5 | R5: =(ABS(K5)-Q5)*100 | S5: =INDEX('10_GICS_Asset_Vol'!$C$3:$C$165,MATCH(B5,'10_GICS_Asset_Vol'!$A$3:$A$165,0)) | T5: =INDEX('10_GICS_Asset_Vol'!$D$3:$D$165,MATCH(B5,'10_GICS_Asset_Vol'!$A$3:$A$165,0)) | U5: =INDEX('10_GICS_Asset_Vol'!$E$3:$E$165,MATCH(B5,'10_GICS_Asset_Vol'!$A$3:$A$165,0)) | V5: =INDEX('8_UK_Spread_Input'!$D$5:$D$15,MATCH(S5,'8_UK_Spread_Input'!$A$5:$A$15,0)) | W5: =INDEX('8_UK_Spread_Input'!$D$20:$D$44,MATCH(U5,'8_UK_Spread_Input'!$A$20:$A$44,0)) | X5: =INDEX('8_UK_Spread_Input'!$D$49:$D$122,MATCH(T5,'8_UK_Spread_Input'!$A$49:$A$122,0)) | Y5: =INDEX('8_UK_Spread_Input'!$D$127:$D$289,MATCH(B5,'8_UK_Spread_Input'!$A$127:$A$289,0)) | Z5: =(W5/V5)*(X5/W5)*(Y5/X5) | AA5: =J5*(-I5*((M5*Z5)/10000))
A6: ='3_Scenario_Engine'!A6 | B6: ='3_Scenario_Engine'!B6 | C6: ='11_Credit_Risk_Engine'!K6 | D6: ='11_Credit_Risk_Engine'!Q6 | E6: =C6*D6*10000 | F6: ='3_Scenario_Engine'!Z6 | G6: =IF(F6<'6_Credit_Bridge_Assumptions'!$B$15,'6_Credit_Bridge_Assumptions'!$B$22,IF(F6<'6_Credit_Bridge_Assumptions'!$B$16,'6_Credit_Bridge_Assumptions'!$B$23,'6_Credit_Bridge_Assumptions'!$B$24)) | H6: =E6*G6 | I6: ='3_Scenario_Engine'!T6 | J6: ='3_Scenario_Engine'!U6 | K6: =-I6*(H6/10000) | L6: =J6*K6 | M6: ='3_Scenario_Engine'!F6 | N6: ='3_Scenario_Engine'!AQ6 | O6: =L6-N6 | P6: ='11_Credit_Risk_Engine'!W6 | Q6: =P6/J6 | R6: =(ABS(K6)-Q6)*100 | S6: =INDEX('10_GICS_Asset_Vol'!$C$3:$C$165,MATCH(B6,'10_GICS_Asset_Vol'!$A$3:$A$165,0)) | T6: =INDEX('10_GICS_Asset_Vol'!$D$3:$D$165,MATCH(B6,'10_GICS_Asset_Vol'!$A$3:$A$165,0)) | U6: =INDEX('10_GICS_Asset_Vol'!$E$3:$E$165,MATCH(B6,'10_GICS_Asset_Vol'!$A$3:$A$165,0)) | V6: =INDEX('8_UK_Spread_Input'!$D$5:$D$15,MATCH(S6,'8_UK_Spread_Input'!$A$5:$A$15,0)) | W6: =INDEX('8_UK_Spread_Input'!$D$20:$D$44,MATCH(U6,'8_UK_Spread_Input'!$A$20:$A$44,0)) | X6: =INDEX('8_UK_Spread_Input'!$D$49:$D$122,MATCH(T6,'8_UK_Spread_Input'!$A$49:$A$122,0)) | Y6: =INDEX('8_UK_Spread_Input'!$D$127:$D$289,MATCH(B6,'8_UK_Spread_Input'!$A$127:$A$289,0)) | Z6: =(W6/V6)*(X6/W6)*(Y6/X6) | AA6: =J6*(-I6*((M6*Z6)/10000))
A7: ='3_Scenario_Engine'!A7 | B7: ='3_Scenario_Engine'!B7 | C7: ='11_Credit_Risk_Engine'!K7 | D7: ='11_Credit_Risk_Engine'!Q7 | E7: =C7*D7*10000 | F7: ='3_Scenario_Engine'!Z7 | G7: =IF(F7<'6_Credit_Bridge_Assumptions'!$B$15,'6_Credit_Bridge_Assumptions'!$B$22,IF(F7<'6_Credit_Bridge_Assumptions'!$B$16,'6_Credit_Bridge_Assumptions'!$B$23,'6_Credit_Bridge_Assumptions'!$B$24)) | H7: =E7*G7 | I7: ='3_Scenario_Engine'!T7 | J7: ='3_Scenario_Engine'!U7 | K7: =-I7*(H7/10000) | L7: =J7*K7 | M7: ='3_Scenario_Engine'!F7 | N7: ='3_Scenario_Engine'!AQ7 | O7: =L7-N7 | P7: ='11_Credit_Risk_Engine'!W7 | Q7: =P7/J7 | R7: =(ABS(K7)-Q7)*100 | S7: =INDEX('10_GICS_Asset_Vol'!$C$3:$C$165,MATCH(B7,'10_GICS_Asset_Vol'!$A$3:$A$165,0)) | T7: =INDEX('10_GICS_Asset_Vol'!$D$3:$D$165,MATCH(B7,'10_GICS_Asset_Vol'!$A$3:$A$165,0)) | U7: =INDEX('10_GICS_Asset_Vol'!$E$3:$E$165,MATCH(B7,'10_GICS_Asset_Vol'!$A$3:$A$165,0)) | V7: =INDEX('8_UK_Spread_Input'!$D$5:$D$15,MATCH(S7,'8_UK_Spread_Input'!$A$5:$A$15,0)) | W7: =INDEX('8_UK_Spread_Input'!$D$20:$D$44,MATCH(U7,'8_UK_Spread_Input'!$A$20:$A$44,0)) | X7: =INDEX('8_UK_Spread_Input'!$D$49:$D$122,MATCH(T7,'8_UK_Spread_Input'!$A$49:$A$122,0)) | Y7: =INDEX('8_UK_Spread_Input'!$D$127:$D$289,MATCH(B7,'8_UK_Spread_Input'!$A$127:$A$289,0)) | Z7: =(W7/V7)*(X7/W7)*(Y7/X7) | AA7: =J7*(-I7*((M7*Z7)/10000))
A8: ='3_Scenario_Engine'!A8 | B8: ='3_Scenario_Engine'!B8 | C8: ='11_Credit_Risk_Engine'!K8 | D8: ='11_Credit_Risk_Engine'!Q8 | E8: =C8*D8*10000 | F8: ='3_Scenario_Engine'!Z8 | G8: =IF(F8<'6_Credit_Bridge_Assumptions'!$B$15,'6_Credit_Bridge_Assumptions'!$B$22,IF(F8<'6_Credit_Bridge_Assumptions'!$B$16,'6_Credit_Bridge_Assumptions'!$B$23,'6_Credit_Bridge_Assumptions'!$B$24)) | H8: =E8*G8 | I8: ='3_Scenario_Engine'!T8 | J8: ='3_Scenario_Engine'!U8 | K8: =-I8*(H8/10000) | L8: =J8*K8 | M8: ='3_Scenario_Engine'!F8 | N8: ='3_Scenario_Engine'!AQ8 | O8: =L8-N8 | P8: ='11_Credit_Risk_Engine'!W8 | Q8: =P8/J8 | R8: =(ABS(K8)-Q8)*100 | S8: =INDEX('10_GICS_Asset_Vol'!$C$3:$C$165,MATCH(B8,'10_GICS_Asset_Vol'!$A$3:$A$165,0)) | T8: =INDEX('10_GICS_Asset_Vol'!$D$3:$D$165,MATCH(B8,'10_GICS_Asset_Vol'!$A$3:$A$165,0)) | U8: =INDEX('10_GICS_Asset_Vol'!$E$3:$E$165,MATCH(B8,'10_GICS_Asset_Vol'!$A$3:$A$165,0)) | V8: =INDEX('8_UK_Spread_Input'!$D$5:$D$15,MATCH(S8,'8_UK_Spread_Input'!$A$5:$A$15,0)) | W8: =INDEX('8_UK_Spread_Input'!$D$20:$D$44,MATCH(U8,'8_UK_Spread_Input'!$A$20:$A$44,0)) | X8: =INDEX('8_UK_Spread_Input'!$D$49:$D$122,MATCH(T8,'8_UK_Spread_Input'!$A$49:$A$122,0)) | Y8: =INDEX('8_UK_Spread_Input'!$D$127:$D$289,MATCH(B8,'8_UK_Spread_Input'!$A$127:$A$289,0)) | Z8: =(W8/V8)*(X8/W8)*(Y8/X8) | AA8: =J8*(-I8*((M8*Z8)/10000))
A9: ='3_Scenario_Engine'!A9 | B9: ='3_Scenario_Engine'!B9 | C9: ='11_Credit_Risk_Engine'!K9 | D9: ='11_Credit_Risk_Engine'!Q9 | E9: =C9*D9*10000 | F9: ='3_Scenario_Engine'!Z9 | G9: =IF(F9<'6_Credit_Bridge_Assumptions'!$B$15,'6_Credit_Bridge_Assumptions'!$B$22,IF(F9<'6_Credit_Bridge_Assumptions'!$B$16,'6_Credit_Bridge_Assumptions'!$B$23,'6_Credit_Bridge_Assumptions'!$B$24)) | H9: =E9*G9 | I9: ='3_Scenario_Engine'!T9 | J9: ='3_Scenario_Engine'!U9 | K9: =-I9*(H9/10000) | L9: =J9*K9 | M9: ='3_Scenario_Engine'!F9 | N9: ='3_Scenario_Engine'!AQ9 | O9: =L9-N9 | P9: ='11_Credit_Risk_Engine'!W9 | Q9: =P9/J9 | R9: =(ABS(K9)-Q9)*100 | S9: =INDEX('10_GICS_Asset_Vol'!$C$3:$C$165,MATCH(B9,'10_GICS_Asset_Vol'!$A$3:$A$165,0)) | T9: =INDEX('10_GICS_Asset_Vol'!$D$3:$D$165,MATCH(B9,'10_GICS_Asset_Vol'!$A$3:$A$165,0)) | U9: =INDEX('10_GICS_Asset_Vol'!$E$3:$E$165,MATCH(B9,'10_GICS_Asset_Vol'!$A$3:$A$165,0)) | V9: =INDEX('8_UK_Spread_Input'!$D$5:$D$15,MATCH(S9,'8_UK_Spread_Input'!$A$5:$A$15,0)) | W9: =INDEX('8_UK_Spread_Input'!$D$20:$D$44,MATCH(U9,'8_UK_Spread_Input'!$A$20:$A$44,0)) | X9: =INDEX('8_UK_Spread_Input'!$D$49:$D$122,MATCH(T9,'8_UK_Spread_Input'!$A$49:$A$122,0)) | Y9: =INDEX('8_UK_Spread_Input'!$D$127:$D$289,MATCH(B9,'8_UK_Spread_Input'!$A$127:$A$289,0)) | Z9: =(W9/V9)*(X9/W9)*(Y9/X9) | AA9: =J9*(-I9*((M9*Z9)/10000))
A10: ='3_Scenario_Engine'!A10 | B10: ='3_Scenario_Engine'!B10 | C10: ='11_Credit_Risk_Engine'!K10 | D10: ='11_Credit_Risk_Engine'!Q10 | E10: =C10*D10*10000 | F10: ='3_Scenario_Engine'!Z10 | G10: =IF(F10<'6_Credit_Bridge_Assumptions'!$B$15,'6_Credit_Bridge_Assumptions'!$B$22,IF(F10<'6_Credit_Bridge_Assumptions'!$B$16,'6_Credit_Bridge_Assumptions'!$B$23,'6_Credit_Bridge_Assumptions'!$B$24)) | H10: =E10*G10 | I10: ='3_Scenario_Engine'!T10 | J10: ='3_Scenario_Engine'!U10 | K10: =-I10*(H10/10000) | L10: =J10*K10 | M10: ='3_Scenario_Engine'!F10 | N10: ='3_Scenario_Engine'!AQ10 | O10: =L10-N10 | P10: ='11_Credit_Risk_Engine'!W10 | Q10: =P10/J10 | R10: =(ABS(K10)-Q10)*100 | S10: =INDEX('10_GICS_Asset_Vol'!$C$3:$C$165,MATCH(B10,'10_GICS_Asset_Vol'!$A$3:$A$165,0)) | T10: =INDEX('10_GICS_Asset_Vol'!$D$3:$D$165,MATCH(B10,'10_GICS_Asset_Vol'!$A$3:$A$165,0)) | U10: =INDEX('10_GICS_Asset_Vol'!$E$3:$E$165,MATCH(B10,'10_GICS_Asset_Vol'!$A$3:$A$165,0)) | V10: =INDEX('8_UK_Spread_Input'!$D$5:$D$15,MATCH(S10,'8_UK_Spread_Input'!$A$5:$A$15,0)) | W10: =INDEX('8_UK_Spread_Input'!$D$20:$D$44,MATCH(U10,'8_UK_Spread_Input'!$A$20:$A$44,0)) | X10: =INDEX('8_UK_Spread_Input'!$D$49:$D$122,MATCH(T10,'8_UK_Spread_Input'!$A$49:$A$122,0)) | Y10: =INDEX('8_UK_Spread_Input'!$D$127:$D$289,MATCH(B10,'8_UK_Spread_Input'!$A$127:$A$289,0)) | Z10: =(W10/V10)*(X10/W10)*(Y10/X10) | AA10: =J10*(-I10*((M10*Z10)/10000))
A11: ='3_Scenario_Engine'!A11 | B11: ='3_Scenario_Engine'!B11 | C11: ='11_Credit_Risk_Engine'!K11 | D11: ='11_Credit_Risk_Engine'!Q11 | E11: =C11*D11*10000 | F11: ='3_Scenario_Engine'!Z11 | G11: =IF(F11<'6_Credit_Bridge_Assumptions'!$B$15,'6_Credit_Bridge_Assumptions'!$B$22,IF(F11<'6_Credit_Bridge_Assumptions'!$B$16,'6_Credit_Bridge_Assumptions'!$B$23,'6_Credit_Bridge_Assumptions'!$B$24)) | H11: =E11*G11 | I11: ='3_Scenario_Engine'!T11 | J11: ='3_Scenario_Engine'!U11 | K11: =-I11*(H11/10000) | L11: =J11*K11 | M11: ='3_Scenario_Engine'!F11 | N11: ='3_Scenario_Engine'!AQ11 | O11: =L11-N11 | P11: ='11_Credit_Risk_Engine'!W11 | Q11: =P11/J11 | R11: =(ABS(K11)-Q11)*100 | S11: =INDEX('10_GICS_Asset_Vol'!$C$3:$C$165,MATCH(B11,'10_GICS_Asset_Vol'!$A$3:$A$165,0)) | T11: =INDEX('10_GICS_Asset_Vol'!$D$3:$D$165,MATCH(B11,'10_GICS_Asset_Vol'!$A$3:$A$165,0)) | U11: =INDEX('10_GICS_Asset_Vol'!$E$3:$E$165,MATCH(B11,'10_GICS_Asset_Vol'!$A$3:$A$165,0)) | V11: =INDEX('8_UK_Spread_Input'!$D$5:$D$15,MATCH(S11,'8_UK_Spread_Input'!$A$5:$A$15,0)) | W11: =INDEX('8_UK_Spread_Input'!$D$20:$D$44,MATCH(U11,'8_UK_Spread_Input'!$A$20:$A$44,0)) | X11: =INDEX('8_UK_Spread_Input'!$D$49:$D$122,MATCH(T11,'8_UK_Spread_Input'!$A$49:$A$122,0)) | Y11: =INDEX('8_UK_Spread_Input'!$D$127:$D$289,MATCH(B11,'8_UK_Spread_Input'!$A$127:$A$289,0)) | Z11: =(W11/V11)*(X11/W11)*(Y11/X11) | AA11: =J11*(-I11*((M11*Z11)/10000))
A12: ='3_Scenario_Engine'!A12 | B12: ='3_Scenario_Engine'!B12 | C12: ='11_Credit_Risk_Engine'!K12 | D12: ='11_Credit_Risk_Engine'!Q12 | E12: =C12*D12*10000 | F12: ='3_Scenario_Engine'!Z12 | G12: =IF(F12<'6_Credit_Bridge_Assumptions'!$B$15,'6_Credit_Bridge_Assumptions'!$B$22,IF(F12<'6_Credit_Bridge_Assumptions'!$B$16,'6_Credit_Bridge_Assumptions'!$B$23,'6_Credit_Bridge_Assumptions'!$B$24)) | H12: =E12*G12 | I12: ='3_Scenario_Engine'!T12 | J12: ='3_Scenario_Engine'!U12 | K12: =-I12*(H12/10000) | L12: =J12*K12 | M12: ='3_Scenario_Engine'!F12 | N12: ='3_Scenario_Engine'!AQ12 | O12: =L12-N12 | P12: ='11_Credit_Risk_Engine'!W12 | Q12: =P12/J12 | R12: =(ABS(K12)-Q12)*100 | S12: =INDEX('10_GICS_Asset_Vol'!$C$3:$C$165,MATCH(B12,'10_GICS_Asset_Vol'!$A$3:$A$165,0)) | T12: =INDEX('10_GICS_Asset_Vol'!$D$3:$D$165,MATCH(B12,'10_GICS_Asset_Vol'!$A$3:$A$165,0)) | U12: =INDEX('10_GICS_Asset_Vol'!$E$3:$E$165,MATCH(B12,'10_GICS_Asset_Vol'!$A$3:$A$165,0)) | V12: =INDEX('8_UK_Spread_Input'!$D$5:$D$15,MATCH(S12,'8_UK_Spread_Input'!$A$5:$A$15,0)) | W12: =INDEX('8_UK_Spread_Input'!$D$20:$D$44,MATCH(U12,'8_UK_Spread_Input'!$A$20:$A$44,0)) | X12: =INDEX('8_UK_Spread_Input'!$D$49:$D$122,MATCH(T12,'8_UK_Spread_Input'!$A$49:$A$122,0)) | Y12: =INDEX('8_UK_Spread_Input'!$D$127:$D$289,MATCH(B12,'8_UK_Spread_Input'!$A$127:$A$289,0)) | Z12: =(W12/V12)*(X12/W12)*(Y12/X12) | AA12: =J12*(-I12*((M12*Z12)/10000))
A13: ='3_Scenario_Engine'!A13 | B13: ='3_Scenario_Engine'!B13 | C13: ='11_Credit_Risk_Engine'!K13 | D13: ='11_Credit_Risk_Engine'!Q13 | E13: =C13*D13*10000 | F13: ='3_Scenario_Engine'!Z13 | G13: =IF(F13<'6_Credit_Bridge_Assumptions'!$B$15,'6_Credit_Bridge_Assumptions'!$B$22,IF(F13<'6_Credit_Bridge_Assumptions'!$B$16,'6_Credit_Bridge_Assumptions'!$B$23,'6_Credit_Bridge_Assumptions'!$B$24)) | H13: =E13*G13 | I13: ='3_Scenario_Engine'!T13 | J13: ='3_Scenario_Engine'!U13 | K13: =-I13*(H13/10000) | L13: =J13*K13 | M13: ='3_Scenario_Engine'!F13 | N13: ='3_Scenario_Engine'!AQ13 | O13: =L13-N13 | P13: ='11_Credit_Risk_Engine'!W13 | Q13: =P13/J13 | R13: =(ABS(K13)-Q13)*100 | S13: =INDEX('10_GICS_Asset_Vol'!$C$3:$C$165,MATCH(B13,'10_GICS_Asset_Vol'!$A$3:$A$165,0)) | T13: =INDEX('10_GICS_Asset_Vol'!$D$3:$D$165,MATCH(B13,'10_GICS_Asset_Vol'!$A$3:$A$165,0)) | U13: =INDEX('10_GICS_Asset_Vol'!$E$3:$E$165,MATCH(B13,'10_GICS_Asset_Vol'!$A$3:$A$165,0)) | V13: =INDEX('8_UK_Spread_Input'!$D$5:$D$15,MATCH(S13,'8_UK_Spread_Input'!$A$5:$A$15,0)) | W13: =INDEX('8_UK_Spread_Input'!$D$20:$D$44,MATCH(U13,'8_UK_Spread_Input'!$A$20:$A$44,0)) | X13: =INDEX('8_UK_Spread_Input'!$D$49:$D$122,MATCH(T13,'8_UK_Spread_Input'!$A$49:$A$122,0)) | Y13: =INDEX('8_UK_Spread_Input'!$D$127:$D$289,MATCH(B13,'8_UK_Spread_Input'!$A$127:$A$289,0)) | Z13: =(W13/V13)*(X13/W13)*(Y13/X13) | AA13: =J13*(-I13*((M13*Z13)/10000))
A14: ='3_Scenario_Engine'!A14 | B14: ='3_Scenario_Engine'!B14 | C14: ='11_Credit_Risk_Engine'!K14 | D14: ='11_Credit_Risk_Engine'!Q14 | E14: =C14*D14*10000 | F14: ='3_Scenario_Engine'!Z14 | G14: =IF(F14<'6_Credit_Bridge_Assumptions'!$B$15,'6_Credit_Bridge_Assumptions'!$B$22,IF(F14<'6_Credit_Bridge_Assumptions'!$B$16,'6_Credit_Bridge_Assumptions'!$B$23,'6_Credit_Bridge_Assumptions'!$B$24)) | H14: =E14*G14 | I14: ='3_Scenario_Engine'!T14 | J14: ='3_Scenario_Engine'!U14 | K14: =-I14*(H14/10000) | L14: =J14*K14 | M14: ='3_Scenario_Engine'!F14 | N14: ='3_Scenario_Engine'!AQ14 | O14: =L14-N14 | P14: ='11_Credit_Risk_Engine'!W14 | Q14: =P14/J14 | R14: =(ABS(K14)-Q14)*100 | S14: =INDEX('10_GICS_Asset_Vol'!$C$3:$C$165,MATCH(B14,'10_GICS_Asset_Vol'!$A$3:$A$165,0)) | T14: =INDEX('10_GICS_Asset_Vol'!$D$3:$D$165,MATCH(B14,'10_GICS_Asset_Vol'!$A$3:$A$165,0)) | U14: =INDEX('10_GICS_Asset_Vol'!$E$3:$E$165,MATCH(B14,'10_GICS_Asset_Vol'!$A$3:$A$165,0)) | V14: =INDEX('8_UK_Spread_Input'!$D$5:$D$15,MATCH(S14,'8_UK_Spread_Input'!$A$5:$A$15,0)) | W14: =INDEX('8_UK_Spread_Input'!$D$20:$D$44,MATCH(U14,'8_UK_Spread_Input'!$A$20:$A$44,0)) | X14: =INDEX('8_UK_Spread_Input'!$D$49:$D$122,MATCH(T14,'8_UK_Spread_Input'!$A$49:$A$122,0)) | Y14: =INDEX('8_UK_Spread_Input'!$D$127:$D$289,MATCH(B14,'8_UK_Spread_Input'!$A$127:$A$289,0)) | Z14: =(W14/V14)*(X14/W14)*(Y14/X14) | AA14: =J14*(-I14*((M14*Z14)/10000))
... A32: ='3_Scenario_Engine'!A32 | B32: ='3_Scenario_Engine'!B32 | C32: ='11_Credit_Risk_Engine'!K32 | D32: ='11_Credit_Risk_Engine'!Q32 | E32: =C32*D32*10000 | F32: ='3_Scenario_Engine'!Z32 | G32: =IF(F32<'6_Credit_Bridge_Assumptions'!$B$15,'6_Credit_Bridge_Assumptions'!$B$22,IF(F32<'6_Credit_Bridge_Assumptions'!$B$16,'6_Credit_Bridge_Assumptions'!$B$23,'6_Credit_Bridge_Assumptions'!$B$24)) | H32: =E32*G32 | I32: ='3_Scenario_Engine'!T32 | J32: ='3_Scenario_Engine'!U32 | K32: =-I32*(H32/10000) | L32: =J32*K32 | M32: ='3_Scenario_Engine'!F32 | N32: ='3_Scenario_Engine'!AQ32 | O32: =L32-N32 | P32: ='11_Credit_Risk_Engine'!W32 | Q32: =P32/J32 | R32: =(ABS(K32)-Q32)*100 | S32: =INDEX('10_GICS_Asset_Vol'!$C$3:$C$165,MATCH(B32,'10_GICS_Asset_Vol'!$A$3:$A$165,0)) | T32: =INDEX('10_GICS_Asset_Vol'!$D$3:$D$165,MATCH(B32,'10_GICS_Asset_Vol'!$A$3:$A$165,0)) | U32: =INDEX('10_GICS_Asset_Vol'!$E$3:$E$165,MATCH(B32,'10_GICS_Asset_Vol'!$A$3:$A$165,0)) | V32: =INDEX('8_UK_Spread_Input'!$D$5:$D$15,MATCH(S32,'8_UK_Spread_Input'!$A$5:$A$15,0)) | W32: =INDEX('8_UK_Spread_Input'!$D$20:$D$44,MATCH(U32,'8_UK_Spread_Input'!$A$20:$A$44,0)) | X32: =INDEX('8_UK_Spread_Input'!$D$49:$D$122,MATCH(T32,'8_UK_Spread_Input'!$A$49:$A$122,0)) | Y32: =INDEX('8_UK_Spread_Input'!$D$127:$D$289,MATCH(B32,'8_UK_Spread_Input'!$A$127:$A$289,0)) | Z32: =(W32/V32)*(X32/W32)*(Y32/X32) | AA32: =J32*(-I32*((M32*Z32)/10000))

Sheet 13_Reconciliation
A1: STEP 13 — bottom-up and THREE top-down bases, shown side by side on the SAME basis (stress loss, $m and % of invested), plus sensitivity and rating cross-check.
A3: SIDE-BY-SIDE — same portfolio, same SWES scenario, same units (stress loss). Bottom-up is an accounting/fundamental EL view; the three top-down bases are mark-to-market views — read together, not forced to equal each other (see 5_CreditBridge_ReadMe).
A5: Metric | B5: BOTTOM-UP (Merton PD x LGD x EAD) | C5: TOP-DOWN (Credit-Derived Spread) | D5: TOP-DOWN (Exogenous SWES Spread) | E5: TOP-DOWN (Spread-Cascade-Adjusted, dummy)
A6: Stress loss ($m) | B6: =SUM('11_Credit_Risk_Engine'!$W$3:$W$32) | C6: =ABS(SUM('12_TopDown_Spread_Engine'!$L$3:$L$32)) | D6: =ABS(SUM('12_TopDown_Spread_Engine'!$N$3:$N$32)) | E6: =ABS(SUM('12_TopDown_Spread_Engine'!$AA$3:$AA$32))
A7: Stress loss (% of invested) | B7: =SUM('11_Credit_Risk_Engine'!$W$3:$W$32)/SUM('12_TopDown_Spread_Engine'!$J$3:$J$32) | C7: =ABS(SUM('12_TopDown_Spread_Engine'!$L$3:$L$32))/SUM('12_TopDown_Spread_Engine'!$J$3:$J$32) | D7: =ABS(SUM('12_TopDown_Spread_Engine'!$N$3:$N$32))/SUM('12_TopDown_Spread_Engine'!$J$3:$J$32) | E7: =ABS(SUM('12_TopDown_Spread_Engine'!$AA$3:$AA$32))/SUM('12_TopDown_Spread_Engine'!$J$3:$J$32)
A8: Ratio to bottom-up (x) | B8: =1 | C8: =ABS(SUM('12_TopDown_Spread_Engine'!$L$3:$L$32))/SUM('11_Credit_Risk_Engine'!$W$3:$W$32) | D8: =ABS(SUM('12_TopDown_Spread_Engine'!$N$3:$N$32))/SUM('11_Credit_Risk_Engine'!$W$3:$W$32) | E8: =ABS(SUM('12_TopDown_Spread_Engine'!$AA$3:$AA$32))/SUM('11_Credit_Risk_Engine'!$W$3:$W$32)
A10: Total invested at cost ($m) | B10: =SUM('12_TopDown_Spread_Engine'!$J$3:$J$32)
A12: SENSITIVITY — portfolio credit-derived MTM at a FLAT Risk Premium Multiplier (overrides the rating-band table)
A13: MTM at 1.0x (≈ pure actuarial expected loss) | B13: =-SUMPRODUCT('12_TopDown_Spread_Engine'!$I$3:$I$32,'12_TopDown_Spread_Engine'!$E$3:$E$32)/10000*1.0
A14: MTM at 1.5x | B14: =-SUMPRODUCT('12_TopDown_Spread_Engine'!$I$3:$I$32,'12_TopDown_Spread_Engine'!$E$3:$E$32)/10000*1.5
A15: MTM at 2.0x | B15: =-SUMPRODUCT('12_TopDown_Spread_Engine'!$I$3:$I$32,'12_TopDown_Spread_Engine'!$E$3:$E$32)/10000*2.0
A16: MTM at 2.5x | B16: =-SUMPRODUCT('12_TopDown_Spread_Engine'!$I$3:$I$32,'12_TopDown_Spread_Engine'!$E$3:$E$32)/10000*2.5
A17: MTM at 3.0x | B17: =-SUMPRODUCT('12_TopDown_Spread_Engine'!$I$3:$I$32,'12_TopDown_Spread_Engine'!$E$3:$E$32)/10000*3.0
A19: RATING CROSS-CHECK — invested-weighted Merton stressed PD vs S&P Global long-run average, by implied rating
A20: BB — # deals / invested-wtd Merton PD / S&P benchmark PD | B20: =COUNTIF('11_Credit_Risk_Engine'!$M$3:$M$32,"BB")&" / "&TEXT(SUMPRODUCT(('11_Credit_Risk_Engine'!$M$3:$M$32="BB")*'11_Credit_Risk_Engine'!$J$3:$J$32*'11_Credit_Risk_Engine'!$T$3:$T$32)/MAX(1,SUMPRODUCT(('11_Credit_Risk_Engine'!$M$3:$M$32="BB")*'11_Credit_Risk_Engine'!$T$3:$T$32)),"0.00%")&" / "&TEXT('6_Credit_Bridge_Assumptions'!$B$17,"0.00%")
A21: B — # deals / invested-wtd Merton PD / S&P benchmark PD | B21: =COUNTIF('11_Credit_Risk_Engine'!$M$3:$M$32,"B")&" / "&TEXT(SUMPRODUCT(('11_Credit_Risk_Engine'!$M$3:$M$32="B")*'11_Credit_Risk_Engine'!$J$3:$J$32*'11_Credit_Risk_Engine'!$T$3:$T$32)/MAX(1,SUMPRODUCT(('11_Credit_Risk_Engine'!$M$3:$M$32="B")*'11_Credit_Risk_Engine'!$T$3:$T$32)),"0.00%")&" / "&TEXT('6_Credit_Bridge_Assumptions'!$B$18,"0.00%")
A22: CCC/C — # deals / invested-wtd Merton PD / S&P benchmark PD | B22: =COUNTIF('11_Credit_Risk_Engine'!$M$3:$M$32,"CCC/C")&" / "&TEXT(SUMPRODUCT(('11_Credit_Risk_Engine'!$M$3:$M$32="CCC/C")*'11_Credit_Risk_Engine'!$J$3:$J$32*'11_Credit_Risk_Engine'!$T$3:$T$32)/MAX(1,SUMPRODUCT(('11_Credit_Risk_Engine'!$M$3:$M$32="CCC/C")*'11_Credit_Risk_Engine'!$T$3:$T$32)),"0.00%")&" / "&TEXT('6_Credit_Bridge_Assumptions'!$B$19,"0.00%")
A24: Rating cross-check cells are text concatenations (count / invested-weighted Merton PD / S&P benchmark PD) for quick eyeballing — pull the three components apart into separate cells if you want them chartable.
