Workbook

Sheet 0_ReadMe
A1: UK GICS SHOCK PROPAGATION — REAL DATA + BETA CASCADE + SPREAD CASCADE (DUMMY, FORMULA-READY)
A2: Extends UK_Shock_Propagation_RealData_Only.xlsx. All beta/spread values in 4_UK_Beta_Input and 5_UK_DefaultRisk_Input are DUMMY PLACEHOLDERS — overwrite with real data, everything downstream recalculates automatically.
A5: WHAT'S NEW
A6: 4_UK_Beta_Input — a paste zone holding an UNLEVERED beta value at EACH of the four GICS levels
A7: (Sector, Industry Group, Industry, Sub-Industry) independently. This matches how Bloomberg's EQS 'Total by
A8: Group' can aggregate a field at any of these four groupings directly on the terminal — paste in real averages
A9: at whichever level(s) you pull them, no Excel rollup step needed. ALL VALUES ARE DUMMY RIGHT NOW (a varied,
A10: clearly-synthetic placeholder pattern — 0.70/0.85/1.00/1.15/1.30, decorrelated across levels by a hash rather
A11: than a naive mod-cycle, since GICS codes are nested numeric prefixes and a naive cycle would collide across
A12: all four levels for many codes — so the formula chain is verifiable today, not trivially multiplying by 1.0).
A14: 5_UK_DefaultRisk_Input — same structure, one level down: Bloomberg issuer default-risk spread (bps, e.g. a
A15: DRSK-implied CDS-equivalent spread) at all four GICS levels, DUMMY for now. Used as a THIRD EV/EBITDA basis
... A56: 8_Output clean flat table for lookup against a loan tape's GICS sub-industry code

Sheet 1_GICS_Structure
A1: Reference sheet, GICS hierarchy for context/navigation and for the beta-cascade parent lookups on 5_Cascade_Engine.
A2: Sector Code | B2: Sector | C2: IG Code | D2: Industry Group | E2: Industry Code | F2: Industry | G2: Sub-Ind Code | H2: Sub-Industry
A3: 10 | B3: Energy | C3: 1010 | D3: Energy | E3: 101010 | F3: Energy Equipment & Services | G3: 10101010 | H3: Oil & Gas Drilling
A4: 10 | B4: Energy | C4: 1010 | D4: Energy | E4: 101010 | F4: Energy Equipment & Services | G4: 10101020 | H4: Oil & Gas Equipment & Services
A5: 10 | B5: Energy | C5: 1010 | D5: Energy | E5: 101020 | F5: Oil, Gas & Consumable Fuels | G5: 10102010 | H5: Integrated Oil & Gas
A6: 10 | B6: Energy | C6: 1010 | D6: Energy | E6: 101020 | F6: Oil, Gas & Consumable Fuels | G6: 10102020 | H6: Oil & Gas Exploration & Production
A7: 10 | B7: Energy | C7: 1010 | D7: Energy | E7: 101020 | F7: Oil, Gas & Consumable Fuels | G7: 10102030 | H7: Oil & Gas Refining & Marketing
A8: 10 | B8: Energy | C8: 1010 | D8: Energy | E8: 101020 | F8: Oil, Gas & Consumable Fuels | G8: 10102040 | H8: Oil & Gas Storage & Transportation
A9: 10 | B9: Energy | C9: 1010 | D9: Energy | E9: 101020 | F9: Oil, Gas & Consumable Fuels | G9: 10102050 | H9: Coal & Consumable Fuels
A10: 15 | B10: Materials | C10: 1510 | D10: Materials | E10: 151010 | F10: Chemicals | G10: 15101010 | H10: Commodity Chemicals
A11: 15 | B11: Materials | C11: 1510 | D11: Materials | E11: 151010 | F11: Chemicals | G11: 15101020 | H11: Diversified Chemicals
A12: 15 | B12: Materials | C12: 1510 | D12: Materials | E12: 151010 | F12: Chemicals | G12: 15101030 | H12: Fertilizers & Agricultural Chemicals
A13: 15 | B13: Materials | C13: 1510 | D13: Materials | E13: 151010 | F13: Chemicals | G13: 15101040 | H13: Industrial Gases
A14: 15 | B14: Materials | C14: 1510 | D14: Materials | E14: 151010 | F14: Chemicals | G14: 15101050 | H14: Specialty Chemicals
... A165: 60 | B165: Real Estate | C165: 6020 | D165: Real Estate Management & Development | E165: 602010 | F165: Real Estate Management & Development | G165: 60201040 | H165: Real Estate Services

Sheet 2_UK_Bloomberg_Data
A1: REAL DATA, VALUES ONLY. Bloomberg EQS<GO>, UK Refined/Investable Universe (1,298 companies), GICS Sub-Industry level, two independent exports cross-validated: 139/139 names and market caps matched exactly. Read 8 Aug 2026.
A3: Sub-Ind Code | B3: Sub-Industry | C3: N Cos | D3: Sector Code | E3: Market Cap (GBP) | F3: Revenue T12M (GBP) | G3: Current EV/EBITDA | H3: BF EV/EBITDA | I3: Multiple Used (outlier-corrected) | J3: Note
A4: 10101010 | B4: Oil & Gas Drilling | C4: 1 | D4: 10 | E4: 2270000000 | F4: 554970000 | I4: 3.74
A5: 10101020 | B5: Oil & Gas Equipment & Services | C5: 7 | D5: 10 | E5: 18050000000 | F5: 2690000000 | I5: 8.22
A6: 10102010 | B6: Integrated Oil & Gas | C6: 2 | D6: 10 | E6: 131690000000 | F6: 256880000000 | I6: 3.39
A7: 10102020 | B7: Oil & Gas Exploration & Production | C7: 48 | D7: 10 | E7: 288850000 | F7: 217770000 | I7: 3.17
A8: 10102030 | B8: Oil & Gas Refining & Marketing | C8: 1 | D8: 10 | E8: 22750000 | F8: 87000
A9: 10102040 | B9: Oil & Gas Storage & Transportation | C9: 3 | D9: 10 | E9: 6580000000 | F9: 901710000 | I9: 3.94
A10: 10102050 | B10: Coal & Consumable Fuels | C10: 8 | D10: 10 | E10: 210400000 | I10: 9.47 | J10: Revenue 0.00 in source — no-data
A11: 15101010 | B11: Commodity Chemicals | C11: 2 | D11: 15 | E11: 266070000 | F11: 246000000 | I11: 5.64
A12: 15101030 | B12: Fertilizers & Agricultural Chemicals | C12: 3 | D12: 15 | E12: 20780000 | F12: 21070000
A13: 15101040 | B13: Industrial Gases | C13: 2 | D13: 15 | E13: 44030000 | J13: Revenue 0.00 in source — no-data
A14: 15101050 | B14: Specialty Chemicals | C14: 13 | D14: 15 | E14: 876550000 | F14: 1590000000 | I14: 8.87
A15: 15102010 | B15: Construction Materials | C15: 6 | D15: 15 | E15: 655910000 | F15: 699210000 | I15: 6.57
A16: 15103010 | B16: Metal, Glass & Plastic Containers | C16: 1 | D16: 15 | E16: 5110000 | F16: 33260000
A17: 15103020 | B17: Paper & Plastic Packaging Products & Materials | C17: 1 | D17: 15 | E17: 20940000 | F17: 56210000 | I17: 3.38
A18: 15104020 | B18: Diversified Metals & Mining | C18: 47 | D18: 15 | E18: 3860000000 | F18: 1930000000 | I18: 5.94
A19: 15104025 | B19: Copper | C19: 3 | D19: 15 | E19: 98500000 | F19: 76620000 | I19: 1.5
A20: 15104030 | B20: Gold | C20: 14 | D20: 15 | E20: 1430000000 | F20: 410600000 | I20: 4.23
A21: 15104040 | B21: Precious Metals & Minerals | C21: 6 | D21: 15 | E21: 32640000 | F21: 20970000
A22: 15104050 | B22: Steel | C22: 6 | D22: 15 | E22: 509320000 | F22: 229700000 | I22: 10.16
A23: 15105010 | B23: Forest Products | C23: 1 | D23: 15 | E23: 170210000 | F23: 153280000 | I23: 9.59
A24: 15105020 | B24: Paper Products | C24: 2 | D24: 15 | E24: 2060000000 | F24: 3920000000 | I24: 6.56
A25: 20101010 | B25: Aerospace & Defense | C25: 14 | D25: 20 | E25: 15250000000 | F25: 4670000000 | I25: 13.03
A26: 20102010 | B26: Building Products | C26: 9 | D26: 20 | E26: 358510000 | F26: 250880000 | I26: 7.16
A27: 20103010 | B27: Construction & Engineering | C27: 14 | D27: 20 | E27: 850040000 | F27: 1920000000 | I27: 6.91
A28: 20104010 | B28: Electrical Components & Equipment | C28: 16 | D28: 20 | E28: 2040000000 | F28: 480480000 | I28: 9.8 | J28: Outlier-corrected (near-zero-EBITDA artifact) — using BF multiple
A29: 20104020 | B29: Heavy Electrical Equipment | C29: 4 | D29: 20 | E29: 2180000000 | F29: 229090000 | I29: 38.05
A30: 20105010 | B30: Industrial Conglomerates | C30: 2 | D30: 20 | E30: 3980000000 | F30: 1130000000 | I30: 12.91
A31: 20106015 | B31: Agricultural & Farm Machinery | C31: 1 | D31: 20 | E31: 13500000000 | F31: 18180000000 | I31: 27.38
A32: 20106020 | B32: Industrial Machinery & Supplies & Components | C32: 17 | D32: 20 | E32: 2440000000 | F32: 966980000 | I32: 10.77
A33: 20107010 | B33: Trading Companies & Distributors | C33: 18 | D33: 20 | E33: 1790000000 | F33: 1710000000 | I33: 7.57
A34: 20201010 | B34: Commercial Printing | C34: 1 | D34: 20 | E34: 62410000 | F34: 22260000
A35: 20201050 | B35: Environmental & Facilities Services | C35: 6 | D35: 20 | E35: 2410000000 | F35: 2970000000 | I35: 8.34
A36: 20201070 | B36: Diversified Support Services | C36: 10 | D36: 20 | E36: 221420000 | F36: 272250000 | I36: 5.61
A37: 20201080 | B37: Security & Alarm Services | C37: 1 | D37: 20 | E37: 9930000000 | F37: 13500000000 | I37: 8.49
A38: 20202010 | B38: Human Resource & Employment Services | C38: 10 | D38: 20 | E38: 225530000 | F38: 1210000000 | I38: 9.43
A39: 20202020 | B39: Research & Consulting Services | C39: 25 | D39: 20 | E39: 2380000000 | F39: 760740000 | I39: 7.31
A40: 20202030 | B40: Data Processing & Outsourced Services | C40: 1 | D40: 20 | E40: 318990000 | F40: 279910000 | I40: 6.59
A41: 20301010 | B41: Air Freight & Logistics | C41: 1 | D41: 20 | E41: 731310000 | F41: 137040000 | I41: 6.05
A42: 20302010 | B42: Passenger Airlines | C42: 3 | D42: 20 | E42: 9190000000 | F42: 17130000000 | I42: 3.69
A43: 20303010 | B43: Marine Transportation | C43: 3 | D43: 20 | E43: 7130000000 | F43: 1460000000 | I43: 6
A44: 20304010 | B44: Rail Transportation | C44: 1 | D44: 20 | E44: 1010000000 | F44: 4750000000 | I44: 2.53
A45: 20304040 | B45: Passenger Ground Transportation | C45: 2 | D45: 20 | E45: 613190000 | F45: 2300000000 | I45: 3.68
A46: 20305030 | B46: Marine Ports & Services | C46: 3 | D46: 20 | E46: 107990000 | F46: 180500000 | I46: 4.85
... A48: 25102010 | B48: Automobile Manufacturers | C48: 1 | D48: 25 | E48: 357390000 | F48: 1430000000 | I48: 6.3
A49: 25102020 | B49: Motorcycle Manufacturers | C49: 1 | D49: 25 | E49: 651000 | J49: Revenue 0.00 in source — no-data
A50: 25201010 | B50: Consumer Electronics | C50: 2 | D50: 25 | E50: 117000000 | F50: 196060000 | I50: 7.26
A51: 25201020 | B51: Home Furnishings | C51: 4 | D51: 25 | E51: 52820000 | F51: 321410000 | I51: 6.76
A52: 25201030 | B52: Homebuilding | C52: 12 | D52: 25 | E52: 1550000000 | F52: 2020000000 | I52: 7.39
A53: 25201040 | B53: Household Appliances | C53: 2 | D53: 25 | E53: 300730000 | F53: 426540000 | I53: 7.75
A54: 25201050 | B54: Housewares & Specialties | C54: 3 | D54: 25 | E54: 55210000 | F54: 128400000 | I54: 6.28
A55: 25202010 | B55: Leisure Products | C55: 3 | D55: 25 | E55: 2100000000 | F55: 260530000 | I55: 11.68
A56: 25203010 | B56: Apparel, Accessories & Luxury Goods | C56: 6 | D56: 25 | E56: 1020000000 | F56: 1210000000 | I56: 7.24
A57: 25203020 | B57: Footwear | C57: 2 | D57: 25 | E57: 3940000000 | F57: 1470000000 | I57: 7.46
A58: 25203030 | B58: Textiles | C58: 1 | D58: 25 | E58: 1660000000 | F58: 1600000000 | I58: 7.15
A59: 25301010 | B59: Casinos & Gaming | C59: 5 | D59: 25 | E59: 1610000000 | F59: 1740000000 | I59: 7.29
A60: 25301020 | B60: Hotels, Resorts & Cruise Lines | C60: 7 | D60: 25 | E60: 4130000000 | F60: 1270000000 | I60: 9.21
A61: 25301030 | B61: Leisure Facilities | C61: 4 | D61: 25 | E61: 223280000 | F61: 148090000 | I61: 6.4
... A72: 25504060 | B72: Homefurnishing Retail | C72: 3 | D72: 25 | E72: 740720000 | F72: 359370000 | I72: 4.6
A73: 30101010 | B73: Drug Retail | C73: 1 | D73: 30 | E73: 55230000 | J73: Revenue 0.00 in source — no-data
A74: 30101030 | B74: Food Retail | C74: 7 | D74: 30 | E74: 6860000000 | F74: 18100000000 | I74: 5.77
A75: 30201010 | B75: Brewers | C75: 2 | D75: 30 | E75: 44350000 | F75: 113830000 | I75: 6.18
A76: 30201020 | B76: Distillers & Vintners | C76: 4 | D76: 30 | E76: 9990000000 | F76: 4920000000 | I76: 19.57
A77: 30201030 | B77: Soft Drinks & Non-alcoholic Beverages | C77: 4 | D77: 30 | E77: 12510000000 | F77: 5570000000 | I77: 11.96
A78: 30202010 | B78: Agricultural Products & Services | C78: 7 | D78: 30 | E78: 316950000 | F78: 700400000 | I78: 5.8
A79: 30202030 | B79: Packaged Foods & Meats | C79: 10 | D79: 30 | E79: 2520000000 | F79: 3470000000 | I79: 7.49
A80: 30203010 | B80: Tobacco | C80: 2 | D80: 30 | E80: 58530000000 | F80: 26210000000 | I80: 8.57
A81: 30301010 | B81: Household Products | C81: 2 | D81: 30 | E81: 16990000000 | F81: 7280000000 | I81: 8.12
A82: 30302010 | B82: Personal Care Products | C82: 11 | D82: 30 | E82: 10240000000 | F82: 4710000000 | I82: 10.41
A83: 35101010 | B83: Health Care Equipment | C83: 11 | D83: 35 | E83: 1400000000 | F83: 795190000 | I83: 13.59
A84: 35101020 | B84: Health Care Supplies | C84: 8 | D84: 35 | E84: 787430000 | F84: 112670000 | I84: 12.07
A85: 35102010 | B85: Health Care Distributors | C85: 1 | D85: 35 | E85: 2380000 | F85: 12420
A86: 35102015 | B86: Health Care Services | C86: 9 | D86: 35 | E86: 57660000 | F86: 26960000 | I86: 4.62
A87: 35102020 | B87: Health Care Facilities | C87: 3 | D87: 35 | E87: 610570000 | F87: 756150000 | I87: 7.33
A88: 35103010 | B88: Health Care Technology | C88: 8 | D88: 35 | E88: 82100000 | F88: 173230000 | I88: 8.13
A89: 35201010 | B89: Biotechnology | C89: 35 | D89: 35 | E89: 407840000 | F89: 72750000 | I89: 25.22
A90: 35202010 | B90: Pharmaceuticals | C90: 15 | D90: 35 | E90: 21460000000 | F90: 7290000000 | I90: 9.18
A91: 35203010 | B91: Life Sciences Tools & Services | C91: 9 | D91: 35 | E91: 162120000 | F91: 36120000 | I91: 16.2 | J91: Outlier-corrected (near-zero-EBITDA artifact) — using BF multiple
A92: 40101010 | B92: Diversified Banks | C92: 9 | D92: 40 | E92: 56790000000 | F92: 28150000000
A93: 40101015 | B93: Regional Banks | C93: 2 | D93: 40 | E93: 1450000000 | F93: 410600000
A94: 40201020 | B94: Diversified Financial Services | C94: 1 | D94: 40 | E94: 8750000000 | F94: 18230000000
A95: 40201040 | B95: Specialized Finance | C95: 6 | D95: 40 | E95: 41070000 | F95: 41090000 | I95: 6.17
A96: 40201050 | B96: Commercial & Residential Mortgage Finance | C96: 6 | D96: 40 | E96: 1010000000 | F96: 3880000000 | I96: 5.95
A97: 40201060 | B97: Transaction & Payment Processing Services | C97: 9 | D97: 40 | E97: 2980000000 | F97: 1010000000 | I97: 15.31
A98: 40202010 | B98: Consumer Finance | C98: 5 | D98: 40 | E98: 276710000 | F98: 246000000 | I98: 5.59
A99: 40203010 | B99: Asset Management & Custody Banks | C99: 75 | D99: 40 | E99: 1280000000 | F99: 3060000000 | I99: 11.61
A100: 40203020 | B100: Investment Banking & Brokerage | C100: 11 | D100: 40 | E100: 1060000000 | F100: 421470000 | I100: 10.49
A101: 40203040 | B101: Financial Exchanges & Data | C101: 4 | D101: 40 | E101: 12530000000 | F101: 2630000000 | I101: 11.47
A102: 40301010 | B102: Insurance Brokers | C102: 2 | D102: 40 | E102: 54010000000 | F102: 13840000000 | I102: 13.45
A103: 40301020 | B103: Life & Health Insurance | C103: 3 | D103: 40 | E103: 9250000000 | F103: 13500000000
A104: 40301030 | B104: Multi-line Insurance | C104: 3 | D104: 40 | E104: 7540000000 | F104: 9240000000 | I104: 9.53
A105: 40301040 | B105: Property & Casualty Insurance | C105: 5 | D105: 40 | E105: 4340000000 | F105: 2690000000
A106: 45102010 | B106: IT Consulting & Other Services | C106: 15 | D106: 45 | E106: 745840000 | F106: 845570000 | I106: 9.31
A107: 45102030 | B107: Internet Services & Infrastructure | C107: 7 | D107: 45 | E107: 144280000 | F107: 85470000 | I107: 7.59
A108: 45103010 | B108: Application Software | C108: 49 | D108: 45 | E108: 354900000 | F108: 100060000 | I108: 12.1
A109: 45103020 | B109: Systems Software | C109: 5 | D109: 45 | E109: 27190000 | F109: 14860000 | I109: 19.39
A110: 45201020 | B110: Communications Equipment | C110: 4 | D110: 45 | E110: 203930000 | F110: 46790000 | I110: 20.73
A111: 45202030 | B111: Technology Hardware, Storage & Peripherals | C111: 3 | D111: 45 | E111: 554470000 | F111: 143870000 | I111: 25.1
A112: 45203010 | B112: Electronic Equipment & Instruments | C112: 15 | D112: 45 | E112: 1350000000 | F112: 1190000000 | I112: 10.82
...

Sheet 3_UK_L1_Input
A1: STEP 3 — PASTE ZONE. PRA SWES Level-1 (GICS Sector) UK shocks, Year 1, from the BoE annex.
A3: Sector Code | B3: GICS Sector | C3: UK Revenue Shock % | D3: UK EV/EBITDA Shock %
A4: 10 | B4: Energy | C4: 0.08 | D4: 0
A5: 15 | B5: Materials | C5: -0.05 | D5: -0.28
A6: 20 | B6: Industrials | C6: -0.1 | D6: -0.32
A7: 25 | B7: Consumer Discretionary | C7: -0.1 | D7: -0.25
A8: 30 | B8: Consumer Staples | C8: -0.05 | D8: -0.25
A9: 35 | B9: Health Care | C9: -0.05 | D9: -0.25
A10: 40 | B10: Financials | C10: -0.1 | D10: -0.32
A11: 45 | B11: Information Technology | C11: -0.1 | D11: -0.36
A12: 50 | B12: Communication Services | C12: -0.05 | D12: -0.26
A13: 55 | B13: Utilities | C13: 0.02 | D13: -0.01
A14: 60 | B14: Real Estate | C14: -0.1 | D14: -0.36

Sheet 4_UK_Beta_Input
A1: PASTE ZONE — DUMMY VALUES. Unlevered beta at each of the four GICS levels independently. Replace the 'Unlevered Beta (DUMMY)' column with real data (e.g. from Bloomberg EQS 'Total by Group', or your own Hamada delevering of raw beta using each company's effective tax rate and D/E) — every downstream formula recalculates automatically. Dummy values follow a varied, clearly-synthetic pattern (0.70/0.85/1.00/1.15/1.30 cycling by code) so the cascade is verifiable now, not trivially = 1.0.
A3: SECTOR (11)
A4: Code | B4: Name | D4: Unlevered Beta (DUMMY)
A5: 10 | B5: Energy | D5: 0.7
A6: 15 | B6: Materials | D6: 1
A7: 20 | B7: Industrials | D7: 1.3
A8: 25 | B8: Consumer Discretionary | D8: 0.85
A9: 30 | B9: Consumer Staples | D9: 1.15
A10: 35 | B10: Health Care | D10: 0.7
A11: 40 | B11: Financials | D11: 1
A12: 45 | B12: Information Technology | D12: 1.3
A13: 50 | B13: Communication Services | D13: 0.85
A14: 55 | B14: Utilities | D14: 1.15
A15: 60 | B15: Real Estate | D15: 1.3
A18: INDUSTRY GROUP (25)
A19: Code | B19: Name | D19: Unlevered Beta (DUMMY)
A20: 1010 | B20: Energy | D20: 1
A21: 1510 | B21: Materials | D21: 1.15
A22: 2010 | B22: Capital Goods | D22: 1.3
A23: 2020 | B23: Commercial & Professional Services | D23: 1.15
A24: 2030 | B24: Transportation | D24: 1
A25: 2510 | B25: Automobiles & Components | D25: 0.7
A26: 2520 | B26: Consumer Durables & Apparel | D26: 1.3
A27: 2530 | B27: Consumer Services | D27: 1.15
A28: 2550 | B28: Consumer Discretionary Distribution & Retail | D28: 0.85
A29: 3010 | B29: Consumer Staples Distribution & Retail | D29: 0.85
A30: 3020 | B30: Food, Beverage & Tobacco | D30: 0.7
A31: 3030 | B31: Household & Personal Products | D31: 1.3
... A44: 6020 | B44: Real Estate Management & Development | D44: 0.85
A47: INDUSTRY (74)
A48: Code | B48: Name | D48: Unlevered Beta (DUMMY)
A49: 101010 | B49: Energy Equipment & Services | D49: 1.3
A50: 101020 | B50: Oil, Gas & Consumable Fuels | D50: 1.15
A51: 151010 | B51: Chemicals | D51: 1
A52: 151020 | B52: Construction Materials | D52: 0.85
A53: 151030 | B53: Containers & Packaging | D53: 0.7
A54: 151040 | B54: Metals & Mining | D54: 1.3
A55: 151050 | B55: Paper & Forest Products | D55: 1
A56: 201010 | B56: Aerospace & Defense | D56: 0.7
A57: 201020 | B57: Building Products | D57: 1.3
A58: 201030 | B58: Construction & Engineering | D58: 1.15
A59: 201040 | B59: Electrical Equipment | D59: 1
A60: 201050 | B60: Industrial Conglomerates | D60: 0.85
... A122: 602010 | B122: Real Estate Management & Development | D122: 1.3
A125: SUB-INDUSTRY (163)
A126: Code | B126: Name | D126: Unlevered Beta (DUMMY)
A127: 10101010 | B127: Oil & Gas Drilling | D127: 1.3
A128: 10101020 | B128: Oil & Gas Equipment & Services | D128: 1.15
A129: 10102010 | B129: Integrated Oil & Gas | D129: 0.85
A130: 10102020 | B130: Oil & Gas Exploration & Production | D130: 0.7
A131: 10102030 | B131: Oil & Gas Refining & Marketing | D131: 1.3
A132: 10102040 | B132: Oil & Gas Storage & Transportation | D132: 1
A133: 10102050 | B133: Coal & Consumable Fuels | D133: 0.85
A134: 15101010 | B134: Commodity Chemicals | D134: 1.3
A135: 15101020 | B135: Diversified Chemicals | D135: 1.15
A136: 15101030 | B136: Fertilizers & Agricultural Chemicals | D136: 1
A137: 15101040 | B137: Industrial Gases | D137: 0.85
A138: 15101050 | B138: Specialty Chemicals | D138: 1.3
... A289: 60201040 | B289: Real Estate Services | D289: 1.15

Sheet 5_UK_DefaultRisk_Input
A1: PASTE ZONE — DUMMY VALUES. Bloomberg issuer default risk spread (bps, e.g. DRSK-implied CDS-equivalent spread) at each of the four GICS levels independently, same structure as 4_UK_Beta_Input. Replace with real data when available — every downstream formula recalculates automatically. Dummy values follow a varied, clearly-synthetic pattern (120/220/320/420/520bps cycling by code, decorrelated from the beta dummy pattern) so the cascade is verifiable now, not trivially flat.
A3: SECTOR (11)
A4: Code | B4: Name | D4: Default Risk Spread bps (DUMMY)
A5: 10 | B5: Energy | D5: 220
A6: 15 | B6: Materials | D6: 420
A7: 20 | B7: Industrials | D7: 120
A8: 25 | B8: Consumer Discretionary | D8: 320
A9: 30 | B9: Consumer Staples | D9: 520
A10: 35 | B10: Health Care | D10: 220
A11: 40 | B11: Financials | D11: 420
A12: 45 | B12: Information Technology | D12: 120
A13: 50 | B13: Communication Services | D13: 320
A14: 55 | B14: Utilities | D14: 520
A15: 60 | B15: Real Estate | D15: 120
A18: INDUSTRY GROUP (25)
A19: Code | B19: Name | D19: Default Risk Spread bps (DUMMY)
A20: 1010 | B20: Energy | D20: 420
A21: 1510 | B21: Materials | D21: 520
A22: 2010 | B22: Capital Goods | D22: 120
A23: 2020 | B23: Commercial & Professional Services | D23: 520
A24: 2030 | B24: Transportation | D24: 420
A25: 2510 | B25: Automobiles & Components | D25: 220
A26: 2520 | B26: Consumer Durables & Apparel | D26: 120
A27: 2530 | B27: Consumer Services | D27: 520
A28: 2550 | B28: Consumer Discretionary Distribution & Retail | D28: 320
A29: 3010 | B29: Consumer Staples Distribution & Retail | D29: 320
A30: 3020 | B30: Food, Beverage & Tobacco | D30: 220
A31: 3030 | B31: Household & Personal Products | D31: 120
... A44: 6020 | B44: Real Estate Management & Development | D44: 320
A47: INDUSTRY (74)
A48: Code | B48: Name | D48: Default Risk Spread bps (DUMMY)
A49: 101010 | B49: Energy Equipment & Services | D49: 120
A50: 101020 | B50: Oil, Gas & Consumable Fuels | D50: 520
A51: 151010 | B51: Chemicals | D51: 420
A52: 151020 | B52: Construction Materials | D52: 320
A53: 151030 | B53: Containers & Packaging | D53: 220
A54: 151040 | B54: Metals & Mining | D54: 120
A55: 151050 | B55: Paper & Forest Products | D55: 420
A56: 201010 | B56: Aerospace & Defense | D56: 220
A57: 201020 | B57: Building Products | D57: 120
A58: 201030 | B58: Construction & Engineering | D58: 520
A59: 201040 | B59: Electrical Equipment | D59: 420
A60: 201050 | B60: Industrial Conglomerates | D60: 320
... A122: 602010 | B122: Real Estate Management & Development | D122: 120
A125: SUB-INDUSTRY (163)
A126: Code | B126: Name | D126: Default Risk Spread bps (DUMMY)
A127: 10101010 | B127: Oil & Gas Drilling | D127: 120
A128: 10101020 | B128: Oil & Gas Equipment & Services | D128: 520
A129: 10102010 | B129: Integrated Oil & Gas | D129: 320
A130: 10102020 | B130: Oil & Gas Exploration & Production | D130: 220
A131: 10102030 | B131: Oil & Gas Refining & Marketing | D131: 120
A132: 10102040 | B132: Oil & Gas Storage & Transportation | D132: 420
A133: 10102050 | B133: Coal & Consumable Fuels | D133: 320
A134: 15101010 | B134: Commodity Chemicals | D134: 120
A135: 15101020 | B135: Diversified Chemicals | D135: 520
A136: 15101030 | B136: Fertilizers & Agricultural Chemicals | D136: 420
A137: 15101040 | B137: Industrial Gases | D137: 320
A138: 15101050 | B138: Specialty Chemicals | D138: 120
... A289: 60201040 | B289: Real Estate Services | D289: 520

Sheet 6_Cascade_Engine
A1: STEP 6 — 163 sub-industries. Columns G-L: real-data EV/EBITDA (both weighting bases). Columns M-P: beta cascade (RelBeta_L2/L3/L4, from 4_UK_Beta_Input — DUMMY until you paste real data), used as the EV/EBITDA fallback and shown as an alternative Revenue differentiator. Columns V-AA: issuer default-risk-spread cascade (from 5_UK_DefaultRisk_Input — DUMMY), a THIRD EV/EBITDA basis — used for EV/EBITDA only, not Revenue, for the same reason levered beta isn't: a credit spread embeds financing/leverage risk, not pure operating cyclicality, so it isn't the right differentiator for a pre-financing metric like revenue.
A2: Sub-Ind Code | B2: Sub-Industry | C2: Sector Code | D2: Industry Code | E2: IG Code | F2: Real UK Revenue | G2: Real UK Multiple Used | H2: Sector Avg Mult (Rev-Wtd) | I2: Sector Avg Mult (Eq-Wtd) | J2: RelMultiple (Rev-Wtd) | K2: RelMultiple (Eq-Wtd) | L2: Sector Beta | M2: IG Beta | N2: Industry Beta | O2: Sub-Ind Beta | P2: RelBeta L2 x L3 x L4 | Q2: EV/EBITDA Shock (Rev-Wtd basis) | R2: EV/EBITDA Shock (Eq-Wtd basis) | S2: EV/EBITDA Source | T2: Revenue Shock (flat pass-through) | U2: Revenue Shock (beta cascade) | V2: Sector Spread bps | W2: IG Spread bps | X2: Industry Spread bps | Y2: Sub-Ind Spread bps | Z2: RelSpread L2 x L3 x L4 | AA2: EV/EBITDA Shock (Spread basis, dummy)
A3: 10101010 | B3: Oil & Gas Drilling | C3: 10 | D3: 101010 | E3: 1010 | F3: 554970000 | G3: 3.74 | H3: =IFERROR(SUMPRODUCT(($C$3:$C$165=C3)*ISNUMBER($G$3:$G$165)*ISNUMBER($F$3:$F$165)*IF(ISNUMBER($F$3:$F$165),$F$3:$F$165,0)*IF(ISNUMBER($G$3:$G$165),$G$3:$G$165,0))/SUMPRODUCT(($C$3:$C$165=C3)*ISNUMBER($G$3:$G$165)*ISNUMBER($F$3:$F$165)*IF(ISNUMBER($F$3:$F$165),$F$3:$F$165,0)),"") | I3: =IFERROR(SUMPRODUCT(($C$3:$C$165=C3)*ISNUMBER($G$3:$G$165)*IF(ISNUMBER($G$3:$G$165),$G$3:$G$165,0))/SUMPRODUCT(($C$3:$C$165=C3)*ISNUMBER($G$3:$G$165)),"") | J3: =IF(OR(G3="",H3=""),"",G3/H3) | K3: =IF(OR(G3="",I3=""),"",G3/I3) | L3: =INDEX('4_UK_Beta_Input'!$D$5:$D$15,MATCH($C3,'4_UK_Beta_Input'!$A$5:$A$15,0)) | M3: =INDEX('4_UK_Beta_Input'!$D$20:$D$44,MATCH($E3,'4_UK_Beta_Input'!$A$20:$A$44,0)) | N3: =INDEX('4_UK_Beta_Input'!$D$49:$D$122,MATCH($D3,'4_UK_Beta_Input'!$A$49:$A$122,0)) | O3: =INDEX('4_UK_Beta_Input'!$D$127:$D$289,MATCH($A3,'4_UK_Beta_Input'!$A$127:$A$289,0)) | P3: =(M3/L3)*(N3/M3)*(O3/N3) | Q3: =IF(J3="",INDEX('3_UK_L1_Input'!$D$4:$D$14,MATCH($C3,'3_UK_L1_Input'!$A$4:$A$14,0))*P3,INDEX('3_UK_L1_Input'!$D$4:$D$14,MATCH($C3,'3_UK_L1_Input'!$A$4:$A$14,0))*J3) | R3: =IF(K3="",INDEX('3_UK_L1_Input'!$D$4:$D$14,MATCH($C3,'3_UK_L1_Input'!$A$4:$A$14,0))*P3,INDEX('3_UK_L1_Input'!$D$4:$D$14,MATCH($C3,'3_UK_L1_Input'!$A$4:$A$14,0))*K3) | S3: =IF(G3="","BETA CASCADE FALLBACK (dummy — replace with real beta)","REAL (Bloomberg UK)") | T3: =INDEX('3_UK_L1_Input'!$C$4:$C$14,MATCH($C3,'3_UK_L1_Input'!$A$4:$A$14,0)) | U3: =INDEX('3_UK_L1_Input'!$C$4:$C$14,MATCH($C3,'3_UK_L1_Input'!$A$4:$A$14,0))*P3 | V3: =INDEX('5_UK_DefaultRisk_Input'!$D$5:$D$15,MATCH($C3,'5_UK_DefaultRisk_Input'!$A$5:$A$15,0)) | W3: =INDEX('5_UK_DefaultRisk_Input'!$D$20:$D$44,MATCH($E3,'5_UK_DefaultRisk_Input'!$A$20:$A$44,0)) | X3: =INDEX('5_UK_DefaultRisk_Input'!$D$49:$D$122,MATCH($D3,'5_UK_DefaultRisk_Input'!$A$49:$A$122,0)) | Y3: =INDEX('5_UK_DefaultRisk_Input'!$D$127:$D$289,MATCH($A3,'5_UK_DefaultRisk_Input'!$A$127:$A$289,0)) | Z3: =(W3/V3)*(X3/W3)*(Y3/X3) | AA3: =INDEX('3_UK_L1_Input'!$D$4:$D$14,MATCH($C3,'3_UK_L1_Input'!$A$4:$A$14,0))*Z3
A4: 10101020 | B4: Oil & Gas Equipment & Services | C4: 10 | D4: 101010 | E4: 1010 | F4: 2690000000 | G4: 8.22 | H4: =IFERROR(SUMPRODUCT(($C$3:$C$165=C4)*ISNUMBER($G$3:$G$165)*ISNUMBER($F$3:$F$165)*IF(ISNUMBER($F$3:$F$165),$F$3:$F$165,0)*IF(ISNUMBER($G$3:$G$165),$G$3:$G$165,0))/SUMPRODUCT(($C$3:$C$165=C4)*ISNUMBER($G$3:$G$165)*ISNUMBER($F$3:$F$165)*IF(ISNUMBER($F$3:$F$165),$F$3:$F$165,0)),"") | I4: =IFERROR(SUMPRODUCT(($C$3:$C$165=C4)*ISNUMBER($G$3:$G$165)*IF(ISNUMBER($G$3:$G$165),$G$3:$G$165,0))/SUMPRODUCT(($C$3:$C$165=C4)*ISNUMBER($G$3:$G$165)),"") | J4: =IF(OR(G4="",H4=""),"",G4/H4) | K4: =IF(OR(G4="",I4=""),"",G4/I4) | L4: =INDEX('4_UK_Beta_Input'!$D$5:$D$15,MATCH($C4,'4_UK_Beta_Input'!$A$5:$A$15,0)) | M4: =INDEX('4_UK_Beta_Input'!$D$20:$D$44,MATCH($E4,'4_UK_Beta_Input'!$A$20:$A$44,0)) | N4: =INDEX('4_UK_Beta_Input'!$D$49:$D$122,MATCH($D4,'4_UK_Beta_Input'!$A$49:$A$122,0)) | O4: =INDEX('4_UK_Beta_Input'!$D$127:$D$289,MATCH($A4,'4_UK_Beta_Input'!$A$127:$A$289,0)) | P4: =(M4/L4)*(N4/M4)*(O4/N4) | Q4: =IF(J4="",INDEX('3_UK_L1_Input'!$D$4:$D$14,MATCH($C4,'3_UK_L1_Input'!$A$4:$A$14,0))*P4,INDEX('3_UK_L1_Input'!$D$4:$D$14,MATCH($C4,'3_UK_L1_Input'!$A$4:$A$14,0))*J4) | R4: =IF(K4="",INDEX('3_UK_L1_Input'!$D$4:$D$14,MATCH($C4,'3_UK_L1_Input'!$A$4:$A$14,0))*P4,INDEX('3_UK_L1_Input'!$D$4:$D$14,MATCH($C4,'3_UK_L1_Input'!$A$4:$A$14,0))*K4) | S4: =IF(G4="","BETA CASCADE FALLBACK (dummy — replace with real beta)","REAL (Bloomberg UK)") | T4: =INDEX('3_UK_L1_Input'!$C$4:$C$14,MATCH($C4,'3_UK_L1_Input'!$A$4:$A$14,0)) | U4: =INDEX('3_UK_L1_Input'!$C$4:$C$14,MATCH($C4,'3_UK_L1_Input'!$A$4:$A$14,0))*P4 | V4: =INDEX('5_UK_DefaultRisk_Input'!$D$5:$D$15,MATCH($C4,'5_UK_DefaultRisk_Input'!$A$5:$A$15,0)) | W4: =INDEX('5_UK_DefaultRisk_Input'!$D$20:$D$44,MATCH($E4,'5_UK_DefaultRisk_Input'!$A$20:$A$44,0)) | X4: =INDEX('5_UK_DefaultRisk_Input'!$D$49:$D$122,MATCH($D4,'5_UK_DefaultRisk_Input'!$A$49:$A$122,0)) | Y4: =INDEX('5_UK_DefaultRisk_Input'!$D$127:$D$289,MATCH($A4,'5_UK_DefaultRisk_Input'!$A$127:$A$289,0)) | Z4: =(W4/V4)*(X4/W4)*(Y4/X4) | AA4: =INDEX('3_UK_L1_Input'!$D$4:$D$14,MATCH($C4,'3_UK_L1_Input'!$A$4:$A$14,0))*Z4
A5: 10102010 | B5: Integrated Oil & Gas | C5: 10 | D5: 101020 | E5: 1010 | F5: 256880000000 | G5: 3.39 | H5: =IFERROR(SUMPRODUCT(($C$3:$C$165=C5)*ISNUMBER($G$3:$G$165)*ISNUMBER($F$3:$F$165)*IF(ISNUMBER($F$3:$F$165),$F$3:$F$165,0)*IF(ISNUMBER($G$3:$G$165),$G$3:$G$165,0))/SUMPRODUCT(($C$3:$C$165=C5)*ISNUMBER($G$3:$G$165)*ISNUMBER($F$3:$F$165)*IF(ISNUMBER($F$3:$F$165),$F$3:$F$165,0)),"") | I5: =IFERROR(SUMPRODUCT(($C$3:$C$165=C5)*ISNUMBER($G$3:$G$165)*IF(ISNUMBER($G$3:$G$165),$G$3:$G$165,0))/SUMPRODUCT(($C$3:$C$165=C5)*ISNUMBER($G$3:$G$165)),"") | J5: =IF(OR(G5="",H5=""),"",G5/H5) | K5: =IF(OR(G5="",I5=""),"",G5/I5) | L5: =INDEX('4_UK_Beta_Input'!$D$5:$D$15,MATCH($C5,'4_UK_Beta_Input'!$A$5:$A$15,0)) | M5: =INDEX('4_UK_Beta_Input'!$D$20:$D$44,MATCH($E5,'4_UK_Beta_Input'!$A$20:$A$44,0)) | N5: =INDEX('4_UK_Beta_Input'!$D$49:$D$122,MATCH($D5,'4_UK_Beta_Input'!$A$49:$A$122,0)) | O5: =INDEX('4_UK_Beta_Input'!$D$127:$D$289,MATCH($A5,'4_UK_Beta_Input'!$A$127:$A$289,0)) | P5: =(M5/L5)*(N5/M5)*(O5/N5) | Q5: =IF(J5="",INDEX('3_UK_L1_Input'!$D$4:$D$14,MATCH($C5,'3_UK_L1_Input'!$A$4:$A$14,0))*P5,INDEX('3_UK_L1_Input'!$D$4:$D$14,MATCH($C5,'3_UK_L1_Input'!$A$4:$A$14,0))*J5) | R5: =IF(K5="",INDEX('3_UK_L1_Input'!$D$4:$D$14,MATCH($C5,'3_UK_L1_Input'!$A$4:$A$14,0))*P5,INDEX('3_UK_L1_Input'!$D$4:$D$14,MATCH($C5,'3_UK_L1_Input'!$A$4:$A$14,0))*K5) | S5: =IF(G5="","BETA CASCADE FALLBACK (dummy — replace with real beta)","REAL (Bloomberg UK)") | T5: =INDEX('3_UK_L1_Input'!$C$4:$C$14,MATCH($C5,'3_UK_L1_Input'!$A$4:$A$14,0)) | U5: =INDEX('3_UK_L1_Input'!$C$4:$C$14,MATCH($C5,'3_UK_L1_Input'!$A$4:$A$14,0))*P5 | V5: =INDEX('5_UK_DefaultRisk_Input'!$D$5:$D$15,MATCH($C5,'5_UK_DefaultRisk_Input'!$A$5:$A$15,0)) | W5: =INDEX('5_UK_DefaultRisk_Input'!$D$20:$D$44,MATCH($E5,'5_UK_DefaultRisk_Input'!$A$20:$A$44,0)) | X5: =INDEX('5_UK_DefaultRisk_Input'!$D$49:$D$122,MATCH($D5,'5_UK_DefaultRisk_Input'!$A$49:$A$122,0)) | Y5: =INDEX('5_UK_DefaultRisk_Input'!$D$127:$D$289,MATCH($A5,'5_UK_DefaultRisk_Input'!$A$127:$A$289,0)) | Z5: =(W5/V5)*(X5/W5)*(Y5/X5) | AA5: =INDEX('3_UK_L1_Input'!$D$4:$D$14,MATCH($C5,'3_UK_L1_Input'!$A$4:$A$14,0))*Z5
A6: 10102020 | B6: Oil & Gas Exploration & Production | C6: 10 | D6: 101020 | E6: 1010 | F6: 217770000 | G6: 3.17 | H6: =IFERROR(SUMPRODUCT(($C$3:$C$165=C6)*ISNUMBER($G$3:$G$165)*ISNUMBER($F$3:$F$165)*IF(ISNUMBER($F$3:$F$165),$F$3:$F$165,0)*IF(ISNUMBER($G$3:$G$165),$G$3:$G$165,0))/SUMPRODUCT(($C$3:$C$165=C6)*ISNUMBER($G$3:$G$165)*ISNUMBER($F$3:$F$165)*IF(ISNUMBER($F$3:$F$165),$F$3:$F$165,0)),"") | I6: =IFERROR(SUMPRODUCT(($C$3:$C$165=C6)*ISNUMBER($G$3:$G$165)*IF(ISNUMBER($G$3:$G$165),$G$3:$G$165,0))/SUMPRODUCT(($C$3:$C$165=C6)*ISNUMBER($G$3:$G$165)),"") | J6: =IF(OR(G6="",H6=""),"",G6/H6) | K6: =IF(OR(G6="",I6=""),"",G6/I6) | L6: =INDEX('4_UK_Beta_Input'!$D$5:$D$15,MATCH($C6,'4_UK_Beta_Input'!$A$5:$A$15,0)) | M6: =INDEX('4_UK_Beta_Input'!$D$20:$D$44,MATCH($E6,'4_UK_Beta_Input'!$A$20:$A$44,0)) | N6: =INDEX('4_UK_Beta_Input'!$D$49:$D$122,MATCH($D6,'4_UK_Beta_Input'!$A$49:$A$122,0)) | O6: =INDEX('4_UK_Beta_Input'!$D$127:$D$289,MATCH($A6,'4_UK_Beta_Input'!$A$127:$A$289,0)) | P6: =(M6/L6)*(N6/M6)*(O6/N6) | Q6: =IF(J6="",INDEX('3_UK_L1_Input'!$D$4:$D$14,MATCH($C6,'3_UK_L1_Input'!$A$4:$A$14,0))*P6,INDEX('3_UK_L1_Input'!$D$4:$D$14,MATCH($C6,'3_UK_L1_Input'!$A$4:$A$14,0))*J6) | R6: =IF(K6="",INDEX('3_UK_L1_Input'!$D$4:$D$14,MATCH($C6,'3_UK_L1_Input'!$A$4:$A$14,0))*P6,INDEX('3_UK_L1_Input'!$D$4:$D$14,MATCH($C6,'3_UK_L1_Input'!$A$4:$A$14,0))*K6) | S6: =IF(G6="","BETA CASCADE FALLBACK (dummy — replace with real beta)","REAL (Bloomberg UK)") | T6: =INDEX('3_UK_L1_Input'!$C$4:$C$14,MATCH($C6,'3_UK_L1_Input'!$A$4:$A$14,0)) | U6: =INDEX('3_UK_L1_Input'!$C$4:$C$14,MATCH($C6,'3_UK_L1_Input'!$A$4:$A$14,0))*P6 | V6: =INDEX('5_UK_DefaultRisk_Input'!$D$5:$D$15,MATCH($C6,'5_UK_DefaultRisk_Input'!$A$5:$A$15,0)) | W6: =INDEX('5_UK_DefaultRisk_Input'!$D$20:$D$44,MATCH($E6,'5_UK_DefaultRisk_Input'!$A$20:$A$44,0)) | X6: =INDEX('5_UK_DefaultRisk_Input'!$D$49:$D$122,MATCH($D6,'5_UK_DefaultRisk_Input'!$A$49:$A$122,0)) | Y6: =INDEX('5_UK_DefaultRisk_Input'!$D$127:$D$289,MATCH($A6,'5_UK_DefaultRisk_Input'!$A$127:$A$289,0)) | Z6: =(W6/V6)*(X6/W6)*(Y6/X6) | AA6: =INDEX('3_UK_L1_Input'!$D$4:$D$14,MATCH($C6,'3_UK_L1_Input'!$A$4:$A$14,0))*Z6
A7: 10102030 | B7: Oil & Gas Refining & Marketing | C7: 10 | D7: 101020 | E7: 1010 | F7: 87000 | H7: =IFERROR(SUMPRODUCT(($C$3:$C$165=C7)*ISNUMBER($G$3:$G$165)*ISNUMBER($F$3:$F$165)*IF(ISNUMBER($F$3:$F$165),$F$3:$F$165,0)*IF(ISNUMBER($G$3:$G$165),$G$3:$G$165,0))/SUMPRODUCT(($C$3:$C$165=C7)*ISNUMBER($G$3:$G$165)*ISNUMBER($F$3:$F$165)*IF(ISNUMBER($F$3:$F$165),$F$3:$F$165,0)),"") | I7: =IFERROR(SUMPRODUCT(($C$3:$C$165=C7)*ISNUMBER($G$3:$G$165)*IF(ISNUMBER($G$3:$G$165),$G$3:$G$165,0))/SUMPRODUCT(($C$3:$C$165=C7)*ISNUMBER($G$3:$G$165)),"") | J7: =IF(OR(G7="",H7=""),"",G7/H7) | K7: =IF(OR(G7="",I7=""),"",G7/I7) | L7: =INDEX('4_UK_Beta_Input'!$D$5:$D$15,MATCH($C7,'4_UK_Beta_Input'!$A$5:$A$15,0)) | M7: =INDEX('4_UK_Beta_Input'!$D$20:$D$44,MATCH($E7,'4_UK_Beta_Input'!$A$20:$A$44,0)) | N7: =INDEX('4_UK_Beta_Input'!$D$49:$D$122,MATCH($D7,'4_UK_Beta_Input'!$A$49:$A$122,0)) | O7: =INDEX('4_UK_Beta_Input'!$D$127:$D$289,MATCH($A7,'4_UK_Beta_Input'!$A$127:$A$289,0)) | P7: =(M7/L7)*(N7/M7)*(O7/N7) | Q7: =IF(J7="",INDEX('3_UK_L1_Input'!$D$4:$D$14,MATCH($C7,'3_UK_L1_Input'!$A$4:$A$14,0))*P7,INDEX('3_UK_L1_Input'!$D$4:$D$14,MATCH($C7,'3_UK_L1_Input'!$A$4:$A$14,0))*J7) | R7: =IF(K7="",INDEX('3_UK_L1_Input'!$D$4:$D$14,MATCH($C7,'3_UK_L1_Input'!$A$4:$A$14,0))*P7,INDEX('3_UK_L1_Input'!$D$4:$D$14,MATCH($C7,'3_UK_L1_Input'!$A$4:$A$14,0))*K7) | S7: =IF(G7="","BETA CASCADE FALLBACK (dummy — replace with real beta)","REAL (Bloomberg UK)") | T7: =INDEX('3_UK_L1_Input'!$C$4:$C$14,MATCH($C7,'3_UK_L1_Input'!$A$4:$A$14,0)) | U7: =INDEX('3_UK_L1_Input'!$C$4:$C$14,MATCH($C7,'3_UK_L1_Input'!$A$4:$A$14,0))*P7 | V7: =INDEX('5_UK_DefaultRisk_Input'!$D$5:$D$15,MATCH($C7,'5_UK_DefaultRisk_Input'!$A$5:$A$15,0)) | W7: =INDEX('5_UK_DefaultRisk_Input'!$D$20:$D$44,MATCH($E7,'5_UK_DefaultRisk_Input'!$A$20:$A$44,0)) | X7: =INDEX('5_UK_DefaultRisk_Input'!$D$49:$D$122,MATCH($D7,'5_UK_DefaultRisk_Input'!$A$49:$A$122,0)) | Y7: =INDEX('5_UK_DefaultRisk_Input'!$D$127:$D$289,MATCH($A7,'5_UK_DefaultRisk_Input'!$A$127:$A$289,0)) | Z7: =(W7/V7)*(X7/W7)*(Y7/X7) | AA7: =INDEX('3_UK_L1_Input'!$D$4:$D$14,MATCH($C7,'3_UK_L1_Input'!$A$4:$A$14,0))*Z7
A8: 10102040 | B8: Oil & Gas Storage & Transportation | C8: 10 | D8: 101020 | E8: 1010 | F8: 901710000 | G8: 3.94 | H8: =IFERROR(SUMPRODUCT(($C$3:$C$165=C8)*ISNUMBER($G$3:$G$165)*ISNUMBER($F$3:$F$165)*IF(ISNUMBER($F$3:$F$165),$F$3:$F$165,0)*IF(ISNUMBER($G$3:$G$165),$G$3:$G$165,0))/SUMPRODUCT(($C$3:$C$165=C8)*ISNUMBER($G$3:$G$165)*ISNUMBER($F$3:$F$165)*IF(ISNUMBER($F$3:$F$165),$F$3:$F$165,0)),"") | I8: =IFERROR(SUMPRODUCT(($C$3:$C$165=C8)*ISNUMBER($G$3:$G$165)*IF(ISNUMBER($G$3:$G$165),$G$3:$G$165,0))/SUMPRODUCT(($C$3:$C$165=C8)*ISNUMBER($G$3:$G$165)),"") | J8: =IF(OR(G8="",H8=""),"",G8/H8) | K8: =IF(OR(G8="",I8=""),"",G8/I8) | L8: =INDEX('4_UK_Beta_Input'!$D$5:$D$15,MATCH($C8,'4_UK_Beta_Input'!$A$5:$A$15,0)) | M8: =INDEX('4_UK_Beta_Input'!$D$20:$D$44,MATCH($E8,'4_UK_Beta_Input'!$A$20:$A$44,0)) | N8: =INDEX('4_UK_Beta_Input'!$D$49:$D$122,MATCH($D8,'4_UK_Beta_Input'!$A$49:$A$122,0)) | O8: =INDEX('4_UK_Beta_Input'!$D$127:$D$289,MATCH($A8,'4_UK_Beta_Input'!$A$127:$A$289,0)) | P8: =(M8/L8)*(N8/M8)*(O8/N8) | Q8: =IF(J8="",INDEX('3_UK_L1_Input'!$D$4:$D$14,MATCH($C8,'3_UK_L1_Input'!$A$4:$A$14,0))*P8,INDEX('3_UK_L1_Input'!$D$4:$D$14,MATCH($C8,'3_UK_L1_Input'!$A$4:$A$14,0))*J8) | R8: =IF(K8="",INDEX('3_UK_L1_Input'!$D$4:$D$14,MATCH($C8,'3_UK_L1_Input'!$A$4:$A$14,0))*P8,INDEX('3_UK_L1_Input'!$D$4:$D$14,MATCH($C8,'3_UK_L1_Input'!$A$4:$A$14,0))*K8) | S8: =IF(G8="","BETA CASCADE FALLBACK (dummy — replace with real beta)","REAL (Bloomberg UK)") | T8: =INDEX('3_UK_L1_Input'!$C$4:$C$14,MATCH($C8,'3_UK_L1_Input'!$A$4:$A$14,0)) | U8: =INDEX('3_UK_L1_Input'!$C$4:$C$14,MATCH($C8,'3_UK_L1_Input'!$A$4:$A$14,0))*P8 | V8: =INDEX('5_UK_DefaultRisk_Input'!$D$5:$D$15,MATCH($C8,'5_UK_DefaultRisk_Input'!$A$5:$A$15,0)) | W8: =INDEX('5_UK_DefaultRisk_Input'!$D$20:$D$44,MATCH($E8,'5_UK_DefaultRisk_Input'!$A$20:$A$44,0)) | X8: =INDEX('5_UK_DefaultRisk_Input'!$D$49:$D$122,MATCH($D8,'5_UK_DefaultRisk_Input'!$A$49:$A$122,0)) | Y8: =INDEX('5_UK_DefaultRisk_Input'!$D$127:$D$289,MATCH($A8,'5_UK_DefaultRisk_Input'!$A$127:$A$289,0)) | Z8: =(W8/V8)*(X8/W8)*(Y8/X8) | AA8: =INDEX('3_UK_L1_Input'!$D$4:$D$14,MATCH($C8,'3_UK_L1_Input'!$A$4:$A$14,0))*Z8
A9: 10102050 | B9: Coal & Consumable Fuels | C9: 10 | D9: 101020 | E9: 1010 | G9: 9.47 | H9: =IFERROR(SUMPRODUCT(($C$3:$C$165=C9)*ISNUMBER($G$3:$G$165)*ISNUMBER($F$3:$F$165)*IF(ISNUMBER($F$3:$F$165),$F$3:$F$165,0)*IF(ISNUMBER($G$3:$G$165),$G$3:$G$165,0))/SUMPRODUCT(($C$3:$C$165=C9)*ISNUMBER($G$3:$G$165)*ISNUMBER($F$3:$F$165)*IF(ISNUMBER($F$3:$F$165),$F$3:$F$165,0)),"") | I9: =IFERROR(SUMPRODUCT(($C$3:$C$165=C9)*ISNUMBER($G$3:$G$165)*IF(ISNUMBER($G$3:$G$165),$G$3:$G$165,0))/SUMPRODUCT(($C$3:$C$165=C9)*ISNUMBER($G$3:$G$165)),"") | J9: =IF(OR(G9="",H9=""),"",G9/H9) | K9: =IF(OR(G9="",I9=""),"",G9/I9) | L9: =INDEX('4_UK_Beta_Input'!$D$5:$D$15,MATCH($C9,'4_UK_Beta_Input'!$A$5:$A$15,0)) | M9: =INDEX('4_UK_Beta_Input'!$D$20:$D$44,MATCH($E9,'4_UK_Beta_Input'!$A$20:$A$44,0)) | N9: =INDEX('4_UK_Beta_Input'!$D$49:$D$122,MATCH($D9,'4_UK_Beta_Input'!$A$49:$A$122,0)) | O9: =INDEX('4_UK_Beta_Input'!$D$127:$D$289,MATCH($A9,'4_UK_Beta_Input'!$A$127:$A$289,0)) | P9: =(M9/L9)*(N9/M9)*(O9/N9) | Q9: =IF(J9="",INDEX('3_UK_L1_Input'!$D$4:$D$14,MATCH($C9,'3_UK_L1_Input'!$A$4:$A$14,0))*P9,INDEX('3_UK_L1_Input'!$D$4:$D$14,MATCH($C9,'3_UK_L1_Input'!$A$4:$A$14,0))*J9) | R9: =IF(K9="",INDEX('3_UK_L1_Input'!$D$4:$D$14,MATCH($C9,'3_UK_L1_Input'!$A$4:$A$14,0))*P9,INDEX('3_UK_L1_Input'!$D$4:$D$14,MATCH($C9,'3_UK_L1_Input'!$A$4:$A$14,0))*K9) | S9: =IF(G9="","BETA CASCADE FALLBACK (dummy — replace with real beta)","REAL (Bloomberg UK)") | T9: =INDEX('3_UK_L1_Input'!$C$4:$C$14,MATCH($C9,'3_UK_L1_Input'!$A$4:$A$14,0)) | U9: =INDEX('3_UK_L1_Input'!$C$4:$C$14,MATCH($C9,'3_UK_L1_Input'!$A$4:$A$14,0))*P9 | V9: =INDEX('5_UK_DefaultRisk_Input'!$D$5:$D$15,MATCH($C9,'5_UK_DefaultRisk_Input'!$A$5:$A$15,0)) | W9: =INDEX('5_UK_DefaultRisk_Input'!$D$20:$D$44,MATCH($E9,'5_UK_DefaultRisk_Input'!$A$20:$A$44,0)) | X9: =INDEX('5_UK_DefaultRisk_Input'!$D$49:$D$122,MATCH($D9,'5_UK_DefaultRisk_Input'!$A$49:$A$122,0)) | Y9: =INDEX('5_UK_DefaultRisk_Input'!$D$127:$D$289,MATCH($A9,'5_UK_DefaultRisk_Input'!$A$127:$A$289,0)) | Z9: =(W9/V9)*(X9/W9)*(Y9/X9) | AA9: =INDEX('3_UK_L1_Input'!$D$4:$D$14,MATCH($C9,'3_UK_L1_Input'!$A$4:$A$14,0))*Z9
A10: 15101010 | B10: Commodity Chemicals | C10: 15 | D10: 151010 | E10: 1510 | F10: 246000000 | G10: 5.64 | H10: =IFERROR(SUMPRODUCT(($C$3:$C$165=C10)*ISNUMBER($G$3:$G$165)*ISNUMBER($F$3:$F$165)*IF(ISNUMBER($F$3:$F$165),$F$3:$F$165,0)*IF(ISNUMBER($G$3:$G$165),$G$3:$G$165,0))/SUMPRODUCT(($C$3:$C$165=C10)*ISNUMBER($G$3:$G$165)*ISNUMBER($F$3:$F$165)*IF(ISNUMBER($F$3:$F$165),$F$3:$F$165,0)),"") | I10: =IFERROR(SUMPRODUCT(($C$3:$C$165=C10)*ISNUMBER($G$3:$G$165)*IF(ISNUMBER($G$3:$G$165),$G$3:$G$165,0))/SUMPRODUCT(($C$3:$C$165=C10)*ISNUMBER($G$3:$G$165)),"") | J10: =IF(OR(G10="",H10=""),"",G10/H10) | K10: =IF(OR(G10="",I10=""),"",G10/I10) | L10: =INDEX('4_UK_Beta_Input'!$D$5:$D$15,MATCH($C10,'4_UK_Beta_Input'!$A$5:$A$15,0)) | M10: =INDEX('4_UK_Beta_Input'!$D$20:$D$44,MATCH($E10,'4_UK_Beta_Input'!$A$20:$A$44,0)) | N10: =INDEX('4_UK_Beta_Input'!$D$49:$D$122,MATCH($D10,'4_UK_Beta_Input'!$A$49:$A$122,0)) | O10: =INDEX('4_UK_Beta_Input'!$D$127:$D$289,MATCH($A10,'4_UK_Beta_Input'!$A$127:$A$289,0)) | P10: =(M10/L10)*(N10/M10)*(O10/N10) | Q10: =IF(J10="",INDEX('3_UK_L1_Input'!$D$4:$D$14,MATCH($C10,'3_UK_L1_Input'!$A$4:$A$14,0))*P10,INDEX('3_UK_L1_Input'!$D$4:$D$14,MATCH($C10,'3_UK_L1_Input'!$A$4:$A$14,0))*J10) | R10: =IF(K10="",INDEX('3_UK_L1_Input'!$D$4:$D$14,MATCH($C10,'3_UK_L1_Input'!$A$4:$A$14,0))*P10,INDEX('3_UK_L1_Input'!$D$4:$D$14,MATCH($C10,'3_UK_L1_Input'!$A$4:$A$14,0))*K10) | S10: =IF(G10="","BETA CASCADE FALLBACK (dummy — replace with real beta)","REAL (Bloomberg UK)") | T10: =INDEX('3_UK_L1_Input'!$C$4:$C$14,MATCH($C10,'3_UK_L1_Input'!$A$4:$A$14,0)) | U10: =INDEX('3_UK_L1_Input'!$C$4:$C$14,MATCH($C10,'3_UK_L1_Input'!$A$4:$A$14,0))*P10 | V10: =INDEX('5_UK_DefaultRisk_Input'!$D$5:$D$15,MATCH($C10,'5_UK_DefaultRisk_Input'!$A$5:$A$15,0)) | W10: =INDEX('5_UK_DefaultRisk_Input'!$D$20:$D$44,MATCH($E10,'5_UK_DefaultRisk_Input'!$A$20:$A$44,0)) | X10: =INDEX('5_UK_DefaultRisk_Input'!$D$49:$D$122,MATCH($D10,'5_UK_DefaultRisk_Input'!$A$49:$A$122,0)) | Y10: =INDEX('5_UK_DefaultRisk_Input'!$D$127:$D$289,MATCH($A10,'5_UK_DefaultRisk_Input'!$A$127:$A$289,0)) | Z10: =(W10/V10)*(X10/W10)*(Y10/X10) | AA10: =INDEX('3_UK_L1_Input'!$D$4:$D$14,MATCH($C10,'3_UK_L1_Input'!$A$4:$A$14,0))*Z10
A11: 15101020 | B11: Diversified Chemicals | C11: 15 | D11: 151010 | E11: 1510 | H11: =IFERROR(SUMPRODUCT(($C$3:$C$165=C11)*ISNUMBER($G$3:$G$165)*ISNUMBER($F$3:$F$165)*IF(ISNUMBER($F$3:$F$165),$F$3:$F$165,0)*IF(ISNUMBER($G$3:$G$165),$G$3:$G$165,0))/SUMPRODUCT(($C$3:$C$165=C11)*ISNUMBER($G$3:$G$165)*ISNUMBER($F$3:$F$165)*IF(ISNUMBER($F$3:$F$165),$F$3:$F$165,0)),"") | I11: =IFERROR(SUMPRODUCT(($C$3:$C$165=C11)*ISNUMBER($G$3:$G$165)*IF(ISNUMBER($G$3:$G$165),$G$3:$G$165,0))/SUMPRODUCT(($C$3:$C$165=C11)*ISNUMBER($G$3:$G$165)),"") | J11: =IF(OR(G11="",H11=""),"",G11/H11) | K11: =IF(OR(G11="",I11=""),"",G11/I11) | L11: =INDEX('4_UK_Beta_Input'!$D$5:$D$15,MATCH($C11,'4_UK_Beta_Input'!$A$5:$A$15,0)) | M11: =INDEX('4_UK_Beta_Input'!$D$20:$D$44,MATCH($E11,'4_UK_Beta_Input'!$A$20:$A$44,0)) | N11: =INDEX('4_UK_Beta_Input'!$D$49:$D$122,MATCH($D11,'4_UK_Beta_Input'!$A$49:$A$122,0)) | O11: =INDEX('4_UK_Beta_Input'!$D$127:$D$289,MATCH($A11,'4_UK_Beta_Input'!$A$127:$A$289,0)) | P11: =(M11/L11)*(N11/M11)*(O11/N11) | Q11: =IF(J11="",INDEX('3_UK_L1_Input'!$D$4:$D$14,MATCH($C11,'3_UK_L1_Input'!$A$4:$A$14,0))*P11,INDEX('3_UK_L1_Input'!$D$4:$D$14,MATCH($C11,'3_UK_L1_Input'!$A$4:$A$14,0))*J11) | R11: =IF(K11="",INDEX('3_UK_L1_Input'!$D$4:$D$14,MATCH($C11,'3_UK_L1_Input'!$A$4:$A$14,0))*P11,INDEX('3_UK_L1_Input'!$D$4:$D$14,MATCH($C11,'3_UK_L1_Input'!$A$4:$A$14,0))*K11) | S11: =IF(G11="","BETA CASCADE FALLBACK (dummy — replace with real beta)","REAL (Bloomberg UK)") | T11: =INDEX('3_UK_L1_Input'!$C$4:$C$14,MATCH($C11,'3_UK_L1_Input'!$A$4:$A$14,0)) | U11: =INDEX('3_UK_L1_Input'!$C$4:$C$14,MATCH($C11,'3_UK_L1_Input'!$A$4:$A$14,0))*P11 | V11: =INDEX('5_UK_DefaultRisk_Input'!$D$5:$D$15,MATCH($C11,'5_UK_DefaultRisk_Input'!$A$5:$A$15,0)) | W11: =INDEX('5_UK_DefaultRisk_Input'!$D$20:$D$44,MATCH($E11,'5_UK_DefaultRisk_Input'!$A$20:$A$44,0)) | X11: =INDEX('5_UK_DefaultRisk_Input'!$D$49:$D$122,MATCH($D11,'5_UK_DefaultRisk_Input'!$A$49:$A$122,0)) | Y11: =INDEX('5_UK_DefaultRisk_Input'!$D$127:$D$289,MATCH($A11,'5_UK_DefaultRisk_Input'!$A$127:$A$289,0)) | Z11: =(W11/V11)*(X11/W11)*(Y11/X11) | AA11: =INDEX('3_UK_L1_Input'!$D$4:$D$14,MATCH($C11,'3_UK_L1_Input'!$A$4:$A$14,0))*Z11
A12: 15101030 | B12: Fertilizers & Agricultural Chemicals | C12: 15 | D12: 151010 | E12: 1510 | F12: 21070000 | H12: =IFERROR(SUMPRODUCT(($C$3:$C$165=C12)*ISNUMBER($G$3:$G$165)*ISNUMBER($F$3:$F$165)*IF(ISNUMBER($F$3:$F$165),$F$3:$F$165,0)*IF(ISNUMBER($G$3:$G$165),$G$3:$G$165,0))/SUMPRODUCT(($C$3:$C$165=C12)*ISNUMBER($G$3:$G$165)*ISNUMBER($F$3:$F$165)*IF(ISNUMBER($F$3:$F$165),$F$3:$F$165,0)),"") | I12: =IFERROR(SUMPRODUCT(($C$3:$C$165=C12)*ISNUMBER($G$3:$G$165)*IF(ISNUMBER($G$3:$G$165),$G$3:$G$165,0))/SUMPRODUCT(($C$3:$C$165=C12)*ISNUMBER($G$3:$G$165)),"") | J12: =IF(OR(G12="",H12=""),"",G12/H12) | K12: =IF(OR(G12="",I12=""),"",G12/I12) | L12: =INDEX('4_UK_Beta_Input'!$D$5:$D$15,MATCH($C12,'4_UK_Beta_Input'!$A$5:$A$15,0)) | M12: =INDEX('4_UK_Beta_Input'!$D$20:$D$44,MATCH($E12,'4_UK_Beta_Input'!$A$20:$A$44,0)) | N12: =INDEX('4_UK_Beta_Input'!$D$49:$D$122,MATCH($D12,'4_UK_Beta_Input'!$A$49:$A$122,0)) | O12: =INDEX('4_UK_Beta_Input'!$D$127:$D$289,MATCH($A12,'4_UK_Beta_Input'!$A$127:$A$289,0)) | P12: =(M12/L12)*(N12/M12)*(O12/N12) | Q12: =IF(J12="",INDEX('3_UK_L1_Input'!$D$4:$D$14,MATCH($C12,'3_UK_L1_Input'!$A$4:$A$14,0))*P12,INDEX('3_UK_L1_Input'!$D$4:$D$14,MATCH($C12,'3_UK_L1_Input'!$A$4:$A$14,0))*J12) | R12: =IF(K12="",INDEX('3_UK_L1_Input'!$D$4:$D$14,MATCH($C12,'3_UK_L1_Input'!$A$4:$A$14,0))*P12,INDEX('3_UK_L1_Input'!$D$4:$D$14,MATCH($C12,'3_UK_L1_Input'!$A$4:$A$14,0))*K12) | S12: =IF(G12="","BETA CASCADE FALLBACK (dummy — replace with real beta)","REAL (Bloomberg UK)") | T12: =INDEX('3_UK_L1_Input'!$C$4:$C$14,MATCH($C12,'3_UK_L1_Input'!$A$4:$A$14,0)) | U12: =INDEX('3_UK_L1_Input'!$C$4:$C$14,MATCH($C12,'3_UK_L1_Input'!$A$4:$A$14,0))*P12 | V12: =INDEX('5_UK_DefaultRisk_Input'!$D$5:$D$15,MATCH($C12,'5_UK_DefaultRisk_Input'!$A$5:$A$15,0)) | W12: =INDEX('5_UK_DefaultRisk_Input'!$D$20:$D$44,MATCH($E12,'5_UK_DefaultRisk_Input'!$A$20:$A$44,0)) | X12: =INDEX('5_UK_DefaultRisk_Input'!$D$49:$D$122,MATCH($D12,'5_UK_DefaultRisk_Input'!$A$49:$A$122,0)) | Y12: =INDEX('5_UK_DefaultRisk_Input'!$D$127:$D$289,MATCH($A12,'5_UK_DefaultRisk_Input'!$A$127:$A$289,0)) | Z12: =(W12/V12)*(X12/W12)*(Y12/X12) | AA12: =INDEX('3_UK_L1_Input'!$D$4:$D$14,MATCH($C12,'3_UK_L1_Input'!$A$4:$A$14,0))*Z12
A13: 15101040 | B13: Industrial Gases | C13: 15 | D13: 151010 | E13: 1510 | H13: =IFERROR(SUMPRODUCT(($C$3:$C$165=C13)*ISNUMBER($G$3:$G$165)*ISNUMBER($F$3:$F$165)*IF(ISNUMBER($F$3:$F$165),$F$3:$F$165,0)*IF(ISNUMBER($G$3:$G$165),$G$3:$G$165,0))/SUMPRODUCT(($C$3:$C$165=C13)*ISNUMBER($G$3:$G$165)*ISNUMBER($F$3:$F$165)*IF(ISNUMBER($F$3:$F$165),$F$3:$F$165,0)),"") | I13: =IFERROR(SUMPRODUCT(($C$3:$C$165=C13)*ISNUMBER($G$3:$G$165)*IF(ISNUMBER($G$3:$G$165),$G$3:$G$165,0))/SUMPRODUCT(($C$3:$C$165=C13)*ISNUMBER($G$3:$G$165)),"") | J13: =IF(OR(G13="",H13=""),"",G13/H13) | K13: =IF(OR(G13="",I13=""),"",G13/I13) | L13: =INDEX('4_UK_Beta_Input'!$D$5:$D$15,MATCH($C13,'4_UK_Beta_Input'!$A$5:$A$15,0)) | M13: =INDEX('4_UK_Beta_Input'!$D$20:$D$44,MATCH($E13,'4_UK_Beta_Input'!$A$20:$A$44,0)) | N13: =INDEX('4_UK_Beta_Input'!$D$49:$D$122,MATCH($D13,'4_UK_Beta_Input'!$A$49:$A$122,0)) | O13: =INDEX('4_UK_Beta_Input'!$D$127:$D$289,MATCH($A13,'4_UK_Beta_Input'!$A$127:$A$289,0)) | P13: =(M13/L13)*(N13/M13)*(O13/N13) | Q13: =IF(J13="",INDEX('3_UK_L1_Input'!$D$4:$D$14,MATCH($C13,'3_UK_L1_Input'!$A$4:$A$14,0))*P13,INDEX('3_UK_L1_Input'!$D$4:$D$14,MATCH($C13,'3_UK_L1_Input'!$A$4:$A$14,0))*J13) | R13: =IF(K13="",INDEX('3_UK_L1_Input'!$D$4:$D$14,MATCH($C13,'3_UK_L1_Input'!$A$4:$A$14,0))*P13,INDEX('3_UK_L1_Input'!$D$4:$D$14,MATCH($C13,'3_UK_L1_Input'!$A$4:$A$14,0))*K13) | S13: =IF(G13="","BETA CASCADE FALLBACK (dummy — replace with real beta)","REAL (Bloomberg UK)") | T13: =INDEX('3_UK_L1_Input'!$C$4:$C$14,MATCH($C13,'3_UK_L1_Input'!$A$4:$A$14,0)) | U13: =INDEX('3_UK_L1_Input'!$C$4:$C$14,MATCH($C13,'3_UK_L1_Input'!$A$4:$A$14,0))*P13 | V13: =INDEX('5_UK_DefaultRisk_Input'!$D$5:$D$15,MATCH($C13,'5_UK_DefaultRisk_Input'!$A$5:$A$15,0)) | W13: =INDEX('5_UK_DefaultRisk_Input'!$D$20:$D$44,MATCH($E13,'5_UK_DefaultRisk_Input'!$A$20:$A$44,0)) | X13: =INDEX('5_UK_DefaultRisk_Input'!$D$49:$D$122,MATCH($D13,'5_UK_DefaultRisk_Input'!$A$49:$A$122,0)) | Y13: =INDEX('5_UK_DefaultRisk_Input'!$D$127:$D$289,MATCH($A13,'5_UK_DefaultRisk_Input'!$A$127:$A$289,0)) | Z13: =(W13/V13)*(X13/W13)*(Y13/X13) | AA13: =INDEX('3_UK_L1_Input'!$D$4:$D$14,MATCH($C13,'3_UK_L1_Input'!$A$4:$A$14,0))*Z13
A14: 15101050 | B14: Specialty Chemicals | C14: 15 | D14: 151010 | E14: 1510 | F14: 1590000000 | G14: 8.87 | H14: =IFERROR(SUMPRODUCT(($C$3:$C$165=C14)*ISNUMBER($G$3:$G$165)*ISNUMBER($F$3:$F$165)*IF(ISNUMBER($F$3:$F$165),$F$3:$F$165,0)*IF(ISNUMBER($G$3:$G$165),$G$3:$G$165,0))/SUMPRODUCT(($C$3:$C$165=C14)*ISNUMBER($G$3:$G$165)*ISNUMBER($F$3:$F$165)*IF(ISNUMBER($F$3:$F$165),$F$3:$F$165,0)),"") | I14: =IFERROR(SUMPRODUCT(($C$3:$C$165=C14)*ISNUMBER($G$3:$G$165)*IF(ISNUMBER($G$3:$G$165),$G$3:$G$165,0))/SUMPRODUCT(($C$3:$C$165=C14)*ISNUMBER($G$3:$G$165)),"") | J14: =IF(OR(G14="",H14=""),"",G14/H14) | K14: =IF(OR(G14="",I14=""),"",G14/I14) | L14: =INDEX('4_UK_Beta_Input'!$D$5:$D$15,MATCH($C14,'4_UK_Beta_Input'!$A$5:$A$15,0)) | M14: =INDEX('4_UK_Beta_Input'!$D$20:$D$44,MATCH($E14,'4_UK_Beta_Input'!$A$20:$A$44,0)) | N14: =INDEX('4_UK_Beta_Input'!$D$49:$D$122,MATCH($D14,'4_UK_Beta_Input'!$A$49:$A$122,0)) | O14: =INDEX('4_UK_Beta_Input'!$D$127:$D$289,MATCH($A14,'4_UK_Beta_Input'!$A$127:$A$289,0)) | P14: =(M14/L14)*(N14/M14)*(O14/N14) | Q14: =IF(J14="",INDEX('3_UK_L1_Input'!$D$4:$D$14,MATCH($C14,'3_UK_L1_Input'!$A$4:$A$14,0))*P14,INDEX('3_UK_L1_Input'!$D$4:$D$14,MATCH($C14,'3_UK_L1_Input'!$A$4:$A$14,0))*J14) | R14: =IF(K14="",INDEX('3_UK_L1_Input'!$D$4:$D$14,MATCH($C14,'3_UK_L1_Input'!$A$4:$A$14,0))*P14,INDEX('3_UK_L1_Input'!$D$4:$D$14,MATCH($C14,'3_UK_L1_Input'!$A$4:$A$14,0))*K14) | S14: =IF(G14="","BETA CASCADE FALLBACK (dummy — replace with real beta)","REAL (Bloomberg UK)") | T14: =INDEX('3_UK_L1_Input'!$C$4:$C$14,MATCH($C14,'3_UK_L1_Input'!$A$4:$A$14,0)) | U14: =INDEX('3_UK_L1_Input'!$C$4:$C$14,MATCH($C14,'3_UK_L1_Input'!$A$4:$A$14,0))*P14 | V14: =INDEX('5_UK_DefaultRisk_Input'!$D$5:$D$15,MATCH($C14,'5_UK_DefaultRisk_Input'!$A$5:$A$15,0)) | W14: =INDEX('5_UK_DefaultRisk_Input'!$D$20:$D$44,MATCH($E14,'5_UK_DefaultRisk_Input'!$A$20:$A$44,0)) | X14: =INDEX('5_UK_DefaultRisk_Input'!$D$49:$D$122,MATCH($D14,'5_UK_DefaultRisk_Input'!$A$49:$A$122,0)) | Y14: =INDEX('5_UK_DefaultRisk_Input'!$D$127:$D$289,MATCH($A14,'5_UK_DefaultRisk_Input'!$A$127:$A$289,0)) | Z14: =(W14/V14)*(X14/W14)*(Y14/X14) | AA14: =INDEX('3_UK_L1_Input'!$D$4:$D$14,MATCH($C14,'3_UK_L1_Input'!$A$4:$A$14,0))*Z14
A15: 15102010 | B15: Construction Materials | C15: 15 | D15: 151020 | E15: 1510 | F15: 699210000 | G15: 6.57 | H15: =IFERROR(SUMPRODUCT(($C$3:$C$165=C15)*ISNUMBER($G$3:$G$165)*ISNUMBER($F$3:$F$165)*IF(ISNUMBER($F$3:$F$165),$F$3:$F$165,0)*IF(ISNUMBER($G$3:$G$165),$G$3:$G$165,0))/SUMPRODUCT(($C$3:$C$165=C15)*ISNUMBER($G$3:$G$165)*ISNUMBER($F$3:$F$165)*IF(ISNUMBER($F$3:$F$165),$F$3:$F$165,0)),"") | I15: =IFERROR(SUMPRODUCT(($C$3:$C$165=C15)*ISNUMBER($G$3:$G$165)*IF(ISNUMBER($G$3:$G$165),$G$3:$G$165,0))/SUMPRODUCT(($C$3:$C$165=C15)*ISNUMBER($G$3:$G$165)),"") | J15: =IF(OR(G15="",H15=""),"",G15/H15) | K15: =IF(OR(G15="",I15=""),"",G15/I15) | L15: =INDEX('4_UK_Beta_Input'!$D$5:$D$15,MATCH($C15,'4_UK_Beta_Input'!$A$5:$A$15,0)) | M15: =INDEX('4_UK_Beta_Input'!$D$20:$D$44,MATCH($E15,'4_UK_Beta_Input'!$A$20:$A$44,0)) | N15: =INDEX('4_UK_Beta_Input'!$D$49:$D$122,MATCH($D15,'4_UK_Beta_Input'!$A$49:$A$122,0)) | O15: =INDEX('4_UK_Beta_Input'!$D$127:$D$289,MATCH($A15,'4_UK_Beta_Input'!$A$127:$A$289,0)) | P15: =(M15/L15)*(N15/M15)*(O15/N15) | Q15: =IF(J15="",INDEX('3_UK_L1_Input'!$D$4:$D$14,MATCH($C15,'3_UK_L1_Input'!$A$4:$A$14,0))*P15,INDEX('3_UK_L1_Input'!$D$4:$D$14,MATCH($C15,'3_UK_L1_Input'!$A$4:$A$14,0))*J15) | R15: =IF(K15="",INDEX('3_UK_L1_Input'!$D$4:$D$14,MATCH($C15,'3_UK_L1_Input'!$A$4:$A$14,0))*P15,INDEX('3_UK_L1_Input'!$D$4:$D$14,MATCH($C15,'3_UK_L1_Input'!$A$4:$A$14,0))*K15) | S15: =IF(G15="","BETA CASCADE FALLBACK (dummy — replace with real beta)","REAL (Bloomberg UK)") | T15: =INDEX('3_UK_L1_Input'!$C$4:$C$14,MATCH($C15,'3_UK_L1_Input'!$A$4:$A$14,0)) | U15: =INDEX('3_UK_L1_Input'!$C$4:$C$14,MATCH($C15,'3_UK_L1_Input'!$A$4:$A$14,0))*P15 | V15: =INDEX('5_UK_DefaultRisk_Input'!$D$5:$D$15,MATCH($C15,'5_UK_DefaultRisk_Input'!$A$5:$A$15,0)) | W15: =INDEX('5_UK_DefaultRisk_Input'!$D$20:$D$44,MATCH($E15,'5_UK_DefaultRisk_Input'!$A$20:$A$44,0)) | X15: =INDEX('5_UK_DefaultRisk_Input'!$D$49:$D$122,MATCH($D15,'5_UK_DefaultRisk_Input'!$A$49:$A$122,0)) | Y15: =INDEX('5_UK_DefaultRisk_Input'!$D$127:$D$289,MATCH($A15,'5_UK_DefaultRisk_Input'!$A$127:$A$289,0)) | Z15: =(W15/V15)*(X15/W15)*(Y15/X15) | AA15: =INDEX('3_UK_L1_Input'!$D$4:$D$14,MATCH($C15,'3_UK_L1_Input'!$A$4:$A$14,0))*Z15
A16: 15103010 | B16: Metal, Glass & Plastic Containers | C16: 15 | D16: 151030 | E16: 1510 | F16: 33260000 | H16: =IFERROR(SUMPRODUCT(($C$3:$C$165=C16)*ISNUMBER($G$3:$G$165)*ISNUMBER($F$3:$F$165)*IF(ISNUMBER($F$3:$F$165),$F$3:$F$165,0)*IF(ISNUMBER($G$3:$G$165),$G$3:$G$165,0))/SUMPRODUCT(($C$3:$C$165=C16)*ISNUMBER($G$3:$G$165)*ISNUMBER($F$3:$F$165)*IF(ISNUMBER($F$3:$F$165),$F$3:$F$165,0)),"") | I16: =IFERROR(SUMPRODUCT(($C$3:$C$165=C16)*ISNUMBER($G$3:$G$165)*IF(ISNUMBER($G$3:$G$165),$G$3:$G$165,0))/SUMPRODUCT(($C$3:$C$165=C16)*ISNUMBER($G$3:$G$165)),"") | J16: =IF(OR(G16="",H16=""),"",G16/H16) | K16: =IF(OR(G16="",I16=""),"",G16/I16) | L16: =INDEX('4_UK_Beta_Input'!$D$5:$D$15,MATCH($C16,'4_UK_Beta_Input'!$A$5:$A$15,0)) | M16: =INDEX('4_UK_Beta_Input'!$D$20:$D$44,MATCH($E16,'4_UK_Beta_Input'!$A$20:$A$44,0)) | N16: =INDEX('4_UK_Beta_Input'!$D$49:$D$122,MATCH($D16,'4_UK_Beta_Input'!$A$49:$A$122,0)) | O16: =INDEX('4_UK_Beta_Input'!$D$127:$D$289,MATCH($A16,'4_UK_Beta_Input'!$A$127:$A$289,0)) | P16: =(M16/L16)*(N16/M16)*(O16/N16) | Q16: =IF(J16="",INDEX('3_UK_L1_Input'!$D$4:$D$14,MATCH($C16,'3_UK_L1_Input'!$A$4:$A$14,0))*P16,INDEX('3_UK_L1_Input'!$D$4:$D$14,MATCH($C16,'3_UK_L1_Input'!$A$4:$A$14,0))*J16) | R16: =IF(K16="",INDEX('3_UK_L1_Input'!$D$4:$D$14,MATCH($C16,'3_UK_L1_Input'!$A$4:$A$14,0))*P16,INDEX('3_UK_L1_Input'!$D$4:$D$14,MATCH($C16,'3_UK_L1_Input'!$A$4:$A$14,0))*K16) | S16: =IF(G16="","BETA CASCADE FALLBACK (dummy — replace with real beta)","REAL (Bloomberg UK)") | T16: =INDEX('3_UK_L1_Input'!$C$4:$C$14,MATCH($C16,'3_UK_L1_Input'!$A$4:$A$14,0)) | U16: =INDEX('3_UK_L1_Input'!$C$4:$C$14,MATCH($C16,'3_UK_L1_Input'!$A$4:$A$14,0))*P16 | V16: =INDEX('5_UK_DefaultRisk_Input'!$D$5:$D$15,MATCH($C16,'5_UK_DefaultRisk_Input'!$A$5:$A$15,0)) | W16: =INDEX('5_UK_DefaultRisk_Input'!$D$20:$D$44,MATCH($E16,'5_UK_DefaultRisk_Input'!$A$20:$A$44,0)) | X16: =INDEX('5_UK_DefaultRisk_Input'!$D$49:$D$122,MATCH($D16,'5_UK_DefaultRisk_Input'!$A$49:$A$122,0)) | Y16: =INDEX('5_UK_DefaultRisk_Input'!$D$127:$D$289,MATCH($A16,'5_UK_DefaultRisk_Input'!$A$127:$A$289,0)) | Z16: =(W16/V16)*(X16/W16)*(Y16/X16) | AA16: =INDEX('3_UK_L1_Input'!$D$4:$D$14,MATCH($C16,'3_UK_L1_Input'!$A$4:$A$14,0))*Z16
A17: 15103020 | B17: Paper & Plastic Packaging Products & Materials | C17: 15 | D17: 151030 | E17: 1510 | F17: 56210000 | G17: 3.38 | H17: =IFERROR(SUMPRODUCT(($C$3:$C$165=C17)*ISNUMBER($G$3:$G$165)*ISNUMBER($F$3:$F$165)*IF(ISNUMBER($F$3:$F$165),$F$3:$F$165,0)*IF(ISNUMBER($G$3:$G$165),$G$3:$G$165,0))/SUMPRODUCT(($C$3:$C$165=C17)*ISNUMBER($G$3:$G$165)*ISNUMBER($F$3:$F$165)*IF(ISNUMBER($F$3:$F$165),$F$3:$F$165,0)),"") | I17: =IFERROR(SUMPRODUCT(($C$3:$C$165=C17)*ISNUMBER($G$3:$G$165)*IF(ISNUMBER($G$3:$G$165),$G$3:$G$165,0))/SUMPRODUCT(($C$3:$C$165=C17)*ISNUMBER($G$3:$G$165)),"") | J17: =IF(OR(G17="",H17=""),"",G17/H17) | K17: =IF(OR(G17="",I17=""),"",G17/I17) | L17: =INDEX('4_UK_Beta_Input'!$D$5:$D$15,MATCH($C17,'4_UK_Beta_Input'!$A$5:$A$15,0)) | M17: =INDEX('4_UK_Beta_Input'!$D$20:$D$44,MATCH($E17,'4_UK_Beta_Input'!$A$20:$A$44,0)) | N17: =INDEX('4_UK_Beta_Input'!$D$49:$D$122,MATCH($D17,'4_UK_Beta_Input'!$A$49:$A$122,0)) | O17: =INDEX('4_UK_Beta_Input'!$D$127:$D$289,MATCH($A17,'4_UK_Beta_Input'!$A$127:$A$289,0)) | P17: =(M17/L17)*(N17/M17)*(O17/N17) | Q17: =IF(J17="",INDEX('3_UK_L1_Input'!$D$4:$D$14,MATCH($C17,'3_UK_L1_Input'!$A$4:$A$14,0))*P17,INDEX('3_UK_L1_Input'!$D$4:$D$14,MATCH($C17,'3_UK_L1_Input'!$A$4:$A$14,0))*J17) | R17: =IF(K17="",INDEX('3_UK_L1_Input'!$D$4:$D$14,MATCH($C17,'3_UK_L1_Input'!$A$4:$A$14,0))*P17,INDEX('3_UK_L1_Input'!$D$4:$D$14,MATCH($C17,'3_UK_L1_Input'!$A$4:$A$14,0))*K17) | S17: =IF(G17="","BETA CASCADE FALLBACK (dummy — replace with real beta)","REAL (Bloomberg UK)") | T17: =INDEX('3_UK_L1_Input'!$C$4:$C$14,MATCH($C17,'3_UK_L1_Input'!$A$4:$A$14,0)) | U17: =INDEX('3_UK_L1_Input'!$C$4:$C$14,MATCH($C17,'3_UK_L1_Input'!$A$4:$A$14,0))*P17 | V17: =INDEX('5_UK_DefaultRisk_Input'!$D$5:$D$15,MATCH($C17,'5_UK_DefaultRisk_Input'!$A$5:$A$15,0)) | W17: =INDEX('5_UK_DefaultRisk_Input'!$D$20:$D$44,MATCH($E17,'5_UK_DefaultRisk_Input'!$A$20:$A$44,0)) | X17: =INDEX('5_UK_DefaultRisk_Input'!$D$49:$D$122,MATCH($D17,'5_UK_DefaultRisk_Input'!$A$49:$A$122,0)) | Y17: =INDEX('5_UK_DefaultRisk_Input'!$D$127:$D$289,MATCH($A17,'5_UK_DefaultRisk_Input'!$A$127:$A$289,0)) | Z17: =(W17/V17)*(X17/W17)*(Y17/X17) | AA17: =INDEX('3_UK_L1_Input'!$D$4:$D$14,MATCH($C17,'3_UK_L1_Input'!$A$4:$A$14,0))*Z17
A18: 15104010 | B18: Aluminum | C18: 15 | D18: 151040 | E18: 1510 | H18: =IFERROR(SUMPRODUCT(($C$3:$C$165=C18)*ISNUMBER($G$3:$G$165)*ISNUMBER($F$3:$F$165)*IF(ISNUMBER($F$3:$F$165),$F$3:$F$165,0)*IF(ISNUMBER($G$3:$G$165),$G$3:$G$165,0))/SUMPRODUCT(($C$3:$C$165=C18)*ISNUMBER($G$3:$G$165)*ISNUMBER($F$3:$F$165)*IF(ISNUMBER($F$3:$F$165),$F$3:$F$165,0)),"") | I18: =IFERROR(SUMPRODUCT(($C$3:$C$165=C18)*ISNUMBER($G$3:$G$165)*IF(ISNUMBER($G$3:$G$165),$G$3:$G$165,0))/SUMPRODUCT(($C$3:$C$165=C18)*ISNUMBER($G$3:$G$165)),"") | J18: =IF(OR(G18="",H18=""),"",G18/H18) | K18: =IF(OR(G18="",I18=""),"",G18/I18) | L18: =INDEX('4_UK_Beta_Input'!$D$5:$D$15,MATCH($C18,'4_UK_Beta_Input'!$A$5:$A$15,0)) | M18: =INDEX('4_UK_Beta_Input'!$D$20:$D$44,MATCH($E18,'4_UK_Beta_Input'!$A$20:$A$44,0)) | N18: =INDEX('4_UK_Beta_Input'!$D$49:$D$122,MATCH($D18,'4_UK_Beta_Input'!$A$49:$A$122,0)) | O18: =INDEX('4_UK_Beta_Input'!$D$127:$D$289,MATCH($A18,'4_UK_Beta_Input'!$A$127:$A$289,0)) | P18: =(M18/L18)*(N18/M18)*(O18/N18) | Q18: =IF(J18="",INDEX('3_UK_L1_Input'!$D$4:$D$14,MATCH($C18,'3_UK_L1_Input'!$A$4:$A$14,0))*P18,INDEX('3_UK_L1_Input'!$D$4:$D$14,MATCH($C18,'3_UK_L1_Input'!$A$4:$A$14,0))*J18) | R18: =IF(K18="",INDEX('3_UK_L1_Input'!$D$4:$D$14,MATCH($C18,'3_UK_L1_Input'!$A$4:$A$14,0))*P18,INDEX('3_UK_L1_Input'!$D$4:$D$14,MATCH($C18,'3_UK_L1_Input'!$A$4:$A$14,0))*K18) | S18: =IF(G18="","BETA CASCADE FALLBACK (dummy — replace with real beta)","REAL (Bloomberg UK)") | T18: =INDEX('3_UK_L1_Input'!$C$4:$C$14,MATCH($C18,'3_UK_L1_Input'!$A$4:$A$14,0)) | U18: =INDEX('3_UK_L1_Input'!$C$4:$C$14,MATCH($C18,'3_UK_L1_Input'!$A$4:$A$14,0))*P18 | V18: =INDEX('5_UK_DefaultRisk_Input'!$D$5:$D$15,MATCH($C18,'5_UK_DefaultRisk_Input'!$A$5:$A$15,0)) | W18: =INDEX('5_UK_DefaultRisk_Input'!$D$20:$D$44,MATCH($E18,'5_UK_DefaultRisk_Input'!$A$20:$A$44,0)) | X18: =INDEX('5_UK_DefaultRisk_Input'!$D$49:$D$122,MATCH($D18,'5_UK_DefaultRisk_Input'!$A$49:$A$122,0)) | Y18: =INDEX('5_UK_DefaultRisk_Input'!$D$127:$D$289,MATCH($A18,'5_UK_DefaultRisk_Input'!$A$127:$A$289,0)) | Z18: =(W18/V18)*(X18/W18)*(Y18/X18) | AA18: =INDEX('3_UK_L1_Input'!$D$4:$D$14,MATCH($C18,'3_UK_L1_Input'!$A$4:$A$14,0))*Z18
A19: 15104020 | B19: Diversified Metals & Mining | C19: 15 | D19: 151040 | E19: 1510 | F19: 1930000000 | G19: 5.94 | H19: =IFERROR(SUMPRODUCT(($C$3:$C$165=C19)*ISNUMBER($G$3:$G$165)*ISNUMBER($F$3:$F$165)*IF(ISNUMBER($F$3:$F$165),$F$3:$F$165,0)*IF(ISNUMBER($G$3:$G$165),$G$3:$G$165,0))/SUMPRODUCT(($C$3:$C$165=C19)*ISNUMBER($G$3:$G$165)*ISNUMBER($F$3:$F$165)*IF(ISNUMBER($F$3:$F$165),$F$3:$F$165,0)),"") | I19: =IFERROR(SUMPRODUCT(($C$3:$C$165=C19)*ISNUMBER($G$3:$G$165)*IF(ISNUMBER($G$3:$G$165),$G$3:$G$165,0))/SUMPRODUCT(($C$3:$C$165=C19)*ISNUMBER($G$3:$G$165)),"") | J19: =IF(OR(G19="",H19=""),"",G19/H19) | K19: =IF(OR(G19="",I19=""),"",G19/I19) | L19: =INDEX('4_UK_Beta_Input'!$D$5:$D$15,MATCH($C19,'4_UK_Beta_Input'!$A$5:$A$15,0)) | M19: =INDEX('4_UK_Beta_Input'!$D$20:$D$44,MATCH($E19,'4_UK_Beta_Input'!$A$20:$A$44,0)) | N19: =INDEX('4_UK_Beta_Input'!$D$49:$D$122,MATCH($D19,'4_UK_Beta_Input'!$A$49:$A$122,0)) | O19: =INDEX('4_UK_Beta_Input'!$D$127:$D$289,MATCH($A19,'4_UK_Beta_Input'!$A$127:$A$289,0)) | P19: =(M19/L19)*(N19/M19)*(O19/N19) | Q19: =IF(J19="",INDEX('3_UK_L1_Input'!$D$4:$D$14,MATCH($C19,'3_UK_L1_Input'!$A$4:$A$14,0))*P19,INDEX('3_UK_L1_Input'!$D$4:$D$14,MATCH($C19,'3_UK_L1_Input'!$A$4:$A$14,0))*J19) | R19: =IF(K19="",INDEX('3_UK_L1_Input'!$D$4:$D$14,MATCH($C19,'3_UK_L1_Input'!$A$4:$A$14,0))*P19,INDEX('3_UK_L1_Input'!$D$4:$D$14,MATCH($C19,'3_UK_L1_Input'!$A$4:$A$14,0))*K19) | S19: =IF(G19="","BETA CASCADE FALLBACK (dummy — replace with real beta)","REAL (Bloomberg UK)") | T19: =INDEX('3_UK_L1_Input'!$C$4:$C$14,MATCH($C19,'3_UK_L1_Input'!$A$4:$A$14,0)) | U19: =INDEX('3_UK_L1_Input'!$C$4:$C$14,MATCH($C19,'3_UK_L1_Input'!$A$4:$A$14,0))*P19 | V19: =INDEX('5_UK_DefaultRisk_Input'!$D$5:$D$15,MATCH($C19,'5_UK_DefaultRisk_Input'!$A$5:$A$15,0)) | W19: =INDEX('5_UK_DefaultRisk_Input'!$D$20:$D$44,MATCH($E19,'5_UK_DefaultRisk_Input'!$A$20:$A$44,0)) | X19: =INDEX('5_UK_DefaultRisk_Input'!$D$49:$D$122,MATCH($D19,'5_UK_DefaultRisk_Input'!$A$49:$A$122,0)) | Y19: =INDEX('5_UK_DefaultRisk_Input'!$D$127:$D$289,MATCH($A19,'5_UK_DefaultRisk_Input'!$A$127:$A$289,0)) | Z19: =(W19/V19)*(X19/W19)*(Y19/X19) | AA19: =INDEX('3_UK_L1_Input'!$D$4:$D$14,MATCH($C19,'3_UK_L1_Input'!$A$4:$A$14,0))*Z19
A20: 15104025 | B20: Copper | C20: 15 | D20: 151040 | E20: 1510 | F20: 76620000 | G20: 1.5 | H20: =IFERROR(SUMPRODUCT(($C$3:$C$165=C20)*ISNUMBER($G$3:$G$165)*ISNUMBER($F$3:$F$165)*IF(ISNUMBER($F$3:$F$165),$F$3:$F$165,0)*IF(ISNUMBER($G$3:$G$165),$G$3:$G$165,0))/SUMPRODUCT(($C$3:$C$165=C20)*ISNUMBER($G$3:$G$165)*ISNUMBER($F$3:$F$165)*IF(ISNUMBER($F$3:$F$165),$F$3:$F$165,0)),"") | I20: =IFERROR(SUMPRODUCT(($C$3:$C$165=C20)*ISNUMBER($G$3:$G$165)*IF(ISNUMBER($G$3:$G$165),$G$3:$G$165,0))/SUMPRODUCT(($C$3:$C$165=C20)*ISNUMBER($G$3:$G$165)),"") | J20: =IF(OR(G20="",H20=""),"",G20/H20) | K20: =IF(OR(G20="",I20=""),"",G20/I20) | L20: =INDEX('4_UK_Beta_Input'!$D$5:$D$15,MATCH($C20,'4_UK_Beta_Input'!$A$5:$A$15,0)) | M20: =INDEX('4_UK_Beta_Input'!$D$20:$D$44,MATCH($E20,'4_UK_Beta_Input'!$A$20:$A$44,0)) | N20: =INDEX('4_UK_Beta_Input'!$D$49:$D$122,MATCH($D20,'4_UK_Beta_Input'!$A$49:$A$122,0)) | O20: =INDEX('4_UK_Beta_Input'!$D$127:$D$289,MATCH($A20,'4_UK_Beta_Input'!$A$127:$A$289,0)) | P20: =(M20/L20)*(N20/M20)*(O20/N20) | Q20: =IF(J20="",INDEX('3_UK_L1_Input'!$D$4:$D$14,MATCH($C20,'3_UK_L1_Input'!$A$4:$A$14,0))*P20,INDEX('3_UK_L1_Input'!$D$4:$D$14,MATCH($C20,'3_UK_L1_Input'!$A$4:$A$14,0))*J20) | R20: =IF(K20="",INDEX('3_UK_L1_Input'!$D$4:$D$14,MATCH($C20,'3_UK_L1_Input'!$A$4:$A$14,0))*P20,INDEX('3_UK_L1_Input'!$D$4:$D$14,MATCH($C20,'3_UK_L1_Input'!$A$4:$A$14,0))*K20) | S20: =IF(G20="","BETA CASCADE FALLBACK (dummy — replace with real beta)","REAL (Bloomberg UK)") | T20: =INDEX('3_UK_L1_Input'!$C$4:$C$14,MATCH($C20,'3_UK_L1_Input'!$A$4:$A$14,0)) | U20: =INDEX('3_UK_L1_Input'!$C$4:$C$14,MATCH($C20,'3_UK_L1_Input'!$A$4:$A$14,0))*P20 | V20: =INDEX('5_UK_DefaultRisk_Input'!$D$5:$D$15,MATCH($C20,'5_UK_DefaultRisk_Input'!$A$5:$A$15,0)) | W20: =INDEX('5_UK_DefaultRisk_Input'!$D$20:$D$44,MATCH($E20,'5_UK_DefaultRisk_Input'!$A$20:$A$44,0)) | X20: =INDEX('5_UK_DefaultRisk_Input'!$D$49:$D$122,MATCH($D20,'5_UK_DefaultRisk_Input'!$A$49:$A$122,0)) | Y20: =INDEX('5_UK_DefaultRisk_Input'!$D$127:$D$289,MATCH($A20,'5_UK_DefaultRisk_Input'!$A$127:$A$289,0)) | Z20: =(W20/V20)*(X20/W20)*(Y20/X20) | AA20: =INDEX('3_UK_L1_Input'!$D$4:$D$14,MATCH($C20,'3_UK_L1_Input'!$A$4:$A$14,0))*Z20
A21: 15104030 | B21: Gold | C21: 15 | D21: 151040 | E21: 1510 | F21: 410600000 | G21: 4.23 | H21: =IFERROR(SUMPRODUCT(($C$3:$C$165=C21)*ISNUMBER($G$3:$G$165)*ISNUMBER($F$3:$F$165)*IF(ISNUMBER($F$3:$F$165),$F$3:$F$165,0)*IF(ISNUMBER($G$3:$G$165),$G$3:$G$165,0))/SUMPRODUCT(($C$3:$C$165=C21)*ISNUMBER($G$3:$G$165)*ISNUMBER($F$3:$F$165)*IF(ISNUMBER($F$3:$F$165),$F$3:$F$165,0)),"") | I21: =IFERROR(SUMPRODUCT(($C$3:$C$165=C21)*ISNUMBER($G$3:$G$165)*IF(ISNUMBER($G$3:$G$165),$G$3:$G$165,0))/SUMPRODUCT(($C$3:$C$165=C21)*ISNUMBER($G$3:$G$165)),"") | J21: =IF(OR(G21="",H21=""),"",G21/H21) | K21: =IF(OR(G21="",I21=""),"",G21/I21) | L21: =INDEX('4_UK_Beta_Input'!$D$5:$D$15,MATCH($C21,'4_UK_Beta_Input'!$A$5:$A$15,0)) | M21: =INDEX('4_UK_Beta_Input'!$D$20:$D$44,MATCH($E21,'4_UK_Beta_Input'!$A$20:$A$44,0)) | N21: =INDEX('4_UK_Beta_Input'!$D$49:$D$122,MATCH($D21,'4_UK_Beta_Input'!$A$49:$A$122,0)) | O21: =INDEX('4_UK_Beta_Input'!$D$127:$D$289,MATCH($A21,'4_UK_Beta_Input'!$A$127:$A$289,0)) | P21: =(M21/L21)*(N21/M21)*(O21/N21) | Q21: =IF(J21="",INDEX('3_UK_L1_Input'!$D$4:$D$14,MATCH($C21,'3_UK_L1_Input'!$A$4:$A$14,0))*P21,INDEX('3_UK_L1_Input'!$D$4:$D$14,MATCH($C21,'3_UK_L1_Input'!$A$4:$A$14,0))*J21) | R21: =IF(K21="",INDEX('3_UK_L1_Input'!$D$4:$D$14,MATCH($C21,'3_UK_L1_Input'!$A$4:$A$14,0))*P21,INDEX('3_UK_L1_Input'!$D$4:$D$14,MATCH($C21,'3_UK_L1_Input'!$A$4:$A$14,0))*K21) | S21: =IF(G21="","BETA CASCADE FALLBACK (dummy — replace with real beta)","REAL (Bloomberg UK)") | T21: =INDEX('3_UK_L1_Input'!$C$4:$C$14,MATCH($C21,'3_UK_L1_Input'!$A$4:$A$14,0)) | U21: =INDEX('3_UK_L1_Input'!$C$4:$C$14,MATCH($C21,'3_UK_L1_Input'!$A$4:$A$14,0))*P21 | V21: =INDEX('5_UK_DefaultRisk_Input'!$D$5:$D$15,MATCH($C21,'5_UK_DefaultRisk_Input'!$A$5:$A$15,0)) | W21: =INDEX('5_UK_DefaultRisk_Input'!$D$20:$D$44,MATCH($E21,'5_UK_DefaultRisk_Input'!$A$20:$A$44,0)) | X21: =INDEX('5_UK_DefaultRisk_Input'!$D$49:$D$122,MATCH($D21,'5_UK_DefaultRisk_Input'!$A$49:$A$122,0)) | Y21: =INDEX('5_UK_DefaultRisk_Input'!$D$127:$D$289,MATCH($A21,'5_UK_DefaultRisk_Input'!$A$127:$A$289,0)) | Z21: =(W21/V21)*(X21/W21)*(Y21/X21) | AA21: =INDEX('3_UK_L1_Input'!$D$4:$D$14,MATCH($C21,'3_UK_L1_Input'!$A$4:$A$14,0))*Z21
A22: 15104040 | B22: Precious Metals & Minerals | C22: 15 | D22: 151040 | E22: 1510 | F22: 20970000 | H22: =IFERROR(SUMPRODUCT(($C$3:$C$165=C22)*ISNUMBER($G$3:$G$165)*ISNUMBER($F$3:$F$165)*IF(ISNUMBER($F$3:$F$165),$F$3:$F$165,0)*IF(ISNUMBER($G$3:$G$165),$G$3:$G$165,0))/SUMPRODUCT(($C$3:$C$165=C22)*ISNUMBER($G$3:$G$165)*ISNUMBER($F$3:$F$165)*IF(ISNUMBER($F$3:$F$165),$F$3:$F$165,0)),"") | I22: =IFERROR(SUMPRODUCT(($C$3:$C$165=C22)*ISNUMBER($G$3:$G$165)*IF(ISNUMBER($G$3:$G$165),$G$3:$G$165,0))/SUMPRODUCT(($C$3:$C$165=C22)*ISNUMBER($G$3:$G$165)),"") | J22: =IF(OR(G22="",H22=""),"",G22/H22) | K22: =IF(OR(G22="",I22=""),"",G22/I22) | L22: =INDEX('4_UK_Beta_Input'!$D$5:$D$15,MATCH($C22,'4_UK_Beta_Input'!$A$5:$A$15,0)) | M22: =INDEX('4_UK_Beta_Input'!$D$20:$D$44,MATCH($E22,'4_UK_Beta_Input'!$A$20:$A$44,0)) | N22: =INDEX('4_UK_Beta_Input'!$D$49:$D$122,MATCH($D22,'4_UK_Beta_Input'!$A$49:$A$122,0)) | O22: =INDEX('4_UK_Beta_Input'!$D$127:$D$289,MATCH($A22,'4_UK_Beta_Input'!$A$127:$A$289,0)) | P22: =(M22/L22)*(N22/M22)*(O22/N22) | Q22: =IF(J22="",INDEX('3_UK_L1_Input'!$D$4:$D$14,MATCH($C22,'3_UK_L1_Input'!$A$4:$A$14,0))*P22,INDEX('3_UK_L1_Input'!$D$4:$D$14,MATCH($C22,'3_UK_L1_Input'!$A$4:$A$14,0))*J22) | R22: =IF(K22="",INDEX('3_UK_L1_Input'!$D$4:$D$14,MATCH($C22,'3_UK_L1_Input'!$A$4:$A$14,0))*P22,INDEX('3_UK_L1_Input'!$D$4:$D$14,MATCH($C22,'3_UK_L1_Input'!$A$4:$A$14,0))*K22) | S22: =IF(G22="","BETA CASCADE FALLBACK (dummy — replace with real beta)","REAL (Bloomberg UK)") | T22: =INDEX('3_UK_L1_Input'!$C$4:$C$14,MATCH($C22,'3_UK_L1_Input'!$A$4:$A$14,0)) | U22: =INDEX('3_UK_L1_Input'!$C$4:$C$14,MATCH($C22,'3_UK_L1_Input'!$A$4:$A$14,0))*P22 | V22: =INDEX('5_UK_DefaultRisk_Input'!$D$5:$D$15,MATCH($C22,'5_UK_DefaultRisk_Input'!$A$5:$A$15,0)) | W22: =INDEX('5_UK_DefaultRisk_Input'!$D$20:$D$44,MATCH($E22,'5_UK_DefaultRisk_Input'!$A$20:$A$44,0)) | X22: =INDEX('5_UK_DefaultRisk_Input'!$D$49:$D$122,MATCH($D22,'5_UK_DefaultRisk_Input'!$A$49:$A$122,0)) | Y22: =INDEX('5_UK_DefaultRisk_Input'!$D$127:$D$289,MATCH($A22,'5_UK_DefaultRisk_Input'!$A$127:$A$289,0)) | Z22: =(W22/V22)*(X22/W22)*(Y22/X22) | AA22: =INDEX('3_UK_L1_Input'!$D$4:$D$14,MATCH($C22,'3_UK_L1_Input'!$A$4:$A$14,0))*Z22
A23: 15104045 | B23: Silver | C23: 15 | D23: 151040 | E23: 1510 | H23: =IFERROR(SUMPRODUCT(($C$3:$C$165=C23)*ISNUMBER($G$3:$G$165)*ISNUMBER($F$3:$F$165)*IF(ISNUMBER($F$3:$F$165),$F$3:$F$165,0)*IF(ISNUMBER($G$3:$G$165),$G$3:$G$165,0))/SUMPRODUCT(($C$3:$C$165=C23)*ISNUMBER($G$3:$G$165)*ISNUMBER($F$3:$F$165)*IF(ISNUMBER($F$3:$F$165),$F$3:$F$165,0)),"") | I23: =IFERROR(SUMPRODUCT(($C$3:$C$165=C23)*ISNUMBER($G$3:$G$165)*IF(ISNUMBER($G$3:$G$165),$G$3:$G$165,0))/SUMPRODUCT(($C$3:$C$165=C23)*ISNUMBER($G$3:$G$165)),"") | J23: =IF(OR(G23="",H23=""),"",G23/H23) | K23: =IF(OR(G23="",I23=""),"",G23/I23) | L23: =INDEX('4_UK_Beta_Input'!$D$5:$D$15,MATCH($C23,'4_UK_Beta_Input'!$A$5:$A$15,0)) | M23: =INDEX('4_UK_Beta_Input'!$D$20:$D$44,MATCH($E23,'4_UK_Beta_Input'!$A$20:$A$44,0)) | N23: =INDEX('4_UK_Beta_Input'!$D$49:$D$122,MATCH($D23,'4_UK_Beta_Input'!$A$49:$A$122,0)) | O23: =INDEX('4_UK_Beta_Input'!$D$127:$D$289,MATCH($A23,'4_UK_Beta_Input'!$A$127:$A$289,0)) | P23: =(M23/L23)*(N23/M23)*(O23/N23) | Q23: =IF(J23="",INDEX('3_UK_L1_Input'!$D$4:$D$14,MATCH($C23,'3_UK_L1_Input'!$A$4:$A$14,0))*P23,INDEX('3_UK_L1_Input'!$D$4:$D$14,MATCH($C23,'3_UK_L1_Input'!$A$4:$A$14,0))*J23) | R23: =IF(K23="",INDEX('3_UK_L1_Input'!$D$4:$D$14,MATCH($C23,'3_UK_L1_Input'!$A$4:$A$14,0))*P23,INDEX('3_UK_L1_Input'!$D$4:$D$14,MATCH($C23,'3_UK_L1_Input'!$A$4:$A$14,0))*K23) | S23: =IF(G23="","BETA CASCADE FALLBACK (dummy — replace with real beta)","REAL (Bloomberg UK)") | T23: =INDEX('3_UK_L1_Input'!$C$4:$C$14,MATCH($C23,'3_UK_L1_Input'!$A$4:$A$14,0)) | U23: =INDEX('3_UK_L1_Input'!$C$4:$C$14,MATCH($C23,'3_UK_L1_Input'!$A$4:$A$14,0))*P23 | V23: =INDEX('5_UK_DefaultRisk_Input'!$D$5:$D$15,MATCH($C23,'5_UK_DefaultRisk_Input'!$A$5:$A$15,0)) | W23: =INDEX('5_UK_DefaultRisk_Input'!$D$20:$D$44,MATCH($E23,'5_UK_DefaultRisk_Input'!$A$20:$A$44,0)) | X23: =INDEX('5_UK_DefaultRisk_Input'!$D$49:$D$122,MATCH($D23,'5_UK_DefaultRisk_Input'!$A$49:$A$122,0)) | Y23: =INDEX('5_UK_DefaultRisk_Input'!$D$127:$D$289,MATCH($A23,'5_UK_DefaultRisk_Input'!$A$127:$A$289,0)) | Z23: =(W23/V23)*(X23/W23)*(Y23/X23) | AA23: =INDEX('3_UK_L1_Input'!$D$4:$D$14,MATCH($C23,'3_UK_L1_Input'!$A$4:$A$14,0))*Z23
A24: 15104050 | B24: Steel | C24: 15 | D24: 151040 | E24: 1510 | F24: 229700000 | G24: 10.16 | H24: =IFERROR(SUMPRODUCT(($C$3:$C$165=C24)*ISNUMBER($G$3:$G$165)*ISNUMBER($F$3:$F$165)*IF(ISNUMBER($F$3:$F$165),$F$3:$F$165,0)*IF(ISNUMBER($G$3:$G$165),$G$3:$G$165,0))/SUMPRODUCT(($C$3:$C$165=C24)*ISNUMBER($G$3:$G$165)*ISNUMBER($F$3:$F$165)*IF(ISNUMBER($F$3:$F$165),$F$3:$F$165,0)),"") | I24: =IFERROR(SUMPRODUCT(($C$3:$C$165=C24)*ISNUMBER($G$3:$G$165)*IF(ISNUMBER($G$3:$G$165),$G$3:$G$165,0))/SUMPRODUCT(($C$3:$C$165=C24)*ISNUMBER($G$3:$G$165)),"") | J24: =IF(OR(G24="",H24=""),"",G24/H24) | K24: =IF(OR(G24="",I24=""),"",G24/I24) | L24: =INDEX('4_UK_Beta_Input'!$D$5:$D$15,MATCH($C24,'4_UK_Beta_Input'!$A$5:$A$15,0)) | M24: =INDEX('4_UK_Beta_Input'!$D$20:$D$44,MATCH($E24,'4_UK_Beta_Input'!$A$20:$A$44,0)) | N24: =INDEX('4_UK_Beta_Input'!$D$49:$D$122,MATCH($D24,'4_UK_Beta_Input'!$A$49:$A$122,0)) | O24: =INDEX('4_UK_Beta_Input'!$D$127:$D$289,MATCH($A24,'4_UK_Beta_Input'!$A$127:$A$289,0)) | P24: =(M24/L24)*(N24/M24)*(O24/N24) | Q24: =IF(J24="",INDEX('3_UK_L1_Input'!$D$4:$D$14,MATCH($C24,'3_UK_L1_Input'!$A$4:$A$14,0))*P24,INDEX('3_UK_L1_Input'!$D$4:$D$14,MATCH($C24,'3_UK_L1_Input'!$A$4:$A$14,0))*J24) | R24: =IF(K24="",INDEX('3_UK_L1_Input'!$D$4:$D$14,MATCH($C24,'3_UK_L1_Input'!$A$4:$A$14,0))*P24,INDEX('3_UK_L1_Input'!$D$4:$D$14,MATCH($C24,'3_UK_L1_Input'!$A$4:$A$14,0))*K24) | S24: =IF(G24="","BETA CASCADE FALLBACK (dummy — replace with real beta)","REAL (Bloomberg UK)") | T24: =INDEX('3_UK_L1_Input'!$C$4:$C$14,MATCH($C24,'3_UK_L1_Input'!$A$4:$A$14,0)) | U24: =INDEX('3_UK_L1_Input'!$C$4:$C$14,MATCH($C24,'3_UK_L1_Input'!$A$4:$A$14,0))*P24 | V24: =INDEX('5_UK_DefaultRisk_Input'!$D$5:$D$15,MATCH($C24,'5_UK_DefaultRisk_Input'!$A$5:$A$15,0)) | W24: =INDEX('5_UK_DefaultRisk_Input'!$D$20:$D$44,MATCH($E24,'5_UK_DefaultRisk_Input'!$A$20:$A$44,0)) | X24: =INDEX('5_UK_DefaultRisk_Input'!$D$49:$D$122,MATCH($D24,'5_UK_DefaultRisk_Input'!$A$49:$A$122,0)) | Y24: =INDEX('5_UK_DefaultRisk_Input'!$D$127:$D$289,MATCH($A24,'5_UK_DefaultRisk_Input'!$A$127:$A$289,0)) | Z24: =(W24/V24)*(X24/W24)*(Y24/X24) | AA24: =INDEX('3_UK_L1_Input'!$D$4:$D$14,MATCH($C24,'3_UK_L1_Input'!$A$4:$A$14,0))*Z24
A25: 15105010 | B25: Forest Products | C25: 15 | D25: 151050 | E25: 1510 | F25: 153280000 | G25: 9.59 | H25: =IFERROR(SUMPRODUCT(($C$3:$C$165=C25)*ISNUMBER($G$3:$G$165)*ISNUMBER($F$3:$F$165)*IF(ISNUMBER($F$3:$F$165),$F$3:$F$165,0)*IF(ISNUMBER($G$3:$G$165),$G$3:$G$165,0))/SUMPRODUCT(($C$3:$C$165=C25)*ISNUMBER($G$3:$G$165)*ISNUMBER($F$3:$F$165)*IF(ISNUMBER($F$3:$F$165),$F$3:$F$165,0)),"") | I25: =IFERROR(SUMPRODUCT(($C$3:$C$165=C25)*ISNUMBER($G$3:$G$165)*IF(ISNUMBER($G$3:$G$165),$G$3:$G$165,0))/SUMPRODUCT(($C$3:$C$165=C25)*ISNUMBER($G$3:$G$165)),"") | J25: =IF(OR(G25="",H25=""),"",G25/H25) | K25: =IF(OR(G25="",I25=""),"",G25/I25) | L25: =INDEX('4_UK_Beta_Input'!$D$5:$D$15,MATCH($C25,'4_UK_Beta_Input'!$A$5:$A$15,0)) | M25: =INDEX('4_UK_Beta_Input'!$D$20:$D$44,MATCH($E25,'4_UK_Beta_Input'!$A$20:$A$44,0)) | N25: =INDEX('4_UK_Beta_Input'!$D$49:$D$122,MATCH($D25,'4_UK_Beta_Input'!$A$49:$A$122,0)) | O25: =INDEX('4_UK_Beta_Input'!$D$127:$D$289,MATCH($A25,'4_UK_Beta_Input'!$A$127:$A$289,0)) | P25: =(M25/L25)*(N25/M25)*(O25/N25) | Q25: =IF(J25="",INDEX('3_UK_L1_Input'!$D$4:$D$14,MATCH($C25,'3_UK_L1_Input'!$A$4:$A$14,0))*P25,INDEX('3_UK_L1_Input'!$D$4:$D$14,MATCH($C25,'3_UK_L1_Input'!$A$4:$A$14,0))*J25) | R25: =IF(K25="",INDEX('3_UK_L1_Input'!$D$4:$D$14,MATCH($C25,'3_UK_L1_Input'!$A$4:$A$14,0))*P25,INDEX('3_UK_L1_Input'!$D$4:$D$14,MATCH($C25,'3_UK_L1_Input'!$A$4:$A$14,0))*K25) | S25: =IF(G25="","BETA CASCADE FALLBACK (dummy — replace with real beta)","REAL (Bloomberg UK)") | T25: =INDEX('3_UK_L1_Input'!$C$4:$C$14,MATCH($C25,'3_UK_L1_Input'!$A$4:$A$14,0)) | U25: =INDEX('3_UK_L1_Input'!$C$4:$C$14,MATCH($C25,'3_UK_L1_Input'!$A$4:$A$14,0))*P25 | V25: =INDEX('5_UK_DefaultRisk_Input'!$D$5:$D$15,MATCH($C25,'5_UK_DefaultRisk_Input'!$A$5:$A$15,0)) | W25: =INDEX('5_UK_DefaultRisk_Input'!$D$20:$D$44,MATCH($E25,'5_UK_DefaultRisk_Input'!$A$20:$A$44,0)) | X25: =INDEX('5_UK_DefaultRisk_Input'!$D$49:$D$122,MATCH($D25,'5_UK_DefaultRisk_Input'!$A$49:$A$122,0)) | Y25: =INDEX('5_UK_DefaultRisk_Input'!$D$127:$D$289,MATCH($A25,'5_UK_DefaultRisk_Input'!$A$127:$A$289,0)) | Z25: =(W25/V25)*(X25/W25)*(Y25/X25) | AA25: =INDEX('3_UK_L1_Input'!$D$4:$D$14,MATCH($C25,'3_UK_L1_Input'!$A$4:$A$14,0))*Z25
A26: 15105020 | B26: Paper Products | C26: 15 | D26: 151050 | E26: 1510 | F26: 3920000000 | G26: 6.56 | H26: =IFERROR(SUMPRODUCT(($C$3:$C$165=C26)*ISNUMBER($G$3:$G$165)*ISNUMBER($F$3:$F$165)*IF(ISNUMBER($F$3:$F$165),$F$3:$F$165,0)*IF(ISNUMBER($G$3:$G$165),$G$3:$G$165,0))/SUMPRODUCT(($C$3:$C$165=C26)*ISNUMBER($G$3:$G$165)*ISNUMBER($F$3:$F$165)*IF(ISNUMBER($F$3:$F$165),$F$3:$F$165,0)),"") | I26: =IFERROR(SUMPRODUCT(($C$3:$C$165=C26)*ISNUMBER($G$3:$G$165)*IF(ISNUMBER($G$3:$G$165),$G$3:$G$165,0))/SUMPRODUCT(($C$3:$C$165=C26)*ISNUMBER($G$3:$G$165)),"") | J26: =IF(OR(G26="",H26=""),"",G26/H26) | K26: =IF(OR(G26="",I26=""),"",G26/I26) | L26: =INDEX('4_UK_Beta_Input'!$D$5:$D$15,MATCH($C26,'4_UK_Beta_Input'!$A$5:$A$15,0)) | M26: =INDEX('4_UK_Beta_Input'!$D$20:$D$44,MATCH($E26,'4_UK_Beta_Input'!$A$20:$A$44,0)) | N26: =INDEX('4_UK_Beta_Input'!$D$49:$D$122,MATCH($D26,'4_UK_Beta_Input'!$A$49:$A$122,0)) | O26: =INDEX('4_UK_Beta_Input'!$D$127:$D$289,MATCH($A26,'4_UK_Beta_Input'!$A$127:$A$289,0)) | P26: =(M26/L26)*(N26/M26)*(O26/N26) | Q26: =IF(J26="",INDEX('3_UK_L1_Input'!$D$4:$D$14,MATCH($C26,'3_UK_L1_Input'!$A$4:$A$14,0))*P26,INDEX('3_UK_L1_Input'!$D$4:$D$14,MATCH($C26,'3_UK_L1_Input'!$A$4:$A$14,0))*J26) | R26: =IF(K26="",INDEX('3_UK_L1_Input'!$D$4:$D$14,MATCH($C26,'3_UK_L1_Input'!$A$4:$A$14,0))*P26,INDEX('3_UK_L1_Input'!$D$4:$D$14,MATCH($C26,'3_UK_L1_Input'!$A$4:$A$14,0))*K26) | S26: =IF(G26="","BETA CASCADE FALLBACK (dummy — replace with real beta)","REAL (Bloomberg UK)") | T26: =INDEX('3_UK_L1_Input'!$C$4:$C$14,MATCH($C26,'3_UK_L1_Input'!$A$4:$A$14,0)) | U26: =INDEX('3_UK_L1_Input'!$C$4:$C$14,MATCH($C26,'3_UK_L1_Input'!$A$4:$A$14,0))*P26 | V26: =INDEX('5_UK_DefaultRisk_Input'!$D$5:$D$15,MATCH($C26,'5_UK_DefaultRisk_Input'!$A$5:$A$15,0)) | W26: =INDEX('5_UK_DefaultRisk_Input'!$D$20:$D$44,MATCH($E26,'5_UK_DefaultRisk_Input'!$A$20:$A$44,0)) | X26: =INDEX('5_UK_DefaultRisk_Input'!$D$49:$D$122,MATCH($D26,'5_UK_DefaultRisk_Input'!$A$49:$A$122,0)) | Y26: =INDEX('5_UK_DefaultRisk_Input'!$D$127:$D$289,MATCH($A26,'5_UK_DefaultRisk_Input'!$A$127:$A$289,0)) | Z26: =(W26/V26)*(X26/W26)*(Y26/X26) | AA26: =INDEX('3_UK_L1_Input'!$D$4:$D$14,MATCH($C26,'3_UK_L1_Input'!$A$4:$A$14,0))*Z26
A27: 20101010 | B27: Aerospace & Defense | C27: 20 | D27: 201010 | E27: 2010 | F27: 4670000000 | G27: 13.03 | H27: =IFERROR(SUMPRODUCT(($C$3:$C$165=C27)*ISNUMBER($G$3:$G$165)*ISNUMBER($F$3:$F$165)*IF(ISNUMBER($F$3:$F$165),$F$3:$F$165,0)*IF(ISNUMBER($G$3:$G$165),$G$3:$G$165,0))/SUMPRODUCT(($C$3:$C$165=C27)*ISNUMBER($G$3:$G$165)*ISNUMBER($F$3:$F$165)*IF(ISNUMBER($F$3:$F$165),$F$3:$F$165,0)),"") | I27: =IFERROR(SUMPRODUCT(($C$3:$C$165=C27)*ISNUMBER($G$3:$G$165)*IF(ISNUMBER($G$3:$G$165),$G$3:$G$165,0))/SUMPRODUCT(($C$3:$C$165=C27)*ISNUMBER($G$3:$G$165)),"") | J27: =IF(OR(G27="",H27=""),"",G27/H27) | K27: =IF(OR(G27="",I27=""),"",G27/I27) | L27: =INDEX('4_UK_Beta_Input'!$D$5:$D$15,MATCH($C27,'4_UK_Beta_Input'!$A$5:$A$15,0)) | M27: =INDEX('4_UK_Beta_Input'!$D$20:$D$44,MATCH($E27,'4_UK_Beta_Input'!$A$20:$A$44,0)) | N27: =INDEX('4_UK_Beta_Input'!$D$49:$D$122,MATCH($D27,'4_UK_Beta_Input'!$A$49:$A$122,0)) | O27: =INDEX('4_UK_Beta_Input'!$D$127:$D$289,MATCH($A27,'4_UK_Beta_Input'!$A$127:$A$289,0)) | P27: =(M27/L27)*(N27/M27)*(O27/N27) | Q27: =IF(J27="",INDEX('3_UK_L1_Input'!$D$4:$D$14,MATCH($C27,'3_UK_L1_Input'!$A$4:$A$14,0))*P27,INDEX('3_UK_L1_Input'!$D$4:$D$14,MATCH($C27,'3_UK_L1_Input'!$A$4:$A$14,0))*J27) | R27: =IF(K27="",INDEX('3_UK_L1_Input'!$D$4:$D$14,MATCH($C27,'3_UK_L1_Input'!$A$4:$A$14,0))*P27,INDEX('3_UK_L1_Input'!$D$4:$D$14,MATCH($C27,'3_UK_L1_Input'!$A$4:$A$14,0))*K27) | S27: =IF(G27="","BETA CASCADE FALLBACK (dummy — replace with real beta)","REAL (Bloomberg UK)") | T27: =INDEX('3_UK_L1_Input'!$C$4:$C$14,MATCH($C27,'3_UK_L1_Input'!$A$4:$A$14,0)) | U27: =INDEX('3_UK_L1_Input'!$C$4:$C$14,MATCH($C27,'3_UK_L1_Input'!$A$4:$A$14,0))*P27 | V27: =INDEX('5_UK_DefaultRisk_Input'!$D$5:$D$15,MATCH($C27,'5_UK_DefaultRisk_Input'!$A$5:$A$15,0)) | W27: =INDEX('5_UK_DefaultRisk_Input'!$D$20:$D$44,MATCH($E27,'5_UK_DefaultRisk_Input'!$A$20:$A$44,0)) | X27: =INDEX('5_UK_DefaultRisk_Input'!$D$49:$D$122,MATCH($D27,'5_UK_DefaultRisk_Input'!$A$49:$A$122,0)) | Y27: =INDEX('5_UK_DefaultRisk_Input'!$D$127:$D$289,MATCH($A27,'5_UK_DefaultRisk_Input'!$A$127:$A$289,0)) | Z27: =(W27/V27)*(X27/W27)*(Y27/X27) | AA27: =INDEX('3_UK_L1_Input'!$D$4:$D$14,MATCH($C27,'3_UK_L1_Input'!$A$4:$A$14,0))*Z27
A28: 20102010 | B28: Building Products | C28: 20 | D28: 201020 | E28: 2010 | F28: 250880000 | G28: 7.16 | H28: =IFERROR(SUMPRODUCT(($C$3:$C$165=C28)*ISNUMBER($G$3:$G$165)*ISNUMBER($F$3:$F$165)*IF(ISNUMBER($F$3:$F$165),$F$3:$F$165,0)*IF(ISNUMBER($G$3:$G$165),$G$3:$G$165,0))/SUMPRODUCT(($C$3:$C$165=C28)*ISNUMBER($G$3:$G$165)*ISNUMBER($F$3:$F$165)*IF(ISNUMBER($F$3:$F$165),$F$3:$F$165,0)),"") | I28: =IFERROR(SUMPRODUCT(($C$3:$C$165=C28)*ISNUMBER($G$3:$G$165)*IF(ISNUMBER($G$3:$G$165),$G$3:$G$165,0))/SUMPRODUCT(($C$3:$C$165=C28)*ISNUMBER($G$3:$G$165)),"") | J28: =IF(OR(G28="",H28=""),"",G28/H28) | K28: =IF(OR(G28="",I28=""),"",G28/I28) | L28: =INDEX('4_UK_Beta_Input'!$D$5:$D$15,MATCH($C28,'4_UK_Beta_Input'!$A$5:$A$15,0)) | M28: =INDEX('4_UK_Beta_Input'!$D$20:$D$44,MATCH($E28,'4_UK_Beta_Input'!$A$20:$A$44,0)) | N28: =INDEX('4_UK_Beta_Input'!$D$49:$D$122,MATCH($D28,'4_UK_Beta_Input'!$A$49:$A$122,0)) | O28: =INDEX('4_UK_Beta_Input'!$D$127:$D$289,MATCH($A28,'4_UK_Beta_Input'!$A$127:$A$289,0)) | P28: =(M28/L28)*(N28/M28)*(O28/N28) | Q28: =IF(J28="",INDEX('3_UK_L1_Input'!$D$4:$D$14,MATCH($C28,'3_UK_L1_Input'!$A$4:$A$14,0))*P28,INDEX('3_UK_L1_Input'!$D$4:$D$14,MATCH($C28,'3_UK_L1_Input'!$A$4:$A$14,0))*J28) | R28: =IF(K28="",INDEX('3_UK_L1_Input'!$D$4:$D$14,MATCH($C28,'3_UK_L1_Input'!$A$4:$A$14,0))*P28,INDEX('3_UK_L1_Input'!$D$4:$D$14,MATCH($C28,'3_UK_L1_Input'!$A$4:$A$14,0))*K28) | S28: =IF(G28="","BETA CASCADE FALLBACK (dummy — replace with real beta)","REAL (Bloomberg UK)") | T28: =INDEX('3_UK_L1_Input'!$C$4:$C$14,MATCH($C28,'3_UK_L1_Input'!$A$4:$A$14,0)) | U28: =INDEX('3_UK_L1_Input'!$C$4:$C$14,MATCH($C28,'3_UK_L1_Input'!$A$4:$A$14,0))*P28 | V28: =INDEX('5_UK_DefaultRisk_Input'!$D$5:$D$15,MATCH($C28,'5_UK_DefaultRisk_Input'!$A$5:$A$15,0)) | W28: =INDEX('5_UK_DefaultRisk_Input'!$D$20:$D$44,MATCH($E28,'5_UK_DefaultRisk_Input'!$A$20:$A$44,0)) | X28: =INDEX('5_UK_DefaultRisk_Input'!$D$49:$D$122,MATCH($D28,'5_UK_DefaultRisk_Input'!$A$49:$A$122,0)) | Y28: =INDEX('5_UK_DefaultRisk_Input'!$D$127:$D$289,MATCH($A28,'5_UK_DefaultRisk_Input'!$A$127:$A$289,0)) | Z28: =(W28/V28)*(X28/W28)*(Y28/X28) | AA28: =INDEX('3_UK_L1_Input'!$D$4:$D$14,MATCH($C28,'3_UK_L1_Input'!$A$4:$A$14,0))*Z28
A29: 20103010 | B29: Construction & Engineering | C29: 20 | D29: 201030 | E29: 2010 | F29: 1920000000 | G29: 6.91 | H29: =IFERROR(SUMPRODUCT(($C$3:$C$165=C29)*ISNUMBER($G$3:$G$165)*ISNUMBER($F$3:$F$165)*IF(ISNUMBER($F$3:$F$165),$F$3:$F$165,0)*IF(ISNUMBER($G$3:$G$165),$G$3:$G$165,0))/SUMPRODUCT(($C$3:$C$165=C29)*ISNUMBER($G$3:$G$165)*ISNUMBER($F$3:$F$165)*IF(ISNUMBER($F$3:$F$165),$F$3:$F$165,0)),"") | I29: =IFERROR(SUMPRODUCT(($C$3:$C$165=C29)*ISNUMBER($G$3:$G$165)*IF(ISNUMBER($G$3:$G$165),$G$3:$G$165,0))/SUMPRODUCT(($C$3:$C$165=C29)*ISNUMBER($G$3:$G$165)),"") | J29: =IF(OR(G29="",H29=""),"",G29/H29) | K29: =IF(OR(G29="",I29=""),"",G29/I29) | L29: =INDEX('4_UK_Beta_Input'!$D$5:$D$15,MATCH($C29,'4_UK_Beta_Input'!$A$5:$A$15,0)) | M29: =INDEX('4_UK_Beta_Input'!$D$20:$D$44,MATCH($E29,'4_UK_Beta_Input'!$A$20:$A$44,0)) | N29: =INDEX('4_UK_Beta_Input'!$D$49:$D$122,MATCH($D29,'4_UK_Beta_Input'!$A$49:$A$122,0)) | O29: =INDEX('4_UK_Beta_Input'!$D$127:$D$289,MATCH($A29,'4_UK_Beta_Input'!$A$127:$A$289,0)) | P29: =(M29/L29)*(N29/M29)*(O29/N29) | Q29: =IF(J29="",INDEX('3_UK_L1_Input'!$D$4:$D$14,MATCH($C29,'3_UK_L1_Input'!$A$4:$A$14,0))*P29,INDEX('3_UK_L1_Input'!$D$4:$D$14,MATCH($C29,'3_UK_L1_Input'!$A$4:$A$14,0))*J29) | R29: =IF(K29="",INDEX('3_UK_L1_Input'!$D$4:$D$14,MATCH($C29,'3_UK_L1_Input'!$A$4:$A$14,0))*P29,INDEX('3_UK_L1_Input'!$D$4:$D$14,MATCH($C29,'3_UK_L1_Input'!$A$4:$A$14,0))*K29) | S29: =IF(G29="","BETA CASCADE FALLBACK (dummy — replace with real beta)","REAL (Bloomberg UK)") | T29: =INDEX('3_UK_L1_Input'!$C$4:$C$14,MATCH($C29,'3_UK_L1_Input'!$A$4:$A$14,0)) | U29: =INDEX('3_UK_L1_Input'!$C$4:$C$14,MATCH($C29,'3_UK_L1_Input'!$A$4:$A$14,0))*P29 | V29: =INDEX('5_UK_DefaultRisk_Input'!$D$5:$D$15,MATCH($C29,'5_UK_DefaultRisk_Input'!$A$5:$A$15,0)) | W29: =INDEX('5_UK_DefaultRisk_Input'!$D$20:$D$44,MATCH($E29,'5_UK_DefaultRisk_Input'!$A$20:$A$44,0)) | X29: =INDEX('5_UK_DefaultRisk_Input'!$D$49:$D$122,MATCH($D29,'5_UK_DefaultRisk_Input'!$A$49:$A$122,0)) | Y29: =INDEX('5_UK_DefaultRisk_Input'!$D$127:$D$289,MATCH($A29,'5_UK_DefaultRisk_Input'!$A$127:$A$289,0)) | Z29: =(W29/V29)*(X29/W29)*(Y29/X29) | AA29: =INDEX('3_UK_L1_Input'!$D$4:$D$14,MATCH($C29,'3_UK_L1_Input'!$A$4:$A$14,0))*Z29
A30: 20104010 | B30: Electrical Components & Equipment | C30: 20 | D30: 201040 | E30: 2010 | F30: 480480000 | G30: 9.8 | H30: =IFERROR(SUMPRODUCT(($C$3:$C$165=C30)*ISNUMBER($G$3:$G$165)*ISNUMBER($F$3:$F$165)*IF(ISNUMBER($F$3:$F$165),$F$3:$F$165,0)*IF(ISNUMBER($G$3:$G$165),$G$3:$G$165,0))/SUMPRODUCT(($C$3:$C$165=C30)*ISNUMBER($G$3:$G$165)*ISNUMBER($F$3:$F$165)*IF(ISNUMBER($F$3:$F$165),$F$3:$F$165,0)),"") | I30: =IFERROR(SUMPRODUCT(($C$3:$C$165=C30)*ISNUMBER($G$3:$G$165)*IF(ISNUMBER($G$3:$G$165),$G$3:$G$165,0))/SUMPRODUCT(($C$3:$C$165=C30)*ISNUMBER($G$3:$G$165)),"") | J30: =IF(OR(G30="",H30=""),"",G30/H30) | K30: =IF(OR(G30="",I30=""),"",G30/I30) | L30: =INDEX('4_UK_Beta_Input'!$D$5:$D$15,MATCH($C30,'4_UK_Beta_Input'!$A$5:$A$15,0)) | M30: =INDEX('4_UK_Beta_Input'!$D$20:$D$44,MATCH($E30,'4_UK_Beta_Input'!$A$20:$A$44,0)) | N30: =INDEX('4_UK_Beta_Input'!$D$49:$D$122,MATCH($D30,'4_UK_Beta_Input'!$A$49:$A$122,0)) | O30: =INDEX('4_UK_Beta_Input'!$D$127:$D$289,MATCH($A30,'4_UK_Beta_Input'!$A$127:$A$289,0)) | P30: =(M30/L30)*(N30/M30)*(O30/N30) | Q30: =IF(J30="",INDEX('3_UK_L1_Input'!$D$4:$D$14,MATCH($C30,'3_UK_L1_Input'!$A$4:$A$14,0))*P30,INDEX('3_UK_L1_Input'!$D$4:$D$14,MATCH($C30,'3_UK_L1_Input'!$A$4:$A$14,0))*J30) | R30: =IF(K30="",INDEX('3_UK_L1_Input'!$D$4:$D$14,MATCH($C30,'3_UK_L1_Input'!$A$4:$A$14,0))*P30,INDEX('3_UK_L1_Input'!$D$4:$D$14,MATCH($C30,'3_UK_L1_Input'!$A$4:$A$14,0))*K30) | S30: =IF(G30="","BETA CASCADE FALLBACK (dummy — replace with real beta)","REAL (Bloomberg UK)") | T30: =INDEX('3_UK_L1_Input'!$C$4:$C$14,MATCH($C30,'3_UK_L1_Input'!$A$4:$A$14,0)) | U30: =INDEX('3_UK_L1_Input'!$C$4:$C$14,MATCH($C30,'3_UK_L1_Input'!$A$4:$A$14,0))*P30 | V30: =INDEX('5_UK_DefaultRisk_Input'!$D$5:$D$15,MATCH($C30,'5_UK_DefaultRisk_Input'!$A$5:$A$15,0)) | W30: =INDEX('5_UK_DefaultRisk_Input'!$D$20:$D$44,MATCH($E30,'5_UK_DefaultRisk_Input'!$A$20:$A$44,0)) | X30: =INDEX('5_UK_DefaultRisk_Input'!$D$49:$D$122,MATCH($D30,'5_UK_DefaultRisk_Input'!$A$49:$A$122,0)) | Y30: =INDEX('5_UK_DefaultRisk_Input'!$D$127:$D$289,MATCH($A30,'5_UK_DefaultRisk_Input'!$A$127:$A$289,0)) | Z30: =(W30/V30)*(X30/W30)*(Y30/X30) | AA30: =INDEX('3_UK_L1_Input'!$D$4:$D$14,MATCH($C30,'3_UK_L1_Input'!$A$4:$A$14,0))*Z30
A31: 20104020 | B31: Heavy Electrical Equipment | C31: 20 | D31: 201040 | E31: 2010 | F31: 229090000 | G31: 38.05 | H31: =IFERROR(SUMPRODUCT(($C$3:$C$165=C31)*ISNUMBER($G$3:$G$165)*ISNUMBER($F$3:$F$165)*IF(ISNUMBER($F$3:$F$165),$F$3:$F$165,0)*IF(ISNUMBER($G$3:$G$165),$G$3:$G$165,0))/SUMPRODUCT(($C$3:$C$165=C31)*ISNUMBER($G$3:$G$165)*ISNUMBER($F$3:$F$165)*IF(ISNUMBER($F$3:$F$165),$F$3:$F$165,0)),"") | I31: =IFERROR(SUMPRODUCT(($C$3:$C$165=C31)*ISNUMBER($G$3:$G$165)*IF(ISNUMBER($G$3:$G$165),$G$3:$G$165,0))/SUMPRODUCT(($C$3:$C$165=C31)*ISNUMBER($G$3:$G$165)),"") | J31: =IF(OR(G31="",H31=""),"",G31/H31) | K31: =IF(OR(G31="",I31=""),"",G31/I31) | L31: =INDEX('4_UK_Beta_Input'!$D$5:$D$15,MATCH($C31,'4_UK_Beta_Input'!$A$5:$A$15,0)) | M31: =INDEX('4_UK_Beta_Input'!$D$20:$D$44,MATCH($E31,'4_UK_Beta_Input'!$A$20:$A$44,0)) | N31: =INDEX('4_UK_Beta_Input'!$D$49:$D$122,MATCH($D31,'4_UK_Beta_Input'!$A$49:$A$122,0)) | O31: =INDEX('4_UK_Beta_Input'!$D$127:$D$289,MATCH($A31,'4_UK_Beta_Input'!$A$127:$A$289,0)) | P31: =(M31/L31)*(N31/M31)*(O31/N31) | Q31: =IF(J31="",INDEX('3_UK_L1_Input'!$D$4:$D$14,MATCH($C31,'3_UK_L1_Input'!$A$4:$A$14,0))*P31,INDEX('3_UK_L1_Input'!$D$4:$D$14,MATCH($C31,'3_UK_L1_Input'!$A$4:$A$14,0))*J31) | R31: =IF(K31="",INDEX('3_UK_L1_Input'!$D$4:$D$14,MATCH($C31,'3_UK_L1_Input'!$A$4:$A$14,0))*P31,INDEX('3_UK_L1_Input'!$D$4:$D$14,MATCH($C31,'3_UK_L1_Input'!$A$4:$A$14,0))*K31) | S31: =IF(G31="","BETA CASCADE FALLBACK (dummy — replace with real beta)","REAL (Bloomberg UK)") | T31: =INDEX('3_UK_L1_Input'!$C$4:$C$14,MATCH($C31,'3_UK_L1_Input'!$A$4:$A$14,0)) | U31: =INDEX('3_UK_L1_Input'!$C$4:$C$14,MATCH($C31,'3_UK_L1_Input'!$A$4:$A$14,0))*P31 | V31: =INDEX('5_UK_DefaultRisk_Input'!$D$5:$D$15,MATCH($C31,'5_UK_DefaultRisk_Input'!$A$5:$A$15,0)) | W31: =INDEX('5_UK_DefaultRisk_Input'!$D$20:$D$44,MATCH($E31,'5_UK_DefaultRisk_Input'!$A$20:$A$44,0)) | X31: =INDEX('5_UK_DefaultRisk_Input'!$D$49:$D$122,MATCH($D31,'5_UK_DefaultRisk_Input'!$A$49:$A$122,0)) | Y31: =INDEX('5_UK_DefaultRisk_Input'!$D$127:$D$289,MATCH($A31,'5_UK_DefaultRisk_Input'!$A$127:$A$289,0)) | Z31: =(W31/V31)*(X31/W31)*(Y31/X31) | AA31: =INDEX('3_UK_L1_Input'!$D$4:$D$14,MATCH($C31,'3_UK_L1_Input'!$A$4:$A$14,0))*Z31
A32: 20105010 | B32: Industrial Conglomerates | C32: 20 | D32: 201050 | E32: 2010 | F32: 1130000000 | G32: 12.91 | H32: =IFERROR(SUMPRODUCT(($C$3:$C$165=C32)*ISNUMBER($G$3:$G$165)*ISNUMBER($F$3:$F$165)*IF(ISNUMBER($F$3:$F$165),$F$3:$F$165,0)*IF(ISNUMBER($G$3:$G$165),$G$3:$G$165,0))/SUMPRODUCT(($C$3:$C$165=C32)*ISNUMBER($G$3:$G$165)*ISNUMBER($F$3:$F$165)*IF(ISNUMBER($F$3:$F$165),$F$3:$F$165,0)),"") | I32: =IFERROR(SUMPRODUCT(($C$3:$C$165=C32)*ISNUMBER($G$3:$G$165)*IF(ISNUMBER($G$3:$G$165),$G$3:$G$165,0))/SUMPRODUCT(($C$3:$C$165=C32)*ISNUMBER($G$3:$G$165)),"") | J32: =IF(OR(G32="",H32=""),"",G32/H32) | K32: =IF(OR(G32="",I32=""),"",G32/I32) | L32: =INDEX('4_UK_Beta_Input'!$D$5:$D$15,MATCH($C32,'4_UK_Beta_Input'!$A$5:$A$15,0)) | M32: =INDEX('4_UK_Beta_Input'!$D$20:$D$44,MATCH($E32,'4_UK_Beta_Input'!$A$20:$A$44,0)) | N32: =INDEX('4_UK_Beta_Input'!$D$49:$D$122,MATCH($D32,'4_UK_Beta_Input'!$A$49:$A$122,0)) | O32: =INDEX('4_UK_Beta_Input'!$D$127:$D$289,MATCH($A32,'4_UK_Beta_Input'!$A$127:$A$289,0)) | P32: =(M32/L32)*(N32/M32)*(O32/N32) | Q32: =IF(J32="",INDEX('3_UK_L1_Input'!$D$4:$D$14,MATCH($C32,'3_UK_L1_Input'!$A$4:$A$14,0))*P32,INDEX('3_UK_L1_Input'!$D$4:$D$14,MATCH($C32,'3_UK_L1_Input'!$A$4:$A$14,0))*J32) | R32: =IF(K32="",INDEX('3_UK_L1_Input'!$D$4:$D$14,MATCH($C32,'3_UK_L1_Input'!$A$4:$A$14,0))*P32,INDEX('3_UK_L1_Input'!$D$4:$D$14,MATCH($C32,'3_UK_L1_Input'!$A$4:$A$14,0))*K32) | S32: =IF(G32="","BETA CASCADE FALLBACK (dummy — replace with real beta)","REAL (Bloomberg UK)") | T32: =INDEX('3_UK_L1_Input'!$C$4:$C$14,MATCH($C32,'3_UK_L1_Input'!$A$4:$A$14,0)) | U32: =INDEX('3_UK_L1_Input'!$C$4:$C$14,MATCH($C32,'3_UK_L1_Input'!$A$4:$A$14,0))*P32 | V32: =INDEX('5_UK_DefaultRisk_Input'!$D$5:$D$15,MATCH($C32,'5_UK_DefaultRisk_Input'!$A$5:$A$15,0)) | W32: =INDEX('5_UK_DefaultRisk_Input'!$D$20:$D$44,MATCH($E32,'5_UK_DefaultRisk_Input'!$A$20:$A$44,0)) | X32: =INDEX('5_UK_DefaultRisk_Input'!$D$49:$D$122,MATCH($D32,'5_UK_DefaultRisk_Input'!$A$49:$A$122,0)) | Y32: =INDEX('5_UK_DefaultRisk_Input'!$D$127:$D$289,MATCH($A32,'5_UK_DefaultRisk_Input'!$A$127:$A$289,0)) | Z32: =(W32/V32)*(X32/W32)*(Y32/X32) | AA32: =INDEX('3_UK_L1_Input'!$D$4:$D$14,MATCH($C32,'3_UK_L1_Input'!$A$4:$A$14,0))*Z32
A33: 20106010 | B33: Construction Machinery & Heavy Transportation Equipment | C33: 20 | D33: 201060 | E33: 2010 | H33: =IFERROR(SUMPRODUCT(($C$3:$C$165=C33)*ISNUMBER($G$3:$G$165)*ISNUMBER($F$3:$F$165)*IF(ISNUMBER($F$3:$F$165),$F$3:$F$165,0)*IF(ISNUMBER($G$3:$G$165),$G$3:$G$165,0))/SUMPRODUCT(($C$3:$C$165=C33)*ISNUMBER($G$3:$G$165)*ISNUMBER($F$3:$F$165)*IF(ISNUMBER($F$3:$F$165),$F$3:$F$165,0)),"") | I33: =IFERROR(SUMPRODUCT(($C$3:$C$165=C33)*ISNUMBER($G$3:$G$165)*IF(ISNUMBER($G$3:$G$165),$G$3:$G$165,0))/SUMPRODUCT(($C$3:$C$165=C33)*ISNUMBER($G$3:$G$165)),"") | J33: =IF(OR(G33="",H33=""),"",G33/H33) | K33: =IF(OR(G33="",I33=""),"",G33/I33) | L33: =INDEX('4_UK_Beta_Input'!$D$5:$D$15,MATCH($C33,'4_UK_Beta_Input'!$A$5:$A$15,0)) | M33: =INDEX('4_UK_Beta_Input'!$D$20:$D$44,MATCH($E33,'4_UK_Beta_Input'!$A$20:$A$44,0)) | N33: =INDEX('4_UK_Beta_Input'!$D$49:$D$122,MATCH($D33,'4_UK_Beta_Input'!$A$49:$A$122,0)) | O33: =INDEX('4_UK_Beta_Input'!$D$127:$D$289,MATCH($A33,'4_UK_Beta_Input'!$A$127:$A$289,0)) | P33: =(M33/L33)*(N33/M33)*(O33/N33) | Q33: =IF(J33="",INDEX('3_UK_L1_Input'!$D$4:$D$14,MATCH($C33,'3_UK_L1_Input'!$A$4:$A$14,0))*P33,INDEX('3_UK_L1_Input'!$D$4:$D$14,MATCH($C33,'3_UK_L1_Input'!$A$4:$A$14,0))*J33) | R33: =IF(K33="",INDEX('3_UK_L1_Input'!$D$4:$D$14,MATCH($C33,'3_UK_L1_Input'!$A$4:$A$14,0))*P33,INDEX('3_UK_L1_Input'!$D$4:$D$14,MATCH($C33,'3_UK_L1_Input'!$A$4:$A$14,0))*K33) | S33: =IF(G33="","BETA CASCADE FALLBACK (dummy — replace with real beta)","REAL (Bloomberg UK)") | T33: =INDEX('3_UK_L1_Input'!$C$4:$C$14,MATCH($C33,'3_UK_L1_Input'!$A$4:$A$14,0)) | U33: =INDEX('3_UK_L1_Input'!$C$4:$C$14,MATCH($C33,'3_UK_L1_Input'!$A$4:$A$14,0))*P33 | V33: =INDEX('5_UK_DefaultRisk_Input'!$D$5:$D$15,MATCH($C33,'5_UK_DefaultRisk_Input'!$A$5:$A$15,0)) | W33: =INDEX('5_UK_DefaultRisk_Input'!$D$20:$D$44,MATCH($E33,'5_UK_DefaultRisk_Input'!$A$20:$A$44,0)) | X33: =INDEX('5_UK_DefaultRisk_Input'!$D$49:$D$122,MATCH($D33,'5_UK_DefaultRisk_Input'!$A$49:$A$122,0)) | Y33: =INDEX('5_UK_DefaultRisk_Input'!$D$127:$D$289,MATCH($A33,'5_UK_DefaultRisk_Input'!$A$127:$A$289,0)) | Z33: =(W33/V33)*(X33/W33)*(Y33/X33) | AA33: =INDEX('3_UK_L1_Input'!$D$4:$D$14,MATCH($C33,'3_UK_L1_Input'!$A$4:$A$14,0))*Z33
A34: 20106015 | B34: Agricultural & Farm Machinery | C34: 20 | D34: 201060 | E34: 2010 | F34: 18180000000 | G34: 27.38 | H34: =IFERROR(SUMPRODUCT(($C$3:$C$165=C34)*ISNUMBER($G$3:$G$165)*ISNUMBER($F$3:$F$165)*IF(ISNUMBER($F$3:$F$165),$F$3:$F$165,0)*IF(ISNUMBER($G$3:$G$165),$G$3:$G$165,0))/SUMPRODUCT(($C$3:$C$165=C34)*ISNUMBER($G$3:$G$165)*ISNUMBER($F$3:$F$165)*IF(ISNUMBER($F$3:$F$165),$F$3:$F$165,0)),"") | I34: =IFERROR(SUMPRODUCT(($C$3:$C$165=C34)*ISNUMBER($G$3:$G$165)*IF(ISNUMBER($G$3:$G$165),$G$3:$G$165,0))/SUMPRODUCT(($C$3:$C$165=C34)*ISNUMBER($G$3:$G$165)),"") | J34: =IF(OR(G34="",H34=""),"",G34/H34) | K34: =IF(OR(G34="",I34=""),"",G34/I34) | L34: =INDEX('4_UK_Beta_Input'!$D$5:$D$15,MATCH($C34,'4_UK_Beta_Input'!$A$5:$A$15,0)) | M34: =INDEX('4_UK_Beta_Input'!$D$20:$D$44,MATCH($E34,'4_UK_Beta_Input'!$A$20:$A$44,0)) | N34: =INDEX('4_UK_Beta_Input'!$D$49:$D$122,MATCH($D34,'4_UK_Beta_Input'!$A$49:$A$122,0)) | O34: =INDEX('4_UK_Beta_Input'!$D$127:$D$289,MATCH($A34,'4_UK_Beta_Input'!$A$127:$A$289,0)) | P34: =(M34/L34)*(N34/M34)*(O34/N34) | Q34: =IF(J34="",INDEX('3_UK_L1_Input'!$D$4:$D$14,MATCH($C34,'3_UK_L1_Input'!$A$4:$A$14,0))*P34,INDEX('3_UK_L1_Input'!$D$4:$D$14,MATCH($C34,'3_UK_L1_Input'!$A$4:$A$14,0))*J34) | R34: =IF(K34="",INDEX('3_UK_L1_Input'!$D$4:$D$14,MATCH($C34,'3_UK_L1_Input'!$A$4:$A$14,0))*P34,INDEX('3_UK_L1_Input'!$D$4:$D$14,MATCH($C34,'3_UK_L1_Input'!$A$4:$A$14,0))*K34) | S34: =IF(G34="","BETA CASCADE FALLBACK (dummy — replace with real beta)","REAL (Bloomberg UK)") | T34: =INDEX('3_UK_L1_Input'!$C$4:$C$14,MATCH($C34,'3_UK_L1_Input'!$A$4:$A$14,0)) | U34: =INDEX('3_UK_L1_Input'!$C$4:$C$14,MATCH($C34,'3_UK_L1_Input'!$A$4:$A$14,0))*P34 | V34: =INDEX('5_UK_DefaultRisk_Input'!$D$5:$D$15,MATCH($C34,'5_UK_DefaultRisk_Input'!$A$5:$A$15,0)) | W34: =INDEX('5_UK_DefaultRisk_Input'!$D$20:$D$44,MATCH($E34,'5_UK_DefaultRisk_Input'!$A$20:$A$44,0)) | X34: =INDEX('5_UK_DefaultRisk_Input'!$D$49:$D$122,MATCH($D34,'5_UK_DefaultRisk_Input'!$A$49:$A$122,0)) | Y34: =INDEX('5_UK_DefaultRisk_Input'!$D$127:$D$289,MATCH($A34,'5_UK_DefaultRisk_Input'!$A$127:$A$289,0)) | Z34: =(W34/V34)*(X34/W34)*(Y34/X34) | AA34: =INDEX('3_UK_L1_Input'!$D$4:$D$14,MATCH($C34,'3_UK_L1_Input'!$A$4:$A$14,0))*Z34
A35: 20106020 | B35: Industrial Machinery & Supplies & Components | C35: 20 | D35: 201060 | E35: 2010 | F35: 966980000 | G35: 10.77 | H35: =IFERROR(SUMPRODUCT(($C$3:$C$165=C35)*ISNUMBER($G$3:$G$165)*ISNUMBER($F$3:$F$165)*IF(ISNUMBER($F$3:$F$165),$F$3:$F$165,0)*IF(ISNUMBER($G$3:$G$165),$G$3:$G$165,0))/SUMPRODUCT(($C$3:$C$165=C35)*ISNUMBER($G$3:$G$165)*ISNUMBER($F$3:$F$165)*IF(ISNUMBER($F$3:$F$165),$F$3:$F$165,0)),"") | I35: =IFERROR(SUMPRODUCT(($C$3:$C$165=C35)*ISNUMBER($G$3:$G$165)*IF(ISNUMBER($G$3:$G$165),$G$3:$G$165,0))/SUMPRODUCT(($C$3:$C$165=C35)*ISNUMBER($G$3:$G$165)),"") | J35: =IF(OR(G35="",H35=""),"",G35/H35) | K35: =IF(OR(G35="",I35=""),"",G35/I35) | L35: =INDEX('4_UK_Beta_Input'!$D$5:$D$15,MATCH($C35,'4_UK_Beta_Input'!$A$5:$A$15,0)) | M35: =INDEX('4_UK_Beta_Input'!$D$20:$D$44,MATCH($E35,'4_UK_Beta_Input'!$A$20:$A$44,0)) | N35: =INDEX('4_UK_Beta_Input'!$D$49:$D$122,MATCH($D35,'4_UK_Beta_Input'!$A$49:$A$122,0)) | O35: =INDEX('4_UK_Beta_Input'!$D$127:$D$289,MATCH($A35,'4_UK_Beta_Input'!$A$127:$A$289,0)) | P35: =(M35/L35)*(N35/M35)*(O35/N35) | Q35: =IF(J35="",INDEX('3_UK_L1_Input'!$D$4:$D$14,MATCH($C35,'3_UK_L1_Input'!$A$4:$A$14,0))*P35,INDEX('3_UK_L1_Input'!$D$4:$D$14,MATCH($C35,'3_UK_L1_Input'!$A$4:$A$14,0))*J35) | R35: =IF(K35="",INDEX('3_UK_L1_Input'!$D$4:$D$14,MATCH($C35,'3_UK_L1_Input'!$A$4:$A$14,0))*P35,INDEX('3_UK_L1_Input'!$D$4:$D$14,MATCH($C35,'3_UK_L1_Input'!$A$4:$A$14,0))*K35) | S35: =IF(G35="","BETA CASCADE FALLBACK (dummy — replace with real beta)","REAL (Bloomberg UK)") | T35: =INDEX('3_UK_L1_Input'!$C$4:$C$14,MATCH($C35,'3_UK_L1_Input'!$A$4:$A$14,0)) | U35: =INDEX('3_UK_L1_Input'!$C$4:$C$14,MATCH($C35,'3_UK_L1_Input'!$A$4:$A$14,0))*P35 | V35: =INDEX('5_UK_DefaultRisk_Input'!$D$5:$D$15,MATCH($C35,'5_UK_DefaultRisk_Input'!$A$5:$A$15,0)) | W35: =INDEX('5_UK_DefaultRisk_Input'!$D$20:$D$44,MATCH($E35,'5_UK_DefaultRisk_Input'!$A$20:$A$44,0)) | X35: =INDEX('5_UK_DefaultRisk_Input'!$D$49:$D$122,MATCH($D35,'5_UK_DefaultRisk_Input'!$A$49:$A$122,0)) | Y35: =INDEX('5_UK_DefaultRisk_Input'!$D$127:$D$289,MATCH($A35,'5_UK_DefaultRisk_Input'!$A$127:$A$289,0)) | Z35: =(W35/V35)*(X35/W35)*(Y35/X35) | AA35: =INDEX('3_UK_L1_Input'!$D$4:$D$14,MATCH($C35,'3_UK_L1_Input'!$A$4:$A$14,0))*Z35
A36: 20107010 | B36: Trading Companies & Distributors | C36: 20 | D36: 201070 | E36: 2010 | F36: 1710000000 | G36: 7.57 | H36: =IFERROR(SUMPRODUCT(($C$3:$C$165=C36)*ISNUMBER($G$3:$G$165)*ISNUMBER($F$3:$F$165)*IF(ISNUMBER($F$3:$F$165),$F$3:$F$165,0)*IF(ISNUMBER($G$3:$G$165),$G$3:$G$165,0))/SUMPRODUCT(($C$3:$C$165=C36)*ISNUMBER($G$3:$G$165)*ISNUMBER($F$3:$F$165)*IF(ISNUMBER($F$3:$F$165),$F$3:$F$165,0)),"") | I36: =IFERROR(SUMPRODUCT(($C$3:$C$165=C36)*ISNUMBER($G$3:$G$165)*IF(ISNUMBER($G$3:$G$165),$G$3:$G$165,0))/SUMPRODUCT(($C$3:$C$165=C36)*ISNUMBER($G$3:$G$165)),"") | J36: =IF(OR(G36="",H36=""),"",G36/H36) | K36: =IF(OR(G36="",I36=""),"",G36/I36) | L36: =INDEX('4_UK_Beta_Input'!$D$5:$D$15,MATCH($C36,'4_UK_Beta_Input'!$A$5:$A$15,0)) | M36: =INDEX('4_UK_Beta_Input'!$D$20:$D$44,MATCH($E36,'4_UK_Beta_Input'!$A$20:$A$44,0)) | N36: =INDEX('4_UK_Beta_Input'!$D$49:$D$122,MATCH($D36,'4_UK_Beta_Input'!$A$49:$A$122,0)) | O36: =INDEX('4_UK_Beta_Input'!$D$127:$D$289,MATCH($A36,'4_UK_Beta_Input'!$A$127:$A$289,0)) | P36: =(M36/L36)*(N36/M36)*(O36/N36) | Q36: =IF(J36="",INDEX('3_UK_L1_Input'!$D$4:$D$14,MATCH($C36,'3_UK_L1_Input'!$A$4:$A$14,0))*P36,INDEX('3_UK_L1_Input'!$D$4:$D$14,MATCH($C36,'3_UK_L1_Input'!$A$4:$A$14,0))*J36) | R36: =IF(K36="",INDEX('3_UK_L1_Input'!$D$4:$D$14,MATCH($C36,'3_UK_L1_Input'!$A$4:$A$14,0))*P36,INDEX('3_UK_L1_Input'!$D$4:$D$14,MATCH($C36,'3_UK_L1_Input'!$A$4:$A$14,0))*K36) | S36: =IF(G36="","BETA CASCADE FALLBACK (dummy — replace with real beta)","REAL (Bloomberg UK)") | T36: =INDEX('3_UK_L1_Input'!$C$4:$C$14,MATCH($C36,'3_UK_L1_Input'!$A$4:$A$14,0)) | U36: =INDEX('3_UK_L1_Input'!$C$4:$C$14,MATCH($C36,'3_UK_L1_Input'!$A$4:$A$14,0))*P36 | V36: =INDEX('5_UK_DefaultRisk_Input'!$D$5:$D$15,MATCH($C36,'5_UK_DefaultRisk_Input'!$A$5:$A$15,0)) | W36: =INDEX('5_UK_DefaultRisk_Input'!$D$20:$D$44,MATCH($E36,'5_UK_DefaultRisk_Input'!$A$20:$A$44,0)) | X36: =INDEX('5_UK_DefaultRisk_Input'!$D$49:$D$122,MATCH($D36,'5_UK_DefaultRisk_Input'!$A$49:$A$122,0)) | Y36: =INDEX('5_UK_DefaultRisk_Input'!$D$127:$D$289,MATCH($A36,'5_UK_DefaultRisk_Input'!$A$127:$A$289,0)) | Z36: =(W36/V36)*(X36/W36)*(Y36/X36) | AA36: =INDEX('3_UK_L1_Input'!$D$4:$D$14,MATCH($C36,'3_UK_L1_Input'!$A$4:$A$14,0))*Z36
A37: 20201010 | B37: Commercial Printing | C37: 20 | D37: 202010 | E37: 2020 | F37: 22260000 | H37: =IFERROR(SUMPRODUCT(($C$3:$C$165=C37)*ISNUMBER($G$3:$G$165)*ISNUMBER($F$3:$F$165)*IF(ISNUMBER($F$3:$F$165),$F$3:$F$165,0)*IF(ISNUMBER($G$3:$G$165),$G$3:$G$165,0))/SUMPRODUCT(($C$3:$C$165=C37)*ISNUMBER($G$3:$G$165)*ISNUMBER($F$3:$F$165)*IF(ISNUMBER($F$3:$F$165),$F$3:$F$165,0)),"") | I37: =IFERROR(SUMPRODUCT(($C$3:$C$165=C37)*ISNUMBER($G$3:$G$165)*IF(ISNUMBER($G$3:$G$165),$G$3:$G$165,0))/SUMPRODUCT(($C$3:$C$165=C37)*ISNUMBER($G$3:$G$165)),"") | J37: =IF(OR(G37="",H37=""),"",G37/H37) | K37: =IF(OR(G37="",I37=""),"",G37/I37) | L37: =INDEX('4_UK_Beta_Input'!$D$5:$D$15,MATCH($C37,'4_UK_Beta_Input'!$A$5:$A$15,0)) | M37: =INDEX('4_UK_Beta_Input'!$D$20:$D$44,MATCH($E37,'4_UK_Beta_Input'!$A$20:$A$44,0)) | N37: =INDEX('4_UK_Beta_Input'!$D$49:$D$122,MATCH($D37,'4_UK_Beta_Input'!$A$49:$A$122,0)) | O37: =INDEX('4_UK_Beta_Input'!$D$127:$D$289,MATCH($A37,'4_UK_Beta_Input'!$A$127:$A$289,0)) | P37: =(M37/L37)*(N37/M37)*(O37/N37) | Q37: =IF(J37="",INDEX('3_UK_L1_Input'!$D$4:$D$14,MATCH($C37,'3_UK_L1_Input'!$A$4:$A$14,0))*P37,INDEX('3_UK_L1_Input'!$D$4:$D$14,MATCH($C37,'3_UK_L1_Input'!$A$4:$A$14,0))*J37) | R37: =IF(K37="",INDEX('3_UK_L1_Input'!$D$4:$D$14,MATCH($C37,'3_UK_L1_Input'!$A$4:$A$14,0))*P37,INDEX('3_UK_L1_Input'!$D$4:$D$14,MATCH($C37,'3_UK_L1_Input'!$A$4:$A$14,0))*K37) | S37: =IF(G37="","BETA CASCADE FALLBACK (dummy — replace with real beta)","REAL (Bloomberg UK)") | T37: =INDEX('3_UK_L1_Input'!$C$4:$C$14,MATCH($C37,'3_UK_L1_Input'!$A$4:$A$14,0)) | U37: =INDEX('3_UK_L1_Input'!$C$4:$C$14,MATCH($C37,'3_UK_L1_Input'!$A$4:$A$14,0))*P37 | V37: =INDEX('5_UK_DefaultRisk_Input'!$D$5:$D$15,MATCH($C37,'5_UK_DefaultRisk_Input'!$A$5:$A$15,0)) | W37: =INDEX('5_UK_DefaultRisk_Input'!$D$20:$D$44,MATCH($E37,'5_UK_DefaultRisk_Input'!$A$20:$A$44,0)) | X37: =INDEX('5_UK_DefaultRisk_Input'!$D$49:$D$122,MATCH($D37,'5_UK_DefaultRisk_Input'!$A$49:$A$122,0)) | Y37: =INDEX('5_UK_DefaultRisk_Input'!$D$127:$D$289,MATCH($A37,'5_UK_DefaultRisk_Input'!$A$127:$A$289,0)) | Z37: =(W37/V37)*(X37/W37)*(Y37/X37) | AA37: =INDEX('3_UK_L1_Input'!$D$4:$D$14,MATCH($C37,'3_UK_L1_Input'!$A$4:$A$14,0))*Z37
A38: 20201050 | B38: Environmental & Facilities Services | C38: 20 | D38: 202010 | E38: 2020 | F38: 2970000000 | G38: 8.34 | H38: =IFERROR(SUMPRODUCT(($C$3:$C$165=C38)*ISNUMBER($G$3:$G$165)*ISNUMBER($F$3:$F$165)*IF(ISNUMBER($F$3:$F$165),$F$3:$F$165,0)*IF(ISNUMBER($G$3:$G$165),$G$3:$G$165,0))/SUMPRODUCT(($C$3:$C$165=C38)*ISNUMBER($G$3:$G$165)*ISNUMBER($F$3:$F$165)*IF(ISNUMBER($F$3:$F$165),$F$3:$F$165,0)),"") | I38: =IFERROR(SUMPRODUCT(($C$3:$C$165=C38)*ISNUMBER($G$3:$G$165)*IF(ISNUMBER($G$3:$G$165),$G$3:$G$165,0))/SUMPRODUCT(($C$3:$C$165=C38)*ISNUMBER($G$3:$G$165)),"") | J38: =IF(OR(G38="",H38=""),"",G38/H38) | K38: =IF(OR(G38="",I38=""),"",G38/I38) | L38: =INDEX('4_UK_Beta_Input'!$D$5:$D$15,MATCH($C38,'4_UK_Beta_Input'!$A$5:$A$15,0)) | M38: =INDEX('4_UK_Beta_Input'!$D$20:$D$44,MATCH($E38,'4_UK_Beta_Input'!$A$20:$A$44,0)) | N38: =INDEX('4_UK_Beta_Input'!$D$49:$D$122,MATCH($D38,'4_UK_Beta_Input'!$A$49:$A$122,0)) | O38: =INDEX('4_UK_Beta_Input'!$D$127:$D$289,MATCH($A38,'4_UK_Beta_Input'!$A$127:$A$289,0)) | P38: =(M38/L38)*(N38/M38)*(O38/N38) | Q38: =IF(J38="",INDEX('3_UK_L1_Input'!$D$4:$D$14,MATCH($C38,'3_UK_L1_Input'!$A$4:$A$14,0))*P38,INDEX('3_UK_L1_Input'!$D$4:$D$14,MATCH($C38,'3_UK_L1_Input'!$A$4:$A$14,0))*J38) | R38: =IF(K38="",INDEX('3_UK_L1_Input'!$D$4:$D$14,MATCH($C38,'3_UK_L1_Input'!$A$4:$A$14,0))*P38,INDEX('3_UK_L1_Input'!$D$4:$D$14,MATCH($C38,'3_UK_L1_Input'!$A$4:$A$14,0))*K38) | S38: =IF(G38="","BETA CASCADE FALLBACK (dummy — replace with real beta)","REAL (Bloomberg UK)") | T38: =INDEX('3_UK_L1_Input'!$C$4:$C$14,MATCH($C38,'3_UK_L1_Input'!$A$4:$A$14,0)) | U38: =INDEX('3_UK_L1_Input'!$C$4:$C$14,MATCH($C38,'3_UK_L1_Input'!$A$4:$A$14,0))*P38 | V38: =INDEX('5_UK_DefaultRisk_Input'!$D$5:$D$15,MATCH($C38,'5_UK_DefaultRisk_Input'!$A$5:$A$15,0)) | W38: =INDEX('5_UK_DefaultRisk_Input'!$D$20:$D$44,MATCH($E38,'5_UK_DefaultRisk_Input'!$A$20:$A$44,0)) | X38: =INDEX('5_UK_DefaultRisk_Input'!$D$49:$D$122,MATCH($D38,'5_UK_DefaultRisk_Input'!$A$49:$A$122,0)) | Y38: =INDEX('5_UK_DefaultRisk_Input'!$D$127:$D$289,MATCH($A38,'5_UK_DefaultRisk_Input'!$A$127:$A$289,0)) | Z38: =(W38/V38)*(X38/W38)*(Y38/X38) | AA38: =INDEX('3_UK_L1_Input'!$D$4:$D$14,MATCH($C38,'3_UK_L1_Input'!$A$4:$A$14,0))*Z38
A39: 20201060 | B39: Office Services & Supplies | C39: 20 | D39: 202010 | E39: 2020 | H39: =IFERROR(SUMPRODUCT(($C$3:$C$165=C39)*ISNUMBER($G$3:$G$165)*ISNUMBER($F$3:$F$165)*IF(ISNUMBER($F$3:$F$165),$F$3:$F$165,0)*IF(ISNUMBER($G$3:$G$165),$G$3:$G$165,0))/SUMPRODUCT(($C$3:$C$165=C39)*ISNUMBER($G$3:$G$165)*ISNUMBER($F$3:$F$165)*IF(ISNUMBER($F$3:$F$165),$F$3:$F$165,0)),"") | I39: =IFERROR(SUMPRODUCT(($C$3:$C$165=C39)*ISNUMBER($G$3:$G$165)*IF(ISNUMBER($G$3:$G$165),$G$3:$G$165,0))/SUMPRODUCT(($C$3:$C$165=C39)*ISNUMBER($G$3:$G$165)),"") | J39: =IF(OR(G39="",H39=""),"",G39/H39) | K39: =IF(OR(G39="",I39=""),"",G39/I39) | L39: =INDEX('4_UK_Beta_Input'!$D$5:$D$15,MATCH($C39,'4_UK_Beta_Input'!$A$5:$A$15,0)) | M39: =INDEX('4_UK_Beta_Input'!$D$20:$D$44,MATCH($E39,'4_UK_Beta_Input'!$A$20:$A$44,0)) | N39: =INDEX('4_UK_Beta_Input'!$D$49:$D$122,MATCH($D39,'4_UK_Beta_Input'!$A$49:$A$122,0)) | O39: =INDEX('4_UK_Beta_Input'!$D$127:$D$289,MATCH($A39,'4_UK_Beta_Input'!$A$127:$A$289,0)) | P39: =(M39/L39)*(N39/M39)*(O39/N39) | Q39: =IF(J39="",INDEX('3_UK_L1_Input'!$D$4:$D$14,MATCH($C39,'3_UK_L1_Input'!$A$4:$A$14,0))*P39,INDEX('3_UK_L1_Input'!$D$4:$D$14,MATCH($C39,'3_UK_L1_Input'!$A$4:$A$14,0))*J39) | R39: =IF(K39="",INDEX('3_UK_L1_Input'!$D$4:$D$14,MATCH($C39,'3_UK_L1_Input'!$A$4:$A$14,0))*P39,INDEX('3_UK_L1_Input'!$D$4:$D$14,MATCH($C39,'3_UK_L1_Input'!$A$4:$A$14,0))*K39) | S39: =IF(G39="","BETA CASCADE FALLBACK (dummy — replace with real beta)","REAL (Bloomberg UK)") | T39: =INDEX('3_UK_L1_Input'!$C$4:$C$14,MATCH($C39,'3_UK_L1_Input'!$A$4:$A$14,0)) | U39: =INDEX('3_UK_L1_Input'!$C$4:$C$14,MATCH($C39,'3_UK_L1_Input'!$A$4:$A$14,0))*P39 | V39: =INDEX('5_UK_DefaultRisk_Input'!$D$5:$D$15,MATCH($C39,'5_UK_DefaultRisk_Input'!$A$5:$A$15,0)) | W39: =INDEX('5_UK_DefaultRisk_Input'!$D$20:$D$44,MATCH($E39,'5_UK_DefaultRisk_Input'!$A$20:$A$44,0)) | X39: =INDEX('5_UK_DefaultRisk_Input'!$D$49:$D$122,MATCH($D39,'5_UK_DefaultRisk_Input'!$A$49:$A$122,0)) | Y39: =INDEX('5_UK_DefaultRisk_Input'!$D$127:$D$289,MATCH($A39,'5_UK_DefaultRisk_Input'!$A$127:$A$289,0)) | Z39: =(W39/V39)*(X39/W39)*(Y39/X39) | AA39: =INDEX('3_UK_L1_Input'!$D$4:$D$14,MATCH($C39,'3_UK_L1_Input'!$A$4:$A$14,0))*Z39
A40: 20201070 | B40: Diversified Support Services | C40: 20 | D40: 202010 | E40: 2020 | F40: 272250000 | G40: 5.61 | H40: =IFERROR(SUMPRODUCT(($C$3:$C$165=C40)*ISNUMBER($G$3:$G$165)*ISNUMBER($F$3:$F$165)*IF(ISNUMBER($F$3:$F$165),$F$3:$F$165,0)*IF(ISNUMBER($G$3:$G$165),$G$3:$G$165,0))/SUMPRODUCT(($C$3:$C$165=C40)*ISNUMBER($G$3:$G$165)*ISNUMBER($F$3:$F$165)*IF(ISNUMBER($F$3:$F$165),$F$3:$F$165,0)),"") | I40: =IFERROR(SUMPRODUCT(($C$3:$C$165=C40)*ISNUMBER($G$3:$G$165)*IF(ISNUMBER($G$3:$G$165),$G$3:$G$165,0))/SUMPRODUCT(($C$3:$C$165=C40)*ISNUMBER($G$3:$G$165)),"") | J40: =IF(OR(G40="",H40=""),"",G40/H40) | K40: =IF(OR(G40="",I40=""),"",G40/I40) | L40: =INDEX('4_UK_Beta_Input'!$D$5:$D$15,MATCH($C40,'4_UK_Beta_Input'!$A$5:$A$15,0)) | M40: =INDEX('4_UK_Beta_Input'!$D$20:$D$44,MATCH($E40,'4_UK_Beta_Input'!$A$20:$A$44,0)) | N40: =INDEX('4_UK_Beta_Input'!$D$49:$D$122,MATCH($D40,'4_UK_Beta_Input'!$A$49:$A$122,0)) | O40: =INDEX('4_UK_Beta_Input'!$D$127:$D$289,MATCH($A40,'4_UK_Beta_Input'!$A$127:$A$289,0)) | P40: =(M40/L40)*(N40/M40)*(O40/N40) | Q40: =IF(J40="",INDEX('3_UK_L1_Input'!$D$4:$D$14,MATCH($C40,'3_UK_L1_Input'!$A$4:$A$14,0))*P40,INDEX('3_UK_L1_Input'!$D$4:$D$14,MATCH($C40,'3_UK_L1_Input'!$A$4:$A$14,0))*J40) | R40: =IF(K40="",INDEX('3_UK_L1_Input'!$D$4:$D$14,MATCH($C40,'3_UK_L1_Input'!$A$4:$A$14,0))*P40,INDEX('3_UK_L1_Input'!$D$4:$D$14,MATCH($C40,'3_UK_L1_Input'!$A$4:$A$14,0))*K40) | S40: =IF(G40="","BETA CASCADE FALLBACK (dummy — replace with real beta)","REAL (Bloomberg UK)") | T40: =INDEX('3_UK_L1_Input'!$C$4:$C$14,MATCH($C40,'3_UK_L1_Input'!$A$4:$A$14,0)) | U40: =INDEX('3_UK_L1_Input'!$C$4:$C$14,MATCH($C40,'3_UK_L1_Input'!$A$4:$A$14,0))*P40 | V40: =INDEX('5_UK_DefaultRisk_Input'!$D$5:$D$15,MATCH($C40,'5_UK_DefaultRisk_Input'!$A$5:$A$15,0)) | W40: =INDEX('5_UK_DefaultRisk_Input'!$D$20:$D$44,MATCH($E40,'5_UK_DefaultRisk_Input'!$A$20:$A$44,0)) | X40: =INDEX('5_UK_DefaultRisk_Input'!$D$49:$D$122,MATCH($D40,'5_UK_DefaultRisk_Input'!$A$49:$A$122,0)) | Y40: =INDEX('5_UK_DefaultRisk_Input'!$D$127:$D$289,MATCH($A40,'5_UK_DefaultRisk_Input'!$A$127:$A$289,0)) | Z40: =(W40/V40)*(X40/W40)*(Y40/X40) | AA40: =INDEX('3_UK_L1_Input'!$D$4:$D$14,MATCH($C40,'3_UK_L1_Input'!$A$4:$A$14,0))*Z40
A41: 20201080 | B41: Security & Alarm Services | C41: 20 | D41: 202010 | E41: 2020 | F41: 13500000000 | G41: 8.49 | H41: =IFERROR(SUMPRODUCT(($C$3:$C$165=C41)*ISNUMBER($G$3:$G$165)*ISNUMBER($F$3:$F$165)*IF(ISNUMBER($F$3:$F$165),$F$3:$F$165,0)*IF(ISNUMBER($G$3:$G$165),$G$3:$G$165,0))/SUMPRODUCT(($C$3:$C$165=C41)*ISNUMBER($G$3:$G$165)*ISNUMBER($F$3:$F$165)*IF(ISNUMBER($F$3:$F$165),$F$3:$F$165,0)),"") | I41: =IFERROR(SUMPRODUCT(($C$3:$C$165=C41)*ISNUMBER($G$3:$G$165)*IF(ISNUMBER($G$3:$G$165),$G$3:$G$165,0))/SUMPRODUCT(($C$3:$C$165=C41)*ISNUMBER($G$3:$G$165)),"") | J41: =IF(OR(G41="",H41=""),"",G41/H41) | K41: =IF(OR(G41="",I41=""),"",G41/I41) | L41: =INDEX('4_UK_Beta_Input'!$D$5:$D$15,MATCH($C41,'4_UK_Beta_Input'!$A$5:$A$15,0)) | M41: =INDEX('4_UK_Beta_Input'!$D$20:$D$44,MATCH($E41,'4_UK_Beta_Input'!$A$20:$A$44,0)) | N41: =INDEX('4_UK_Beta_Input'!$D$49:$D$122,MATCH($D41,'4_UK_Beta_Input'!$A$49:$A$122,0)) | O41: =INDEX('4_UK_Beta_Input'!$D$127:$D$289,MATCH($A41,'4_UK_Beta_Input'!$A$127:$A$289,0)) | P41: =(M41/L41)*(N41/M41)*(O41/N41) | Q41: =IF(J41="",INDEX('3_UK_L1_Input'!$D$4:$D$14,MATCH($C41,'3_UK_L1_Input'!$A$4:$A$14,0))*P41,INDEX('3_UK_L1_Input'!$D$4:$D$14,MATCH($C41,'3_UK_L1_Input'!$A$4:$A$14,0))*J41) | R41: =IF(K41="",INDEX('3_UK_L1_Input'!$D$4:$D$14,MATCH($C41,'3_UK_L1_Input'!$A$4:$A$14,0))*P41,INDEX('3_UK_L1_Input'!$D$4:$D$14,MATCH($C41,'3_UK_L1_Input'!$A$4:$A$14,0))*K41) | S41: =IF(G41="","BETA CASCADE FALLBACK (dummy — replace with real beta)","REAL (Bloomberg UK)") | T41: =INDEX('3_UK_L1_Input'!$C$4:$C$14,MATCH($C41,'3_UK_L1_Input'!$A$4:$A$14,0)) | U41: =INDEX('3_UK_L1_Input'!$C$4:$C$14,MATCH($C41,'3_UK_L1_Input'!$A$4:$A$14,0))*P41 | V41: =INDEX('5_UK_DefaultRisk_Input'!$D$5:$D$15,MATCH($C41,'5_UK_DefaultRisk_Input'!$A$5:$A$15,0)) | W41: =INDEX('5_UK_DefaultRisk_Input'!$D$20:$D$44,MATCH($E41,'5_UK_DefaultRisk_Input'!$A$20:$A$44,0)) | X41: =INDEX('5_UK_DefaultRisk_Input'!$D$49:$D$122,MATCH($D41,'5_UK_DefaultRisk_Input'!$A$49:$A$122,0)) | Y41: =INDEX('5_UK_DefaultRisk_Input'!$D$127:$D$289,MATCH($A41,'5_UK_DefaultRisk_Input'!$A$127:$A$289,0)) | Z41: =(W41/V41)*(X41/W41)*(Y41/X41) | AA41: =INDEX('3_UK_L1_Input'!$D$4:$D$14,MATCH($C41,'3_UK_L1_Input'!$A$4:$A$14,0))*Z41
A42: 20202010 | B42: Human Resource & Employment Services | C42: 20 | D42: 202020 | E42: 2020 | F42: 1210000000 | G42: 9.43 | H42: =IFERROR(SUMPRODUCT(($C$3:$C$165=C42)*ISNUMBER($G$3:$G$165)*ISNUMBER($F$3:$F$165)*IF(ISNUMBER($F$3:$F$165),$F$3:$F$165,0)*IF(ISNUMBER($G$3:$G$165),$G$3:$G$165,0))/SUMPRODUCT(($C$3:$C$165=C42)*ISNUMBER($G$3:$G$165)*ISNUMBER($F$3:$F$165)*IF(ISNUMBER($F$3:$F$165),$F$3:$F$165,0)),"") | I42: =IFERROR(SUMPRODUCT(($C$3:$C$165=C42)*ISNUMBER($G$3:$G$165)*IF(ISNUMBER($G$3:$G$165),$G$3:$G$165,0))/SUMPRODUCT(($C$3:$C$165=C42)*ISNUMBER($G$3:$G$165)),"") | J42: =IF(OR(G42="",H42=""),"",G42/H42) | K42: =IF(OR(G42="",I42=""),"",G42/I42) | L42: =INDEX('4_UK_Beta_Input'!$D$5:$D$15,MATCH($C42,'4_UK_Beta_Input'!$A$5:$A$15,0)) | M42: =INDEX('4_UK_Beta_Input'!$D$20:$D$44,MATCH($E42,'4_UK_Beta_Input'!$A$20:$A$44,0)) | N42: =INDEX('4_UK_Beta_Input'!$D$49:$D$122,MATCH($D42,'4_UK_Beta_Input'!$A$49:$A$122,0)) | O42: =INDEX('4_UK_Beta_Input'!$D$127:$D$289,MATCH($A42,'4_UK_Beta_Input'!$A$127:$A$289,0)) | P42: =(M42/L42)*(N42/M42)*(O42/N42) | Q42: =IF(J42="",INDEX('3_UK_L1_Input'!$D$4:$D$14,MATCH($C42,'3_UK_L1_Input'!$A$4:$A$14,0))*P42,INDEX('3_UK_L1_Input'!$D$4:$D$14,MATCH($C42,'3_UK_L1_Input'!$A$4:$A$14,0))*J42) | R42: =IF(K42="",INDEX('3_UK_L1_Input'!$D$4:$D$14,MATCH($C42,'3_UK_L1_Input'!$A$4:$A$14,0))*P42,INDEX('3_UK_L1_Input'!$D$4:$D$14,MATCH($C42,'3_UK_L1_Input'!$A$4:$A$14,0))*K42) | S42: =IF(G42="","BETA CASCADE FALLBACK (dummy — replace with real beta)","REAL (Bloomberg UK)") | T42: =INDEX('3_UK_L1_Input'!$C$4:$C$14,MATCH($C42,'3_UK_L1_Input'!$A$4:$A$14,0)) | U42: =INDEX('3_UK_L1_Input'!$C$4:$C$14,MATCH($C42,'3_UK_L1_Input'!$A$4:$A$14,0))*P42 | V42: =INDEX('5_UK_DefaultRisk_Input'!$D$5:$D$15,MATCH($C42,'5_UK_DefaultRisk_Input'!$A$5:$A$15,0)) | W42: =INDEX('5_UK_DefaultRisk_Input'!$D$20:$D$44,MATCH($E42,'5_UK_DefaultRisk_Input'!$A$20:$A$44,0)) | X42: =INDEX('5_UK_DefaultRisk_Input'!$D$49:$D$122,MATCH($D42,'5_UK_DefaultRisk_Input'!$A$49:$A$122,0)) | Y42: =INDEX('5_UK_DefaultRisk_Input'!$D$127:$D$289,MATCH($A42,'5_UK_DefaultRisk_Input'!$A$127:$A$289,0)) | Z42: =(W42/V42)*(X42/W42)*(Y42/X42) | AA42: =INDEX('3_UK_L1_Input'!$D$4:$D$14,MATCH($C42,'3_UK_L1_Input'!$A$4:$A$14,0))*Z42
A43: 20202020 | B43: Research & Consulting Services | C43: 20 | D43: 202020 | E43: 2020 | F43: 760740000 | G43: 7.31 | H43: =IFERROR(SUMPRODUCT(($C$3:$C$165=C43)*ISNUMBER($G$3:$G$165)*ISNUMBER($F$3:$F$165)*IF(ISNUMBER($F$3:$F$165),$F$3:$F$165,0)*IF(ISNUMBER($G$3:$G$165),$G$3:$G$165,0))/SUMPRODUCT(($C$3:$C$165=C43)*ISNUMBER($G$3:$G$165)*ISNUMBER($F$3:$F$165)*IF(ISNUMBER($F$3:$F$165),$F$3:$F$165,0)),"") | I43: =IFERROR(SUMPRODUCT(($C$3:$C$165=C43)*ISNUMBER($G$3:$G$165)*IF(ISNUMBER($G$3:$G$165),$G$3:$G$165,0))/SUMPRODUCT(($C$3:$C$165=C43)*ISNUMBER($G$3:$G$165)),"") | J43: =IF(OR(G43="",H43=""),"",G43/H43) | K43: =IF(OR(G43="",I43=""),"",G43/I43) | L43: =INDEX('4_UK_Beta_Input'!$D$5:$D$15,MATCH($C43,'4_UK_Beta_Input'!$A$5:$A$15,0)) | M43: =INDEX('4_UK_Beta_Input'!$D$20:$D$44,MATCH($E43,'4_UK_Beta_Input'!$A$20:$A$44,0)) | N43: =INDEX('4_UK_Beta_Input'!$D$49:$D$122,MATCH($D43,'4_UK_Beta_Input'!$A$49:$A$122,0)) | O43: =INDEX('4_UK_Beta_Input'!$D$127:$D$289,MATCH($A43,'4_UK_Beta_Input'!$A$127:$A$289,0)) | P43: =(M43/L43)*(N43/M43)*(O43/N43) | Q43: =IF(J43="",INDEX('3_UK_L1_Input'!$D$4:$D$14,MATCH($C43,'3_UK_L1_Input'!$A$4:$A$14,0))*P43,INDEX('3_UK_L1_Input'!$D$4:$D$14,MATCH($C43,'3_UK_L1_Input'!$A$4:$A$14,0))*J43) | R43: =IF(K43="",INDEX('3_UK_L1_Input'!$D$4:$D$14,MATCH($C43,'3_UK_L1_Input'!$A$4:$A$14,0))*P43,INDEX('3_UK_L1_Input'!$D$4:$D$14,MATCH($C43,'3_UK_L1_Input'!$A$4:$A$14,0))*K43) | S43: =IF(G43="","BETA CASCADE FALLBACK (dummy — replace with real beta)","REAL (Bloomberg UK)") | T43: =INDEX('3_UK_L1_Input'!$C$4:$C$14,MATCH($C43,'3_UK_L1_Input'!$A$4:$A$14,0)) | U43: =INDEX('3_UK_L1_Input'!$C$4:$C$14,MATCH($C43,'3_UK_L1_Input'!$A$4:$A$14,0))*P43 | V43: =INDEX('5_UK_DefaultRisk_Input'!$D$5:$D$15,MATCH($C43,'5_UK_DefaultRisk_Input'!$A$5:$A$15,0)) | W43: =INDEX('5_UK_DefaultRisk_Input'!$D$20:$D$44,MATCH($E43,'5_UK_DefaultRisk_Input'!$A$20:$A$44,0)) | X43: =INDEX('5_UK_DefaultRisk_Input'!$D$49:$D$122,MATCH($D43,'5_UK_DefaultRisk_Input'!$A$49:$A$122,0)) | Y43: =INDEX('5_UK_DefaultRisk_Input'!$D$127:$D$289,MATCH($A43,'5_UK_DefaultRisk_Input'!$A$127:$A$289,0)) | Z43: =(W43/V43)*(X43/W43)*(Y43/X43) | AA43: =INDEX('3_UK_L1_Input'!$D$4:$D$14,MATCH($C43,'3_UK_L1_Input'!$A$4:$A$14,0))*Z43
A44: 20202030 | B44: Data Processing & Outsourced Services | C44: 20 | D44: 202020 | E44: 2020 | F44: 279910000 | G44: 6.59 | H44: =IFERROR(SUMPRODUCT(($C$3:$C$165=C44)*ISNUMBER($G$3:$G$165)*ISNUMBER($F$3:$F$165)*IF(ISNUMBER($F$3:$F$165),$F$3:$F$165,0)*IF(ISNUMBER($G$3:$G$165),$G$3:$G$165,0))/SUMPRODUCT(($C$3:$C$165=C44)*ISNUMBER($G$3:$G$165)*ISNUMBER($F$3:$F$165)*IF(ISNUMBER($F$3:$F$165),$F$3:$F$165,0)),"") | I44: =IFERROR(SUMPRODUCT(($C$3:$C$165=C44)*ISNUMBER($G$3:$G$165)*IF(ISNUMBER($G$3:$G$165),$G$3:$G$165,0))/SUMPRODUCT(($C$3:$C$165=C44)*ISNUMBER($G$3:$G$165)),"") | J44: =IF(OR(G44="",H44=""),"",G44/H44) | K44: =IF(OR(G44="",I44=""),"",G44/I44) | L44: =INDEX('4_UK_Beta_Input'!$D$5:$D$15,MATCH($C44,'4_UK_Beta_Input'!$A$5:$A$15,0)) | M44: =INDEX('4_UK_Beta_Input'!$D$20:$D$44,MATCH($E44,'4_UK_Beta_Input'!$A$20:$A$44,0)) | N44: =INDEX('4_UK_Beta_Input'!$D$49:$D$122,MATCH($D44,'4_UK_Beta_Input'!$A$49:$A$122,0)) | O44: =INDEX('4_UK_Beta_Input'!$D$127:$D$289,MATCH($A44,'4_UK_Beta_Input'!$A$127:$A$289,0)) | P44: =(M44/L44)*(N44/M44)*(O44/N44) | Q44: =IF(J44="",INDEX('3_UK_L1_Input'!$D$4:$D$14,MATCH($C44,'3_UK_L1_Input'!$A$4:$A$14,0))*P44,INDEX('3_UK_L1_Input'!$D$4:$D$14,MATCH($C44,'3_UK_L1_Input'!$A$4:$A$14,0))*J44) | R44: =IF(K44="",INDEX('3_UK_L1_Input'!$D$4:$D$14,MATCH($C44,'3_UK_L1_Input'!$A$4:$A$14,0))*P44,INDEX('3_UK_L1_Input'!$D$4:$D$14,MATCH($C44,'3_UK_L1_Input'!$A$4:$A$14,0))*K44) | S44: =IF(G44="","BETA CASCADE FALLBACK (dummy — replace with real beta)","REAL (Bloomberg UK)") | T44: =INDEX('3_UK_L1_Input'!$C$4:$C$14,MATCH($C44,'3_UK_L1_Input'!$A$4:$A$14,0)) | U44: =INDEX('3_UK_L1_Input'!$C$4:$C$14,MATCH($C44,'3_UK_L1_Input'!$A$4:$A$14,0))*P44 | V44: =INDEX('5_UK_DefaultRisk_Input'!$D$5:$D$15,MATCH($C44,'5_UK_DefaultRisk_Input'!$A$5:$A$15,0)) | W44: =INDEX('5_UK_DefaultRisk_Input'!$D$20:$D$44,MATCH($E44,'5_UK_DefaultRisk_Input'!$A$20:$A$44,0)) | X44: =INDEX('5_UK_DefaultRisk_Input'!$D$49:$D$122,MATCH($D44,'5_UK_DefaultRisk_Input'!$A$49:$A$122,0)) | Y44: =INDEX('5_UK_DefaultRisk_Input'!$D$127:$D$289,MATCH($A44,'5_UK_DefaultRisk_Input'!$A$127:$A$289,0)) | Z44: =(W44/V44)*(X44/W44)*(Y44/X44) | AA44: =INDEX('3_UK_L1_Input'!$D$4:$D$14,MATCH($C44,'3_UK_L1_Input'!$A$4:$A$14,0))*Z44
A45: 20301010 | B45: Air Freight & Logistics | C45: 20 | D45: 203010 | E45: 2030 | F45: 137040000 | G45: 6.05 | H45: =IFERROR(SUMPRODUCT(($C$3:$C$165=C45)*ISNUMBER($G$3:$G$165)*ISNUMBER($F$3:$F$165)*IF(ISNUMBER($F$3:$F$165),$F$3:$F$165,0)*IF(ISNUMBER($G$3:$G$165),$G$3:$G$165,0))/SUMPRODUCT(($C$3:$C$165=C45)*ISNUMBER($G$3:$G$165)*ISNUMBER($F$3:$F$165)*IF(ISNUMBER($F$3:$F$165),$F$3:$F$165,0)),"") | I45: =IFERROR(SUMPRODUCT(($C$3:$C$165=C45)*ISNUMBER($G$3:$G$165)*IF(ISNUMBER($G$3:$G$165),$G$3:$G$165,0))/SUMPRODUCT(($C$3:$C$165=C45)*ISNUMBER($G$3:$G$165)),"") | J45: =IF(OR(G45="",H45=""),"",G45/H45) | K45: =IF(OR(G45="",I45=""),"",G45/I45) | L45: =INDEX('4_UK_Beta_Input'!$D$5:$D$15,MATCH($C45,'4_UK_Beta_Input'!$A$5:$A$15,0)) | M45: =INDEX('4_UK_Beta_Input'!$D$20:$D$44,MATCH($E45,'4_UK_Beta_Input'!$A$20:$A$44,0)) | N45: =INDEX('4_UK_Beta_Input'!$D$49:$D$122,MATCH($D45,'4_UK_Beta_Input'!$A$49:$A$122,0)) | O45: =INDEX('4_UK_Beta_Input'!$D$127:$D$289,MATCH($A45,'4_UK_Beta_Input'!$A$127:$A$289,0)) | P45: =(M45/L45)*(N45/M45)*(O45/N45) | Q45: =IF(J45="",INDEX('3_UK_L1_Input'!$D$4:$D$14,MATCH($C45,'3_UK_L1_Input'!$A$4:$A$14,0))*P45,INDEX('3_UK_L1_Input'!$D$4:$D$14,MATCH($C45,'3_UK_L1_Input'!$A$4:$A$14,0))*J45) | R45: =IF(K45="",INDEX('3_UK_L1_Input'!$D$4:$D$14,MATCH($C45,'3_UK_L1_Input'!$A$4:$A$14,0))*P45,INDEX('3_UK_L1_Input'!$D$4:$D$14,MATCH($C45,'3_UK_L1_Input'!$A$4:$A$14,0))*K45) | S45: =IF(G45="","BETA CASCADE FALLBACK (dummy — replace with real beta)","REAL (Bloomberg UK)") | T45: =INDEX('3_UK_L1_Input'!$C$4:$C$14,MATCH($C45,'3_UK_L1_Input'!$A$4:$A$14,0)) | U45: =INDEX('3_UK_L1_Input'!$C$4:$C$14,MATCH($C45,'3_UK_L1_Input'!$A$4:$A$14,0))*P45 | V45: =INDEX('5_UK_DefaultRisk_Input'!$D$5:$D$15,MATCH($C45,'5_UK_DefaultRisk_Input'!$A$5:$A$15,0)) | W45: =INDEX('5_UK_DefaultRisk_Input'!$D$20:$D$44,MATCH($E45,'5_UK_DefaultRisk_Input'!$A$20:$A$44,0)) | X45: =INDEX('5_UK_DefaultRisk_Input'!$D$49:$D$122,MATCH($D45,'5_UK_DefaultRisk_Input'!$A$49:$A$122,0)) | Y45: =INDEX('5_UK_DefaultRisk_Input'!$D$127:$D$289,MATCH($A45,'5_UK_DefaultRisk_Input'!$A$127:$A$289,0)) | Z45: =(W45/V45)*(X45/W45)*(Y45/X45) | AA45: =INDEX('3_UK_L1_Input'!$D$4:$D$14,MATCH($C45,'3_UK_L1_Input'!$A$4:$A$14,0))*Z45
A46: 20302010 | B46: Passenger Airlines | C46: 20 | D46: 203020 | E46: 2030 | F46: 17130000000 | G46: 3.69 | H46: =IFERROR(SUMPRODUCT(($C$3:$C$165=C46)*ISNUMBER($G$3:$G$165)*ISNUMBER($F$3:$F$165)*IF(ISNUMBER($F$3:$F$165),$F$3:$F$165,0)*IF(ISNUMBER($G$3:$G$165),$G$3:$G$165,0))/SUMPRODUCT(($C$3:$C$165=C46)*ISNUMBER($G$3:$G$165)*ISNUMBER($F$3:$F$165)*IF(ISNUMBER($F$3:$F$165),$F$3:$F$165,0)),"") | I46: =IFERROR(SUMPRODUCT(($C$3:$C$165=C46)*ISNUMBER($G$3:$G$165)*IF(ISNUMBER($G$3:$G$165),$G$3:$G$165,0))/SUMPRODUCT(($C$3:$C$165=C46)*ISNUMBER($G$3:$G$165)),"") | J46: =IF(OR(G46="",H46=""),"",G46/H46) | K46: =IF(OR(G46="",I46=""),"",G46/I46) | L46: =INDEX('4_UK_Beta_Input'!$D$5:$D$15,MATCH($C46,'4_UK_Beta_Input'!$A$5:$A$15,0)) | M46: =INDEX('4_UK_Beta_Input'!$D$20:$D$44,MATCH($E46,'4_UK_Beta_Input'!$A$20:$A$44,0)) | N46: =INDEX('4_UK_Beta_Input'!$D$49:$D$122,MATCH($D46,'4_UK_Beta_Input'!$A$49:$A$122,0)) | O46: =INDEX('4_UK_Beta_Input'!$D$127:$D$289,MATCH($A46,'4_UK_Beta_Input'!$A$127:$A$289,0)) | P46: =(M46/L46)*(N46/M46)*(O46/N46) | Q46: =IF(J46="",INDEX('3_UK_L1_Input'!$D$4:$D$14,MATCH($C46,'3_UK_L1_Input'!$A$4:$A$14,0))*P46,INDEX('3_UK_L1_Input'!$D$4:$D$14,MATCH($C46,'3_UK_L1_Input'!$A$4:$A$14,0))*J46) | R46: =IF(K46="",INDEX('3_UK_L1_Input'!$D$4:$D$14,MATCH($C46,'3_UK_L1_Input'!$A$4:$A$14,0))*P46,INDEX('3_UK_L1_Input'!$D$4:$D$14,MATCH($C46,'3_UK_L1_Input'!$A$4:$A$14,0))*K46) | S46: =IF(G46="","BETA CASCADE FALLBACK (dummy — replace with real beta)","REAL (Bloomberg UK)") | T46: =INDEX('3_UK_L1_Input'!$C$4:$C$14,MATCH($C46,'3_UK_L1_Input'!$A$4:$A$14,0)) | U46: =INDEX('3_UK_L1_Input'!$C$4:$C$14,MATCH($C46,'3_UK_L1_Input'!$A$4:$A$14,0))*P46 | V46: =INDEX('5_UK_DefaultRisk_Input'!$D$5:$D$15,MATCH($C46,'5_UK_DefaultRisk_Input'!$A$5:$A$15,0)) | W46: =INDEX('5_UK_DefaultRisk_Input'!$D$20:$D$44,MATCH($E46,'5_UK_DefaultRisk_Input'!$A$20:$A$44,0)) | X46: =INDEX('5_UK_DefaultRisk_Input'!$D$49:$D$122,MATCH($D46,'5_UK_DefaultRisk_Input'!$A$49:$A$122,0)) | Y46: =INDEX('5_UK_DefaultRisk_Input'!$D$127:$D$289,MATCH($A46,'5_UK_DefaultRisk_Input'!$A$127:$A$289,0)) | Z46: =(W46/V46)*(X46/W46)*(Y46/X46) | AA46: =INDEX('3_UK_L1_Input'!$D$4:$D$14,MATCH($C46,'3_UK_L1_Input'!$A$4:$A$14,0))*Z46
A47: 20303010 | B47: Marine Transportation | C47: 20 | D47: 203030 | E47: 2030 | F47: 1460000000 | G47: 6 | H47: =IFERROR(SUMPRODUCT(($C$3:$C$165=C47)*ISNUMBER($G$3:$G$165)*ISNUMBER($F$3:$F$165)*IF(ISNUMBER($F$3:$F$165),$F$3:$F$165,0)*IF(ISNUMBER($G$3:$G$165),$G$3:$G$165,0))/SUMPRODUCT(($C$3:$C$165=C47)*ISNUMBER($G$3:$G$165)*ISNUMBER($F$3:$F$165)*IF(ISNUMBER($F$3:$F$165),$F$3:$F$165,0)),"") | I47: =IFERROR(SUMPRODUCT(($C$3:$C$165=C47)*ISNUMBER($G$3:$G$165)*IF(ISNUMBER($G$3:$G$165),$G$3:$G$165,0))/SUMPRODUCT(($C$3:$C$165=C47)*ISNUMBER($G$3:$G$165)),"") | J47: =IF(OR(G47="",H47=""),"",G47/H47) | K47: =IF(OR(G47="",I47=""),"",G47/I47) | L47: =INDEX('4_UK_Beta_Input'!$D$5:$D$15,MATCH($C47,'4_UK_Beta_Input'!$A$5:$A$15,0)) | M47: =INDEX('4_UK_Beta_Input'!$D$20:$D$44,MATCH($E47,'4_UK_Beta_Input'!$A$20:$A$44,0)) | N47: =INDEX('4_UK_Beta_Input'!$D$49:$D$122,MATCH($D47,'4_UK_Beta_Input'!$A$49:$A$122,0)) | O47: =INDEX('4_UK_Beta_Input'!$D$127:$D$289,MATCH($A47,'4_UK_Beta_Input'!$A$127:$A$289,0)) | P47: =(M47/L47)*(N47/M47)*(O47/N47) | Q47: =IF(J47="",INDEX('3_UK_L1_Input'!$D$4:$D$14,MATCH($C47,'3_UK_L1_Input'!$A$4:$A$14,0))*P47,INDEX('3_UK_L1_Input'!$D$4:$D$14,MATCH($C47,'3_UK_L1_Input'!$A$4:$A$14,0))*J47) | R47: =IF(K47="",INDEX('3_UK_L1_Input'!$D$4:$D$14,MATCH($C47,'3_UK_L1_Input'!$A$4:$A$14,0))*P47,INDEX('3_UK_L1_Input'!$D$4:$D$14,MATCH($C47,'3_UK_L1_Input'!$A$4:$A$14,0))*K47) | S47: =IF(G47="","BETA CASCADE FALLBACK (dummy — replace with real beta)","REAL (Bloomberg UK)") | T47: =INDEX('3_UK_L1_Input'!$C$4:$C$14,MATCH($C47,'3_UK_L1_Input'!$A$4:$A$14,0)) | U47: =INDEX('3_UK_L1_Input'!$C$4:$C$14,MATCH($C47,'3_UK_L1_Input'!$A$4:$A$14,0))*P47 | V47: =INDEX('5_UK_DefaultRisk_Input'!$D$5:$D$15,MATCH($C47,'5_UK_DefaultRisk_Input'!$A$5:$A$15,0)) | W47: =INDEX('5_UK_DefaultRisk_Input'!$D$20:$D$44,MATCH($E47,'5_UK_DefaultRisk_Input'!$A$20:$A$44,0)) | X47: =INDEX('5_UK_DefaultRisk_Input'!$D$49:$D$122,MATCH($D47,'5_UK_DefaultRisk_Input'!$A$49:$A$122,0)) | Y47: =INDEX('5_UK_DefaultRisk_Input'!$D$127:$D$289,MATCH($A47,'5_UK_DefaultRisk_Input'!$A$127:$A$289,0)) | Z47: =(W47/V47)*(X47/W47)*(Y47/X47) | AA47: =INDEX('3_UK_L1_Input'!$D$4:$D$14,MATCH($C47,'3_UK_L1_Input'!$A$4:$A$14,0))*Z47
A48: 20304010 | B48: Rail Transportation | C48: 20 | D48: 203040 | E48: 2030 | F48: 4750000000 | G48: 2.53 | H48: =IFERROR(SUMPRODUCT(($C$3:$C$165=C48)*ISNUMBER($G$3:$G$165)*ISNUMBER($F$3:$F$165)*IF(ISNUMBER($F$3:$F$165),$F$3:$F$165,0)*IF(ISNUMBER($G$3:$G$165),$G$3:$G$165,0))/SUMPRODUCT(($C$3:$C$165=C48)*ISNUMBER($G$3:$G$165)*ISNUMBER($F$3:$F$165)*IF(ISNUMBER($F$3:$F$165),$F$3:$F$165,0)),"") | I48: =IFERROR(SUMPRODUCT(($C$3:$C$165=C48)*ISNUMBER($G$3:$G$165)*IF(ISNUMBER($G$3:$G$165),$G$3:$G$165,0))/SUMPRODUCT(($C$3:$C$165=C48)*ISNUMBER($G$3:$G$165)),"") | J48: =IF(OR(G48="",H48=""),"",G48/H48) | K48: =IF(OR(G48="",I48=""),"",G48/I48) | L48: =INDEX('4_UK_Beta_Input'!$D$5:$D$15,MATCH($C48,'4_UK_Beta_Input'!$A$5:$A$15,0)) | M48: =INDEX('4_UK_Beta_Input'!$D$20:$D$44,MATCH($E48,'4_UK_Beta_Input'!$A$20:$A$44,0)) | N48: =INDEX('4_UK_Beta_Input'!$D$49:$D$122,MATCH($D48,'4_UK_Beta_Input'!$A$49:$A$122,0)) | O48: =INDEX('4_UK_Beta_Input'!$D$127:$D$289,MATCH($A48,'4_UK_Beta_Input'!$A$127:$A$289,0)) | P48: =(M48/L48)*(N48/M48)*(O48/N48) | Q48: =IF(J48="",INDEX('3_UK_L1_Input'!$D$4:$D$14,MATCH($C48,'3_UK_L1_Input'!$A$4:$A$14,0))*P48,INDEX('3_UK_L1_Input'!$D$4:$D$14,MATCH($C48,'3_UK_L1_Input'!$A$4:$A$14,0))*J48) | R48: =IF(K48="",INDEX('3_UK_L1_Input'!$D$4:$D$14,MATCH($C48,'3_UK_L1_Input'!$A$4:$A$14,0))*P48,INDEX('3_UK_L1_Input'!$D$4:$D$14,MATCH($C48,'3_UK_L1_Input'!$A$4:$A$14,0))*K48) | S48: =IF(G48="","BETA CASCADE FALLBACK (dummy — replace with real beta)","REAL (Bloomberg UK)") | T48: =INDEX('3_UK_L1_Input'!$C$4:$C$14,MATCH($C48,'3_UK_L1_Input'!$A$4:$A$14,0)) | U48: =INDEX('3_UK_L1_Input'!$C$4:$C$14,MATCH($C48,'3_UK_L1_Input'!$A$4:$A$14,0))*P48 | V48: =INDEX('5_UK_DefaultRisk_Input'!$D$5:$D$15,MATCH($C48,'5_UK_DefaultRisk_Input'!$A$5:$A$15,0)) | W48: =INDEX('5_UK_DefaultRisk_Input'!$D$20:$D$44,MATCH($E48,'5_UK_DefaultRisk_Input'!$A$20:$A$44,0)) | X48: =INDEX('5_UK_DefaultRisk_Input'!$D$49:$D$122,MATCH($D48,'5_UK_DefaultRisk_Input'!$A$49:$A$122,0)) | Y48: =INDEX('5_UK_DefaultRisk_Input'!$D$127:$D$289,MATCH($A48,'5_UK_DefaultRisk_Input'!$A$127:$A$289,0)) | Z48: =(W48/V48)*(X48/W48)*(Y48/X48) | AA48: =INDEX('3_UK_L1_Input'!$D$4:$D$14,MATCH($C48,'3_UK_L1_Input'!$A$4:$A$14,0))*Z48
A49: 20304030 | B49: Cargo Ground Transportation | C49: 20 | D49: 203040 | E49: 2030 | H49: =IFERROR(SUMPRODUCT(($C$3:$C$165=C49)*ISNUMBER($G$3:$G$165)*ISNUMBER($F$3:$F$165)*IF(ISNUMBER($F$3:$F$165),$F$3:$F$165,0)*IF(ISNUMBER($G$3:$G$165),$G$3:$G$165,0))/SUMPRODUCT(($C$3:$C$165=C49)*ISNUMBER($G$3:$G$165)*ISNUMBER($F$3:$F$165)*IF(ISNUMBER($F$3:$F$165),$F$3:$F$165,0)),"") | I49: =IFERROR(SUMPRODUCT(($C$3:$C$165=C49)*ISNUMBER($G$3:$G$165)*IF(ISNUMBER($G$3:$G$165),$G$3:$G$165,0))/SUMPRODUCT(($C$3:$C$165=C49)*ISNUMBER($G$3:$G$165)),"") | J49: =IF(OR(G49="",H49=""),"",G49/H49) | K49: =IF(OR(G49="",I49=""),"",G49/I49) | L49: =INDEX('4_UK_Beta_Input'!$D$5:$D$15,MATCH($C49,'4_UK_Beta_Input'!$A$5:$A$15,0)) | M49: =INDEX('4_UK_Beta_Input'!$D$20:$D$44,MATCH($E49,'4_UK_Beta_Input'!$A$20:$A$44,0)) | N49: =INDEX('4_UK_Beta_Input'!$D$49:$D$122,MATCH($D49,'4_UK_Beta_Input'!$A$49:$A$122,0)) | O49: =INDEX('4_UK_Beta_Input'!$D$127:$D$289,MATCH($A49,'4_UK_Beta_Input'!$A$127:$A$289,0)) | P49: =(M49/L49)*(N49/M49)*(O49/N49) | Q49: =IF(J49="",INDEX('3_UK_L1_Input'!$D$4:$D$14,MATCH($C49,'3_UK_L1_Input'!$A$4:$A$14,0))*P49,INDEX('3_UK_L1_Input'!$D$4:$D$14,MATCH($C49,'3_UK_L1_Input'!$A$4:$A$14,0))*J49) | R49: =IF(K49="",INDEX('3_UK_L1_Input'!$D$4:$D$14,MATCH($C49,'3_UK_L1_Input'!$A$4:$A$14,0))*P49,INDEX('3_UK_L1_Input'!$D$4:$D$14,MATCH($C49,'3_UK_L1_Input'!$A$4:$A$14,0))*K49) | S49: =IF(G49="","BETA CASCADE FALLBACK (dummy — replace with real beta)","REAL (Bloomberg UK)") | T49: =INDEX('3_UK_L1_Input'!$C$4:$C$14,MATCH($C49,'3_UK_L1_Input'!$A$4:$A$14,0)) | U49: =INDEX('3_UK_L1_Input'!$C$4:$C$14,MATCH($C49,'3_UK_L1_Input'!$A$4:$A$14,0))*P49 | V49: =INDEX('5_UK_DefaultRisk_Input'!$D$5:$D$15,MATCH($C49,'5_UK_DefaultRisk_Input'!$A$5:$A$15,0)) | W49: =INDEX('5_UK_DefaultRisk_Input'!$D$20:$D$44,MATCH($E49,'5_UK_DefaultRisk_Input'!$A$20:$A$44,0)) | X49: =INDEX('5_UK_DefaultRisk_Input'!$D$49:$D$122,MATCH($D49,'5_UK_DefaultRisk_Input'!$A$49:$A$122,0)) | Y49: =INDEX('5_UK_DefaultRisk_Input'!$D$127:$D$289,MATCH($A49,'5_UK_DefaultRisk_Input'!$A$127:$A$289,0)) | Z49: =(W49/V49)*(X49/W49)*(Y49/X49) | AA49: =INDEX('3_UK_L1_Input'!$D$4:$D$14,MATCH($C49,'3_UK_L1_Input'!$A$4:$A$14,0))*Z49
A50: 20304040 | B50: Passenger Ground Transportation | C50: 20 | D50: 203040 | E50: 2030 | F50: 2300000000 | G50: 3.68 | H50: =IFERROR(SUMPRODUCT(($C$3:$C$165=C50)*ISNUMBER($G$3:$G$165)*ISNUMBER($F$3:$F$165)*IF(ISNUMBER($F$3:$F$165),$F$3:$F$165,0)*IF(ISNUMBER($G$3:$G$165),$G$3:$G$165,0))/SUMPRODUCT(($C$3:$C$165=C50)*ISNUMBER($G$3:$G$165)*ISNUMBER($F$3:$F$165)*IF(ISNUMBER($F$3:$F$165),$F$3:$F$165,0)),"") | I50: =IFERROR(SUMPRODUCT(($C$3:$C$165=C50)*ISNUMBER($G$3:$G$165)*IF(ISNUMBER($G$3:$G$165),$G$3:$G$165,0))/SUMPRODUCT(($C$3:$C$165=C50)*ISNUMBER($G$3:$G$165)),"") | J50: =IF(OR(G50="",H50=""),"",G50/H50) | K50: =IF(OR(G50="",I50=""),"",G50/I50) | L50: =INDEX('4_UK_Beta_Input'!$D$5:$D$15,MATCH($C50,'4_UK_Beta_Input'!$A$5:$A$15,0)) | M50: =INDEX('4_UK_Beta_Input'!$D$20:$D$44,MATCH($E50,'4_UK_Beta_Input'!$A$20:$A$44,0)) | N50: =INDEX('4_UK_Beta_Input'!$D$49:$D$122,MATCH($D50,'4_UK_Beta_Input'!$A$49:$A$122,0)) | O50: =INDEX('4_UK_Beta_Input'!$D$127:$D$289,MATCH($A50,'4_UK_Beta_Input'!$A$127:$A$289,0)) | P50: =(M50/L50)*(N50/M50)*(O50/N50) | Q50: =IF(J50="",INDEX('3_UK_L1_Input'!$D$4:$D$14,MATCH($C50,'3_UK_L1_Input'!$A$4:$A$14,0))*P50,INDEX('3_UK_L1_Input'!$D$4:$D$14,MATCH($C50,'3_UK_L1_Input'!$A$4:$A$14,0))*J50) | R50: =IF(K50="",INDEX('3_UK_L1_Input'!$D$4:$D$14,MATCH($C50,'3_UK_L1_Input'!$A$4:$A$14,0))*P50,INDEX('3_UK_L1_Input'!$D$4:$D$14,MATCH($C50,'3_UK_L1_Input'!$A$4:$A$14,0))*K50) | S50: =IF(G50="","BETA CASCADE FALLBACK (dummy — replace with real beta)","REAL (Bloomberg UK)") | T50: =INDEX('3_UK_L1_Input'!$C$4:$C$14,MATCH($C50,'3_UK_L1_Input'!$A$4:$A$14,0)) | U50: =INDEX('3_UK_L1_Input'!$C$4:$C$14,MATCH($C50,'3_UK_L1_Input'!$A$4:$A$14,0))*P50 | V50: =INDEX('5_UK_DefaultRisk_Input'!$D$5:$D$15,MATCH($C50,'5_UK_DefaultRisk_Input'!$A$5:$A$15,0)) | W50: =INDEX('5_UK_DefaultRisk_Input'!$D$20:$D$44,MATCH($E50,'5_UK_DefaultRisk_Input'!$A$20:$A$44,0)) | X50: =INDEX('5_UK_DefaultRisk_Input'!$D$49:$D$122,MATCH($D50,'5_UK_DefaultRisk_Input'!$A$49:$A$122,0)) | Y50: =INDEX('5_UK_DefaultRisk_Input'!$D$127:$D$289,MATCH($A50,'5_UK_DefaultRisk_Input'!$A$127:$A$289,0)) | Z50: =(W50/V50)*(X50/W50)*(Y50/X50) | AA50: =INDEX('3_UK_L1_Input'!$D$4:$D$14,MATCH($C50,'3_UK_L1_Input'!$A$4:$A$14,0))*Z50
A51: 20305010 | B51: Airport Services | C51: 20 | D51: 203050 | E51: 2030 | H51: =IFERROR(SUMPRODUCT(($C$3:$C$165=C51)*ISNUMBER($G$3:$G$165)*ISNUMBER($F$3:$F$165)*IF(ISNUMBER($F$3:$F$165),$F$3:$F$165,0)*IF(ISNUMBER($G$3:$G$165),$G$3:$G$165,0))/SUMPRODUCT(($C$3:$C$165=C51)*ISNUMBER($G$3:$G$165)*ISNUMBER($F$3:$F$165)*IF(ISNUMBER($F$3:$F$165),$F$3:$F$165,0)),"") | I51: =IFERROR(SUMPRODUCT(($C$3:$C$165=C51)*ISNUMBER($G$3:$G$165)*IF(ISNUMBER($G$3:$G$165),$G$3:$G$165,0))/SUMPRODUCT(($C$3:$C$165=C51)*ISNUMBER($G$3:$G$165)),"") | J51: =IF(OR(G51="",H51=""),"",G51/H51) | K51: =IF(OR(G51="",I51=""),"",G51/I51) | L51: =INDEX('4_UK_Beta_Input'!$D$5:$D$15,MATCH($C51,'4_UK_Beta_Input'!$A$5:$A$15,0)) | M51: =INDEX('4_UK_Beta_Input'!$D$20:$D$44,MATCH($E51,'4_UK_Beta_Input'!$A$20:$A$44,0)) | N51: =INDEX('4_UK_Beta_Input'!$D$49:$D$122,MATCH($D51,'4_UK_Beta_Input'!$A$49:$A$122,0)) | O51: =INDEX('4_UK_Beta_Input'!$D$127:$D$289,MATCH($A51,'4_UK_Beta_Input'!$A$127:$A$289,0)) | P51: =(M51/L51)*(N51/M51)*(O51/N51) | Q51: =IF(J51="",INDEX('3_UK_L1_Input'!$D$4:$D$14,MATCH($C51,'3_UK_L1_Input'!$A$4:$A$14,0))*P51,INDEX('3_UK_L1_Input'!$D$4:$D$14,MATCH($C51,'3_UK_L1_Input'!$A$4:$A$14,0))*J51) | R51: =IF(K51="",INDEX('3_UK_L1_Input'!$D$4:$D$14,MATCH($C51,'3_UK_L1_Input'!$A$4:$A$14,0))*P51,INDEX('3_UK_L1_Input'!$D$4:$D$14,MATCH($C51,'3_UK_L1_Input'!$A$4:$A$14,0))*K51) | S51: =IF(G51="","BETA CASCADE FALLBACK (dummy — replace with real beta)","REAL (Bloomberg UK)") | T51: =INDEX('3_UK_L1_Input'!$C$4:$C$14,MATCH($C51,'3_UK_L1_Input'!$A$4:$A$14,0)) | U51: =INDEX('3_UK_L1_Input'!$C$4:$C$14,MATCH($C51,'3_UK_L1_Input'!$A$4:$A$14,0))*P51 | V51: =INDEX('5_UK_DefaultRisk_Input'!$D$5:$D$15,MATCH($C51,'5_UK_DefaultRisk_Input'!$A$5:$A$15,0)) | W51: =INDEX('5_UK_DefaultRisk_Input'!$D$20:$D$44,MATCH($E51,'5_UK_DefaultRisk_Input'!$A$20:$A$44,0)) | X51: =INDEX('5_UK_DefaultRisk_Input'!$D$49:$D$122,MATCH($D51,'5_UK_DefaultRisk_Input'!$A$49:$A$122,0)) | Y51: =INDEX('5_UK_DefaultRisk_Input'!$D$127:$D$289,MATCH($A51,'5_UK_DefaultRisk_Input'!$A$127:$A$289,0)) | Z51: =(W51/V51)*(X51/W51)*(Y51/X51) | AA51: =INDEX('3_UK_L1_Input'!$D$4:$D$14,MATCH($C51,'3_UK_L1_Input'!$A$4:$A$14,0))*Z51
A52: 20305020 | B52: Highways & Railtracks | C52: 20 | D52: 203050 | E52: 2030 | H52: =IFERROR(SUMPRODUCT(($C$3:$C$165=C52)*ISNUMBER($G$3:$G$165)*ISNUMBER($F$3:$F$165)*IF(ISNUMBER($F$3:$F$165),$F$3:$F$165,0)*IF(ISNUMBER($G$3:$G$165),$G$3:$G$165,0))/SUMPRODUCT(($C$3:$C$165=C52)*ISNUMBER($G$3:$G$165)*ISNUMBER($F$3:$F$165)*IF(ISNUMBER($F$3:$F$165),$F$3:$F$165,0)),"") | I52: =IFERROR(SUMPRODUCT(($C$3:$C$165=C52)*ISNUMBER($G$3:$G$165)*IF(ISNUMBER($G$3:$G$165),$G$3:$G$165,0))/SUMPRODUCT(($C$3:$C$165=C52)*ISNUMBER($G$3:$G$165)),"") | J52: =IF(OR(G52="",H52=""),"",G52/H52) | K52: =IF(OR(G52="",I52=""),"",G52/I52) | L52: =INDEX('4_UK_Beta_Input'!$D$5:$D$15,MATCH($C52,'4_UK_Beta_Input'!$A$5:$A$15,0)) | M52: =INDEX('4_UK_Beta_Input'!$D$20:$D$44,MATCH($E52,'4_UK_Beta_Input'!$A$20:$A$44,0)) | N52: =INDEX('4_UK_Beta_Input'!$D$49:$D$122,MATCH($D52,'4_UK_Beta_Input'!$A$49:$A$122,0)) | O52: =INDEX('4_UK_Beta_Input'!$D$127:$D$289,MATCH($A52,'4_UK_Beta_Input'!$A$127:$A$289,0)) | P52: =(M52/L52)*(N52/M52)*(O52/N52) | Q52: =IF(J52="",INDEX('3_UK_L1_Input'!$D$4:$D$14,MATCH($C52,'3_UK_L1_Input'!$A$4:$A$14,0))*P52,INDEX('3_UK_L1_Input'!$D$4:$D$14,MATCH($C52,'3_UK_L1_Input'!$A$4:$A$14,0))*J52) | R52: =IF(K52="",INDEX('3_UK_L1_Input'!$D$4:$D$14,MATCH($C52,'3_UK_L1_Input'!$A$4:$A$14,0))*P52,INDEX('3_UK_L1_Input'!$D$4:$D$14,MATCH($C52,'3_UK_L1_Input'!$A$4:$A$14,0))*K52) | S52: =IF(G52="","BETA CASCADE FALLBACK (dummy — replace with real beta)","REAL (Bloomberg UK)") | T52: =INDEX('3_UK_L1_Input'!$C$4:$C$14,MATCH($C52,'3_UK_L1_Input'!$A$4:$A$14,0)) | U52: =INDEX('3_UK_L1_Input'!$C$4:$C$14,MATCH($C52,'3_UK_L1_Input'!$A$4:$A$14,0))*P52 | V52: =INDEX('5_UK_DefaultRisk_Input'!$D$5:$D$15,MATCH($C52,'5_UK_DefaultRisk_Input'!$A$5:$A$15,0)) | W52: =INDEX('5_UK_DefaultRisk_Input'!$D$20:$D$44,MATCH($E52,'5_UK_DefaultRisk_Input'!$A$20:$A$44,0)) | X52: =INDEX('5_UK_DefaultRisk_Input'!$D$49:$D$122,MATCH($D52,'5_UK_DefaultRisk_Input'!$A$49:$A$122,0)) | Y52: =INDEX('5_UK_DefaultRisk_Input'!$D$127:$D$289,MATCH($A52,'5_UK_DefaultRisk_Input'!$A$127:$A$289,0)) | Z52: =(W52/V52)*(X52/W52)*(Y52/X52) | AA52: =INDEX('3_UK_L1_Input'!$D$4:$D$14,MATCH($C52,'3_UK_L1_Input'!$A$4:$A$14,0))*Z52
A53: 20305030 | B53: Marine Ports & Services | C53: 20 | D53: 203050 | E53: 2030 | F53: 180500000 | G53: 4.85 | H53: =IFERROR(SUMPRODUCT(($C$3:$C$165=C53)*ISNUMBER($G$3:$G$165)*ISNUMBER($F$3:$F$165)*IF(ISNUMBER($F$3:$F$165),$F$3:$F$165,0)*IF(ISNUMBER($G$3:$G$165),$G$3:$G$165,0))/SUMPRODUCT(($C$3:$C$165=C53)*ISNUMBER($G$3:$G$165)*ISNUMBER($F$3:$F$165)*IF(ISNUMBER($F$3:$F$165),$F$3:$F$165,0)),"") | I53: =IFERROR(SUMPRODUCT(($C$3:$C$165=C53)*ISNUMBER($G$3:$G$165)*IF(ISNUMBER($G$3:$G$165),$G$3:$G$165,0))/SUMPRODUCT(($C$3:$C$165=C53)*ISNUMBER($G$3:$G$165)),"") | J53: =IF(OR(G53="",H53=""),"",G53/H53) | K53: =IF(OR(G53="",I53=""),"",G53/I53) | L53: =INDEX('4_UK_Beta_Input'!$D$5:$D$15,MATCH($C53,'4_UK_Beta_Input'!$A$5:$A$15,0)) | M53: =INDEX('4_UK_Beta_Input'!$D$20:$D$44,MATCH($E53,'4_UK_Beta_Input'!$A$20:$A$44,0)) | N53: =INDEX('4_UK_Beta_Input'!$D$49:$D$122,MATCH($D53,'4_UK_Beta_Input'!$A$49:$A$122,0)) | O53: =INDEX('4_UK_Beta_Input'!$D$127:$D$289,MATCH($A53,'4_UK_Beta_Input'!$A$127:$A$289,0)) | P53: =(M53/L53)*(N53/M53)*(O53/N53) | Q53: =IF(J53="",INDEX('3_UK_L1_Input'!$D$4:$D$14,MATCH($C53,'3_UK_L1_Input'!$A$4:$A$14,0))*P53,INDEX('3_UK_L1_Input'!$D$4:$D$14,MATCH($C53,'3_UK_L1_Input'!$A$4:$A$14,0))*J53) | R53: =IF(K53="",INDEX('3_UK_L1_Input'!$D$4:$D$14,MATCH($C53,'3_UK_L1_Input'!$A$4:$A$14,0))*P53,INDEX('3_UK_L1_Input'!$D$4:$D$14,MATCH($C53,'3_UK_L1_Input'!$A$4:$A$14,0))*K53) | S53: =IF(G53="","BETA CASCADE FALLBACK (dummy — replace with real beta)","REAL (Bloomberg UK)") | T53: =INDEX('3_UK_L1_Input'!$C$4:$C$14,MATCH($C53,'3_UK_L1_Input'!$A$4:$A$14,0)) | U53: =INDEX('3_UK_L1_Input'!$C$4:$C$14,MATCH($C53,'3_UK_L1_Input'!$A$4:$A$14,0))*P53 | V53: =INDEX('5_UK_DefaultRisk_Input'!$D$5:$D$15,MATCH($C53,'5_UK_DefaultRisk_Input'!$A$5:$A$15,0)) | W53: =INDEX('5_UK_DefaultRisk_Input'!$D$20:$D$44,MATCH($E53,'5_UK_DefaultRisk_Input'!$A$20:$A$44,0)) | X53: =INDEX('5_UK_DefaultRisk_Input'!$D$49:$D$122,MATCH($D53,'5_UK_DefaultRisk_Input'!$A$49:$A$122,0)) | Y53: =INDEX('5_UK_DefaultRisk_Input'!$D$127:$D$289,MATCH($A53,'5_UK_DefaultRisk_Input'!$A$127:$A$289,0)) | Z53: =(W53/V53)*(X53/W53)*(Y53/X53) | AA53: =INDEX('3_UK_L1_Input'!$D$4:$D$14,MATCH($C53,'3_UK_L1_Input'!$A$4:$A$14,0))*Z53
A54: 25101010 | B54: Automotive Parts & Equipment | C54: 25 | D54: 251010 | E54: 2510 | F54: 127580000 | G54: 8.12 | H54: =IFERROR(SUMPRODUCT(($C$3:$C$165=C54)*ISNUMBER($G$3:$G$165)*ISNUMBER($F$3:$F$165)*IF(ISNUMBER($F$3:$F$165),$F$3:$F$165,0)*IF(ISNUMBER($G$3:$G$165),$G$3:$G$165,0))/SUMPRODUCT(($C$3:$C$165=C54)*ISNUMBER($G$3:$G$165)*ISNUMBER($F$3:$F$165)*IF(ISNUMBER($F$3:$F$165),$F$3:$F$165,0)),"") | I54: =IFERROR(SUMPRODUCT(($C$3:$C$165=C54)*ISNUMBER($G$3:$G$165)*IF(ISNUMBER($G$3:$G$165),$G$3:$G$165,0))/SUMPRODUCT(($C$3:$C$165=C54)*ISNUMBER($G$3:$G$165)),"") | J54: =IF(OR(G54="",H54=""),"",G54/H54) | K54: =IF(OR(G54="",I54=""),"",G54/I54) | L54: =INDEX('4_UK_Beta_Input'!$D$5:$D$15,MATCH($C54,'4_UK_Beta_Input'!$A$5:$A$15,0)) | M54: =INDEX('4_UK_Beta_Input'!$D$20:$D$44,MATCH($E54,'4_UK_Beta_Input'!$A$20:$A$44,0)) | N54: =INDEX('4_UK_Beta_Input'!$D$49:$D$122,MATCH($D54,'4_UK_Beta_Input'!$A$49:$A$122,0)) | O54: =INDEX('4_UK_Beta_Input'!$D$127:$D$289,MATCH($A54,'4_UK_Beta_Input'!$A$127:$A$289,0)) | P54: =(M54/L54)*(N54/M54)*(O54/N54) | Q54: =IF(J54="",INDEX('3_UK_L1_Input'!$D$4:$D$14,MATCH($C54,'3_UK_L1_Input'!$A$4:$A$14,0))*P54,INDEX('3_UK_L1_Input'!$D$4:$D$14,MATCH($C54,'3_UK_L1_Input'!$A$4:$A$14,0))*J54) | R54: =IF(K54="",INDEX('3_UK_L1_Input'!$D$4:$D$14,MATCH($C54,'3_UK_L1_Input'!$A$4:$A$14,0))*P54,INDEX('3_UK_L1_Input'!$D$4:$D$14,MATCH($C54,'3_UK_L1_Input'!$A$4:$A$14,0))*K54) | S54: =IF(G54="","BETA CASCADE FALLBACK (dummy — replace with real beta)","REAL (Bloomberg UK)") | T54: =INDEX('3_UK_L1_Input'!$C$4:$C$14,MATCH($C54,'3_UK_L1_Input'!$A$4:$A$14,0)) | U54: =INDEX('3_UK_L1_Input'!$C$4:$C$14,MATCH($C54,'3_UK_L1_Input'!$A$4:$A$14,0))*P54 | V54: =INDEX('5_UK_DefaultRisk_Input'!$D$5:$D$15,MATCH($C54,'5_UK_DefaultRisk_Input'!$A$5:$A$15,0)) | W54: =INDEX('5_UK_DefaultRisk_Input'!$D$20:$D$44,MATCH($E54,'5_UK_DefaultRisk_Input'!$A$20:$A$44,0)) | X54: =INDEX('5_UK_DefaultRisk_Input'!$D$49:$D$122,MATCH($D54,'5_UK_DefaultRisk_Input'!$A$49:$A$122,0)) | Y54: =INDEX('5_UK_DefaultRisk_Input'!$D$127:$D$289,MATCH($A54,'5_UK_DefaultRisk_Input'!$A$127:$A$289,0)) | Z54: =(W54/V54)*(X54/W54)*(Y54/X54) | AA54: =INDEX('3_UK_L1_Input'!$D$4:$D$14,MATCH($C54,'3_UK_L1_Input'!$A$4:$A$14,0))*Z54
A55: 25101020 | B55: Tires & Rubber | C55: 25 | D55: 251010 | E55: 2510 | H55: =IFERROR(SUMPRODUCT(($C$3:$C$165=C55)*ISNUMBER($G$3:$G$165)*ISNUMBER($F$3:$F$165)*IF(ISNUMBER($F$3:$F$165),$F$3:$F$165,0)*IF(ISNUMBER($G$3:$G$165),$G$3:$G$165,0))/SUMPRODUCT(($C$3:$C$165=C55)*ISNUMBER($G$3:$G$165)*ISNUMBER($F$3:$F$165)*IF(ISNUMBER($F$3:$F$165),$F$3:$F$165,0)),"") | I55: =IFERROR(SUMPRODUCT(($C$3:$C$165=C55)*ISNUMBER($G$3:$G$165)*IF(ISNUMBER($G$3:$G$165),$G$3:$G$165,0))/SUMPRODUCT(($C$3:$C$165=C55)*ISNUMBER($G$3:$G$165)),"") | J55: =IF(OR(G55="",H55=""),"",G55/H55) | K55: =IF(OR(G55="",I55=""),"",G55/I55) | L55: =INDEX('4_UK_Beta_Input'!$D$5:$D$15,MATCH($C55,'4_UK_Beta_Input'!$A$5:$A$15,0)) | M55: =INDEX('4_UK_Beta_Input'!$D$20:$D$44,MATCH($E55,'4_UK_Beta_Input'!$A$20:$A$44,0)) | N55: =INDEX('4_UK_Beta_Input'!$D$49:$D$122,MATCH($D55,'4_UK_Beta_Input'!$A$49:$A$122,0)) | O55: =INDEX('4_UK_Beta_Input'!$D$127:$D$289,MATCH($A55,'4_UK_Beta_Input'!$A$127:$A$289,0)) | P55: =(M55/L55)*(N55/M55)*(O55/N55) | Q55: =IF(J55="",INDEX('3_UK_L1_Input'!$D$4:$D$14,MATCH($C55,'3_UK_L1_Input'!$A$4:$A$14,0))*P55,INDEX('3_UK_L1_Input'!$D$4:$D$14,MATCH($C55,'3_UK_L1_Input'!$A$4:$A$14,0))*J55) | R55: =IF(K55="",INDEX('3_UK_L1_Input'!$D$4:$D$14,MATCH($C55,'3_UK_L1_Input'!$A$4:$A$14,0))*P55,INDEX('3_UK_L1_Input'!$D$4:$D$14,MATCH($C55,'3_UK_L1_Input'!$A$4:$A$14,0))*K55) | S55: =IF(G55="","BETA CASCADE FALLBACK (dummy — replace with real beta)","REAL (Bloomberg UK)") | T55: =INDEX('3_UK_L1_Input'!$C$4:$C$14,MATCH($C55,'3_UK_L1_Input'!$A$4:$A$14,0)) | U55: =INDEX('3_UK_L1_Input'!$C$4:$C$14,MATCH($C55,'3_UK_L1_Input'!$A$4:$A$14,0))*P55 | V55: =INDEX('5_UK_DefaultRisk_Input'!$D$5:$D$15,MATCH($C55,'5_UK_DefaultRisk_Input'!$A$5:$A$15,0)) | W55: =INDEX('5_UK_DefaultRisk_Input'!$D$20:$D$44,MATCH($E55,'5_UK_DefaultRisk_Input'!$A$20:$A$44,0)) | X55: =INDEX('5_UK_DefaultRisk_Input'!$D$49:$D$122,MATCH($D55,'5_UK_DefaultRisk_Input'!$A$49:$A$122,0)) | Y55: =INDEX('5_UK_DefaultRisk_Input'!$D$127:$D$289,MATCH($A55,'5_UK_DefaultRisk_Input'!$A$127:$A$289,0)) | Z55: =(W55/V55)*(X55/W55)*(Y55/X55) | AA55: =INDEX('3_UK_L1_Input'!$D$4:$D$14,MATCH($C55,'3_UK_L1_Input'!$A$4:$A$14,0))*Z55
A56: 25102010 | B56: Automobile Manufacturers | C56: 25 | D56: 251020 | E56: 2510 | F56: 1430000000 | G56: 6.3 | H56: =IFERROR(SUMPRODUCT(($C$3:$C$165=C56)*ISNUMBER($G$3:$G$165)*ISNUMBER($F$3:$F$165)*IF(ISNUMBER($F$3:$F$165),$F$3:$F$165,0)*IF(ISNUMBER($G$3:$G$165),$G$3:$G$165,0))/SUMPRODUCT(($C$3:$C$165=C56)*ISNUMBER($G$3:$G$165)*ISNUMBER($F$3:$F$165)*IF(ISNUMBER($F$3:$F$165),$F$3:$F$165,0)),"") | I56: =IFERROR(SUMPRODUCT(($C$3:$C$165=C56)*ISNUMBER($G$3:$G$165)*IF(ISNUMBER($G$3:$G$165),$G$3:$G$165,0))/SUMPRODUCT(($C$3:$C$165=C56)*ISNUMBER($G$3:$G$165)),"") | J56: =IF(OR(G56="",H56=""),"",G56/H56) | K56: =IF(OR(G56="",I56=""),"",G56/I56) | L56: =INDEX('4_UK_Beta_Input'!$D$5:$D$15,MATCH($C56,'4_UK_Beta_Input'!$A$5:$A$15,0)) | M56: =INDEX('4_UK_Beta_Input'!$D$20:$D$44,MATCH($E56,'4_UK_Beta_Input'!$A$20:$A$44,0)) | N56: =INDEX('4_UK_Beta_Input'!$D$49:$D$122,MATCH($D56,'4_UK_Beta_Input'!$A$49:$A$122,0)) | O56: =INDEX('4_UK_Beta_Input'!$D$127:$D$289,MATCH($A56,'4_UK_Beta_Input'!$A$127:$A$289,0)) | P56: =(M56/L56)*(N56/M56)*(O56/N56) | Q56: =IF(J56="",INDEX('3_UK_L1_Input'!$D$4:$D$14,MATCH($C56,'3_UK_L1_Input'!$A$4:$A$14,0))*P56,INDEX('3_UK_L1_Input'!$D$4:$D$14,MATCH($C56,'3_UK_L1_Input'!$A$4:$A$14,0))*J56) | R56: =IF(K56="",INDEX('3_UK_L1_Input'!$D$4:$D$14,MATCH($C56,'3_UK_L1_Input'!$A$4:$A$14,0))*P56,INDEX('3_UK_L1_Input'!$D$4:$D$14,MATCH($C56,'3_UK_L1_Input'!$A$4:$A$14,0))*K56) | S56: =IF(G56="","BETA CASCADE FALLBACK (dummy — replace with real beta)","REAL (Bloomberg UK)") | T56: =INDEX('3_UK_L1_Input'!$C$4:$C$14,MATCH($C56,'3_UK_L1_Input'!$A$4:$A$14,0)) | U56: =INDEX('3_UK_L1_Input'!$C$4:$C$14,MATCH($C56,'3_UK_L1_Input'!$A$4:$A$14,0))*P56 | V56: =INDEX('5_UK_DefaultRisk_Input'!$D$5:$D$15,MATCH($C56,'5_UK_DefaultRisk_Input'!$A$5:$A$15,0)) | W56: =INDEX('5_UK_DefaultRisk_Input'!$D$20:$D$44,MATCH($E56,'5_UK_DefaultRisk_Input'!$A$20:$A$44,0)) | X56: =INDEX('5_UK_DefaultRisk_Input'!$D$49:$D$122,MATCH($D56,'5_UK_DefaultRisk_Input'!$A$49:$A$122,0)) | Y56: =INDEX('5_UK_DefaultRisk_Input'!$D$127:$D$289,MATCH($A56,'5_UK_DefaultRisk_Input'!$A$127:$A$289,0)) | Z56: =(W56/V56)*(X56/W56)*(Y56/X56) | AA56: =INDEX('3_UK_L1_Input'!$D$4:$D$14,MATCH($C56,'3_UK_L1_Input'!$A$4:$A$14,0))*Z56
A57: 25102020 | B57: Motorcycle Manufacturers | C57: 25 | D57: 251020 | E57: 2510 | H57: =IFERROR(SUMPRODUCT(($C$3:$C$165=C57)*ISNUMBER($G$3:$G$165)*ISNUMBER($F$3:$F$165)*IF(ISNUMBER($F$3:$F$165),$F$3:$F$165,0)*IF(ISNUMBER($G$3:$G$165),$G$3:$G$165,0))/SUMPRODUCT(($C$3:$C$165=C57)*ISNUMBER($G$3:$G$165)*ISNUMBER($F$3:$F$165)*IF(ISNUMBER($F$3:$F$165),$F$3:$F$165,0)),"") | I57: =IFERROR(SUMPRODUCT(($C$3:$C$165=C57)*ISNUMBER($G$3:$G$165)*IF(ISNUMBER($G$3:$G$165),$G$3:$G$165,0))/SUMPRODUCT(($C$3:$C$165=C57)*ISNUMBER($G$3:$G$165)),"") | J57: =IF(OR(G57="",H57=""),"",G57/H57) | K57: =IF(OR(G57="",I57=""),"",G57/I57) | L57: =INDEX('4_UK_Beta_Input'!$D$5:$D$15,MATCH($C57,'4_UK_Beta_Input'!$A$5:$A$15,0)) | M57: =INDEX('4_UK_Beta_Input'!$D$20:$D$44,MATCH($E57,'4_UK_Beta_Input'!$A$20:$A$44,0)) | N57: =INDEX('4_UK_Beta_Input'!$D$49:$D$122,MATCH($D57,'4_UK_Beta_Input'!$A$49:$A$122,0)) | O57: =INDEX('4_UK_Beta_Input'!$D$127:$D$289,MATCH($A57,'4_UK_Beta_Input'!$A$127:$A$289,0)) | P57: =(M57/L57)*(N57/M57)*(O57/N57) | Q57: =IF(J57="",INDEX('3_UK_L1_Input'!$D$4:$D$14,MATCH($C57,'3_UK_L1_Input'!$A$4:$A$14,0))*P57,INDEX('3_UK_L1_Input'!$D$4:$D$14,MATCH($C57,'3_UK_L1_Input'!$A$4:$A$14,0))*J57) | R57: =IF(K57="",INDEX('3_UK_L1_Input'!$D$4:$D$14,MATCH($C57,'3_UK_L1_Input'!$A$4:$A$14,0))*P57,INDEX('3_UK_L1_Input'!$D$4:$D$14,MATCH($C57,'3_UK_L1_Input'!$A$4:$A$14,0))*K57) | S57: =IF(G57="","BETA CASCADE FALLBACK (dummy — replace with real beta)","REAL (Bloomberg UK)") | T57: =INDEX('3_UK_L1_Input'!$C$4:$C$14,MATCH($C57,'3_UK_L1_Input'!$A$4:$A$14,0)) | U57: =INDEX('3_UK_L1_Input'!$C$4:$C$14,MATCH($C57,'3_UK_L1_Input'!$A$4:$A$14,0))*P57 | V57: =INDEX('5_UK_DefaultRisk_Input'!$D$5:$D$15,MATCH($C57,'5_UK_DefaultRisk_Input'!$A$5:$A$15,0)) | W57: =INDEX('5_UK_DefaultRisk_Input'!$D$20:$D$44,MATCH($E57,'5_UK_DefaultRisk_Input'!$A$20:$A$44,0)) | X57: =INDEX('5_UK_DefaultRisk_Input'!$D$49:$D$122,MATCH($D57,'5_UK_DefaultRisk_Input'!$A$49:$A$122,0)) | Y57: =INDEX('5_UK_DefaultRisk_Input'!$D$127:$D$289,MATCH($A57,'5_UK_DefaultRisk_Input'!$A$127:$A$289,0)) | Z57: =(W57/V57)*(X57/W57)*(Y57/X57) | AA57: =INDEX('3_UK_L1_Input'!$D$4:$D$14,MATCH($C57,'3_UK_L1_Input'!$A$4:$A$14,0))*Z57
A58: 25201010 | B58: Consumer Electronics | C58: 25 | D58: 252010 | E58: 2520 | F58: 196060000 | G58: 7.26 | H58: =IFERROR(SUMPRODUCT(($C$3:$C$165=C58)*ISNUMBER($G$3:$G$165)*ISNUMBER($F$3:$F$165)*IF(ISNUMBER($F$3:$F$165),$F$3:$F$165,0)*IF(ISNUMBER($G$3:$G$165),$G$3:$G$165,0))/SUMPRODUCT(($C$3:$C$165=C58)*ISNUMBER($G$3:$G$165)*ISNUMBER($F$3:$F$165)*IF(ISNUMBER($F$3:$F$165),$F$3:$F$165,0)),"") | I58: =IFERROR(SUMPRODUCT(($C$3:$C$165=C58)*ISNUMBER($G$3:$G$165)*IF(ISNUMBER($G$3:$G$165),$G$3:$G$165,0))/SUMPRODUCT(($C$3:$C$165=C58)*ISNUMBER($G$3:$G$165)),"") | J58: =IF(OR(G58="",H58=""),"",G58/H58) | K58: =IF(OR(G58="",I58=""),"",G58/I58) | L58: =INDEX('4_UK_Beta_Input'!$D$5:$D$15,MATCH($C58,'4_UK_Beta_Input'!$A$5:$A$15,0)) | M58: =INDEX('4_UK_Beta_Input'!$D$20:$D$44,MATCH($E58,'4_UK_Beta_Input'!$A$20:$A$44,0)) | N58: =INDEX('4_UK_Beta_Input'!$D$49:$D$122,MATCH($D58,'4_UK_Beta_Input'!$A$49:$A$122,0)) | O58: =INDEX('4_UK_Beta_Input'!$D$127:$D$289,MATCH($A58,'4_UK_Beta_Input'!$A$127:$A$289,0)) | P58: =(M58/L58)*(N58/M58)*(O58/N58) | Q58: =IF(J58="",INDEX('3_UK_L1_Input'!$D$4:$D$14,MATCH($C58,'3_UK_L1_Input'!$A$4:$A$14,0))*P58,INDEX('3_UK_L1_Input'!$D$4:$D$14,MATCH($C58,'3_UK_L1_Input'!$A$4:$A$14,0))*J58) | R58: =IF(K58="",INDEX('3_UK_L1_Input'!$D$4:$D$14,MATCH($C58,'3_UK_L1_Input'!$A$4:$A$14,0))*P58,INDEX('3_UK_L1_Input'!$D$4:$D$14,MATCH($C58,'3_UK_L1_Input'!$A$4:$A$14,0))*K58) | S58: =IF(G58="","BETA CASCADE FALLBACK (dummy — replace with real beta)","REAL (Bloomberg UK)") | T58: =INDEX('3_UK_L1_Input'!$C$4:$C$14,MATCH($C58,'3_UK_L1_Input'!$A$4:$A$14,0)) | U58: =INDEX('3_UK_L1_Input'!$C$4:$C$14,MATCH($C58,'3_UK_L1_Input'!$A$4:$A$14,0))*P58 | V58: =INDEX('5_UK_DefaultRisk_Input'!$D$5:$D$15,MATCH($C58,'5_UK_DefaultRisk_Input'!$A$5:$A$15,0)) | W58: =INDEX('5_UK_DefaultRisk_Input'!$D$20:$D$44,MATCH($E58,'5_UK_DefaultRisk_Input'!$A$20:$A$44,0)) | X58: =INDEX('5_UK_DefaultRisk_Input'!$D$49:$D$122,MATCH($D58,'5_UK_DefaultRisk_Input'!$A$49:$A$122,0)) | Y58: =INDEX('5_UK_DefaultRisk_Input'!$D$127:$D$289,MATCH($A58,'5_UK_DefaultRisk_Input'!$A$127:$A$289,0)) | Z58: =(W58/V58)*(X58/W58)*(Y58/X58) | AA58: =INDEX('3_UK_L1_Input'!$D$4:$D$14,MATCH($C58,'3_UK_L1_Input'!$A$4:$A$14,0))*Z58
A59: 25201020 | B59: Home Furnishings | C59: 25 | D59: 252010 | E59: 2520 | F59: 321410000 | G59: 6.76 | H59: =IFERROR(SUMPRODUCT(($C$3:$C$165=C59)*ISNUMBER($G$3:$G$165)*ISNUMBER($F$3:$F$165)*IF(ISNUMBER($F$3:$F$165),$F$3:$F$165,0)*IF(ISNUMBER($G$3:$G$165),$G$3:$G$165,0))/SUMPRODUCT(($C$3:$C$165=C59)*ISNUMBER($G$3:$G$165)*ISNUMBER($F$3:$F$165)*IF(ISNUMBER($F$3:$F$165),$F$3:$F$165,0)),"") | I59: =IFERROR(SUMPRODUCT(($C$3:$C$165=C59)*ISNUMBER($G$3:$G$165)*IF(ISNUMBER($G$3:$G$165),$G$3:$G$165,0))/SUMPRODUCT(($C$3:$C$165=C59)*ISNUMBER($G$3:$G$165)),"") | J59: =IF(OR(G59="",H59=""),"",G59/H59) | K59: =IF(OR(G59="",I59=""),"",G59/I59) | L59: =INDEX('4_UK_Beta_Input'!$D$5:$D$15,MATCH($C59,'4_UK_Beta_Input'!$A$5:$A$15,0)) | M59: =INDEX('4_UK_Beta_Input'!$D$20:$D$44,MATCH($E59,'4_UK_Beta_Input'!$A$20:$A$44,0)) | N59: =INDEX('4_UK_Beta_Input'!$D$49:$D$122,MATCH($D59,'4_UK_Beta_Input'!$A$49:$A$122,0)) | O59: =INDEX('4_UK_Beta_Input'!$D$127:$D$289,MATCH($A59,'4_UK_Beta_Input'!$A$127:$A$289,0)) | P59: =(M59/L59)*(N59/M59)*(O59/N59) | Q59: =IF(J59="",INDEX('3_UK_L1_Input'!$D$4:$D$14,MATCH($C59,'3_UK_L1_Input'!$A$4:$A$14,0))*P59,INDEX('3_UK_L1_Input'!$D$4:$D$14,MATCH($C59,'3_UK_L1_Input'!$A$4:$A$14,0))*J59) | R59: =IF(K59="",INDEX('3_UK_L1_Input'!$D$4:$D$14,MATCH($C59,'3_UK_L1_Input'!$A$4:$A$14,0))*P59,INDEX('3_UK_L1_Input'!$D$4:$D$14,MATCH($C59,'3_UK_L1_Input'!$A$4:$A$14,0))*K59) | S59: =IF(G59="","BETA CASCADE FALLBACK (dummy — replace with real beta)","REAL (Bloomberg UK)") | T59: =INDEX('3_UK_L1_Input'!$C$4:$C$14,MATCH($C59,'3_UK_L1_Input'!$A$4:$A$14,0)) | U59: =INDEX('3_UK_L1_Input'!$C$4:$C$14,MATCH($C59,'3_UK_L1_Input'!$A$4:$A$14,0))*P59 | V59: =INDEX('5_UK_DefaultRisk_Input'!$D$5:$D$15,MATCH($C59,'5_UK_DefaultRisk_Input'!$A$5:$A$15,0)) | W59: =INDEX('5_UK_DefaultRisk_Input'!$D$20:$D$44,MATCH($E59,'5_UK_DefaultRisk_Input'!$A$20:$A$44,0)) | X59: =INDEX('5_UK_DefaultRisk_Input'!$D$49:$D$122,MATCH($D59,'5_UK_DefaultRisk_Input'!$A$49:$A$122,0)) | Y59: =INDEX('5_UK_DefaultRisk_Input'!$D$127:$D$289,MATCH($A59,'5_UK_DefaultRisk_Input'!$A$127:$A$289,0)) | Z59: =(W59/V59)*(X59/W59)*(Y59/X59) | AA59: =INDEX('3_UK_L1_Input'!$D$4:$D$14,MATCH($C59,'3_UK_L1_Input'!$A$4:$A$14,0))*Z59
A60: 25201030 | B60: Homebuilding | C60: 25 | D60: 252010 | E60: 2520 | F60: 2020000000 | G60: 7.39 | H60: =IFERROR(SUMPRODUCT(($C$3:$C$165=C60)*ISNUMBER($G$3:$G$165)*ISNUMBER($F$3:$F$165)*IF(ISNUMBER($F$3:$F$165),$F$3:$F$165,0)*IF(ISNUMBER($G$3:$G$165),$G$3:$G$165,0))/SUMPRODUCT(($C$3:$C$165=C60)*ISNUMBER($G$3:$G$165)*ISNUMBER($F$3:$F$165)*IF(ISNUMBER($F$3:$F$165),$F$3:$F$165,0)),"") | I60: =IFERROR(SUMPRODUCT(($C$3:$C$165=C60)*ISNUMBER($G$3:$G$165)*IF(ISNUMBER($G$3:$G$165),$G$3:$G$165,0))/SUMPRODUCT(($C$3:$C$165=C60)*ISNUMBER($G$3:$G$165)),"") | J60: =IF(OR(G60="",H60=""),"",G60/H60) | K60: =IF(OR(G60="",I60=""),"",G60/I60) | L60: =INDEX('4_UK_Beta_Input'!$D$5:$D$15,MATCH($C60,'4_UK_Beta_Input'!$A$5:$A$15,0)) | M60: =INDEX('4_UK_Beta_Input'!$D$20:$D$44,MATCH($E60,'4_UK_Beta_Input'!$A$20:$A$44,0)) | N60: =INDEX('4_UK_Beta_Input'!$D$49:$D$122,MATCH($D60,'4_UK_Beta_Input'!$A$49:$A$122,0)) | O60: =INDEX('4_UK_Beta_Input'!$D$127:$D$289,MATCH($A60,'4_UK_Beta_Input'!$A$127:$A$289,0)) | P60: =(M60/L60)*(N60/M60)*(O60/N60) | Q60: =IF(J60="",INDEX('3_UK_L1_Input'!$D$4:$D$14,MATCH($C60,'3_UK_L1_Input'!$A$4:$A$14,0))*P60,INDEX('3_UK_L1_Input'!$D$4:$D$14,MATCH($C60,'3_UK_L1_Input'!$A$4:$A$14,0))*J60) | R60: =IF(K60="",INDEX('3_UK_L1_Input'!$D$4:$D$14,MATCH($C60,'3_UK_L1_Input'!$A$4:$A$14,0))*P60,INDEX('3_UK_L1_Input'!$D$4:$D$14,MATCH($C60,'3_UK_L1_Input'!$A$4:$A$14,0))*K60) | S60: =IF(G60="","BETA CASCADE FALLBACK (dummy — replace with real beta)","REAL (Bloomberg UK)") | T60: =INDEX('3_UK_L1_Input'!$C$4:$C$14,MATCH($C60,'3_UK_L1_Input'!$A$4:$A$14,0)) | U60: =INDEX('3_UK_L1_Input'!$C$4:$C$14,MATCH($C60,'3_UK_L1_Input'!$A$4:$A$14,0))*P60 | V60: =INDEX('5_UK_DefaultRisk_Input'!$D$5:$D$15,MATCH($C60,'5_UK_DefaultRisk_Input'!$A$5:$A$15,0)) | W60: =INDEX('5_UK_DefaultRisk_Input'!$D$20:$D$44,MATCH($E60,'5_UK_DefaultRisk_Input'!$A$20:$A$44,0)) | X60: =INDEX('5_UK_DefaultRisk_Input'!$D$49:$D$122,MATCH($D60,'5_UK_DefaultRisk_Input'!$A$49:$A$122,0)) | Y60: =INDEX('5_UK_DefaultRisk_Input'!$D$127:$D$289,MATCH($A60,'5_UK_DefaultRisk_Input'!$A$127:$A$289,0)) | Z60: =(W60/V60)*(X60/W60)*(Y60/X60) | AA60: =INDEX('3_UK_L1_Input'!$D$4:$D$14,MATCH($C60,'3_UK_L1_Input'!$A$4:$A$14,0))*Z60
A61: 25201040 | B61: Household Appliances | C61: 25 | D61: 252010 | E61: 2520 | F61: 426540000 | G61: 7.75 | H61: =IFERROR(SUMPRODUCT(($C$3:$C$165=C61)*ISNUMBER($G$3:$G$165)*ISNUMBER($F$3:$F$165)*IF(ISNUMBER($F$3:$F$165),$F$3:$F$165,0)*IF(ISNUMBER($G$3:$G$165),$G$3:$G$165,0))/SUMPRODUCT(($C$3:$C$165=C61)*ISNUMBER($G$3:$G$165)*ISNUMBER($F$3:$F$165)*IF(ISNUMBER($F$3:$F$165),$F$3:$F$165,0)),"") | I61: =IFERROR(SUMPRODUCT(($C$3:$C$165=C61)*ISNUMBER($G$3:$G$165)*IF(ISNUMBER($G$3:$G$165),$G$3:$G$165,0))/SUMPRODUCT(($C$3:$C$165=C61)*ISNUMBER($G$3:$G$165)),"") | J61: =IF(OR(G61="",H61=""),"",G61/H61) | K61: =IF(OR(G61="",I61=""),"",G61/I61) | L61: =INDEX('4_UK_Beta_Input'!$D$5:$D$15,MATCH($C61,'4_UK_Beta_Input'!$A$5:$A$15,0)) | M61: =INDEX('4_UK_Beta_Input'!$D$20:$D$44,MATCH($E61,'4_UK_Beta_Input'!$A$20:$A$44,0)) | N61: =INDEX('4_UK_Beta_Input'!$D$49:$D$122,MATCH($D61,'4_UK_Beta_Input'!$A$49:$A$122,0)) | O61: =INDEX('4_UK_Beta_Input'!$D$127:$D$289,MATCH($A61,'4_UK_Beta_Input'!$A$127:$A$289,0)) | P61: =(M61/L61)*(N61/M61)*(O61/N61) | Q61: =IF(J61="",INDEX('3_UK_L1_Input'!$D$4:$D$14,MATCH($C61,'3_UK_L1_Input'!$A$4:$A$14,0))*P61,INDEX('3_UK_L1_Input'!$D$4:$D$14,MATCH($C61,'3_UK_L1_Input'!$A$4:$A$14,0))*J61) | R61: =IF(K61="",INDEX('3_UK_L1_Input'!$D$4:$D$14,MATCH($C61,'3_UK_L1_Input'!$A$4:$A$14,0))*P61,INDEX('3_UK_L1_Input'!$D$4:$D$14,MATCH($C61,'3_UK_L1_Input'!$A$4:$A$14,0))*K61) | S61: =IF(G61="","BETA CASCADE FALLBACK (dummy — replace with real beta)","REAL (Bloomberg UK)") | T61: =INDEX('3_UK_L1_Input'!$C$4:$C$14,MATCH($C61,'3_UK_L1_Input'!$A$4:$A$14,0)) | U61: =INDEX('3_UK_L1_Input'!$C$4:$C$14,MATCH($C61,'3_UK_L1_Input'!$A$4:$A$14,0))*P61 | V61: =INDEX('5_UK_DefaultRisk_Input'!$D$5:$D$15,MATCH($C61,'5_UK_DefaultRisk_Input'!$A$5:$A$15,0)) | W61: =INDEX('5_UK_DefaultRisk_Input'!$D$20:$D$44,MATCH($E61,'5_UK_DefaultRisk_Input'!$A$20:$A$44,0)) | X61: =INDEX('5_UK_DefaultRisk_Input'!$D$49:$D$122,MATCH($D61,'5_UK_DefaultRisk_Input'!$A$49:$A$122,0)) | Y61: =INDEX('5_UK_DefaultRisk_Input'!$D$127:$D$289,MATCH($A61,'5_UK_DefaultRisk_Input'!$A$127:$A$289,0)) | Z61: =(W61/V61)*(X61/W61)*(Y61/X61) | AA61: =INDEX('3_UK_L1_Input'!$D$4:$D$14,MATCH($C61,'3_UK_L1_Input'!$A$4:$A$14,0))*Z61
A62: 25201050 | B62: Housewares & Specialties | C62: 25 | D62: 252010 | E62: 2520 | F62: 128400000 | G62: 6.28 | H62: =IFERROR(SUMPRODUCT(($C$3:$C$165=C62)*ISNUMBER($G$3:$G$165)*ISNUMBER($F$3:$F$165)*IF(ISNUMBER($F$3:$F$165),$F$3:$F$165,0)*IF(ISNUMBER($G$3:$G$165),$G$3:$G$165,0))/SUMPRODUCT(($C$3:$C$165=C62)*ISNUMBER($G$3:$G$165)*ISNUMBER($F$3:$F$165)*IF(ISNUMBER($F$3:$F$165),$F$3:$F$165,0)),"") | I62: =IFERROR(SUMPRODUCT(($C$3:$C$165=C62)*ISNUMBER($G$3:$G$165)*IF(ISNUMBER($G$3:$G$165),$G$3:$G$165,0))/SUMPRODUCT(($C$3:$C$165=C62)*ISNUMBER($G$3:$G$165)),"") | J62: =IF(OR(G62="",H62=""),"",G62/H62) | K62: =IF(OR(G62="",I62=""),"",G62/I62) | L62: =INDEX('4_UK_Beta_Input'!$D$5:$D$15,MATCH($C62,'4_UK_Beta_Input'!$A$5:$A$15,0)) | M62: =INDEX('4_UK_Beta_Input'!$D$20:$D$44,MATCH($E62,'4_UK_Beta_Input'!$A$20:$A$44,0)) | N62: =INDEX('4_UK_Beta_Input'!$D$49:$D$122,MATCH($D62,'4_UK_Beta_Input'!$A$49:$A$122,0)) | O62: =INDEX('4_UK_Beta_Input'!$D$127:$D$289,MATCH($A62,'4_UK_Beta_Input'!$A$127:$A$289,0)) | P62: =(M62/L62)*(N62/M62)*(O62/N62) | Q62: =IF(J62="",INDEX('3_UK_L1_Input'!$D$4:$D$14,MATCH($C62,'3_UK_L1_Input'!$A$4:$A$14,0))*P62,INDEX('3_UK_L1_Input'!$D$4:$D$14,MATCH($C62,'3_UK_L1_Input'!$A$4:$A$14,0))*J62) | R62: =IF(K62="",INDEX('3_UK_L1_Input'!$D$4:$D$14,MATCH($C62,'3_UK_L1_Input'!$A$4:$A$14,0))*P62,INDEX('3_UK_L1_Input'!$D$4:$D$14,MATCH($C62,'3_UK_L1_Input'!$A$4:$A$14,0))*K62) | S62: =IF(G62="","BETA CASCADE FALLBACK (dummy — replace with real beta)","REAL (Bloomberg UK)") | T62: =INDEX('3_UK_L1_Input'!$C$4:$C$14,MATCH($C62,'3_UK_L1_Input'!$A$4:$A$14,0)) | U62: =INDEX('3_UK_L1_Input'!$C$4:$C$14,MATCH($C62,'3_UK_L1_Input'!$A$4:$A$14,0))*P62 | V62: =INDEX('5_UK_DefaultRisk_Input'!$D$5:$D$15,MATCH($C62,'5_UK_DefaultRisk_Input'!$A$5:$A$15,0)) | W62: =INDEX('5_UK_DefaultRisk_Input'!$D$20:$D$44,MATCH($E62,'5_UK_DefaultRisk_Input'!$A$20:$A$44,0)) | X62: =INDEX('5_UK_DefaultRisk_Input'!$D$49:$D$122,MATCH($D62,'5_UK_DefaultRisk_Input'!$A$49:$A$122,0)) | Y62: =INDEX('5_UK_DefaultRisk_Input'!$D$127:$D$289,MATCH($A62,'5_UK_DefaultRisk_Input'!$A$127:$A$289,0)) | Z62: =(W62/V62)*(X62/W62)*(Y62/X62) | AA62: =INDEX('3_UK_L1_Input'!$D$4:$D$14,MATCH($C62,'3_UK_L1_Input'!$A$4:$A$14,0))*Z62
A63: 25202010 | B63: Leisure Products | C63: 25 | D63: 252020 | E63: 2520 | F63: 260530000 | G63: 11.68 | H63: =IFERROR(SUMPRODUCT(($C$3:$C$165=C63)*ISNUMBER($G$3:$G$165)*ISNUMBER($F$3:$F$165)*IF(ISNUMBER($F$3:$F$165),$F$3:$F$165,0)*IF(ISNUMBER($G$3:$G$165),$G$3:$G$165,0))/SUMPRODUCT(($C$3:$C$165=C63)*ISNUMBER($G$3:$G$165)*ISNUMBER($F$3:$F$165)*IF(ISNUMBER($F$3:$F$165),$F$3:$F$165,0)),"") | I63: =IFERROR(SUMPRODUCT(($C$3:$C$165=C63)*ISNUMBER($G$3:$G$165)*IF(ISNUMBER($G$3:$G$165),$G$3:$G$165,0))/SUMPRODUCT(($C$3:$C$165=C63)*ISNUMBER($G$3:$G$165)),"") | J63: =IF(OR(G63="",H63=""),"",G63/H63) | K63: =IF(OR(G63="",I63=""),"",G63/I63) | L63: =INDEX('4_UK_Beta_Input'!$D$5:$D$15,MATCH($C63,'4_UK_Beta_Input'!$A$5:$A$15,0)) | M63: =INDEX('4_UK_Beta_Input'!$D$20:$D$44,MATCH($E63,'4_UK_Beta_Input'!$A$20:$A$44,0)) | N63: =INDEX('4_UK_Beta_Input'!$D$49:$D$122,MATCH($D63,'4_UK_Beta_Input'!$A$49:$A$122,0)) | O63: =INDEX('4_UK_Beta_Input'!$D$127:$D$289,MATCH($A63,'4_UK_Beta_Input'!$A$127:$A$289,0)) | P63: =(M63/L63)*(N63/M63)*(O63/N63) | Q63: =IF(J63="",INDEX('3_UK_L1_Input'!$D$4:$D$14,MATCH($C63,'3_UK_L1_Input'!$A$4:$A$14,0))*P63,INDEX('3_UK_L1_Input'!$D$4:$D$14,MATCH($C63,'3_UK_L1_Input'!$A$4:$A$14,0))*J63) | R63: =IF(K63="",INDEX('3_UK_L1_Input'!$D$4:$D$14,MATCH($C63,'3_UK_L1_Input'!$A$4:$A$14,0))*P63,INDEX('3_UK_L1_Input'!$D$4:$D$14,MATCH($C63,'3_UK_L1_Input'!$A$4:$A$14,0))*K63) | S63: =IF(G63="","BETA CASCADE FALLBACK (dummy — replace with real beta)","REAL (Bloomberg UK)") | T63: =INDEX('3_UK_L1_Input'!$C$4:$C$14,MATCH($C63,'3_UK_L1_Input'!$A$4:$A$14,0)) | U63: =INDEX('3_UK_L1_Input'!$C$4:$C$14,MATCH($C63,'3_UK_L1_Input'!$A$4:$A$14,0))*P63 | V63: =INDEX('5_UK_DefaultRisk_Input'!$D$5:$D$15,MATCH($C63,'5_UK_DefaultRisk_Input'!$A$5:$A$15,0)) | W63: =INDEX('5_UK_DefaultRisk_Input'!$D$20:$D$44,MATCH($E63,'5_UK_DefaultRisk_Input'!$A$20:$A$44,0)) | X63: =INDEX('5_UK_DefaultRisk_Input'!$D$49:$D$122,MATCH($D63,'5_UK_DefaultRisk_Input'!$A$49:$A$122,0)) | Y63: =INDEX('5_UK_DefaultRisk_Input'!$D$127:$D$289,MATCH($A63,'5_UK_DefaultRisk_Input'!$A$127:$A$289,0)) | Z63: =(W63/V63)*(X63/W63)*(Y63/X63) | AA63: =INDEX('3_UK_L1_Input'!$D$4:$D$14,MATCH($C63,'3_UK_L1_Input'!$A$4:$A$14,0))*Z63
A64: 25203010 | B64: Apparel, Accessories & Luxury Goods | C64: 25 | D64: 252030 | E64: 2520 | F64: 1210000000 | G64: 7.24 | H64: =IFERROR(SUMPRODUCT(($C$3:$C$165=C64)*ISNUMBER($G$3:$G$165)*ISNUMBER($F$3:$F$165)*IF(ISNUMBER($F$3:$F$165),$F$3:$F$165,0)*IF(ISNUMBER($G$3:$G$165),$G$3:$G$165,0))/SUMPRODUCT(($C$3:$C$165=C64)*ISNUMBER($G$3:$G$165)*ISNUMBER($F$3:$F$165)*IF(ISNUMBER($F$3:$F$165),$F$3:$F$165,0)),"") | I64: =IFERROR(SUMPRODUCT(($C$3:$C$165=C64)*ISNUMBER($G$3:$G$165)*IF(ISNUMBER($G$3:$G$165),$G$3:$G$165,0))/SUMPRODUCT(($C$3:$C$165=C64)*ISNUMBER($G$3:$G$165)),"") | J64: =IF(OR(G64="",H64=""),"",G64/H64) | K64: =IF(OR(G64="",I64=""),"",G64/I64) | L64: =INDEX('4_UK_Beta_Input'!$D$5:$D$15,MATCH($C64,'4_UK_Beta_Input'!$A$5:$A$15,0)) | M64: =INDEX('4_UK_Beta_Input'!$D$20:$D$44,MATCH($E64,'4_UK_Beta_Input'!$A$20:$A$44,0)) | N64: =INDEX('4_UK_Beta_Input'!$D$49:$D$122,MATCH($D64,'4_UK_Beta_Input'!$A$49:$A$122,0)) | O64: =INDEX('4_UK_Beta_Input'!$D$127:$D$289,MATCH($A64,'4_UK_Beta_Input'!$A$127:$A$289,0)) | P64: =(M64/L64)*(N64/M64)*(O64/N64) | Q64: =IF(J64="",INDEX('3_UK_L1_Input'!$D$4:$D$14,MATCH($C64,'3_UK_L1_Input'!$A$4:$A$14,0))*P64,INDEX('3_UK_L1_Input'!$D$4:$D$14,MATCH($C64,'3_UK_L1_Input'!$A$4:$A$14,0))*J64) | R64: =IF(K64="",INDEX('3_UK_L1_Input'!$D$4:$D$14,MATCH($C64,'3_UK_L1_Input'!$A$4:$A$14,0))*P64,INDEX('3_UK_L1_Input'!$D$4:$D$14,MATCH($C64,'3_UK_L1_Input'!$A$4:$A$14,0))*K64) | S64: =IF(G64="","BETA CASCADE FALLBACK (dummy — replace with real beta)","REAL (Bloomberg UK)") | T64: =INDEX('3_UK_L1_Input'!$C$4:$C$14,MATCH($C64,'3_UK_L1_Input'!$A$4:$A$14,0)) | U64: =INDEX('3_UK_L1_Input'!$C$4:$C$14,MATCH($C64,'3_UK_L1_Input'!$A$4:$A$14,0))*P64 | V64: =INDEX('5_UK_DefaultRisk_Input'!$D$5:$D$15,MATCH($C64,'5_UK_DefaultRisk_Input'!$A$5:$A$15,0)) | W64: =INDEX('5_UK_DefaultRisk_Input'!$D$20:$D$44,MATCH($E64,'5_UK_DefaultRisk_Input'!$A$20:$A$44,0)) | X64: =INDEX('5_UK_DefaultRisk_Input'!$D$49:$D$122,MATCH($D64,'5_UK_DefaultRisk_Input'!$A$49:$A$122,0)) | Y64: =INDEX('5_UK_DefaultRisk_Input'!$D$127:$D$289,MATCH($A64,'5_UK_DefaultRisk_Input'!$A$127:$A$289,0)) | Z64: =(W64/V64)*(X64/W64)*(Y64/X64) | AA64: =INDEX('3_UK_L1_Input'!$D$4:$D$14,MATCH($C64,'3_UK_L1_Input'!$A$4:$A$14,0))*Z64
A65: 25203020 | B65: Footwear | C65: 25 | D65: 252030 | E65: 2520 | F65: 1470000000 | G65: 7.46 | H65: =IFERROR(SUMPRODUCT(($C$3:$C$165=C65)*ISNUMBER($G$3:$G$165)*ISNUMBER($F$3:$F$165)*IF(ISNUMBER($F$3:$F$165),$F$3:$F$165,0)*IF(ISNUMBER($G$3:$G$165),$G$3:$G$165,0))/SUMPRODUCT(($C$3:$C$165=C65)*ISNUMBER($G$3:$G$165)*ISNUMBER($F$3:$F$165)*IF(ISNUMBER($F$3:$F$165),$F$3:$F$165,0)),"") | I65: =IFERROR(SUMPRODUCT(($C$3:$C$165=C65)*ISNUMBER($G$3:$G$165)*IF(ISNUMBER($G$3:$G$165),$G$3:$G$165,0))/SUMPRODUCT(($C$3:$C$165=C65)*ISNUMBER($G$3:$G$165)),"") | J65: =IF(OR(G65="",H65=""),"",G65/H65) | K65: =IF(OR(G65="",I65=""),"",G65/I65) | L65: =INDEX('4_UK_Beta_Input'!$D$5:$D$15,MATCH($C65,'4_UK_Beta_Input'!$A$5:$A$15,0)) | M65: =INDEX('4_UK_Beta_Input'!$D$20:$D$44,MATCH($E65,'4_UK_Beta_Input'!$A$20:$A$44,0)) | N65: =INDEX('4_UK_Beta_Input'!$D$49:$D$122,MATCH($D65,'4_UK_Beta_Input'!$A$49:$A$122,0)) | O65: =INDEX('4_UK_Beta_Input'!$D$127:$D$289,MATCH($A65,'4_UK_Beta_Input'!$A$127:$A$289,0)) | P65: =(M65/L65)*(N65/M65)*(O65/N65) | Q65: =IF(J65="",INDEX('3_UK_L1_Input'!$D$4:$D$14,MATCH($C65,'3_UK_L1_Input'!$A$4:$A$14,0))*P65,INDEX('3_UK_L1_Input'!$D$4:$D$14,MATCH($C65,'3_UK_L1_Input'!$A$4:$A$14,0))*J65) | R65: =IF(K65="",INDEX('3_UK_L1_Input'!$D$4:$D$14,MATCH($C65,'3_UK_L1_Input'!$A$4:$A$14,0))*P65,INDEX('3_UK_L1_Input'!$D$4:$D$14,MATCH($C65,'3_UK_L1_Input'!$A$4:$A$14,0))*K65) | S65: =IF(G65="","BETA CASCADE FALLBACK (dummy — replace with real beta)","REAL (Bloomberg UK)") | T65: =INDEX('3_UK_L1_Input'!$C$4:$C$14,MATCH($C65,'3_UK_L1_Input'!$A$4:$A$14,0)) | U65: =INDEX('3_UK_L1_Input'!$C$4:$C$14,MATCH($C65,'3_UK_L1_Input'!$A$4:$A$14,0))*P65 | V65: =INDEX('5_UK_DefaultRisk_Input'!$D$5:$D$15,MATCH($C65,'5_UK_DefaultRisk_Input'!$A$5:$A$15,0)) | W65: =INDEX('5_UK_DefaultRisk_Input'!$D$20:$D$44,MATCH($E65,'5_UK_DefaultRisk_Input'!$A$20:$A$44,0)) | X65: =INDEX('5_UK_DefaultRisk_Input'!$D$49:$D$122,MATCH($D65,'5_UK_DefaultRisk_Input'!$A$49:$A$122,0)) | Y65: =INDEX('5_UK_DefaultRisk_Input'!$D$127:$D$289,MATCH($A65,'5_UK_DefaultRisk_Input'!$A$127:$A$289,0)) | Z65: =(W65/V65)*(X65/W65)*(Y65/X65) | AA65: =INDEX('3_UK_L1_Input'!$D$4:$D$14,MATCH($C65,'3_UK_L1_Input'!$A$4:$A$14,0))*Z65
A66: 25203030 | B66: Textiles | C66: 25 | D66: 252030 | E66: 2520 | F66: 1600000000 | G66: 7.15 | H66: =IFERROR(SUMPRODUCT(($C$3:$C$165=C66)*ISNUMBER($G$3:$G$165)*ISNUMBER($F$3:$F$165)*IF(ISNUMBER($F$3:$F$165),$F$3:$F$165,0)*IF(ISNUMBER($G$3:$G$165),$G$3:$G$165,0))/SUMPRODUCT(($C$3:$C$165=C66)*ISNUMBER($G$3:$G$165)*ISNUMBER($F$3:$F$165)*IF(ISNUMBER($F$3:$F$165),$F$3:$F$165,0)),"") | I66: =IFERROR(SUMPRODUCT(($C$3:$C$165=C66)*ISNUMBER($G$3:$G$165)*IF(ISNUMBER($G$3:$G$165),$G$3:$G$165,0))/SUMPRODUCT(($C$3:$C$165=C66)*ISNUMBER($G$3:$G$165)),"") | J66: =IF(OR(G66="",H66=""),"",G66/H66) | K66: =IF(OR(G66="",I66=""),"",G66/I66) | L66: =INDEX('4_UK_Beta_Input'!$D$5:$D$15,MATCH($C66,'4_UK_Beta_Input'!$A$5:$A$15,0)) | M66: =INDEX('4_UK_Beta_Input'!$D$20:$D$44,MATCH($E66,'4_UK_Beta_Input'!$A$20:$A$44,0)) | N66: =INDEX('4_UK_Beta_Input'!$D$49:$D$122,MATCH($D66,'4_UK_Beta_Input'!$A$49:$A$122,0)) | O66: =INDEX('4_UK_Beta_Input'!$D$127:$D$289,MATCH($A66,'4_UK_Beta_Input'!$A$127:$A$289,0)) | P66: =(M66/L66)*(N66/M66)*(O66/N66) | Q66: =IF(J66="",INDEX('3_UK_L1_Input'!$D$4:$D$14,MATCH($C66,'3_UK_L1_Input'!$A$4:$A$14,0))*P66,INDEX('3_UK_L1_Input'!$D$4:$D$14,MATCH($C66,'3_UK_L1_Input'!$A$4:$A$14,0))*J66) | R66: =IF(K66="",INDEX('3_UK_L1_Input'!$D$4:$D$14,MATCH($C66,'3_UK_L1_Input'!$A$4:$A$14,0))*P66,INDEX('3_UK_L1_Input'!$D$4:$D$14,MATCH($C66,'3_UK_L1_Input'!$A$4:$A$14,0))*K66) | S66: =IF(G66="","BETA CASCADE FALLBACK (dummy — replace with real beta)","REAL (Bloomberg UK)") | T66: =INDEX('3_UK_L1_Input'!$C$4:$C$14,MATCH($C66,'3_UK_L1_Input'!$A$4:$A$14,0)) | U66: =INDEX('3_UK_L1_Input'!$C$4:$C$14,MATCH($C66,'3_UK_L1_Input'!$A$4:$A$14,0))*P66 | V66: =INDEX('5_UK_DefaultRisk_Input'!$D$5:$D$15,MATCH($C66,'5_UK_DefaultRisk_Input'!$A$5:$A$15,0)) | W66: =INDEX('5_UK_DefaultRisk_Input'!$D$20:$D$44,MATCH($E66,'5_UK_DefaultRisk_Input'!$A$20:$A$44,0)) | X66: =INDEX('5_UK_DefaultRisk_Input'!$D$49:$D$122,MATCH($D66,'5_UK_DefaultRisk_Input'!$A$49:$A$122,0)) | Y66: =INDEX('5_UK_DefaultRisk_Input'!$D$127:$D$289,MATCH($A66,'5_UK_DefaultRisk_Input'!$A$127:$A$289,0)) | Z66: =(W66/V66)*(X66/W66)*(Y66/X66) | AA66: =INDEX('3_UK_L1_Input'!$D$4:$D$14,MATCH($C66,'3_UK_L1_Input'!$A$4:$A$14,0))*Z66
A67: 25301010 | B67: Casinos & Gaming | C67: 25 | D67: 253010 | E67: 2530 | F67: 1740000000 | G67: 7.29 | H67: =IFERROR(SUMPRODUCT(($C$3:$C$165=C67)*ISNUMBER($G$3:$G$165)*ISNUMBER($F$3:$F$165)*IF(ISNUMBER($F$3:$F$165),$F$3:$F$165,0)*IF(ISNUMBER($G$3:$G$165),$G$3:$G$165,0))/SUMPRODUCT(($C$3:$C$165=C67)*ISNUMBER($G$3:$G$165)*ISNUMBER($F$3:$F$165)*IF(ISNUMBER($F$3:$F$165),$F$3:$F$165,0)),"") | I67: =IFERROR(SUMPRODUCT(($C$3:$C$165=C67)*ISNUMBER($G$3:$G$165)*IF(ISNUMBER($G$3:$G$165),$G$3:$G$165,0))/SUMPRODUCT(($C$3:$C$165=C67)*ISNUMBER($G$3:$G$165)),"") | J67: =IF(OR(G67="",H67=""),"",G67/H67) | K67: =IF(OR(G67="",I67=""),"",G67/I67) | L67: =INDEX('4_UK_Beta_Input'!$D$5:$D$15,MATCH($C67,'4_UK_Beta_Input'!$A$5:$A$15,0)) | M67: =INDEX('4_UK_Beta_Input'!$D$20:$D$44,MATCH($E67,'4_UK_Beta_Input'!$A$20:$A$44,0)) | N67: =INDEX('4_UK_Beta_Input'!$D$49:$D$122,MATCH($D67,'4_UK_Beta_Input'!$A$49:$A$122,0)) | O67: =INDEX('4_UK_Beta_Input'!$D$127:$D$289,MATCH($A67,'4_UK_Beta_Input'!$A$127:$A$289,0)) | P67: =(M67/L67)*(N67/M67)*(O67/N67) | Q67: =IF(J67="",INDEX('3_UK_L1_Input'!$D$4:$D$14,MATCH($C67,'3_UK_L1_Input'!$A$4:$A$14,0))*P67,INDEX('3_UK_L1_Input'!$D$4:$D$14,MATCH($C67,'3_UK_L1_Input'!$A$4:$A$14,0))*J67) | R67: =IF(K67="",INDEX('3_UK_L1_Input'!$D$4:$D$14,MATCH($C67,'3_UK_L1_Input'!$A$4:$A$14,0))*P67,INDEX('3_UK_L1_Input'!$D$4:$D$14,MATCH($C67,'3_UK_L1_Input'!$A$4:$A$14,0))*K67) | S67: =IF(G67="","BETA CASCADE FALLBACK (dummy — replace with real beta)","REAL (Bloomberg UK)") | T67: =INDEX('3_UK_L1_Input'!$C$4:$C$14,MATCH($C67,'3_UK_L1_Input'!$A$4:$A$14,0)) | U67: =INDEX('3_UK_L1_Input'!$C$4:$C$14,MATCH($C67,'3_UK_L1_Input'!$A$4:$A$14,0))*P67 | V67: =INDEX('5_UK_DefaultRisk_Input'!$D$5:$D$15,MATCH($C67,'5_UK_DefaultRisk_Input'!$A$5:$A$15,0)) | W67: =INDEX('5_UK_DefaultRisk_Input'!$D$20:$D$44,MATCH($E67,'5_UK_DefaultRisk_Input'!$A$20:$A$44,0)) | X67: =INDEX('5_UK_DefaultRisk_Input'!$D$49:$D$122,MATCH($D67,'5_UK_DefaultRisk_Input'!$A$49:$A$122,0)) | Y67: =INDEX('5_UK_DefaultRisk_Input'!$D$127:$D$289,MATCH($A67,'5_UK_DefaultRisk_Input'!$A$127:$A$289,0)) | Z67: =(W67/V67)*(X67/W67)*(Y67/X67) | AA67: =INDEX('3_UK_L1_Input'!$D$4:$D$14,MATCH($C67,'3_UK_L1_Input'!$A$4:$A$14,0))*Z67
A68: 25301020 | B68: Hotels, Resorts & Cruise Lines | C68: 25 | D68: 253010 | E68: 2530 | F68: 1270000000 | G68: 9.21 | H68: =IFERROR(SUMPRODUCT(($C$3:$C$165=C68)*ISNUMBER($G$3:$G$165)*ISNUMBER($F$3:$F$165)*IF(ISNUMBER($F$3:$F$165),$F$3:$F$165,0)*IF(ISNUMBER($G$3:$G$165),$G$3:$G$165,0))/SUMPRODUCT(($C$3:$C$165=C68)*ISNUMBER($G$3:$G$165)*ISNUMBER($F$3:$F$165)*IF(ISNUMBER($F$3:$F$165),$F$3:$F$165,0)),"") | I68: =IFERROR(SUMPRODUCT(($C$3:$C$165=C68)*ISNUMBER($G$3:$G$165)*IF(ISNUMBER($G$3:$G$165),$G$3:$G$165,0))/SUMPRODUCT(($C$3:$C$165=C68)*ISNUMBER($G$3:$G$165)),"") | J68: =IF(OR(G68="",H68=""),"",G68/H68) | K68: =IF(OR(G68="",I68=""),"",G68/I68) | L68: =INDEX('4_UK_Beta_Input'!$D$5:$D$15,MATCH($C68,'4_UK_Beta_Input'!$A$5:$A$15,0)) | M68: =INDEX('4_UK_Beta_Input'!$D$20:$D$44,MATCH($E68,'4_UK_Beta_Input'!$A$20:$A$44,0)) | N68: =INDEX('4_UK_Beta_Input'!$D$49:$D$122,MATCH($D68,'4_UK_Beta_Input'!$A$49:$A$122,0)) | O68: =INDEX('4_UK_Beta_Input'!$D$127:$D$289,MATCH($A68,'4_UK_Beta_Input'!$A$127:$A$289,0)) | P68: =(M68/L68)*(N68/M68)*(O68/N68) | Q68: =IF(J68="",INDEX('3_UK_L1_Input'!$D$4:$D$14,MATCH($C68,'3_UK_L1_Input'!$A$4:$A$14,0))*P68,INDEX('3_UK_L1_Input'!$D$4:$D$14,MATCH($C68,'3_UK_L1_Input'!$A$4:$A$14,0))*J68) | R68: =IF(K68="",INDEX('3_UK_L1_Input'!$D$4:$D$14,MATCH($C68,'3_UK_L1_Input'!$A$4:$A$14,0))*P68,INDEX('3_UK_L1_Input'!$D$4:$D$14,MATCH($C68,'3_UK_L1_Input'!$A$4:$A$14,0))*K68) | S68: =IF(G68="","BETA CASCADE FALLBACK (dummy — replace with real beta)","REAL (Bloomberg UK)") | T68: =INDEX('3_UK_L1_Input'!$C$4:$C$14,MATCH($C68,'3_UK_L1_Input'!$A$4:$A$14,0)) | U68: =INDEX('3_UK_L1_Input'!$C$4:$C$14,MATCH($C68,'3_UK_L1_Input'!$A$4:$A$14,0))*P68 | V68: =INDEX('5_UK_DefaultRisk_Input'!$D$5:$D$15,MATCH($C68,'5_UK_DefaultRisk_Input'!$A$5:$A$15,0)) | W68: =INDEX('5_UK_DefaultRisk_Input'!$D$20:$D$44,MATCH($E68,'5_UK_DefaultRisk_Input'!$A$20:$A$44,0)) | X68: =INDEX('5_UK_DefaultRisk_Input'!$D$49:$D$122,MATCH($D68,'5_UK_DefaultRisk_Input'!$A$49:$A$122,0)) | Y68: =INDEX('5_UK_DefaultRisk_Input'!$D$127:$D$289,MATCH($A68,'5_UK_DefaultRisk_Input'!$A$127:$A$289,0)) | Z68: =(W68/V68)*(X68/W68)*(Y68/X68) | AA68: =INDEX('3_UK_L1_Input'!$D$4:$D$14,MATCH($C68,'3_UK_L1_Input'!$A$4:$A$14,0))*Z68
A69: 25301030 | B69: Leisure Facilities | C69: 25 | D69: 253010 | E69: 2530 | F69: 148090000 | G69: 6.4 | H69: =IFERROR(SUMPRODUCT(($C$3:$C$165=C69)*ISNUMBER($G$3:$G$165)*ISNUMBER($F$3:$F$165)*IF(ISNUMBER($F$3:$F$165),$F$3:$F$165,0)*IF(ISNUMBER($G$3:$G$165),$G$3:$G$165,0))/SUMPRODUCT(($C$3:$C$165=C69)*ISNUMBER($G$3:$G$165)*ISNUMBER($F$3:$F$165)*IF(ISNUMBER($F$3:$F$165),$F$3:$F$165,0)),"") | I69: =IFERROR(SUMPRODUCT(($C$3:$C$165=C69)*ISNUMBER($G$3:$G$165)*IF(ISNUMBER($G$3:$G$165),$G$3:$G$165,0))/SUMPRODUCT(($C$3:$C$165=C69)*ISNUMBER($G$3:$G$165)),"") | J69: =IF(OR(G69="",H69=""),"",G69/H69) | K69: =IF(OR(G69="",I69=""),"",G69/I69) | L69: =INDEX('4_UK_Beta_Input'!$D$5:$D$15,MATCH($C69,'4_UK_Beta_Input'!$A$5:$A$15,0)) | M69: =INDEX('4_UK_Beta_Input'!$D$20:$D$44,MATCH($E69,'4_UK_Beta_Input'!$A$20:$A$44,0)) | N69: =INDEX('4_UK_Beta_Input'!$D$49:$D$122,MATCH($D69,'4_UK_Beta_Input'!$A$49:$A$122,0)) | O69: =INDEX('4_UK_Beta_Input'!$D$127:$D$289,MATCH($A69,'4_UK_Beta_Input'!$A$127:$A$289,0)) | P69: =(M69/L69)*(N69/M69)*(O69/N69) | Q69: =IF(J69="",INDEX('3_UK_L1_Input'!$D$4:$D$14,MATCH($C69,'3_UK_L1_Input'!$A$4:$A$14,0))*P69,INDEX('3_UK_L1_Input'!$D$4:$D$14,MATCH($C69,'3_UK_L1_Input'!$A$4:$A$14,0))*J69) | R69: =IF(K69="",INDEX('3_UK_L1_Input'!$D$4:$D$14,MATCH($C69,'3_UK_L1_Input'!$A$4:$A$14,0))*P69,INDEX('3_UK_L1_Input'!$D$4:$D$14,MATCH($C69,'3_UK_L1_Input'!$A$4:$A$14,0))*K69) | S69: =IF(G69="","BETA CASCADE FALLBACK (dummy — replace with real beta)","REAL (Bloomberg UK)") | T69: =INDEX('3_UK_L1_Input'!$C$4:$C$14,MATCH($C69,'3_UK_L1_Input'!$A$4:$A$14,0)) | U69: =INDEX('3_UK_L1_Input'!$C$4:$C$14,MATCH($C69,'3_UK_L1_Input'!$A$4:$A$14,0))*P69 | V69: =INDEX('5_UK_DefaultRisk_Input'!$D$5:$D$15,MATCH($C69,'5_UK_DefaultRisk_Input'!$A$5:$A$15,0)) | W69: =INDEX('5_UK_DefaultRisk_Input'!$D$20:$D$44,MATCH($E69,'5_UK_DefaultRisk_Input'!$A$20:$A$44,0)) | X69: =INDEX('5_UK_DefaultRisk_Input'!$D$49:$D$122,MATCH($D69,'5_UK_DefaultRisk_Input'!$A$49:$A$122,0)) | Y69: =INDEX('5_UK_DefaultRisk_Input'!$D$127:$D$289,MATCH($A69,'5_UK_DefaultRisk_Input'!$A$127:$A$289,0)) | Z69: =(W69/V69)*(X69/W69)*(Y69/X69) | AA69: =INDEX('3_UK_L1_Input'!$D$4:$D$14,MATCH($C69,'3_UK_L1_Input'!$A$4:$A$14,0))*Z69
... A80: 25504060 | B80: Homefurnishing Retail | C80: 25 | D80: 255040 | E80: 2550 | F80: 359370000 | G80: 4.6 | H80: =IFERROR(SUMPRODUCT(($C$3:$C$165=C80)*ISNUMBER($G$3:$G$165)*ISNUMBER($F$3:$F$165)*IF(ISNUMBER($F$3:$F$165),$F$3:$F$165,0)*IF(ISNUMBER($G$3:$G$165),$G$3:$G$165,0))/SUMPRODUCT(($C$3:$C$165=C80)*ISNUMBER($G$3:$G$165)*ISNUMBER($F$3:$F$165)*IF(ISNUMBER($F$3:$F$165),$F$3:$F$165,0)),"") | I80: =IFERROR(SUMPRODUCT(($C$3:$C$165=C80)*ISNUMBER($G$3:$G$165)*IF(ISNUMBER($G$3:$G$165),$G$3:$G$165,0))/SUMPRODUCT(($C$3:$C$165=C80)*ISNUMBER($G$3:$G$165)),"") | J80: =IF(OR(G80="",H80=""),"",G80/H80) | K80: =IF(OR(G80="",I80=""),"",G80/I80) | L80: =INDEX('4_UK_Beta_Input'!$D$5:$D$15,MATCH($C80,'4_UK_Beta_Input'!$A$5:$A$15,0)) | M80: =INDEX('4_UK_Beta_Input'!$D$20:$D$44,MATCH($E80,'4_UK_Beta_Input'!$A$20:$A$44,0)) | N80: =INDEX('4_UK_Beta_Input'!$D$49:$D$122,MATCH($D80,'4_UK_Beta_Input'!$A$49:$A$122,0)) | O80: =INDEX('4_UK_Beta_Input'!$D$127:$D$289,MATCH($A80,'4_UK_Beta_Input'!$A$127:$A$289,0)) | P80: =(M80/L80)*(N80/M80)*(O80/N80) | Q80: =IF(J80="",INDEX('3_UK_L1_Input'!$D$4:$D$14,MATCH($C80,'3_UK_L1_Input'!$A$4:$A$14,0))*P80,INDEX('3_UK_L1_Input'!$D$4:$D$14,MATCH($C80,'3_UK_L1_Input'!$A$4:$A$14,0))*J80) | R80: =IF(K80="",INDEX('3_UK_L1_Input'!$D$4:$D$14,MATCH($C80,'3_UK_L1_Input'!$A$4:$A$14,0))*P80,INDEX('3_UK_L1_Input'!$D$4:$D$14,MATCH($C80,'3_UK_L1_Input'!$A$4:$A$14,0))*K80) | S80: =IF(G80="","BETA CASCADE FALLBACK (dummy — replace with real beta)","REAL (Bloomberg UK)") | T80: =INDEX('3_UK_L1_Input'!$C$4:$C$14,MATCH($C80,'3_UK_L1_Input'!$A$4:$A$14,0)) | U80: =INDEX('3_UK_L1_Input'!$C$4:$C$14,MATCH($C80,'3_UK_L1_Input'!$A$4:$A$14,0))*P80 | V80: =INDEX('5_UK_DefaultRisk_Input'!$D$5:$D$15,MATCH($C80,'5_UK_DefaultRisk_Input'!$A$5:$A$15,0)) | W80: =INDEX('5_UK_DefaultRisk_Input'!$D$20:$D$44,MATCH($E80,'5_UK_DefaultRisk_Input'!$A$20:$A$44,0)) | X80: =INDEX('5_UK_DefaultRisk_Input'!$D$49:$D$122,MATCH($D80,'5_UK_DefaultRisk_Input'!$A$49:$A$122,0)) | Y80: =INDEX('5_UK_DefaultRisk_Input'!$D$127:$D$289,MATCH($A80,'5_UK_DefaultRisk_Input'!$A$127:$A$289,0)) | Z80: =(W80/V80)*(X80/W80)*(Y80/X80) | AA80: =INDEX('3_UK_L1_Input'!$D$4:$D$14,MATCH($C80,'3_UK_L1_Input'!$A$4:$A$14,0))*Z80
A81: 30101010 | B81: Drug Retail | C81: 30 | D81: 301010 | E81: 3010 | H81: =IFERROR(SUMPRODUCT(($C$3:$C$165=C81)*ISNUMBER($G$3:$G$165)*ISNUMBER($F$3:$F$165)*IF(ISNUMBER($F$3:$F$165),$F$3:$F$165,0)*IF(ISNUMBER($G$3:$G$165),$G$3:$G$165,0))/SUMPRODUCT(($C$3:$C$165=C81)*ISNUMBER($G$3:$G$165)*ISNUMBER($F$3:$F$165)*IF(ISNUMBER($F$3:$F$165),$F$3:$F$165,0)),"") | I81: =IFERROR(SUMPRODUCT(($C$3:$C$165=C81)*ISNUMBER($G$3:$G$165)*IF(ISNUMBER($G$3:$G$165),$G$3:$G$165,0))/SUMPRODUCT(($C$3:$C$165=C81)*ISNUMBER($G$3:$G$165)),"") | J81: =IF(OR(G81="",H81=""),"",G81/H81) | K81: =IF(OR(G81="",I81=""),"",G81/I81) | L81: =INDEX('4_UK_Beta_Input'!$D$5:$D$15,MATCH($C81,'4_UK_Beta_Input'!$A$5:$A$15,0)) | M81: =INDEX('4_UK_Beta_Input'!$D$20:$D$44,MATCH($E81,'4_UK_Beta_Input'!$A$20:$A$44,0)) | N81: =INDEX('4_UK_Beta_Input'!$D$49:$D$122,MATCH($D81,'4_UK_Beta_Input'!$A$49:$A$122,0)) | O81: =INDEX('4_UK_Beta_Input'!$D$127:$D$289,MATCH($A81,'4_UK_Beta_Input'!$A$127:$A$289,0)) | P81: =(M81/L81)*(N81/M81)*(O81/N81) | Q81: =IF(J81="",INDEX('3_UK_L1_Input'!$D$4:$D$14,MATCH($C81,'3_UK_L1_Input'!$A$4:$A$14,0))*P81,INDEX('3_UK_L1_Input'!$D$4:$D$14,MATCH($C81,'3_UK_L1_Input'!$A$4:$A$14,0))*J81) | R81: =IF(K81="",INDEX('3_UK_L1_Input'!$D$4:$D$14,MATCH($C81,'3_UK_L1_Input'!$A$4:$A$14,0))*P81,INDEX('3_UK_L1_Input'!$D$4:$D$14,MATCH($C81,'3_UK_L1_Input'!$A$4:$A$14,0))*K81) | S81: =IF(G81="","BETA CASCADE FALLBACK (dummy — replace with real beta)","REAL (Bloomberg UK)") | T81: =INDEX('3_UK_L1_Input'!$C$4:$C$14,MATCH($C81,'3_UK_L1_Input'!$A$4:$A$14,0)) | U81: =INDEX('3_UK_L1_Input'!$C$4:$C$14,MATCH($C81,'3_UK_L1_Input'!$A$4:$A$14,0))*P81 | V81: =INDEX('5_UK_DefaultRisk_Input'!$D$5:$D$15,MATCH($C81,'5_UK_DefaultRisk_Input'!$A$5:$A$15,0)) | W81: =INDEX('5_UK_DefaultRisk_Input'!$D$20:$D$44,MATCH($E81,'5_UK_DefaultRisk_Input'!$A$20:$A$44,0)) | X81: =INDEX('5_UK_DefaultRisk_Input'!$D$49:$D$122,MATCH($D81,'5_UK_DefaultRisk_Input'!$A$49:$A$122,0)) | Y81: =INDEX('5_UK_DefaultRisk_Input'!$D$127:$D$289,MATCH($A81,'5_UK_DefaultRisk_Input'!$A$127:$A$289,0)) | Z81: =(W81/V81)*(X81/W81)*(Y81/X81) | AA81: =INDEX('3_UK_L1_Input'!$D$4:$D$14,MATCH($C81,'3_UK_L1_Input'!$A$4:$A$14,0))*Z81
A82: 30101020 | B82: Food Distributors | C82: 30 | D82: 301010 | E82: 3010 | H82: =IFERROR(SUMPRODUCT(($C$3:$C$165=C82)*ISNUMBER($G$3:$G$165)*ISNUMBER($F$3:$F$165)*IF(ISNUMBER($F$3:$F$165),$F$3:$F$165,0)*IF(ISNUMBER($G$3:$G$165),$G$3:$G$165,0))/SUMPRODUCT(($C$3:$C$165=C82)*ISNUMBER($G$3:$G$165)*ISNUMBER($F$3:$F$165)*IF(ISNUMBER($F$3:$F$165),$F$3:$F$165,0)),"") | I82: =IFERROR(SUMPRODUCT(($C$3:$C$165=C82)*ISNUMBER($G$3:$G$165)*IF(ISNUMBER($G$3:$G$165),$G$3:$G$165,0))/SUMPRODUCT(($C$3:$C$165=C82)*ISNUMBER($G$3:$G$165)),"") | J82: =IF(OR(G82="",H82=""),"",G82/H82) | K82: =IF(OR(G82="",I82=""),"",G82/I82) | L82: =INDEX('4_UK_Beta_Input'!$D$5:$D$15,MATCH($C82,'4_UK_Beta_Input'!$A$5:$A$15,0)) | M82: =INDEX('4_UK_Beta_Input'!$D$20:$D$44,MATCH($E82,'4_UK_Beta_Input'!$A$20:$A$44,0)) | N82: =INDEX('4_UK_Beta_Input'!$D$49:$D$122,MATCH($D82,'4_UK_Beta_Input'!$A$49:$A$122,0)) | O82: =INDEX('4_UK_Beta_Input'!$D$127:$D$289,MATCH($A82,'4_UK_Beta_Input'!$A$127:$A$289,0)) | P82: =(M82/L82)*(N82/M82)*(O82/N82) | Q82: =IF(J82="",INDEX('3_UK_L1_Input'!$D$4:$D$14,MATCH($C82,'3_UK_L1_Input'!$A$4:$A$14,0))*P82,INDEX('3_UK_L1_Input'!$D$4:$D$14,MATCH($C82,'3_UK_L1_Input'!$A$4:$A$14,0))*J82) | R82: =IF(K82="",INDEX('3_UK_L1_Input'!$D$4:$D$14,MATCH($C82,'3_UK_L1_Input'!$A$4:$A$14,0))*P82,INDEX('3_UK_L1_Input'!$D$4:$D$14,MATCH($C82,'3_UK_L1_Input'!$A$4:$A$14,0))*K82) | S82: =IF(G82="","BETA CASCADE FALLBACK (dummy — replace with real beta)","REAL (Bloomberg UK)") | T82: =INDEX('3_UK_L1_Input'!$C$4:$C$14,MATCH($C82,'3_UK_L1_Input'!$A$4:$A$14,0)) | U82: =INDEX('3_UK_L1_Input'!$C$4:$C$14,MATCH($C82,'3_UK_L1_Input'!$A$4:$A$14,0))*P82 | V82: =INDEX('5_UK_DefaultRisk_Input'!$D$5:$D$15,MATCH($C82,'5_UK_DefaultRisk_Input'!$A$5:$A$15,0)) | W82: =INDEX('5_UK_DefaultRisk_Input'!$D$20:$D$44,MATCH($E82,'5_UK_DefaultRisk_Input'!$A$20:$A$44,0)) | X82: =INDEX('5_UK_DefaultRisk_Input'!$D$49:$D$122,MATCH($D82,'5_UK_DefaultRisk_Input'!$A$49:$A$122,0)) | Y82: =INDEX('5_UK_DefaultRisk_Input'!$D$127:$D$289,MATCH($A82,'5_UK_DefaultRisk_Input'!$A$127:$A$289,0)) | Z82: =(W82/V82)*(X82/W82)*(Y82/X82) | AA82: =INDEX('3_UK_L1_Input'!$D$4:$D$14,MATCH($C82,'3_UK_L1_Input'!$A$4:$A$14,0))*Z82
A83: 30101030 | B83: Food Retail | C83: 30 | D83: 301010 | E83: 3010 | F83: 18100000000 | G83: 5.77 | H83: =IFERROR(SUMPRODUCT(($C$3:$C$165=C83)*ISNUMBER($G$3:$G$165)*ISNUMBER($F$3:$F$165)*IF(ISNUMBER($F$3:$F$165),$F$3:$F$165,0)*IF(ISNUMBER($G$3:$G$165),$G$3:$G$165,0))/SUMPRODUCT(($C$3:$C$165=C83)*ISNUMBER($G$3:$G$165)*ISNUMBER($F$3:$F$165)*IF(ISNUMBER($F$3:$F$165),$F$3:$F$165,0)),"") | I83: =IFERROR(SUMPRODUCT(($C$3:$C$165=C83)*ISNUMBER($G$3:$G$165)*IF(ISNUMBER($G$3:$G$165),$G$3:$G$165,0))/SUMPRODUCT(($C$3:$C$165=C83)*ISNUMBER($G$3:$G$165)),"") | J83: =IF(OR(G83="",H83=""),"",G83/H83) | K83: =IF(OR(G83="",I83=""),"",G83/I83) | L83: =INDEX('4_UK_Beta_Input'!$D$5:$D$15,MATCH($C83,'4_UK_Beta_Input'!$A$5:$A$15,0)) | M83: =INDEX('4_UK_Beta_Input'!$D$20:$D$44,MATCH($E83,'4_UK_Beta_Input'!$A$20:$A$44,0)) | N83: =INDEX('4_UK_Beta_Input'!$D$49:$D$122,MATCH($D83,'4_UK_Beta_Input'!$A$49:$A$122,0)) | O83: =INDEX('4_UK_Beta_Input'!$D$127:$D$289,MATCH($A83,'4_UK_Beta_Input'!$A$127:$A$289,0)) | P83: =(M83/L83)*(N83/M83)*(O83/N83) | Q83: =IF(J83="",INDEX('3_UK_L1_Input'!$D$4:$D$14,MATCH($C83,'3_UK_L1_Input'!$A$4:$A$14,0))*P83,INDEX('3_UK_L1_Input'!$D$4:$D$14,MATCH($C83,'3_UK_L1_Input'!$A$4:$A$14,0))*J83) | R83: =IF(K83="",INDEX('3_UK_L1_Input'!$D$4:$D$14,MATCH($C83,'3_UK_L1_Input'!$A$4:$A$14,0))*P83,INDEX('3_UK_L1_Input'!$D$4:$D$14,MATCH($C83,'3_UK_L1_Input'!$A$4:$A$14,0))*K83) | S83: =IF(G83="","BETA CASCADE FALLBACK (dummy — replace with real beta)","REAL (Bloomberg UK)") | T83: =INDEX('3_UK_L1_Input'!$C$4:$C$14,MATCH($C83,'3_UK_L1_Input'!$A$4:$A$14,0)) | U83: =INDEX('3_UK_L1_Input'!$C$4:$C$14,MATCH($C83,'3_UK_L1_Input'!$A$4:$A$14,0))*P83 | V83: =INDEX('5_UK_DefaultRisk_Input'!$D$5:$D$15,MATCH($C83,'5_UK_DefaultRisk_Input'!$A$5:$A$15,0)) | W83: =INDEX('5_UK_DefaultRisk_Input'!$D$20:$D$44,MATCH($E83,'5_UK_DefaultRisk_Input'!$A$20:$A$44,0)) | X83: =INDEX('5_UK_DefaultRisk_Input'!$D$49:$D$122,MATCH($D83,'5_UK_DefaultRisk_Input'!$A$49:$A$122,0)) | Y83: =INDEX('5_UK_DefaultRisk_Input'!$D$127:$D$289,MATCH($A83,'5_UK_DefaultRisk_Input'!$A$127:$A$289,0)) | Z83: =(W83/V83)*(X83/W83)*(Y83/X83) | AA83: =INDEX('3_UK_L1_Input'!$D$4:$D$14,MATCH($C83,'3_UK_L1_Input'!$A$4:$A$14,0))*Z83
A84: 30101040 | B84: Consumer Staples Merchandise Retail | C84: 30 | D84: 301010 | E84: 3010 | H84: =IFERROR(SUMPRODUCT(($C$3:$C$165=C84)*ISNUMBER($G$3:$G$165)*ISNUMBER($F$3:$F$165)*IF(ISNUMBER($F$3:$F$165),$F$3:$F$165,0)*IF(ISNUMBER($G$3:$G$165),$G$3:$G$165,0))/SUMPRODUCT(($C$3:$C$165=C84)*ISNUMBER($G$3:$G$165)*ISNUMBER($F$3:$F$165)*IF(ISNUMBER($F$3:$F$165),$F$3:$F$165,0)),"") | I84: =IFERROR(SUMPRODUCT(($C$3:$C$165=C84)*ISNUMBER($G$3:$G$165)*IF(ISNUMBER($G$3:$G$165),$G$3:$G$165,0))/SUMPRODUCT(($C$3:$C$165=C84)*ISNUMBER($G$3:$G$165)),"") | J84: =IF(OR(G84="",H84=""),"",G84/H84) | K84: =IF(OR(G84="",I84=""),"",G84/I84) | L84: =INDEX('4_UK_Beta_Input'!$D$5:$D$15,MATCH($C84,'4_UK_Beta_Input'!$A$5:$A$15,0)) | M84: =INDEX('4_UK_Beta_Input'!$D$20:$D$44,MATCH($E84,'4_UK_Beta_Input'!$A$20:$A$44,0)) | N84: =INDEX('4_UK_Beta_Input'!$D$49:$D$122,MATCH($D84,'4_UK_Beta_Input'!$A$49:$A$122,0)) | O84: =INDEX('4_UK_Beta_Input'!$D$127:$D$289,MATCH($A84,'4_UK_Beta_Input'!$A$127:$A$289,0)) | P84: =(M84/L84)*(N84/M84)*(O84/N84) | Q84: =IF(J84="",INDEX('3_UK_L1_Input'!$D$4:$D$14,MATCH($C84,'3_UK_L1_Input'!$A$4:$A$14,0))*P84,INDEX('3_UK_L1_Input'!$D$4:$D$14,MATCH($C84,'3_UK_L1_Input'!$A$4:$A$14,0))*J84) | R84: =IF(K84="",INDEX('3_UK_L1_Input'!$D$4:$D$14,MATCH($C84,'3_UK_L1_Input'!$A$4:$A$14,0))*P84,INDEX('3_UK_L1_Input'!$D$4:$D$14,MATCH($C84,'3_UK_L1_Input'!$A$4:$A$14,0))*K84) | S84: =IF(G84="","BETA CASCADE FALLBACK (dummy — replace with real beta)","REAL (Bloomberg UK)") | T84: =INDEX('3_UK_L1_Input'!$C$4:$C$14,MATCH($C84,'3_UK_L1_Input'!$A$4:$A$14,0)) | U84: =INDEX('3_UK_L1_Input'!$C$4:$C$14,MATCH($C84,'3_UK_L1_Input'!$A$4:$A$14,0))*P84 | V84: =INDEX('5_UK_DefaultRisk_Input'!$D$5:$D$15,MATCH($C84,'5_UK_DefaultRisk_Input'!$A$5:$A$15,0)) | W84: =INDEX('5_UK_DefaultRisk_Input'!$D$20:$D$44,MATCH($E84,'5_UK_DefaultRisk_Input'!$A$20:$A$44,0)) | X84: =INDEX('5_UK_DefaultRisk_Input'!$D$49:$D$122,MATCH($D84,'5_UK_DefaultRisk_Input'!$A$49:$A$122,0)) | Y84: =INDEX('5_UK_DefaultRisk_Input'!$D$127:$D$289,MATCH($A84,'5_UK_DefaultRisk_Input'!$A$127:$A$289,0)) | Z84: =(W84/V84)*(X84/W84)*(Y84/X84) | AA84: =INDEX('3_UK_L1_Input'!$D$4:$D$14,MATCH($C84,'3_UK_L1_Input'!$A$4:$A$14,0))*Z84
A85: 30201010 | B85: Brewers | C85: 30 | D85: 302010 | E85: 3020 | F85: 113830000 | G85: 6.18 | H85: =IFERROR(SUMPRODUCT(($C$3:$C$165=C85)*ISNUMBER($G$3:$G$165)*ISNUMBER($F$3:$F$165)*IF(ISNUMBER($F$3:$F$165),$F$3:$F$165,0)*IF(ISNUMBER($G$3:$G$165),$G$3:$G$165,0))/SUMPRODUCT(($C$3:$C$165=C85)*ISNUMBER($G$3:$G$165)*ISNUMBER($F$3:$F$165)*IF(ISNUMBER($F$3:$F$165),$F$3:$F$165,0)),"") | I85: =IFERROR(SUMPRODUCT(($C$3:$C$165=C85)*ISNUMBER($G$3:$G$165)*IF(ISNUMBER($G$3:$G$165),$G$3:$G$165,0))/SUMPRODUCT(($C$3:$C$165=C85)*ISNUMBER($G$3:$G$165)),"") | J85: =IF(OR(G85="",H85=""),"",G85/H85) | K85: =IF(OR(G85="",I85=""),"",G85/I85) | L85: =INDEX('4_UK_Beta_Input'!$D$5:$D$15,MATCH($C85,'4_UK_Beta_Input'!$A$5:$A$15,0)) | M85: =INDEX('4_UK_Beta_Input'!$D$20:$D$44,MATCH($E85,'4_UK_Beta_Input'!$A$20:$A$44,0)) | N85: =INDEX('4_UK_Beta_Input'!$D$49:$D$122,MATCH($D85,'4_UK_Beta_Input'!$A$49:$A$122,0)) | O85: =INDEX('4_UK_Beta_Input'!$D$127:$D$289,MATCH($A85,'4_UK_Beta_Input'!$A$127:$A$289,0)) | P85: =(M85/L85)*(N85/M85)*(O85/N85) | Q85: =IF(J85="",INDEX('3_UK_L1_Input'!$D$4:$D$14,MATCH($C85,'3_UK_L1_Input'!$A$4:$A$14,0))*P85,INDEX('3_UK_L1_Input'!$D$4:$D$14,MATCH($C85,'3_UK_L1_Input'!$A$4:$A$14,0))*J85) | R85: =IF(K85="",INDEX('3_UK_L1_Input'!$D$4:$D$14,MATCH($C85,'3_UK_L1_Input'!$A$4:$A$14,0))*P85,INDEX('3_UK_L1_Input'!$D$4:$D$14,MATCH($C85,'3_UK_L1_Input'!$A$4:$A$14,0))*K85) | S85: =IF(G85="","BETA CASCADE FALLBACK (dummy — replace with real beta)","REAL (Bloomberg UK)") | T85: =INDEX('3_UK_L1_Input'!$C$4:$C$14,MATCH($C85,'3_UK_L1_Input'!$A$4:$A$14,0)) | U85: =INDEX('3_UK_L1_Input'!$C$4:$C$14,MATCH($C85,'3_UK_L1_Input'!$A$4:$A$14,0))*P85 | V85: =INDEX('5_UK_DefaultRisk_Input'!$D$5:$D$15,MATCH($C85,'5_UK_DefaultRisk_Input'!$A$5:$A$15,0)) | W85: =INDEX('5_UK_DefaultRisk_Input'!$D$20:$D$44,MATCH($E85,'5_UK_DefaultRisk_Input'!$A$20:$A$44,0)) | X85: =INDEX('5_UK_DefaultRisk_Input'!$D$49:$D$122,MATCH($D85,'5_UK_DefaultRisk_Input'!$A$49:$A$122,0)) | Y85: =INDEX('5_UK_DefaultRisk_Input'!$D$127:$D$289,MATCH($A85,'5_UK_DefaultRisk_Input'!$A$127:$A$289,0)) | Z85: =(W85/V85)*(X85/W85)*(Y85/X85) | AA85: =INDEX('3_UK_L1_Input'!$D$4:$D$14,MATCH($C85,'3_UK_L1_Input'!$A$4:$A$14,0))*Z85
A86: 30201020 | B86: Distillers & Vintners | C86: 30 | D86: 302010 | E86: 3020 | F86: 4920000000 | G86: 19.57 | H86: =IFERROR(SUMPRODUCT(($C$3:$C$165=C86)*ISNUMBER($G$3:$G$165)*ISNUMBER($F$3:$F$165)*IF(ISNUMBER($F$3:$F$165),$F$3:$F$165,0)*IF(ISNUMBER($G$3:$G$165),$G$3:$G$165,0))/SUMPRODUCT(($C$3:$C$165=C86)*ISNUMBER($G$3:$G$165)*ISNUMBER($F$3:$F$165)*IF(ISNUMBER($F$3:$F$165),$F$3:$F$165,0)),"") | I86: =IFERROR(SUMPRODUCT(($C$3:$C$165=C86)*ISNUMBER($G$3:$G$165)*IF(ISNUMBER($G$3:$G$165),$G$3:$G$165,0))/SUMPRODUCT(($C$3:$C$165=C86)*ISNUMBER($G$3:$G$165)),"") | J86: =IF(OR(G86="",H86=""),"",G86/H86) | K86: =IF(OR(G86="",I86=""),"",G86/I86) | L86: =INDEX('4_UK_Beta_Input'!$D$5:$D$15,MATCH($C86,'4_UK_Beta_Input'!$A$5:$A$15,0)) | M86: =INDEX('4_UK_Beta_Input'!$D$20:$D$44,MATCH($E86,'4_UK_Beta_Input'!$A$20:$A$44,0)) | N86: =INDEX('4_UK_Beta_Input'!$D$49:$D$122,MATCH($D86,'4_UK_Beta_Input'!$A$49:$A$122,0)) | O86: =INDEX('4_UK_Beta_Input'!$D$127:$D$289,MATCH($A86,'4_UK_Beta_Input'!$A$127:$A$289,0)) | P86: =(M86/L86)*(N86/M86)*(O86/N86) | Q86: =IF(J86="",INDEX('3_UK_L1_Input'!$D$4:$D$14,MATCH($C86,'3_UK_L1_Input'!$A$4:$A$14,0))*P86,INDEX('3_UK_L1_Input'!$D$4:$D$14,MATCH($C86,'3_UK_L1_Input'!$A$4:$A$14,0))*J86) | R86: =IF(K86="",INDEX('3_UK_L1_Input'!$D$4:$D$14,MATCH($C86,'3_UK_L1_Input'!$A$4:$A$14,0))*P86,INDEX('3_UK_L1_Input'!$D$4:$D$14,MATCH($C86,'3_UK_L1_Input'!$A$4:$A$14,0))*K86) | S86: =IF(G86="","BETA CASCADE FALLBACK (dummy — replace with real beta)","REAL (Bloomberg UK)") | T86: =INDEX('3_UK_L1_Input'!$C$4:$C$14,MATCH($C86,'3_UK_L1_Input'!$A$4:$A$14,0)) | U86: =INDEX('3_UK_L1_Input'!$C$4:$C$14,MATCH($C86,'3_UK_L1_Input'!$A$4:$A$14,0))*P86 | V86: =INDEX('5_UK_DefaultRisk_Input'!$D$5:$D$15,MATCH($C86,'5_UK_DefaultRisk_Input'!$A$5:$A$15,0)) | W86: =INDEX('5_UK_DefaultRisk_Input'!$D$20:$D$44,MATCH($E86,'5_UK_DefaultRisk_Input'!$A$20:$A$44,0)) | X86: =INDEX('5_UK_DefaultRisk_Input'!$D$49:$D$122,MATCH($D86,'5_UK_DefaultRisk_Input'!$A$49:$A$122,0)) | Y86: =INDEX('5_UK_DefaultRisk_Input'!$D$127:$D$289,MATCH($A86,'5_UK_DefaultRisk_Input'!$A$127:$A$289,0)) | Z86: =(W86/V86)*(X86/W86)*(Y86/X86) | AA86: =INDEX('3_UK_L1_Input'!$D$4:$D$14,MATCH($C86,'3_UK_L1_Input'!$A$4:$A$14,0))*Z86
A87: 30201030 | B87: Soft Drinks & Non-alcoholic Beverages | C87: 30 | D87: 302010 | E87: 3020 | F87: 5570000000 | G87: 11.96 | H87: =IFERROR(SUMPRODUCT(($C$3:$C$165=C87)*ISNUMBER($G$3:$G$165)*ISNUMBER($F$3:$F$165)*IF(ISNUMBER($F$3:$F$165),$F$3:$F$165,0)*IF(ISNUMBER($G$3:$G$165),$G$3:$G$165,0))/SUMPRODUCT(($C$3:$C$165=C87)*ISNUMBER($G$3:$G$165)*ISNUMBER($F$3:$F$165)*IF(ISNUMBER($F$3:$F$165),$F$3:$F$165,0)),"") | I87: =IFERROR(SUMPRODUCT(($C$3:$C$165=C87)*ISNUMBER($G$3:$G$165)*IF(ISNUMBER($G$3:$G$165),$G$3:$G$165,0))/SUMPRODUCT(($C$3:$C$165=C87)*ISNUMBER($G$3:$G$165)),"") | J87: =IF(OR(G87="",H87=""),"",G87/H87) | K87: =IF(OR(G87="",I87=""),"",G87/I87) | L87: =INDEX('4_UK_Beta_Input'!$D$5:$D$15,MATCH($C87,'4_UK_Beta_Input'!$A$5:$A$15,0)) | M87: =INDEX('4_UK_Beta_Input'!$D$20:$D$44,MATCH($E87,'4_UK_Beta_Input'!$A$20:$A$44,0)) | N87: =INDEX('4_UK_Beta_Input'!$D$49:$D$122,MATCH($D87,'4_UK_Beta_Input'!$A$49:$A$122,0)) | O87: =INDEX('4_UK_Beta_Input'!$D$127:$D$289,MATCH($A87,'4_UK_Beta_Input'!$A$127:$A$289,0)) | P87: =(M87/L87)*(N87/M87)*(O87/N87) | Q87: =IF(J87="",INDEX('3_UK_L1_Input'!$D$4:$D$14,MATCH($C87,'3_UK_L1_Input'!$A$4:$A$14,0))*P87,INDEX('3_UK_L1_Input'!$D$4:$D$14,MATCH($C87,'3_UK_L1_Input'!$A$4:$A$14,0))*J87) | R87: =IF(K87="",INDEX('3_UK_L1_Input'!$D$4:$D$14,MATCH($C87,'3_UK_L1_Input'!$A$4:$A$14,0))*P87,INDEX('3_UK_L1_Input'!$D$4:$D$14,MATCH($C87,'3_UK_L1_Input'!$A$4:$A$14,0))*K87) | S87: =IF(G87="","BETA CASCADE FALLBACK (dummy — replace with real beta)","REAL (Bloomberg UK)") | T87: =INDEX('3_UK_L1_Input'!$C$4:$C$14,MATCH($C87,'3_UK_L1_Input'!$A$4:$A$14,0)) | U87: =INDEX('3_UK_L1_Input'!$C$4:$C$14,MATCH($C87,'3_UK_L1_Input'!$A$4:$A$14,0))*P87 | V87: =INDEX('5_UK_DefaultRisk_Input'!$D$5:$D$15,MATCH($C87,'5_UK_DefaultRisk_Input'!$A$5:$A$15,0)) | W87: =INDEX('5_UK_DefaultRisk_Input'!$D$20:$D$44,MATCH($E87,'5_UK_DefaultRisk_Input'!$A$20:$A$44,0)) | X87: =INDEX('5_UK_DefaultRisk_Input'!$D$49:$D$122,MATCH($D87,'5_UK_DefaultRisk_Input'!$A$49:$A$122,0)) | Y87: =INDEX('5_UK_DefaultRisk_Input'!$D$127:$D$289,MATCH($A87,'5_UK_DefaultRisk_Input'!$A$127:$A$289,0)) | Z87: =(W87/V87)*(X87/W87)*(Y87/X87) | AA87: =INDEX('3_UK_L1_Input'!$D$4:$D$14,MATCH($C87,'3_UK_L1_Input'!$A$4:$A$14,0))*Z87
A88: 30202010 | B88: Agricultural Products & Services | C88: 30 | D88: 302020 | E88: 3020 | F88: 700400000 | G88: 5.8 | H88: =IFERROR(SUMPRODUCT(($C$3:$C$165=C88)*ISNUMBER($G$3:$G$165)*ISNUMBER($F$3:$F$165)*IF(ISNUMBER($F$3:$F$165),$F$3:$F$165,0)*IF(ISNUMBER($G$3:$G$165),$G$3:$G$165,0))/SUMPRODUCT(($C$3:$C$165=C88)*ISNUMBER($G$3:$G$165)*ISNUMBER($F$3:$F$165)*IF(ISNUMBER($F$3:$F$165),$F$3:$F$165,0)),"") | I88: =IFERROR(SUMPRODUCT(($C$3:$C$165=C88)*ISNUMBER($G$3:$G$165)*IF(ISNUMBER($G$3:$G$165),$G$3:$G$165,0))/SUMPRODUCT(($C$3:$C$165=C88)*ISNUMBER($G$3:$G$165)),"") | J88: =IF(OR(G88="",H88=""),"",G88/H88) | K88: =IF(OR(G88="",I88=""),"",G88/I88) | L88: =INDEX('4_UK_Beta_Input'!$D$5:$D$15,MATCH($C88,'4_UK_Beta_Input'!$A$5:$A$15,0)) | M88: =INDEX('4_UK_Beta_Input'!$D$20:$D$44,MATCH($E88,'4_UK_Beta_Input'!$A$20:$A$44,0)) | N88: =INDEX('4_UK_Beta_Input'!$D$49:$D$122,MATCH($D88,'4_UK_Beta_Input'!$A$49:$A$122,0)) | O88: =INDEX('4_UK_Beta_Input'!$D$127:$D$289,MATCH($A88,'4_UK_Beta_Input'!$A$127:$A$289,0)) | P88: =(M88/L88)*(N88/M88)*(O88/N88) | Q88: =IF(J88="",INDEX('3_UK_L1_Input'!$D$4:$D$14,MATCH($C88,'3_UK_L1_Input'!$A$4:$A$14,0))*P88,INDEX('3_UK_L1_Input'!$D$4:$D$14,MATCH($C88,'3_UK_L1_Input'!$A$4:$A$14,0))*J88) | R88: =IF(K88="",INDEX('3_UK_L1_Input'!$D$4:$D$14,MATCH($C88,'3_UK_L1_Input'!$A$4:$A$14,0))*P88,INDEX('3_UK_L1_Input'!$D$4:$D$14,MATCH($C88,'3_UK_L1_Input'!$A$4:$A$14,0))*K88) | S88: =IF(G88="","BETA CASCADE FALLBACK (dummy — replace with real beta)","REAL (Bloomberg UK)") | T88: =INDEX('3_UK_L1_Input'!$C$4:$C$14,MATCH($C88,'3_UK_L1_Input'!$A$4:$A$14,0)) | U88: =INDEX('3_UK_L1_Input'!$C$4:$C$14,MATCH($C88,'3_UK_L1_Input'!$A$4:$A$14,0))*P88 | V88: =INDEX('5_UK_DefaultRisk_Input'!$D$5:$D$15,MATCH($C88,'5_UK_DefaultRisk_Input'!$A$5:$A$15,0)) | W88: =INDEX('5_UK_DefaultRisk_Input'!$D$20:$D$44,MATCH($E88,'5_UK_DefaultRisk_Input'!$A$20:$A$44,0)) | X88: =INDEX('5_UK_DefaultRisk_Input'!$D$49:$D$122,MATCH($D88,'5_UK_DefaultRisk_Input'!$A$49:$A$122,0)) | Y88: =INDEX('5_UK_DefaultRisk_Input'!$D$127:$D$289,MATCH($A88,'5_UK_DefaultRisk_Input'!$A$127:$A$289,0)) | Z88: =(W88/V88)*(X88/W88)*(Y88/X88) | AA88: =INDEX('3_UK_L1_Input'!$D$4:$D$14,MATCH($C88,'3_UK_L1_Input'!$A$4:$A$14,0))*Z88
A89: 30202030 | B89: Packaged Foods & Meats | C89: 30 | D89: 302020 | E89: 3020 | F89: 3470000000 | G89: 7.49 | H89: =IFERROR(SUMPRODUCT(($C$3:$C$165=C89)*ISNUMBER($G$3:$G$165)*ISNUMBER($F$3:$F$165)*IF(ISNUMBER($F$3:$F$165),$F$3:$F$165,0)*IF(ISNUMBER($G$3:$G$165),$G$3:$G$165,0))/SUMPRODUCT(($C$3:$C$165=C89)*ISNUMBER($G$3:$G$165)*ISNUMBER($F$3:$F$165)*IF(ISNUMBER($F$3:$F$165),$F$3:$F$165,0)),"") | I89: =IFERROR(SUMPRODUCT(($C$3:$C$165=C89)*ISNUMBER($G$3:$G$165)*IF(ISNUMBER($G$3:$G$165),$G$3:$G$165,0))/SUMPRODUCT(($C$3:$C$165=C89)*ISNUMBER($G$3:$G$165)),"") | J89: =IF(OR(G89="",H89=""),"",G89/H89) | K89: =IF(OR(G89="",I89=""),"",G89/I89) | L89: =INDEX('4_UK_Beta_Input'!$D$5:$D$15,MATCH($C89,'4_UK_Beta_Input'!$A$5:$A$15,0)) | M89: =INDEX('4_UK_Beta_Input'!$D$20:$D$44,MATCH($E89,'4_UK_Beta_Input'!$A$20:$A$44,0)) | N89: =INDEX('4_UK_Beta_Input'!$D$49:$D$122,MATCH($D89,'4_UK_Beta_Input'!$A$49:$A$122,0)) | O89: =INDEX('4_UK_Beta_Input'!$D$127:$D$289,MATCH($A89,'4_UK_Beta_Input'!$A$127:$A$289,0)) | P89: =(M89/L89)*(N89/M89)*(O89/N89) | Q89: =IF(J89="",INDEX('3_UK_L1_Input'!$D$4:$D$14,MATCH($C89,'3_UK_L1_Input'!$A$4:$A$14,0))*P89,INDEX('3_UK_L1_Input'!$D$4:$D$14,MATCH($C89,'3_UK_L1_Input'!$A$4:$A$14,0))*J89) | R89: =IF(K89="",INDEX('3_UK_L1_Input'!$D$4:$D$14,MATCH($C89,'3_UK_L1_Input'!$A$4:$A$14,0))*P89,INDEX('3_UK_L1_Input'!$D$4:$D$14,MATCH($C89,'3_UK_L1_Input'!$A$4:$A$14,0))*K89) | S89: =IF(G89="","BETA CASCADE FALLBACK (dummy — replace with real beta)","REAL (Bloomberg UK)") | T89: =INDEX('3_UK_L1_Input'!$C$4:$C$14,MATCH($C89,'3_UK_L1_Input'!$A$4:$A$14,0)) | U89: =INDEX('3_UK_L1_Input'!$C$4:$C$14,MATCH($C89,'3_UK_L1_Input'!$A$4:$A$14,0))*P89 | V89: =INDEX('5_UK_DefaultRisk_Input'!$D$5:$D$15,MATCH($C89,'5_UK_DefaultRisk_Input'!$A$5:$A$15,0)) | W89: =INDEX('5_UK_DefaultRisk_Input'!$D$20:$D$44,MATCH($E89,'5_UK_DefaultRisk_Input'!$A$20:$A$44,0)) | X89: =INDEX('5_UK_DefaultRisk_Input'!$D$49:$D$122,MATCH($D89,'5_UK_DefaultRisk_Input'!$A$49:$A$122,0)) | Y89: =INDEX('5_UK_DefaultRisk_Input'!$D$127:$D$289,MATCH($A89,'5_UK_DefaultRisk_Input'!$A$127:$A$289,0)) | Z89: =(W89/V89)*(X89/W89)*(Y89/X89) | AA89: =INDEX('3_UK_L1_Input'!$D$4:$D$14,MATCH($C89,'3_UK_L1_Input'!$A$4:$A$14,0))*Z89
A90: 30203010 | B90: Tobacco | C90: 30 | D90: 302030 | E90: 3020 | F90: 26210000000 | G90: 8.57 | H90: =IFERROR(SUMPRODUCT(($C$3:$C$165=C90)*ISNUMBER($G$3:$G$165)*ISNUMBER($F$3:$F$165)*IF(ISNUMBER($F$3:$F$165),$F$3:$F$165,0)*IF(ISNUMBER($G$3:$G$165),$G$3:$G$165,0))/SUMPRODUCT(($C$3:$C$165=C90)*ISNUMBER($G$3:$G$165)*ISNUMBER($F$3:$F$165)*IF(ISNUMBER($F$3:$F$165),$F$3:$F$165,0)),"") | I90: =IFERROR(SUMPRODUCT(($C$3:$C$165=C90)*ISNUMBER($G$3:$G$165)*IF(ISNUMBER($G$3:$G$165),$G$3:$G$165,0))/SUMPRODUCT(($C$3:$C$165=C90)*ISNUMBER($G$3:$G$165)),"") | J90: =IF(OR(G90="",H90=""),"",G90/H90) | K90: =IF(OR(G90="",I90=""),"",G90/I90) | L90: =INDEX('4_UK_Beta_Input'!$D$5:$D$15,MATCH($C90,'4_UK_Beta_Input'!$A$5:$A$15,0)) | M90: =INDEX('4_UK_Beta_Input'!$D$20:$D$44,MATCH($E90,'4_UK_Beta_Input'!$A$20:$A$44,0)) | N90: =INDEX('4_UK_Beta_Input'!$D$49:$D$122,MATCH($D90,'4_UK_Beta_Input'!$A$49:$A$122,0)) | O90: =INDEX('4_UK_Beta_Input'!$D$127:$D$289,MATCH($A90,'4_UK_Beta_Input'!$A$127:$A$289,0)) | P90: =(M90/L90)*(N90/M90)*(O90/N90) | Q90: =IF(J90="",INDEX('3_UK_L1_Input'!$D$4:$D$14,MATCH($C90,'3_UK_L1_Input'!$A$4:$A$14,0))*P90,INDEX('3_UK_L1_Input'!$D$4:$D$14,MATCH($C90,'3_UK_L1_Input'!$A$4:$A$14,0))*J90) | R90: =IF(K90="",INDEX('3_UK_L1_Input'!$D$4:$D$14,MATCH($C90,'3_UK_L1_Input'!$A$4:$A$14,0))*P90,INDEX('3_UK_L1_Input'!$D$4:$D$14,MATCH($C90,'3_UK_L1_Input'!$A$4:$A$14,0))*K90) | S90: =IF(G90="","BETA CASCADE FALLBACK (dummy — replace with real beta)","REAL (Bloomberg UK)") | T90: =INDEX('3_UK_L1_Input'!$C$4:$C$14,MATCH($C90,'3_UK_L1_Input'!$A$4:$A$14,0)) | U90: =INDEX('3_UK_L1_Input'!$C$4:$C$14,MATCH($C90,'3_UK_L1_Input'!$A$4:$A$14,0))*P90 | V90: =INDEX('5_UK_DefaultRisk_Input'!$D$5:$D$15,MATCH($C90,'5_UK_DefaultRisk_Input'!$A$5:$A$15,0)) | W90: =INDEX('5_UK_DefaultRisk_Input'!$D$20:$D$44,MATCH($E90,'5_UK_DefaultRisk_Input'!$A$20:$A$44,0)) | X90: =INDEX('5_UK_DefaultRisk_Input'!$D$49:$D$122,MATCH($D90,'5_UK_DefaultRisk_Input'!$A$49:$A$122,0)) | Y90: =INDEX('5_UK_DefaultRisk_Input'!$D$127:$D$289,MATCH($A90,'5_UK_DefaultRisk_Input'!$A$127:$A$289,0)) | Z90: =(W90/V90)*(X90/W90)*(Y90/X90) | AA90: =INDEX('3_UK_L1_Input'!$D$4:$D$14,MATCH($C90,'3_UK_L1_Input'!$A$4:$A$14,0))*Z90
A91: 30301010 | B91: Household Products | C91: 30 | D91: 303010 | E91: 3030 | F91: 7280000000 | G91: 8.12 | H91: =IFERROR(SUMPRODUCT(($C$3:$C$165=C91)*ISNUMBER($G$3:$G$165)*ISNUMBER($F$3:$F$165)*IF(ISNUMBER($F$3:$F$165),$F$3:$F$165,0)*IF(ISNUMBER($G$3:$G$165),$G$3:$G$165,0))/SUMPRODUCT(($C$3:$C$165=C91)*ISNUMBER($G$3:$G$165)*ISNUMBER($F$3:$F$165)*IF(ISNUMBER($F$3:$F$165),$F$3:$F$165,0)),"") | I91: =IFERROR(SUMPRODUCT(($C$3:$C$165=C91)*ISNUMBER($G$3:$G$165)*IF(ISNUMBER($G$3:$G$165),$G$3:$G$165,0))/SUMPRODUCT(($C$3:$C$165=C91)*ISNUMBER($G$3:$G$165)),"") | J91: =IF(OR(G91="",H91=""),"",G91/H91) | K91: =IF(OR(G91="",I91=""),"",G91/I91) | L91: =INDEX('4_UK_Beta_Input'!$D$5:$D$15,MATCH($C91,'4_UK_Beta_Input'!$A$5:$A$15,0)) | M91: =INDEX('4_UK_Beta_Input'!$D$20:$D$44,MATCH($E91,'4_UK_Beta_Input'!$A$20:$A$44,0)) | N91: =INDEX('4_UK_Beta_Input'!$D$49:$D$122,MATCH($D91,'4_UK_Beta_Input'!$A$49:$A$122,0)) | O91: =INDEX('4_UK_Beta_Input'!$D$127:$D$289,MATCH($A91,'4_UK_Beta_Input'!$A$127:$A$289,0)) | P91: =(M91/L91)*(N91/M91)*(O91/N91) | Q91: =IF(J91="",INDEX('3_UK_L1_Input'!$D$4:$D$14,MATCH($C91,'3_UK_L1_Input'!$A$4:$A$14,0))*P91,INDEX('3_UK_L1_Input'!$D$4:$D$14,MATCH($C91,'3_UK_L1_Input'!$A$4:$A$14,0))*J91) | R91: =IF(K91="",INDEX('3_UK_L1_Input'!$D$4:$D$14,MATCH($C91,'3_UK_L1_Input'!$A$4:$A$14,0))*P91,INDEX('3_UK_L1_Input'!$D$4:$D$14,MATCH($C91,'3_UK_L1_Input'!$A$4:$A$14,0))*K91) | S91: =IF(G91="","BETA CASCADE FALLBACK (dummy — replace with real beta)","REAL (Bloomberg UK)") | T91: =INDEX('3_UK_L1_Input'!$C$4:$C$14,MATCH($C91,'3_UK_L1_Input'!$A$4:$A$14,0)) | U91: =INDEX('3_UK_L1_Input'!$C$4:$C$14,MATCH($C91,'3_UK_L1_Input'!$A$4:$A$14,0))*P91 | V91: =INDEX('5_UK_DefaultRisk_Input'!$D$5:$D$15,MATCH($C91,'5_UK_DefaultRisk_Input'!$A$5:$A$15,0)) | W91: =INDEX('5_UK_DefaultRisk_Input'!$D$20:$D$44,MATCH($E91,'5_UK_DefaultRisk_Input'!$A$20:$A$44,0)) | X91: =INDEX('5_UK_DefaultRisk_Input'!$D$49:$D$122,MATCH($D91,'5_UK_DefaultRisk_Input'!$A$49:$A$122,0)) | Y91: =INDEX('5_UK_DefaultRisk_Input'!$D$127:$D$289,MATCH($A91,'5_UK_DefaultRisk_Input'!$A$127:$A$289,0)) | Z91: =(W91/V91)*(X91/W91)*(Y91/X91) | AA91: =INDEX('3_UK_L1_Input'!$D$4:$D$14,MATCH($C91,'3_UK_L1_Input'!$A$4:$A$14,0))*Z91
A92: 30302010 | B92: Personal Care Products | C92: 30 | D92: 303020 | E92: 3030 | F92: 4710000000 | G92: 10.41 | H92: =IFERROR(SUMPRODUCT(($C$3:$C$165=C92)*ISNUMBER($G$3:$G$165)*ISNUMBER($F$3:$F$165)*IF(ISNUMBER($F$3:$F$165),$F$3:$F$165,0)*IF(ISNUMBER($G$3:$G$165),$G$3:$G$165,0))/SUMPRODUCT(($C$3:$C$165=C92)*ISNUMBER($G$3:$G$165)*ISNUMBER($F$3:$F$165)*IF(ISNUMBER($F$3:$F$165),$F$3:$F$165,0)),"") | I92: =IFERROR(SUMPRODUCT(($C$3:$C$165=C92)*ISNUMBER($G$3:$G$165)*IF(ISNUMBER($G$3:$G$165),$G$3:$G$165,0))/SUMPRODUCT(($C$3:$C$165=C92)*ISNUMBER($G$3:$G$165)),"") | J92: =IF(OR(G92="",H92=""),"",G92/H92) | K92: =IF(OR(G92="",I92=""),"",G92/I92) | L92: =INDEX('4_UK_Beta_Input'!$D$5:$D$15,MATCH($C92,'4_UK_Beta_Input'!$A$5:$A$15,0)) | M92: =INDEX('4_UK_Beta_Input'!$D$20:$D$44,MATCH($E92,'4_UK_Beta_Input'!$A$20:$A$44,0)) | N92: =INDEX('4_UK_Beta_Input'!$D$49:$D$122,MATCH($D92,'4_UK_Beta_Input'!$A$49:$A$122,0)) | O92: =INDEX('4_UK_Beta_Input'!$D$127:$D$289,MATCH($A92,'4_UK_Beta_Input'!$A$127:$A$289,0)) | P92: =(M92/L92)*(N92/M92)*(O92/N92) | Q92: =IF(J92="",INDEX('3_UK_L1_Input'!$D$4:$D$14,MATCH($C92,'3_UK_L1_Input'!$A$4:$A$14,0))*P92,INDEX('3_UK_L1_Input'!$D$4:$D$14,MATCH($C92,'3_UK_L1_Input'!$A$4:$A$14,0))*J92) | R92: =IF(K92="",INDEX('3_UK_L1_Input'!$D$4:$D$14,MATCH($C92,'3_UK_L1_Input'!$A$4:$A$14,0))*P92,INDEX('3_UK_L1_Input'!$D$4:$D$14,MATCH($C92,'3_UK_L1_Input'!$A$4:$A$14,0))*K92) | S92: =IF(G92="","BETA CASCADE FALLBACK (dummy — replace with real beta)","REAL (Bloomberg UK)") | T92: =INDEX('3_UK_L1_Input'!$C$4:$C$14,MATCH($C92,'3_UK_L1_Input'!$A$4:$A$14,0)) | U92: =INDEX('3_UK_L1_Input'!$C$4:$C$14,MATCH($C92,'3_UK_L1_Input'!$A$4:$A$14,0))*P92 | V92: =INDEX('5_UK_DefaultRisk_Input'!$D$5:$D$15,MATCH($C92,'5_UK_DefaultRisk_Input'!$A$5:$A$15,0)) | W92: =INDEX('5_UK_DefaultRisk_Input'!$D$20:$D$44,MATCH($E92,'5_UK_DefaultRisk_Input'!$A$20:$A$44,0)) | X92: =INDEX('5_UK_DefaultRisk_Input'!$D$49:$D$122,MATCH($D92,'5_UK_DefaultRisk_Input'!$A$49:$A$122,0)) | Y92: =INDEX('5_UK_DefaultRisk_Input'!$D$127:$D$289,MATCH($A92,'5_UK_DefaultRisk_Input'!$A$127:$A$289,0)) | Z92: =(W92/V92)*(X92/W92)*(Y92/X92) | AA92: =INDEX('3_UK_L1_Input'!$D$4:$D$14,MATCH($C92,'3_UK_L1_Input'!$A$4:$A$14,0))*Z92
